Workbook

Sheet Instructions
A2: 2026 Fantasy Football Auction Draft Tool
A4: Step 1: | B4: Go to the Setup tab and enter your league's Starting Budget, Number of Teams, and Scoring Format.
A6: Step 2: | B6: Still on Setup, enter your Roster Shape -- Starters at each position, any Flex slots (RB/WR/TE, RB/WR, WR/TE, or Superflex -- these can combine, e.g. 1 RB/WR flex AND 1 Superflex in the same league), DEF, K, and Bench spots.
B7: Every value on the whole board recalculates instantly when you change anything here -- you should sort each position by "
A9: Step 3: | B9: Go to the Draft Board tab. Each position (QB/RB/WR/TE) has its own set of columns. "Starting Value" is what a player is worth before any picks are made. "Market Value" is the live price that updates as your draft happens.
A11: Step 4: | B11: As players get drafted -- by you or anyone else in your league -- enter the actual winning bid in that player's "Price Paid" column. You don't need to delete, sort, or remove anything; Market Value for every remaining player updates on its own.
B12: Click the dropdown arrow on any position's header row to sort that block -- handy after switching Scoring Format, since row order is only set once when the sheet is built.
A14: Step 5: | B14: Track your own roster and remaining budget on the My Team tab -- separate from the main board, just for you.
A17: Note | B17: A single pick won't swing anyone's price much -- Market Value only moves once a couple of real prices come in for players near each other in value, and even then it's a modest nudge, not a big swing.
A19: Note | B19: The board is trimmed to a realistic depth per position -- you won't see every player who could theoretically be rostered, just anyone with a real shot at being drafted.
A21: Note | B21: If you change anything on Setup mid-draft, every value recalculates instantly -- but any Price Paid you've already entered stays exactly as typed.
A24: Field Legend
A25: Player / Team | B25: Who and where.
A26: Proj Pts | B26: Projected season points, based on your selected Scoring Format.
A27: Starting Value | B27: What we'd expect this player to cost before any picks are made.
A28: Price Paid | B28: Enter the real winning bid once a player is drafted -- blank until then.
A29: Market Value | B29: The live price estimate. Equals Price Paid once you've entered it; otherwise it's the current estimate given who's already gone.

Sheet Setup
A1: League Setup
A3: Starting Budget ($) | B3: 200
A5: Number of Teams | B5: 12
A7: Scoring Format | B7: Half-PPR
A9: Roster Shape
A11: QB Starters | B11: 1
A13: RB Starters | B13: 2
A15: WR Starters | B15: 3
A17: TE Starters | B17: 1
A19: Flex: RB/WR/TE Count | B19: 1
A21: Flex: RB/WR Count | B21: 0
A23: Flex: WR/TE Count | B23: 0
A25: Superflex Count (QB/RB/WR/TE) | B25: 0
A27: DEF | B27: 1
A29: K | B29: 1
A31: Bench | B31: 6

Sheet Draft Board
A1: Player | B1: Team | C1: Points (STD) | D1: Points (Half-PPR) | E1: Points (PPR) | F1: Proj Pts | G1: Tier | H1: Weighted VORP | I1: Row Num | J1: Gap Start | K1: Gap Tier Top | L1: Tier Start | M1: Starting Value | N1: Price Paid | O1: Market Value | Q1: Player | R1: Team | S1: Points (STD) | T1: Points (Half-PPR) | U1: Points (PPR) | V1: Proj Pts | W1: Tier | X1: Weighted VORP | Y1: Row Num | Z1: Gap Start | AA1: Gap Tier Top | AB1: Tier Start | AC1: Starting Value | AD1: Price Paid | AE1: Market Value | AG1: Player | AH1: Team | AI1: Points (STD) | AJ1: Points (Half-PPR) | AK1: Points (PPR) | AL1: Proj Pts | AM1: Tier | AN1: Weighted VORP | AO1: Row Num | AP1: Gap Start | AQ1: Gap Tier Top | AR1: Tier Start | AS1: Starting Value | AT1: Price Paid | AU1: Market Value | AW1: Player | AX1: Team | AY1: Points (STD) | AZ1: Points (Half-PPR) | BA1: Points (PPR) | BB1: Proj Pts | BC1: Tier | BD1: Weighted VORP | BE1: Row Num | BF1: Gap Start | BG1: Gap Tier Top | BH1: Tier Start | BI1: Starting Value | BJ1: Price Paid | BK1: Market Value
A2: Josh Allen | B2: BUF | C2: 353.44 | D2: 353.44 | E2: 353.44 | F2: =CHOOSE(MATCH(Setup!$B$7,{"STD","Half-PPR","PPR"},0),C2,D2,E2) -> 353.44 | G2: =COUNTIFS('Draft Board'!$H$2:$H$61,">="&H2,'Draft Board'!$L$2:$L$61,1) -> 1 | H2: =MAX(0,F2-'Live Calc'!$H$19)^'Live Calc'!$E$19 -> 219.20307 | I2: 2 | J2: =IF(I2<>_xlfn.MINIFS('Draft Board'!$I$2:$I$61,'Draft Board'!$H$2:$H$61,"="&H2),0,IF(_xlfn.MINIFS('Draft Board'!$H$2:$H$61,'Draft Board'!$H$2:$H$61,">"&H2)=0,1,IF((_xlfn.MINIFS('Draft Board'!$H$2:$H$61,'Draft Board'!$H$2:$H$61,">"&H2)-H2)/_xlfn.MINIFS('Draft Board'!$H$2:$H$61,'Draft Board'!$H$2:$H$61,">"&H2)>0.08,1,0))) -> 1 | K2: =_xlfn.MINIFS('Draft Board'!$H$2:$H$61,'Draft Board'!$H$2:$H$61,">="&H2,'Draft Board'!$J$2:$J$61,1) -> 219.20307 | L2: =IF(I2<>_xlfn.MINIFS('Draft Board'!$I$2:$I$61,'Draft Board'!$H$2:$H$61,"="&H2),0,IF(OR(J2=1,IFERROR(FLOOR((K2-H2)/K2/0.25,1),0)<>IFERROR(FLOOR((K2-_xlfn.MINIFS('Draft Board'!$H$2:$H$61,'Draft Board'!$H$2:$H$61,">"&H2))/K2/0.25,1),0)),1,0)) -> 1 | M2: =ROUND(1+H2*'Live Calc'!$D$26,0) -> 30 | O2: =IF(N2<>"",N2,ROUND(M2*INDEX('Live Calc'!$G$33:$G$92,MATCH(G2,'Live Calc'!$A$33:$A$92,0))*'Live Calc'!$J$543,0)) -> 30 | Q2: Jahmyr Gibbs | R2: DET | S2: 282.55 | T2: 316.56 | U2: 350.57 | V2: =CHOOSE(MATCH(Setup!$B$7,{"STD","Half-PPR","PPR"},0),S2,T2,U2) -> 316.56 | W2: =COUNTIFS('Draft Board'!$X$2:$X$161,">="&X2,'Draft Board'!$AB$2:$AB$161,1) -> 1 | X2: =MAX(0,V2-'Live Calc'!$H$20)^'Live Calc'!$E$20 -> 631.95742 | Y2: 2 | Z2: =IF(Y2<>_xlfn.MINIFS('Draft Board'!$Y$2:$Y$161,'Draft Board'!$X$2:$X$161,"="&X2),0,IF(_xlfn.MINIFS('Draft Board'!$X$2:$X$161,'Draft Board'!$X$2:$X$161,">"&X2)=0,1,IF((_xlfn.MINIFS('Draft Board'!$X$2:$X$161,'Draft Board'!$X$2:$X$161,">"&X2)-X2)/_xlfn.MINIFS('Draft Board'!$X$2:$X$161,'Draft Board'!$X$2:$X$161,">"&X2)>0.08,1,0))) -> 1 | AA2: =_xlfn.MINIFS('Draft Board'!$X$2:$X$161,'Draft Board'!$X$2:$X$161,">="&X2,'Draft Board'!$Z$2:$Z$161,1) -> 631.95742 | AB2: =IF(Y2<>_xlfn.MINIFS('Draft Board'!$Y$2:$Y$161,'Draft Board'!$X$2:$X$161,"="&X2),0,IF(OR(Z2=1,IFERROR(FLOOR((AA2-X2)/AA2/0.25,1),0)<>IFERROR(FLOOR((AA2-_xlfn.MINIFS('Draft Board'!$X$2:$X$161,'Draft Board'!$X$2:$X$161,">"&X2))/AA2/0.25,1),0)),1,0)) -> 1 | AC2: =ROUND(1+X2*'Live Calc'!$D$27,0) -> 59 | AE2: =IF(AD2<>"",AD2,ROUND(AC2*INDEX('Live Calc'!$G$96:$G$255,MATCH(W2,'Live Calc'!$A$96:$A$255,0))*'Live Calc'!$J$543,0)) -> 59 | AG2: Puka Nacua | AH2: LAR | AI2: 216.956 | AJ2: 276.484 | AK2: 336.008 | AL2: =CHOOSE(MATCH(Setup!$B$7,{"STD","Half-PPR","PPR"},0),AI2,AJ2,AK2) -> 276.484 | AM2: =COUNTIFS('Draft Board'!$AN$2:$AN$193,">="&AN2,'Draft Board'!$AR$2:$AR$193,1) -> 1 | AN2: =MAX(0,AL2-'Live Calc'!$H$21)^'Live Calc'!$E$21 -> 637.60828 | AO2: 2 | AP2: =IF(AO2<>_xlfn.MINIFS('Draft Board'!$AO$2:$AO$193,'Draft Board'!$AN$2:$AN$193,"="&AN2),0,IF(_xlfn.MINIFS('Draft Board'!$AN$2:$AN$193,'Draft Board'!$AN$2:$AN$193,">"&AN2)=0,1,IF((_xlfn.MINIFS('Draft Board'!$AN$2:$AN$193,'Draft Board'!$AN$2:$AN$193,">"&AN2)-AN2)/_xlfn.MINIFS('Draft Board'!$AN$2:$AN$193,'Draft Board'!$AN$2:$AN$193,">"&AN2)>0.08,1,0))) -> 1 | AQ2: =_xlfn.MINIFS('Draft Board'!$AN$2:$AN$193,'Draft Board'!$AN$2:$AN$193,">="&AN2,'Draft Board'!$AP$2:$AP$193,1) -> 637.60828 | AR2: =IF(AO2<>_xlfn.MINIFS('Draft Board'!$AO$2:$AO$193,'Draft Board'!$AN$2:$AN$193,"="&AN2),0,IF(OR(AP2=1,IFERROR(FLOOR((AQ2-AN2)/AQ2/0.25,1),0)<>IFERROR(FLOOR((AQ2-_xlfn.MINIFS('Draft Board'!$AN$2:$AN$193,'Draft Board'!$AN$2:$AN$193,">"&AN2))/AQ2/0.25,1),0)),1,0)) -> 1 | AS2: =ROUND(1+AN2*'Live Calc'!$D$28,0) -> 53 | AU2: =IF(AT2<>"",AT2,ROUND(AS2*INDEX('Live Calc'!$G$259:$G$450,MATCH(AM2,'Live Calc'!$A$259:$A$450,0))*'Live Calc'!$J$543,0)) -> 53 | AW2: Trey McBride | AX2: ARI | AY2: 143.988 | AZ2: 194.046 | BA2: 244.098 | BB2: =CHOOSE(MATCH(Setup!$B$7,{"STD","Half-PPR","PPR"},0),AY2,AZ2,BA2) -> 194.046 | BC2: =COUNTIFS('Draft Board'!$BD$2:$BD$87,">="&BD2,'Draft Board'!$BH$2:$BH$87,1) -> 1 | BD2: =MAX(0,BB2-'Live Calc'!$H$22)^'Live Calc'!$E$22 -> 90.796 | BE2: 2 | BF2: =IF(BE2<>_xlfn.MINIFS('Draft Board'!$BE$2:$BE$87,'Draft Board'!$BD$2:$BD$87,"="&BD2),0,IF(_xlfn.MINIFS('Draft Board'!$BD$2:$BD$87,'Draft Board'!$BD$2:$BD$87,">"&BD2)=0,1,IF((_xlfn.MINIFS('Draft Board'!$BD$2:$BD$87,'Draft Board'!$BD$2:$BD$87,">"&BD2)-BD2)/_xlfn.MINIFS('Draft Board'!$BD$2:$BD$87,'Draft Board'!$BD$2:$BD$87,">"&BD2)>0.08,1,0))) -> 1 | BG2: =_xlfn.MINIFS('Draft Board'!$BD$2:$BD$87,'Draft Board'!$BD$2:$BD$87,">="&BD2,'Draft Board'!$BF$2:$BF$87,1) -> 90.796 | BH2: =IF(BE2<>_xlfn.MINIFS('Draft Board'!$BE$2:$BE$87,'Draft Board'!$BD$2:$BD$87,"="&BD2),0,IF(OR(BF2=1,IFERROR(FLOOR((BG2-BD2)/BG2/0.25,1),0)<>IFERROR(FLOOR((BG2-_xlfn.MINIFS('Draft Board'!$BD$2:$BD$87,'Draft Board'!$BD$2:$BD$87,">"&BD2))/BG2/0.25,1),0)),1,0)) -> 1 | BI2: =ROUND(1+BD2*'Live Calc'!$D$29,0) -> 25 | BK2: =IF(BJ2<>"",BJ2,ROUND(BI2*INDEX('Live Calc'!$G$454:$G$539,MATCH(BC2,'Live Calc'!$A$454:$A$539,0))*'Live Calc'!$J$543,0)) -> 25
A3: Lamar Jackson | B3: BAL | C3: 316.27 | D3: 316.27 | E3: 316.27 | F3: =CHOOSE(MATCH(Setup!$B$7,{"STD","Half-PPR","PPR"},0),C3,D3,E3) -> 316.27 | G3: =COUNTIFS('Draft Board'!$H$2:$H$61,">="&H3,'Draft Board'!$L$2:$L$61,1) -> 2 | H3: =MAX(0,F3-'Live Calc'!$H$19)^'Live Calc'!$E$19 -> 114.86964 | I3: 3 | J3: =IF(I3<>_xlfn.MINIFS('Draft Board'!$I$2:$I$61,'Draft Board'!$H$2:$H$61,"="&H3),0,IF(_xlfn.MINIFS('Draft Board'!$H$2:$H$61,'Draft Board'!$H$2:$H$61,">"&H3)=0,1,IF((_xlfn.MINIFS('Draft Board'!$H$2:$H$61,'Draft Board'!$H$2:$H$61,">"&H3)-H3)/_xlfn.MINIFS('Draft Board'!$H$2:$H$61,'Draft Board'!$H$2:$H$61,">"&H3)>0.08,1,0))) -> 1 | K3: =_xlfn.MINIFS('Draft Board'!$H$2:$H$61,'Draft Board'!$H$2:$H$61,">="&H3,'Draft Board'!$J$2:$J$61,1) -> 114.86964 | L3: =IF(I3<>_xlfn.MINIFS('Draft Board'!$I$2:$I$61,'Draft Board'!$H$2:$H$61,"="&H3),0,IF(OR(J3=1,IFERROR(FLOOR((K3-H3)/K3/0.25,1),0)<>IFERROR(FLOOR((K3-_xlfn.MINIFS('Draft Board'!$H$2:$H$61,'Draft Board'!$H$2:$H$61,">"&H3))/K3/0.25,1),0)),1,0)) -> 1 | M3: =ROUND(1+H3*'Live Calc'!$D$26,0) -> 16 | O3: =IF(N3<>"",N3,ROUND(M3*INDEX('Live Calc'!$G$33:$G$92,MATCH(G3,'Live Calc'!$A$33:$A$92,0))*'Live Calc'!$J$543,0)) -> 16 | Q3: Bijan Robinson | R3: ATL | S3: 272.86 | T3: 309.55 | U3: 346.24 | V3: =CHOOSE(MATCH(Setup!$B$7,{"STD","Half-PPR","PPR"},0),S3,T3,U3) -> 309.55 | W3: =COUNTIFS('Draft Board'!$X$2:$X$161,">="&X3,'Draft Board'!$AB$2:$AB$161,1) -> 1 | X3: =MAX(0,V3-'Live Calc'!$H$20)^'Live Calc'!$E$20 -> 607.39594 | Y3: 3 | Z3: =IF(Y3<>_xlfn.MINIFS('Draft Board'!$Y$2:$Y$161,'Draft Board'!$X$2:$X$161,"="&X3),0,IF(_xlfn.MINIFS('Draft Board'!$X$2:$X$161,'Draft Board'!$X$2:$X$161,">"&X3)=0,1,IF((_xlfn.MINIFS('Draft Board'!$X$2:$X$161,'Draft Board'!$X$2:$X$161,">"&X3)-X3)/_xlfn.MINIFS('Draft Board'!$X$2:$X$161,'Draft Board'!$X$2:$X$161,">"&X3)>0.08,1,0))) -> 0 | AA3: =_xlfn.MINIFS('Draft Board'!$X$2:$X$161,'Draft Board'!$X$2:$X$161,">="&X3,'Draft Board'!$Z$2:$Z$161,1) -> 631.95742 | AB3: =IF(Y3<>_xlfn.MINIFS('Draft Board'!$Y$2:$Y$161,'Draft Board'!$X$2:$X$161,"="&X3),0,IF(OR(Z3=1,IFERROR(FLOOR((AA3-X3)/AA3/0.25,1),0)<>IFERROR(FLOOR((AA3-_xlfn.MINIFS('Draft Board'!$X$2:$X$161,'Draft Board'!$X$2:$X$161,">"&X3))/AA3/0.25,1),0)),1,0)) -> 0 | AC3: =ROUND(1+X3*'Live Calc'!$D$27,0) -> 57 | AE3: =IF(AD3<>"",AD3,ROUND(AC3*INDEX('Live Calc'!$G$96:$G$255,MATCH(W3,'Live Calc'!$A$96:$A$255,0))*'Live Calc'!$J$543,0)) -> 57 | AG3: Ja'Marr Chase | AH3: CIN | AI3: 216.274 | AJ3: 275.946 | AK3: 335.612 | AL3: =CHOOSE(MATCH(Setup!$B$7,{"STD","Half-PPR","PPR"},0),AI3,AJ3,AK3) -> 275.946 | AM3: =COUNTIFS('Draft Board'!$AN$2:$AN$193,">="&AN3,'Draft Board'!$AR$2:$AR$193,1) -> 1 | AN3: =MAX(0,AL3-'Live Calc'!$H$21)^'Live Calc'!$E$21 -> 635.16239 | AO3: 3 | AP3: =IF(AO3<>_xlfn.MINIFS('Draft Board'!$AO$2:$AO$193,'Draft Board'!$AN$2:$AN$193,"="&AN3),0,IF(_xlfn.MINIFS('Draft Board'!$AN$2:$AN$193,'Draft Board'!$AN$2:$AN$193,">"&AN3)=0,1,IF((_xlfn.MINIFS('Draft Board'!$AN$2:$AN$193,'Draft Board'!$AN$2:$AN$193,">"&AN3)-AN3)/_xlfn.MINIFS('Draft Board'!$AN$2:$AN$193,'Draft Board'!$AN$2:$AN$193,">"&AN3)>0.08,1,0))) -> 0 | AQ3: =_xlfn.MINIFS('Draft Board'!$AN$2:$AN$193,'Draft Board'!$AN$2:$AN$193,">="&AN3,'Draft Board'!$AP$2:$AP$193,1) -> 637.60828 | AR3: =IF(AO3<>_xlfn.MINIFS('Draft Board'!$AO$2:$AO$193,'Draft Board'!$AN$2:$AN$193,"="&AN3),0,IF(OR(AP3=1,IFERROR(FLOOR((AQ3-AN3)/AQ3/0.25,1),0)<>IFERROR(FLOOR((AQ3-_xlfn.MINIFS('Draft Board'!$AN$2:$AN$193,'Draft Board'!$AN$2:$AN$193,">"&AN3))/AQ3/0.25,1),0)),1,0)) -> 0 | AS3: =ROUND(1+AN3*'Live Calc'!$D$28,0) -> 53 | AU3: =IF(AT3<>"",AT3,ROUND(AS3*INDEX('Live Calc'!$G$259:$G$450,MATCH(AM3,'Live Calc'!$A$259:$A$450,0))*'Live Calc'!$J$543,0)) -> 53 | AW3: Brock Bowers | AX3: LV | AY3: 143.402 | AZ3: 192.154 | BA3: 240.902 | BB3: =CHOOSE(MATCH(Setup!$B$7,{"STD","Half-PPR","PPR"},0),AY3,AZ3,BA3) -> 192.154 | BC3: =COUNTIFS('Draft Board'!$BD$2:$BD$87,">="&BD3,'Draft Board'!$BH$2:$BH$87,1) -> 1 | BD3: =MAX(0,BB3-'Live Calc'!$H$22)^'Live Calc'!$E$22 -> 88.904 | BE3: 3 | BF3: =IF(BE3<>_xlfn.MINIFS('Draft Board'!$BE$2:$BE$87,'Draft Board'!$BD$2:$BD$87,"="&BD3),0,IF(_xlfn.MINIFS('Draft Board'!$BD$2:$BD$87,'Draft Board'!$BD$2:$BD$87,">"&BD3)=0,1,IF((_xlfn.MINIFS('Draft Board'!$BD$2:$BD$87,'Draft Board'!$BD$2:$BD$87,">"&BD3)-BD3)/_xlfn.MINIFS('Draft Board'!$BD$2:$BD$87,'Draft Board'!$BD$2:$BD$87,">"&BD3)>0.08,1,0))) -> 0 | BG3: =_xlfn.MINIFS('Draft Board'!$BD$2:$BD$87,'Draft Board'!$BD$2:$BD$87,">="&BD3,'Draft Board'!$BF$2:$BF$87,1) -> 90.796 | BH3: =IF(BE3<>_xlfn.MINIFS('Draft Board'!$BE$2:$BE$87,'Draft Board'!$BD$2:$BD$87,"="&BD3),0,IF(OR(BF3=1,IFERROR(FLOOR((BG3-BD3)/BG3/0.25,1),0)<>IFERROR(FLOOR((BG3-_xlfn.MINIFS('Draft Board'!$BD$2:$BD$87,'Draft Board'!$BD$2:$BD$87,">"&BD3))/BG3/0.25,1),0)),1,0)) -> 0 | BI3: =ROUND(1+BD3*'Live Calc'!$D$29,0) -> 25 | BK3: =IF(BJ3<>"",BJ3,ROUND(BI3*INDEX('Live Calc'!$G$454:$G$539,MATCH(BC3,'Live Calc'!$A$454:$A$539,0))*'Live Calc'!$J$543,0)) -> 25
A4: Drake Maye | B4: NE | C4: 309.29 | D4: 309.29 | E4: 309.29 | F4: =CHOOSE(MATCH(Setup!$B$7,{"STD","Half-PPR","PPR"},0),C4,D4,E4) -> 309.29 | G4: =COUNTIFS('Draft Board'!$H$2:$H$61,">="&H4,'Draft Board'!$L$2:$L$61,1) -> 3 | H4: =MAX(0,F4-'Live Calc'!$H$19)^'Live Calc'!$E$19 -> 96.659136 | I4: 4 | J4: =IF(I4<>_xlfn.MINIFS('Draft Board'!$I$2:$I$61,'Draft Board'!$H$2:$H$61,"="&H4),0,IF(_xlfn.MINIFS('Draft Board'!$H$2:$H$61,'Draft Board'!$H$2:$H$61,">"&H4)=0,1,IF((_xlfn.MINIFS('Draft Board'!$H$2:$H$61,'Draft Board'!$H$2:$H$61,">"&H4)-H4)/_xlfn.MINIFS('Draft Board'!$H$2:$H$61,'Draft Board'!$H$2:$H$61,">"&H4)>0.08,1,0))) -> 1 | K4: =_xlfn.MINIFS('Draft Board'!$H$2:$H$61,'Draft Board'!$H$2:$H$61,">="&H4,'Draft Board'!$J$2:$J$61,1) -> 96.659136 | L4: =IF(I4<>_xlfn.MINIFS('Draft Board'!$I$2:$I$61,'Draft Board'!$H$2:$H$61,"="&H4),0,IF(OR(J4=1,IFERROR(FLOOR((K4-H4)/K4/0.25,1),0)<>IFERROR(FLOOR((K4-_xlfn.MINIFS('Draft Board'!$H$2:$H$61,'Draft Board'!$H$2:$H$61,">"&H4))/K4/0.25,1),0)),1,0)) -> 1 | M4: =ROUND(1+H4*'Live Calc'!$D$26,0) -> 14 | O4: =IF(N4<>"",N4,ROUND(M4*INDEX('Live Calc'!$G$33:$G$92,MATCH(G4,'Live Calc'!$A$33:$A$92,0))*'Live Calc'!$J$543,0)) -> 14 | Q4: Christian McCaffrey | R4: SF | S4: 255.134 | T4: 289.53 | U4: 327.45 | V4: =CHOOSE(MATCH(Setup!$B$7,{"STD","Half-PPR","PPR"},0),S4,T4,U4) -> 289.53 | W4: =COUNTIFS('Draft Board'!$X$2:$X$161,">="&X4,'Draft Board'!$AB$2:$AB$161,1) -> 2 | X4: =MAX(0,V4-'Live Calc'!$H$20)^'Live Calc'!$E$20 -> 538.17158 | Y4: 4 | Z4: =IF(Y4<>_xlfn.MINIFS('Draft Board'!$Y$2:$Y$161,'Draft Board'!$X$2:$X$161,"="&X4),0,IF(_xlfn.MINIFS('Draft Board'!$X$2:$X$161,'Draft Board'!$X$2:$X$161,">"&X4)=0,1,IF((_xlfn.MINIFS('Draft Board'!$X$2:$X$161,'Draft Board'!$X$2:$X$161,">"&X4)-X4)/_xlfn.MINIFS('Draft Board'!$X$2:$X$161,'Draft Board'!$X$2:$X$161,">"&X4)>0.08,1,0))) -> 1 | AA4: =_xlfn.MINIFS('Draft Board'!$X$2:$X$161,'Draft Board'!$X$2:$X$161,">="&X4,'Draft Board'!$Z$2:$Z$161,1) -> 538.17158 | AB4: =IF(Y4<>_xlfn.MINIFS('Draft Board'!$Y$2:$Y$161,'Draft Board'!$X$2:$X$161,"="&X4),0,IF(OR(Z4=1,IFERROR(FLOOR((AA4-X4)/AA4/0.25,1),0)<>IFERROR(FLOOR((AA4-_xlfn.MINIFS('Draft Board'!$X$2:$X$161,'Draft Board'!$X$2:$X$161,">"&X4))/AA4/0.25,1),0)),1,0)) -> 1 | AC4: =ROUND(1+X4*'Live Calc'!$D$27,0) -> 50 | AE4: =IF(AD4<>"",AD4,ROUND(AC4*INDEX('Live Calc'!$G$96:$G$255,MATCH(W4,'Live Calc'!$A$96:$A$255,0))*'Live Calc'!$J$543,0)) -> 50 | AG4: Jaxon Smith-Njigba | AH4: SEA | AI4: 206.86 | AJ4: 260.31 | AK4: 313.76 | AL4: =CHOOSE(MATCH(Setup!$B$7,{"STD","Half-PPR","PPR"},0),AI4,AJ4,AK4) -> 260.31 | AM4: =COUNTIFS('Draft Board'!$AN$2:$AN$193,">="&AN4,'Draft Board'!$AR$2:$AR$193,1) -> 2 | AN4: =MAX(0,AL4-'Live Calc'!$H$21)^'Live Calc'!$E$21 -> 564.91792 | AO4: 4 | AP4: =IF(AO4<>_xlfn.MINIFS('Draft Board'!$AO$2:$AO$193,'Draft Board'!$AN$2:$AN$193,"="&AN4),0,IF(_xlfn.MINIFS('Draft Board'!$AN$2:$AN$193,'Draft Board'!$AN$2:$AN$193,">"&AN4)=0,1,IF((_xlfn.MINIFS('Draft Board'!$AN$2:$AN$193,'Draft Board'!$AN$2:$AN$193,">"&AN4)-AN4)/_xlfn.MINIFS('Draft Board'!$AN$2:$AN$193,'Draft Board'!$AN$2:$AN$193,">"&AN4)>0.08,1,0))) -> 1 | AQ4: =_xlfn.MINIFS('Draft Board'!$AN$2:$AN$193,'Draft Board'!$AN$2:$AN$193,">="&AN4,'Draft Board'!$AP$2:$AP$193,1) -> 564.91792 | AR4: =IF(AO4<>_xlfn.MINIFS('Draft Board'!$AO$2:$AO$193,'Draft Board'!$AN$2:$AN$193,"="&AN4),0,IF(OR(AP4=1,IFERROR(FLOOR((AQ4-AN4)/AQ4/0.25,1),0)<>IFERROR(FLOOR((AQ4-_xlfn.MINIFS('Draft Board'!$AN$2:$AN$193,'Draft Board'!$AN$2:$AN$193,">"&AN4))/AQ4/0.25,1),0)),1,0)) -> 1 | AS4: =ROUND(1+AN4*'Live Calc'!$D$28,0) -> 47 | AU4: =IF(AT4<>"",AT4,ROUND(AS4*INDEX('Live Calc'!$G$259:$G$450,MATCH(AM4,'Live Calc'!$A$259:$A$450,0))*'Live Calc'!$J$543,0)) -> 47 | AW4: Colston Loveland | AX4: CHI | AY4: 131.02 | AZ4: 169.01 | BA4: 207 | BB4: =CHOOSE(MATCH(Setup!$B$7,{"STD","Half-PPR","PPR"},0),AY4,AZ4,BA4) -> 169.01 | BC4: =COUNTIFS('Draft Board'!$BD$2:$BD$87,">="&BD4,'Draft Board'!$BH$2:$BH$87,1) -> 2 | BD4: =MAX(0,BB4-'Live Calc'!$H$22)^'Live Calc'!$E$22 -> 65.76 | BE4: 4 | BF4: =IF(BE4<>_xlfn.MINIFS('Draft Board'!$BE$2:$BE$87,'Draft Board'!$BD$2:$BD$87,"="&BD4),0,IF(_xlfn.MINIFS('Draft Board'!$BD$2:$BD$87,'Draft Board'!$BD$2:$BD$87,">"&BD4)=0,1,IF((_xlfn.MINIFS('Draft Board'!$BD$2:$BD$87,'Draft Board'!$BD$2:$BD$87,">"&BD4)-BD4)/_xlfn.MINIFS('Draft Board'!$BD$2:$BD$87,'Draft Board'!$BD$2:$BD$87,">"&BD4)>0.08,1,0))) -> 1 | BG4: =_xlfn.MINIFS('Draft Board'!$BD$2:$BD$87,'Draft Board'!$BD$2:$BD$87,">="&BD4,'Draft Board'!$BF$2:$BF$87,1) -> 65.76 | BH4: =IF(BE4<>_xlfn.MINIFS('Draft Board'!$BE$2:$BE$87,'Draft Board'!$BD$2:$BD$87,"="&BD4),0,IF(OR(BF4=1,IFERROR(FLOOR((BG4-BD4)/BG4/0.25,1),0)<>IFERROR(FLOOR((BG4-_xlfn.MINIFS('Draft Board'!$BD$2:$BD$87,'Draft Board'!$BD$2:$BD$87,">"&BD4))/BG4/0.25,1),0)),1,0)) -> 1 | BI4: =ROUND(1+BD4*'Live Calc'!$D$29,0) -> 19 | BK4: =IF(BJ4<>"",BJ4,ROUND(BI4*INDEX('Live Calc'!$G$454:$G$539,MATCH(BC4,'Live Calc'!$A$454:$A$539,0))*'Live Calc'!$J$543,0)) -> 19
A5: Jayden Daniels | B5: WAS | C5: 308.258 | D5: 308.258 | E5: 308.258 | F5: =CHOOSE(MATCH(Setup!$B$7,{"STD","Half-PPR","PPR"},0),C5,D5,E5) -> 308.258 | G5: =COUNTIFS('Draft Board'!$H$2:$H$61,">="&H5,'Draft Board'!$L$2:$L$61,1) -> 3 | H5: =MAX(0,F5-'Live Calc'!$H$19)^'Live Calc'!$E$19 -> 94.012257 | I5: 5 | J5: =IF(I5<>_xlfn.MINIFS('Draft Board'!$I$2:$I$61,'Draft Board'!$H$2:$H$61,"="&H5),0,IF(_xlfn.MINIFS('Draft Board'!$H$2:$H$61,'Draft Board'!$H$2:$H$61,">"&H5)=0,1,IF((_xlfn.MINIFS('Draft Board'!$H$2:$H$61,'Draft Board'!$H$2:$H$61,">"&H5)-H5)/_xlfn.MINIFS('Draft Board'!$H$2:$H$61,'Draft Board'!$H$2:$H$61,">"&H5)>0.08,1,0))) -> 0 | K5: =_xlfn.MINIFS('Draft Board'!$H$2:$H$61,'Draft Board'!$H$2:$H$61,">="&H5,'Draft Board'!$J$2:$J$61,1) -> 96.659136 | L5: =IF(I5<>_xlfn.MINIFS('Draft Board'!$I$2:$I$61,'Draft Board'!$H$2:$H$61,"="&H5),0,IF(OR(J5=1,IFERROR(FLOOR((K5-H5)/K5/0.25,1),0)<>IFERROR(FLOOR((K5-_xlfn.MINIFS('Draft Board'!$H$2:$H$61,'Draft Board'!$H$2:$H$61,">"&H5))/K5/0.25,1),0)),1,0)) -> 0 | M5: =ROUND(1+H5*'Live Calc'!$D$26,0) -> 14 | O5: =IF(N5<>"",N5,ROUND(M5*INDEX('Live Calc'!$G$33:$G$92,MATCH(G5,'Live Calc'!$A$33:$A$92,0))*'Live Calc'!$J$543,0)) -> 14 | Q5: Jonathan Taylor | R5: IND | S5: 256.896 | T5: 281.54 | U5: 302.67 | V5: =CHOOSE(MATCH(Setup!$B$7,{"STD","Half-PPR","PPR"},0),S5,T5,U5) -> 281.54 | W5: =COUNTIFS('Draft Board'!$X$2:$X$161,">="&X5,'Draft Board'!$AB$2:$AB$161,1) -> 2 | X5: =MAX(0,V5-'Live Calc'!$H$20)^'Live Calc'!$E$20 -> 510.94347 | Y5: 5 | Z5: =IF(Y5<>_xlfn.MINIFS('Draft Board'!$Y$2:$Y$161,'Draft Board'!$X$2:$X$161,"="&X5),0,IF(_xlfn.MINIFS('Draft Board'!$X$2:$X$161,'Draft Board'!$X$2:$X$161,">"&X5)=0,1,IF((_xlfn.MINIFS('Draft Board'!$X$2:$X$161,'Draft Board'!$X$2:$X$161,">"&X5)-X5)/_xlfn.MINIFS('Draft Board'!$X$2:$X$161,'Draft Board'!$X$2:$X$161,">"&X5)>0.08,1,0))) -> 0 | AA5: =_xlfn.MINIFS('Draft Board'!$X$2:$X$161,'Draft Board'!$X$2:$X$161,">="&X5,'Draft Board'!$Z$2:$Z$161,1) -> 538.17158 | AB5: =IF(Y5<>_xlfn.MINIFS('Draft Board'!$Y$2:$Y$161,'Draft Board'!$X$2:$X$161,"="&X5),0,IF(OR(Z5=1,IFERROR(FLOOR((AA5-X5)/AA5/0.25,1),0)<>IFERROR(FLOOR((AA5-_xlfn.MINIFS('Draft Board'!$X$2:$X$161,'Draft Board'!$X$2:$X$161,">"&X5))/AA5/0.25,1),0)),1,0)) -> 0 | AC5: =ROUND(1+X5*'Live Calc'!$D$27,0) -> 48 | AE5: =IF(AD5<>"",AD5,ROUND(AC5*INDEX('Live Calc'!$G$96:$G$255,MATCH(W5,'Live Calc'!$A$96:$A$255,0))*'Live Calc'!$J$543,0)) -> 48 | AG5: Amon-Ra St. Brown | AH5: DET | AI5: 194.82 | AJ5: 251.54 | AK5: 308.25 | AL5: =CHOOSE(MATCH(Setup!$B$7,{"STD","Half-PPR","PPR"},0),AI5,AJ5,AK5) -> 251.54 | AM5: =COUNTIFS('Draft Board'!$AN$2:$AN$193,">="&AN5,'Draft Board'!$AR$2:$AR$193,1) -> 2 | AN5: =MAX(0,AL5-'Live Calc'!$H$21)^'Live Calc'!$E$21 -> 526.25802 | AO5: 5 | AP5: =IF(AO5<>_xlfn.MINIFS('Draft Board'!$AO$2:$AO$193,'Draft Board'!$AN$2:$AN$193,"="&AN5),0,IF(_xlfn.MINIFS('Draft Board'!$AN$2:$AN$193,'Draft Board'!$AN$2:$AN$193,">"&AN5)=0,1,IF((_xlfn.MINIFS('Draft Board'!$AN$2:$AN$193,'Draft Board'!$AN$2:$AN$193,">"&AN5)-AN5)/_xlfn.MINIFS('Draft Board'!$AN$2:$AN$193,'Draft Board'!$AN$2:$AN$193,">"&AN5)>0.08,1,0))) -> 0 | AQ5: =_xlfn.MINIFS('Draft Board'!$AN$2:$AN$193,'Draft Board'!$AN$2:$AN$193,">="&AN5,'Draft Board'!$AP$2:$AP$193,1) -> 564.91792 | AR5: =IF(AO5<>_xlfn.MINIFS('Draft Board'!$AO$2:$AO$193,'Draft Board'!$AN$2:$AN$193,"="&AN5),0,IF(OR(AP5=1,IFERROR(FLOOR((AQ5-AN5)/AQ5/0.25,1),0)<>IFERROR(FLOOR((AQ5-_xlfn.MINIFS('Draft Board'!$AN$2:$AN$193,'Draft Board'!$AN$2:$AN$193,">"&AN5))/AQ5/0.25,1),0)),1,0)) -> 0 | AS5: =ROUND(1+AN5*'Live Calc'!$D$28,0) -> 44 | AU5: =IF(AT5<>"",AT5,ROUND(AS5*INDEX('Live Calc'!$G$259:$G$450,MATCH(AM5,'Live Calc'!$A$259:$A$450,0))*'Live Calc'!$J$543,0)) -> 44 | AW5: Tyler Warren | AX5: IND | AY5: 121.14 | AZ5: 161.46 | BA5: 201.79 | BB5: =CHOOSE(MATCH(Setup!$B$7,{"STD","Half-PPR","PPR"},0),AY5,AZ5,BA5) -> 161.46 | BC5: =COUNTIFS('Draft Board'!$BD$2:$BD$87,">="&BD5,'Draft Board'!$BH$2:$BH$87,1) -> 3 | BD5: =MAX(0,BB5-'Live Calc'!$H$22)^'Live Calc'!$E$22 -> 58.21 | BE5: 5 | BF5: =IF(BE5<>_xlfn.MINIFS('Draft Board'!$BE$2:$BE$87,'Draft Board'!$BD$2:$BD$87,"="&BD5),0,IF(_xlfn.MINIFS('Draft Board'!$BD$2:$BD$87,'Draft Board'!$BD$2:$BD$87,">"&BD5)=0,1,IF((_xlfn.MINIFS('Draft Board'!$BD$2:$BD$87,'Draft Board'!$BD$2:$BD$87,">"&BD5)-BD5)/_xlfn.MINIFS('Draft Board'!$BD$2:$BD$87,'Draft Board'!$BD$2:$BD$87,">"&BD5)>0.08,1,0))) -> 1 | BG5: =_xlfn.MINIFS('Draft Board'!$BD$2:$BD$87,'Draft Board'!$BD$2:$BD$87,">="&BD5,'Draft Board'!$BF$2:$BF$87,1) -> 58.21 | BH5: =IF(BE5<>_xlfn.MINIFS('Draft Board'!$BE$2:$BE$87,'Draft Board'!$BD$2:$BD$87,"="&BD5),0,IF(OR(BF5=1,IFERROR(FLOOR((BG5-BD5)/BG5/0.25,1),0)<>IFERROR(FLOOR((BG5-_xlfn.MINIFS('Draft Board'!$BD$2:$BD$87,'Draft Board'!$BD$2:$BD$87,">"&BD5))/BG5/0.25,1),0)),1,0)) -> 1 | BI5: =ROUND(1+BD5*'Live Calc'!$D$29,0) -> 17 | BK5: =IF(BJ5<>"",BJ5,ROUND(BI5*INDEX('Live Calc'!$G$454:$G$539,MATCH(BC5,'Live Calc'!$A$454:$A$539,0))*'Live Calc'!$J$543,0)) -> 17
A6: Jalen Hurts | B6: PHI | C6: 306.536 | D6: 306.536 | E6: 306.536 | F6: =CHOOSE(MATCH(Setup!$B$7,{"STD","Half-PPR","PPR"},0),C6,D6,E6) -> 306.536 | G6: =COUNTIFS('Draft Board'!$H$2:$H$61,">="&H6,'Draft Board'!$L$2:$L$61,1) -> 3 | H6: =MAX(0,F6-'Live Calc'!$H$19)^'Live Calc'!$E$19 -> 89.623305 | I6: 6 | J6: =IF(I6<>_xlfn.MINIFS('Draft Board'!$I$2:$I$61,'Draft Board'!$H$2:$H$61,"="&H6),0,IF(_xlfn.MINIFS('Draft Board'!$H$2:$H$61,'Draft Board'!$H$2:$H$61,">"&H6)=0,1,IF((_xlfn.MINIFS('Draft Board'!$H$2:$H$61,'Draft Board'!$H$2:$H$61,">"&H6)-H6)/_xlfn.MINIFS('Draft Board'!$H$2:$H$61,'Draft Board'!$H$2:$H$61,">"&H6)>0.08,1,0))) -> 0 | K6: =_xlfn.MINIFS('Draft Board'!$H$2:$H$61,'Draft Board'!$H$2:$H$61,">="&H6,'Draft Board'!$J$2:$J$61,1) -> 96.659136 | L6: =IF(I6<>_xlfn.MINIFS('Draft Board'!$I$2:$I$61,'Draft Board'!$H$2:$H$61,"="&H6),0,IF(OR(J6=1,IFERROR(FLOOR((K6-H6)/K6/0.25,1),0)<>IFERROR(FLOOR((K6-_xlfn.MINIFS('Draft Board'!$H$2:$H$61,'Draft Board'!$H$2:$H$61,">"&H6))/K6/0.25,1),0)),1,0)) -> 0 | M6: =ROUND(1+H6*'Live Calc'!$D$26,0) -> 13 | O6: =IF(N6<>"",N6,ROUND(M6*INDEX('Live Calc'!$G$33:$G$92,MATCH(G6,'Live Calc'!$A$33:$A$92,0))*'Live Calc'!$J$543,0)) -> 13 | Q6: James Cook III | R6: BUF | S6: 233.902 | T6: 250.618 | U6: 266.058 | V6: =CHOOSE(MATCH(Setup!$B$7,{"STD","Half-PPR","PPR"},0),S6,T6,U6) -> 250.618 | W6: =COUNTIFS('Draft Board'!$X$2:$X$161,">="&X6,'Draft Board'!$AB$2:$AB$161,1) -> 3 | X6: =MAX(0,V6-'Live Calc'!$H$20)^'Live Calc'!$E$20 -> 407.91105 | Y6: 6 | Z6: =IF(Y6<>_xlfn.MINIFS('Draft Board'!$Y$2:$Y$161,'Draft Board'!$X$2:$X$161,"="&X6),0,IF(_xlfn.MINIFS('Draft Board'!$X$2:$X$161,'Draft Board'!$X$2:$X$161,">"&X6)=0,1,IF((_xlfn.MINIFS('Draft Board'!$X$2:$X$161,'Draft Board'!$X$2:$X$161,">"&X6)-X6)/_xlfn.MINIFS('Draft Board'!$X$2:$X$161,'Draft Board'!$X$2:$X$161,">"&X6)>0.08,1,0))) -> 1 | AA6: =_xlfn.MINIFS('Draft Board'!$X$2:$X$161,'Draft Board'!$X$2:$X$161,">="&X6,'Draft Board'!$Z$2:$Z$161,1) -> 407.91105 | AB6: =IF(Y6<>_xlfn.MINIFS('Draft Board'!$Y$2:$Y$161,'Draft Board'!$X$2:$X$161,"="&X6),0,IF(OR(Z6=1,IFERROR(FLOOR((AA6-X6)/AA6/0.25,1),0)<>IFERROR(FLOOR((AA6-_xlfn.MINIFS('Draft Board'!$X$2:$X$161,'Draft Board'!$X$2:$X$161,">"&X6))/AA6/0.25,1),0)),1,0)) -> 1 | AC6: =ROUND(1+X6*'Live Calc'!$D$27,0) -> 38 | AE6: =IF(AD6<>"",AD6,ROUND(AC6*INDEX('Live Calc'!$G$96:$G$255,MATCH(W6,'Live Calc'!$A$96:$A$255,0))*'Live Calc'!$J$543,0)) -> 38 | AG6: CeeDee Lamb | AH6: DAL | AI6: 174.29 | AJ6: 222.49 | AK6: 270.75 | AL6: =CHOOSE(MATCH(Setup!$B$7,{"STD","Half-PPR","PPR"},0),AI6,AJ6,AK6) -> 222.49 | AM6: =COUNTIFS('Draft Board'!$AN$2:$AN$193,">="&AN6,'Draft Board'!$AR$2:$AR$193,1) -> 3 | AN6: =MAX(0,AL6-'Live Calc'!$H$21)^'Live Calc'!$E$21 -> 402.34831 | AO6: 6 | AP6: =IF(AO6<>_xlfn.MINIFS('Draft Board'!$AO$2:$AO$193,'Draft Board'!$AN$2:$AN$193,"="&AN6),0,IF(_xlfn.MINIFS('Draft Board'!$AN$2:$AN$193,'Draft Board'!$AN$2:$AN$193,">"&AN6)=0,1,IF((_xlfn.MINIFS('Draft Board'!$AN$2:$AN$193,'Draft Board'!$AN$2:$AN$193,">"&AN6)-AN6)/_xlfn.MINIFS('Draft Board'!$AN$2:$AN$193,'Draft Board'!$AN$2:$AN$193,">"&AN6)>0.08,1,0))) -> 1 | AQ6: =_xlfn.MINIFS('Draft Board'!$AN$2:$AN$193,'Draft Board'!$AN$2:$AN$193,">="&AN6,'Draft Board'!$AP$2:$AP$193,1) -> 402.34831 | AR6: =IF(AO6<>_xlfn.MINIFS('Draft Board'!$AO$2:$AO$193,'Draft Board'!$AN$2:$AN$193,"="&AN6),0,IF(OR(AP6=1,IFERROR(FLOOR((AQ6-AN6)/AQ6/0.25,1),0)<>IFERROR(FLOOR((AQ6-_xlfn.MINIFS('Draft Board'!$AN$2:$AN$193,'Draft Board'!$AN$2:$AN$193,">"&AN6))/AQ6/0.25,1),0)),1,0)) -> 1 | AS6: =ROUND(1+AN6*'Live Calc'!$D$28,0) -> 34 | AU6: =IF(AT6<>"",AT6,ROUND(AS6*INDEX('Live Calc'!$G$259:$G$450,MATCH(AM6,'Live Calc'!$A$259:$A$450,0))*'Live Calc'!$J$543,0)) -> 34 | AW6: Harold Fannin Jr. | AX6: CLE | AY6: 111.82 | AZ6: 147.922 | BA6: 183.044 | BB6: =CHOOSE(MATCH(Setup!$B$7,{"STD","Half-PPR","PPR"},0),AY6,AZ6,BA6) -> 147.922 | BC6: =COUNTIFS('Draft Board'!$BD$2:$BD$87,">="&BD6,'Draft Board'!$BH$2:$BH$87,1) -> 4 | BD6: =MAX(0,BB6-'Live Calc'!$H$22)^'Live Calc'!$E$22 -> 44.672 | BE6: 6 | BF6: =IF(BE6<>_xlfn.MINIFS('Draft Board'!$BE$2:$BE$87,'Draft Board'!$BD$2:$BD$87,"="&BD6),0,IF(_xlfn.MINIFS('Draft Board'!$BD$2:$BD$87,'Draft Board'!$BD$2:$BD$87,">"&BD6)=0,1,IF((_xlfn.MINIFS('Draft Board'!$BD$2:$BD$87,'Draft Board'!$BD$2:$BD$87,">"&BD6)-BD6)/_xlfn.MINIFS('Draft Board'!$BD$2:$BD$87,'Draft Board'!$BD$2:$BD$87,">"&BD6)>0.08,1,0))) -> 1 | BG6: =_xlfn.MINIFS('Draft Board'!$BD$2:$BD$87,'Draft Board'!$BD$2:$BD$87,">="&BD6,'Draft Board'!$BF$2:$BF$87,1) -> 44.672 | BH6: =IF(BE6<>_xlfn.MINIFS('Draft Board'!$BE$2:$BE$87,'Draft Board'!$BD$2:$BD$87,"="&BD6),0,IF(OR(BF6=1,IFERROR(FLOOR((BG6-BD6)/BG6/0.25,1),0)<>IFERROR(FLOOR((BG6-_xlfn.MINIFS('Draft Board'!$BD$2:$BD$87,'Draft Board'!$BD$2:$BD$87,">"&BD6))/BG6/0.25,1),0)),1,0)) -> 1 | BI6: =ROUND(1+BD6*'Live Calc'!$D$29,0) -> 13 | BK6: =IF(BJ6<>"",BJ6,ROUND(BI6*INDEX('Live Calc'!$G$454:$G$539,MATCH(BC6,'Live Calc'!$A$454:$A$539,0))*'Live Calc'!$J$543,0)) -> 13
A7: Joe Burrow | B7: CIN | C7: 305.066 | D7: 305.066 | E7: 305.066 | F7: =CHOOSE(MATCH(Setup!$B$7,{"STD","Half-PPR","PPR"},0),C7,D7,E7) -> 305.066 | G7: =COUNTIFS('Draft Board'!$H$2:$H$61,">="&H7,'Draft Board'!$L$2:$L$61,1) -> 3 | H7: =MAX(0,F7-'Live Calc'!$H$19)^'Live Calc'!$E$19 -> 85.904714 | I7: 7 | J7: =IF(I7<>_xlfn.MINIFS('Draft Board'!$I$2:$I$61,'Draft Board'!$H$2:$H$61,"="&H7),0,IF(_xlfn.MINIFS('Draft Board'!$H$2:$H$61,'Draft Board'!$H$2:$H$61,">"&H7)=0,1,IF((_xlfn.MINIFS('Draft Board'!$H$2:$H$61,'Draft Board'!$H$2:$H$61,">"&H7)-H7)/_xlfn.MINIFS('Draft Board'!$H$2:$H$61,'Draft Board'!$H$2:$H$61,">"&H7)>0.08,1,0))) -> 0 | K7: =_xlfn.MINIFS('Draft Board'!$H$2:$H$61,'Draft Board'!$H$2:$H$61,">="&H7,'Draft Board'!$J$2:$J$61,1) -> 96.659136 | L7: =IF(I7<>_xlfn.MINIFS('Draft Board'!$I$2:$I$61,'Draft Board'!$H$2:$H$61,"="&H7),0,IF(OR(J7=1,IFERROR(FLOOR((K7-H7)/K7/0.25,1),0)<>IFERROR(FLOOR((K7-_xlfn.MINIFS('Draft Board'!$H$2:$H$61,'Draft Board'!$H$2:$H$61,">"&H7))/K7/0.25,1),0)),1,0)) -> 0 | M7: =ROUND(1+H7*'Live Calc'!$D$26,0) -> 13 | O7: =IF(N7<>"",N7,ROUND(M7*INDEX('Live Calc'!$G$33:$G$92,MATCH(G7,'Live Calc'!$A$33:$A$92,0))*'Live Calc'!$J$543,0)) -> 13 | Q7: De'Von Achane | R7: MIA | S7: 213.318 | T7: 245.74 | U7: 277.26 | V7: =CHOOSE(MATCH(Setup!$B$7,{"STD","Half-PPR","PPR"},0),S7,T7,U7) -> 245.74 | W7: =COUNTIFS('Draft Board'!$X$2:$X$161,">="&X7,'Draft Board'!$AB$2:$AB$161,1) -> 3 | X7: =MAX(0,V7-'Live Calc'!$H$20)^'Live Calc'!$E$20 -> 392.02236 | Y7: 7 | Z7: =IF(Y7<>_xlfn.MINIFS('Draft Board'!$Y$2:$Y$161,'Draft Board'!$X$2:$X$161,"="&X7),0,IF(_xlfn.MINIFS('Draft Board'!$X$2:$X$161,'Draft Board'!$X$2:$X$161,">"&X7)=0,1,IF((_xlfn.MINIFS('Draft Board'!$X$2:$X$161,'Draft Board'!$X$2:$X$161,">"&X7)-X7)/_xlfn.MINIFS('Draft Board'!$X$2:$X$161,'Draft Board'!$X$2:$X$161,">"&X7)>0.08,1,0))) -> 0 | AA7: =_xlfn.MINIFS('Draft Board'!$X$2:$X$161,'Draft Board'!$X$2:$X$161,">="&X7,'Draft Board'!$Z$2:$Z$161,1) -> 407.91105 | AB7: =IF(Y7<>_xlfn.MINIFS('Draft Board'!$Y$2:$Y$161,'Draft Board'!$X$2:$X$161,"="&X7),0,IF(OR(Z7=1,IFERROR(FLOOR((AA7-X7)/AA7/0.25,1),0)<>IFERROR(FLOOR((AA7-_xlfn.MINIFS('Draft Board'!$X$2:$X$161,'Draft Board'!$X$2:$X$161,">"&X7))/AA7/0.25,1),0)),1,0)) -> 0 | AC7: =ROUND(1+X7*'Live Calc'!$D$27,0) -> 37 | AE7: =IF(AD7<>"",AD7,ROUND(AC7*INDEX('Live Calc'!$G$96:$G$255,MATCH(W7,'Live Calc'!$A$96:$A$255,0))*'Live Calc'!$J$543,0)) -> 37 | AG7: Drake London | AH7: ATL | AI7: 170.76 | AJ7: 219.778 | AK7: 267.742 | AL7: =CHOOSE(MATCH(Setup!$B$7,{"STD","Half-PPR","PPR"},0),AI7,AJ7,AK7) -> 219.778 | AM7: =COUNTIFS('Draft Board'!$AN$2:$AN$193,">="&AN7,'Draft Board'!$AR$2:$AR$193,1) -> 3 | AN7: =MAX(0,AL7-'Live Calc'!$H$21)^'Live Calc'!$E$21 -> 391.13078 | AO7: 7 | AP7: =IF(AO7<>_xlfn.MINIFS('Draft Board'!$AO$2:$AO$193,'Draft Board'!$AN$2:$AN$193,"="&AN7),0,IF(_xlfn.MINIFS('Draft Board'!$AN$2:$AN$193,'Draft Board'!$AN$2:$AN$193,">"&AN7)=0,1,IF((_xlfn.MINIFS('Draft Board'!$AN$2:$AN$193,'Draft Board'!$AN$2:$AN$193,">"&AN7)-AN7)/_xlfn.MINIFS('Draft Board'!$AN$2:$AN$193,'Draft Board'!$AN$2:$AN$193,">"&AN7)>0.08,1,0))) -> 0 | AQ7: =_xlfn.MINIFS('Draft Board'!$AN$2:$AN$193,'Draft Board'!$AN$2:$AN$193,">="&AN7,'Draft Board'!$AP$2:$AP$193,1) -> 402.34831 | AR7: =IF(AO7<>_xlfn.MINIFS('Draft Board'!$AO$2:$AO$193,'Draft Board'!$AN$2:$AN$193,"="&AN7),0,IF(OR(AP7=1,IFERROR(FLOOR((AQ7-AN7)/AQ7/0.25,1),0)<>IFERROR(FLOOR((AQ7-_xlfn.MINIFS('Draft Board'!$AN$2:$AN$193,'Draft Board'!$AN$2:$AN$193,">"&AN7))/AQ7/0.25,1),0)),1,0)) -> 0 | AS7: =ROUND(1+AN7*'Live Calc'!$D$28,0) -> 33 | AU7: =IF(AT7<>"",AT7,ROUND(AS7*INDEX('Live Calc'!$G$259:$G$450,MATCH(AM7,'Live Calc'!$A$259:$A$450,0))*'Live Calc'!$J$543,0)) -> 33 | AW7: Tucker Kraft | AX7: GB | AY7: 115.9 | AZ7: 147.498 | BA7: 180.534 | BB7: =CHOOSE(MATCH(Setup!$B$7,{"STD","Half-PPR","PPR"},0),AY7,AZ7,BA7) -> 147.498 | BC7: =COUNTIFS('Draft Board'!$BD$2:$BD$87,">="&BD7,'Draft Board'!$BH$2:$BH$87,1) -> 4 | BD7: =MAX(0,BB7-'Live Calc'!$H$22)^'Live Calc'!$E$22 -> 44.248 | BE7: 7 | BF7: =IF(BE7<>_xlfn.MINIFS('Draft Board'!$BE$2:$BE$87,'Draft Board'!$BD$2:$BD$87,"="&BD7),0,IF(_xlfn.MINIFS('Draft Board'!$BD$2:$BD$87,'Draft Board'!$BD$2:$BD$87,">"&BD7)=0,1,IF((_xlfn.MINIFS('Draft Board'!$BD$2:$BD$87,'Draft Board'!$BD$2:$BD$87,">"&BD7)-BD7)/_xlfn.MINIFS('Draft Board'!$BD$2:$BD$87,'Draft Board'!$BD$2:$BD$87,">"&BD7)>0.08,1,0))) -> 0 | BG7: =_xlfn.MINIFS('Draft Board'!$BD$2:$BD$87,'Draft Board'!$BD$2:$BD$87,">="&BD7,'Draft Board'!$BF$2:$BF$87,1) -> 44.672 | BH7: =IF(BE7<>_xlfn.MINIFS('Draft Board'!$BE$2:$BE$87,'Draft Board'!$BD$2:$BD$87,"="&BD7),0,IF(OR(BF7=1,IFERROR(FLOOR((BG7-BD7)/BG7/0.25,1),0)<>IFERROR(FLOOR((BG7-_xlfn.MINIFS('Draft Board'!$BD$2:$BD$87,'Draft Board'!$BD$2:$BD$87,">"&BD7))/BG7/0.25,1),0)),1,0)) -> 0 | BI7: =ROUND(1+BD7*'Live Calc'!$D$29,0) -> 13 | BK7: =IF(BJ7<>"",BJ7,ROUND(BI7*INDEX('Live Calc'!$G$454:$G$539,MATCH(BC7,'Live Calc'!$A$454:$A$539,0))*'Live Calc'!$J$543,0)) -> 13
A8: Caleb Williams | B8: CHI | C8: 294.432 | D8: 294.432 | E8: 294.432 | F8: =CHOOSE(MATCH(Setup!$B$7,{"STD","Half-PPR","PPR"},0),C8,D8,E8) -> 294.432 | G8: =COUNTIFS('Draft Board'!$H$2:$H$61,">="&H8,'Draft Board'!$L$2:$L$61,1) -> 4 | H8: =MAX(0,F8-'Live Calc'!$H$19)^'Live Calc'!$E$19 -> 59.851791 | I8: 8 | J8: =IF(I8<>_xlfn.MINIFS('Draft Board'!$I$2:$I$61,'Draft Board'!$H$2:$H$61,"="&H8),0,IF(_xlfn.MINIFS('Draft Board'!$H$2:$H$61,'Draft Board'!$H$2:$H$61,">"&H8)=0,1,IF((_xlfn.MINIFS('Draft Board'!$H$2:$H$61,'Draft Board'!$H$2:$H$61,">"&H8)-H8)/_xlfn.MINIFS('Draft Board'!$H$2:$H$61,'Draft Board'!$H$2:$H$61,">"&H8)>0.08,1,0))) -> 1 | K8: =_xlfn.MINIFS('Draft Board'!$H$2:$H$61,'Draft Board'!$H$2:$H$61,">="&H8,'Draft Board'!$J$2:$J$61,1) -> 59.851791 | L8: =IF(I8<>_xlfn.MINIFS('Draft Board'!$I$2:$I$61,'Draft Board'!$H$2:$H$61,"="&H8),0,IF(OR(J8=1,IFERROR(FLOOR((K8-H8)/K8/0.25,1),0)<>IFERROR(FLOOR((K8-_xlfn.MINIFS('Draft Board'!$H$2:$H$61,'Draft Board'!$H$2:$H$61,">"&H8))/K8/0.25,1),0)),1,0)) -> 1 | M8: =ROUND(1+H8*'Live Calc'!$D$26,0) -> 9 | O8: =IF(N8<>"",N8,ROUND(M8*INDEX('Live Calc'!$G$33:$G$92,MATCH(G8,'Live Calc'!$A$33:$A$92,0))*'Live Calc'!$J$543,0)) -> 9 | Q8: Ashton Jeanty | R8: LV | S8: 212.604 | T8: 242.976 | U8: 274.632 | V8: =CHOOSE(MATCH(Setup!$B$7,{"STD","Half-PPR","PPR"},0),S8,T8,U8) -> 242.976 | W8: =COUNTIFS('Draft Board'!$X$2:$X$161,">="&X8,'Draft Board'!$AB$2:$AB$161,1) -> 3 | X8: =MAX(0,V8-'Live Calc'!$H$20)^'Live Calc'!$E$20 -> 383.06656 | Y8: 8 | Z8: =IF(Y8<>_xlfn.MINIFS('Draft Board'!$Y$2:$Y$161,'Draft Board'!$X$2:$X$161,"="&X8),0,IF(_xlfn.MINIFS('Draft Board'!$X$2:$X$161,'Draft Board'!$X$2:$X$161,">"&X8)=0,1,IF((_xlfn.MINIFS('Draft Board'!$X$2:$X$161,'Draft Board'!$X$2:$X$161,">"&X8)-X8)/_xlfn.MINIFS('Draft Board'!$X$2:$X$161,'Draft Board'!$X$2:$X$161,">"&X8)>0.08,1,0))) -> 0 | AA8: =_xlfn.MINIFS('Draft Board'!$X$2:$X$161,'Draft Board'!$X$2:$X$161,">="&X8,'Draft Board'!$Z$2:$Z$161,1) -> 407.91105 | AB8: =IF(Y8<>_xlfn.MINIFS('Draft Board'!$Y$2:$Y$161,'Draft Board'!$X$2:$X$161,"="&X8),0,IF(OR(Z8=1,IFERROR(FLOOR((AA8-X8)/AA8/0.25,1),0)<>IFERROR(FLOOR((AA8-_xlfn.MINIFS('Draft Board'!$X$2:$X$161,'Draft Board'!$X$2:$X$161,">"&X8))/AA8/0.25,1),0)),1,0)) -> 0 | AC8: =ROUND(1+X8*'Live Calc'!$D$27,0) -> 36 | AE8: =IF(AD8<>"",AD8,ROUND(AC8*INDEX('Live Calc'!$G$96:$G$255,MATCH(W8,'Live Calc'!$A$96:$A$255,0))*'Live Calc'!$J$543,0)) -> 36 | AG8: Justin Jefferson | AH8: MIN | AI8: 170.486 | AJ8: 218.702 | AK8: 266.868 | AL8: =CHOOSE(MATCH(Setup!$B$7,{"STD","Half-PPR","PPR"},0),AI8,AJ8,AK8) -> 218.702 | AM8: =COUNTIFS('Draft Board'!$AN$2:$AN$193,">="&AN8,'Draft Board'!$AR$2:$AR$193,1) -> 3 | AN8: =MAX(0,AL8-'Live Calc'!$H$21)^'Live Calc'!$E$21 -> 386.69783 | AO8: 8 | AP8: =IF(AO8<>_xlfn.MINIFS('Draft Board'!$AO$2:$AO$193,'Draft Board'!$AN$2:$AN$193,"="&AN8),0,IF(_xlfn.MINIFS('Draft Board'!$AN$2:$AN$193,'Draft Board'!$AN$2:$AN$193,">"&AN8)=0,1,IF((_xlfn.MINIFS('Draft Board'!$AN$2:$AN$193,'Draft Board'!$AN$2:$AN$193,">"&AN8)-AN8)/_xlfn.MINIFS('Draft Board'!$AN$2:$AN$193,'Draft Board'!$AN$2:$AN$193,">"&AN8)>0.08,1,0))) -> 0 | AQ8: =_xlfn.MINIFS('Draft Board'!$AN$2:$AN$193,'Draft Board'!$AN$2:$AN$193,">="&AN8,'Draft Board'!$AP$2:$AP$193,1) -> 402.34831 | AR8: =IF(AO8<>_xlfn.MINIFS('Draft Board'!$AO$2:$AO$193,'Draft Board'!$AN$2:$AN$193,"="&AN8),0,IF(OR(AP8=1,IFERROR(FLOOR((AQ8-AN8)/AQ8/0.25,1),0)<>IFERROR(FLOOR((AQ8-_xlfn.MINIFS('Draft Board'!$AN$2:$AN$193,'Draft Board'!$AN$2:$AN$193,">"&AN8))/AQ8/0.25,1),0)),1,0)) -> 0 | AS8: =ROUND(1+AN8*'Live Calc'!$D$28,0) -> 33 | AU8: =IF(AT8<>"",AT8,ROUND(AS8*INDEX('Live Calc'!$G$259:$G$450,MATCH(AM8,'Live Calc'!$A$259:$A$450,0))*'Live Calc'!$J$543,0)) -> 33 | AW8: Sam LaPorta | AX8: DET | AY8: 111.58 | AZ8: 145.19 | BA8: 178.538 | BB8: =CHOOSE(MATCH(Setup!$B$7,{"STD","Half-PPR","PPR"},0),AY8,AZ8,BA8) -> 145.19 | BC8: =COUNTIFS('Draft Board'!$BD$2:$BD$87,">="&BD8,'Draft Board'!$BH$2:$BH$87,1) -> 4 | BD8: =MAX(0,BB8-'Live Calc'!$H$22)^'Live Calc'!$E$22 -> 41.94 | BE8: 8 | BF8: =IF(BE8<>_xlfn.MINIFS('Draft Board'!$BE$2:$BE$87,'Draft Board'!$BD$2:$BD$87,"="&BD8),0,IF(_xlfn.MINIFS('Draft Board'!$BD$2:$BD$87,'Draft Board'!$BD$2:$BD$87,">"&BD8)=0,1,IF((_xlfn.MINIFS('Draft Board'!$BD$2:$BD$87,'Draft Board'!$BD$2:$BD$87,">"&BD8)-BD8)/_xlfn.MINIFS('Draft Board'!$BD$2:$BD$87,'Draft Board'!$BD$2:$BD$87,">"&BD8)>0.08,1,0))) -> 0 | BG8: =_xlfn.MINIFS('Draft Board'!$BD$2:$BD$87,'Draft Board'!$BD$2:$BD$87,">="&BD8,'Draft Board'!$BF$2:$BF$87,1) -> 44.672 | BH8: =IF(BE8<>_xlfn.MINIFS('Draft Board'!$BE$2:$BE$87,'Draft Board'!$BD$2:$BD$87,"="&BD8),0,IF(OR(BF8=1,IFERROR(FLOOR((BG8-BD8)/BG8/0.25,1),0)<>IFERROR(FLOOR((BG8-_xlfn.MINIFS('Draft Board'!$BD$2:$BD$87,'Draft Board'!$BD$2:$BD$87,">"&BD8))/BG8/0.25,1),0)),1,0)) -> 0 | BI8: =ROUND(1+BD8*'Live Calc'!$D$29,0) -> 12 | BK8: =IF(BJ8<>"",BJ8,ROUND(BI8*INDEX('Live Calc'!$G$454:$G$539,MATCH(BC8,'Live Calc'!$A$454:$A$539,0))*'Live Calc'!$J$543,0)) -> 12
A9: Dak Prescott | B9: DAL | C9: 294.02 | D9: 294.02 | E9: 294.02 | F9: =CHOOSE(MATCH(Setup!$B$7,{"STD","Half-PPR","PPR"},0),C9,D9,E9) -> 294.02 | G9: =COUNTIFS('Draft Board'!$H$2:$H$61,">="&H9,'Draft Board'!$L$2:$L$61,1) -> 4 | H9: =MAX(0,F9-'Live Calc'!$H$19)^'Live Calc'!$E$19 -> 58.875309 | I9: 9 | J9: =IF(I9<>_xlfn.MINIFS('Draft Board'!$I$2:$I$61,'Draft Board'!$H$2:$H$61,"="&H9),0,IF(_xlfn.MINIFS('Draft Board'!$H$2:$H$61,'Draft Board'!$H$2:$H$61,">"&H9)=0,1,IF((_xlfn.MINIFS('Draft Board'!$H$2:$H$61,'Draft Board'!$H$2:$H$61,">"&H9)-H9)/_xlfn.MINIFS('Draft Board'!$H$2:$H$61,'Draft Board'!$H$2:$H$61,">"&H9)>0.08,1,0))) -> 0 | K9: =_xlfn.MINIFS('Draft Board'!$H$2:$H$61,'Draft Board'!$H$2:$H$61,">="&H9,'Draft Board'!$J$2:$J$61,1) -> 59.851791 | L9: =IF(I9<>_xlfn.MINIFS('Draft Board'!$I$2:$I$61,'Draft Board'!$H$2:$H$61,"="&H9),0,IF(OR(J9=1,IFERROR(FLOOR((K9-H9)/K9/0.25,1),0)<>IFERROR(FLOOR((K9-_xlfn.MINIFS('Draft Board'!$H$2:$H$61,'Draft Board'!$H$2:$H$61,">"&H9))/K9/0.25,1),0)),1,0)) -> 0 | M9: =ROUND(1+H9*'Live Calc'!$D$26,0) -> 9 | O9: =IF(N9<>"",N9,ROUND(M9*INDEX('Live Calc'!$G$33:$G$92,MATCH(G9,'Live Calc'!$A$33:$A$92,0))*'Live Calc'!$J$543,0)) -> 9 | Q9: Saquon Barkley | R9: PHI | S9: 217.798 | T9: 238.37 | U9: 253.2 | V9: =CHOOSE(MATCH(Setup!$B$7,{"STD","Half-PPR","PPR"},0),S9,T9,U9) -> 238.37 | W9: =COUNTIFS('Draft Board'!$X$2:$X$161,">="&X9,'Draft Board'!$AB$2:$AB$161,1) -> 3 | X9: =MAX(0,V9-'Live Calc'!$H$20)^'Live Calc'!$E$20 -> 368.21989 | Y9: 9 | Z9: =IF(Y9<>_xlfn.MINIFS('Draft Board'!$Y$2:$Y$161,'Draft Board'!$X$2:$X$161,"="&X9),0,IF(_xlfn.MINIFS('Draft Board'!$X$2:$X$161,'Draft Board'!$X$2:$X$161,">"&X9)=0,1,IF((_xlfn.MINIFS('Draft Board'!$X$2:$X$161,'Draft Board'!$X$2:$X$161,">"&X9)-X9)/_xlfn.MINIFS('Draft Board'!$X$2:$X$161,'Draft Board'!$X$2:$X$161,">"&X9)>0.08,1,0))) -> 0 | AA9: =_xlfn.MINIFS('Draft Board'!$X$2:$X$161,'Draft Board'!$X$2:$X$161,">="&X9,'Draft Board'!$Z$2:$Z$161,1) -> 407.91105 | AB9: =IF(Y9<>_xlfn.MINIFS('Draft Board'!$Y$2:$Y$161,'Draft Board'!$X$2:$X$161,"="&X9),0,IF(OR(Z9=1,IFERROR(FLOOR((AA9-X9)/AA9/0.25,1),0)<>IFERROR(FLOOR((AA9-_xlfn.MINIFS('Draft Board'!$X$2:$X$161,'Draft Board'!$X$2:$X$161,">"&X9))/AA9/0.25,1),0)),1,0)) -> 0 | AC9: =ROUND(1+X9*'Live Calc'!$D$27,0) -> 35 | AE9: =IF(AD9<>"",AD9,ROUND(AC9*INDEX('Live Calc'!$G$96:$G$255,MATCH(W9,'Live Calc'!$A$96:$A$255,0))*'Live Calc'!$J$543,0)) -> 35 | AG9: A.J. Brown | AH9: NE | AI9: 163.77 | AJ9: 206.088 | AK9: 249.07 | AL9: =CHOOSE(MATCH(Setup!$B$7,{"STD","Half-PPR","PPR"},0),AI9,AJ9,AK9) -> 206.088 | AM9: =COUNTIFS('Draft Board'!$AN$2:$AN$193,">="&AN9,'Draft Board'!$AR$2:$AR$193,1) -> 4 | AN9: =MAX(0,AL9-'Live Calc'!$H$21)^'Live Calc'!$E$21 -> 335.50592 | AO9: 9 | AP9: =IF(AO9<>_xlfn.MINIFS('Draft Board'!$AO$2:$AO$193,'Draft Board'!$AN$2:$AN$193,"="&AN9),0,IF(_xlfn.MINIFS('Draft Board'!$AN$2:$AN$193,'Draft Board'!$AN$2:$AN$193,">"&AN9)=0,1,IF((_xlfn.MINIFS('Draft Board'!$AN$2:$AN$193,'Draft Board'!$AN$2:$AN$193,">"&AN9)-AN9)/_xlfn.MINIFS('Draft Board'!$AN$2:$AN$193,'Draft Board'!$AN$2:$AN$193,">"&AN9)>0.08,1,0))) -> 1 | AQ9: =_xlfn.MINIFS('Draft Board'!$AN$2:$AN$193,'Draft Board'!$AN$2:$AN$193,">="&AN9,'Draft Board'!$AP$2:$AP$193,1) -> 335.50592 | AR9: =IF(AO9<>_xlfn.MINIFS('Draft Board'!$AO$2:$AO$193,'Draft Board'!$AN$2:$AN$193,"="&AN9),0,IF(OR(AP9=1,IFERROR(FLOOR((AQ9-AN9)/AQ9/0.25,1),0)<>IFERROR(FLOOR((AQ9-_xlfn.MINIFS('Draft Board'!$AN$2:$AN$193,'Draft Board'!$AN$2:$AN$193,">"&AN9))/AQ9/0.25,1),0)),1,0)) -> 1 | AS9: =ROUND(1+AN9*'Live Calc'!$D$28,0) -> 28 | AU9: =IF(AT9<>"",AT9,ROUND(AS9*INDEX('Live Calc'!$G$259:$G$450,MATCH(AM9,'Live Calc'!$A$259:$A$450,0))*'Live Calc'!$J$543,0)) -> 28 | AW9: Kyle Pitts Sr. | AX9: ATL | AY9: 106.39 | AZ9: 143.09 | BA9: 179.584 | BB9: =CHOOSE(MATCH(Setup!$B$7,{"STD","Half-PPR","PPR"},0),AY9,AZ9,BA9) -> 143.09 | BC9: =COUNTIFS('Draft Board'!$BD$2:$BD$87,">="&BD9,'Draft Board'!$BH$2:$BH$87,1) -> 4 | BD9: =MAX(0,BB9-'Live Calc'!$H$22)^'Live Calc'!$E$22 -> 39.84 | BE9: 9 | BF9: =IF(BE9<>_xlfn.MINIFS('Draft Board'!$BE$2:$BE$87,'Draft Board'!$BD$2:$BD$87,"="&BD9),0,IF(_xlfn.MINIFS('Draft Board'!$BD$2:$BD$87,'Draft Board'!$BD$2:$BD$87,">"&BD9)=0,1,IF((_xlfn.MINIFS('Draft Board'!$BD$2:$BD$87,'Draft Board'!$BD$2:$BD$87,">"&BD9)-BD9)/_xlfn.MINIFS('Draft Board'!$BD$2:$BD$87,'Draft Board'!$BD$2:$BD$87,">"&BD9)>0.08,1,0))) -> 0 | BG9: =_xlfn.MINIFS('Draft Board'!$BD$2:$BD$87,'Draft Board'!$BD$2:$BD$87,">="&BD9,'Draft Board'!$BF$2:$BF$87,1) -> 44.672 | BH9: =IF(BE9<>_xlfn.MINIFS('Draft Board'!$BE$2:$BE$87,'Draft Board'!$BD$2:$BD$87,"="&BD9),0,IF(OR(BF9=1,IFERROR(FLOOR((BG9-BD9)/BG9/0.25,1),0)<>IFERROR(FLOOR((BG9-_xlfn.MINIFS('Draft Board'!$BD$2:$BD$87,'Draft Board'!$BD$2:$BD$87,">"&BD9))/BG9/0.25,1),0)),1,0)) -> 0 | BI9: =ROUND(1+BD9*'Live Calc'!$D$29,0) -> 12 | BK9: =IF(BJ9<>"",BJ9,ROUND(BI9*INDEX('Live Calc'!$G$454:$G$539,MATCH(BC9,'Live Calc'!$A$454:$A$539,0))*'Live Calc'!$J$543,0)) -> 12
A10: Trevor Lawrence | B10: JAC | C10: 293.342 | D10: 293.342 | E10: 293.342 | F10: =CHOOSE(MATCH(Setup!$B$7,{"STD","Half-PPR","PPR"},0),C10,D10,E10) -> 293.342 | G10: =COUNTIFS('Draft Board'!$H$2:$H$61,">="&H10,'Draft Board'!$L$2:$L$61,1) -> 4 | H10: =MAX(0,F10-'Live Calc'!$H$19)^'Live Calc'!$E$19 -> 57.274255 | I10: 10 | J10: =IF(I10<>_xlfn.MINIFS('Draft Board'!$I$2:$I$61,'Draft Board'!$H$2:$H$61,"="&H10),0,IF(_xlfn.MINIFS('Draft Board'!$H$2:$H$61,'Draft Board'!$H$2:$H$61,">"&H10)=0,1,IF((_xlfn.MINIFS('Draft Board'!$H$2:$H$61,'Draft Board'!$H$2:$H$61,">"&H10)-H10)/_xlfn.MINIFS('Draft Board'!$H$2:$H$61,'Draft Board'!$H$2:$H$61,">"&H10)>0.08,1,0))) -> 0 | K10: =_xlfn.MINIFS('Draft Board'!$H$2:$H$61,'Draft Board'!$H$2:$H$61,">="&H10,'Draft Board'!$J$2:$J$61,1) -> 59.851791 | L10: =IF(I10<>_xlfn.MINIFS('Draft Board'!$I$2:$I$61,'Draft Board'!$H$2:$H$61,"="&H10),0,IF(OR(J10=1,IFERROR(FLOOR((K10-H10)/K10/0.25,1),0)<>IFERROR(FLOOR((K10-_xlfn.MINIFS('Draft Board'!$H$2:$H$61,'Draft Board'!$H$2:$H$61,">"&H10))/K10/0.25,1),0)),1,0)) -> 0 | M10: =ROUND(1+H10*'Live Calc'!$D$26,0) -> 9 | O10: =IF(N10<>"",N10,ROUND(M10*INDEX('Live Calc'!$G$33:$G$92,MATCH(G10,'Live Calc'!$A$33:$A$92,0))*'Live Calc'!$J$543,0)) -> 9 | Q10: Derrick Henry | R10: BAL | S10: 234.618 | T10: 236.068 | U10: 249.784 | V10: =CHOOSE(MATCH(Setup!$B$7,{"STD","Half-PPR","PPR"},0),S10,T10,U10) -> 236.068 | W10: =COUNTIFS('Draft Board'!$X$2:$X$161,">="&X10,'Draft Board'!$AB$2:$AB$161,1) -> 3 | X10: =MAX(0,V10-'Live Calc'!$H$20)^'Live Calc'!$E$20 -> 360.83676 | Y10: 10 | Z10: =IF(Y10<>_xlfn.MINIFS('Draft Board'!$Y$2:$Y$161,'Draft Board'!$X$2:$X$161,"="&X10),0,IF(_xlfn.MINIFS('Draft Board'!$X$2:$X$161,'Draft Board'!$X$2:$X$161,">"&X10)=0,1,IF((_xlfn.MINIFS('Draft Board'!$X$2:$X$161,'Draft Board'!$X$2:$X$161,">"&X10)-X10)/_xlfn.MINIFS('Draft Board'!$X$2:$X$161,'Draft Board'!$X$2:$X$161,">"&X10)>0.08,1,0))) -> 0 | AA10: =_xlfn.MINIFS('Draft Board'!$X$2:$X$161,'Draft Board'!$X$2:$X$161,">="&X10,'Draft Board'!$Z$2:$Z$161,1) -> 407.91105 | AB10: =IF(Y10<>_xlfn.MINIFS('Draft Board'!$Y$2:$Y$161,'Draft Board'!$X$2:$X$161,"="&X10),0,IF(OR(Z10=1,IFERROR(FLOOR((AA10-X10)/AA10/0.25,1),0)<>IFERROR(FLOOR((AA10-_xlfn.MINIFS('Draft Board'!$X$2:$X$161,'Draft Board'!$X$2:$X$161,">"&X10))/AA10/0.25,1),0)),1,0)) -> 0 | AC10: =ROUND(1+X10*'Live Calc'!$D$27,0) -> 34 | AE10: =IF(AD10<>"",AD10,ROUND(AC10*INDEX('Live Calc'!$G$96:$G$255,MATCH(W10,'Live Calc'!$A$96:$A$255,0))*'Live Calc'!$J$543,0)) -> 34 | AG10: George Pickens | AH10: DAL | AI10: 163.822 | AJ10: 204.554 | AK10: 245.86 | AL10: =CHOOSE(MATCH(Setup!$B$7,{"STD","Half-PPR","PPR"},0),AI10,AJ10,AK10) -> 204.554 | AM10: =COUNTIFS('Draft Board'!$AN$2:$AN$193,">="&AN10,'Draft Board'!$AR$2:$AR$193,1) -> 4 | AN10: =MAX(0,AL10-'Live Calc'!$H$21)^'Live Calc'!$E$21 -> 329.38132 | AO10: 10 | AP10: =IF(AO10<>_xlfn.MINIFS('Draft Board'!$AO$2:$AO$193,'Draft Board'!$AN$2:$AN$193,"="&AN10),0,IF(_xlfn.MINIFS('Draft Board'!$AN$2:$AN$193,'Draft Board'!$AN$2:$AN$193,">"&AN10)=0,1,IF((_xlfn.MINIFS('Draft Board'!$AN$2:$AN$193,'Draft Board'!$AN$2:$AN$193,">"&AN10)-AN10)/_xlfn.MINIFS('Draft Board'!$AN$2:$AN$193,'Draft Board'!$AN$2:$AN$193,">"&AN10)>0.08,1,0))) -> 0 | AQ10: =_xlfn.MINIFS('Draft Board'!$AN$2:$AN$193,'Draft Board'!$AN$2:$AN$193,">="&AN10,'Draft Board'!$AP$2:$AP$193,1) -> 335.50592 | AR10: =IF(AO10<>_xlfn.MINIFS('Draft Board'!$AO$2:$AO$193,'Draft Board'!$AN$2:$AN$193,"="&AN10),0,IF(OR(AP10=1,IFERROR(FLOOR((AQ10-AN10)/AQ10/0.25,1),0)<>IFERROR(FLOOR((AQ10-_xlfn.MINIFS('Draft Board'!$AN$2:$AN$193,'Draft Board'!$AN$2:$AN$193,">"&AN10))/AQ10/0.25,1),0)),1,0)) -> 0 | AS10: =ROUND(1+AN10*'Live Calc'!$D$28,0) -> 28 | AU10: =IF(AT10<>"",AT10,ROUND(AS10*INDEX('Live Calc'!$G$259:$G$450,MATCH(AM10,'Live Calc'!$A$259:$A$450,0))*'Live Calc'!$J$543,0)) -> 28 | AW10: Travis Kelce | AX10: KC | AY10: 102.914 | AZ10: 137.114 | BA10: 170.48 | BB10: =CHOOSE(MATCH(Setup!$B$7,{"STD","Half-PPR","PPR"},0),AY10,AZ10,BA10) -> 137.114 | BC10: =COUNTIFS('Draft Board'!$BD$2:$BD$87,">="&BD10,'Draft Board'!$BH$2:$BH$87,1) -> 5 | BD10: =MAX(0,BB10-'Live Calc'!$H$22)^'Live Calc'!$E$22 -> 33.864 | BE10: 10 | BF10: =IF(BE10<>_xlfn.MINIFS('Draft Board'!$BE$2:$BE$87,'Draft Board'!$BD$2:$BD$87,"="&BD10),0,IF(_xlfn.MINIFS('Draft Board'!$BD$2:$BD$87,'Draft Board'!$BD$2:$BD$87,">"&BD10)=0,1,IF((_xlfn.MINIFS('Draft Board'!$BD$2:$BD$87,'Draft Board'!$BD$2:$BD$87,">"&BD10)-BD10)/_xlfn.MINIFS('Draft Board'!$BD$2:$BD$87,'Draft Board'!$BD$2:$BD$87,">"&BD10)>0.08,1,0))) -> 1 | BG10: =_xlfn.MINIFS('Draft Board'!$BD$2:$BD$87,'Draft Board'!$BD$2:$BD$87,">="&BD10,'Draft Board'!$BF$2:$BF$87,1) -> 33.864 | BH10: =IF(BE10<>_xlfn.MINIFS('Draft Board'!$BE$2:$BE$87,'Draft Board'!$BD$2:$BD$87,"="&BD10),0,IF(OR(BF10=1,IFERROR(FLOOR((BG10-BD10)/BG10/0.25,1),0)<>IFERROR(FLOOR((BG10-_xlfn.MINIFS('Draft Board'!$BD$2:$BD$87,'Draft Board'!$BD$2:$BD$87,">"&BD10))/BG10/0.25,1),0)),1,0)) -> 1 | BI10: =ROUND(1+BD10*'Live Calc'!$D$29,0) -> 10 | BK10: =IF(BJ10<>"",BJ10,ROUND(BI10*INDEX('Live Calc'!$G$454:$G$539,MATCH(BC10,'Live Calc'!$A$454:$A$539,0))*'Live Calc'!$J$543,0)) -> 10
A11: Jaxson Dart | B11: NYG | C11: 292.892 | D11: 292.892 | E11: 292.892 | F11: =CHOOSE(MATCH(Setup!$B$7,{"STD","Half-PPR","PPR"},0),C11,D11,E11) -> 292.892 | G11: =COUNTIFS('Draft Board'!$H$2:$H$61,">="&H11,'Draft Board'!$L$2:$L$61,1) -> 4 | H11: =MAX(0,F11-'Live Calc'!$H$19)^'Live Calc'!$E$19 -> 56.215699 | I11: 11 | J11: =IF(I11<>_xlfn.MINIFS('Draft Board'!$I$2:$I$61,'Draft Board'!$H$2:$H$61,"="&H11),0,IF(_xlfn.MINIFS('Draft Board'!$H$2:$H$61,'Draft Board'!$H$2:$H$61,">"&H11)=0,1,IF((_xlfn.MINIFS('Draft Board'!$H$2:$H$61,'Draft Board'!$H$2:$H$61,">"&H11)-H11)/_xlfn.MINIFS('Draft Board'!$H$2:$H$61,'Draft Board'!$H$2:$H$61,">"&H11)>0.08,1,0))) -> 0 | K11: =_xlfn.MINIFS('Draft Board'!$H$2:$H$61,'Draft Board'!$H$2:$H$61,">="&H11,'Draft Board'!$J$2:$J$61,1) -> 59.851791 | L11: =IF(I11<>_xlfn.MINIFS('Draft Board'!$I$2:$I$61,'Draft Board'!$H$2:$H$61,"="&H11),0,IF(OR(J11=1,IFERROR(FLOOR((K11-H11)/K11/0.25,1),0)<>IFERROR(FLOOR((K11-_xlfn.MINIFS('Draft Board'!$H$2:$H$61,'Draft Board'!$H$2:$H$61,">"&H11))/K11/0.25,1),0)),1,0)) -> 0 | M11: =ROUND(1+H11*'Live Calc'!$D$26,0) -> 9 | O11: =IF(N11<>"",N11,ROUND(M11*INDEX('Live Calc'!$G$33:$G$92,MATCH(G11,'Live Calc'!$A$33:$A$92,0))*'Live Calc'!$J$543,0)) -> 9 | Q11: Chase Brown | R11: CIN | S11: 200.93 | T11: 232.19 | U11: 263.46 | V11: =CHOOSE(MATCH(Setup!$B$7,{"STD","Half-PPR","PPR"},0),S11,T11,U11) -> 232.19 | W11: =COUNTIFS('Draft Board'!$X$2:$X$161,">="&X11,'Draft Board'!$AB$2:$AB$161,1) -> 3 | X11: =MAX(0,V11-'Live Calc'!$H$20)^'Live Calc'!$E$20 -> 348.45591 | Y11: 11 | Z11: =IF(Y11<>_xlfn.MINIFS('Draft Board'!$Y$2:$Y$161,'Draft Board'!$X$2:$X$161,"="&X11),0,IF(_xlfn.MINIFS('Draft Board'!$X$2:$X$161,'Draft Board'!$X$2:$X$161,">"&X11)=0,1,IF((_xlfn.MINIFS('Draft Board'!$X$2:$X$161,'Draft Board'!$X$2:$X$161,">"&X11)-X11)/_xlfn.MINIFS('Draft Board'!$X$2:$X$161,'Draft Board'!$X$2:$X$161,">"&X11)>0.08,1,0))) -> 0 | AA11: =_xlfn.MINIFS('Draft Board'!$X$2:$X$161,'Draft Board'!$X$2:$X$161,">="&X11,'Draft Board'!$Z$2:$Z$161,1) -> 407.91105 | AB11: =IF(Y11<>_xlfn.MINIFS('Draft Board'!$Y$2:$Y$161,'Draft Board'!$X$2:$X$161,"="&X11),0,IF(OR(Z11=1,IFERROR(FLOOR((AA11-X11)/AA11/0.25,1),0)<>IFERROR(FLOOR((AA11-_xlfn.MINIFS('Draft Board'!$X$2:$X$161,'Draft Board'!$X$2:$X$161,">"&X11))/AA11/0.25,1),0)),1,0)) -> 0 | AC11: =ROUND(1+X11*'Live Calc'!$D$27,0) -> 33 | AE11: =IF(AD11<>"",AD11,ROUND(AC11*INDEX('Live Calc'!$G$96:$G$255,MATCH(W11,'Live Calc'!$A$96:$A$255,0))*'Live Calc'!$J$543,0)) -> 33 | AG11: Nico Collins | AH11: HOU | AI11: 164.132 | AJ11: 203.432 | AK11: 244.142 | AL11: =CHOOSE(MATCH(Setup!$B$7,{"STD","Half-PPR","PPR"},0),AI11,AJ11,AK11) -> 203.432 | AM11: =COUNTIFS('Draft Board'!$AN$2:$AN$193,">="&AN11,'Draft Board'!$AR$2:$AR$193,1) -> 4 | AN11: =MAX(0,AL11-'Live Calc'!$H$21)^'Live Calc'!$E$21 -> 324.91602 | AO11: 11 | AP11: =IF(AO11<>_xlfn.MINIFS('Draft Board'!$AO$2:$AO$193,'Draft Board'!$AN$2:$AN$193,"="&AN11),0,IF(_xlfn.MINIFS('Draft Board'!$AN$2:$AN$193,'Draft Board'!$AN$2:$AN$193,">"&AN11)=0,1,IF((_xlfn.MINIFS('Draft Board'!$AN$2:$AN$193,'Draft Board'!$AN$2:$AN$193,">"&AN11)-AN11)/_xlfn.MINIFS('Draft Board'!$AN$2:$AN$193,'Draft Board'!$AN$2:$AN$193,">"&AN11)>0.08,1,0))) -> 0 | AQ11: =_xlfn.MINIFS('Draft Board'!$AN$2:$AN$193,'Draft Board'!$AN$2:$AN$193,">="&AN11,'Draft Board'!$AP$2:$AP$193,1) -> 335.50592 | AR11: =IF(AO11<>_xlfn.MINIFS('Draft Board'!$AO$2:$AO$193,'Draft Board'!$AN$2:$AN$193,"="&AN11),0,IF(OR(AP11=1,IFERROR(FLOOR((AQ11-AN11)/AQ11/0.25,1),0)<>IFERROR(FLOOR((AQ11-_xlfn.MINIFS('Draft Board'!$AN$2:$AN$193,'Draft Board'!$AN$2:$AN$193,">"&AN11))/AQ11/0.25,1),0)),1,0)) -> 0 | AS11: =ROUND(1+AN11*'Live Calc'!$D$28,0) -> 28 | AU11: =IF(AT11<>"",AT11,ROUND(AS11*INDEX('Live Calc'!$G$259:$G$450,MATCH(AM11,'Live Calc'!$A$259:$A$450,0))*'Live Calc'!$J$543,0)) -> 28 | AW11: George Kittle | AX11: SF | AY11: 104.186 | AZ11: 135.182 | BA11: 167.54 | BB11: =CHOOSE(MATCH(Setup!$B$7,{"STD","Half-PPR","PPR"},0),AY11,AZ11,BA11) -> 135.182 | BC11: =COUNTIFS('Draft Board'!$BD$2:$BD$87,">="&BD11,'Draft Board'!$BH$2:$BH$87,1) -> 5 | BD11: =MAX(0,BB11-'Live Calc'!$H$22)^'Live Calc'!$E$22 -> 31.932 | BE11: 11 | BF11: =IF(BE11<>_xlfn.MINIFS('Draft Board'!$BE$2:$BE$87,'Draft Board'!$BD$2:$BD$87,"="&BD11),0,IF(_xlfn.MINIFS('Draft Board'!$BD$2:$BD$87,'Draft Board'!$BD$2:$BD$87,">"&BD11)=0,1,IF((_xlfn.MINIFS('Draft Board'!$BD$2:$BD$87,'Draft Board'!$BD$2:$BD$87,">"&BD11)-BD11)/_xlfn.MINIFS('Draft Board'!$BD$2:$BD$87,'Draft Board'!$BD$2:$BD$87,">"&BD11)>0.08,1,0))) -> 0 | BG11: =_xlfn.MINIFS('Draft Board'!$BD$2:$BD$87,'Draft Board'!$BD$2:$BD$87,">="&BD11,'Draft Board'!$BF$2:$BF$87,1) -> 33.864 | BH11: =IF(BE11<>_xlfn.MINIFS('Draft Board'!$BE$2:$BE$87,'Draft Board'!$BD$2:$BD$87,"="&BD11),0,IF(OR(BF11=1,IFERROR(FLOOR((BG11-BD11)/BG11/0.25,1),0)<>IFERROR(FLOOR((BG11-_xlfn.MINIFS('Draft Board'!$BD$2:$BD$87,'Draft Board'!$BD$2:$BD$87,">"&BD11))/BG11/0.25,1),0)),1,0)) -> 0 | BI11: =ROUND(1+BD11*'Live Calc'!$D$29,0) -> 10 | BK11: =IF(BJ11<>"",BJ11,ROUND(BI11*INDEX('Live Calc'!$G$454:$G$539,MATCH(BC11,'Live Calc'!$A$454:$A$539,0))*'Live Calc'!$J$543,0)) -> 10
A12: Justin Herbert | B12: LAC | C12: 292.624 | D12: 292.624 | E12: 292.624 | F12: =CHOOSE(MATCH(Setup!$B$7,{"STD","Half-PPR","PPR"},0),C12,D12,E12) -> 292.624 | G12: =COUNTIFS('Draft Board'!$H$2:$H$61,">="&H12,'Draft Board'!$L$2:$L$61,1) -> 4 | H12: =MAX(0,F12-'Live Calc'!$H$19)^'Live Calc'!$E$19 -> 55.586841 | I12: 12 | J12: =IF(I12<>_xlfn.MINIFS('Draft Board'!$I$2:$I$61,'Draft Board'!$H$2:$H$61,"="&H12),0,IF(_xlfn.MINIFS('Draft Board'!$H$2:$H$61,'Draft Board'!$H$2:$H$61,">"&H12)=0,1,IF((_xlfn.MINIFS('Draft Board'!$H$2:$H$61,'Draft Board'!$H$2:$H$61,">"&H12)-H12)/_xlfn.MINIFS('Draft Board'!$H$2:$H$61,'Draft Board'!$H$2:$H$61,">"&H12)>0.08,1,0))) -> 0 | K12: =_xlfn.MINIFS('Draft Board'!$H$2:$H$61,'Draft Board'!$H$2:$H$61,">="&H12,'Draft Board'!$J$2:$J$61,1) -> 59.851791 | L12: =IF(I12<>_xlfn.MINIFS('Draft Board'!$I$2:$I$61,'Draft Board'!$H$2:$H$61,"="&H12),0,IF(OR(J12=1,IFERROR(FLOOR((K12-H12)/K12/0.25,1),0)<>IFERROR(FLOOR((K12-_xlfn.MINIFS('Draft Board'!$H$2:$H$61,'Draft Board'!$H$2:$H$61,">"&H12))/K12/0.25,1),0)),1,0)) -> 0 | M12: =ROUND(1+H12*'Live Calc'!$D$26,0) -> 8 | O12: =IF(N12<>"",N12,ROUND(M12*INDEX('Live Calc'!$G$33:$G$92,MATCH(G12,'Live Calc'!$A$33:$A$92,0))*'Live Calc'!$J$543,0)) -> 8 | Q12: Kenneth Walker III | R12: KC | S12: 205.05 | T12: 229.728 | U12: 247.496 | V12: =CHOOSE(MATCH(Setup!$B$7,{"STD","Half-PPR","PPR"},0),S12,T12,U12) -> 229.728 | W12: =COUNTIFS('Draft Board'!$X$2:$X$161,">="&X12,'Draft Board'!$AB$2:$AB$161,1) -> 3 | X12: =MAX(0,V12-'Live Calc'!$H$20)^'Live Calc'!$E$20 -> 340.63348 | Y12: 12 | Z12: =IF(Y12<>_xlfn.MINIFS('Draft Board'!$Y$2:$Y$161,'Draft Board'!$X$2:$X$161,"="&X12),0,IF(_xlfn.MINIFS('Draft Board'!$X$2:$X$161,'Draft Board'!$X$2:$X$161,">"&X12)=0,1,IF((_xlfn.MINIFS('Draft Board'!$X$2:$X$161,'Draft Board'!$X$2:$X$161,">"&X12)-X12)/_xlfn.MINIFS('Draft Board'!$X$2:$X$161,'Draft Board'!$X$2:$X$161,">"&X12)>0.08,1,0))) -> 0 | AA12: =_xlfn.MINIFS('Draft Board'!$X$2:$X$161,'Draft Board'!$X$2:$X$161,">="&X12,'Draft Board'!$Z$2:$Z$161,1) -> 407.91105 | AB12: =IF(Y12<>_xlfn.MINIFS('Draft Board'!$Y$2:$Y$161,'Draft Board'!$X$2:$X$161,"="&X12),0,IF(OR(Z12=1,IFERROR(FLOOR((AA12-X12)/AA12/0.25,1),0)<>IFERROR(FLOOR((AA12-_xlfn.MINIFS('Draft Board'!$X$2:$X$161,'Draft Board'!$X$2:$X$161,">"&X12))/AA12/0.25,1),0)),1,0)) -> 0 | AC12: =ROUND(1+X12*'Live Calc'!$D$27,0) -> 32 | AE12: =IF(AD12<>"",AD12,ROUND(AC12*INDEX('Live Calc'!$G$96:$G$255,MATCH(W12,'Live Calc'!$A$96:$A$255,0))*'Live Calc'!$J$543,0)) -> 32 | AG12: Rashee Rice | AH12: KC | AI12: 157.63 | AJ12: 202.376 | AK12: 245.548 | AL12: =CHOOSE(MATCH(Setup!$B$7,{"STD","Half-PPR","PPR"},0),AI12,AJ12,AK12) -> 202.376 | AM12: =COUNTIFS('Draft Board'!$AN$2:$AN$193,">="&AN12,'Draft Board'!$AR$2:$AR$193,1) -> 4 | AN12: =MAX(0,AL12-'Live Calc'!$H$21)^'Live Calc'!$E$21 -> 320.72456 | AO12: 12 | AP12: =IF(AO12<>_xlfn.MINIFS('Draft Board'!$AO$2:$AO$193,'Draft Board'!$AN$2:$AN$193,"="&AN12),0,IF(_xlfn.MINIFS('Draft Board'!$AN$2:$AN$193,'Draft Board'!$AN$2:$AN$193,">"&AN12)=0,1,IF((_xlfn.MINIFS('Draft Board'!$AN$2:$AN$193,'Draft Board'!$AN$2:$AN$193,">"&AN12)-AN12)/_xlfn.MINIFS('Draft Board'!$AN$2:$AN$193,'Draft Board'!$AN$2:$AN$193,">"&AN12)>0.08,1,0))) -> 0 | AQ12: =_xlfn.MINIFS('Draft Board'!$AN$2:$AN$193,'Draft Board'!$AN$2:$AN$193,">="&AN12,'Draft Board'!$AP$2:$AP$193,1) -> 335.50592 | AR12: =IF(AO12<>_xlfn.MINIFS('Draft Board'!$AO$2:$AO$193,'Draft Board'!$AN$2:$AN$193,"="&AN12),0,IF(OR(AP12=1,IFERROR(FLOOR((AQ12-AN12)/AQ12/0.25,1),0)<>IFERROR(FLOOR((AQ12-_xlfn.MINIFS('Draft Board'!$AN$2:$AN$193,'Draft Board'!$AN$2:$AN$193,">"&AN12))/AQ12/0.25,1),0)),1,0)) -> 0 | AS12: =ROUND(1+AN12*'Live Calc'!$D$28,0) -> 27 | AU12: =IF(AT12<>"",AT12,ROUND(AS12*INDEX('Live Calc'!$G$259:$G$450,MATCH(AM12,'Live Calc'!$A$259:$A$450,0))*'Live Calc'!$J$543,0)) -> 27 | AW12: Mark Andrews | AX12: BAL | AY12: 105.13 | AZ12: 133.544 | BA12: 162.118 | BB12: =CHOOSE(MATCH(Setup!$B$7,{"STD","Half-PPR","PPR"},0),AY12,AZ12,BA12) -> 133.544 | BC12: =COUNTIFS('Draft Board'!$BD$2:$BD$87,">="&BD12,'Draft Board'!$BH$2:$BH$87,1) -> 5 | BD12: =MAX(0,BB12-'Live Calc'!$H$22)^'Live Calc'!$E$22 -> 30.294 | BE12: 12 | BF12: =IF(BE12<>_xlfn.MINIFS('Draft Board'!$BE$2:$BE$87,'Draft Board'!$BD$2:$BD$87,"="&BD12),0,IF(_xlfn.MINIFS('Draft Board'!$BD$2:$BD$87,'Draft Board'!$BD$2:$BD$87,">"&BD12)=0,1,IF((_xlfn.MINIFS('Draft Board'!$BD$2:$BD$87,'Draft Board'!$BD$2:$BD$87,">"&BD12)-BD12)/_xlfn.MINIFS('Draft Board'!$BD$2:$BD$87,'Draft Board'!$BD$2:$BD$87,">"&BD12)>0.08,1,0))) -> 0 | BG12: =_xlfn.MINIFS('Draft Board'!$BD$2:$BD$87,'Draft Board'!$BD$2:$BD$87,">="&BD12,'Draft Board'!$BF$2:$BF$87,1) -> 33.864 | BH12: =IF(BE12<>_xlfn.MINIFS('Draft Board'!$BE$2:$BE$87,'Draft Board'!$BD$2:$BD$87,"="&BD12),0,IF(OR(BF12=1,IFERROR(FLOOR((BG12-BD12)/BG12/0.25,1),0)<>IFERROR(FLOOR((BG12-_xlfn.MINIFS('Draft Board'!$BD$2:$BD$87,'Draft Board'!$BD$2:$BD$87,">"&BD12))/BG12/0.25,1),0)),1,0)) -> 0 | BI12: =ROUND(1+BD12*'Live Calc'!$D$29,0) -> 9 | BK12: =IF(BJ12<>"",BJ12,ROUND(BI12*INDEX('Live Calc'!$G$454:$G$539,MATCH(BC12,'Live Calc'!$A$454:$A$539,0))*'Live Calc'!$J$543,0)) -> 9
A13: Brock Purdy | B13: SF | C13: 287.944 | D13: 287.944 | E13: 287.944 | F13: =CHOOSE(MATCH(Setup!$B$7,{"STD","Half-PPR","PPR"},0),C13,D13,E13) -> 287.944 | G13: =COUNTIFS('Draft Board'!$H$2:$H$61,">="&H13,'Draft Board'!$L$2:$L$61,1) -> 5 | H13: =MAX(0,F13-'Live Calc'!$H$19)^'Live Calc'!$E$19 -> 44.804611 | I13: 13 | J13: =IF(I13<>_xlfn.MINIFS('Draft Board'!$I$2:$I$61,'Draft Board'!$H$2:$H$61,"="&H13),0,IF(_xlfn.MINIFS('Draft Board'!$H$2:$H$61,'Draft Board'!$H$2:$H$61,">"&H13)=0,1,IF((_xlfn.MINIFS('Draft Board'!$H$2:$H$61,'Draft Board'!$H$2:$H$61,">"&H13)-H13)/_xlfn.MINIFS('Draft Board'!$H$2:$H$61,'Draft Board'!$H$2:$H$61,">"&H13)>0.08,1,0))) -> 1 | K13: =_xlfn.MINIFS('Draft Board'!$H$2:$H$61,'Draft Board'!$H$2:$H$61,">="&H13,'Draft Board'!$J$2:$J$61,1) -> 44.804611 | L13: =IF(I13<>_xlfn.MINIFS('Draft Board'!$I$2:$I$61,'Draft Board'!$H$2:$H$61,"="&H13),0,IF(OR(J13=1,IFERROR(FLOOR((K13-H13)/K13/0.25,1),0)<>IFERROR(FLOOR((K13-_xlfn.MINIFS('Draft Board'!$H$2:$H$61,'Draft Board'!$H$2:$H$61,">"&H13))/K13/0.25,1),0)),1,0)) -> 1 | M13: =ROUND(1+H13*'Live Calc'!$D$26,0) -> 7 | O13: =IF(N13<>"",N13,ROUND(M13*INDEX('Live Calc'!$G$33:$G$92,MATCH(G13,'Live Calc'!$A$33:$A$92,0))*'Live Calc'!$J$543,0)) -> 7 | Q13: Omarion Hampton | R13: LAC | S13: 202.638 | T13: 225.35 | U13: 251.284 | V13: =CHOOSE(MATCH(Setup!$B$7,{"STD","Half-PPR","PPR"},0),S13,T13,U13) -> 225.35 | W13: =COUNTIFS('Draft Board'!$X$2:$X$161,">="&X13,'Draft Board'!$AB$2:$AB$161,1) -> 3 | X13: =MAX(0,V13-'Live Calc'!$H$20)^'Live Calc'!$E$20 -> 326.79738 | Y13: 13 | Z13: =IF(Y13<>_xlfn.MINIFS('Draft Board'!$Y$2:$Y$161,'Draft Board'!$X$2:$X$161,"="&X13),0,IF(_xlfn.MINIFS('Draft Board'!$X$2:$X$161,'Draft Board'!$X$2:$X$161,">"&X13)=0,1,IF((_xlfn.MINIFS('Draft Board'!$X$2:$X$161,'Draft Board'!$X$2:$X$161,">"&X13)-X13)/_xlfn.MINIFS('Draft Board'!$X$2:$X$161,'Draft Board'!$X$2:$X$161,">"&X13)>0.08,1,0))) -> 0 | AA13: =_xlfn.MINIFS('Draft Board'!$X$2:$X$161,'Draft Board'!$X$2:$X$161,">="&X13,'Draft Board'!$Z$2:$Z$161,1) -> 407.91105 | AB13: =IF(Y13<>_xlfn.MINIFS('Draft Board'!$Y$2:$Y$161,'Draft Board'!$X$2:$X$161,"="&X13),0,IF(OR(Z13=1,IFERROR(FLOOR((AA13-X13)/AA13/0.25,1),0)<>IFERROR(FLOOR((AA13-_xlfn.MINIFS('Draft Board'!$X$2:$X$161,'Draft Board'!$X$2:$X$161,">"&X13))/AA13/0.25,1),0)),1,0)) -> 0 | AC13: =ROUND(1+X13*'Live Calc'!$D$27,0) -> 31 | AE13: =IF(AD13<>"",AD13,ROUND(AC13*INDEX('Live Calc'!$G$96:$G$255,MATCH(W13,'Live Calc'!$A$96:$A$255,0))*'Live Calc'!$J$543,0)) -> 31 | AG13: Chris Olave | AH13: NO | AI13: 152.8 | AJ13: 195.858 | AK13: 238.126 | AL13: =CHOOSE(MATCH(Setup!$B$7,{"STD","Half-PPR","PPR"},0),AI13,AJ13,AK13) -> 195.858 | AM13: =COUNTIFS('Draft Board'!$AN$2:$AN$193,">="&AN13,'Draft Board'!$AR$2:$AR$193,1) -> 4 | AN13: =MAX(0,AL13-'Live Calc'!$H$21)^'Live Calc'!$E$21 -> 295.09864 | AO13: 13 | AP13: =IF(AO13<>_xlfn.MINIFS('Draft Board'!$AO$2:$AO$193,'Draft Board'!$AN$2:$AN$193,"="&AN13),0,IF(_xlfn.MINIFS('Draft Board'!$AN$2:$AN$193,'Draft Board'!$AN$2:$AN$193,">"&AN13)=0,1,IF((_xlfn.MINIFS('Draft Board'!$AN$2:$AN$193,'Draft Board'!$AN$2:$AN$193,">"&AN13)-AN13)/_xlfn.MINIFS('Draft Board'!$AN$2:$AN$193,'Draft Board'!$AN$2:$AN$193,">"&AN13)>0.08,1,0))) -> 0 | AQ13: =_xlfn.MINIFS('Draft Board'!$AN$2:$AN$193,'Draft Board'!$AN$2:$AN$193,">="&AN13,'Draft Board'!$AP$2:$AP$193,1) -> 335.50592 | AR13: =IF(AO13<>_xlfn.MINIFS('Draft Board'!$AO$2:$AO$193,'Draft Board'!$AN$2:$AN$193,"="&AN13),0,IF(OR(AP13=1,IFERROR(FLOOR((AQ13-AN13)/AQ13/0.25,1),0)<>IFERROR(FLOOR((AQ13-_xlfn.MINIFS('Draft Board'!$AN$2:$AN$193,'Draft Board'!$AN$2:$AN$193,">"&AN13))/AQ13/0.25,1),0)),1,0)) -> 0 | AS13: =ROUND(1+AN13*'Live Calc'!$D$28,0) -> 25 | AU13: =IF(AT13<>"",AT13,ROUND(AS13*INDEX('Live Calc'!$G$259:$G$450,MATCH(AM13,'Live Calc'!$A$259:$A$450,0))*'Live Calc'!$J$543,0)) -> 25 | AW13: Dallas Goedert | AX13: PHI | AY13: 99.98 | AZ13: 130.546 | BA13: 158.972 | BB13: =CHOOSE(MATCH(Setup!$B$7,{"STD","Half-PPR","PPR"},0),AY13,AZ13,BA13) -> 130.546 | BC13: =COUNTIFS('Draft Board'!$BD$2:$BD$87,">="&BD13,'Draft Board'!$BH$2:$BH$87,1) -> 6 | BD13: =MAX(0,BB13-'Live Calc'!$H$22)^'Live Calc'!$E$22 -> 27.296 | BE13: 13 | BF13: =IF(BE13<>_xlfn.MINIFS('Draft Board'!$BE$2:$BE$87,'Draft Board'!$BD$2:$BD$87,"="&BD13),0,IF(_xlfn.MINIFS('Draft Board'!$BD$2:$BD$87,'Draft Board'!$BD$2:$BD$87,">"&BD13)=0,1,IF((_xlfn.MINIFS('Draft Board'!$BD$2:$BD$87,'Draft Board'!$BD$2:$BD$87,">"&BD13)-BD13)/_xlfn.MINIFS('Draft Board'!$BD$2:$BD$87,'Draft Board'!$BD$2:$BD$87,">"&BD13)>0.08,1,0))) -> 1 | BG13: =_xlfn.MINIFS('Draft Board'!$BD$2:$BD$87,'Draft Board'!$BD$2:$BD$87,">="&BD13,'Draft Board'!$BF$2:$BF$87,1) -> 27.296 | BH13: =IF(BE13<>_xlfn.MINIFS('Draft Board'!$BE$2:$BE$87,'Draft Board'!$BD$2:$BD$87,"="&BD13),0,IF(OR(BF13=1,IFERROR(FLOOR((BG13-BD13)/BG13/0.25,1),0)<>IFERROR(FLOOR((BG13-_xlfn.MINIFS('Draft Board'!$BD$2:$BD$87,'Draft Board'!$BD$2:$BD$87,">"&BD13))/BG13/0.25,1),0)),1,0)) -> 1 | BI13: =ROUND(1+BD13*'Live Calc'!$D$29,0) -> 8 | BK13: =IF(BJ13<>"",BJ13,ROUND(BI13*INDEX('Live Calc'!$G$454:$G$539,MATCH(BC13,'Live Calc'!$A$454:$A$539,0))*'Live Calc'!$J$543,0)) -> 8
... A61: Tyson Bagent | B61: CHI | C61: 13.07 | D61: 13.07 | E61: 13.07 | F61: =CHOOSE(MATCH(Setup!$B$7,{"STD","Half-PPR","PPR"},0),C61,D61,E61) -> 13.07 | G61: =COUNTIFS('Draft Board'!$H$2:$H$61,">="&H61,'Draft Board'!$L$2:$L$61,1) -> 11 | H61: =MAX(0,F61-'Live Calc'!$H$19)^'Live Calc'!$E$19 -> 0 | I61: 61 | J61: =IF(I61<>_xlfn.MINIFS('Draft Board'!$I$2:$I$61,'Draft Board'!$H$2:$H$61,"="&H61),0,IF(_xlfn.MINIFS('Draft Board'!$H$2:$H$61,'Draft Board'!$H$2:$H$61,">"&H61)=0,1,IF((_xlfn.MINIFS('Draft Board'!$H$2:$H$61,'Draft Board'!$H$2:$H$61,">"&H61)-H61)/_xlfn.MINIFS('Draft Board'!$H$2:$H$61,'Draft Board'!$H$2:$H$61,">"&H61)>0.08,1,0))) -> 0 | K61: =_xlfn.MINIFS('Draft Board'!$H$2:$H$61,'Draft Board'!$H$2:$H$61,">="&H61,'Draft Board'!$J$2:$J$61,1) -> 0 | L61: =IF(I61<>_xlfn.MINIFS('Draft Board'!$I$2:$I$61,'Draft Board'!$H$2:$H$61,"="&H61),0,IF(OR(J61=1,IFERROR(FLOOR((K61-H61)/K61/0.25,1),0)<>IFERROR(FLOOR((K61-_xlfn.MINIFS('Draft Board'!$H$2:$H$61,'Draft Board'!$H$2:$H$61,">"&H61))/K61/0.25,1),0)),1,0)) -> 0 | M61: =ROUND(1+H61*'Live Calc'!$D$26,0) -> 1 | O61: =IF(N61<>"",N61,ROUND(M61*INDEX('Live Calc'!$G$33:$G$92,MATCH(G61,'Live Calc'!$A$33:$A$92,0))*'Live Calc'!$J$543,0)) -> 1 | Q61: Emmett Johnson | R61: KC | S61: 46.98 | T61: 54.548 | U61: 62.15 | V61: =CHOOSE(MATCH(Setup!$B$7,{"STD","Half-PPR","PPR"},0),S61,T61,U61) -> 54.548 | W61: =COUNTIFS('Draft Board'!$X$2:$X$161,">="&X61,'Draft Board'!$AB$2:$AB$161,1) -> 14 | X61: =MAX(0,V61-'Live Calc'!$H$20)^'Live Calc'!$E$20 -> 0 | Y61: 61 | Z61: =IF(Y61<>_xlfn.MINIFS('Draft Board'!$Y$2:$Y$161,'Draft Board'!$X$2:$X$161,"="&X61),0,IF(_xlfn.MINIFS('Draft Board'!$X$2:$X$161,'Draft Board'!$X$2:$X$161,">"&X61)=0,1,IF((_xlfn.MINIFS('Draft Board'!$X$2:$X$161,'Draft Board'!$X$2:$X$161,">"&X61)-X61)/_xlfn.MINIFS('Draft Board'!$X$2:$X$161,'Draft Board'!$X$2:$X$161,">"&X61)>0.08,1,0))) -> 0 | AA61: =_xlfn.MINIFS('Draft Board'!$X$2:$X$161,'Draft Board'!$X$2:$X$161,">="&X61,'Draft Board'!$Z$2:$Z$161,1) -> 0 | AB61: =IF(Y61<>_xlfn.MINIFS('Draft Board'!$Y$2:$Y$161,'Draft Board'!$X$2:$X$161,"="&X61),0,IF(OR(Z61=1,IFERROR(FLOOR((AA61-X61)/AA61/0.25,1),0)<>IFERROR(FLOOR((AA61-_xlfn.MINIFS('Draft Board'!$X$2:$X$161,'Draft Board'!$X$2:$X$161,">"&X61))/AA61/0.25,1),0)),1,0)) -> 0 | AC61: =ROUND(1+X61*'Live Calc'!$D$27,0) -> 1 | AE61: =IF(AD61<>"",AD61,ROUND(AC61*INDEX('Live Calc'!$G$96:$G$255,MATCH(W61,'Live Calc'!$A$96:$A$255,0))*'Live Calc'!$J$543,0)) -> 1 | AG61: Jauan Jennings | AH61: MIN | AI61: 78.906 | AJ61: 101.24 | AK61: 126.244 | AL61: =CHOOSE(MATCH(Setup!$B$7,{"STD","Half-PPR","PPR"},0),AI61,AJ61,AK61) -> 101.24 | AM61: =COUNTIFS('Draft Board'!$AN$2:$AN$193,">="&AN61,'Draft Board'!$AR$2:$AR$193,1) -> 20 | AN61: =MAX(0,AL61-'Live Calc'!$H$21)^'Live Calc'!$E$21 -> 0 | AO61: 61 | AP61: =IF(AO61<>_xlfn.MINIFS('Draft Board'!$AO$2:$AO$193,'Draft Board'!$AN$2:$AN$193,"="&AN61),0,IF(_xlfn.MINIFS('Draft Board'!$AN$2:$AN$193,'Draft Board'!$AN$2:$AN$193,">"&AN61)=0,1,IF((_xlfn.MINIFS('Draft Board'!$AN$2:$AN$193,'Draft Board'!$AN$2:$AN$193,">"&AN61)-AN61)/_xlfn.MINIFS('Draft Board'!$AN$2:$AN$193,'Draft Board'!$AN$2:$AN$193,">"&AN61)>0.08,1,0))) -> 1 | AQ61: =_xlfn.MINIFS('Draft Board'!$AN$2:$AN$193,'Draft Board'!$AN$2:$AN$193,">="&AN61,'Draft Board'!$AP$2:$AP$193,1) -> 0 | AR61: =IF(AO61<>_xlfn.MINIFS('Draft Board'!$AO$2:$AO$193,'Draft Board'!$AN$2:$AN$193,"="&AN61),0,IF(OR(AP61=1,IFERROR(FLOOR((AQ61-AN61)/AQ61/0.25,1),0)<>IFERROR(FLOOR((AQ61-_xlfn.MINIFS('Draft Board'!$AN$2:$AN$193,'Draft Board'!$AN$2:$AN$193,">"&AN61))/AQ61/0.25,1),0)),1,0)) -> 1 | AS61: =ROUND(1+AN61*'Live Calc'!$D$28,0) -> 1 | AU61: =IF(AT61<>"",AT61,ROUND(AS61*INDEX('Live Calc'!$G$259:$G$450,MATCH(AM61,'Live Calc'!$A$259:$A$450,0))*'Live Calc'!$J$543,0)) -> 1 | AW61: Daniel Bellinger | AX61: TEN | AY61: 25.18 | AZ61: 33.65 | BA61: 42.11 | BB61: =CHOOSE(MATCH(Setup!$B$7,{"STD","Half-PPR","PPR"},0),AY61,AZ61,BA61) -> 33.65 | BC61: =COUNTIFS('Draft Board'!$BD$2:$BD$87,">="&BD61,'Draft Board'!$BH$2:$BH$87,1) -> 15 | BD61: =MAX(0,BB61-'Live Calc'!$H$22)^'Live Calc'!$E$22 -> 0 | BE61: 61 | BF61: =IF(BE61<>_xlfn.MINIFS('Draft Board'!$BE$2:$BE$87,'Draft Board'!$BD$2:$BD$87,"="&BD61),0,IF(_xlfn.MINIFS('Draft Board'!$BD$2:$BD$87,'Draft Board'!$BD$2:$BD$87,">"&BD61)=0,1,IF((_xlfn.MINIFS('Draft Board'!$BD$2:$BD$87,'Draft Board'!$BD$2:$BD$87,">"&BD61)-BD61)/_xlfn.MINIFS('Draft Board'!$BD$2:$BD$87,'Draft Board'!$BD$2:$BD$87,">"&BD61)>0.08,1,0))) -> 0 | BG61: =_xlfn.MINIFS('Draft Board'!$BD$2:$BD$87,'Draft Board'!$BD$2:$BD$87,">="&BD61,'Draft Board'!$BF$2:$BF$87,1) -> 0 | BH61: =IF(BE61<>_xlfn.MINIFS('Draft Board'!$BE$2:$BE$87,'Draft Board'!$BD$2:$BD$87,"="&BD61),0,IF(OR(BF61=1,IFERROR(FLOOR((BG61-BD61)/BG61/0.25,1),0)<>IFERROR(FLOOR((BG61-_xlfn.MINIFS('Draft Board'!$BD$2:$BD$87,'Draft Board'!$BD$2:$BD$87,">"&BD61))/BG61/0.25,1),0)),1,0)) -> 0 | BI61: =ROUND(1+BD61*'Live Calc'!$D$29,0) -> 1 | BK61: =IF(BJ61<>"",BJ61,ROUND(BI61*INDEX('Live Calc'!$G$454:$G$539,MATCH(BC61,'Live Calc'!$A$454:$A$539,0))*'Live Calc'!$J$543,0)) -> 1
Q62: Kimani Vidal | R62: LAC | S62: 47.344 | T62: 53.994 | U62: 59.778 | V62: =CHOOSE(MATCH(Setup!$B$7,{"STD","Half-PPR","PPR"},0),S62,T62,U62) -> 53.994 | W62: =COUNTIFS('Draft Board'!$X$2:$X$161,">="&X62,'Draft Board'!$AB$2:$AB$161,1) -> 14 | X62: =MAX(0,V62-'Live Calc'!$H$20)^'Live Calc'!$E$20 -> 0 | Y62: 62 | Z62: =IF(Y62<>_xlfn.MINIFS('Draft Board'!$Y$2:$Y$161,'Draft Board'!$X$2:$X$161,"="&X62),0,IF(_xlfn.MINIFS('Draft Board'!$X$2:$X$161,'Draft Board'!$X$2:$X$161,">"&X62)=0,1,IF((_xlfn.MINIFS('Draft Board'!$X$2:$X$161,'Draft Board'!$X$2:$X$161,">"&X62)-X62)/_xlfn.MINIFS('Draft Board'!$X$2:$X$161,'Draft Board'!$X$2:$X$161,">"&X62)>0.08,1,0))) -> 0 | AA62: =_xlfn.MINIFS('Draft Board'!$X$2:$X$161,'Draft Board'!$X$2:$X$161,">="&X62,'Draft Board'!$Z$2:$Z$161,1) -> 0 | AB62: =IF(Y62<>_xlfn.MINIFS('Draft Board'!$Y$2:$Y$161,'Draft Board'!$X$2:$X$161,"="&X62),0,IF(OR(Z62=1,IFERROR(FLOOR((AA62-X62)/AA62/0.25,1),0)<>IFERROR(FLOOR((AA62-_xlfn.MINIFS('Draft Board'!$X$2:$X$161,'Draft Board'!$X$2:$X$161,">"&X62))/AA62/0.25,1),0)),1,0)) -> 0 | AC62: =ROUND(1+X62*'Live Calc'!$D$27,0) -> 1 | AE62: =IF(AD62<>"",AD62,ROUND(AC62*INDEX('Live Calc'!$G$96:$G$255,MATCH(W62,'Live Calc'!$A$96:$A$255,0))*'Live Calc'!$J$543,0)) -> 1 | AG62: Omar Cooper Jr. | AH62: NYJ | AI62: 78.582 | AJ62: 101.01 | AK62: 122.734 | AL62: =CHOOSE(MATCH(Setup!$B$7,{"STD","Half-PPR","PPR"},0),AI62,AJ62,AK62) -> 101.01 | AM62: =COUNTIFS('Draft Board'!$AN$2:$AN$193,">="&AN62,'Draft Board'!$AR$2:$AR$193,1) -> 20 | AN62: =MAX(0,AL62-'Live Calc'!$H$21)^'Live Calc'!$E$21 -> 0 | AO62: 62 | AP62: =IF(AO62<>_xlfn.MINIFS('Draft Board'!$AO$2:$AO$193,'Draft Board'!$AN$2:$AN$193,"="&AN62),0,IF(_xlfn.MINIFS('Draft Board'!$AN$2:$AN$193,'Draft Board'!$AN$2:$AN$193,">"&AN62)=0,1,IF((_xlfn.MINIFS('Draft Board'!$AN$2:$AN$193,'Draft Board'!$AN$2:$AN$193,">"&AN62)-AN62)/_xlfn.MINIFS('Draft Board'!$AN$2:$AN$193,'Draft Board'!$AN$2:$AN$193,">"&AN62)>0.08,1,0))) -> 0 | AQ62: =_xlfn.MINIFS('Draft Board'!$AN$2:$AN$193,'Draft Board'!$AN$2:$AN$193,">="&AN62,'Draft Board'!$AP$2:$AP$193,1) -> 0 | AR62: =IF(AO62<>_xlfn.MINIFS('Draft Board'!$AO$2:$AO$193,'Draft Board'!$AN$2:$AN$193,"="&AN62),0,IF(OR(AP62=1,IFERROR(FLOOR((AQ62-AN62)/AQ62/0.25,1),0)<>IFERROR(FLOOR((AQ62-_xlfn.MINIFS('Draft Board'!$AN$2:$AN$193,'Draft Board'!$AN$2:$AN$193,">"&AN62))/AQ62/0.25,1),0)),1,0)) -> 0 | AS62: =ROUND(1+AN62*'Live Calc'!$D$28,0) -> 1 | AU62: =IF(AT62<>"",AT62,ROUND(AS62*INDEX('Live Calc'!$G$259:$G$450,MATCH(AM62,'Live Calc'!$A$259:$A$450,0))*'Live Calc'!$J$543,0)) -> 1 | AW62: Elijah Higgins | AX62: ARI | AY62: 23.31 | AZ62: 33.16 | BA62: 43.01 | BB62: =CHOOSE(MATCH(Setup!$B$7,{"STD","Half-PPR","PPR"},0),AY62,AZ62,BA62) -> 33.16 | BC62: =COUNTIFS('Draft Board'!$BD$2:$BD$87,">="&BD62,'Draft Board'!$BH$2:$BH$87,1) -> 15 | BD62: =MAX(0,BB62-'Live Calc'!$H$22)^'Live Calc'!$E$22 -> 0 | BE62: 62 | BF62: =IF(BE62<>_xlfn.MINIFS('Draft Board'!$BE$2:$BE$87,'Draft Board'!$BD$2:$BD$87,"="&BD62),0,IF(_xlfn.MINIFS('Draft Board'!$BD$2:$BD$87,'Draft Board'!$BD$2:$BD$87,">"&BD62)=0,1,IF((_xlfn.MINIFS('Draft Board'!$BD$2:$BD$87,'Draft Board'!$BD$2:$BD$87,">"&BD62)-BD62)/_xlfn.MINIFS('Draft Board'!$BD$2:$BD$87,'Draft Board'!$BD$2:$BD$87,">"&BD62)>0.08,1,0))) -> 0 | BG62: =_xlfn.MINIFS('Draft Board'!$BD$2:$BD$87,'Draft Board'!$BD$2:$BD$87,">="&BD62,'Draft Board'!$BF$2:$BF$87,1) -> 0 | BH62: =IF(BE62<>_xlfn.MINIFS('Draft Board'!$BE$2:$BE$87,'Draft Board'!$BD$2:$BD$87,"="&BD62),0,IF(OR(BF62=1,IFERROR(FLOOR((BG62-BD62)/BG62/0.25,1),0)<>IFERROR(FLOOR((BG62-_xlfn.MINIFS('Draft Board'!$BD$2:$BD$87,'Draft Board'!$BD$2:$BD$87,">"&BD62))/BG62/0.25,1),0)),1,0)) -> 0 | BI62: =ROUND(1+BD62*'Live Calc'!$D$29,0) -> 1 | BK62: =IF(BJ62<>"",BJ62,ROUND(BI62*INDEX('Live Calc'!$G$454:$G$539,MATCH(BC62,'Live Calc'!$A$454:$A$539,0))*'Live Calc'!$J$543,0)) -> 1
Q63: MarShawn Lloyd | R63: GB | S63: 47.152 | T63: 52.604 | U63: 58.052 | V63: =CHOOSE(MATCH(Setup!$B$7,{"STD","Half-PPR","PPR"},0),S63,T63,U63) -> 52.604 | W63: =COUNTIFS('Draft Board'!$X$2:$X$161,">="&X63,'Draft Board'!$AB$2:$AB$161,1) -> 14 | X63: =MAX(0,V63-'Live Calc'!$H$20)^'Live Calc'!$E$20 -> 0 | Y63: 63 | Z63: =IF(Y63<>_xlfn.MINIFS('Draft Board'!$Y$2:$Y$161,'Draft Board'!$X$2:$X$161,"="&X63),0,IF(_xlfn.MINIFS('Draft Board'!$X$2:$X$161,'Draft Board'!$X$2:$X$161,">"&X63)=0,1,IF((_xlfn.MINIFS('Draft Board'!$X$2:$X$161,'Draft Board'!$X$2:$X$161,">"&X63)-X63)/_xlfn.MINIFS('Draft Board'!$X$2:$X$161,'Draft Board'!$X$2:$X$161,">"&X63)>0.08,1,0))) -> 0 | AA63: =_xlfn.MINIFS('Draft Board'!$X$2:$X$161,'Draft Board'!$X$2:$X$161,">="&X63,'Draft Board'!$Z$2:$Z$161,1) -> 0 | AB63: =IF(Y63<>_xlfn.MINIFS('Draft Board'!$Y$2:$Y$161,'Draft Board'!$X$2:$X$161,"="&X63),0,IF(OR(Z63=1,IFERROR(FLOOR((AA63-X63)/AA63/0.25,1),0)<>IFERROR(FLOOR((AA63-_xlfn.MINIFS('Draft Board'!$X$2:$X$161,'Draft Board'!$X$2:$X$161,">"&X63))/AA63/0.25,1),0)),1,0)) -> 0 | AC63: =ROUND(1+X63*'Live Calc'!$D$27,0) -> 1 | AE63: =IF(AD63<>"",AD63,ROUND(AC63*INDEX('Live Calc'!$G$96:$G$255,MATCH(W63,'Live Calc'!$A$96:$A$255,0))*'Live Calc'!$J$543,0)) -> 1 | AG63: Jerry Jeudy | AH63: CLE | AI63: 77.75 | AJ63: 100.522 | AK63: 123.296 | AL63: =CHOOSE(MATCH(Setup!$B$7,{"STD","Half-PPR","PPR"},0),AI63,AJ63,AK63) -> 100.522 | AM63: =COUNTIFS('Draft Board'!$AN$2:$AN$193,">="&AN63,'Draft Board'!$AR$2:$AR$193,1) -> 20 | AN63: =MAX(0,AL63-'Live Calc'!$H$21)^'Live Calc'!$E$21 -> 0 | AO63: 63 | AP63: =IF(AO63<>_xlfn.MINIFS('Draft Board'!$AO$2:$AO$193,'Draft Board'!$AN$2:$AN$193,"="&AN63),0,IF(_xlfn.MINIFS('Draft Board'!$AN$2:$AN$193,'Draft Board'!$AN$2:$AN$193,">"&AN63)=0,1,IF((_xlfn.MINIFS('Draft Board'!$AN$2:$AN$193,'Draft Board'!$AN$2:$AN$193,">"&AN63)-AN63)/_xlfn.MINIFS('Draft Board'!$AN$2:$AN$193,'Draft Board'!$AN$2:$AN$193,">"&AN63)>0.08,1,0))) -> 0 | AQ63: =_xlfn.MINIFS('Draft Board'!$AN$2:$AN$193,'Draft Board'!$AN$2:$AN$193,">="&AN63,'Draft Board'!$AP$2:$AP$193,1) -> 0 | AR63: =IF(AO63<>_xlfn.MINIFS('Draft Board'!$AO$2:$AO$193,'Draft Board'!$AN$2:$AN$193,"="&AN63),0,IF(OR(AP63=1,IFERROR(FLOOR((AQ63-AN63)/AQ63/0.25,1),0)<>IFERROR(FLOOR((AQ63-_xlfn.MINIFS('Draft Board'!$AN$2:$AN$193,'Draft Board'!$AN$2:$AN$193,">"&AN63))/AQ63/0.25,1),0)),1,0)) -> 0 | AS63: =ROUND(1+AN63*'Live Calc'!$D$28,0) -> 1 | AU63: =IF(AT63<>"",AT63,ROUND(AS63*INDEX('Live Calc'!$G$259:$G$450,MATCH(AM63,'Live Calc'!$A$259:$A$450,0))*'Live Calc'!$J$543,0)) -> 1 | AW63: Will Kacmarek | AX63: MIA | AY63: 23.98 | AZ63: 33.11 | BA63: 42.25 | BB63: =CHOOSE(MATCH(Setup!$B$7,{"STD","Half-PPR","PPR"},0),AY63,AZ63,BA63) -> 33.11 | BC63: =COUNTIFS('Draft Board'!$BD$2:$BD$87,">="&BD63,'Draft Board'!$BH$2:$BH$87,1) -> 15 | BD63: =MAX(0,BB63-'Live Calc'!$H$22)^'Live Calc'!$E$22 -> 0 | BE63: 63 | BF63: =IF(BE63<>_xlfn.MINIFS('Draft Board'!$BE$2:$BE$87,'Draft Board'!$BD$2:$BD$87,"="&BD63),0,IF(_xlfn.MINIFS('Draft Board'!$BD$2:$BD$87,'Draft Board'!$BD$2:$BD$87,">"&BD63)=0,1,IF((_xlfn.MINIFS('Draft Board'!$BD$2:$BD$87,'Draft Board'!$BD$2:$BD$87,">"&BD63)-BD63)/_xlfn.MINIFS('Draft Board'!$BD$2:$BD$87,'Draft Board'!$BD$2:$BD$87,">"&BD63)>0.08,1,0))) -> 0 | BG63: =_xlfn.MINIFS('Draft Board'!$BD$2:$BD$87,'Draft Board'!$BD$2:$BD$87,">="&BD63,'Draft Board'!$BF$2:$BF$87,1) -> 0 | BH63: =IF(BE63<>_xlfn.MINIFS('Draft Board'!$BE$2:$BE$87,'Draft Board'!$BD$2:$BD$87,"="&BD63),0,IF(OR(BF63=1,IFERROR(FLOOR((BG63-BD63)/BG63/0.25,1),0)<>IFERROR(FLOOR((BG63-_xlfn.MINIFS('Draft Board'!$BD$2:$BD$87,'Draft Board'!$BD$2:$BD$87,">"&BD63))/BG63/0.25,1),0)),1,0)) -> 0 | BI63: =ROUND(1+BD63*'Live Calc'!$D$29,0) -> 1 | BK63: =IF(BJ63<>"",BJ63,ROUND(BI63*INDEX('Live Calc'!$G$454:$G$539,MATCH(BC63,'Live Calc'!$A$454:$A$539,0))*'Live Calc'!$J$543,0)) -> 1
Q64: Ray Davis | R64: BUF | S64: 47.336 | T64: 52.552 | U64: 57.696 | V64: =CHOOSE(MATCH(Setup!$B$7,{"STD","Half-PPR","PPR"},0),S64,T64,U64) -> 52.552 | W64: =COUNTIFS('Draft Board'!$X$2:$X$161,">="&X64,'Draft Board'!$AB$2:$AB$161,1) -> 14 | X64: =MAX(0,V64-'Live Calc'!$H$20)^'Live Calc'!$E$20 -> 0 | Y64: 64 | Z64: =IF(Y64<>_xlfn.MINIFS('Draft Board'!$Y$2:$Y$161,'Draft Board'!$X$2:$X$161,"="&X64),0,IF(_xlfn.MINIFS('Draft Board'!$X$2:$X$161,'Draft Board'!$X$2:$X$161,">"&X64)=0,1,IF((_xlfn.MINIFS('Draft Board'!$X$2:$X$161,'Draft Board'!$X$2:$X$161,">"&X64)-X64)/_xlfn.MINIFS('Draft Board'!$X$2:$X$161,'Draft Board'!$X$2:$X$161,">"&X64)>0.08,1,0))) -> 0 | AA64: =_xlfn.MINIFS('Draft Board'!$X$2:$X$161,'Draft Board'!$X$2:$X$161,">="&X64,'Draft Board'!$Z$2:$Z$161,1) -> 0 | AB64: =IF(Y64<>_xlfn.MINIFS('Draft Board'!$Y$2:$Y$161,'Draft Board'!$X$2:$X$161,"="&X64),0,IF(OR(Z64=1,IFERROR(FLOOR((AA64-X64)/AA64/0.25,1),0)<>IFERROR(FLOOR((AA64-_xlfn.MINIFS('Draft Board'!$X$2:$X$161,'Draft Board'!$X$2:$X$161,">"&X64))/AA64/0.25,1),0)),1,0)) -> 0 | AC64: =ROUND(1+X64*'Live Calc'!$D$27,0) -> 1 | AE64: =IF(AD64<>"",AD64,ROUND(AC64*INDEX('Live Calc'!$G$96:$G$255,MATCH(W64,'Live Calc'!$A$96:$A$255,0))*'Live Calc'!$J$543,0)) -> 1 | AG64: Jalen Nailor | AH64: LV | AI64: 77.02 | AJ64: 99.098 | AK64: 120.31 | AL64: =CHOOSE(MATCH(Setup!$B$7,{"STD","Half-PPR","PPR"},0),AI64,AJ64,AK64) -> 99.098 | AM64: =COUNTIFS('Draft Board'!$AN$2:$AN$193,">="&AN64,'Draft Board'!$AR$2:$AR$193,1) -> 20 | AN64: =MAX(0,AL64-'Live Calc'!$H$21)^'Live Calc'!$E$21 -> 0 | AO64: 64 | AP64: =IF(AO64<>_xlfn.MINIFS('Draft Board'!$AO$2:$AO$193,'Draft Board'!$AN$2:$AN$193,"="&AN64),0,IF(_xlfn.MINIFS('Draft Board'!$AN$2:$AN$193,'Draft Board'!$AN$2:$AN$193,">"&AN64)=0,1,IF((_xlfn.MINIFS('Draft Board'!$AN$2:$AN$193,'Draft Board'!$AN$2:$AN$193,">"&AN64)-AN64)/_xlfn.MINIFS('Draft Board'!$AN$2:$AN$193,'Draft Board'!$AN$2:$AN$193,">"&AN64)>0.08,1,0))) -> 0 | AQ64: =_xlfn.MINIFS('Draft Board'!$AN$2:$AN$193,'Draft Board'!$AN$2:$AN$193,">="&AN64,'Draft Board'!$AP$2:$AP$193,1) -> 0 | AR64: =IF(AO64<>_xlfn.MINIFS('Draft Board'!$AO$2:$AO$193,'Draft Board'!$AN$2:$AN$193,"="&AN64),0,IF(OR(AP64=1,IFERROR(FLOOR((AQ64-AN64)/AQ64/0.25,1),0)<>IFERROR(FLOOR((AQ64-_xlfn.MINIFS('Draft Board'!$AN$2:$AN$193,'Draft Board'!$AN$2:$AN$193,">"&AN64))/AQ64/0.25,1),0)),1,0)) -> 0 | AS64: =ROUND(1+AN64*'Live Calc'!$D$28,0) -> 1 | AU64: =IF(AT64<>"",AT64,ROUND(AS64*INDEX('Live Calc'!$G$259:$G$450,MATCH(AM64,'Live Calc'!$A$259:$A$450,0))*'Live Calc'!$J$543,0)) -> 1 | AW64: Adam Trautman | AX64: DEN | AY64: 24.38 | AZ64: 32.9 | BA64: 41.41 | BB64: =CHOOSE(MATCH(Setup!$B$7,{"STD","Half-PPR","PPR"},0),AY64,AZ64,BA64) -> 32.9 | BC64: =COUNTIFS('Draft Board'!$BD$2:$BD$87,">="&BD64,'Draft Board'!$BH$2:$BH$87,1) -> 15 | BD64: =MAX(0,BB64-'Live Calc'!$H$22)^'Live Calc'!$E$22 -> 0 | BE64: 64 | BF64: =IF(BE64<>_xlfn.MINIFS('Draft Board'!$BE$2:$BE$87,'Draft Board'!$BD$2:$BD$87,"="&BD64),0,IF(_xlfn.MINIFS('Draft Board'!$BD$2:$BD$87,'Draft Board'!$BD$2:$BD$87,">"&BD64)=0,1,IF((_xlfn.MINIFS('Draft Board'!$BD$2:$BD$87,'Draft Board'!$BD$2:$BD$87,">"&BD64)-BD64)/_xlfn.MINIFS('Draft Board'!$BD$2:$BD$87,'Draft Board'!$BD$2:$BD$87,">"&BD64)>0.08,1,0))) -> 0 | BG64: =_xlfn.MINIFS('Draft Board'!$BD$2:$BD$87,'Draft Board'!$BD$2:$BD$87,">="&BD64,'Draft Board'!$BF$2:$BF$87,1) -> 0 | BH64: =IF(BE64<>_xlfn.MINIFS('Draft Board'!$BE$2:$BE$87,'Draft Board'!$BD$2:$BD$87,"="&BD64),0,IF(OR(BF64=1,IFERROR(FLOOR((BG64-BD64)/BG64/0.25,1),0)<>IFERROR(FLOOR((BG64-_xlfn.MINIFS('Draft Board'!$BD$2:$BD$87,'Draft Board'!$BD$2:$BD$87,">"&BD64))/BG64/0.25,1),0)),1,0)) -> 0 | BI64: =ROUND(1+BD64*'Live Calc'!$D$29,0) -> 1 | BK64: =IF(BJ64<>"",BJ64,ROUND(BI64*INDEX('Live Calc'!$G$454:$G$539,MATCH(BC64,'Live Calc'!$A$454:$A$539,0))*'Live Calc'!$J$543,0)) -> 1
Q65: Sean Tucker | R65: TB | S65: 49.204 | T65: 52.48 | U65: 55.41 | V65: =CHOOSE(MATCH(Setup!$B$7,{"STD","Half-PPR","PPR"},0),S65,T65,U65) -> 52.48 | W65: =COUNTIFS('Draft Board'!$X$2:$X$161,">="&X65,'Draft Board'!$AB$2:$AB$161,1) -> 14 | X65: =MAX(0,V65-'Live Calc'!$H$20)^'Live Calc'!$E$20 -> 0 | Y65: 65 | Z65: =IF(Y65<>_xlfn.MINIFS('Draft Board'!$Y$2:$Y$161,'Draft Board'!$X$2:$X$161,"="&X65),0,IF(_xlfn.MINIFS('Draft Board'!$X$2:$X$161,'Draft Board'!$X$2:$X$161,">"&X65)=0,1,IF((_xlfn.MINIFS('Draft Board'!$X$2:$X$161,'Draft Board'!$X$2:$X$161,">"&X65)-X65)/_xlfn.MINIFS('Draft Board'!$X$2:$X$161,'Draft Board'!$X$2:$X$161,">"&X65)>0.08,1,0))) -> 0 | AA65: =_xlfn.MINIFS('Draft Board'!$X$2:$X$161,'Draft Board'!$X$2:$X$161,">="&X65,'Draft Board'!$Z$2:$Z$161,1) -> 0 | AB65: =IF(Y65<>_xlfn.MINIFS('Draft Board'!$Y$2:$Y$161,'Draft Board'!$X$2:$X$161,"="&X65),0,IF(OR(Z65=1,IFERROR(FLOOR((AA65-X65)/AA65/0.25,1),0)<>IFERROR(FLOOR((AA65-_xlfn.MINIFS('Draft Board'!$X$2:$X$161,'Draft Board'!$X$2:$X$161,">"&X65))/AA65/0.25,1),0)),1,0)) -> 0 | AC65: =ROUND(1+X65*'Live Calc'!$D$27,0) -> 1 | AE65: =IF(AD65<>"",AD65,ROUND(AC65*INDEX('Live Calc'!$G$96:$G$255,MATCH(W65,'Live Calc'!$A$96:$A$255,0))*'Live Calc'!$J$543,0)) -> 1 | AG65: Denzel Boston | AH65: CLE | AI65: 76.438 | AJ65: 98.552 | AK65: 125.324 | AL65: =CHOOSE(MATCH(Setup!$B$7,{"STD","Half-PPR","PPR"},0),AI65,AJ65,AK65) -> 98.552 | AM65: =COUNTIFS('Draft Board'!$AN$2:$AN$193,">="&AN65,'Draft Board'!$AR$2:$AR$193,1) -> 20 | AN65: =MAX(0,AL65-'Live Calc'!$H$21)^'Live Calc'!$E$21 -> 0 | AO65: 65 | AP65: =IF(AO65<>_xlfn.MINIFS('Draft Board'!$AO$2:$AO$193,'Draft Board'!$AN$2:$AN$193,"="&AN65),0,IF(_xlfn.MINIFS('Draft Board'!$AN$2:$AN$193,'Draft Board'!$AN$2:$AN$193,">"&AN65)=0,1,IF((_xlfn.MINIFS('Draft Board'!$AN$2:$AN$193,'Draft Board'!$AN$2:$AN$193,">"&AN65)-AN65)/_xlfn.MINIFS('Draft Board'!$AN$2:$AN$193,'Draft Board'!$AN$2:$AN$193,">"&AN65)>0.08,1,0))) -> 0 | AQ65: =_xlfn.MINIFS('Draft Board'!$AN$2:$AN$193,'Draft Board'!$AN$2:$AN$193,">="&AN65,'Draft Board'!$AP$2:$AP$193,1) -> 0 | AR65: =IF(AO65<>_xlfn.MINIFS('Draft Board'!$AO$2:$AO$193,'Draft Board'!$AN$2:$AN$193,"="&AN65),0,IF(OR(AP65=1,IFERROR(FLOOR((AQ65-AN65)/AQ65/0.25,1),0)<>IFERROR(FLOOR((AQ65-_xlfn.MINIFS('Draft Board'!$AN$2:$AN$193,'Draft Board'!$AN$2:$AN$193,">"&AN65))/AQ65/0.25,1),0)),1,0)) -> 0 | AS65: =ROUND(1+AN65*'Live Calc'!$D$28,0) -> 1 | AU65: =IF(AT65<>"",AT65,ROUND(AS65*INDEX('Live Calc'!$G$259:$G$450,MATCH(AM65,'Live Calc'!$A$259:$A$450,0))*'Live Calc'!$J$543,0)) -> 1 | AW65: Oscar Delp | AX65: NO | AY65: 25.01 | AZ65: 32.316 | BA65: 38.264 | BB65: =CHOOSE(MATCH(Setup!$B$7,{"STD","Half-PPR","PPR"},0),AY65,AZ65,BA65) -> 32.316 | BC65: =COUNTIFS('Draft Board'!$BD$2:$BD$87,">="&BD65,'Draft Board'!$BH$2:$BH$87,1) -> 15 | BD65: =MAX(0,BB65-'Live Calc'!$H$22)^'Live Calc'!$E$22 -> 0 | BE65: 65 | BF65: =IF(BE65<>_xlfn.MINIFS('Draft Board'!$BE$2:$BE$87,'Draft Board'!$BD$2:$BD$87,"="&BD65),0,IF(_xlfn.MINIFS('Draft Board'!$BD$2:$BD$87,'Draft Board'!$BD$2:$BD$87,">"&BD65)=0,1,IF((_xlfn.MINIFS('Draft Board'!$BD$2:$BD$87,'Draft Board'!$BD$2:$BD$87,">"&BD65)-BD65)/_xlfn.MINIFS('Draft Board'!$BD$2:$BD$87,'Draft Board'!$BD$2:$BD$87,">"&BD65)>0.08,1,0))) -> 0 | BG65: =_xlfn.MINIFS('Draft Board'!$BD$2:$BD$87,'Draft Board'!$BD$2:$BD$87,">="&BD65,'Draft Board'!$BF$2:$BF$87,1) -> 0 | BH65: =IF(BE65<>_xlfn.MINIFS('Draft Board'!$BE$2:$BE$87,'Draft Board'!$BD$2:$BD$87,"="&BD65),0,IF(OR(BF65=1,IFERROR(FLOOR((BG65-BD65)/BG65/0.25,1),0)<>IFERROR(FLOOR((BG65-_xlfn.MINIFS('Draft Board'!$BD$2:$BD$87,'Draft Board'!$BD$2:$BD$87,">"&BD65))/BG65/0.25,1),0)),1,0)) -> 0 | BI65: =ROUND(1+BD65*'Live Calc'!$D$29,0) -> 1 | BK65: =IF(BJ65<>"",BJ65,ROUND(BI65*INDEX('Live Calc'!$G$454:$G$539,MATCH(BC65,'Live Calc'!$A$454:$A$539,0))*'Live Calc'!$J$543,0)) -> 1
Q66: Jordan James | R66: SF | S66: 46.7 | T66: 51.21 | U66: 57.224 | V66: =CHOOSE(MATCH(Setup!$B$7,{"STD","Half-PPR","PPR"},0),S66,T66,U66) -> 51.21 | W66: =COUNTIFS('Draft Board'!$X$2:$X$161,">="&X66,'Draft Board'!$AB$2:$AB$161,1) -> 14 | X66: =MAX(0,V66-'Live Calc'!$H$20)^'Live Calc'!$E$20 -> 0 | Y66: 66 | Z66: =IF(Y66<>_xlfn.MINIFS('Draft Board'!$Y$2:$Y$161,'Draft Board'!$X$2:$X$161,"="&X66),0,IF(_xlfn.MINIFS('Draft Board'!$X$2:$X$161,'Draft Board'!$X$2:$X$161,">"&X66)=0,1,IF((_xlfn.MINIFS('Draft Board'!$X$2:$X$161,'Draft Board'!$X$2:$X$161,">"&X66)-X66)/_xlfn.MINIFS('Draft Board'!$X$2:$X$161,'Draft Board'!$X$2:$X$161,">"&X66)>0.08,1,0))) -> 0 | AA66: =_xlfn.MINIFS('Draft Board'!$X$2:$X$161,'Draft Board'!$X$2:$X$161,">="&X66,'Draft Board'!$Z$2:$Z$161,1) -> 0 | AB66: =IF(Y66<>_xlfn.MINIFS('Draft Board'!$Y$2:$Y$161,'Draft Board'!$X$2:$X$161,"="&X66),0,IF(OR(Z66=1,IFERROR(FLOOR((AA66-X66)/AA66/0.25,1),0)<>IFERROR(FLOOR((AA66-_xlfn.MINIFS('Draft Board'!$X$2:$X$161,'Draft Board'!$X$2:$X$161,">"&X66))/AA66/0.25,1),0)),1,0)) -> 0 | AC66: =ROUND(1+X66*'Live Calc'!$D$27,0) -> 1 | AE66: =IF(AD66<>"",AD66,ROUND(AC66*INDEX('Live Calc'!$G$96:$G$255,MATCH(W66,'Live Calc'!$A$96:$A$255,0))*'Live Calc'!$J$543,0)) -> 1 | AG66: Deebo Samuel | AH66: FA | AI66: 75.288 | AJ66: 95.148 | AK66: 114.83 | AL66: =CHOOSE(MATCH(Setup!$B$7,{"STD","Half-PPR","PPR"},0),AI66,AJ66,AK66) -> 95.148 | AM66: =COUNTIFS('Draft Board'!$AN$2:$AN$193,">="&AN66,'Draft Board'!$AR$2:$AR$193,1) -> 20 | AN66: =MAX(0,AL66-'Live Calc'!$H$21)^'Live Calc'!$E$21 -> 0 | AO66: 66 | AP66: =IF(AO66<>_xlfn.MINIFS('Draft Board'!$AO$2:$AO$193,'Draft Board'!$AN$2:$AN$193,"="&AN66),0,IF(_xlfn.MINIFS('Draft Board'!$AN$2:$AN$193,'Draft Board'!$AN$2:$AN$193,">"&AN66)=0,1,IF((_xlfn.MINIFS('Draft Board'!$AN$2:$AN$193,'Draft Board'!$AN$2:$AN$193,">"&AN66)-AN66)/_xlfn.MINIFS('Draft Board'!$AN$2:$AN$193,'Draft Board'!$AN$2:$AN$193,">"&AN66)>0.08,1,0))) -> 0 | AQ66: =_xlfn.MINIFS('Draft Board'!$AN$2:$AN$193,'Draft Board'!$AN$2:$AN$193,">="&AN66,'Draft Board'!$AP$2:$AP$193,1) -> 0 | AR66: =IF(AO66<>_xlfn.MINIFS('Draft Board'!$AO$2:$AO$193,'Draft Board'!$AN$2:$AN$193,"="&AN66),0,IF(OR(AP66=1,IFERROR(FLOOR((AQ66-AN66)/AQ66/0.25,1),0)<>IFERROR(FLOOR((AQ66-_xlfn.MINIFS('Draft Board'!$AN$2:$AN$193,'Draft Board'!$AN$2:$AN$193,">"&AN66))/AQ66/0.25,1),0)),1,0)) -> 0 | AS66: =ROUND(1+AN66*'Live Calc'!$D$28,0) -> 1 | AU66: =IF(AT66<>"",AT66,ROUND(AS66*INDEX('Live Calc'!$G$259:$G$450,MATCH(AM66,'Live Calc'!$A$259:$A$450,0))*'Live Calc'!$J$543,0)) -> 1 | AW66: Ben Sinnott | AX66: WAS | AY66: 23.344 | AZ66: 31.754 | BA66: 40.126 | BB66: =CHOOSE(MATCH(Setup!$B$7,{"STD","Half-PPR","PPR"},0),AY66,AZ66,BA66) -> 31.754 | BC66: =COUNTIFS('Draft Board'!$BD$2:$BD$87,">="&BD66,'Draft Board'!$BH$2:$BH$87,1) -> 15 | BD66: =MAX(0,BB66-'Live Calc'!$H$22)^'Live Calc'!$E$22 -> 0 | BE66: 66 | BF66: =IF(BE66<>_xlfn.MINIFS('Draft Board'!$BE$2:$BE$87,'Draft Board'!$BD$2:$BD$87,"="&BD66),0,IF(_xlfn.MINIFS('Draft Board'!$BD$2:$BD$87,'Draft Board'!$BD$2:$BD$87,">"&BD66)=0,1,IF((_xlfn.MINIFS('Draft Board'!$BD$2:$BD$87,'Draft Board'!$BD$2:$BD$87,">"&BD66)-BD66)/_xlfn.MINIFS('Draft Board'!$BD$2:$BD$87,'Draft Board'!$BD$2:$BD$87,">"&BD66)>0.08,1,0))) -> 0 | BG66: =_xlfn.MINIFS('Draft Board'!$BD$2:$BD$87,'Draft Board'!$BD$2:$BD$87,">="&BD66,'Draft Board'!$BF$2:$BF$87,1) -> 0 | BH66: =IF(BE66<>_xlfn.MINIFS('Draft Board'!$BE$2:$BE$87,'Draft Board'!$BD$2:$BD$87,"="&BD66),0,IF(OR(BF66=1,IFERROR(FLOOR((BG66-BD66)/BG66/0.25,1),0)<>IFERROR(FLOOR((BG66-_xlfn.MINIFS('Draft Board'!$BD$2:$BD$87,'Draft Board'!$BD$2:$BD$87,">"&BD66))/BG66/0.25,1),0)),1,0)) -> 0 | BI66: =ROUND(1+BD66*'Live Calc'!$D$29,0) -> 1 | BK66: =IF(BJ66<>"",BJ66,ROUND(BI66*INDEX('Live Calc'!$G$454:$G$539,MATCH(BC66,'Live Calc'!$A$454:$A$539,0))*'Live Calc'!$J$543,0)) -> 1
Q67: James Conner | R67: ARI | S67: 43.746 | T67: 49.898 | U67: 56.81 | V67: =CHOOSE(MATCH(Setup!$B$7,{"STD","Half-PPR","PPR"},0),S67,T67,U67) -> 49.898 | W67: =COUNTIFS('Draft Board'!$X$2:$X$161,">="&X67,'Draft Board'!$AB$2:$AB$161,1) -> 14 | X67: =MAX(0,V67-'Live Calc'!$H$20)^'Live Calc'!$E$20 -> 0 | Y67: 67 | Z67: =IF(Y67<>_xlfn.MINIFS('Draft Board'!$Y$2:$Y$161,'Draft Board'!$X$2:$X$161,"="&X67),0,IF(_xlfn.MINIFS('Draft Board'!$X$2:$X$161,'Draft Board'!$X$2:$X$161,">"&X67)=0,1,IF((_xlfn.MINIFS('Draft Board'!$X$2:$X$161,'Draft Board'!$X$2:$X$161,">"&X67)-X67)/_xlfn.MINIFS('Draft Board'!$X$2:$X$161,'Draft Board'!$X$2:$X$161,">"&X67)>0.08,1,0))) -> 0 | AA67: =_xlfn.MINIFS('Draft Board'!$X$2:$X$161,'Draft Board'!$X$2:$X$161,">="&X67,'Draft Board'!$Z$2:$Z$161,1) -> 0 | AB67: =IF(Y67<>_xlfn.MINIFS('Draft Board'!$Y$2:$Y$161,'Draft Board'!$X$2:$X$161,"="&X67),0,IF(OR(Z67=1,IFERROR(FLOOR((AA67-X67)/AA67/0.25,1),0)<>IFERROR(FLOOR((AA67-_xlfn.MINIFS('Draft Board'!$X$2:$X$161,'Draft Board'!$X$2:$X$161,">"&X67))/AA67/0.25,1),0)),1,0)) -> 0 | AC67: =ROUND(1+X67*'Live Calc'!$D$27,0) -> 1 | AE67: =IF(AD67<>"",AD67,ROUND(AC67*INDEX('Live Calc'!$G$96:$G$255,MATCH(W67,'Live Calc'!$A$96:$A$255,0))*'Live Calc'!$J$543,0)) -> 1 | AG67: Calvin Ridley | AH67: TEN | AI67: 76.24 | AJ67: 94.474 | AK67: 114.176 | AL67: =CHOOSE(MATCH(Setup!$B$7,{"STD","Half-PPR","PPR"},0),AI67,AJ67,AK67) -> 94.474 | AM67: =COUNTIFS('Draft Board'!$AN$2:$AN$193,">="&AN67,'Draft Board'!$AR$2:$AR$193,1) -> 20 | AN67: =MAX(0,AL67-'Live Calc'!$H$21)^'Live Calc'!$E$21 -> 0 | AO67: 67 | AP67: =IF(AO67<>_xlfn.MINIFS('Draft Board'!$AO$2:$AO$193,'Draft Board'!$AN$2:$AN$193,"="&AN67),0,IF(_xlfn.MINIFS('Draft Board'!$AN$2:$AN$193,'Draft Board'!$AN$2:$AN$193,">"&AN67)=0,1,IF((_xlfn.MINIFS('Draft Board'!$AN$2:$AN$193,'Draft Board'!$AN$2:$AN$193,">"&AN67)-AN67)/_xlfn.MINIFS('Draft Board'!$AN$2:$AN$193,'Draft Board'!$AN$2:$AN$193,">"&AN67)>0.08,1,0))) -> 0 | AQ67: =_xlfn.MINIFS('Draft Board'!$AN$2:$AN$193,'Draft Board'!$AN$2:$AN$193,">="&AN67,'Draft Board'!$AP$2:$AP$193,1) -> 0 | AR67: =IF(AO67<>_xlfn.MINIFS('Draft Board'!$AO$2:$AO$193,'Draft Board'!$AN$2:$AN$193,"="&AN67),0,IF(OR(AP67=1,IFERROR(FLOOR((AQ67-AN67)/AQ67/0.25,1),0)<>IFERROR(FLOOR((AQ67-_xlfn.MINIFS('Draft Board'!$AN$2:$AN$193,'Draft Board'!$AN$2:$AN$193,">"&AN67))/AQ67/0.25,1),0)),1,0)) -> 0 | AS67: =ROUND(1+AN67*'Live Calc'!$D$28,0) -> 1 | AU67: =IF(AT67<>"",AT67,ROUND(AS67*INDEX('Live Calc'!$G$259:$G$450,MATCH(AM67,'Live Calc'!$A$259:$A$450,0))*'Live Calc'!$J$543,0)) -> 1 | AW67: Justin Joly | AX67: DEN | AY67: 24.232 | AZ67: 29.47 | BA67: 37.014 | BB67: =CHOOSE(MATCH(Setup!$B$7,{"STD","Half-PPR","PPR"},0),AY67,AZ67,BA67) -> 29.47 | BC67: =COUNTIFS('Draft Board'!$BD$2:$BD$87,">="&BD67,'Draft Board'!$BH$2:$BH$87,1) -> 15 | BD67: =MAX(0,BB67-'Live Calc'!$H$22)^'Live Calc'!$E$22 -> 0 | BE67: 67 | BF67: =IF(BE67<>_xlfn.MINIFS('Draft Board'!$BE$2:$BE$87,'Draft Board'!$BD$2:$BD$87,"="&BD67),0,IF(_xlfn.MINIFS('Draft Board'!$BD$2:$BD$87,'Draft Board'!$BD$2:$BD$87,">"&BD67)=0,1,IF((_xlfn.MINIFS('Draft Board'!$BD$2:$BD$87,'Draft Board'!$BD$2:$BD$87,">"&BD67)-BD67)/_xlfn.MINIFS('Draft Board'!$BD$2:$BD$87,'Draft Board'!$BD$2:$BD$87,">"&BD67)>0.08,1,0))) -> 0 | BG67: =_xlfn.MINIFS('Draft Board'!$BD$2:$BD$87,'Draft Board'!$BD$2:$BD$87,">="&BD67,'Draft Board'!$BF$2:$BF$87,1) -> 0 | BH67: =IF(BE67<>_xlfn.MINIFS('Draft Board'!$BE$2:$BE$87,'Draft Board'!$BD$2:$BD$87,"="&BD67),0,IF(OR(BF67=1,IFERROR(FLOOR((BG67-BD67)/BG67/0.25,1),0)<>IFERROR(FLOOR((BG67-_xlfn.MINIFS('Draft Board'!$BD$2:$BD$87,'Draft Board'!$BD$2:$BD$87,">"&BD67))/BG67/0.25,1),0)),1,0)) -> 0 | BI67: =ROUND(1+BD67*'Live Calc'!$D$29,0) -> 1 | BK67: =IF(BJ67<>"",BJ67,ROUND(BI67*INDEX('Live Calc'!$G$454:$G$539,MATCH(BC67,'Live Calc'!$A$454:$A$539,0))*'Live Calc'!$J$543,0)) -> 1
Q68: Kaelon Black | R68: SF | S68: 44.93 | T68: 48.69 | U68: 53.376 | V68: =CHOOSE(MATCH(Setup!$B$7,{"STD","Half-PPR","PPR"},0),S68,T68,U68) -> 48.69 | W68: =COUNTIFS('Draft Board'!$X$2:$X$161,">="&X68,'Draft Board'!$AB$2:$AB$161,1) -> 14 | X68: =MAX(0,V68-'Live Calc'!$H$20)^'Live Calc'!$E$20 -> 0 | Y68: 68 | Z68: =IF(Y68<>_xlfn.MINIFS('Draft Board'!$Y$2:$Y$161,'Draft Board'!$X$2:$X$161,"="&X68),0,IF(_xlfn.MINIFS('Draft Board'!$X$2:$X$161,'Draft Board'!$X$2:$X$161,">"&X68)=0,1,IF((_xlfn.MINIFS('Draft Board'!$X$2:$X$161,'Draft Board'!$X$2:$X$161,">"&X68)-X68)/_xlfn.MINIFS('Draft Board'!$X$2:$X$161,'Draft Board'!$X$2:$X$161,">"&X68)>0.08,1,0))) -> 0 | AA68: =_xlfn.MINIFS('Draft Board'!$X$2:$X$161,'Draft Board'!$X$2:$X$161,">="&X68,'Draft Board'!$Z$2:$Z$161,1) -> 0 | AB68: =IF(Y68<>_xlfn.MINIFS('Draft Board'!$Y$2:$Y$161,'Draft Board'!$X$2:$X$161,"="&X68),0,IF(OR(Z68=1,IFERROR(FLOOR((AA68-X68)/AA68/0.25,1),0)<>IFERROR(FLOOR((AA68-_xlfn.MINIFS('Draft Board'!$X$2:$X$161,'Draft Board'!$X$2:$X$161,">"&X68))/AA68/0.25,1),0)),1,0)) -> 0 | AC68: =ROUND(1+X68*'Live Calc'!$D$27,0) -> 1 | AE68: =IF(AD68<>"",AD68,ROUND(AC68*INDEX('Live Calc'!$G$96:$G$255,MATCH(W68,'Live Calc'!$A$96:$A$255,0))*'Live Calc'!$J$543,0)) -> 1 | AG68: Adonai Mitchell | AH68: NYJ | AI68: 72.954 | AJ68: 93.556 | AK68: 112.194 | AL68: =CHOOSE(MATCH(Setup!$B$7,{"STD","Half-PPR","PPR"},0),AI68,AJ68,AK68) -> 93.556 | AM68: =COUNTIFS('Draft Board'!$AN$2:$AN$193,">="&AN68,'Draft Board'!$AR$2:$AR$193,1) -> 20 | AN68: =MAX(0,AL68-'Live Calc'!$H$21)^'Live Calc'!$E$21 -> 0 | AO68: 68 | AP68: =IF(AO68<>_xlfn.MINIFS('Draft Board'!$AO$2:$AO$193,'Draft Board'!$AN$2:$AN$193,"="&AN68),0,IF(_xlfn.MINIFS('Draft Board'!$AN$2:$AN$193,'Draft Board'!$AN$2:$AN$193,">"&AN68)=0,1,IF((_xlfn.MINIFS('Draft Board'!$AN$2:$AN$193,'Draft Board'!$AN$2:$AN$193,">"&AN68)-AN68)/_xlfn.MINIFS('Draft Board'!$AN$2:$AN$193,'Draft Board'!$AN$2:$AN$193,">"&AN68)>0.08,1,0))) -> 0 | AQ68: =_xlfn.MINIFS('Draft Board'!$AN$2:$AN$193,'Draft Board'!$AN$2:$AN$193,">="&AN68,'Draft Board'!$AP$2:$AP$193,1) -> 0 | AR68: =IF(AO68<>_xlfn.MINIFS('Draft Board'!$AO$2:$AO$193,'Draft Board'!$AN$2:$AN$193,"="&AN68),0,IF(OR(AP68=1,IFERROR(FLOOR((AQ68-AN68)/AQ68/0.25,1),0)<>IFERROR(FLOOR((AQ68-_xlfn.MINIFS('Draft Board'!$AN$2:$AN$193,'Draft Board'!$AN$2:$AN$193,">"&AN68))/AQ68/0.25,1),0)),1,0)) -> 0 | AS68: =ROUND(1+AN68*'Live Calc'!$D$28,0) -> 1 | AU68: =IF(AT68<>"",AT68,ROUND(AS68*INDEX('Live Calc'!$G$259:$G$450,MATCH(AM68,'Live Calc'!$A$259:$A$450,0))*'Live Calc'!$J$543,0)) -> 1 | AW68: Connor Heyward | AX68: LV | AY68: 22.3 | AZ68: 29.3 | BA68: 36.3 | BB68: =CHOOSE(MATCH(Setup!$B$7,{"STD","Half-PPR","PPR"},0),AY68,AZ68,BA68) -> 29.3 | BC68: =COUNTIFS('Draft Board'!$BD$2:$BD$87,">="&BD68,'Draft Board'!$BH$2:$BH$87,1) -> 15 | BD68: =MAX(0,BB68-'Live Calc'!$H$22)^'Live Calc'!$E$22 -> 0 | BE68: 68 | BF68: =IF(BE68<>_xlfn.MINIFS('Draft Board'!$BE$2:$BE$87,'Draft Board'!$BD$2:$BD$87,"="&BD68),0,IF(_xlfn.MINIFS('Draft Board'!$BD$2:$BD$87,'Draft Board'!$BD$2:$BD$87,">"&BD68)=0,1,IF((_xlfn.MINIFS('Draft Board'!$BD$2:$BD$87,'Draft Board'!$BD$2:$BD$87,">"&BD68)-BD68)/_xlfn.MINIFS('Draft Board'!$BD$2:$BD$87,'Draft Board'!$BD$2:$BD$87,">"&BD68)>0.08,1,0))) -> 0 | BG68: =_xlfn.MINIFS('Draft Board'!$BD$2:$BD$87,'Draft Board'!$BD$2:$BD$87,">="&BD68,'Draft Board'!$BF$2:$BF$87,1) -> 0 | BH68: =IF(BE68<>_xlfn.MINIFS('Draft Board'!$BE$2:$BE$87,'Draft Board'!$BD$2:$BD$87,"="&BD68),0,IF(OR(BF68=1,IFERROR(FLOOR((BG68-BD68)/BG68/0.25,1),0)<>IFERROR(FLOOR((BG68-_xlfn.MINIFS('Draft Board'!$BD$2:$BD$87,'Draft Board'!$BD$2:$BD$87,">"&BD68))/BG68/0.25,1),0)),1,0)) -> 0 | BI68: =ROUND(1+BD68*'Live Calc'!$D$29,0) -> 1 | BK68: =IF(BJ68<>"",BJ68,ROUND(BI68*INDEX('Live Calc'!$G$454:$G$539,MATCH(BC68,'Live Calc'!$A$454:$A$539,0))*'Live Calc'!$J$543,0)) -> 1
Q69: Emanuel Wilson | R69: SEA | S69: 44.002 | T69: 48.302 | U69: 52.826 | V69: =CHOOSE(MATCH(Setup!$B$7,{"STD","Half-PPR","PPR"},0),S69,T69,U69) -> 48.302 | W69: =COUNTIFS('Draft Board'!$X$2:$X$161,">="&X69,'Draft Board'!$AB$2:$AB$161,1) -> 14 | X69: =MAX(0,V69-'Live Calc'!$H$20)^'Live Calc'!$E$20 -> 0 | Y69: 69 | Z69: =IF(Y69<>_xlfn.MINIFS('Draft Board'!$Y$2:$Y$161,'Draft Board'!$X$2:$X$161,"="&X69),0,IF(_xlfn.MINIFS('Draft Board'!$X$2:$X$161,'Draft Board'!$X$2:$X$161,">"&X69)=0,1,IF((_xlfn.MINIFS('Draft Board'!$X$2:$X$161,'Draft Board'!$X$2:$X$161,">"&X69)-X69)/_xlfn.MINIFS('Draft Board'!$X$2:$X$161,'Draft Board'!$X$2:$X$161,">"&X69)>0.08,1,0))) -> 0 | AA69: =_xlfn.MINIFS('Draft Board'!$X$2:$X$161,'Draft Board'!$X$2:$X$161,">="&X69,'Draft Board'!$Z$2:$Z$161,1) -> 0 | AB69: =IF(Y69<>_xlfn.MINIFS('Draft Board'!$Y$2:$Y$161,'Draft Board'!$X$2:$X$161,"="&X69),0,IF(OR(Z69=1,IFERROR(FLOOR((AA69-X69)/AA69/0.25,1),0)<>IFERROR(FLOOR((AA69-_xlfn.MINIFS('Draft Board'!$X$2:$X$161,'Draft Board'!$X$2:$X$161,">"&X69))/AA69/0.25,1),0)),1,0)) -> 0 | AC69: =ROUND(1+X69*'Live Calc'!$D$27,0) -> 1 | AE69: =IF(AD69<>"",AD69,ROUND(AC69*INDEX('Live Calc'!$G$96:$G$255,MATCH(W69,'Live Calc'!$A$96:$A$255,0))*'Live Calc'!$J$543,0)) -> 1 | AG69: Ryan Flournoy | AH69: DAL | AI69: 69.92 | AJ69: 91.088 | AK69: 111.768 | AL69: =CHOOSE(MATCH(Setup!$B$7,{"STD","Half-PPR","PPR"},0),AI69,AJ69,AK69) -> 91.088 | AM69: =COUNTIFS('Draft Board'!$AN$2:$AN$193,">="&AN69,'Draft Board'!$AR$2:$AR$193,1) -> 20 | AN69: =MAX(0,AL69-'Live Calc'!$H$21)^'Live Calc'!$E$21 -> 0 | AO69: 69 | AP69: =IF(AO69<>_xlfn.MINIFS('Draft Board'!$AO$2:$AO$193,'Draft Board'!$AN$2:$AN$193,"="&AN69),0,IF(_xlfn.MINIFS('Draft Board'!$AN$2:$AN$193,'Draft Board'!$AN$2:$AN$193,">"&AN69)=0,1,IF((_xlfn.MINIFS('Draft Board'!$AN$2:$AN$193,'Draft Board'!$AN$2:$AN$193,">"&AN69)-AN69)/_xlfn.MINIFS('Draft Board'!$AN$2:$AN$193,'Draft Board'!$AN$2:$AN$193,">"&AN69)>0.08,1,0))) -> 0 | AQ69: =_xlfn.MINIFS('Draft Board'!$AN$2:$AN$193,'Draft Board'!$AN$2:$AN$193,">="&AN69,'Draft Board'!$AP$2:$AP$193,1) -> 0 | AR69: =IF(AO69<>_xlfn.MINIFS('Draft Board'!$AO$2:$AO$193,'Draft Board'!$AN$2:$AN$193,"="&AN69),0,IF(OR(AP69=1,IFERROR(FLOOR((AQ69-AN69)/AQ69/0.25,1),0)<>IFERROR(FLOOR((AQ69-_xlfn.MINIFS('Draft Board'!$AN$2:$AN$193,'Draft Board'!$AN$2:$AN$193,">"&AN69))/AQ69/0.25,1),0)),1,0)) -> 0 | AS69: =ROUND(1+AN69*'Live Calc'!$D$28,0) -> 1 | AU69: =IF(AT69<>"",AT69,ROUND(AS69*INDEX('Live Calc'!$G$259:$G$450,MATCH(AM69,'Live Calc'!$A$259:$A$450,0))*'Live Calc'!$J$543,0)) -> 1 | AW69: Nate Boerkircher | AX69: JAC | AY69: 21.75 | AZ69: 29.096 | BA69: 32.43 | BB69: =CHOOSE(MATCH(Setup!$B$7,{"STD","Half-PPR","PPR"},0),AY69,AZ69,BA69) -> 29.096 | BC69: =COUNTIFS('Draft Board'!$BD$2:$BD$87,">="&BD69,'Draft Board'!$BH$2:$BH$87,1) -> 15 | BD69: =MAX(0,BB69-'Live Calc'!$H$22)^'Live Calc'!$E$22 -> 0 | BE69: 69 | BF69: =IF(BE69<>_xlfn.MINIFS('Draft Board'!$BE$2:$BE$87,'Draft Board'!$BD$2:$BD$87,"="&BD69),0,IF(_xlfn.MINIFS('Draft Board'!$BD$2:$BD$87,'Draft Board'!$BD$2:$BD$87,">"&BD69)=0,1,IF((_xlfn.MINIFS('Draft Board'!$BD$2:$BD$87,'Draft Board'!$BD$2:$BD$87,">"&BD69)-BD69)/_xlfn.MINIFS('Draft Board'!$BD$2:$BD$87,'Draft Board'!$BD$2:$BD$87,">"&BD69)>0.08,1,0))) -> 0 | BG69: =_xlfn.MINIFS('Draft Board'!$BD$2:$BD$87,'Draft Board'!$BD$2:$BD$87,">="&BD69,'Draft Board'!$BF$2:$BF$87,1) -> 0 | BH69: =IF(BE69<>_xlfn.MINIFS('Draft Board'!$BE$2:$BE$87,'Draft Board'!$BD$2:$BD$87,"="&BD69),0,IF(OR(BF69=1,IFERROR(FLOOR((BG69-BD69)/BG69/0.25,1),0)<>IFERROR(FLOOR((BG69-_xlfn.MINIFS('Draft Board'!$BD$2:$BD$87,'Draft Board'!$BD$2:$BD$87,">"&BD69))/BG69/0.25,1),0)),1,0)) -> 0 | BI69: =ROUND(1+BD69*'Live Calc'!$D$29,0) -> 1 | BK69: =IF(BJ69<>"",BJ69,ROUND(BI69*INDEX('Live Calc'!$G$454:$G$539,MATCH(BC69,'Live Calc'!$A$454:$A$539,0))*'Live Calc'!$J$543,0)) -> 1
Q70: Jaylen Wright | R70: MIA | S70: 44.764 | T70: 48.108 | U70: 52.216 | V70: =CHOOSE(MATCH(Setup!$B$7,{"STD","Half-PPR","PPR"},0),S70,T70,U70) -> 48.108 | W70: =COUNTIFS('Draft Board'!$X$2:$X$161,">="&X70,'Draft Board'!$AB$2:$AB$161,1) -> 14 | X70: =MAX(0,V70-'Live Calc'!$H$20)^'Live Calc'!$E$20 -> 0 | Y70: 70 | Z70: =IF(Y70<>_xlfn.MINIFS('Draft Board'!$Y$2:$Y$161,'Draft Board'!$X$2:$X$161,"="&X70),0,IF(_xlfn.MINIFS('Draft Board'!$X$2:$X$161,'Draft Board'!$X$2:$X$161,">"&X70)=0,1,IF((_xlfn.MINIFS('Draft Board'!$X$2:$X$161,'Draft Board'!$X$2:$X$161,">"&X70)-X70)/_xlfn.MINIFS('Draft Board'!$X$2:$X$161,'Draft Board'!$X$2:$X$161,">"&X70)>0.08,1,0))) -> 0 | AA70: =_xlfn.MINIFS('Draft Board'!$X$2:$X$161,'Draft Board'!$X$2:$X$161,">="&X70,'Draft Board'!$Z$2:$Z$161,1) -> 0 | AB70: =IF(Y70<>_xlfn.MINIFS('Draft Board'!$Y$2:$Y$161,'Draft Board'!$X$2:$X$161,"="&X70),0,IF(OR(Z70=1,IFERROR(FLOOR((AA70-X70)/AA70/0.25,1),0)<>IFERROR(FLOOR((AA70-_xlfn.MINIFS('Draft Board'!$X$2:$X$161,'Draft Board'!$X$2:$X$161,">"&X70))/AA70/0.25,1),0)),1,0)) -> 0 | AC70: =ROUND(1+X70*'Live Calc'!$D$27,0) -> 1 | AE70: =IF(AD70<>"",AD70,ROUND(AC70*INDEX('Live Calc'!$G$96:$G$255,MATCH(W70,'Live Calc'!$A$96:$A$255,0))*'Live Calc'!$J$543,0)) -> 1 | AG70: Antonio Williams | AH70: WAS | AI70: 69.034 | AJ70: 90.19 | AK70: 110.918 | AL70: =CHOOSE(MATCH(Setup!$B$7,{"STD","Half-PPR","PPR"},0),AI70,AJ70,AK70) -> 90.19 | AM70: =COUNTIFS('Draft Board'!$AN$2:$AN$193,">="&AN70,'Draft Board'!$AR$2:$AR$193,1) -> 20 | AN70: =MAX(0,AL70-'Live Calc'!$H$21)^'Live Calc'!$E$21 -> 0 | AO70: 70 | AP70: =IF(AO70<>_xlfn.MINIFS('Draft Board'!$AO$2:$AO$193,'Draft Board'!$AN$2:$AN$193,"="&AN70),0,IF(_xlfn.MINIFS('Draft Board'!$AN$2:$AN$193,'Draft Board'!$AN$2:$AN$193,">"&AN70)=0,1,IF((_xlfn.MINIFS('Draft Board'!$AN$2:$AN$193,'Draft Board'!$AN$2:$AN$193,">"&AN70)-AN70)/_xlfn.MINIFS('Draft Board'!$AN$2:$AN$193,'Draft Board'!$AN$2:$AN$193,">"&AN70)>0.08,1,0))) -> 0 | AQ70: =_xlfn.MINIFS('Draft Board'!$AN$2:$AN$193,'Draft Board'!$AN$2:$AN$193,">="&AN70,'Draft Board'!$AP$2:$AP$193,1) -> 0 | AR70: =IF(AO70<>_xlfn.MINIFS('Draft Board'!$AO$2:$AO$193,'Draft Board'!$AN$2:$AN$193,"="&AN70),0,IF(OR(AP70=1,IFERROR(FLOOR((AQ70-AN70)/AQ70/0.25,1),0)<>IFERROR(FLOOR((AQ70-_xlfn.MINIFS('Draft Board'!$AN$2:$AN$193,'Draft Board'!$AN$2:$AN$193,">"&AN70))/AQ70/0.25,1),0)),1,0)) -> 0 | AS70: =ROUND(1+AN70*'Live Calc'!$D$28,0) -> 1 | AU70: =IF(AT70<>"",AT70,ROUND(AS70*INDEX('Live Calc'!$G$259:$G$450,MATCH(AM70,'Live Calc'!$A$259:$A$450,0))*'Live Calc'!$J$543,0)) -> 1 | AW70: Tanner Hudson | AX70: CIN | AY70: 19.61 | AZ70: 27.58 | BA70: 35.56 | BB70: =CHOOSE(MATCH(Setup!$B$7,{"STD","Half-PPR","PPR"},0),AY70,AZ70,BA70) -> 27.58 | BC70: =COUNTIFS('Draft Board'!$BD$2:$BD$87,">="&BD70,'Draft Board'!$BH$2:$BH$87,1) -> 15 | BD70: =MAX(0,BB70-'Live Calc'!$H$22)^'Live Calc'!$E$22 -> 0 | BE70: 70 | BF70: =IF(BE70<>_xlfn.MINIFS('Draft Board'!$BE$2:$BE$87,'Draft Board'!$BD$2:$BD$87,"="&BD70),0,IF(_xlfn.MINIFS('Draft Board'!$BD$2:$BD$87,'Draft Board'!$BD$2:$BD$87,">"&BD70)=0,1,IF((_xlfn.MINIFS('Draft Board'!$BD$2:$BD$87,'Draft Board'!$BD$2:$BD$87,">"&BD70)-BD70)/_xlfn.MINIFS('Draft Board'!$BD$2:$BD$87,'Draft Board'!$BD$2:$BD$87,">"&BD70)>0.08,1,0))) -> 0 | BG70: =_xlfn.MINIFS('Draft Board'!$BD$2:$BD$87,'Draft Board'!$BD$2:$BD$87,">="&BD70,'Draft Board'!$BF$2:$BF$87,1) -> 0 | BH70: =IF(BE70<>_xlfn.MINIFS('Draft Board'!$BE$2:$BE$87,'Draft Board'!$BD$2:$BD$87,"="&BD70),0,IF(OR(BF70=1,IFERROR(FLOOR((BG70-BD70)/BG70/0.25,1),0)<>IFERROR(FLOOR((BG70-_xlfn.MINIFS('Draft Board'!$BD$2:$BD$87,'Draft Board'!$BD$2:$BD$87,">"&BD70))/BG70/0.25,1),0)),1,0)) -> 0 | BI70: =ROUND(1+BD70*'Live Calc'!$D$29,0) -> 1 | BK70: =IF(BJ70<>"",BJ70,ROUND(BI70*INDEX('Live Calc'!$G$454:$G$539,MATCH(BC70,'Live Calc'!$A$454:$A$539,0))*'Live Calc'!$J$543,0)) -> 1
Q71: Kaytron Allen | R71: WAS | S71: 42.766 | T71: 47.278 | U71: 50.124 | V71: =CHOOSE(MATCH(Setup!$B$7,{"STD","Half-PPR","PPR"},0),S71,T71,U71) -> 47.278 | W71: =COUNTIFS('Draft Board'!$X$2:$X$161,">="&X71,'Draft Board'!$AB$2:$AB$161,1) -> 14 | X71: =MAX(0,V71-'Live Calc'!$H$20)^'Live Calc'!$E$20 -> 0 | Y71: 71 | Z71: =IF(Y71<>_xlfn.MINIFS('Draft Board'!$Y$2:$Y$161,'Draft Board'!$X$2:$X$161,"="&X71),0,IF(_xlfn.MINIFS('Draft Board'!$X$2:$X$161,'Draft Board'!$X$2:$X$161,">"&X71)=0,1,IF((_xlfn.MINIFS('Draft Board'!$X$2:$X$161,'Draft Board'!$X$2:$X$161,">"&X71)-X71)/_xlfn.MINIFS('Draft Board'!$X$2:$X$161,'Draft Board'!$X$2:$X$161,">"&X71)>0.08,1,0))) -> 0 | AA71: =_xlfn.MINIFS('Draft Board'!$X$2:$X$161,'Draft Board'!$X$2:$X$161,">="&X71,'Draft Board'!$Z$2:$Z$161,1) -> 0 | AB71: =IF(Y71<>_xlfn.MINIFS('Draft Board'!$Y$2:$Y$161,'Draft Board'!$X$2:$X$161,"="&X71),0,IF(OR(Z71=1,IFERROR(FLOOR((AA71-X71)/AA71/0.25,1),0)<>IFERROR(FLOOR((AA71-_xlfn.MINIFS('Draft Board'!$X$2:$X$161,'Draft Board'!$X$2:$X$161,">"&X71))/AA71/0.25,1),0)),1,0)) -> 0 | AC71: =ROUND(1+X71*'Live Calc'!$D$27,0) -> 1 | AE71: =IF(AD71<>"",AD71,ROUND(AC71*INDEX('Live Calc'!$G$96:$G$255,MATCH(W71,'Live Calc'!$A$96:$A$255,0))*'Live Calc'!$J$543,0)) -> 1 | AG71: Germie Bernard | AH71: PIT | AI71: 65.296 | AJ71: 86.232 | AK71: 106.094 | AL71: =CHOOSE(MATCH(Setup!$B$7,{"STD","Half-PPR","PPR"},0),AI71,AJ71,AK71) -> 86.232 | AM71: =COUNTIFS('Draft Board'!$AN$2:$AN$193,">="&AN71,'Draft Board'!$AR$2:$AR$193,1) -> 20 | AN71: =MAX(0,AL71-'Live Calc'!$H$21)^'Live Calc'!$E$21 -> 0 | AO71: 71 | AP71: =IF(AO71<>_xlfn.MINIFS('Draft Board'!$AO$2:$AO$193,'Draft Board'!$AN$2:$AN$193,"="&AN71),0,IF(_xlfn.MINIFS('Draft Board'!$AN$2:$AN$193,'Draft Board'!$AN$2:$AN$193,">"&AN71)=0,1,IF((_xlfn.MINIFS('Draft Board'!$AN$2:$AN$193,'Draft Board'!$AN$2:$AN$193,">"&AN71)-AN71)/_xlfn.MINIFS('Draft Board'!$AN$2:$AN$193,'Draft Board'!$AN$2:$AN$193,">"&AN71)>0.08,1,0))) -> 0 | AQ71: =_xlfn.MINIFS('Draft Board'!$AN$2:$AN$193,'Draft Board'!$AN$2:$AN$193,">="&AN71,'Draft Board'!$AP$2:$AP$193,1) -> 0 | AR71: =IF(AO71<>_xlfn.MINIFS('Draft Board'!$AO$2:$AO$193,'Draft Board'!$AN$2:$AN$193,"="&AN71),0,IF(OR(AP71=1,IFERROR(FLOOR((AQ71-AN71)/AQ71/0.25,1),0)<>IFERROR(FLOOR((AQ71-_xlfn.MINIFS('Draft Board'!$AN$2:$AN$193,'Draft Board'!$AN$2:$AN$193,">"&AN71))/AQ71/0.25,1),0)),1,0)) -> 0 | AS71: =ROUND(1+AN71*'Live Calc'!$D$28,0) -> 1 | AU71: =IF(AT71<>"",AT71,ROUND(AS71*INDEX('Live Calc'!$G$259:$G$450,MATCH(AM71,'Live Calc'!$A$259:$A$450,0))*'Live Calc'!$J$543,0)) -> 1 | AW71: Jackson Hawes | AX71: BUF | AY71: 21.06 | AZ71: 27.14 | BA71: 33.22 | BB71: =CHOOSE(MATCH(Setup!$B$7,{"STD","Half-PPR","PPR"},0),AY71,AZ71,BA71) -> 27.14 | BC71: =COUNTIFS('Draft Board'!$BD$2:$BD$87,">="&BD71,'Draft Board'!$BH$2:$BH$87,1) -> 15 | BD71: =MAX(0,BB71-'Live Calc'!$H$22)^'Live Calc'!$E$22 -> 0 | BE71: 71 | BF71: =IF(BE71<>_xlfn.MINIFS('Draft Board'!$BE$2:$BE$87,'Draft Board'!$BD$2:$BD$87,"="&BD71),0,IF(_xlfn.MINIFS('Draft Board'!$BD$2:$BD$87,'Draft Board'!$BD$2:$BD$87,">"&BD71)=0,1,IF((_xlfn.MINIFS('Draft Board'!$BD$2:$BD$87,'Draft Board'!$BD$2:$BD$87,">"&BD71)-BD71)/_xlfn.MINIFS('Draft Board'!$BD$2:$BD$87,'Draft Board'!$BD$2:$BD$87,">"&BD71)>0.08,1,0))) -> 0 | BG71: =_xlfn.MINIFS('Draft Board'!$BD$2:$BD$87,'Draft Board'!$BD$2:$BD$87,">="&BD71,'Draft Board'!$BF$2:$BF$87,1) -> 0 | BH71: =IF(BE71<>_xlfn.MINIFS('Draft Board'!$BE$2:$BE$87,'Draft Board'!$BD$2:$BD$87,"="&BD71),0,IF(OR(BF71=1,IFERROR(FLOOR((BG71-BD71)/BG71/0.25,1),0)<>IFERROR(FLOOR((BG71-_xlfn.MINIFS('Draft Board'!$BD$2:$BD$87,'Draft Board'!$BD$2:$BD$87,">"&BD71))/BG71/0.25,1),0)),1,0)) -> 0 | BI71: =ROUND(1+BD71*'Live Calc'!$D$29,0) -> 1 | BK71: =IF(BJ71<>"",BJ71,ROUND(BI71*INDEX('Live Calc'!$G$454:$G$539,MATCH(BC71,'Live Calc'!$A$454:$A$539,0))*'Live Calc'!$J$543,0)) -> 1
Q72: Jaydon Blue | R72: DAL | S72: 42.52 | T72: 46.76 | U72: 49.666 | V72: =CHOOSE(MATCH(Setup!$B$7,{"STD","Half-PPR","PPR"},0),S72,T72,U72) -> 46.76 | W72: =COUNTIFS('Draft Board'!$X$2:$X$161,">="&X72,'Draft Board'!$AB$2:$AB$161,1) -> 14 | X72: =MAX(0,V72-'Live Calc'!$H$20)^'Live Calc'!$E$20 -> 0 | Y72: 72 | Z72: =IF(Y72<>_xlfn.MINIFS('Draft Board'!$Y$2:$Y$161,'Draft Board'!$X$2:$X$161,"="&X72),0,IF(_xlfn.MINIFS('Draft Board'!$X$2:$X$161,'Draft Board'!$X$2:$X$161,">"&X72)=0,1,IF((_xlfn.MINIFS('Draft Board'!$X$2:$X$161,'Draft Board'!$X$2:$X$161,">"&X72)-X72)/_xlfn.MINIFS('Draft Board'!$X$2:$X$161,'Draft Board'!$X$2:$X$161,">"&X72)>0.08,1,0))) -> 0 | AA72: =_xlfn.MINIFS('Draft Board'!$X$2:$X$161,'Draft Board'!$X$2:$X$161,">="&X72,'Draft Board'!$Z$2:$Z$161,1) -> 0 | AB72: =IF(Y72<>_xlfn.MINIFS('Draft Board'!$Y$2:$Y$161,'Draft Board'!$X$2:$X$161,"="&X72),0,IF(OR(Z72=1,IFERROR(FLOOR((AA72-X72)/AA72/0.25,1),0)<>IFERROR(FLOOR((AA72-_xlfn.MINIFS('Draft Board'!$X$2:$X$161,'Draft Board'!$X$2:$X$161,">"&X72))/AA72/0.25,1),0)),1,0)) -> 0 | AC72: =ROUND(1+X72*'Live Calc'!$D$27,0) -> 1 | AE72: =IF(AD72<>"",AD72,ROUND(AC72*INDEX('Live Calc'!$G$96:$G$255,MATCH(W72,'Live Calc'!$A$96:$A$255,0))*'Live Calc'!$J$543,0)) -> 1 | AG72: Malik Washington | AH72: MIA | AI72: 60.222 | AJ72: 82.514 | AK72: 103.304 | AL72: =CHOOSE(MATCH(Setup!$B$7,{"STD","Half-PPR","PPR"},0),AI72,AJ72,AK72) -> 82.514 | AM72: =COUNTIFS('Draft Board'!$AN$2:$AN$193,">="&AN72,'Draft Board'!$AR$2:$AR$193,1) -> 20 | AN72: =MAX(0,AL72-'Live Calc'!$H$21)^'Live Calc'!$E$21 -> 0 | AO72: 72 | AP72: =IF(AO72<>_xlfn.MINIFS('Draft Board'!$AO$2:$AO$193,'Draft Board'!$AN$2:$AN$193,"="&AN72),0,IF(_xlfn.MINIFS('Draft Board'!$AN$2:$AN$193,'Draft Board'!$AN$2:$AN$193,">"&AN72)=0,1,IF((_xlfn.MINIFS('Draft Board'!$AN$2:$AN$193,'Draft Board'!$AN$2:$AN$193,">"&AN72)-AN72)/_xlfn.MINIFS('Draft Board'!$AN$2:$AN$193,'Draft Board'!$AN$2:$AN$193,">"&AN72)>0.08,1,0))) -> 0 | AQ72: =_xlfn.MINIFS('Draft Board'!$AN$2:$AN$193,'Draft Board'!$AN$2:$AN$193,">="&AN72,'Draft Board'!$AP$2:$AP$193,1) -> 0 | AR72: =IF(AO72<>_xlfn.MINIFS('Draft Board'!$AO$2:$AO$193,'Draft Board'!$AN$2:$AN$193,"="&AN72),0,IF(OR(AP72=1,IFERROR(FLOOR((AQ72-AN72)/AQ72/0.25,1),0)<>IFERROR(FLOOR((AQ72-_xlfn.MINIFS('Draft Board'!$AN$2:$AN$193,'Draft Board'!$AN$2:$AN$193,">"&AN72))/AQ72/0.25,1),0)),1,0)) -> 0 | AS72: =ROUND(1+AN72*'Live Calc'!$D$28,0) -> 1 | AU72: =IF(AT72<>"",AT72,ROUND(AS72*INDEX('Live Calc'!$G$259:$G$450,MATCH(AM72,'Live Calc'!$A$259:$A$450,0))*'Live Calc'!$J$543,0)) -> 1 | AW72: Will Dissly | AX72: FA | AY72: 19.86 | AZ72: 26.73 | BA72: 33.61 | BB72: =CHOOSE(MATCH(Setup!$B$7,{"STD","Half-PPR","PPR"},0),AY72,AZ72,BA72) -> 26.73 | BC72: =COUNTIFS('Draft Board'!$BD$2:$BD$87,">="&BD72,'Draft Board'!$BH$2:$BH$87,1) -> 15 | BD72: =MAX(0,BB72-'Live Calc'!$H$22)^'Live Calc'!$E$22 -> 0 | BE72: 72 | BF72: =IF(BE72<>_xlfn.MINIFS('Draft Board'!$BE$2:$BE$87,'Draft Board'!$BD$2:$BD$87,"="&BD72),0,IF(_xlfn.MINIFS('Draft Board'!$BD$2:$BD$87,'Draft Board'!$BD$2:$BD$87,">"&BD72)=0,1,IF((_xlfn.MINIFS('Draft Board'!$BD$2:$BD$87,'Draft Board'!$BD$2:$BD$87,">"&BD72)-BD72)/_xlfn.MINIFS('Draft Board'!$BD$2:$BD$87,'Draft Board'!$BD$2:$BD$87,">"&BD72)>0.08,1,0))) -> 0 | BG72: =_xlfn.MINIFS('Draft Board'!$BD$2:$BD$87,'Draft Board'!$BD$2:$BD$87,">="&BD72,'Draft Board'!$BF$2:$BF$87,1) -> 0 | BH72: =IF(BE72<>_xlfn.MINIFS('Draft Board'!$BE$2:$BE$87,'Draft Board'!$BD$2:$BD$87,"="&BD72),0,IF(OR(BF72=1,IFERROR(FLOOR((BG72-BD72)/BG72/0.25,1),0)<>IFERROR(FLOOR((BG72-_xlfn.MINIFS('Draft Board'!$BD$2:$BD$87,'Draft Board'!$BD$2:$BD$87,">"&BD72))/BG72/0.25,1),0)),1,0)) -> 0 | BI72: =ROUND(1+BD72*'Live Calc'!$D$29,0) -> 1 | BK72: =IF(BJ72<>"",BJ72,ROUND(BI72*INDEX('Live Calc'!$G$454:$G$539,MATCH(BC72,'Live Calc'!$A$454:$A$539,0))*'Live Calc'!$J$543,0)) -> 1
Q73: Chris Brooks | R73: GB | S73: 38.142 | T73: 45.396 | U73: 53.224 | V73: =CHOOSE(MATCH(Setup!$B$7,{"STD","Half-PPR","PPR"},0),S73,T73,U73) -> 45.396 | W73: =COUNTIFS('Draft Board'!$X$2:$X$161,">="&X73,'Draft Board'!$AB$2:$AB$161,1) -> 14 | X73: =MAX(0,V73-'Live Calc'!$H$20)^'Live Calc'!$E$20 -> 0 | Y73: 73 | Z73: =IF(Y73<>_xlfn.MINIFS('Draft Board'!$Y$2:$Y$161,'Draft Board'!$X$2:$X$161,"="&X73),0,IF(_xlfn.MINIFS('Draft Board'!$X$2:$X$161,'Draft Board'!$X$2:$X$161,">"&X73)=0,1,IF((_xlfn.MINIFS('Draft Board'!$X$2:$X$161,'Draft Board'!$X$2:$X$161,">"&X73)-X73)/_xlfn.MINIFS('Draft Board'!$X$2:$X$161,'Draft Board'!$X$2:$X$161,">"&X73)>0.08,1,0))) -> 0 | AA73: =_xlfn.MINIFS('Draft Board'!$X$2:$X$161,'Draft Board'!$X$2:$X$161,">="&X73,'Draft Board'!$Z$2:$Z$161,1) -> 0 | AB73: =IF(Y73<>_xlfn.MINIFS('Draft Board'!$Y$2:$Y$161,'Draft Board'!$X$2:$X$161,"="&X73),0,IF(OR(Z73=1,IFERROR(FLOOR((AA73-X73)/AA73/0.25,1),0)<>IFERROR(FLOOR((AA73-_xlfn.MINIFS('Draft Board'!$X$2:$X$161,'Draft Board'!$X$2:$X$161,">"&X73))/AA73/0.25,1),0)),1,0)) -> 0 | AC73: =ROUND(1+X73*'Live Calc'!$D$27,0) -> 1 | AE73: =IF(AD73<>"",AD73,ROUND(AC73*INDEX('Live Calc'!$G$96:$G$255,MATCH(W73,'Live Calc'!$A$96:$A$255,0))*'Live Calc'!$J$543,0)) -> 1 | AG73: Isaac TeSlaa | AH73: DET | AI73: 66.354 | AJ73: 82.416 | AK73: 98.908 | AL73: =CHOOSE(MATCH(Setup!$B$7,{"STD","Half-PPR","PPR"},0),AI73,AJ73,AK73) -> 82.416 | AM73: =COUNTIFS('Draft Board'!$AN$2:$AN$193,">="&AN73,'Draft Board'!$AR$2:$AR$193,1) -> 20 | AN73: =MAX(0,AL73-'Live Calc'!$H$21)^'Live Calc'!$E$21 -> 0 | AO73: 73 | AP73: =IF(AO73<>_xlfn.MINIFS('Draft Board'!$AO$2:$AO$193,'Draft Board'!$AN$2:$AN$193,"="&AN73),0,IF(_xlfn.MINIFS('Draft Board'!$AN$2:$AN$193,'Draft Board'!$AN$2:$AN$193,">"&AN73)=0,1,IF((_xlfn.MINIFS('Draft Board'!$AN$2:$AN$193,'Draft Board'!$AN$2:$AN$193,">"&AN73)-AN73)/_xlfn.MINIFS('Draft Board'!$AN$2:$AN$193,'Draft Board'!$AN$2:$AN$193,">"&AN73)>0.08,1,0))) -> 0 | AQ73: =_xlfn.MINIFS('Draft Board'!$AN$2:$AN$193,'Draft Board'!$AN$2:$AN$193,">="&AN73,'Draft Board'!$AP$2:$AP$193,1) -> 0 | AR73: =IF(AO73<>_xlfn.MINIFS('Draft Board'!$AO$2:$AO$193,'Draft Board'!$AN$2:$AN$193,"="&AN73),0,IF(OR(AP73=1,IFERROR(FLOOR((AQ73-AN73)/AQ73/0.25,1),0)<>IFERROR(FLOOR((AQ73-_xlfn.MINIFS('Draft Board'!$AN$2:$AN$193,'Draft Board'!$AN$2:$AN$193,">"&AN73))/AQ73/0.25,1),0)),1,0)) -> 0 | AS73: =ROUND(1+AN73*'Live Calc'!$D$28,0) -> 1 | AU73: =IF(AT73<>"",AT73,ROUND(AS73*INDEX('Live Calc'!$G$259:$G$450,MATCH(AM73,'Live Calc'!$A$259:$A$450,0))*'Live Calc'!$J$543,0)) -> 1 | AW73: Cade Stover | AX73: HOU | AY73: 18.58 | AZ73: 26.29 | BA73: 37.6 | BB73: =CHOOSE(MATCH(Setup!$B$7,{"STD","Half-PPR","PPR"},0),AY73,AZ73,BA73) -> 26.29 | BC73: =COUNTIFS('Draft Board'!$BD$2:$BD$87,">="&BD73,'Draft Board'!$BH$2:$BH$87,1) -> 15 | BD73: =MAX(0,BB73-'Live Calc'!$H$22)^'Live Calc'!$E$22 -> 0 | BE73: 73 | BF73: =IF(BE73<>_xlfn.MINIFS('Draft Board'!$BE$2:$BE$87,'Draft Board'!$BD$2:$BD$87,"="&BD73),0,IF(_xlfn.MINIFS('Draft Board'!$BD$2:$BD$87,'Draft Board'!$BD$2:$BD$87,">"&BD73)=0,1,IF((_xlfn.MINIFS('Draft Board'!$BD$2:$BD$87,'Draft Board'!$BD$2:$BD$87,">"&BD73)-BD73)/_xlfn.MINIFS('Draft Board'!$BD$2:$BD$87,'Draft Board'!$BD$2:$BD$87,">"&BD73)>0.08,1,0))) -> 0 | BG73: =_xlfn.MINIFS('Draft Board'!$BD$2:$BD$87,'Draft Board'!$BD$2:$BD$87,">="&BD73,'Draft Board'!$BF$2:$BF$87,1) -> 0 | BH73: =IF(BE73<>_xlfn.MINIFS('Draft Board'!$BE$2:$BE$87,'Draft Board'!$BD$2:$BD$87,"="&BD73),0,IF(OR(BF73=1,IFERROR(FLOOR((BG73-BD73)/BG73/0.25,1),0)<>IFERROR(FLOOR((BG73-_xlfn.MINIFS('Draft Board'!$BD$2:$BD$87,'Draft Board'!$BD$2:$BD$87,">"&BD73))/BG73/0.25,1),0)),1,0)) -> 0 | BI73: =ROUND(1+BD73*'Live Calc'!$D$29,0) -> 1 | BK73: =IF(BJ73<>"",BJ73,ROUND(BI73*INDEX('Live Calc'!$G$454:$G$539,MATCH(BC73,'Live Calc'!$A$454:$A$539,0))*'Live Calc'!$J$543,0)) -> 1
... Q87: Demond Claiborne | R87: MIN | S87: 30.4 | T87: 34.22 | U87: 38.102 | V87: =CHOOSE(MATCH(Setup!$B$7,{"STD","Half-PPR","PPR"},0),S87,T87,U87) -> 34.22 | W87: =COUNTIFS('Draft Board'!$X$2:$X$161,">="&X87,'Draft Board'!$AB$2:$AB$161,1) -> 14 | X87: =MAX(0,V87-'Live Calc'!$H$20)^'Live Calc'!$E$20 -> 0 | Y87: 87 | Z87: =IF(Y87<>_xlfn.MINIFS('Draft Board'!$Y$2:$Y$161,'Draft Board'!$X$2:$X$161,"="&X87),0,IF(_xlfn.MINIFS('Draft Board'!$X$2:$X$161,'Draft Board'!$X$2:$X$161,">"&X87)=0,1,IF((_xlfn.MINIFS('Draft Board'!$X$2:$X$161,'Draft Board'!$X$2:$X$161,">"&X87)-X87)/_xlfn.MINIFS('Draft Board'!$X$2:$X$161,'Draft Board'!$X$2:$X$161,">"&X87)>0.08,1,0))) -> 0 | AA87: =_xlfn.MINIFS('Draft Board'!$X$2:$X$161,'Draft Board'!$X$2:$X$161,">="&X87,'Draft Board'!$Z$2:$Z$161,1) -> 0 | AB87: =IF(Y87<>_xlfn.MINIFS('Draft Board'!$Y$2:$Y$161,'Draft Board'!$X$2:$X$161,"="&X87),0,IF(OR(Z87=1,IFERROR(FLOOR((AA87-X87)/AA87/0.25,1),0)<>IFERROR(FLOOR((AA87-_xlfn.MINIFS('Draft Board'!$X$2:$X$161,'Draft Board'!$X$2:$X$161,">"&X87))/AA87/0.25,1),0)),1,0)) -> 0 | AC87: =ROUND(1+X87*'Live Calc'!$D$27,0) -> 1 | AE87: =IF(AD87<>"",AD87,ROUND(AC87*INDEX('Live Calc'!$G$96:$G$255,MATCH(W87,'Live Calc'!$A$96:$A$255,0))*'Live Calc'!$J$543,0)) -> 1 | AG87: Dontayvion Wicks | AH87: PHI | AI87: 54.12 | AJ87: 69.144 | AK87: 85.858 | AL87: =CHOOSE(MATCH(Setup!$B$7,{"STD","Half-PPR","PPR"},0),AI87,AJ87,AK87) -> 69.144 | AM87: =COUNTIFS('Draft Board'!$AN$2:$AN$193,">="&AN87,'Draft Board'!$AR$2:$AR$193,1) -> 20 | AN87: =MAX(0,AL87-'Live Calc'!$H$21)^'Live Calc'!$E$21 -> 0 | AO87: 87 | AP87: =IF(AO87<>_xlfn.MINIFS('Draft Board'!$AO$2:$AO$193,'Draft Board'!$AN$2:$AN$193,"="&AN87),0,IF(_xlfn.MINIFS('Draft Board'!$AN$2:$AN$193,'Draft Board'!$AN$2:$AN$193,">"&AN87)=0,1,IF((_xlfn.MINIFS('Draft Board'!$AN$2:$AN$193,'Draft Board'!$AN$2:$AN$193,">"&AN87)-AN87)/_xlfn.MINIFS('Draft Board'!$AN$2:$AN$193,'Draft Board'!$AN$2:$AN$193,">"&AN87)>0.08,1,0))) -> 0 | AQ87: =_xlfn.MINIFS('Draft Board'!$AN$2:$AN$193,'Draft Board'!$AN$2:$AN$193,">="&AN87,'Draft Board'!$AP$2:$AP$193,1) -> 0 | AR87: =IF(AO87<>_xlfn.MINIFS('Draft Board'!$AO$2:$AO$193,'Draft Board'!$AN$2:$AN$193,"="&AN87),0,IF(OR(AP87=1,IFERROR(FLOOR((AQ87-AN87)/AQ87/0.25,1),0)<>IFERROR(FLOOR((AQ87-_xlfn.MINIFS('Draft Board'!$AN$2:$AN$193,'Draft Board'!$AN$2:$AN$193,">"&AN87))/AQ87/0.25,1),0)),1,0)) -> 0 | AS87: =ROUND(1+AN87*'Live Calc'!$D$28,0) -> 1 | AU87: =IF(AT87<>"",AT87,ROUND(AS87*INDEX('Live Calc'!$G$259:$G$450,MATCH(AM87,'Live Calc'!$A$259:$A$450,0))*'Live Calc'!$J$543,0)) -> 1 | AW87: Tanner Koziol | AX87: JAC | AY87: 14.2 | AZ87: 19.21 | BA87: 24.21 | BB87: =CHOOSE(MATCH(Setup!$B$7,{"STD","Half-PPR","PPR"},0),AY87,AZ87,BA87) -> 19.21 | BC87: =COUNTIFS('Draft Board'!$BD$2:$BD$87,">="&BD87,'Draft Board'!$BH$2:$BH$87,1) -> 15 | BD87: =MAX(0,BB87-'Live Calc'!$H$22)^'Live Calc'!$E$22 -> 0 | BE87: 87 | BF87: =IF(BE87<>_xlfn.MINIFS('Draft Board'!$BE$2:$BE$87,'Draft Board'!$BD$2:$BD$87,"="&BD87),0,IF(_xlfn.MINIFS('Draft Board'!$BD$2:$BD$87,'Draft Board'!$BD$2:$BD$87,">"&BD87)=0,1,IF((_xlfn.MINIFS('Draft Board'!$BD$2:$BD$87,'Draft Board'!$BD$2:$BD$87,">"&BD87)-BD87)/_xlfn.MINIFS('Draft Board'!$BD$2:$BD$87,'Draft Board'!$BD$2:$BD$87,">"&BD87)>0.08,1,0))) -> 0 | BG87: =_xlfn.MINIFS('Draft Board'!$BD$2:$BD$87,'Draft Board'!$BD$2:$BD$87,">="&BD87,'Draft Board'!$BF$2:$BF$87,1) -> 0 | BH87: =IF(BE87<>_xlfn.MINIFS('Draft Board'!$BE$2:$BE$87,'Draft Board'!$BD$2:$BD$87,"="&BD87),0,IF(OR(BF87=1,IFERROR(FLOOR((BG87-BD87)/BG87/0.25,1),0)<>IFERROR(FLOOR((BG87-_xlfn.MINIFS('Draft Board'!$BD$2:$BD$87,'Draft Board'!$BD$2:$BD$87,">"&BD87))/BG87/0.25,1),0)),1,0)) -> 0 | BI87: =ROUND(1+BD87*'Live Calc'!$D$29,0) -> 1 | BK87: =IF(BJ87<>"",BJ87,ROUND(BI87*INDEX('Live Calc'!$G$454:$G$539,MATCH(BC87,'Live Calc'!$A$454:$A$539,0))*'Live Calc'!$J$543,0)) -> 1
Q88: Joe Mixon | R88: FA | S88: 29.052 | T88: 33.836 | U88: 37.428 | V88: =CHOOSE(MATCH(Setup!$B$7,{"STD","Half-PPR","PPR"},0),S88,T88,U88) -> 33.836 | W88: =COUNTIFS('Draft Board'!$X$2:$X$161,">="&X88,'Draft Board'!$AB$2:$AB$161,1) -> 14 | X88: =MAX(0,V88-'Live Calc'!$H$20)^'Live Calc'!$E$20 -> 0 | Y88: 88 | Z88: =IF(Y88<>_xlfn.MINIFS('Draft Board'!$Y$2:$Y$161,'Draft Board'!$X$2:$X$161,"="&X88),0,IF(_xlfn.MINIFS('Draft Board'!$X$2:$X$161,'Draft Board'!$X$2:$X$161,">"&X88)=0,1,IF((_xlfn.MINIFS('Draft Board'!$X$2:$X$161,'Draft Board'!$X$2:$X$161,">"&X88)-X88)/_xlfn.MINIFS('Draft Board'!$X$2:$X$161,'Draft Board'!$X$2:$X$161,">"&X88)>0.08,1,0))) -> 0 | AA88: =_xlfn.MINIFS('Draft Board'!$X$2:$X$161,'Draft Board'!$X$2:$X$161,">="&X88,'Draft Board'!$Z$2:$Z$161,1) -> 0 | AB88: =IF(Y88<>_xlfn.MINIFS('Draft Board'!$Y$2:$Y$161,'Draft Board'!$X$2:$X$161,"="&X88),0,IF(OR(Z88=1,IFERROR(FLOOR((AA88-X88)/AA88/0.25,1),0)<>IFERROR(FLOOR((AA88-_xlfn.MINIFS('Draft Board'!$X$2:$X$161,'Draft Board'!$X$2:$X$161,">"&X88))/AA88/0.25,1),0)),1,0)) -> 0 | AC88: =ROUND(1+X88*'Live Calc'!$D$27,0) -> 1 | AE88: =IF(AD88<>"",AD88,ROUND(AC88*INDEX('Live Calc'!$G$96:$G$255,MATCH(W88,'Live Calc'!$A$96:$A$255,0))*'Live Calc'!$J$543,0)) -> 1 | AG88: Pat Bryant | AH88: DEN | AI88: 52.74 | AJ88: 69.112 | AK88: 85.336 | AL88: =CHOOSE(MATCH(Setup!$B$7,{"STD","Half-PPR","PPR"},0),AI88,AJ88,AK88) -> 69.112 | AM88: =COUNTIFS('Draft Board'!$AN$2:$AN$193,">="&AN88,'Draft Board'!$AR$2:$AR$193,1) -> 20 | AN88: =MAX(0,AL88-'Live Calc'!$H$21)^'Live Calc'!$E$21 -> 0 | AO88: 88 | AP88: =IF(AO88<>_xlfn.MINIFS('Draft Board'!$AO$2:$AO$193,'Draft Board'!$AN$2:$AN$193,"="&AN88),0,IF(_xlfn.MINIFS('Draft Board'!$AN$2:$AN$193,'Draft Board'!$AN$2:$AN$193,">"&AN88)=0,1,IF((_xlfn.MINIFS('Draft Board'!$AN$2:$AN$193,'Draft Board'!$AN$2:$AN$193,">"&AN88)-AN88)/_xlfn.MINIFS('Draft Board'!$AN$2:$AN$193,'Draft Board'!$AN$2:$AN$193,">"&AN88)>0.08,1,0))) -> 0 | AQ88: =_xlfn.MINIFS('Draft Board'!$AN$2:$AN$193,'Draft Board'!$AN$2:$AN$193,">="&AN88,'Draft Board'!$AP$2:$AP$193,1) -> 0 | AR88: =IF(AO88<>_xlfn.MINIFS('Draft Board'!$AO$2:$AO$193,'Draft Board'!$AN$2:$AN$193,"="&AN88),0,IF(OR(AP88=1,IFERROR(FLOOR((AQ88-AN88)/AQ88/0.25,1),0)<>IFERROR(FLOOR((AQ88-_xlfn.MINIFS('Draft Board'!$AN$2:$AN$193,'Draft Board'!$AN$2:$AN$193,">"&AN88))/AQ88/0.25,1),0)),1,0)) -> 0 | AS88: =ROUND(1+AN88*'Live Calc'!$D$28,0) -> 1 | AU88: =IF(AT88<>"",AT88,ROUND(AS88*INDEX('Live Calc'!$G$259:$G$450,MATCH(AM88,'Live Calc'!$A$259:$A$450,0))*'Live Calc'!$J$543,0)) -> 1
Q89: Kareem Hunt | R89: FA | S89: 30.282 | T89: 33.236 | U89: 36.196 | V89: =CHOOSE(MATCH(Setup!$B$7,{"STD","Half-PPR","PPR"},0),S89,T89,U89) -> 33.236 | W89: =COUNTIFS('Draft Board'!$X$2:$X$161,">="&X89,'Draft Board'!$AB$2:$AB$161,1) -> 14 | X89: =MAX(0,V89-'Live Calc'!$H$20)^'Live Calc'!$E$20 -> 0 | Y89: 89 | Z89: =IF(Y89<>_xlfn.MINIFS('Draft Board'!$Y$2:$Y$161,'Draft Board'!$X$2:$X$161,"="&X89),0,IF(_xlfn.MINIFS('Draft Board'!$X$2:$X$161,'Draft Board'!$X$2:$X$161,">"&X89)=0,1,IF((_xlfn.MINIFS('Draft Board'!$X$2:$X$161,'Draft Board'!$X$2:$X$161,">"&X89)-X89)/_xlfn.MINIFS('Draft Board'!$X$2:$X$161,'Draft Board'!$X$2:$X$161,">"&X89)>0.08,1,0))) -> 0 | AA89: =_xlfn.MINIFS('Draft Board'!$X$2:$X$161,'Draft Board'!$X$2:$X$161,">="&X89,'Draft Board'!$Z$2:$Z$161,1) -> 0 | AB89: =IF(Y89<>_xlfn.MINIFS('Draft Board'!$Y$2:$Y$161,'Draft Board'!$X$2:$X$161,"="&X89),0,IF(OR(Z89=1,IFERROR(FLOOR((AA89-X89)/AA89/0.25,1),0)<>IFERROR(FLOOR((AA89-_xlfn.MINIFS('Draft Board'!$X$2:$X$161,'Draft Board'!$X$2:$X$161,">"&X89))/AA89/0.25,1),0)),1,0)) -> 0 | AC89: =ROUND(1+X89*'Live Calc'!$D$27,0) -> 1 | AE89: =IF(AD89<>"",AD89,ROUND(AC89*INDEX('Live Calc'!$G$96:$G$255,MATCH(W89,'Live Calc'!$A$96:$A$255,0))*'Live Calc'!$J$543,0)) -> 1 | AG89: Darius Slayton | AH89: NYG | AI89: 54.18 | AJ89: 68.644 | AK89: 83.38 | AL89: =CHOOSE(MATCH(Setup!$B$7,{"STD","Half-PPR","PPR"},0),AI89,AJ89,AK89) -> 68.644 | AM89: =COUNTIFS('Draft Board'!$AN$2:$AN$193,">="&AN89,'Draft Board'!$AR$2:$AR$193,1) -> 20 | AN89: =MAX(0,AL89-'Live Calc'!$H$21)^'Live Calc'!$E$21 -> 0 | AO89: 89 | AP89: =IF(AO89<>_xlfn.MINIFS('Draft Board'!$AO$2:$AO$193,'Draft Board'!$AN$2:$AN$193,"="&AN89),0,IF(_xlfn.MINIFS('Draft Board'!$AN$2:$AN$193,'Draft Board'!$AN$2:$AN$193,">"&AN89)=0,1,IF((_xlfn.MINIFS('Draft Board'!$AN$2:$AN$193,'Draft Board'!$AN$2:$AN$193,">"&AN89)-AN89)/_xlfn.MINIFS('Draft Board'!$AN$2:$AN$193,'Draft Board'!$AN$2:$AN$193,">"&AN89)>0.08,1,0))) -> 0 | AQ89: =_xlfn.MINIFS('Draft Board'!$AN$2:$AN$193,'Draft Board'!$AN$2:$AN$193,">="&AN89,'Draft Board'!$AP$2:$AP$193,1) -> 0 | AR89: =IF(AO89<>_xlfn.MINIFS('Draft Board'!$AO$2:$AO$193,'Draft Board'!$AN$2:$AN$193,"="&AN89),0,IF(OR(AP89=1,IFERROR(FLOOR((AQ89-AN89)/AQ89/0.25,1),0)<>IFERROR(FLOOR((AQ89-_xlfn.MINIFS('Draft Board'!$AN$2:$AN$193,'Draft Board'!$AN$2:$AN$193,">"&AN89))/AQ89/0.25,1),0)),1,0)) -> 0 | AS89: =ROUND(1+AN89*'Live Calc'!$D$28,0) -> 1 | AU89: =IF(AT89<>"",AT89,ROUND(AS89*INDEX('Live Calc'!$G$259:$G$450,MATCH(AM89,'Live Calc'!$A$259:$A$450,0))*'Live Calc'!$J$543,0)) -> 1
Q90: Kyle Juszczyk | R90: SF | S90: 24.988 | T90: 32.238 | U90: 39.948 | V90: =CHOOSE(MATCH(Setup!$B$7,{"STD","Half-PPR","PPR"},0),S90,T90,U90) -> 32.238 | W90: =COUNTIFS('Draft Board'!$X$2:$X$161,">="&X90,'Draft Board'!$AB$2:$AB$161,1) -> 14 | X90: =MAX(0,V90-'Live Calc'!$H$20)^'Live Calc'!$E$20 -> 0 | Y90: 90 | Z90: =IF(Y90<>_xlfn.MINIFS('Draft Board'!$Y$2:$Y$161,'Draft Board'!$X$2:$X$161,"="&X90),0,IF(_xlfn.MINIFS('Draft Board'!$X$2:$X$161,'Draft Board'!$X$2:$X$161,">"&X90)=0,1,IF((_xlfn.MINIFS('Draft Board'!$X$2:$X$161,'Draft Board'!$X$2:$X$161,">"&X90)-X90)/_xlfn.MINIFS('Draft Board'!$X$2:$X$161,'Draft Board'!$X$2:$X$161,">"&X90)>0.08,1,0))) -> 0 | AA90: =_xlfn.MINIFS('Draft Board'!$X$2:$X$161,'Draft Board'!$X$2:$X$161,">="&X90,'Draft Board'!$Z$2:$Z$161,1) -> 0 | AB90: =IF(Y90<>_xlfn.MINIFS('Draft Board'!$Y$2:$Y$161,'Draft Board'!$X$2:$X$161,"="&X90),0,IF(OR(Z90=1,IFERROR(FLOOR((AA90-X90)/AA90/0.25,1),0)<>IFERROR(FLOOR((AA90-_xlfn.MINIFS('Draft Board'!$X$2:$X$161,'Draft Board'!$X$2:$X$161,">"&X90))/AA90/0.25,1),0)),1,0)) -> 0 | AC90: =ROUND(1+X90*'Live Calc'!$D$27,0) -> 1 | AE90: =IF(AD90<>"",AD90,ROUND(AC90*INDEX('Live Calc'!$G$96:$G$255,MATCH(W90,'Live Calc'!$A$96:$A$255,0))*'Live Calc'!$J$543,0)) -> 1 | AG90: Andrei Iosivas | AH90: CIN | AI90: 51.872 | AJ90: 66.408 | AK90: 80.186 | AL90: =CHOOSE(MATCH(Setup!$B$7,{"STD","Half-PPR","PPR"},0),AI90,AJ90,AK90) -> 66.408 | AM90: =COUNTIFS('Draft Board'!$AN$2:$AN$193,">="&AN90,'Draft Board'!$AR$2:$AR$193,1) -> 20 | AN90: =MAX(0,AL90-'Live Calc'!$H$21)^'Live Calc'!$E$21 -> 0 | AO90: 90 | AP90: =IF(AO90<>_xlfn.MINIFS('Draft Board'!$AO$2:$AO$193,'Draft Board'!$AN$2:$AN$193,"="&AN90),0,IF(_xlfn.MINIFS('Draft Board'!$AN$2:$AN$193,'Draft Board'!$AN$2:$AN$193,">"&AN90)=0,1,IF((_xlfn.MINIFS('Draft Board'!$AN$2:$AN$193,'Draft Board'!$AN$2:$AN$193,">"&AN90)-AN90)/_xlfn.MINIFS('Draft Board'!$AN$2:$AN$193,'Draft Board'!$AN$2:$AN$193,">"&AN90)>0.08,1,0))) -> 0 | AQ90: =_xlfn.MINIFS('Draft Board'!$AN$2:$AN$193,'Draft Board'!$AN$2:$AN$193,">="&AN90,'Draft Board'!$AP$2:$AP$193,1) -> 0 | AR90: =IF(AO90<>_xlfn.MINIFS('Draft Board'!$AO$2:$AO$193,'Draft Board'!$AN$2:$AN$193,"="&AN90),0,IF(OR(AP90=1,IFERROR(FLOOR((AQ90-AN90)/AQ90/0.25,1),0)<>IFERROR(FLOOR((AQ90-_xlfn.MINIFS('Draft Board'!$AN$2:$AN$193,'Draft Board'!$AN$2:$AN$193,">"&AN90))/AQ90/0.25,1),0)),1,0)) -> 0 | AS90: =ROUND(1+AN90*'Live Calc'!$D$28,0) -> 1 | AU90: =IF(AT90<>"",AT90,ROUND(AS90*INDEX('Live Calc'!$G$259:$G$450,MATCH(AM90,'Live Calc'!$A$259:$A$450,0))*'Live Calc'!$J$543,0)) -> 1
Q91: Kendre Miller | R91: NO | S91: 28.372 | T91: 31.06 | U91: 33.872 | V91: =CHOOSE(MATCH(Setup!$B$7,{"STD","Half-PPR","PPR"},0),S91,T91,U91) -> 31.06 | W91: =COUNTIFS('Draft Board'!$X$2:$X$161,">="&X91,'Draft Board'!$AB$2:$AB$161,1) -> 14 | X91: =MAX(0,V91-'Live Calc'!$H$20)^'Live Calc'!$E$20 -> 0 | Y91: 91 | Z91: =IF(Y91<>_xlfn.MINIFS('Draft Board'!$Y$2:$Y$161,'Draft Board'!$X$2:$X$161,"="&X91),0,IF(_xlfn.MINIFS('Draft Board'!$X$2:$X$161,'Draft Board'!$X$2:$X$161,">"&X91)=0,1,IF((_xlfn.MINIFS('Draft Board'!$X$2:$X$161,'Draft Board'!$X$2:$X$161,">"&X91)-X91)/_xlfn.MINIFS('Draft Board'!$X$2:$X$161,'Draft Board'!$X$2:$X$161,">"&X91)>0.08,1,0))) -> 0 | AA91: =_xlfn.MINIFS('Draft Board'!$X$2:$X$161,'Draft Board'!$X$2:$X$161,">="&X91,'Draft Board'!$Z$2:$Z$161,1) -> 0 | AB91: =IF(Y91<>_xlfn.MINIFS('Draft Board'!$Y$2:$Y$161,'Draft Board'!$X$2:$X$161,"="&X91),0,IF(OR(Z91=1,IFERROR(FLOOR((AA91-X91)/AA91/0.25,1),0)<>IFERROR(FLOOR((AA91-_xlfn.MINIFS('Draft Board'!$X$2:$X$161,'Draft Board'!$X$2:$X$161,">"&X91))/AA91/0.25,1),0)),1,0)) -> 0 | AC91: =ROUND(1+X91*'Live Calc'!$D$27,0) -> 1 | AE91: =IF(AD91<>"",AD91,ROUND(AC91*INDEX('Live Calc'!$G$96:$G$255,MATCH(W91,'Live Calc'!$A$96:$A$255,0))*'Live Calc'!$J$543,0)) -> 1 | AG91: Jack Bech | AH91: LV | AI91: 47.914 | AJ91: 65.346 | AK91: 83.172 | AL91: =CHOOSE(MATCH(Setup!$B$7,{"STD","Half-PPR","PPR"},0),AI91,AJ91,AK91) -> 65.346 | AM91: =COUNTIFS('Draft Board'!$AN$2:$AN$193,">="&AN91,'Draft Board'!$AR$2:$AR$193,1) -> 20 | AN91: =MAX(0,AL91-'Live Calc'!$H$21)^'Live Calc'!$E$21 -> 0 | AO91: 91 | AP91: =IF(AO91<>_xlfn.MINIFS('Draft Board'!$AO$2:$AO$193,'Draft Board'!$AN$2:$AN$193,"="&AN91),0,IF(_xlfn.MINIFS('Draft Board'!$AN$2:$AN$193,'Draft Board'!$AN$2:$AN$193,">"&AN91)=0,1,IF((_xlfn.MINIFS('Draft Board'!$AN$2:$AN$193,'Draft Board'!$AN$2:$AN$193,">"&AN91)-AN91)/_xlfn.MINIFS('Draft Board'!$AN$2:$AN$193,'Draft Board'!$AN$2:$AN$193,">"&AN91)>0.08,1,0))) -> 0 | AQ91: =_xlfn.MINIFS('Draft Board'!$AN$2:$AN$193,'Draft Board'!$AN$2:$AN$193,">="&AN91,'Draft Board'!$AP$2:$AP$193,1) -> 0 | AR91: =IF(AO91<>_xlfn.MINIFS('Draft Board'!$AO$2:$AO$193,'Draft Board'!$AN$2:$AN$193,"="&AN91),0,IF(OR(AP91=1,IFERROR(FLOOR((AQ91-AN91)/AQ91/0.25,1),0)<>IFERROR(FLOOR((AQ91-_xlfn.MINIFS('Draft Board'!$AN$2:$AN$193,'Draft Board'!$AN$2:$AN$193,">"&AN91))/AQ91/0.25,1),0)),1,0)) -> 0 | AS91: =ROUND(1+AN91*'Live Calc'!$D$28,0) -> 1 | AU91: =IF(AT91<>"",AT91,ROUND(AS91*INDEX('Live Calc'!$G$259:$G$450,MATCH(AM91,'Live Calc'!$A$259:$A$450,0))*'Live Calc'!$J$543,0)) -> 1
Q92: AJ Dillon | R92: CAR | S92: 28.09 | T92: 31.04 | U92: 33.99 | V92: =CHOOSE(MATCH(Setup!$B$7,{"STD","Half-PPR","PPR"},0),S92,T92,U92) -> 31.04 | W92: =COUNTIFS('Draft Board'!$X$2:$X$161,">="&X92,'Draft Board'!$AB$2:$AB$161,1) -> 14 | X92: =MAX(0,V92-'Live Calc'!$H$20)^'Live Calc'!$E$20 -> 0 | Y92: 92 | Z92: =IF(Y92<>_xlfn.MINIFS('Draft Board'!$Y$2:$Y$161,'Draft Board'!$X$2:$X$161,"="&X92),0,IF(_xlfn.MINIFS('Draft Board'!$X$2:$X$161,'Draft Board'!$X$2:$X$161,">"&X92)=0,1,IF((_xlfn.MINIFS('Draft Board'!$X$2:$X$161,'Draft Board'!$X$2:$X$161,">"&X92)-X92)/_xlfn.MINIFS('Draft Board'!$X$2:$X$161,'Draft Board'!$X$2:$X$161,">"&X92)>0.08,1,0))) -> 0 | AA92: =_xlfn.MINIFS('Draft Board'!$X$2:$X$161,'Draft Board'!$X$2:$X$161,">="&X92,'Draft Board'!$Z$2:$Z$161,1) -> 0 | AB92: =IF(Y92<>_xlfn.MINIFS('Draft Board'!$Y$2:$Y$161,'Draft Board'!$X$2:$X$161,"="&X92),0,IF(OR(Z92=1,IFERROR(FLOOR((AA92-X92)/AA92/0.25,1),0)<>IFERROR(FLOOR((AA92-_xlfn.MINIFS('Draft Board'!$X$2:$X$161,'Draft Board'!$X$2:$X$161,">"&X92))/AA92/0.25,1),0)),1,0)) -> 0 | AC92: =ROUND(1+X92*'Live Calc'!$D$27,0) -> 1 | AE92: =IF(AD92<>"",AD92,ROUND(AC92*INDEX('Live Calc'!$G$96:$G$255,MATCH(W92,'Live Calc'!$A$96:$A$255,0))*'Live Calc'!$J$543,0)) -> 1 | AG92: Zachariah Branch | AH92: ATL | AI92: 49.76 | AJ92: 65.132 | AK92: 80.578 | AL92: =CHOOSE(MATCH(Setup!$B$7,{"STD","Half-PPR","PPR"},0),AI92,AJ92,AK92) -> 65.132 | AM92: =COUNTIFS('Draft Board'!$AN$2:$AN$193,">="&AN92,'Draft Board'!$AR$2:$AR$193,1) -> 20 | AN92: =MAX(0,AL92-'Live Calc'!$H$21)^'Live Calc'!$E$21 -> 0 | AO92: 92 | AP92: =IF(AO92<>_xlfn.MINIFS('Draft Board'!$AO$2:$AO$193,'Draft Board'!$AN$2:$AN$193,"="&AN92),0,IF(_xlfn.MINIFS('Draft Board'!$AN$2:$AN$193,'Draft Board'!$AN$2:$AN$193,">"&AN92)=0,1,IF((_xlfn.MINIFS('Draft Board'!$AN$2:$AN$193,'Draft Board'!$AN$2:$AN$193,">"&AN92)-AN92)/_xlfn.MINIFS('Draft Board'!$AN$2:$AN$193,'Draft Board'!$AN$2:$AN$193,">"&AN92)>0.08,1,0))) -> 0 | AQ92: =_xlfn.MINIFS('Draft Board'!$AN$2:$AN$193,'Draft Board'!$AN$2:$AN$193,">="&AN92,'Draft Board'!$AP$2:$AP$193,1) -> 0 | AR92: =IF(AO92<>_xlfn.MINIFS('Draft Board'!$AO$2:$AO$193,'Draft Board'!$AN$2:$AN$193,"="&AN92),0,IF(OR(AP92=1,IFERROR(FLOOR((AQ92-AN92)/AQ92/0.25,1),0)<>IFERROR(FLOOR((AQ92-_xlfn.MINIFS('Draft Board'!$AN$2:$AN$193,'Draft Board'!$AN$2:$AN$193,">"&AN92))/AQ92/0.25,1),0)),1,0)) -> 0 | AS92: =ROUND(1+AN92*'Live Calc'!$D$28,0) -> 1 | AU92: =IF(AT92<>"",AT92,ROUND(AS92*INDEX('Live Calc'!$G$259:$G$450,MATCH(AM92,'Live Calc'!$A$259:$A$450,0))*'Live Calc'!$J$543,0)) -> 1
Q93: Austin Ekeler | R93: WAS | S93: 25.388 | T93: 29.796 | U93: 34.54 | V93: =CHOOSE(MATCH(Setup!$B$7,{"STD","Half-PPR","PPR"},0),S93,T93,U93) -> 29.796 | W93: =COUNTIFS('Draft Board'!$X$2:$X$161,">="&X93,'Draft Board'!$AB$2:$AB$161,1) -> 14 | X93: =MAX(0,V93-'Live Calc'!$H$20)^'Live Calc'!$E$20 -> 0 | Y93: 93 | Z93: =IF(Y93<>_xlfn.MINIFS('Draft Board'!$Y$2:$Y$161,'Draft Board'!$X$2:$X$161,"="&X93),0,IF(_xlfn.MINIFS('Draft Board'!$X$2:$X$161,'Draft Board'!$X$2:$X$161,">"&X93)=0,1,IF((_xlfn.MINIFS('Draft Board'!$X$2:$X$161,'Draft Board'!$X$2:$X$161,">"&X93)-X93)/_xlfn.MINIFS('Draft Board'!$X$2:$X$161,'Draft Board'!$X$2:$X$161,">"&X93)>0.08,1,0))) -> 0 | AA93: =_xlfn.MINIFS('Draft Board'!$X$2:$X$161,'Draft Board'!$X$2:$X$161,">="&X93,'Draft Board'!$Z$2:$Z$161,1) -> 0 | AB93: =IF(Y93<>_xlfn.MINIFS('Draft Board'!$Y$2:$Y$161,'Draft Board'!$X$2:$X$161,"="&X93),0,IF(OR(Z93=1,IFERROR(FLOOR((AA93-X93)/AA93/0.25,1),0)<>IFERROR(FLOOR((AA93-_xlfn.MINIFS('Draft Board'!$X$2:$X$161,'Draft Board'!$X$2:$X$161,">"&X93))/AA93/0.25,1),0)),1,0)) -> 0 | AC93: =ROUND(1+X93*'Live Calc'!$D$27,0) -> 1 | AE93: =IF(AD93<>"",AD93,ROUND(AC93*INDEX('Live Calc'!$G$96:$G$255,MATCH(W93,'Live Calc'!$A$96:$A$255,0))*'Live Calc'!$J$543,0)) -> 1 | AG93: Tyreek Hill | AH93: FA | AI93: 50.924 | AJ93: 65.118 | AK93: 78.89 | AL93: =CHOOSE(MATCH(Setup!$B$7,{"STD","Half-PPR","PPR"},0),AI93,AJ93,AK93) -> 65.118 | AM93: =COUNTIFS('Draft Board'!$AN$2:$AN$193,">="&AN93,'Draft Board'!$AR$2:$AR$193,1) -> 20 | AN93: =MAX(0,AL93-'Live Calc'!$H$21)^'Live Calc'!$E$21 -> 0 | AO93: 93 | AP93: =IF(AO93<>_xlfn.MINIFS('Draft Board'!$AO$2:$AO$193,'Draft Board'!$AN$2:$AN$193,"="&AN93),0,IF(_xlfn.MINIFS('Draft Board'!$AN$2:$AN$193,'Draft Board'!$AN$2:$AN$193,">"&AN93)=0,1,IF((_xlfn.MINIFS('Draft Board'!$AN$2:$AN$193,'Draft Board'!$AN$2:$AN$193,">"&AN93)-AN93)/_xlfn.MINIFS('Draft Board'!$AN$2:$AN$193,'Draft Board'!$AN$2:$AN$193,">"&AN93)>0.08,1,0))) -> 0 | AQ93: =_xlfn.MINIFS('Draft Board'!$AN$2:$AN$193,'Draft Board'!$AN$2:$AN$193,">="&AN93,'Draft Board'!$AP$2:$AP$193,1) -> 0 | AR93: =IF(AO93<>_xlfn.MINIFS('Draft Board'!$AO$2:$AO$193,'Draft Board'!$AN$2:$AN$193,"="&AN93),0,IF(OR(AP93=1,IFERROR(FLOOR((AQ93-AN93)/AQ93/0.25,1),0)<>IFERROR(FLOOR((AQ93-_xlfn.MINIFS('Draft Board'!$AN$2:$AN$193,'Draft Board'!$AN$2:$AN$193,">"&AN93))/AQ93/0.25,1),0)),1,0)) -> 0 | AS93: =ROUND(1+AN93*'Live Calc'!$D$28,0) -> 1 | AU93: =IF(AT93<>"",AT93,ROUND(AS93*INDEX('Live Calc'!$G$259:$G$450,MATCH(AM93,'Live Calc'!$A$259:$A$450,0))*'Live Calc'!$J$543,0)) -> 1
Q94: Antonio Gibson | R94: FA | S94: 23.914 | T94: 27.66 | U94: 31.29 | V94: =CHOOSE(MATCH(Setup!$B$7,{"STD","Half-PPR","PPR"},0),S94,T94,U94) -> 27.66 | W94: =COUNTIFS('Draft Board'!$X$2:$X$161,">="&X94,'Draft Board'!$AB$2:$AB$161,1) -> 14 | X94: =MAX(0,V94-'Live Calc'!$H$20)^'Live Calc'!$E$20 -> 0 | Y94: 94 | Z94: =IF(Y94<>_xlfn.MINIFS('Draft Board'!$Y$2:$Y$161,'Draft Board'!$X$2:$X$161,"="&X94),0,IF(_xlfn.MINIFS('Draft Board'!$X$2:$X$161,'Draft Board'!$X$2:$X$161,">"&X94)=0,1,IF((_xlfn.MINIFS('Draft Board'!$X$2:$X$161,'Draft Board'!$X$2:$X$161,">"&X94)-X94)/_xlfn.MINIFS('Draft Board'!$X$2:$X$161,'Draft Board'!$X$2:$X$161,">"&X94)>0.08,1,0))) -> 0 | AA94: =_xlfn.MINIFS('Draft Board'!$X$2:$X$161,'Draft Board'!$X$2:$X$161,">="&X94,'Draft Board'!$Z$2:$Z$161,1) -> 0 | AB94: =IF(Y94<>_xlfn.MINIFS('Draft Board'!$Y$2:$Y$161,'Draft Board'!$X$2:$X$161,"="&X94),0,IF(OR(Z94=1,IFERROR(FLOOR((AA94-X94)/AA94/0.25,1),0)<>IFERROR(FLOOR((AA94-_xlfn.MINIFS('Draft Board'!$X$2:$X$161,'Draft Board'!$X$2:$X$161,">"&X94))/AA94/0.25,1),0)),1,0)) -> 0 | AC94: =ROUND(1+X94*'Live Calc'!$D$27,0) -> 1 | AE94: =IF(AD94<>"",AD94,ROUND(AC94*INDEX('Live Calc'!$G$96:$G$255,MATCH(W94,'Live Calc'!$A$96:$A$255,0))*'Live Calc'!$J$543,0)) -> 1 | AG94: Christian Kirk | AH94: SF | AI94: 48.124 | AJ94: 63.868 | AK94: 79.332 | AL94: =CHOOSE(MATCH(Setup!$B$7,{"STD","Half-PPR","PPR"},0),AI94,AJ94,AK94) -> 63.868 | AM94: =COUNTIFS('Draft Board'!$AN$2:$AN$193,">="&AN94,'Draft Board'!$AR$2:$AR$193,1) -> 20 | AN94: =MAX(0,AL94-'Live Calc'!$H$21)^'Live Calc'!$E$21 -> 0 | AO94: 94 | AP94: =IF(AO94<>_xlfn.MINIFS('Draft Board'!$AO$2:$AO$193,'Draft Board'!$AN$2:$AN$193,"="&AN94),0,IF(_xlfn.MINIFS('Draft Board'!$AN$2:$AN$193,'Draft Board'!$AN$2:$AN$193,">"&AN94)=0,1,IF((_xlfn.MINIFS('Draft Board'!$AN$2:$AN$193,'Draft Board'!$AN$2:$AN$193,">"&AN94)-AN94)/_xlfn.MINIFS('Draft Board'!$AN$2:$AN$193,'Draft Board'!$AN$2:$AN$193,">"&AN94)>0.08,1,0))) -> 0 | AQ94: =_xlfn.MINIFS('Draft Board'!$AN$2:$AN$193,'Draft Board'!$AN$2:$AN$193,">="&AN94,'Draft Board'!$AP$2:$AP$193,1) -> 0 | AR94: =IF(AO94<>_xlfn.MINIFS('Draft Board'!$AO$2:$AO$193,'Draft Board'!$AN$2:$AN$193,"="&AN94),0,IF(OR(AP94=1,IFERROR(FLOOR((AQ94-AN94)/AQ94/0.25,1),0)<>IFERROR(FLOOR((AQ94-_xlfn.MINIFS('Draft Board'!$AN$2:$AN$193,'Draft Board'!$AN$2:$AN$193,">"&AN94))/AQ94/0.25,1),0)),1,0)) -> 0 | AS94: =ROUND(1+AN94*'Live Calc'!$D$28,0) -> 1 | AU94: =IF(AT94<>"",AT94,ROUND(AS94*INDEX('Live Calc'!$G$259:$G$450,MATCH(AM94,'Live Calc'!$A$259:$A$450,0))*'Live Calc'!$J$543,0)) -> 1
Q95: Trey Benson | R95: ARI | S95: 23.308 | T95: 26.856 | U95: 30.162 | V95: =CHOOSE(MATCH(Setup!$B$7,{"STD","Half-PPR","PPR"},0),S95,T95,U95) -> 26.856 | W95: =COUNTIFS('Draft Board'!$X$2:$X$161,">="&X95,'Draft Board'!$AB$2:$AB$161,1) -> 14 | X95: =MAX(0,V95-'Live Calc'!$H$20)^'Live Calc'!$E$20 -> 0 | Y95: 95 | Z95: =IF(Y95<>_xlfn.MINIFS('Draft Board'!$Y$2:$Y$161,'Draft Board'!$X$2:$X$161,"="&X95),0,IF(_xlfn.MINIFS('Draft Board'!$X$2:$X$161,'Draft Board'!$X$2:$X$161,">"&X95)=0,1,IF((_xlfn.MINIFS('Draft Board'!$X$2:$X$161,'Draft Board'!$X$2:$X$161,">"&X95)-X95)/_xlfn.MINIFS('Draft Board'!$X$2:$X$161,'Draft Board'!$X$2:$X$161,">"&X95)>0.08,1,0))) -> 0 | AA95: =_xlfn.MINIFS('Draft Board'!$X$2:$X$161,'Draft Board'!$X$2:$X$161,">="&X95,'Draft Board'!$Z$2:$Z$161,1) -> 0 | AB95: =IF(Y95<>_xlfn.MINIFS('Draft Board'!$Y$2:$Y$161,'Draft Board'!$X$2:$X$161,"="&X95),0,IF(OR(Z95=1,IFERROR(FLOOR((AA95-X95)/AA95/0.25,1),0)<>IFERROR(FLOOR((AA95-_xlfn.MINIFS('Draft Board'!$X$2:$X$161,'Draft Board'!$X$2:$X$161,">"&X95))/AA95/0.25,1),0)),1,0)) -> 0 | AC95: =ROUND(1+X95*'Live Calc'!$D$27,0) -> 1 | AE95: =IF(AD95<>"",AD95,ROUND(AC95*INDEX('Live Calc'!$G$96:$G$255,MATCH(W95,'Live Calc'!$A$96:$A$255,0))*'Live Calc'!$J$543,0)) -> 1 | AG95: Chris Bell | AH95: MIA | AI95: 48.748 | AJ95: 63.592 | AK95: 78.746 | AL95: =CHOOSE(MATCH(Setup!$B$7,{"STD","Half-PPR","PPR"},0),AI95,AJ95,AK95) -> 63.592 | AM95: =COUNTIFS('Draft Board'!$AN$2:$AN$193,">="&AN95,'Draft Board'!$AR$2:$AR$193,1) -> 20 | AN95: =MAX(0,AL95-'Live Calc'!$H$21)^'Live Calc'!$E$21 -> 0 | AO95: 95 | AP95: =IF(AO95<>_xlfn.MINIFS('Draft Board'!$AO$2:$AO$193,'Draft Board'!$AN$2:$AN$193,"="&AN95),0,IF(_xlfn.MINIFS('Draft Board'!$AN$2:$AN$193,'Draft Board'!$AN$2:$AN$193,">"&AN95)=0,1,IF((_xlfn.MINIFS('Draft Board'!$AN$2:$AN$193,'Draft Board'!$AN$2:$AN$193,">"&AN95)-AN95)/_xlfn.MINIFS('Draft Board'!$AN$2:$AN$193,'Draft Board'!$AN$2:$AN$193,">"&AN95)>0.08,1,0))) -> 0 | AQ95: =_xlfn.MINIFS('Draft Board'!$AN$2:$AN$193,'Draft Board'!$AN$2:$AN$193,">="&AN95,'Draft Board'!$AP$2:$AP$193,1) -> 0 | AR95: =IF(AO95<>_xlfn.MINIFS('Draft Board'!$AO$2:$AO$193,'Draft Board'!$AN$2:$AN$193,"="&AN95),0,IF(OR(AP95=1,IFERROR(FLOOR((AQ95-AN95)/AQ95/0.25,1),0)<>IFERROR(FLOOR((AQ95-_xlfn.MINIFS('Draft Board'!$AN$2:$AN$193,'Draft Board'!$AN$2:$AN$193,">"&AN95))/AQ95/0.25,1),0)),1,0)) -> 0 | AS95: =ROUND(1+AN95*'Live Calc'!$D$28,0) -> 1 | AU95: =IF(AT95<>"",AT95,ROUND(AS95*INDEX('Live Calc'!$G$259:$G$450,MATCH(AM95,'Live Calc'!$A$259:$A$450,0))*'Live Calc'!$J$543,0)) -> 1
Q96: Jerome Ford | R96: WAS | S96: 21.612 | T96: 25.81 | U96: 27.776 | V96: =CHOOSE(MATCH(Setup!$B$7,{"STD","Half-PPR","PPR"},0),S96,T96,U96) -> 25.81 | W96: =COUNTIFS('Draft Board'!$X$2:$X$161,">="&X96,'Draft Board'!$AB$2:$AB$161,1) -> 14 | X96: =MAX(0,V96-'Live Calc'!$H$20)^'Live Calc'!$E$20 -> 0 | Y96: 96 | Z96: =IF(Y96<>_xlfn.MINIFS('Draft Board'!$Y$2:$Y$161,'Draft Board'!$X$2:$X$161,"="&X96),0,IF(_xlfn.MINIFS('Draft Board'!$X$2:$X$161,'Draft Board'!$X$2:$X$161,">"&X96)=0,1,IF((_xlfn.MINIFS('Draft Board'!$X$2:$X$161,'Draft Board'!$X$2:$X$161,">"&X96)-X96)/_xlfn.MINIFS('Draft Board'!$X$2:$X$161,'Draft Board'!$X$2:$X$161,">"&X96)>0.08,1,0))) -> 0 | AA96: =_xlfn.MINIFS('Draft Board'!$X$2:$X$161,'Draft Board'!$X$2:$X$161,">="&X96,'Draft Board'!$Z$2:$Z$161,1) -> 0 | AB96: =IF(Y96<>_xlfn.MINIFS('Draft Board'!$Y$2:$Y$161,'Draft Board'!$X$2:$X$161,"="&X96),0,IF(OR(Z96=1,IFERROR(FLOOR((AA96-X96)/AA96/0.25,1),0)<>IFERROR(FLOOR((AA96-_xlfn.MINIFS('Draft Board'!$X$2:$X$161,'Draft Board'!$X$2:$X$161,">"&X96))/AA96/0.25,1),0)),1,0)) -> 0 | AC96: =ROUND(1+X96*'Live Calc'!$D$27,0) -> 1 | AE96: =IF(AD96<>"",AD96,ROUND(AC96*INDEX('Live Calc'!$G$96:$G$255,MATCH(W96,'Live Calc'!$A$96:$A$255,0))*'Live Calc'!$J$543,0)) -> 1 | AG96: Devaughn Vele | AH96: NO | AI96: 48.548 | AJ96: 63.504 | AK96: 78.51 | AL96: =CHOOSE(MATCH(Setup!$B$7,{"STD","Half-PPR","PPR"},0),AI96,AJ96,AK96) -> 63.504 | AM96: =COUNTIFS('Draft Board'!$AN$2:$AN$193,">="&AN96,'Draft Board'!$AR$2:$AR$193,1) -> 20 | AN96: =MAX(0,AL96-'Live Calc'!$H$21)^'Live Calc'!$E$21 -> 0 | AO96: 96 | AP96: =IF(AO96<>_xlfn.MINIFS('Draft Board'!$AO$2:$AO$193,'Draft Board'!$AN$2:$AN$193,"="&AN96),0,IF(_xlfn.MINIFS('Draft Board'!$AN$2:$AN$193,'Draft Board'!$AN$2:$AN$193,">"&AN96)=0,1,IF((_xlfn.MINIFS('Draft Board'!$AN$2:$AN$193,'Draft Board'!$AN$2:$AN$193,">"&AN96)-AN96)/_xlfn.MINIFS('Draft Board'!$AN$2:$AN$193,'Draft Board'!$AN$2:$AN$193,">"&AN96)>0.08,1,0))) -> 0 | AQ96: =_xlfn.MINIFS('Draft Board'!$AN$2:$AN$193,'Draft Board'!$AN$2:$AN$193,">="&AN96,'Draft Board'!$AP$2:$AP$193,1) -> 0 | AR96: =IF(AO96<>_xlfn.MINIFS('Draft Board'!$AO$2:$AO$193,'Draft Board'!$AN$2:$AN$193,"="&AN96),0,IF(OR(AP96=1,IFERROR(FLOOR((AQ96-AN96)/AQ96/0.25,1),0)<>IFERROR(FLOOR((AQ96-_xlfn.MINIFS('Draft Board'!$AN$2:$AN$193,'Draft Board'!$AN$2:$AN$193,">"&AN96))/AQ96/0.25,1),0)),1,0)) -> 0 | AS96: =ROUND(1+AN96*'Live Calc'!$D$28,0) -> 1 | AU96: =IF(AT96<>"",AT96,ROUND(AS96*INDEX('Live Calc'!$G$259:$G$450,MATCH(AM96,'Live Calc'!$A$259:$A$450,0))*'Live Calc'!$J$543,0)) -> 1
Q97: Kaleb Johnson | R97: PIT | S97: 23.07 | T97: 25.306 | U97: 27.484 | V97: =CHOOSE(MATCH(Setup!$B$7,{"STD","Half-PPR","PPR"},0),S97,T97,U97) -> 25.306 | W97: =COUNTIFS('Draft Board'!$X$2:$X$161,">="&X97,'Draft Board'!$AB$2:$AB$161,1) -> 14 | X97: =MAX(0,V97-'Live Calc'!$H$20)^'Live Calc'!$E$20 -> 0 | Y97: 97 | Z97: =IF(Y97<>_xlfn.MINIFS('Draft Board'!$Y$2:$Y$161,'Draft Board'!$X$2:$X$161,"="&X97),0,IF(_xlfn.MINIFS('Draft Board'!$X$2:$X$161,'Draft Board'!$X$2:$X$161,">"&X97)=0,1,IF((_xlfn.MINIFS('Draft Board'!$X$2:$X$161,'Draft Board'!$X$2:$X$161,">"&X97)-X97)/_xlfn.MINIFS('Draft Board'!$X$2:$X$161,'Draft Board'!$X$2:$X$161,">"&X97)>0.08,1,0))) -> 0 | AA97: =_xlfn.MINIFS('Draft Board'!$X$2:$X$161,'Draft Board'!$X$2:$X$161,">="&X97,'Draft Board'!$Z$2:$Z$161,1) -> 0 | AB97: =IF(Y97<>_xlfn.MINIFS('Draft Board'!$Y$2:$Y$161,'Draft Board'!$X$2:$X$161,"="&X97),0,IF(OR(Z97=1,IFERROR(FLOOR((AA97-X97)/AA97/0.25,1),0)<>IFERROR(FLOOR((AA97-_xlfn.MINIFS('Draft Board'!$X$2:$X$161,'Draft Board'!$X$2:$X$161,">"&X97))/AA97/0.25,1),0)),1,0)) -> 0 | AC97: =ROUND(1+X97*'Live Calc'!$D$27,0) -> 1 | AE97: =IF(AD97<>"",AD97,ROUND(AC97*INDEX('Live Calc'!$G$96:$G$255,MATCH(W97,'Live Calc'!$A$96:$A$255,0))*'Live Calc'!$J$543,0)) -> 1 | AG97: Marquise Brown | AH97: PHI | AI97: 48.75 | AJ97: 62.53 | AK97: 76.3 | AL97: =CHOOSE(MATCH(Setup!$B$7,{"STD","Half-PPR","PPR"},0),AI97,AJ97,AK97) -> 62.53 | AM97: =COUNTIFS('Draft Board'!$AN$2:$AN$193,">="&AN97,'Draft Board'!$AR$2:$AR$193,1) -> 20 | AN97: =MAX(0,AL97-'Live Calc'!$H$21)^'Live Calc'!$E$21 -> 0 | AO97: 97 | AP97: =IF(AO97<>_xlfn.MINIFS('Draft Board'!$AO$2:$AO$193,'Draft Board'!$AN$2:$AN$193,"="&AN97),0,IF(_xlfn.MINIFS('Draft Board'!$AN$2:$AN$193,'Draft Board'!$AN$2:$AN$193,">"&AN97)=0,1,IF((_xlfn.MINIFS('Draft Board'!$AN$2:$AN$193,'Draft Board'!$AN$2:$AN$193,">"&AN97)-AN97)/_xlfn.MINIFS('Draft Board'!$AN$2:$AN$193,'Draft Board'!$AN$2:$AN$193,">"&AN97)>0.08,1,0))) -> 0 | AQ97: =_xlfn.MINIFS('Draft Board'!$AN$2:$AN$193,'Draft Board'!$AN$2:$AN$193,">="&AN97,'Draft Board'!$AP$2:$AP$193,1) -> 0 | AR97: =IF(AO97<>_xlfn.MINIFS('Draft Board'!$AO$2:$AO$193,'Draft Board'!$AN$2:$AN$193,"="&AN97),0,IF(OR(AP97=1,IFERROR(FLOOR((AQ97-AN97)/AQ97/0.25,1),0)<>IFERROR(FLOOR((AQ97-_xlfn.MINIFS('Draft Board'!$AN$2:$AN$193,'Draft Board'!$AN$2:$AN$193,">"&AN97))/AQ97/0.25,1),0)),1,0)) -> 0 | AS97: =ROUND(1+AN97*'Live Calc'!$D$28,0) -> 1 | AU97: =IF(AT97<>"",AT97,ROUND(AS97*INDEX('Live Calc'!$G$259:$G$450,MATCH(AM97,'Live Calc'!$A$259:$A$450,0))*'Live Calc'!$J$543,0)) -> 1
Q98: Devin Neal | R98: NO | S98: 22.09 | T98: 25.27 | U98: 29.218 | V98: =CHOOSE(MATCH(Setup!$B$7,{"STD","Half-PPR","PPR"},0),S98,T98,U98) -> 25.27 | W98: =COUNTIFS('Draft Board'!$X$2:$X$161,">="&X98,'Draft Board'!$AB$2:$AB$161,1) -> 14 | X98: =MAX(0,V98-'Live Calc'!$H$20)^'Live Calc'!$E$20 -> 0 | Y98: 98 | Z98: =IF(Y98<>_xlfn.MINIFS('Draft Board'!$Y$2:$Y$161,'Draft Board'!$X$2:$X$161,"="&X98),0,IF(_xlfn.MINIFS('Draft Board'!$X$2:$X$161,'Draft Board'!$X$2:$X$161,">"&X98)=0,1,IF((_xlfn.MINIFS('Draft Board'!$X$2:$X$161,'Draft Board'!$X$2:$X$161,">"&X98)-X98)/_xlfn.MINIFS('Draft Board'!$X$2:$X$161,'Draft Board'!$X$2:$X$161,">"&X98)>0.08,1,0))) -> 0 | AA98: =_xlfn.MINIFS('Draft Board'!$X$2:$X$161,'Draft Board'!$X$2:$X$161,">="&X98,'Draft Board'!$Z$2:$Z$161,1) -> 0 | AB98: =IF(Y98<>_xlfn.MINIFS('Draft Board'!$Y$2:$Y$161,'Draft Board'!$X$2:$X$161,"="&X98),0,IF(OR(Z98=1,IFERROR(FLOOR((AA98-X98)/AA98/0.25,1),0)<>IFERROR(FLOOR((AA98-_xlfn.MINIFS('Draft Board'!$X$2:$X$161,'Draft Board'!$X$2:$X$161,">"&X98))/AA98/0.25,1),0)),1,0)) -> 0 | AC98: =ROUND(1+X98*'Live Calc'!$D$27,0) -> 1 | AE98: =IF(AD98<>"",AD98,ROUND(AC98*INDEX('Live Calc'!$G$96:$G$255,MATCH(W98,'Live Calc'!$A$96:$A$255,0))*'Live Calc'!$J$543,0)) -> 1 | AG98: Elijah Sarratt | AH98: BAL | AI98: 48.532 | AJ98: 61.408 | AK98: 74.15 | AL98: =CHOOSE(MATCH(Setup!$B$7,{"STD","Half-PPR","PPR"},0),AI98,AJ98,AK98) -> 61.408 | AM98: =COUNTIFS('Draft Board'!$AN$2:$AN$193,">="&AN98,'Draft Board'!$AR$2:$AR$193,1) -> 20 | AN98: =MAX(0,AL98-'Live Calc'!$H$21)^'Live Calc'!$E$21 -> 0 | AO98: 98 | AP98: =IF(AO98<>_xlfn.MINIFS('Draft Board'!$AO$2:$AO$193,'Draft Board'!$AN$2:$AN$193,"="&AN98),0,IF(_xlfn.MINIFS('Draft Board'!$AN$2:$AN$193,'Draft Board'!$AN$2:$AN$193,">"&AN98)=0,1,IF((_xlfn.MINIFS('Draft Board'!$AN$2:$AN$193,'Draft Board'!$AN$2:$AN$193,">"&AN98)-AN98)/_xlfn.MINIFS('Draft Board'!$AN$2:$AN$193,'Draft Board'!$AN$2:$AN$193,">"&AN98)>0.08,1,0))) -> 0 | AQ98: =_xlfn.MINIFS('Draft Board'!$AN$2:$AN$193,'Draft Board'!$AN$2:$AN$193,">="&AN98,'Draft Board'!$AP$2:$AP$193,1) -> 0 | AR98: =IF(AO98<>_xlfn.MINIFS('Draft Board'!$AO$2:$AO$193,'Draft Board'!$AN$2:$AN$193,"="&AN98),0,IF(OR(AP98=1,IFERROR(FLOOR((AQ98-AN98)/AQ98/0.25,1),0)<>IFERROR(FLOOR((AQ98-_xlfn.MINIFS('Draft Board'!$AN$2:$AN$193,'Draft Board'!$AN$2:$AN$193,">"&AN98))/AQ98/0.25,1),0)),1,0)) -> 0 | AS98: =ROUND(1+AN98*'Live Calc'!$D$28,0) -> 1 | AU98: =IF(AT98<>"",AT98,ROUND(AS98*INDEX('Live Calc'!$G$259:$G$450,MATCH(AM98,'Live Calc'!$A$259:$A$450,0))*'Live Calc'!$J$543,0)) -> 1
Q99: Jawhar Jordan | R99: HOU | S99: 21.744 | T99: 24.698 | U99: 27.448 | V99: =CHOOSE(MATCH(Setup!$B$7,{"STD","Half-PPR","PPR"},0),S99,T99,U99) -> 24.698 | W99: =COUNTIFS('Draft Board'!$X$2:$X$161,">="&X99,'Draft Board'!$AB$2:$AB$161,1) -> 14 | X99: =MAX(0,V99-'Live Calc'!$H$20)^'Live Calc'!$E$20 -> 0 | Y99: 99 | Z99: =IF(Y99<>_xlfn.MINIFS('Draft Board'!$Y$2:$Y$161,'Draft Board'!$X$2:$X$161,"="&X99),0,IF(_xlfn.MINIFS('Draft Board'!$X$2:$X$161,'Draft Board'!$X$2:$X$161,">"&X99)=0,1,IF((_xlfn.MINIFS('Draft Board'!$X$2:$X$161,'Draft Board'!$X$2:$X$161,">"&X99)-X99)/_xlfn.MINIFS('Draft Board'!$X$2:$X$161,'Draft Board'!$X$2:$X$161,">"&X99)>0.08,1,0))) -> 0 | AA99: =_xlfn.MINIFS('Draft Board'!$X$2:$X$161,'Draft Board'!$X$2:$X$161,">="&X99,'Draft Board'!$Z$2:$Z$161,1) -> 0 | AB99: =IF(Y99<>_xlfn.MINIFS('Draft Board'!$Y$2:$Y$161,'Draft Board'!$X$2:$X$161,"="&X99),0,IF(OR(Z99=1,IFERROR(FLOOR((AA99-X99)/AA99/0.25,1),0)<>IFERROR(FLOOR((AA99-_xlfn.MINIFS('Draft Board'!$X$2:$X$161,'Draft Board'!$X$2:$X$161,">"&X99))/AA99/0.25,1),0)),1,0)) -> 0 | AC99: =ROUND(1+X99*'Live Calc'!$D$27,0) -> 1 | AE99: =IF(AD99<>"",AD99,ROUND(AC99*INDEX('Live Calc'!$G$96:$G$255,MATCH(W99,'Live Calc'!$A$96:$A$255,0))*'Live Calc'!$J$543,0)) -> 1 | AG99: Tory Horton | AH99: SEA | AI99: 46.634 | AJ99: 58.72 | AK99: 70.462 | AL99: =CHOOSE(MATCH(Setup!$B$7,{"STD","Half-PPR","PPR"},0),AI99,AJ99,AK99) -> 58.72 | AM99: =COUNTIFS('Draft Board'!$AN$2:$AN$193,">="&AN99,'Draft Board'!$AR$2:$AR$193,1) -> 20 | AN99: =MAX(0,AL99-'Live Calc'!$H$21)^'Live Calc'!$E$21 -> 0 | AO99: 99 | AP99: =IF(AO99<>_xlfn.MINIFS('Draft Board'!$AO$2:$AO$193,'Draft Board'!$AN$2:$AN$193,"="&AN99),0,IF(_xlfn.MINIFS('Draft Board'!$AN$2:$AN$193,'Draft Board'!$AN$2:$AN$193,">"&AN99)=0,1,IF((_xlfn.MINIFS('Draft Board'!$AN$2:$AN$193,'Draft Board'!$AN$2:$AN$193,">"&AN99)-AN99)/_xlfn.MINIFS('Draft Board'!$AN$2:$AN$193,'Draft Board'!$AN$2:$AN$193,">"&AN99)>0.08,1,0))) -> 0 | AQ99: =_xlfn.MINIFS('Draft Board'!$AN$2:$AN$193,'Draft Board'!$AN$2:$AN$193,">="&AN99,'Draft Board'!$AP$2:$AP$193,1) -> 0 | AR99: =IF(AO99<>_xlfn.MINIFS('Draft Board'!$AO$2:$AO$193,'Draft Board'!$AN$2:$AN$193,"="&AN99),0,IF(OR(AP99=1,IFERROR(FLOOR((AQ99-AN99)/AQ99/0.25,1),0)<>IFERROR(FLOOR((AQ99-_xlfn.MINIFS('Draft Board'!$AN$2:$AN$193,'Draft Board'!$AN$2:$AN$193,">"&AN99))/AQ99/0.25,1),0)),1,0)) -> 0 | AS99: =ROUND(1+AN99*'Live Calc'!$D$28,0) -> 1 | AU99: =IF(AT99<>"",AT99,ROUND(AS99*INDEX('Live Calc'!$G$259:$G$450,MATCH(AM99,'Live Calc'!$A$259:$A$450,0))*'Live Calc'!$J$543,0)) -> 1
... Q161: CJ Donaldson | R161: NO | S161: 5.04 | T161: 5.47 | U161: 5.9 | V161: =CHOOSE(MATCH(Setup!$B$7,{"STD","Half-PPR","PPR"},0),S161,T161,U161) -> 5.47 | W161: =COUNTIFS('Draft Board'!$X$2:$X$161,">="&X161,'Draft Board'!$AB$2:$AB$161,1) -> 14 | X161: =MAX(0,V161-'Live Calc'!$H$20)^'Live Calc'!$E$20 -> 0 | Y161: 161 | Z161: =IF(Y161<>_xlfn.MINIFS('Draft Board'!$Y$2:$Y$161,'Draft Board'!$X$2:$X$161,"="&X161),0,IF(_xlfn.MINIFS('Draft Board'!$X$2:$X$161,'Draft Board'!$X$2:$X$161,">"&X161)=0,1,IF((_xlfn.MINIFS('Draft Board'!$X$2:$X$161,'Draft Board'!$X$2:$X$161,">"&X161)-X161)/_xlfn.MINIFS('Draft Board'!$X$2:$X$161,'Draft Board'!$X$2:$X$161,">"&X161)>0.08,1,0))) -> 0 | AA161: =_xlfn.MINIFS('Draft Board'!$X$2:$X$161,'Draft Board'!$X$2:$X$161,">="&X161,'Draft Board'!$Z$2:$Z$161,1) -> 0 | AB161: =IF(Y161<>_xlfn.MINIFS('Draft Board'!$Y$2:$Y$161,'Draft Board'!$X$2:$X$161,"="&X161),0,IF(OR(Z161=1,IFERROR(FLOOR((AA161-X161)/AA161/0.25,1),0)<>IFERROR(FLOOR((AA161-_xlfn.MINIFS('Draft Board'!$X$2:$X$161,'Draft Board'!$X$2:$X$161,">"&X161))/AA161/0.25,1),0)),1,0)) -> 0 | AC161: =ROUND(1+X161*'Live Calc'!$D$27,0) -> 1 | AE161: =IF(AD161<>"",AD161,ROUND(AC161*INDEX('Live Calc'!$G$96:$G$255,MATCH(W161,'Live Calc'!$A$96:$A$255,0))*'Live Calc'!$J$543,0)) -> 1 | AG161: Hunter Renfrow | AH161: FA | AI161: 16.35 | AJ161: 22.3 | AK161: 28.25 | AL161: =CHOOSE(MATCH(Setup!$B$7,{"STD","Half-PPR","PPR"},0),AI161,AJ161,AK161) -> 22.3 | AM161: =COUNTIFS('Draft Board'!$AN$2:$AN$193,">="&AN161,'Draft Board'!$AR$2:$AR$193,1) -> 20 | AN161: =MAX(0,AL161-'Live Calc'!$H$21)^'Live Calc'!$E$21 -> 0 | AO161: 161 | AP161: =IF(AO161<>_xlfn.MINIFS('Draft Board'!$AO$2:$AO$193,'Draft Board'!$AN$2:$AN$193,"="&AN161),0,IF(_xlfn.MINIFS('Draft Board'!$AN$2:$AN$193,'Draft Board'!$AN$2:$AN$193,">"&AN161)=0,1,IF((_xlfn.MINIFS('Draft Board'!$AN$2:$AN$193,'Draft Board'!$AN$2:$AN$193,">"&AN161)-AN161)/_xlfn.MINIFS('Draft Board'!$AN$2:$AN$193,'Draft Board'!$AN$2:$AN$193,">"&AN161)>0.08,1,0))) -> 0 | AQ161: =_xlfn.MINIFS('Draft Board'!$AN$2:$AN$193,'Draft Board'!$AN$2:$AN$193,">="&AN161,'Draft Board'!$AP$2:$AP$193,1) -> 0 | AR161: =IF(AO161<>_xlfn.MINIFS('Draft Board'!$AO$2:$AO$193,'Draft Board'!$AN$2:$AN$193,"="&AN161),0,IF(OR(AP161=1,IFERROR(FLOOR((AQ161-AN161)/AQ161/0.25,1),0)<>IFERROR(FLOOR((AQ161-_xlfn.MINIFS('Draft Board'!$AN$2:$AN$193,'Draft Board'!$AN$2:$AN$193,">"&AN161))/AQ161/0.25,1),0)),1,0)) -> 0 | AS161: =ROUND(1+AN161*'Live Calc'!$D$28,0) -> 1 | AU161: =IF(AT161<>"",AT161,ROUND(AS161*INDEX('Live Calc'!$G$259:$G$450,MATCH(AM161,'Live Calc'!$A$259:$A$450,0))*'Live Calc'!$J$543,0)) -> 1
AG162: Roman Wilson | AH162: PIT | AI162: 16.89 | AJ162: 22.01 | AK162: 27.12 | AL162: =CHOOSE(MATCH(Setup!$B$7,{"STD","Half-PPR","PPR"},0),AI162,AJ162,AK162) -> 22.01 | AM162: =COUNTIFS('Draft Board'!$AN$2:$AN$193,">="&AN162,'Draft Board'!$AR$2:$AR$193,1) -> 20 | AN162: =MAX(0,AL162-'Live Calc'!$H$21)^'Live Calc'!$E$21 -> 0 | AO162: 162 | AP162: =IF(AO162<>_xlfn.MINIFS('Draft Board'!$AO$2:$AO$193,'Draft Board'!$AN$2:$AN$193,"="&AN162),0,IF(_xlfn.MINIFS('Draft Board'!$AN$2:$AN$193,'Draft Board'!$AN$2:$AN$193,">"&AN162)=0,1,IF((_xlfn.MINIFS('Draft Board'!$AN$2:$AN$193,'Draft Board'!$AN$2:$AN$193,">"&AN162)-AN162)/_xlfn.MINIFS('Draft Board'!$AN$2:$AN$193,'Draft Board'!$AN$2:$AN$193,">"&AN162)>0.08,1,0))) -> 0 | AQ162: =_xlfn.MINIFS('Draft Board'!$AN$2:$AN$193,'Draft Board'!$AN$2:$AN$193,">="&AN162,'Draft Board'!$AP$2:$AP$193,1) -> 0 | AR162: =IF(AO162<>_xlfn.MINIFS('Draft Board'!$AO$2:$AO$193,'Draft Board'!$AN$2:$AN$193,"="&AN162),0,IF(OR(AP162=1,IFERROR(FLOOR((AQ162-AN162)/AQ162/0.25,1),0)<>IFERROR(FLOOR((AQ162-_xlfn.MINIFS('Draft Board'!$AN$2:$AN$193,'Draft Board'!$AN$2:$AN$193,">"&AN162))/AQ162/0.25,1),0)),1,0)) -> 0 | AS162: =ROUND(1+AN162*'Live Calc'!$D$28,0) -> 1 | AU162: =IF(AT162<>"",AT162,ROUND(AS162*INDEX('Live Calc'!$G$259:$G$450,MATCH(AM162,'Live Calc'!$A$259:$A$450,0))*'Live Calc'!$J$543,0)) -> 1
AG163: Brandin Cooks | AH163: FA | AI163: 15.4 | AJ163: 19.55 | AK163: 23.7 | AL163: =CHOOSE(MATCH(Setup!$B$7,{"STD","Half-PPR","PPR"},0),AI163,AJ163,AK163) -> 19.55 | AM163: =COUNTIFS('Draft Board'!$AN$2:$AN$193,">="&AN163,'Draft Board'!$AR$2:$AR$193,1) -> 20 | AN163: =MAX(0,AL163-'Live Calc'!$H$21)^'Live Calc'!$E$21 -> 0 | AO163: 163 | AP163: =IF(AO163<>_xlfn.MINIFS('Draft Board'!$AO$2:$AO$193,'Draft Board'!$AN$2:$AN$193,"="&AN163),0,IF(_xlfn.MINIFS('Draft Board'!$AN$2:$AN$193,'Draft Board'!$AN$2:$AN$193,">"&AN163)=0,1,IF((_xlfn.MINIFS('Draft Board'!$AN$2:$AN$193,'Draft Board'!$AN$2:$AN$193,">"&AN163)-AN163)/_xlfn.MINIFS('Draft Board'!$AN$2:$AN$193,'Draft Board'!$AN$2:$AN$193,">"&AN163)>0.08,1,0))) -> 0 | AQ163: =_xlfn.MINIFS('Draft Board'!$AN$2:$AN$193,'Draft Board'!$AN$2:$AN$193,">="&AN163,'Draft Board'!$AP$2:$AP$193,1) -> 0 | AR163: =IF(AO163<>_xlfn.MINIFS('Draft Board'!$AO$2:$AO$193,'Draft Board'!$AN$2:$AN$193,"="&AN163),0,IF(OR(AP163=1,IFERROR(FLOOR((AQ163-AN163)/AQ163/0.25,1),0)<>IFERROR(FLOOR((AQ163-_xlfn.MINIFS('Draft Board'!$AN$2:$AN$193,'Draft Board'!$AN$2:$AN$193,">"&AN163))/AQ163/0.25,1),0)),1,0)) -> 0 | AS163: =ROUND(1+AN163*'Live Calc'!$D$28,0) -> 1 | AU163: =IF(AT163<>"",AT163,ROUND(AS163*INDEX('Live Calc'!$G$259:$G$450,MATCH(AM163,'Live Calc'!$A$259:$A$450,0))*'Live Calc'!$J$543,0)) -> 1
AG164: Jimmy Horn Jr. | AH164: CAR | AI164: 15.12 | AJ164: 19.37 | AK164: 23.63 | AL164: =CHOOSE(MATCH(Setup!$B$7,{"STD","Half-PPR","PPR"},0),AI164,AJ164,AK164) -> 19.37 | AM164: =COUNTIFS('Draft Board'!$AN$2:$AN$193,">="&AN164,'Draft Board'!$AR$2:$AR$193,1) -> 20 | AN164: =MAX(0,AL164-'Live Calc'!$H$21)^'Live Calc'!$E$21 -> 0 | AO164: 164 | AP164: =IF(AO164<>_xlfn.MINIFS('Draft Board'!$AO$2:$AO$193,'Draft Board'!$AN$2:$AN$193,"="&AN164),0,IF(_xlfn.MINIFS('Draft Board'!$AN$2:$AN$193,'Draft Board'!$AN$2:$AN$193,">"&AN164)=0,1,IF((_xlfn.MINIFS('Draft Board'!$AN$2:$AN$193,'Draft Board'!$AN$2:$AN$193,">"&AN164)-AN164)/_xlfn.MINIFS('Draft Board'!$AN$2:$AN$193,'Draft Board'!$AN$2:$AN$193,">"&AN164)>0.08,1,0))) -> 0 | AQ164: =_xlfn.MINIFS('Draft Board'!$AN$2:$AN$193,'Draft Board'!$AN$2:$AN$193,">="&AN164,'Draft Board'!$AP$2:$AP$193,1) -> 0 | AR164: =IF(AO164<>_xlfn.MINIFS('Draft Board'!$AO$2:$AO$193,'Draft Board'!$AN$2:$AN$193,"="&AN164),0,IF(OR(AP164=1,IFERROR(FLOOR((AQ164-AN164)/AQ164/0.25,1),0)<>IFERROR(FLOOR((AQ164-_xlfn.MINIFS('Draft Board'!$AN$2:$AN$193,'Draft Board'!$AN$2:$AN$193,">"&AN164))/AQ164/0.25,1),0)),1,0)) -> 0 | AS164: =ROUND(1+AN164*'Live Calc'!$D$28,0) -> 1 | AU164: =IF(AT164<>"",AT164,ROUND(AS164*INDEX('Live Calc'!$G$259:$G$450,MATCH(AM164,'Live Calc'!$A$259:$A$450,0))*'Live Calc'!$J$543,0)) -> 1
AG165: Xavier Smith | AH165: LAR | AI165: 14.4 | AJ165: 18.49 | AK165: 22.58 | AL165: =CHOOSE(MATCH(Setup!$B$7,{"STD","Half-PPR","PPR"},0),AI165,AJ165,AK165) -> 18.49 | AM165: =COUNTIFS('Draft Board'!$AN$2:$AN$193,">="&AN165,'Draft Board'!$AR$2:$AR$193,1) -> 20 | AN165: =MAX(0,AL165-'Live Calc'!$H$21)^'Live Calc'!$E$21 -> 0 | AO165: 165 | AP165: =IF(AO165<>_xlfn.MINIFS('Draft Board'!$AO$2:$AO$193,'Draft Board'!$AN$2:$AN$193,"="&AN165),0,IF(_xlfn.MINIFS('Draft Board'!$AN$2:$AN$193,'Draft Board'!$AN$2:$AN$193,">"&AN165)=0,1,IF((_xlfn.MINIFS('Draft Board'!$AN$2:$AN$193,'Draft Board'!$AN$2:$AN$193,">"&AN165)-AN165)/_xlfn.MINIFS('Draft Board'!$AN$2:$AN$193,'Draft Board'!$AN$2:$AN$193,">"&AN165)>0.08,1,0))) -> 0 | AQ165: =_xlfn.MINIFS('Draft Board'!$AN$2:$AN$193,'Draft Board'!$AN$2:$AN$193,">="&AN165,'Draft Board'!$AP$2:$AP$193,1) -> 0 | AR165: =IF(AO165<>_xlfn.MINIFS('Draft Board'!$AO$2:$AO$193,'Draft Board'!$AN$2:$AN$193,"="&AN165),0,IF(OR(AP165=1,IFERROR(FLOOR((AQ165-AN165)/AQ165/0.25,1),0)<>IFERROR(FLOOR((AQ165-_xlfn.MINIFS('Draft Board'!$AN$2:$AN$193,'Draft Board'!$AN$2:$AN$193,">"&AN165))/AQ165/0.25,1),0)),1,0)) -> 0 | AS165: =ROUND(1+AN165*'Live Calc'!$D$28,0) -> 1 | AU165: =IF(AT165<>"",AT165,ROUND(AS165*INDEX('Live Calc'!$G$259:$G$450,MATCH(AM165,'Live Calc'!$A$259:$A$450,0))*'Live Calc'!$J$543,0)) -> 1
AG166: Isaiah Williams | AH166: NYJ | AI166: 12.69 | AJ166: 18.09 | AK166: 23.48 | AL166: =CHOOSE(MATCH(Setup!$B$7,{"STD","Half-PPR","PPR"},0),AI166,AJ166,AK166) -> 18.09 | AM166: =COUNTIFS('Draft Board'!$AN$2:$AN$193,">="&AN166,'Draft Board'!$AR$2:$AR$193,1) -> 20 | AN166: =MAX(0,AL166-'Live Calc'!$H$21)^'Live Calc'!$E$21 -> 0 | AO166: 166 | AP166: =IF(AO166<>_xlfn.MINIFS('Draft Board'!$AO$2:$AO$193,'Draft Board'!$AN$2:$AN$193,"="&AN166),0,IF(_xlfn.MINIFS('Draft Board'!$AN$2:$AN$193,'Draft Board'!$AN$2:$AN$193,">"&AN166)=0,1,IF((_xlfn.MINIFS('Draft Board'!$AN$2:$AN$193,'Draft Board'!$AN$2:$AN$193,">"&AN166)-AN166)/_xlfn.MINIFS('Draft Board'!$AN$2:$AN$193,'Draft Board'!$AN$2:$AN$193,">"&AN166)>0.08,1,0))) -> 0 | AQ166: =_xlfn.MINIFS('Draft Board'!$AN$2:$AN$193,'Draft Board'!$AN$2:$AN$193,">="&AN166,'Draft Board'!$AP$2:$AP$193,1) -> 0 | AR166: =IF(AO166<>_xlfn.MINIFS('Draft Board'!$AO$2:$AO$193,'Draft Board'!$AN$2:$AN$193,"="&AN166),0,IF(OR(AP166=1,IFERROR(FLOOR((AQ166-AN166)/AQ166/0.25,1),0)<>IFERROR(FLOOR((AQ166-_xlfn.MINIFS('Draft Board'!$AN$2:$AN$193,'Draft Board'!$AN$2:$AN$193,">"&AN166))/AQ166/0.25,1),0)),1,0)) -> 0 | AS166: =ROUND(1+AN166*'Live Calc'!$D$28,0) -> 1 | AU166: =IF(AT166<>"",AT166,ROUND(AS166*INDEX('Live Calc'!$G$259:$G$450,MATCH(AM166,'Live Calc'!$A$259:$A$450,0))*'Live Calc'!$J$543,0)) -> 1
AG167: KeAndre Lambert-Smith | AH167: LAC | AI167: 13.95 | AJ167: 17.98 | AK167: 22.02 | AL167: =CHOOSE(MATCH(Setup!$B$7,{"STD","Half-PPR","PPR"},0),AI167,AJ167,AK167) -> 17.98 | AM167: =COUNTIFS('Draft Board'!$AN$2:$AN$193,">="&AN167,'Draft Board'!$AR$2:$AR$193,1) -> 20 | AN167: =MAX(0,AL167-'Live Calc'!$H$21)^'Live Calc'!$E$21 -> 0 | AO167: 167 | AP167: =IF(AO167<>_xlfn.MINIFS('Draft Board'!$AO$2:$AO$193,'Draft Board'!$AN$2:$AN$193,"="&AN167),0,IF(_xlfn.MINIFS('Draft Board'!$AN$2:$AN$193,'Draft Board'!$AN$2:$AN$193,">"&AN167)=0,1,IF((_xlfn.MINIFS('Draft Board'!$AN$2:$AN$193,'Draft Board'!$AN$2:$AN$193,">"&AN167)-AN167)/_xlfn.MINIFS('Draft Board'!$AN$2:$AN$193,'Draft Board'!$AN$2:$AN$193,">"&AN167)>0.08,1,0))) -> 0 | AQ167: =_xlfn.MINIFS('Draft Board'!$AN$2:$AN$193,'Draft Board'!$AN$2:$AN$193,">="&AN167,'Draft Board'!$AP$2:$AP$193,1) -> 0 | AR167: =IF(AO167<>_xlfn.MINIFS('Draft Board'!$AO$2:$AO$193,'Draft Board'!$AN$2:$AN$193,"="&AN167),0,IF(OR(AP167=1,IFERROR(FLOOR((AQ167-AN167)/AQ167/0.25,1),0)<>IFERROR(FLOOR((AQ167-_xlfn.MINIFS('Draft Board'!$AN$2:$AN$193,'Draft Board'!$AN$2:$AN$193,">"&AN167))/AQ167/0.25,1),0)),1,0)) -> 0 | AS167: =ROUND(1+AN167*'Live Calc'!$D$28,0) -> 1 | AU167: =IF(AT167<>"",AT167,ROUND(AS167*INDEX('Live Calc'!$G$259:$G$450,MATCH(AM167,'Live Calc'!$A$259:$A$450,0))*'Live Calc'!$J$543,0)) -> 1
AG168: Tim Patrick | AH168: NYJ | AI168: 13.44 | AJ168: 17.96 | AK168: 22.48 | AL168: =CHOOSE(MATCH(Setup!$B$7,{"STD","Half-PPR","PPR"},0),AI168,AJ168,AK168) -> 17.96 | AM168: =COUNTIFS('Draft Board'!$AN$2:$AN$193,">="&AN168,'Draft Board'!$AR$2:$AR$193,1) -> 20 | AN168: =MAX(0,AL168-'Live Calc'!$H$21)^'Live Calc'!$E$21 -> 0 | AO168: 168 | AP168: =IF(AO168<>_xlfn.MINIFS('Draft Board'!$AO$2:$AO$193,'Draft Board'!$AN$2:$AN$193,"="&AN168),0,IF(_xlfn.MINIFS('Draft Board'!$AN$2:$AN$193,'Draft Board'!$AN$2:$AN$193,">"&AN168)=0,1,IF((_xlfn.MINIFS('Draft Board'!$AN$2:$AN$193,'Draft Board'!$AN$2:$AN$193,">"&AN168)-AN168)/_xlfn.MINIFS('Draft Board'!$AN$2:$AN$193,'Draft Board'!$AN$2:$AN$193,">"&AN168)>0.08,1,0))) -> 0 | AQ168: =_xlfn.MINIFS('Draft Board'!$AN$2:$AN$193,'Draft Board'!$AN$2:$AN$193,">="&AN168,'Draft Board'!$AP$2:$AP$193,1) -> 0 | AR168: =IF(AO168<>_xlfn.MINIFS('Draft Board'!$AO$2:$AO$193,'Draft Board'!$AN$2:$AN$193,"="&AN168),0,IF(OR(AP168=1,IFERROR(FLOOR((AQ168-AN168)/AQ168/0.25,1),0)<>IFERROR(FLOOR((AQ168-_xlfn.MINIFS('Draft Board'!$AN$2:$AN$193,'Draft Board'!$AN$2:$AN$193,">"&AN168))/AQ168/0.25,1),0)),1,0)) -> 0 | AS168: =ROUND(1+AN168*'Live Calc'!$D$28,0) -> 1 | AU168: =IF(AT168<>"",AT168,ROUND(AS168*INDEX('Live Calc'!$G$259:$G$450,MATCH(AM168,'Live Calc'!$A$259:$A$450,0))*'Live Calc'!$J$543,0)) -> 1
AG169: Gabriel Davis | AH169: BUF | AI169: 12.1 | AJ169: 17.6 | AK169: 23.1 | AL169: =CHOOSE(MATCH(Setup!$B$7,{"STD","Half-PPR","PPR"},0),AI169,AJ169,AK169) -> 17.6 | AM169: =COUNTIFS('Draft Board'!$AN$2:$AN$193,">="&AN169,'Draft Board'!$AR$2:$AR$193,1) -> 20 | AN169: =MAX(0,AL169-'Live Calc'!$H$21)^'Live Calc'!$E$21 -> 0 | AO169: 169 | AP169: =IF(AO169<>_xlfn.MINIFS('Draft Board'!$AO$2:$AO$193,'Draft Board'!$AN$2:$AN$193,"="&AN169),0,IF(_xlfn.MINIFS('Draft Board'!$AN$2:$AN$193,'Draft Board'!$AN$2:$AN$193,">"&AN169)=0,1,IF((_xlfn.MINIFS('Draft Board'!$AN$2:$AN$193,'Draft Board'!$AN$2:$AN$193,">"&AN169)-AN169)/_xlfn.MINIFS('Draft Board'!$AN$2:$AN$193,'Draft Board'!$AN$2:$AN$193,">"&AN169)>0.08,1,0))) -> 0 | AQ169: =_xlfn.MINIFS('Draft Board'!$AN$2:$AN$193,'Draft Board'!$AN$2:$AN$193,">="&AN169,'Draft Board'!$AP$2:$AP$193,1) -> 0 | AR169: =IF(AO169<>_xlfn.MINIFS('Draft Board'!$AO$2:$AO$193,'Draft Board'!$AN$2:$AN$193,"="&AN169),0,IF(OR(AP169=1,IFERROR(FLOOR((AQ169-AN169)/AQ169/0.25,1),0)<>IFERROR(FLOOR((AQ169-_xlfn.MINIFS('Draft Board'!$AN$2:$AN$193,'Draft Board'!$AN$2:$AN$193,">"&AN169))/AQ169/0.25,1),0)),1,0)) -> 0 | AS169: =ROUND(1+AN169*'Live Calc'!$D$28,0) -> 1 | AU169: =IF(AT169<>"",AT169,ROUND(AS169*INDEX('Live Calc'!$G$259:$G$450,MATCH(AM169,'Live Calc'!$A$259:$A$450,0))*'Live Calc'!$J$543,0)) -> 1
AG170: Tai Felton | AH170: MIN | AI170: 12.42 | AJ170: 17.07 | AK170: 21.72 | AL170: =CHOOSE(MATCH(Setup!$B$7,{"STD","Half-PPR","PPR"},0),AI170,AJ170,AK170) -> 17.07 | AM170: =COUNTIFS('Draft Board'!$AN$2:$AN$193,">="&AN170,'Draft Board'!$AR$2:$AR$193,1) -> 20 | AN170: =MAX(0,AL170-'Live Calc'!$H$21)^'Live Calc'!$E$21 -> 0 | AO170: 170 | AP170: =IF(AO170<>_xlfn.MINIFS('Draft Board'!$AO$2:$AO$193,'Draft Board'!$AN$2:$AN$193,"="&AN170),0,IF(_xlfn.MINIFS('Draft Board'!$AN$2:$AN$193,'Draft Board'!$AN$2:$AN$193,">"&AN170)=0,1,IF((_xlfn.MINIFS('Draft Board'!$AN$2:$AN$193,'Draft Board'!$AN$2:$AN$193,">"&AN170)-AN170)/_xlfn.MINIFS('Draft Board'!$AN$2:$AN$193,'Draft Board'!$AN$2:$AN$193,">"&AN170)>0.08,1,0))) -> 0 | AQ170: =_xlfn.MINIFS('Draft Board'!$AN$2:$AN$193,'Draft Board'!$AN$2:$AN$193,">="&AN170,'Draft Board'!$AP$2:$AP$193,1) -> 0 | AR170: =IF(AO170<>_xlfn.MINIFS('Draft Board'!$AO$2:$AO$193,'Draft Board'!$AN$2:$AN$193,"="&AN170),0,IF(OR(AP170=1,IFERROR(FLOOR((AQ170-AN170)/AQ170/0.25,1),0)<>IFERROR(FLOOR((AQ170-_xlfn.MINIFS('Draft Board'!$AN$2:$AN$193,'Draft Board'!$AN$2:$AN$193,">"&AN170))/AQ170/0.25,1),0)),1,0)) -> 0 | AS170: =ROUND(1+AN170*'Live Calc'!$D$28,0) -> 1 | AU170: =IF(AT170<>"",AT170,ROUND(AS170*INDEX('Live Calc'!$G$259:$G$450,MATCH(AM170,'Live Calc'!$A$259:$A$450,0))*'Live Calc'!$J$543,0)) -> 1
AG171: Marquez Valdes-Scantling | AH171: DAL | AI171: 13.38 | AJ171: 17.02 | AK171: 20.66 | AL171: =CHOOSE(MATCH(Setup!$B$7,{"STD","Half-PPR","PPR"},0),AI171,AJ171,AK171) -> 17.02 | AM171: =COUNTIFS('Draft Board'!$AN$2:$AN$193,">="&AN171,'Draft Board'!$AR$2:$AR$193,1) -> 20 | AN171: =MAX(0,AL171-'Live Calc'!$H$21)^'Live Calc'!$E$21 -> 0 | AO171: 171 | AP171: =IF(AO171<>_xlfn.MINIFS('Draft Board'!$AO$2:$AO$193,'Draft Board'!$AN$2:$AN$193,"="&AN171),0,IF(_xlfn.MINIFS('Draft Board'!$AN$2:$AN$193,'Draft Board'!$AN$2:$AN$193,">"&AN171)=0,1,IF((_xlfn.MINIFS('Draft Board'!$AN$2:$AN$193,'Draft Board'!$AN$2:$AN$193,">"&AN171)-AN171)/_xlfn.MINIFS('Draft Board'!$AN$2:$AN$193,'Draft Board'!$AN$2:$AN$193,">"&AN171)>0.08,1,0))) -> 0 | AQ171: =_xlfn.MINIFS('Draft Board'!$AN$2:$AN$193,'Draft Board'!$AN$2:$AN$193,">="&AN171,'Draft Board'!$AP$2:$AP$193,1) -> 0 | AR171: =IF(AO171<>_xlfn.MINIFS('Draft Board'!$AO$2:$AO$193,'Draft Board'!$AN$2:$AN$193,"="&AN171),0,IF(OR(AP171=1,IFERROR(FLOOR((AQ171-AN171)/AQ171/0.25,1),0)<>IFERROR(FLOOR((AQ171-_xlfn.MINIFS('Draft Board'!$AN$2:$AN$193,'Draft Board'!$AN$2:$AN$193,">"&AN171))/AQ171/0.25,1),0)),1,0)) -> 0 | AS171: =ROUND(1+AN171*'Live Calc'!$D$28,0) -> 1 | AU171: =IF(AT171<>"",AT171,ROUND(AS171*INDEX('Live Calc'!$G$259:$G$450,MATCH(AM171,'Live Calc'!$A$259:$A$450,0))*'Live Calc'!$J$543,0)) -> 1
AG172: Odell Beckham Jr. | AH172: NYG | AI172: 12.66 | AJ172: 16.5 | AK172: 20.35 | AL172: =CHOOSE(MATCH(Setup!$B$7,{"STD","Half-PPR","PPR"},0),AI172,AJ172,AK172) -> 16.5 | AM172: =COUNTIFS('Draft Board'!$AN$2:$AN$193,">="&AN172,'Draft Board'!$AR$2:$AR$193,1) -> 20 | AN172: =MAX(0,AL172-'Live Calc'!$H$21)^'Live Calc'!$E$21 -> 0 | AO172: 172 | AP172: =IF(AO172<>_xlfn.MINIFS('Draft Board'!$AO$2:$AO$193,'Draft Board'!$AN$2:$AN$193,"="&AN172),0,IF(_xlfn.MINIFS('Draft Board'!$AN$2:$AN$193,'Draft Board'!$AN$2:$AN$193,">"&AN172)=0,1,IF((_xlfn.MINIFS('Draft Board'!$AN$2:$AN$193,'Draft Board'!$AN$2:$AN$193,">"&AN172)-AN172)/_xlfn.MINIFS('Draft Board'!$AN$2:$AN$193,'Draft Board'!$AN$2:$AN$193,">"&AN172)>0.08,1,0))) -> 0 | AQ172: =_xlfn.MINIFS('Draft Board'!$AN$2:$AN$193,'Draft Board'!$AN$2:$AN$193,">="&AN172,'Draft Board'!$AP$2:$AP$193,1) -> 0 | AR172: =IF(AO172<>_xlfn.MINIFS('Draft Board'!$AO$2:$AO$193,'Draft Board'!$AN$2:$AN$193,"="&AN172),0,IF(OR(AP172=1,IFERROR(FLOOR((AQ172-AN172)/AQ172/0.25,1),0)<>IFERROR(FLOOR((AQ172-_xlfn.MINIFS('Draft Board'!$AN$2:$AN$193,'Draft Board'!$AN$2:$AN$193,">"&AN172))/AQ172/0.25,1),0)),1,0)) -> 0 | AS172: =ROUND(1+AN172*'Live Calc'!$D$28,0) -> 1 | AU172: =IF(AT172<>"",AT172,ROUND(AS172*INDEX('Live Calc'!$G$259:$G$450,MATCH(AM172,'Live Calc'!$A$259:$A$450,0))*'Live Calc'!$J$543,0)) -> 1
AG173: Bo Melton | AH173: GB | AI173: 12.44 | AJ173: 16.14 | AK173: 19.85 | AL173: =CHOOSE(MATCH(Setup!$B$7,{"STD","Half-PPR","PPR"},0),AI173,AJ173,AK173) -> 16.14 | AM173: =COUNTIFS('Draft Board'!$AN$2:$AN$193,">="&AN173,'Draft Board'!$AR$2:$AR$193,1) -> 20 | AN173: =MAX(0,AL173-'Live Calc'!$H$21)^'Live Calc'!$E$21 -> 0 | AO173: 173 | AP173: =IF(AO173<>_xlfn.MINIFS('Draft Board'!$AO$2:$AO$193,'Draft Board'!$AN$2:$AN$193,"="&AN173),0,IF(_xlfn.MINIFS('Draft Board'!$AN$2:$AN$193,'Draft Board'!$AN$2:$AN$193,">"&AN173)=0,1,IF((_xlfn.MINIFS('Draft Board'!$AN$2:$AN$193,'Draft Board'!$AN$2:$AN$193,">"&AN173)-AN173)/_xlfn.MINIFS('Draft Board'!$AN$2:$AN$193,'Draft Board'!$AN$2:$AN$193,">"&AN173)>0.08,1,0))) -> 0 | AQ173: =_xlfn.MINIFS('Draft Board'!$AN$2:$AN$193,'Draft Board'!$AN$2:$AN$193,">="&AN173,'Draft Board'!$AP$2:$AP$193,1) -> 0 | AR173: =IF(AO173<>_xlfn.MINIFS('Draft Board'!$AO$2:$AO$193,'Draft Board'!$AN$2:$AN$193,"="&AN173),0,IF(OR(AP173=1,IFERROR(FLOOR((AQ173-AN173)/AQ173/0.25,1),0)<>IFERROR(FLOOR((AQ173-_xlfn.MINIFS('Draft Board'!$AN$2:$AN$193,'Draft Board'!$AN$2:$AN$193,">"&AN173))/AQ173/0.25,1),0)),1,0)) -> 0 | AS173: =ROUND(1+AN173*'Live Calc'!$D$28,0) -> 1 | AU173: =IF(AT173<>"",AT173,ROUND(AS173*INDEX('Live Calc'!$G$259:$G$450,MATCH(AM173,'Live Calc'!$A$259:$A$450,0))*'Live Calc'!$J$543,0)) -> 1
... AG193: Reggie Virgil | AH193: ARI | AI193: 8.17 | AJ193: 10.68 | AK193: 13.19 | AL193: =CHOOSE(MATCH(Setup!$B$7,{"STD","Half-PPR","PPR"},0),AI193,AJ193,AK193) -> 10.68 | AM193: =COUNTIFS('Draft Board'!$AN$2:$AN$193,">="&AN193,'Draft Board'!$AR$2:$AR$193,1) -> 20 | AN193: =MAX(0,AL193-'Live Calc'!$H$21)^'Live Calc'!$E$21 -> 0 | AO193: 193 | AP193: =IF(AO193<>_xlfn.MINIFS('Draft Board'!$AO$2:$AO$193,'Draft Board'!$AN$2:$AN$193,"="&AN193),0,IF(_xlfn.MINIFS('Draft Board'!$AN$2:$AN$193,'Draft Board'!$AN$2:$AN$193,">"&AN193)=0,1,IF((_xlfn.MINIFS('Draft Board'!$AN$2:$AN$193,'Draft Board'!$AN$2:$AN$193,">"&AN193)-AN193)/_xlfn.MINIFS('Draft Board'!$AN$2:$AN$193,'Draft Board'!$AN$2:$AN$193,">"&AN193)>0.08,1,0))) -> 0 | AQ193: =_xlfn.MINIFS('Draft Board'!$AN$2:$AN$193,'Draft Board'!$AN$2:$AN$193,">="&AN193,'Draft Board'!$AP$2:$AP$193,1) -> 0 | AR193: =IF(AO193<>_xlfn.MINIFS('Draft Board'!$AO$2:$AO$193,'Draft Board'!$AN$2:$AN$193,"="&AN193),0,IF(OR(AP193=1,IFERROR(FLOOR((AQ193-AN193)/AQ193/0.25,1),0)<>IFERROR(FLOOR((AQ193-_xlfn.MINIFS('Draft Board'!$AN$2:$AN$193,'Draft Board'!$AN$2:$AN$193,">"&AN193))/AQ193/0.25,1),0)),1,0)) -> 0 | AS193: =ROUND(1+AN193*'Live Calc'!$D$28,0) -> 1 | AU193: =IF(AT193<>"",AT193,ROUND(AS193*INDEX('Live Calc'!$G$259:$G$450,MATCH(AM193,'Live Calc'!$A$259:$A$450,0))*'Live Calc'!$J$543,0)) -> 1

Sheet Live Calc
A1: $ SETUP
A2: Total Teams | B2: =Setup!$B$5 -> 12
A3: Total Roster Spots | B3: =B2*(Setup!$B$11+Setup!$B$13+Setup!$B$15+Setup!$B$17+(Setup!$B$19+Setup!$B$21+Setup!$B$23+Setup!$B$25)+Setup!$B$27+Setup!$B$29+Setup!$B$31) -> 192
A4: Total Money ($) | B4: =B2*Setup!$B$3 -> 2400
A5: Total Discretionary ($) | B5: =B4-B3*1 -> 2208
A7: ROSTER REGIME
A8: Has Superflex-Level QB Demand | B8: =OR(Setup!$B$11=2,Setup!$B$25>=1) -> FALSE
A10: BASELINE (real Teams/Format calibration)
A11: Position | B11: Baseline Rank | C11: Baseline Exponent | D11: Baseline Budget Share | E11: SF-Shift Exp Ratio | F11: SF-Shift Share Ratio | G11: Exponent Slope/Flex | H11: Budget-Share Slope/Flex
A12: QB | B12: =CHOOSE(MATCH(Setup!$B$5,{8,10,12,14,16},0)+(MATCH(Setup!$B$7,{"STD","Half-PPR","PPR"},0)-1)*5,V12,Y12,AB12,AE12,AH12,AK12,AN12,AQ12,AT12,AW12,AZ12,BC12,BF12,BI12,BL12) -> 20 | C12: =CHOOSE(MATCH(Setup!$B$5,{8,10,12,14,16},0)+(MATCH(Setup!$B$7,{"STD","Half-PPR","PPR"},0)-1)*5,W12,Z12,AC12,AF12,AI12,AL12,AO12,AR12,AU12,AX12,BA12,BD12,BG12,BJ12,BM12) -> 1.2 | D12: =CHOOSE(MATCH(Setup!$B$5,{8,10,12,14,16},0)+(MATCH(Setup!$B$7,{"STD","Half-PPR","PPR"},0)-1)*5,X12,AA12,AD12,AG12,AJ12,AM12,AP12,AS12,AV12,AY12,BB12,BE12,BH12,BK12,BN12) -> 0.0716 | E12: 1.1667 | F12: 4.1494 | G12: -0.05 | H12: -0.00555 | V12: 14 | W12: 1.1 | X12: 0.0741 | Y12: 16 | Z12: 1.2 | AA12: 0.0741 | AB12: 20 | AC12: 1.3 | AD12: 0.0741 | AE12: 22 | AF12: 1.4 | AG12: 0.0741 | AH12: 22 | AI12: 1.3 | AJ12: 0.0741 | AK12: 14 | AL12: 1.05 | AM12: 0.0716 | AN12: 16 | AO12: 1.1 | AP12: 0.0716 | AQ12: 20 | AR12: 1.2 | AS12: 0.0716 | AT12: 22 | AU12: 1.3 | AV12: 0.0716 | AW12: 22 | AX12: 1.2 | AY12: 0.0716 | AZ12: 16 | BA12: 1.4 | BB12: 0.0711 | BC12: 18 | BD12: 1.3 | BE12: 0.0711 | BF12: 20 | BG12: 1.15 | BH12: 0.0711 | BI12: 22 | BJ12: 1.3 | BK12: 0.0711 | BL12: 24 | BM12: 1.2 | BN12: 0.0711
A13: RB | B13: =CHOOSE(MATCH(Setup!$B$5,{8,10,12,14,16},0)+(MATCH(Setup!$B$7,{"STD","Half-PPR","PPR"},0)-1)*5,V13,Y13,AB13,AE13,AH13,AK13,AN13,AQ13,AT13,AW13,AZ13,BC13,BF13,BI13,BL13) -> 44 | C13: =CHOOSE(MATCH(Setup!$B$5,{8,10,12,14,16},0)+(MATCH(Setup!$B$7,{"STD","Half-PPR","PPR"},0)-1)*5,W13,Z13,AC13,AF13,AI13,AL13,AO13,AR13,AU13,AX13,BA13,BD13,BG13,BJ13,BM13) -> 1.2 | D13: =CHOOSE(MATCH(Setup!$B$5,{8,10,12,14,16},0)+(MATCH(Setup!$B$7,{"STD","Half-PPR","PPR"},0)-1)*5,X13,AA13,AD13,AG13,AJ13,AM13,AP13,AS13,AV13,AY13,BB13,BE13,BH13,BK13,BN13) -> 0.4179 | E13: 1 | F13: 0.7026 | G13: 0.025 | H13: 0.0087 | V13: 32 | W13: 1 | X13: 0.4349 | Y13: 36 | Z13: 1.15 | AA13: 0.4349 | AB13: 44 | AC13: 1.3 | AD13: 0.4349 | AE13: 48 | AF13: 1.1 | AG13: 0.4349 | AH13: 52 | AI13: 1.15 | AJ13: 0.4349 | AK13: 32 | AL13: 1.2 | AM13: 0.4179 | AN13: 36 | AO13: 1.1 | AP13: 0.4179 | AQ13: 44 | AR13: 1.2 | AS13: 0.4179 | AT13: 52 | AU13: 1.3 | AV13: 0.4179 | AW13: 56 | AX13: 1.2 | AY13: 0.4179 | AZ13: 32 | BA13: 1.15 | BB13: 0.4036 | BC13: 36 | BD13: 1.05 | BE13: 0.4036 | BF13: 40 | BG13: 1.05 | BH13: 0.4036 | BI13: 48 | BJ13: 1.1 | BK13: 0.4036 | BL13: 56 | BM13: 1.2 | BN13: 0.4036
A14: WR | B14: =CHOOSE(MATCH(Setup!$B$5,{8,10,12,14,16},0)+(MATCH(Setup!$B$7,{"STD","Half-PPR","PPR"},0)-1)*5,V14,Y14,AB14,AE14,AH14,AK14,AN14,AQ14,AT14,AW14,AZ14,BC14,BF14,BI14,BL14) -> 60 | C14: =CHOOSE(MATCH(Setup!$B$5,{8,10,12,14,16},0)+(MATCH(Setup!$B$7,{"STD","Half-PPR","PPR"},0)-1)*5,W14,Z14,AC14,AF14,AI14,AL14,AO14,AR14,AU14,AX14,BA14,BD14,BG14,BJ14,BM14) -> 1.25 | D14: =CHOOSE(MATCH(Setup!$B$5,{8,10,12,14,16},0)+(MATCH(Setup!$B$7,{"STD","Half-PPR","PPR"},0)-1)*5,X14,AA14,AD14,AG14,AJ14,AM14,AP14,AS14,AV14,AY14,BB14,BE14,BH14,BK14,BN14) -> 0.4219 | E14: 1.04 | F14: 0.7836 | G14: -0.05 | H14: -0.00455 | V14: 40 | W14: 1.25 | X14: 0.4011 | Y14: 55 | Z14: 1.3 | AA14: 0.4011 | AB14: 60 | AC14: 1.2 | AD14: 0.4011 | AE14: 70 | AF14: 1.3 | AG14: 0.4011 | AH14: 80 | AI14: 1.25 | AJ14: 0.4011 | AK14: 40 | AL14: 1.2 | AM14: 0.4219 | AN14: 55 | AO14: 1.3 | AP14: 0.4219 | AQ14: 60 | AR14: 1.25 | AS14: 0.4219 | AT14: 70 | AU14: 1.3 | AV14: 0.4219 | AW14: 75 | AX14: 1.2 | AY14: 0.4219 | AZ14: 40 | BA14: 1.15 | BB14: 0.437 | BC14: 55 | BD14: 1.3 | BE14: 0.437 | BF14: 60 | BG14: 1.25 | BH14: 0.437 | BI14: 70 | BJ14: 1.3 | BK14: 0.437 | BL14: 75 | BM14: 1.2 | BN14: 0.437
A15: TE | B15: =CHOOSE(MATCH(Setup!$B$5,{8,10,12,14,16},0)+(MATCH(Setup!$B$7,{"STD","Half-PPR","PPR"},0)-1)*5,V15,Y15,AB15,AE15,AH15,AK15,AN15,AQ15,AT15,AW15,AZ15,BC15,BF15,BI15,BL15) -> 24 | C15: =CHOOSE(MATCH(Setup!$B$5,{8,10,12,14,16},0)+(MATCH(Setup!$B$7,{"STD","Half-PPR","PPR"},0)-1)*5,W15,Z15,AC15,AF15,AI15,AL15,AO15,AR15,AU15,AX15,BA15,BD15,BG15,BJ15,BM15) -> 1 | D15: =CHOOSE(MATCH(Setup!$B$5,{8,10,12,14,16},0)+(MATCH(Setup!$B$7,{"STD","Half-PPR","PPR"},0)-1)*5,X15,AA15,AD15,AG15,AJ15,AM15,AP15,AS15,AV15,AY15,BB15,BE15,BH15,BK15,BN15) -> 0.0886 | E15: 1 | F15: 0.8883 | G15: 0 | H15: 0.0014 | V15: 16 | W15: 0.9 | X15: 0.0898 | Y15: 20 | Z15: 1.1 | AA15: 0.0898 | AB15: 24 | AC15: 0.9 | AD15: 0.0898 | AE15: 28 | AF15: 0.9 | AG15: 0.0898 | AH15: 30 | AI15: 0.85 | AJ15: 0.0898 | AK15: 16 | AL15: 1 | AM15: 0.0886 | AN15: 18 | AO15: 0.9 | AP15: 0.0886 | AQ15: 24 | AR15: 1 | AS15: 0.0886 | AT15: 28 | AU15: 1 | AV15: 0.0886 | AW15: 30 | AX15: 1.1 | AY15: 0.0886 | AZ15: 14 | BA15: 1 | BB15: 0.0883 | BC15: 18 | BD15: 0.9 | BE15: 0.0883 | BF15: 24 | BG15: 1 | BH15: 0.0883 | BI15: 28 | BJ15: 1.1 | BK15: 0.0883 | BL15: 30 | BM15: 1.1 | BN15: 0.0883
A17: ROSTER-ADJUSTED | J17: RB/WR/TE-type Flex Count
A18: Position | B18: Demand (current) | C18: Demand (baseline) | D18: Adjusted Rank | E18: Exponent (final) | F18: Raw Adjusted Share | G18: Final Budget Share | H18: Replacement Points | J18: =Setup!$B$19 -> 1
A19: QB | B19: =Setup!$B$11+0*Setup!$B$19+0*Setup!$B$21+0*Setup!$B$23+0.4*Setup!$B$25 -> 1 | C19: =1+0*1 -> 1 | D19: =MAX(1,ROUND(B12*IFERROR(B19/C19,1),0)) -> 20 | E19: =IF($B$8,C12*E12,C12+G12*($J$18-1)) -> 1.2 | F19: =IF($B$8,D12*F12,D12+H12*($J$18-1)) -> 0.0716 | G19: =F19/(F19+F20+F21+F22) -> 0.0716 | H19: =LARGE('Draft Board'!$F$2:$F$61,MIN(D19,60)) -> 264.17
A20: RB | B20: =Setup!$B$13+0.1818*Setup!$B$19+0.2048*Setup!$B$21+0*Setup!$B$23+0.3306*Setup!$B$25 -> 2.1818 | C20: =2+0.1818*1 -> 2.1818 | D20: =MAX(1,ROUND(B13*IFERROR(B20/C20,1),0)) -> 44 | E20: =IF($B$8,C13*E13,C13+G13*($J$18-1)) -> 1.2 | F20: =IF($B$8,D13*F13,D13+H13*($J$18-1)) -> 0.4179 | G20: =F20/(F19+F20+F21+F22) -> 0.4179 | H20: =LARGE('Draft Board'!$V$2:$V$161,MIN(D20,160)) -> 100.832
A21: WR | B21: =Setup!$B$15+0.1111*Setup!$B$19+0.1251*Setup!$B$21+0.2475*Setup!$B$23+0.2021*Setup!$B$25 -> 3.1111 | C21: =3+0.1111*1 -> 3.1111 | D21: =MAX(1,ROUND(B14*IFERROR(B21/C21,1),0)) -> 60 | E21: =IF($B$8,C14*E14,C14+G14*($J$18-1)) -> 1.25 | F21: =IF($B$8,D14*F14,D14+H14*($J$18-1)) -> 0.4219 | G21: =F21/(F19+F20+F21+F22) -> 0.4219 | H21: =LARGE('Draft Board'!$AL$2:$AL$193,MIN(D21,192)) -> 101.24
A22: TE | B22: =Setup!$B$17+0.037*Setup!$B$19+0*Setup!$B$21+0.0824*Setup!$B$23+0.0673*Setup!$B$25 -> 1.037 | C22: =1+0.037*1 -> 1.037 | D22: =MAX(1,ROUND(B15*IFERROR(B22/C22,1),0)) -> 24 | E22: =IF($B$8,C15*E15,C15+G15*($J$18-1)) -> 1 | F22: =IF($B$8,D15*F15,D15+H15*($J$18-1)) -> 0.0886 | G22: =F22/(F19+F20+F21+F22) -> 0.0886 | H22: =LARGE('Draft Board'!$BB$2:$BB$87,MIN(D22,86)) -> 103.25
A24: POSITION RATES
A25: Position | B25: Discretionary $ | C25: Total Weighted VORP | D25: Rate
A26: QB | B26: =$B$5*G19 -> 158.0928 | C26: =SUM('Draft Board'!$H$2:$H$61) -> 1174.7646 | D26: =IF(C26<20,0,IFERROR(B26/C26,0)) -> 0.13457402
A27: RB | B27: =$B$5*G20 -> 922.7232 | C27: =SUM('Draft Board'!$X$2:$X$161) -> 10037.517 | D27: =IF(C27<20,0,IFERROR(B27/C27,0)) -> 0.091927439
A28: WR | B28: =$B$5*G21 -> 931.5552 | C28: =SUM('Draft Board'!$AN$2:$AN$193) -> 11420.193 | D28: =IF(C28<20,0,IFERROR(B28/C28,0)) -> 0.08157088
A29: TE | B29: =$B$5*G22 -> 195.6288 | C29: =SUM('Draft Board'!$BD$2:$BD$87) -> 729.24 | D29: =IF(C29<20,0,IFERROR(B29/C29,0)) -> 0.26826395
A31: QB tiers
A32: Tier | B32: Drafted Price Sum | C32: Drafted Static Sum | D32: Drafted Count | E32: Tier Avg Static | F32: Dampening | G32: Tier Factor
A33: 1 | B33: =SUMIFS('Draft Board'!$N$2:$N$61,'Draft Board'!$G$2:$G$61,A33,'Draft Board'!$N$2:$N$61,"<>") -> 0 | C33: =SUMIFS('Draft Board'!$M$2:$M$61,'Draft Board'!$G$2:$G$61,A33,'Draft Board'!$N$2:$N$61,"<>") -> 0 | D33: =COUNTIFS('Draft Board'!$G$2:$G$61,A33,'Draft Board'!$N$2:$N$61,"<>") -> 0 | E33: =IFERROR(AVERAGEIFS('Draft Board'!$M$2:$M$61,'Draft Board'!$G$2:$G$61,A33),0) -> 30 | F33: =MIN(1,E33/(Setup!$B$3*0.1)) -> 1 | G33: =IF(D33<2,1,MEDIAN(0.5,2,1+(IFERROR(B33/C33,1)-1)*F33)) -> 1
A34: 2 | B34: =SUMIFS('Draft Board'!$N$2:$N$61,'Draft Board'!$G$2:$G$61,A34,'Draft Board'!$N$2:$N$61,"<>") -> 0 | C34: =SUMIFS('Draft Board'!$M$2:$M$61,'Draft Board'!$G$2:$G$61,A34,'Draft Board'!$N$2:$N$61,"<>") -> 0 | D34: =COUNTIFS('Draft Board'!$G$2:$G$61,A34,'Draft Board'!$N$2:$N$61,"<>") -> 0 | E34: =IFERROR(AVERAGEIFS('Draft Board'!$M$2:$M$61,'Draft Board'!$G$2:$G$61,A34),0) -> 16 | F34: =MIN(1,E34/(Setup!$B$3*0.1)) -> 0.8 | G34: =IF(D34<2,1,MEDIAN(0.5,2,1+(IFERROR(B34/C34,1)-1)*F34)) -> 1
A35: 3 | B35: =SUMIFS('Draft Board'!$N$2:$N$61,'Draft Board'!$G$2:$G$61,A35,'Draft Board'!$N$2:$N$61,"<>") -> 0 | C35: =SUMIFS('Draft Board'!$M$2:$M$61,'Draft Board'!$G$2:$G$61,A35,'Draft Board'!$N$2:$N$61,"<>") -> 0 | D35: =COUNTIFS('Draft Board'!$G$2:$G$61,A35,'Draft Board'!$N$2:$N$61,"<>") -> 0 | E35: =IFERROR(AVERAGEIFS('Draft Board'!$M$2:$M$61,'Draft Board'!$G$2:$G$61,A35),0) -> 13.5 | F35: =MIN(1,E35/(Setup!$B$3*0.1)) -> 0.675 | G35: =IF(D35<2,1,MEDIAN(0.5,2,1+(IFERROR(B35/C35,1)-1)*F35)) -> 1
A36: 4 | B36: =SUMIFS('Draft Board'!$N$2:$N$61,'Draft Board'!$G$2:$G$61,A36,'Draft Board'!$N$2:$N$61,"<>") -> 0 | C36: =SUMIFS('Draft Board'!$M$2:$M$61,'Draft Board'!$G$2:$G$61,A36,'Draft Board'!$N$2:$N$61,"<>") -> 0 | D36: =COUNTIFS('Draft Board'!$G$2:$G$61,A36,'Draft Board'!$N$2:$N$61,"<>") -> 0 | E36: =IFERROR(AVERAGEIFS('Draft Board'!$M$2:$M$61,'Draft Board'!$G$2:$G$61,A36),0) -> 8.8 | F36: =MIN(1,E36/(Setup!$B$3*0.1)) -> 0.44 | G36: =IF(D36<2,1,MEDIAN(0.5,2,1+(IFERROR(B36/C36,1)-1)*F36)) -> 1
A37: 5 | B37: =SUMIFS('Draft Board'!$N$2:$N$61,'Draft Board'!$G$2:$G$61,A37,'Draft Board'!$N$2:$N$61,"<>") -> 0 | C37: =SUMIFS('Draft Board'!$M$2:$M$61,'Draft Board'!$G$2:$G$61,A37,'Draft Board'!$N$2:$N$61,"<>") -> 0 | D37: =COUNTIFS('Draft Board'!$G$2:$G$61,A37,'Draft Board'!$N$2:$N$61,"<>") -> 0 | E37: =IFERROR(AVERAGEIFS('Draft Board'!$M$2:$M$61,'Draft Board'!$G$2:$G$61,A37),0) -> 7 | F37: =MIN(1,E37/(Setup!$B$3*0.1)) -> 0.35 | G37: =IF(D37<2,1,MEDIAN(0.5,2,1+(IFERROR(B37/C37,1)-1)*F37)) -> 1
A38: 6 | B38: =SUMIFS('Draft Board'!$N$2:$N$61,'Draft Board'!$G$2:$G$61,A38,'Draft Board'!$N$2:$N$61,"<>") -> 0 | C38: =SUMIFS('Draft Board'!$M$2:$M$61,'Draft Board'!$G$2:$G$61,A38,'Draft Board'!$N$2:$N$61,"<>") -> 0 | D38: =COUNTIFS('Draft Board'!$G$2:$G$61,A38,'Draft Board'!$N$2:$N$61,"<>") -> 0 | E38: =IFERROR(AVERAGEIFS('Draft Board'!$M$2:$M$61,'Draft Board'!$G$2:$G$61,A38),0) -> 5 | F38: =MIN(1,E38/(Setup!$B$3*0.1)) -> 0.25 | G38: =IF(D38<2,1,MEDIAN(0.5,2,1+(IFERROR(B38/C38,1)-1)*F38)) -> 1
A39: 7 | B39: =SUMIFS('Draft Board'!$N$2:$N$61,'Draft Board'!$G$2:$G$61,A39,'Draft Board'!$N$2:$N$61,"<>") -> 0 | C39: =SUMIFS('Draft Board'!$M$2:$M$61,'Draft Board'!$G$2:$G$61,A39,'Draft Board'!$N$2:$N$61,"<>") -> 0 | D39: =COUNTIFS('Draft Board'!$G$2:$G$61,A39,'Draft Board'!$N$2:$N$61,"<>") -> 0 | E39: =IFERROR(AVERAGEIFS('Draft Board'!$M$2:$M$61,'Draft Board'!$G$2:$G$61,A39),0) -> 3 | F39: =MIN(1,E39/(Setup!$B$3*0.1)) -> 0.15 | G39: =IF(D39<2,1,MEDIAN(0.5,2,1+(IFERROR(B39/C39,1)-1)*F39)) -> 1
A40: 8 | B40: =SUMIFS('Draft Board'!$N$2:$N$61,'Draft Board'!$G$2:$G$61,A40,'Draft Board'!$N$2:$N$61,"<>") -> 0 | C40: =SUMIFS('Draft Board'!$M$2:$M$61,'Draft Board'!$G$2:$G$61,A40,'Draft Board'!$N$2:$N$61,"<>") -> 0 | D40: =COUNTIFS('Draft Board'!$G$2:$G$61,A40,'Draft Board'!$N$2:$N$61,"<>") -> 0 | E40: =IFERROR(AVERAGEIFS('Draft Board'!$M$2:$M$61,'Draft Board'!$G$2:$G$61,A40),0) -> 3 | F40: =MIN(1,E40/(Setup!$B$3*0.1)) -> 0.15 | G40: =IF(D40<2,1,MEDIAN(0.5,2,1+(IFERROR(B40/C40,1)-1)*F40)) -> 1
A41: 9 | B41: =SUMIFS('Draft Board'!$N$2:$N$61,'Draft Board'!$G$2:$G$61,A41,'Draft Board'!$N$2:$N$61,"<>") -> 0 | C41: =SUMIFS('Draft Board'!$M$2:$M$61,'Draft Board'!$G$2:$G$61,A41,'Draft Board'!$N$2:$N$61,"<>") -> 0 | D41: =COUNTIFS('Draft Board'!$G$2:$G$61,A41,'Draft Board'!$N$2:$N$61,"<>") -> 0 | E41: =IFERROR(AVERAGEIFS('Draft Board'!$M$2:$M$61,'Draft Board'!$G$2:$G$61,A41),0) -> 2 | F41: =MIN(1,E41/(Setup!$B$3*0.1)) -> 0.1 | G41: =IF(D41<2,1,MEDIAN(0.5,2,1+(IFERROR(B41/C41,1)-1)*F41)) -> 1
A42: 10 | B42: =SUMIFS('Draft Board'!$N$2:$N$61,'Draft Board'!$G$2:$G$61,A42,'Draft Board'!$N$2:$N$61,"<>") -> 0 | C42: =SUMIFS('Draft Board'!$M$2:$M$61,'Draft Board'!$G$2:$G$61,A42,'Draft Board'!$N$2:$N$61,"<>") -> 0 | D42: =COUNTIFS('Draft Board'!$G$2:$G$61,A42,'Draft Board'!$N$2:$N$61,"<>") -> 0 | E42: =IFERROR(AVERAGEIFS('Draft Board'!$M$2:$M$61,'Draft Board'!$G$2:$G$61,A42),0) -> 1 | F42: =MIN(1,E42/(Setup!$B$3*0.1)) -> 0.05 | G42: =IF(D42<2,1,MEDIAN(0.5,2,1+(IFERROR(B42/C42,1)-1)*F42)) -> 1
A43: 11 | B43: =SUMIFS('Draft Board'!$N$2:$N$61,'Draft Board'!$G$2:$G$61,A43,'Draft Board'!$N$2:$N$61,"<>") -> 0 | C43: =SUMIFS('Draft Board'!$M$2:$M$61,'Draft Board'!$G$2:$G$61,A43,'Draft Board'!$N$2:$N$61,"<>") -> 0 | D43: =COUNTIFS('Draft Board'!$G$2:$G$61,A43,'Draft Board'!$N$2:$N$61,"<>") -> 0 | E43: =IFERROR(AVERAGEIFS('Draft Board'!$M$2:$M$61,'Draft Board'!$G$2:$G$61,A43),0) -> 1 | F43: =MIN(1,E43/(Setup!$B$3*0.1)) -> 0.05 | G43: =IF(D43<2,1,MEDIAN(0.5,2,1+(IFERROR(B43/C43,1)-1)*F43)) -> 1
A44: 12 | B44: =SUMIFS('Draft Board'!$N$2:$N$61,'Draft Board'!$G$2:$G$61,A44,'Draft Board'!$N$2:$N$61,"<>") -> 0 | C44: =SUMIFS('Draft Board'!$M$2:$M$61,'Draft Board'!$G$2:$G$61,A44,'Draft Board'!$N$2:$N$61,"<>") -> 0 | D44: =COUNTIFS('Draft Board'!$G$2:$G$61,A44,'Draft Board'!$N$2:$N$61,"<>") -> 0 | E44: =IFERROR(AVERAGEIFS('Draft Board'!$M$2:$M$61,'Draft Board'!$G$2:$G$61,A44),0) -> 0 | F44: =MIN(1,E44/(Setup!$B$3*0.1)) -> 0 | G44: =IF(D44<2,1,MEDIAN(0.5,2,1+(IFERROR(B44/C44,1)-1)*F44)) -> 1
... A92: 60 | B92: =SUMIFS('Draft Board'!$N$2:$N$61,'Draft Board'!$G$2:$G$61,A92,'Draft Board'!$N$2:$N$61,"<>") -> 0 | C92: =SUMIFS('Draft Board'!$M$2:$M$61,'Draft Board'!$G$2:$G$61,A92,'Draft Board'!$N$2:$N$61,"<>") -> 0 | D92: =COUNTIFS('Draft Board'!$G$2:$G$61,A92,'Draft Board'!$N$2:$N$61,"<>") -> 0 | E92: =IFERROR(AVERAGEIFS('Draft Board'!$M$2:$M$61,'Draft Board'!$G$2:$G$61,A92),0) -> 0 | F92: =MIN(1,E92/(Setup!$B$3*0.1)) -> 0 | G92: =IF(D92<2,1,MEDIAN(0.5,2,1+(IFERROR(B92/C92,1)-1)*F92)) -> 1
A94: RB tiers
A95: Tier | B95: Drafted Price Sum | C95: Drafted Static Sum | D95: Drafted Count | E95: Tier Avg Static | F95: Dampening | G95: Tier Factor
A96: 1 | B96: =SUMIFS('Draft Board'!$AD$2:$AD$161,'Draft Board'!$W$2:$W$161,A96,'Draft Board'!$AD$2:$AD$161,"<>") -> 0 | C96: =SUMIFS('Draft Board'!$AC$2:$AC$161,'Draft Board'!$W$2:$W$161,A96,'Draft Board'!$AD$2:$AD$161,"<>") -> 0 | D96: =COUNTIFS('Draft Board'!$W$2:$W$161,A96,'Draft Board'!$AD$2:$AD$161,"<>") -> 0 | E96: =IFERROR(AVERAGEIFS('Draft Board'!$AC$2:$AC$161,'Draft Board'!$W$2:$W$161,A96),0) -> 58 | F96: =MIN(1,E96/(Setup!$B$3*0.1)) -> 1 | G96: =IF(D96<2,1,MEDIAN(0.5,2,1+(IFERROR(B96/C96,1)-1)*F96)) -> 1
A97: 2 | B97: =SUMIFS('Draft Board'!$AD$2:$AD$161,'Draft Board'!$W$2:$W$161,A97,'Draft Board'!$AD$2:$AD$161,"<>") -> 0 | C97: =SUMIFS('Draft Board'!$AC$2:$AC$161,'Draft Board'!$W$2:$W$161,A97,'Draft Board'!$AD$2:$AD$161,"<>") -> 0 | D97: =COUNTIFS('Draft Board'!$W$2:$W$161,A97,'Draft Board'!$AD$2:$AD$161,"<>") -> 0 | E97: =IFERROR(AVERAGEIFS('Draft Board'!$AC$2:$AC$161,'Draft Board'!$W$2:$W$161,A97),0) -> 49 | F97: =MIN(1,E97/(Setup!$B$3*0.1)) -> 1 | G97: =IF(D97<2,1,MEDIAN(0.5,2,1+(IFERROR(B97/C97,1)-1)*F97)) -> 1
A98: 3 | B98: =SUMIFS('Draft Board'!$AD$2:$AD$161,'Draft Board'!$W$2:$W$161,A98,'Draft Board'!$AD$2:$AD$161,"<>") -> 0 | C98: =SUMIFS('Draft Board'!$AC$2:$AC$161,'Draft Board'!$W$2:$W$161,A98,'Draft Board'!$AD$2:$AD$161,"<>") -> 0 | D98: =COUNTIFS('Draft Board'!$W$2:$W$161,A98,'Draft Board'!$AD$2:$AD$161,"<>") -> 0 | E98: =IFERROR(AVERAGEIFS('Draft Board'!$AC$2:$AC$161,'Draft Board'!$W$2:$W$161,A98),0) -> 33.5 | F98: =MIN(1,E98/(Setup!$B$3*0.1)) -> 1 | G98: =IF(D98<2,1,MEDIAN(0.5,2,1+(IFERROR(B98/C98,1)-1)*F98)) -> 1
A99: 4 | B99: =SUMIFS('Draft Board'!$AD$2:$AD$161,'Draft Board'!$W$2:$W$161,A99,'Draft Board'!$AD$2:$AD$161,"<>") -> 0 | C99: =SUMIFS('Draft Board'!$AC$2:$AC$161,'Draft Board'!$W$2:$W$161,A99,'Draft Board'!$AD$2:$AD$161,"<>") -> 0 | D99: =COUNTIFS('Draft Board'!$W$2:$W$161,A99,'Draft Board'!$AD$2:$AD$161,"<>") -> 0 | E99: =IFERROR(AVERAGEIFS('Draft Board'!$AC$2:$AC$161,'Draft Board'!$W$2:$W$161,A99),0) -> 26.4 | F99: =MIN(1,E99/(Setup!$B$3*0.1)) -> 1 | G99: =IF(D99<2,1,MEDIAN(0.5,2,1+(IFERROR(B99/C99,1)-1)*F99)) -> 1
A100: 5 | B100: =SUMIFS('Draft Board'!$AD$2:$AD$161,'Draft Board'!$W$2:$W$161,A100,'Draft Board'!$AD$2:$AD$161,"<>") -> 0 | C100: =SUMIFS('Draft Board'!$AC$2:$AC$161,'Draft Board'!$W$2:$W$161,A100,'Draft Board'!$AD$2:$AD$161,"<>") -> 0 | D100: =COUNTIFS('Draft Board'!$W$2:$W$161,A100,'Draft Board'!$AD$2:$AD$161,"<>") -> 0 | E100: =IFERROR(AVERAGEIFS('Draft Board'!$AC$2:$AC$161,'Draft Board'!$W$2:$W$161,A100),0) -> 19.5 | F100: =MIN(1,E100/(Setup!$B$3*0.1)) -> 0.975 | G100: =IF(D100<2,1,MEDIAN(0.5,2,1+(IFERROR(B100/C100,1)-1)*F100)) -> 1
A101: 6 | B101: =SUMIFS('Draft Board'!$AD$2:$AD$161,'Draft Board'!$W$2:$W$161,A101,'Draft Board'!$AD$2:$AD$161,"<>") -> 0 | C101: =SUMIFS('Draft Board'!$AC$2:$AC$161,'Draft Board'!$W$2:$W$161,A101,'Draft Board'!$AD$2:$AD$161,"<>") -> 0 | D101: =COUNTIFS('Draft Board'!$W$2:$W$161,A101,'Draft Board'!$AD$2:$AD$161,"<>") -> 0 | E101: =IFERROR(AVERAGEIFS('Draft Board'!$AC$2:$AC$161,'Draft Board'!$W$2:$W$161,A101),0) -> 14.833333 | F101: =MIN(1,E101/(Setup!$B$3*0.1)) -> 0.74166667 | G101: =IF(D101<2,1,MEDIAN(0.5,2,1+(IFERROR(B101/C101,1)-1)*F101)) -> 1
A102: 7 | B102: =SUMIFS('Draft Board'!$AD$2:$AD$161,'Draft Board'!$W$2:$W$161,A102,'Draft Board'!$AD$2:$AD$161,"<>") -> 0 | C102: =SUMIFS('Draft Board'!$AC$2:$AC$161,'Draft Board'!$W$2:$W$161,A102,'Draft Board'!$AD$2:$AD$161,"<>") -> 0 | D102: =COUNTIFS('Draft Board'!$W$2:$W$161,A102,'Draft Board'!$AD$2:$AD$161,"<>") -> 0 | E102: =IFERROR(AVERAGEIFS('Draft Board'!$AC$2:$AC$161,'Draft Board'!$W$2:$W$161,A102),0) -> 10 | F102: =MIN(1,E102/(Setup!$B$3*0.1)) -> 0.5 | G102: =IF(D102<2,1,MEDIAN(0.5,2,1+(IFERROR(B102/C102,1)-1)*F102)) -> 1
A103: 8 | B103: =SUMIFS('Draft Board'!$AD$2:$AD$161,'Draft Board'!$W$2:$W$161,A103,'Draft Board'!$AD$2:$AD$161,"<>") -> 0 | C103: =SUMIFS('Draft Board'!$AC$2:$AC$161,'Draft Board'!$W$2:$W$161,A103,'Draft Board'!$AD$2:$AD$161,"<>") -> 0 | D103: =COUNTIFS('Draft Board'!$W$2:$W$161,A103,'Draft Board'!$AD$2:$AD$161,"<>") -> 0 | E103: =IFERROR(AVERAGEIFS('Draft Board'!$AC$2:$AC$161,'Draft Board'!$W$2:$W$161,A103),0) -> 8.3333333 | F103: =MIN(1,E103/(Setup!$B$3*0.1)) -> 0.41666667 | G103: =IF(D103<2,1,MEDIAN(0.5,2,1+(IFERROR(B103/C103,1)-1)*F103)) -> 1
A104: 9 | B104: =SUMIFS('Draft Board'!$AD$2:$AD$161,'Draft Board'!$W$2:$W$161,A104,'Draft Board'!$AD$2:$AD$161,"<>") -> 0 | C104: =SUMIFS('Draft Board'!$AC$2:$AC$161,'Draft Board'!$W$2:$W$161,A104,'Draft Board'!$AD$2:$AD$161,"<>") -> 0 | D104: =COUNTIFS('Draft Board'!$W$2:$W$161,A104,'Draft Board'!$AD$2:$AD$161,"<>") -> 0 | E104: =IFERROR(AVERAGEIFS('Draft Board'!$AC$2:$AC$161,'Draft Board'!$W$2:$W$161,A104),0) -> 7 | F104: =MIN(1,E104/(Setup!$B$3*0.1)) -> 0.35 | G104: =IF(D104<2,1,MEDIAN(0.5,2,1+(IFERROR(B104/C104,1)-1)*F104)) -> 1
A105: 10 | B105: =SUMIFS('Draft Board'!$AD$2:$AD$161,'Draft Board'!$W$2:$W$161,A105,'Draft Board'!$AD$2:$AD$161,"<>") -> 0 | C105: =SUMIFS('Draft Board'!$AC$2:$AC$161,'Draft Board'!$W$2:$W$161,A105,'Draft Board'!$AD$2:$AD$161,"<>") -> 0 | D105: =COUNTIFS('Draft Board'!$W$2:$W$161,A105,'Draft Board'!$AD$2:$AD$161,"<>") -> 0 | E105: =IFERROR(AVERAGEIFS('Draft Board'!$AC$2:$AC$161,'Draft Board'!$W$2:$W$161,A105),0) -> 6 | F105: =MIN(1,E105/(Setup!$B$3*0.1)) -> 0.3 | G105: =IF(D105<2,1,MEDIAN(0.5,2,1+(IFERROR(B105/C105,1)-1)*F105)) -> 1
A106: 11 | B106: =SUMIFS('Draft Board'!$AD$2:$AD$161,'Draft Board'!$W$2:$W$161,A106,'Draft Board'!$AD$2:$AD$161,"<>") -> 0 | C106: =SUMIFS('Draft Board'!$AC$2:$AC$161,'Draft Board'!$W$2:$W$161,A106,'Draft Board'!$AD$2:$AD$161,"<>") -> 0 | D106: =COUNTIFS('Draft Board'!$W$2:$W$161,A106,'Draft Board'!$AD$2:$AD$161,"<>") -> 0 | E106: =IFERROR(AVERAGEIFS('Draft Board'!$AC$2:$AC$161,'Draft Board'!$W$2:$W$161,A106),0) -> 5 | F106: =MIN(1,E106/(Setup!$B$3*0.1)) -> 0.25 | G106: =IF(D106<2,1,MEDIAN(0.5,2,1+(IFERROR(B106/C106,1)-1)*F106)) -> 1
A107: 12 | B107: =SUMIFS('Draft Board'!$AD$2:$AD$161,'Draft Board'!$W$2:$W$161,A107,'Draft Board'!$AD$2:$AD$161,"<>") -> 0 | C107: =SUMIFS('Draft Board'!$AC$2:$AC$161,'Draft Board'!$W$2:$W$161,A107,'Draft Board'!$AD$2:$AD$161,"<>") -> 0 | D107: =COUNTIFS('Draft Board'!$W$2:$W$161,A107,'Draft Board'!$AD$2:$AD$161,"<>") -> 0 | E107: =IFERROR(AVERAGEIFS('Draft Board'!$AC$2:$AC$161,'Draft Board'!$W$2:$W$161,A107),0) -> 5 | F107: =MIN(1,E107/(Setup!$B$3*0.1)) -> 0.25 | G107: =IF(D107<2,1,MEDIAN(0.5,2,1+(IFERROR(B107/C107,1)-1)*F107)) -> 1
... A255: 160 | B255: =SUMIFS('Draft Board'!$AD$2:$AD$161,'Draft Board'!$W$2:$W$161,A255,'Draft Board'!$AD$2:$AD$161,"<>") -> 0 | C255: =SUMIFS('Draft Board'!$AC$2:$AC$161,'Draft Board'!$W$2:$W$161,A255,'Draft Board'!$AD$2:$AD$161,"<>") -> 0 | D255: =COUNTIFS('Draft Board'!$W$2:$W$161,A255,'Draft Board'!$AD$2:$AD$161,"<>") -> 0 | E255: =IFERROR(AVERAGEIFS('Draft Board'!$AC$2:$AC$161,'Draft Board'!$W$2:$W$161,A255),0) -> 0 | F255: =MIN(1,E255/(Setup!$B$3*0.1)) -> 0 | G255: =IF(D255<2,1,MEDIAN(0.5,2,1+(IFERROR(B255/C255,1)-1)*F255)) -> 1
A257: WR tiers
A258: Tier | B258: Drafted Price Sum | C258: Drafted Static Sum | D258: Drafted Count | E258: Tier Avg Static | F258: Dampening | G258: Tier Factor
A259: 1 | B259: =SUMIFS('Draft Board'!$AT$2:$AT$193,'Draft Board'!$AM$2:$AM$193,A259,'Draft Board'!$AT$2:$AT$193,"<>") -> 0 | C259: =SUMIFS('Draft Board'!$AS$2:$AS$193,'Draft Board'!$AM$2:$AM$193,A259,'Draft Board'!$AT$2:$AT$193,"<>") -> 0 | D259: =COUNTIFS('Draft Board'!$AM$2:$AM$193,A259,'Draft Board'!$AT$2:$AT$193,"<>") -> 0 | E259: =IFERROR(AVERAGEIFS('Draft Board'!$AS$2:$AS$193,'Draft Board'!$AM$2:$AM$193,A259),0) -> 53 | F259: =MIN(1,E259/(Setup!$B$3*0.1)) -> 1 | G259: =IF(D259<2,1,MEDIAN(0.5,2,1+(IFERROR(B259/C259,1)-1)*F259)) -> 1
A260: 2 | B260: =SUMIFS('Draft Board'!$AT$2:$AT$193,'Draft Board'!$AM$2:$AM$193,A260,'Draft Board'!$AT$2:$AT$193,"<>") -> 0 | C260: =SUMIFS('Draft Board'!$AS$2:$AS$193,'Draft Board'!$AM$2:$AM$193,A260,'Draft Board'!$AT$2:$AT$193,"<>") -> 0 | D260: =COUNTIFS('Draft Board'!$AM$2:$AM$193,A260,'Draft Board'!$AT$2:$AT$193,"<>") -> 0 | E260: =IFERROR(AVERAGEIFS('Draft Board'!$AS$2:$AS$193,'Draft Board'!$AM$2:$AM$193,A260),0) -> 45.5 | F260: =MIN(1,E260/(Setup!$B$3*0.1)) -> 1 | G260: =IF(D260<2,1,MEDIAN(0.5,2,1+(IFERROR(B260/C260,1)-1)*F260)) -> 1
A261: 3 | B261: =SUMIFS('Draft Board'!$AT$2:$AT$193,'Draft Board'!$AM$2:$AM$193,A261,'Draft Board'!$AT$2:$AT$193,"<>") -> 0 | C261: =SUMIFS('Draft Board'!$AS$2:$AS$193,'Draft Board'!$AM$2:$AM$193,A261,'Draft Board'!$AT$2:$AT$193,"<>") -> 0 | D261: =COUNTIFS('Draft Board'!$AM$2:$AM$193,A261,'Draft Board'!$AT$2:$AT$193,"<>") -> 0 | E261: =IFERROR(AVERAGEIFS('Draft Board'!$AS$2:$AS$193,'Draft Board'!$AM$2:$AM$193,A261),0) -> 33.333333 | F261: =MIN(1,E261/(Setup!$B$3*0.1)) -> 1 | G261: =IF(D261<2,1,MEDIAN(0.5,2,1+(IFERROR(B261/C261,1)-1)*F261)) -> 1
A262: 4 | B262: =SUMIFS('Draft Board'!$AT$2:$AT$193,'Draft Board'!$AM$2:$AM$193,A262,'Draft Board'!$AT$2:$AT$193,"<>") -> 0 | C262: =SUMIFS('Draft Board'!$AS$2:$AS$193,'Draft Board'!$AM$2:$AM$193,A262,'Draft Board'!$AT$2:$AT$193,"<>") -> 0 | D262: =COUNTIFS('Draft Board'!$AM$2:$AM$193,A262,'Draft Board'!$AT$2:$AT$193,"<>") -> 0 | E262: =IFERROR(AVERAGEIFS('Draft Board'!$AS$2:$AS$193,'Draft Board'!$AM$2:$AM$193,A262),0) -> 25.444444 | F262: =MIN(1,E262/(Setup!$B$3*0.1)) -> 1 | G262: =IF(D262<2,1,MEDIAN(0.5,2,1+(IFERROR(B262/C262,1)-1)*F262)) -> 1
A263: 5 | B263: =SUMIFS('Draft Board'!$AT$2:$AT$193,'Draft Board'!$AM$2:$AM$193,A263,'Draft Board'!$AT$2:$AT$193,"<>") -> 0 | C263: =SUMIFS('Draft Board'!$AS$2:$AS$193,'Draft Board'!$AM$2:$AM$193,A263,'Draft Board'!$AT$2:$AT$193,"<>") -> 0 | D263: =COUNTIFS('Draft Board'!$AM$2:$AM$193,A263,'Draft Board'!$AT$2:$AT$193,"<>") -> 0 | E263: =IFERROR(AVERAGEIFS('Draft Board'!$AS$2:$AS$193,'Draft Board'!$AM$2:$AM$193,A263),0) -> 18.7 | F263: =MIN(1,E263/(Setup!$B$3*0.1)) -> 0.935 | G263: =IF(D263<2,1,MEDIAN(0.5,2,1+(IFERROR(B263/C263,1)-1)*F263)) -> 1
A264: 6 | B264: =SUMIFS('Draft Board'!$AT$2:$AT$193,'Draft Board'!$AM$2:$AM$193,A264,'Draft Board'!$AT$2:$AT$193,"<>") -> 0 | C264: =SUMIFS('Draft Board'!$AS$2:$AS$193,'Draft Board'!$AM$2:$AM$193,A264,'Draft Board'!$AT$2:$AT$193,"<>") -> 0 | D264: =COUNTIFS('Draft Board'!$AM$2:$AM$193,A264,'Draft Board'!$AT$2:$AT$193,"<>") -> 0 | E264: =IFERROR(AVERAGEIFS('Draft Board'!$AS$2:$AS$193,'Draft Board'!$AM$2:$AM$193,A264),0) -> 15 | F264: =MIN(1,E264/(Setup!$B$3*0.1)) -> 0.75 | G264: =IF(D264<2,1,MEDIAN(0.5,2,1+(IFERROR(B264/C264,1)-1)*F264)) -> 1
A265: 7 | B265: =SUMIFS('Draft Board'!$AT$2:$AT$193,'Draft Board'!$AM$2:$AM$193,A265,'Draft Board'!$AT$2:$AT$193,"<>") -> 0 | C265: =SUMIFS('Draft Board'!$AS$2:$AS$193,'Draft Board'!$AM$2:$AM$193,A265,'Draft Board'!$AT$2:$AT$193,"<>") -> 0 | D265: =COUNTIFS('Draft Board'!$AM$2:$AM$193,A265,'Draft Board'!$AT$2:$AT$193,"<>") -> 0 | E265: =IFERROR(AVERAGEIFS('Draft Board'!$AS$2:$AS$193,'Draft Board'!$AM$2:$AM$193,A265),0) -> 12.428571 | F265: =MIN(1,E265/(Setup!$B$3*0.1)) -> 0.62142857 | G265: =IF(D265<2,1,MEDIAN(0.5,2,1+(IFERROR(B265/C265,1)-1)*F265)) -> 1
A266: 8 | B266: =SUMIFS('Draft Board'!$AT$2:$AT$193,'Draft Board'!$AM$2:$AM$193,A266,'Draft Board'!$AT$2:$AT$193,"<>") -> 0 | C266: =SUMIFS('Draft Board'!$AS$2:$AS$193,'Draft Board'!$AM$2:$AM$193,A266,'Draft Board'!$AT$2:$AT$193,"<>") -> 0 | D266: =COUNTIFS('Draft Board'!$AM$2:$AM$193,A266,'Draft Board'!$AT$2:$AT$193,"<>") -> 0 | E266: =IFERROR(AVERAGEIFS('Draft Board'!$AS$2:$AS$193,'Draft Board'!$AM$2:$AM$193,A266),0) -> 10 | F266: =MIN(1,E266/(Setup!$B$3*0.1)) -> 0.5 | G266: =IF(D266<2,1,MEDIAN(0.5,2,1+(IFERROR(B266/C266,1)-1)*F266)) -> 1
A267: 9 | B267: =SUMIFS('Draft Board'!$AT$2:$AT$193,'Draft Board'!$AM$2:$AM$193,A267,'Draft Board'!$AT$2:$AT$193,"<>") -> 0 | C267: =SUMIFS('Draft Board'!$AS$2:$AS$193,'Draft Board'!$AM$2:$AM$193,A267,'Draft Board'!$AT$2:$AT$193,"<>") -> 0 | D267: =COUNTIFS('Draft Board'!$AM$2:$AM$193,A267,'Draft Board'!$AT$2:$AT$193,"<>") -> 0 | E267: =IFERROR(AVERAGEIFS('Draft Board'!$AS$2:$AS$193,'Draft Board'!$AM$2:$AM$193,A267),0) -> 8.7142857 | F267: =MIN(1,E267/(Setup!$B$3*0.1)) -> 0.43571429 | G267: =IF(D267<2,1,MEDIAN(0.5,2,1+(IFERROR(B267/C267,1)-1)*F267)) -> 1
A268: 10 | B268: =SUMIFS('Draft Board'!$AT$2:$AT$193,'Draft Board'!$AM$2:$AM$193,A268,'Draft Board'!$AT$2:$AT$193,"<>") -> 0 | C268: =SUMIFS('Draft Board'!$AS$2:$AS$193,'Draft Board'!$AM$2:$AM$193,A268,'Draft Board'!$AT$2:$AT$193,"<>") -> 0 | D268: =COUNTIFS('Draft Board'!$AM$2:$AM$193,A268,'Draft Board'!$AT$2:$AT$193,"<>") -> 0 | E268: =IFERROR(AVERAGEIFS('Draft Board'!$AS$2:$AS$193,'Draft Board'!$AM$2:$AM$193,A268),0) -> 7 | F268: =MIN(1,E268/(Setup!$B$3*0.1)) -> 0.35 | G268: =IF(D268<2,1,MEDIAN(0.5,2,1+(IFERROR(B268/C268,1)-1)*F268)) -> 1
A269: 11 | B269: =SUMIFS('Draft Board'!$AT$2:$AT$193,'Draft Board'!$AM$2:$AM$193,A269,'Draft Board'!$AT$2:$AT$193,"<>") -> 0 | C269: =SUMIFS('Draft Board'!$AS$2:$AS$193,'Draft Board'!$AM$2:$AM$193,A269,'Draft Board'!$AT$2:$AT$193,"<>") -> 0 | D269: =COUNTIFS('Draft Board'!$AM$2:$AM$193,A269,'Draft Board'!$AT$2:$AT$193,"<>") -> 0 | E269: =IFERROR(AVERAGEIFS('Draft Board'!$AS$2:$AS$193,'Draft Board'!$AM$2:$AM$193,A269),0) -> 6 | F269: =MIN(1,E269/(Setup!$B$3*0.1)) -> 0.3 | G269: =IF(D269<2,1,MEDIAN(0.5,2,1+(IFERROR(B269/C269,1)-1)*F269)) -> 1
A270: 12 | B270: =SUMIFS('Draft Board'!$AT$2:$AT$193,'Draft Board'!$AM$2:$AM$193,A270,'Draft Board'!$AT$2:$AT$193,"<>") -> 0 | C270: =SUMIFS('Draft Board'!$AS$2:$AS$193,'Draft Board'!$AM$2:$AM$193,A270,'Draft Board'!$AT$2:$AT$193,"<>") -> 0 | D270: =COUNTIFS('Draft Board'!$AM$2:$AM$193,A270,'Draft Board'!$AT$2:$AT$193,"<>") -> 0 | E270: =IFERROR(AVERAGEIFS('Draft Board'!$AS$2:$AS$193,'Draft Board'!$AM$2:$AM$193,A270),0) -> 5 | F270: =MIN(1,E270/(Setup!$B$3*0.1)) -> 0.25 | G270: =IF(D270<2,1,MEDIAN(0.5,2,1+(IFERROR(B270/C270,1)-1)*F270)) -> 1
... A450: 192 | B450: =SUMIFS('Draft Board'!$AT$2:$AT$193,'Draft Board'!$AM$2:$AM$193,A450,'Draft Board'!$AT$2:$AT$193,"<>") -> 0 | C450: =SUMIFS('Draft Board'!$AS$2:$AS$193,'Draft Board'!$AM$2:$AM$193,A450,'Draft Board'!$AT$2:$AT$193,"<>") -> 0 | D450: =COUNTIFS('Draft Board'!$AM$2:$AM$193,A450,'Draft Board'!$AT$2:$AT$193,"<>") -> 0 | E450: =IFERROR(AVERAGEIFS('Draft Board'!$AS$2:$AS$193,'Draft Board'!$AM$2:$AM$193,A450),0) -> 0 | F450: =MIN(1,E450/(Setup!$B$3*0.1)) -> 0 | G450: =IF(D450<2,1,MEDIAN(0.5,2,1+(IFERROR(B450/C450,1)-1)*F450)) -> 1
A452: TE tiers
A453: Tier | B453: Drafted Price Sum | C453: Drafted Static Sum | D453: Drafted Count | E453: Tier Avg Static | F453: Dampening | G453: Tier Factor
A454: 1 | B454: =SUMIFS('Draft Board'!$BJ$2:$BJ$87,'Draft Board'!$BC$2:$BC$87,A454,'Draft Board'!$BJ$2:$BJ$87,"<>") -> 0 | C454: =SUMIFS('Draft Board'!$BI$2:$BI$87,'Draft Board'!$BC$2:$BC$87,A454,'Draft Board'!$BJ$2:$BJ$87,"<>") -> 0 | D454: =COUNTIFS('Draft Board'!$BC$2:$BC$87,A454,'Draft Board'!$BJ$2:$BJ$87,"<>") -> 0 | E454: =IFERROR(AVERAGEIFS('Draft Board'!$BI$2:$BI$87,'Draft Board'!$BC$2:$BC$87,A454),0) -> 25 | F454: =MIN(1,E454/(Setup!$B$3*0.1)) -> 1 | G454: =IF(D454<2,1,MEDIAN(0.5,2,1+(IFERROR(B454/C454,1)-1)*F454)) -> 1
A455: 2 | B455: =SUMIFS('Draft Board'!$BJ$2:$BJ$87,'Draft Board'!$BC$2:$BC$87,A455,'Draft Board'!$BJ$2:$BJ$87,"<>") -> 0 | C455: =SUMIFS('Draft Board'!$BI$2:$BI$87,'Draft Board'!$BC$2:$BC$87,A455,'Draft Board'!$BJ$2:$BJ$87,"<>") -> 0 | D455: =COUNTIFS('Draft Board'!$BC$2:$BC$87,A455,'Draft Board'!$BJ$2:$BJ$87,"<>") -> 0 | E455: =IFERROR(AVERAGEIFS('Draft Board'!$BI$2:$BI$87,'Draft Board'!$BC$2:$BC$87,A455),0) -> 19 | F455: =MIN(1,E455/(Setup!$B$3*0.1)) -> 0.95 | G455: =IF(D455<2,1,MEDIAN(0.5,2,1+(IFERROR(B455/C455,1)-1)*F455)) -> 1
A456: 3 | B456: =SUMIFS('Draft Board'!$BJ$2:$BJ$87,'Draft Board'!$BC$2:$BC$87,A456,'Draft Board'!$BJ$2:$BJ$87,"<>") -> 0 | C456: =SUMIFS('Draft Board'!$BI$2:$BI$87,'Draft Board'!$BC$2:$BC$87,A456,'Draft Board'!$BJ$2:$BJ$87,"<>") -> 0 | D456: =COUNTIFS('Draft Board'!$BC$2:$BC$87,A456,'Draft Board'!$BJ$2:$BJ$87,"<>") -> 0 | E456: =IFERROR(AVERAGEIFS('Draft Board'!$BI$2:$BI$87,'Draft Board'!$BC$2:$BC$87,A456),0) -> 17 | F456: =MIN(1,E456/(Setup!$B$3*0.1)) -> 0.85 | G456: =IF(D456<2,1,MEDIAN(0.5,2,1+(IFERROR(B456/C456,1)-1)*F456)) -> 1
A457: 4 | B457: =SUMIFS('Draft Board'!$BJ$2:$BJ$87,'Draft Board'!$BC$2:$BC$87,A457,'Draft Board'!$BJ$2:$BJ$87,"<>") -> 0 | C457: =SUMIFS('Draft Board'!$BI$2:$BI$87,'Draft Board'!$BC$2:$BC$87,A457,'Draft Board'!$BJ$2:$BJ$87,"<>") -> 0 | D457: =COUNTIFS('Draft Board'!$BC$2:$BC$87,A457,'Draft Board'!$BJ$2:$BJ$87,"<>") -> 0 | E457: =IFERROR(AVERAGEIFS('Draft Board'!$BI$2:$BI$87,'Draft Board'!$BC$2:$BC$87,A457),0) -> 12.5 | F457: =MIN(1,E457/(Setup!$B$3*0.1)) -> 0.625 | G457: =IF(D457<2,1,MEDIAN(0.5,2,1+(IFERROR(B457/C457,1)-1)*F457)) -> 1
A458: 5 | B458: =SUMIFS('Draft Board'!$BJ$2:$BJ$87,'Draft Board'!$BC$2:$BC$87,A458,'Draft Board'!$BJ$2:$BJ$87,"<>") -> 0 | C458: =SUMIFS('Draft Board'!$BI$2:$BI$87,'Draft Board'!$BC$2:$BC$87,A458,'Draft Board'!$BJ$2:$BJ$87,"<>") -> 0 | D458: =COUNTIFS('Draft Board'!$BC$2:$BC$87,A458,'Draft Board'!$BJ$2:$BJ$87,"<>") -> 0 | E458: =IFERROR(AVERAGEIFS('Draft Board'!$BI$2:$BI$87,'Draft Board'!$BC$2:$BC$87,A458),0) -> 9.6666667 | F458: =MIN(1,E458/(Setup!$B$3*0.1)) -> 0.48333333 | G458: =IF(D458<2,1,MEDIAN(0.5,2,1+(IFERROR(B458/C458,1)-1)*F458)) -> 1
