Workbook

Sheet Start Here
B2: 2026 PROJECTIONS - DIRECT ENTRY (v2)
B4: What changed from v1
B5: v1: you entered percentages, everything else was derived, and nothing
B6: could exceed the team total. Yards per carry was an output.
B7: v2: you type the real numbers. Rates and shares are computed as
B8: checks. Nothing is auto-balanced - the footer tells you when you've
B9: gone over instead of silently absorbing it.
B11: Colours
B12: BLUE you type here
B13: CREAM what he actually did - 2023/24/25 volume, yards, team, games
B14: GREY computed: rates, shares, per-game, change vs last year
B16: The footer is the control
... B49: dCar, dTgt change vs last season - big jumps stand out

Sheet ARI
A1: ARI - 2026 projections (direct entry)
A3: TEAM TOTALS | D3: all editable - these are your targets, not hard caps
B4: Games | C4: Plays/G | D4: Plays | E4: Pass Rate | F4: Pass Att | G4: Targets | H4: Rush Att | I4: Pass Yds | J4: Pass TD | K4: Int | L4: Rush Yds | M4: Rush TD
B5: 17 | C5: 62.2 | D5: =C5*B5 -> 1057.4 | E5: 0.595 | F5: =ROUND(D5*E5,0) -> 629 | G5: =ROUND(F5*Settings!$B$4,0) -> 600 | H5: =D5-F5 -> 428.4 | I5: 3992 | J5: 25 | K5: 12 | L5: 1940 | M5: 14
A7: VACATED | B7: 24% of targets and 70% of carries left this roster - that volume is yours to reassign.
A8: STAFF | B8: NEW HC Mike LaFleur + OC Nathaniel Hackett. Pass rate projected to DROP 69.4% -> 58%. Biggest scheme change in the league - revisit Pass Rate above.
A10: Pos | B10: Player | C10: Dep | D10: Age | E10: Status | F10: '23 Car | G10: '24 Car | H10: '25 Car | I10: '25 RuYd | J10: '23 Tgt | K10: '24 Tgt | L10: '25 Tgt | M10: '25 ReYd | N10: '25 Tm | O10: '25 G | P10: 3y Y/C | Q10: 3y Y/R | R10: 3y Ctch | S10: 3y Comp% | T10: 3y Y/A | U10: Games | V10: Pass Att | W10: Cmp | X10: Pass Yds | Y10: Pass TD | Z10: Int | AA10: Rush Att | AB10: Rush Yds | AC10: Rush TD | AD10: Targets | AE10: Rec | AF10: Rec Yds | AG10: Rec TD | AH10: Seed | AI10: Y/C | AJ10: Y/R | AK10: Catch% | AL10: Y/A | AM10: Comp% | AN10: Rush % | AO10: Tgt % | AP10: Pass % | AQ10: Car/G | AR10: Tgt/G | AS10: dTgt | AT10: dCar | AU10: Half PPR
A11: QB | B11: Jacoby Brissett | C11: 1 | D11: 33 | E11: ACT | F11: 3 | G11: 12 | H11: 36 | I11: 168 | N11: ARI | O11: 14 | P11: 4.88 | S11: 0.64 | T11: 6.6 | U11: 17 | V11: 509 | W11: 319 | X11: 3366 | Y11: 21 | Z11: 10 | AA11: 44 | AB11: 193 | AC11: 1 | AD11: 0 | AE11: 0 | AF11: 0 | AG11: 0 | AH11: kept | AI11: =IFERROR(AB11/AA11,"") -> 4.3863636 | AJ11: =IFERROR(AF11/AE11,"") | AK11: =IFERROR(AE11/AD11,"") | AL11: =IFERROR(X11/V11,"") -> 6.6129666 | AM11: =IFERROR(W11/V11,"") -> 0.62671906 | AN11: =IFERROR(AA11/$H$5,"") -> 0.10270775 | AO11: =IFERROR(AD11/$G$5,"") -> 0 | AP11: =IFERROR(V11/$F$5,"") -> 0.80922099 | AQ11: =IFERROR(AA11/U11,"") -> 2.5882353 | AR11: =IFERROR(AD11/U11,"") -> 0 | AS11: =IFERROR(AD11-L11,"") -> 0 | AT11: =IFERROR(AA11-H11,"") -> 8 | AU11: =AF11*Settings!$B$7+AG11*Settings!$B$8+AE11*Settings!$B$9+AB11*Settings!$B$10+AC11*Settings!$B$11+X11*Settings!$B$12+Y11*Settings!$B$13+Z11*Settings!$B$14 -> 223.94
A12: QB | B12: Carson Beck | C12: 2 | D12: 23 | E12: ACT | U12: 17 | V12: 101 | W12: 52 | X12: 624 | Y12: 4 | Z12: 2 | AA12: 6 | AB12: 21 | AC12: 0 | AH12: kept | AI12: =IFERROR(AB12/AA12,"") -> 3.5 | AJ12: =IFERROR(AF12/AE12,"") | AK12: =IFERROR(AE12/AD12,"") | AL12: =IFERROR(X12/V12,"") -> 6.1782178 | AM12: =IFERROR(W12/V12,"") -> 0.51485149 | AN12: =IFERROR(AA12/$H$5,"") -> 0.014005602 | AO12: =IFERROR(AD12/$G$5,"") -> 0 | AP12: =IFERROR(V12/$F$5,"") -> 0.16057234 | AQ12: =IFERROR(AA12/U12,"") -> 0.35294118 | AR12: =IFERROR(AD12/U12,"") -> 0 | AS12: =IFERROR(AD12-L12,"") -> 0 | AT12: =IFERROR(AA12-H12,"") -> 6 | AU12: =AF12*Settings!$B$7+AG12*Settings!$B$8+AE12*Settings!$B$9+AB12*Settings!$B$10+AC12*Settings!$B$11+X12*Settings!$B$12+Y12*Settings!$B$13+Z12*Settings!$B$14 -> 39.06
A13: QB | B13: Kedon Slovis | C13: 3 | D13: 25 | E13: ACT | N13: ARI | O13: 2 | S13: 0.5 | U13: 17 | V13: 12 | W13: 8 | X13: 33 | Y13: 0 | Z13: 0 | AA13: 0 | AB13: 0 | AC13: 0 | AD13: 0 | AE13: 0 | AF13: 0 | AG13: 0 | AH13: kept | AI13: =IFERROR(AB13/AA13,"") | AJ13: =IFERROR(AF13/AE13,"") | AK13: =IFERROR(AE13/AD13,"") | AL13: =IFERROR(X13/V13,"") -> 2.75 | AM13: =IFERROR(W13/V13,"") -> 0.66666667 | AN13: =IFERROR(AA13/$H$5,"") -> 0 | AO13: =IFERROR(AD13/$G$5,"") -> 0 | AP13: =IFERROR(V13/$F$5,"") -> 0.019077901 | AQ13: =IFERROR(AA13/U13,"") -> 0 | AR13: =IFERROR(AD13/U13,"") -> 0 | AS13: =IFERROR(AD13-L13,"") -> 0 | AT13: =IFERROR(AA13-H13,"") -> 0 | AU13: =AF13*Settings!$B$7+AG13*Settings!$B$8+AE13*Settings!$B$9+AB13*Settings!$B$10+AC13*Settings!$B$11+X13*Settings!$B$12+Y13*Settings!$B$13+Z13*Settings!$B$14 -> 1.32
A14: QB | B14: Other QBs | U14: 17 | AI14: =IFERROR(AB14/AA14,"") | AJ14: =IFERROR(AF14/AE14,"") | AK14: =IFERROR(AE14/AD14,"") | AL14: =IFERROR(X14/V14,"") | AM14: =IFERROR(W14/V14,"") | AN14: =IFERROR(AA14/$H$5,"") -> 0 | AO14: =IFERROR(AD14/$G$5,"") -> 0 | AP14: =IFERROR(V14/$F$5,"") -> 0 | AQ14: =IFERROR(AA14/U14,"") -> 0 | AR14: =IFERROR(AD14/U14,"") -> 0 | AS14: =IFERROR(AD14-L14,"") -> 0 | AT14: =IFERROR(AA14-H14,"") -> 0 | AU14: =AF14*Settings!$B$7+AG14*Settings!$B$8+AE14*Settings!$B$9+AB14*Settings!$B$10+AC14*Settings!$B$11+X14*Settings!$B$12+Y14*Settings!$B$13+Z14*Settings!$B$14 -> 0
A15: RB | B15: Jeremiyah Love | C15: 1 | D15: 21 | E15: ACT | U15: 17 | AA15: 221 | AB15: 1022 | AC15: 6 | AD15: 67 | AE15: 49 | AF15: 408 | AG15: 2 | AH15: kept | AI15: =IFERROR(AB15/AA15,"") -> 4.6244344 | AJ15: =IFERROR(AF15/AE15,"") -> 8.3265306 | AK15: =IFERROR(AE15/AD15,"") -> 0.73134328 | AL15: =IFERROR(X15/V15,"") | AM15: =IFERROR(W15/V15,"") | AN15: =IFERROR(AA15/$H$5,"") -> 0.51587302 | AO15: =IFERROR(AD15/$G$5,"") -> 0.11166667 | AP15: =IFERROR(V15/$F$5,"") -> 0 | AQ15: =IFERROR(AA15/U15,"") -> 13 | AR15: =IFERROR(AD15/U15,"") -> 3.9411765 | AS15: =IFERROR(AD15-L15,"") -> 67 | AT15: =IFERROR(AA15-H15,"") -> 221 | AU15: =AF15*Settings!$B$7+AG15*Settings!$B$8+AE15*Settings!$B$9+AB15*Settings!$B$10+AC15*Settings!$B$11+X15*Settings!$B$12+Y15*Settings!$B$13+Z15*Settings!$B$14 -> 215.5
A16: RB | B16: Tyler Allgeier | C16: 2 | D16: 26 | E16: ACT | F16: 186 | G16: 137 | H16: 143 | I16: 514 | J16: 23 | K16: 13 | L16: 16 | M16: 96 | N16: ATL | O16: 17 | P16: 3.95 | Q16: 8.38 | R16: 0.865 | U16: 17 | V16: 0 | W16: 0 | X16: 0 | Y16: 0 | Z16: 0 | AA16: 107 | AB16: 485 | AC16: 5 | AD16: 15 | AE16: 9 | AF16: 88 | AG16: 0 | AH16: kept | AI16: =IFERROR(AB16/AA16,"") -> 4.5327103 | AJ16: =IFERROR(AF16/AE16,"") -> 9.7777778 | AK16: =IFERROR(AE16/AD16,"") -> 0.6 | AL16: =IFERROR(X16/V16,"") | AM16: =IFERROR(W16/V16,"") | AN16: =IFERROR(AA16/$H$5,"") -> 0.24976657 | AO16: =IFERROR(AD16/$G$5,"") -> 0.025 | AP16: =IFERROR(V16/$F$5,"") -> 0 | AQ16: =IFERROR(AA16/U16,"") -> 6.2941176 | AR16: =IFERROR(AD16/U16,"") -> 0.88235294 | AS16: =IFERROR(AD16-L16,"") -> -1 | AT16: =IFERROR(AA16-H16,"") -> -36 | AU16: =AF16*Settings!$B$7+AG16*Settings!$B$8+AE16*Settings!$B$9+AB16*Settings!$B$10+AC16*Settings!$B$11+X16*Settings!$B$12+Y16*Settings!$B$13+Z16*Settings!$B$14 -> 91.8
A17: RB | B17: James Conner | C17: 3 | D17: 31 | E17: QUESTIONABLE | F17: 208 | G17: 236 | H17: 32 | I17: 95 | J17: 33 | K17: 55 | L17: 9 | M17: 38 | N17: ARI | O17: 3 | P17: 4.68 | Q17: 7.52 | R17: 0.845 | U17: 17 | V17: 0 | W17: 0 | X17: 0 | Y17: 0 | Z17: 0 | AA17: 33 | AB17: 148 | AC17: 1 | AD17: 16 | AE17: 12 | AF17: 90 | AG17: 1 | AH17: kept | AI17: =IFERROR(AB17/AA17,"") -> 4.4848485 | AJ17: =IFERROR(AF17/AE17,"") -> 7.5 | AK17: =IFERROR(AE17/AD17,"") -> 0.75 | AL17: =IFERROR(X17/V17,"") | AM17: =IFERROR(W17/V17,"") | AN17: =IFERROR(AA17/$H$5,"") -> 0.077030812 | AO17: =IFERROR(AD17/$G$5,"") -> 0.026666667 | AP17: =IFERROR(V17/$F$5,"") -> 0 | AQ17: =IFERROR(AA17/U17,"") -> 1.9411765 | AR17: =IFERROR(AD17/U17,"") -> 0.94117647 | AS17: =IFERROR(AD17-L17,"") -> 7 | AT17: =IFERROR(AA17-H17,"") -> 1 | AU17: =AF17*Settings!$B$7+AG17*Settings!$B$8+AE17*Settings!$B$9+AB17*Settings!$B$10+AC17*Settings!$B$11+X17*Settings!$B$12+Y17*Settings!$B$13+Z17*Settings!$B$14 -> 41.8
A18: RB | B18: Zonovan Knight | C18: 4 | D18: 25 | E18: ACT | F18: 3 | H18: 82 | I18: 269 | J18: 1 | L18: 31 | M18: 160 | N18: ARI | O18: 12 | P18: 3.32 | Q18: 7.3 | R18: 0.719 | U18: 17 | V18: 0 | W18: 0 | X18: 0 | Y18: 0 | Z18: 0 | AA18: 5 | AB18: 21 | AC18: 0 | AD18: 0 | AE18: 0 | AF18: 0 | AG18: 0 | AH18: kept | AI18: =IFERROR(AB18/AA18,"") -> 4.2 | AJ18: =IFERROR(AF18/AE18,"") | AK18: =IFERROR(AE18/AD18,"") | AL18: =IFERROR(X18/V18,"") | AM18: =IFERROR(W18/V18,"") | AN18: =IFERROR(AA18/$H$5,"") -> 0.011671335 | AO18: =IFERROR(AD18/$G$5,"") -> 0 | AP18: =IFERROR(V18/$F$5,"") -> 0 | AQ18: =IFERROR(AA18/U18,"") -> 0.29411765 | AR18: =IFERROR(AD18/U18,"") -> 0 | AS18: =IFERROR(AD18-L18,"") -> -31 | AT18: =IFERROR(AA18-H18,"") -> -77 | AU18: =AF18*Settings!$B$7+AG18*Settings!$B$8+AE18*Settings!$B$9+AB18*Settings!$B$10+AC18*Settings!$B$11+X18*Settings!$B$12+Y18*Settings!$B$13+Z18*Settings!$B$14 -> 2.1
A19: RB | B19: Trey Benson | C19: 5 | D19: 24 | E19: ACT | G19: 63 | H19: 29 | I19: 160 | K19: 6 | L19: 16 | M19: 64 | N19: ARI | O19: 4 | P19: 4.9 | Q19: 6.47 | R19: 0.864 | U19: 17 | V19: 0 | W19: 0 | X19: 0 | Y19: 0 | Z19: 0 | AA19: 11 | AB19: 44 | AC19: 0 | AD19: 5 | AE19: 4 | AF19: 31 | AG19: 0 | AH19: kept | AI19: =IFERROR(AB19/AA19,"") -> 4 | AJ19: =IFERROR(AF19/AE19,"") -> 7.75 | AK19: =IFERROR(AE19/AD19,"") -> 0.8 | AL19: =IFERROR(X19/V19,"") | AM19: =IFERROR(W19/V19,"") | AN19: =IFERROR(AA19/$H$5,"") -> 0.025676937 | AO19: =IFERROR(AD19/$G$5,"") -> 0.0083333333 | AP19: =IFERROR(V19/$F$5,"") -> 0 | AQ19: =IFERROR(AA19/U19,"") -> 0.64705882 | AR19: =IFERROR(AD19/U19,"") -> 0.29411765 | AS19: =IFERROR(AD19-L19,"") -> -11 | AT19: =IFERROR(AA19-H19,"") -> -18 | AU19: =AF19*Settings!$B$7+AG19*Settings!$B$8+AE19*Settings!$B$9+AB19*Settings!$B$10+AC19*Settings!$B$11+X19*Settings!$B$12+Y19*Settings!$B$13+Z19*Settings!$B$14 -> 9.5
A20: RB | B20: Corey Kiner | C20: 6 | D20: 24 | E20: ACT | H20: 12 | I20: 58 | L20: 3 | M20: 15 | N20: ARI | O20: 4 | P20: 4.83 | Q20: 7.5 | R20: 0.667 | U20: 17 | V20: 0 | W20: 0 | X20: 0 | Y20: 0 | Z20: 0 | AA20: 0 | AB20: 0 | AC20: 0 | AD20: 0 | AE20: 0 | AF20: 0 | AG20: 0 | AH20: kept | AI20: =IFERROR(AB20/AA20,"") | AJ20: =IFERROR(AF20/AE20,"") | AK20: =IFERROR(AE20/AD20,"") | AL20: =IFERROR(X20/V20,"") | AM20: =IFERROR(W20/V20,"") | AN20: =IFERROR(AA20/$H$5,"") -> 0 | AO20: =IFERROR(AD20/$G$5,"") -> 0 | AP20: =IFERROR(V20/$F$5,"") -> 0 | AQ20: =IFERROR(AA20/U20,"") -> 0 | AR20: =IFERROR(AD20/U20,"") -> 0 | AS20: =IFERROR(AD20-L20,"") -> -3 | AT20: =IFERROR(AA20-H20,"") -> -12 | AU20: =AF20*Settings!$B$7+AG20*Settings!$B$8+AE20*Settings!$B$9+AB20*Settings!$B$10+AC20*Settings!$B$11+X20*Settings!$B$12+Y20*Settings!$B$13+Z20*Settings!$B$14 -> 0
A21: RB | B21: Other RBs | U21: 17 | AI21: =IFERROR(AB21/AA21,"") | AJ21: =IFERROR(AF21/AE21,"") | AK21: =IFERROR(AE21/AD21,"") | AL21: =IFERROR(X21/V21,"") | AM21: =IFERROR(W21/V21,"") | AN21: =IFERROR(AA21/$H$5,"") -> 0 | AO21: =IFERROR(AD21/$G$5,"") -> 0 | AP21: =IFERROR(V21/$F$5,"") -> 0 | AQ21: =IFERROR(AA21/U21,"") -> 0 | AR21: =IFERROR(AD21/U21,"") -> 0 | AS21: =IFERROR(AD21-L21,"") -> 0 | AT21: =IFERROR(AA21-H21,"") -> 0 | AU21: =AF21*Settings!$B$7+AG21*Settings!$B$8+AE21*Settings!$B$9+AB21*Settings!$B$10+AC21*Settings!$B$11+X21*Settings!$B$12+Y21*Settings!$B$13+Z21*Settings!$B$14 -> 0
A22: WR | B22: Marvin Harrison | C22: 1 | D22: 23 | E22: ACT | K22: 116 | L22: 73 | M22: 608 | N22: ARI | O22: 12 | Q22: 14.5 | R22: 0.545 | U22: 17 | V22: 0 | W22: 0 | X22: 0 | Y22: 0 | Z22: 0 | AA22: 0 | AB22: 1 | AC22: 0 | AD22: 111 | AE22: 61 | AF22: 864 | AG22: 7 | AH22: kept | AI22: =IFERROR(AB22/AA22,"") | AJ22: =IFERROR(AF22/AE22,"") -> 14.163934 | AK22: =IFERROR(AE22/AD22,"") -> 0.54954955 | AL22: =IFERROR(X22/V22,"") | AM22: =IFERROR(W22/V22,"") | AN22: =IFERROR(AA22/$H$5,"") -> 0 | AO22: =IFERROR(AD22/$G$5,"") -> 0.185 | AP22: =IFERROR(V22/$F$5,"") -> 0 | AQ22: =IFERROR(AA22/U22,"") -> 0 | AR22: =IFERROR(AD22/U22,"") -> 6.5294118 | AS22: =IFERROR(AD22-L22,"") -> 38 | AT22: =IFERROR(AA22-H22,"") -> 0 | AU22: =AF22*Settings!$B$7+AG22*Settings!$B$8+AE22*Settings!$B$9+AB22*Settings!$B$10+AC22*Settings!$B$11+X22*Settings!$B$12+Y22*Settings!$B$13+Z22*Settings!$B$14 -> 159
A23: WR | B23: Michael Wilson | C23: 2 | D23: 26 | E23: ACT | G23: 1 | J23: 58 | K23: 71 | L23: 126 | M23: 1006 | N23: ARI | O23: 17 | P23: 7 | Q23: 13 | R23: 0.639 | U23: 17 | V23: 0 | W23: 0 | X23: 0 | Y23: 0 | Z23: 0 | AA23: 0 | AB23: 1 | AC23: 0 | AD23: 101 | AE23: 63 | AF23: 815 | AG23: 6 | AH23: kept | AI23: =IFERROR(AB23/AA23,"") | AJ23: =IFERROR(AF23/AE23,"") -> 12.936508 | AK23: =IFERROR(AE23/AD23,"") -> 0.62376238 | AL23: =IFERROR(X23/V23,"") | AM23: =IFERROR(W23/V23,"") | AN23: =IFERROR(AA23/$H$5,"") -> 0 | AO23: =IFERROR(AD23/$G$5,"") -> 0.16833333 | AP23: =IFERROR(V23/$F$5,"") -> 0 | AQ23: =IFERROR(AA23/U23,"") -> 0 | AR23: =IFERROR(AD23/U23,"") -> 5.9411765 | AS23: =IFERROR(AD23-L23,"") -> -25 | AT23: =IFERROR(AA23-H23,"") -> 0 | AU23: =AF23*Settings!$B$7+AG23*Settings!$B$8+AE23*Settings!$B$9+AB23*Settings!$B$10+AC23*Settings!$B$11+X23*Settings!$B$12+Y23*Settings!$B$13+Z23*Settings!$B$14 -> 149.1
A24: WR | B24: Kendrick Bourne | C24: 3 | D24: 31 | E24: ACT | F24: 1 | G24: 1 | J24: 55 | K24: 38 | L24: 53 | M24: 551 | N24: SF | O24: 16 | P24: 5 | Q24: 12.37 | R24: 0.699 | U24: 17 | V24: 0 | W24: 0 | X24: 0 | Y24: 0 | Z24: 0 | AA24: 0 | AB24: 1 | AC24: 0 | AD24: 42 | AE24: 28 | AF24: 241 | AG24: 1 | AH24: kept | AI24: =IFERROR(AB24/AA24,"") | AJ24: =IFERROR(AF24/AE24,"") -> 8.6071429 | AK24: =IFERROR(AE24/AD24,"") -> 0.66666667 | AL24: =IFERROR(X24/V24,"") | AM24: =IFERROR(W24/V24,"") | AN24: =IFERROR(AA24/$H$5,"") -> 0 | AO24: =IFERROR(AD24/$G$5,"") -> 0.07 | AP24: =IFERROR(V24/$F$5,"") -> 0 | AQ24: =IFERROR(AA24/U24,"") -> 0 | AR24: =IFERROR(AD24/U24,"") -> 2.4705882 | AS24: =IFERROR(AD24-L24,"") -> -11 | AT24: =IFERROR(AA24-H24,"") -> 0 | AU24: =AF24*Settings!$B$7+AG24*Settings!$B$8+AE24*Settings!$B$9+AB24*Settings!$B$10+AC24*Settings!$B$11+X24*Settings!$B$12+Y24*Settings!$B$13+Z24*Settings!$B$14 -> 44.2
A25: WR | B25: Xavier Weaver | C25: 4 | D25: 25 | E25: ACT | K25: 2 | L25: 13 | M25: 67 | N25: ARI | O25: 10 | Q25: 9.57 | R25: 0.467 | U25: 17 | V25: 0 | W25: 0 | X25: 0 | Y25: 0 | Z25: 0 | AA25: 0 | AB25: 1 | AC25: 0 | AD25: 9 | AE25: 5 | AF25: 51 | AG25: 0 | AH25: kept | AI25: =IFERROR(AB25/AA25,"") | AJ25: =IFERROR(AF25/AE25,"") -> 10.2 | AK25: =IFERROR(AE25/AD25,"") -> 0.55555556 | AL25: =IFERROR(X25/V25,"") | AM25: =IFERROR(W25/V25,"") | AN25: =IFERROR(AA25/$H$5,"") -> 0 | AO25: =IFERROR(AD25/$G$5,"") -> 0.015 | AP25: =IFERROR(V25/$F$5,"") -> 0 | AQ25: =IFERROR(AA25/U25,"") -> 0 | AR25: =IFERROR(AD25/U25,"") -> 0.52941176 | AS25: =IFERROR(AD25-L25,"") -> -4 | AT25: =IFERROR(AA25-H25,"") -> 0 | AU25: =AF25*Settings!$B$7+AG25*Settings!$B$8+AE25*Settings!$B$9+AB25*Settings!$B$10+AC25*Settings!$B$11+X25*Settings!$B$12+Y25*Settings!$B$13+Z25*Settings!$B$14 -> 7.7
A26: WR | B26: Reggie Virgil | C26: 5 | D26: 22 | E26: ACT | U26: 17 | AA26: 0 | AB26: 0 | AC26: 0 | AD26: 8 | AE26: 6 | AF26: 78 | AG26: 0 | AH26: kept | AI26: =IFERROR(AB26/AA26,"") | AJ26: =IFERROR(AF26/AE26,"") -> 13 | AK26: =IFERROR(AE26/AD26,"") -> 0.75 | AL26: =IFERROR(X26/V26,"") | AM26: =IFERROR(W26/V26,"") | AN26: =IFERROR(AA26/$H$5,"") -> 0 | AO26: =IFERROR(AD26/$G$5,"") -> 0.013333333 | AP26: =IFERROR(V26/$F$5,"") -> 0 | AQ26: =IFERROR(AA26/U26,"") -> 0 | AR26: =IFERROR(AD26/U26,"") -> 0.47058824 | AS26: =IFERROR(AD26-L26,"") -> 8 | AT26: =IFERROR(AA26-H26,"") -> 0 | AU26: =AF26*Settings!$B$7+AG26*Settings!$B$8+AE26*Settings!$B$9+AB26*Settings!$B$10+AC26*Settings!$B$11+X26*Settings!$B$12+Y26*Settings!$B$13+Z26*Settings!$B$14 -> 10.8
A27: WR | B27: Simi Fehoko | C27: 6 | D27: 28 | E27: ACT | J27: 2 | K27: 16 | Q27: 16.43 | R27: 0.389 | U27: 17 | AA27: 0 | AB27: 0 | AC27: 0 | AD27: 0 | AE27: 0 | AF27: 4 | AG27: 0 | AH27: kept | AI27: =IFERROR(AB27/AA27,"") | AJ27: =IFERROR(AF27/AE27,"") | AK27: =IFERROR(AE27/AD27,"") | AL27: =IFERROR(X27/V27,"") | AM27: =IFERROR(W27/V27,"") | AN27: =IFERROR(AA27/$H$5,"") -> 0 | AO27: =IFERROR(AD27/$G$5,"") -> 0 | AP27: =IFERROR(V27/$F$5,"") -> 0 | AQ27: =IFERROR(AA27/U27,"") -> 0 | AR27: =IFERROR(AD27/U27,"") -> 0 | AS27: =IFERROR(AD27-L27,"") -> 0 | AT27: =IFERROR(AA27-H27,"") -> 0 | AU27: =AF27*Settings!$B$7+AG27*Settings!$B$8+AE27*Settings!$B$9+AB27*Settings!$B$10+AC27*Settings!$B$11+X27*Settings!$B$12+Y27*Settings!$B$13+Z27*Settings!$B$14 -> 0.4
A28: WR | B28: Devin Duvernay | C28: 7 | D28: 28 | E28: ACT | F28: 4 | G28: 4 | J28: 9 | K28: 16 | L28: 5 | M28: 26 | N28: CHI | O28: 17 | P28: 2.25 | Q28: 7.24 | R28: 0.567 | U28: 17 | V28: 0 | W28: 0 | X28: 0 | Y28: 0 | Z28: 0 | AA28: 1 | AB28: 2 | AC28: 0 | AD28: 4 | AE28: 2 | AF28: 13 | AG28: 0 | AH28: kept | AI28: =IFERROR(AB28/AA28,"") -> 2 | AJ28: =IFERROR(AF28/AE28,"") -> 6.5 | AK28: =IFERROR(AE28/AD28,"") -> 0.5 | AL28: =IFERROR(X28/V28,"") | AM28: =IFERROR(W28/V28,"") | AN28: =IFERROR(AA28/$H$5,"") -> 0.002334267 | AO28: =IFERROR(AD28/$G$5,"") -> 0.0066666667 | AP28: =IFERROR(V28/$F$5,"") -> 0 | AQ28: =IFERROR(AA28/U28,"") -> 0.058823529 | AR28: =IFERROR(AD28/U28,"") -> 0.23529412 | AS28: =IFERROR(AD28-L28,"") -> -1 | AT28: =IFERROR(AA28-H28,"") -> 1 | AU28: =AF28*Settings!$B$7+AG28*Settings!$B$8+AE28*Settings!$B$9+AB28*Settings!$B$10+AC28*Settings!$B$11+X28*Settings!$B$12+Y28*Settings!$B$13+Z28*Settings!$B$14 -> 2.5
A29: WR | B29: Ihmir Smith-Marsette | C29: 8 | D29: 26 | E29: ACT | F29: 8 | J29: 10 | P29: 9.25 | Q29: 6.38 | R29: 0.8 | U29: 17 | AI29: =IFERROR(AB29/AA29,"") | AJ29: =IFERROR(AF29/AE29,"") | AK29: =IFERROR(AE29/AD29,"") | AL29: =IFERROR(X29/V29,"") | AM29: =IFERROR(W29/V29,"") | AN29: =IFERROR(AA29/$H$5,"") -> 0 | AO29: =IFERROR(AD29/$G$5,"") -> 0 | AP29: =IFERROR(V29/$F$5,"") -> 0 | AQ29: =IFERROR(AA29/U29,"") -> 0 | AR29: =IFERROR(AD29/U29,"") -> 0 | AS29: =IFERROR(AD29-L29,"") -> 0 | AT29: =IFERROR(AA29-H29,"") -> 0 | AU29: =AF29*Settings!$B$7+AG29*Settings!$B$8+AE29*Settings!$B$9+AB29*Settings!$B$10+AC29*Settings!$B$11+X29*Settings!$B$12+Y29*Settings!$B$13+Z29*Settings!$B$14 -> 0
A30: WR | B30: Other WRs | U30: 17 | AI30: =IFERROR(AB30/AA30,"") | AJ30: =IFERROR(AF30/AE30,"") | AK30: =IFERROR(AE30/AD30,"") | AL30: =IFERROR(X30/V30,"") | AM30: =IFERROR(W30/V30,"") | AN30: =IFERROR(AA30/$H$5,"") -> 0 | AO30: =IFERROR(AD30/$G$5,"") -> 0 | AP30: =IFERROR(V30/$F$5,"") -> 0 | AQ30: =IFERROR(AA30/U30,"") -> 0 | AR30: =IFERROR(AD30/U30,"") -> 0 | AS30: =IFERROR(AD30-L30,"") -> 0 | AT30: =IFERROR(AA30-H30,"") -> 0 | AU30: =AF30*Settings!$B$7+AG30*Settings!$B$8+AE30*Settings!$B$9+AB30*Settings!$B$10+AC30*Settings!$B$11+X30*Settings!$B$12+Y30*Settings!$B$13+Z30*Settings!$B$14 -> 0
A31: TE | B31: Trey McBride | C31: 1 | D31: 26 | E31: ACT | G31: 1 | J31: 106 | K31: 147 | L31: 169 | M31: 1239 | N31: ARI | O31: 17 | P31: 2 | Q31: 10.09 | R31: 0.754 | U31: 17 | V31: 0 | W31: 0 | X31: 0 | Y31: 0 | Z31: 0 | AA31: 0 | AB31: 0 | AC31: 0 | AD31: 143 | AE31: 104 | AF31: 1052 | AG31: 7 | AH31: kept | AI31: =IFERROR(AB31/AA31,"") | AJ31: =IFERROR(AF31/AE31,"") -> 10.115385 | AK31: =IFERROR(AE31/AD31,"") -> 0.72727273 | AL31: =IFERROR(X31/V31,"") | AM31: =IFERROR(W31/V31,"") | AN31: =IFERROR(AA31/$H$5,"") -> 0 | AO31: =IFERROR(AD31/$G$5,"") -> 0.23833333 | AP31: =IFERROR(V31/$F$5,"") -> 0 | AQ31: =IFERROR(AA31/U31,"") -> 0 | AR31: =IFERROR(AD31/U31,"") -> 8.4117647 | AS31: =IFERROR(AD31-L31,"") -> -26 | AT31: =IFERROR(AA31-H31,"") -> 0 | AU31: =AF31*Settings!$B$7+AG31*Settings!$B$8+AE31*Settings!$B$9+AB31*Settings!$B$10+AC31*Settings!$B$11+X31*Settings!$B$12+Y31*Settings!$B$13+Z31*Settings!$B$14 -> 199.2
A32: TE | B32: Elijah Higgins | C32: 2 | D32: 25 | E32: ACT | J32: 19 | K32: 24 | L32: 37 | M32: 301 | N32: ARI | O32: 17 | Q32: 9.94 | R32: 0.8 | U32: 17 | V32: 0 | W32: 0 | X32: 0 | Y32: 0 | Z32: 0 | AA32: 0 | AB32: 0 | AC32: 0 | AD32: 26 | AE32: 20 | AF32: 185 | AG32: 1 | AH32: kept | AI32: =IFERROR(AB32/AA32,"") | AJ32: =IFERROR(AF32/AE32,"") -> 9.25 | AK32: =IFERROR(AE32/AD32,"") -> 0.76923077 | AL32: =IFERROR(X32/V32,"") | AM32: =IFERROR(W32/V32,"") | AN32: =IFERROR(AA32/$H$5,"") -> 0 | AO32: =IFERROR(AD32/$G$5,"") -> 0.043333333 | AP32: =IFERROR(V32/$F$5,"") -> 0 | AQ32: =IFERROR(AA32/U32,"") -> 0 | AR32: =IFERROR(AD32/U32,"") -> 1.5294118 | AS32: =IFERROR(AD32-L32,"") -> -11 | AT32: =IFERROR(AA32-H32,"") -> 0 | AU32: =AF32*Settings!$B$7+AG32*Settings!$B$8+AE32*Settings!$B$9+AB32*Settings!$B$10+AC32*Settings!$B$11+X32*Settings!$B$12+Y32*Settings!$B$13+Z32*Settings!$B$14 -> 34.5
A33: TE | B33: Teagan Quitoriano | C33: 3 | D33: 26 | E33: ACT | J33: 3 | Q33: 16.5 | R33: 0.667 | U33: 17 | AA33: 0 | AB33: 0 | AC33: 0 | AD33: 5 | AE33: 4 | AF33: 36 | AG33: 0 | AH33: kept | AI33: =IFERROR(AB33/AA33,"") | AJ33: =IFERROR(AF33/AE33,"") -> 9 | AK33: =IFERROR(AE33/AD33,"") -> 0.8 | AL33: =IFERROR(X33/V33,"") | AM33: =IFERROR(W33/V33,"") | AN33: =IFERROR(AA33/$H$5,"") -> 0 | AO33: =IFERROR(AD33/$G$5,"") -> 0.0083333333 | AP33: =IFERROR(V33/$F$5,"") -> 0 | AQ33: =IFERROR(AA33/U33,"") -> 0 | AR33: =IFERROR(AD33/U33,"") -> 0.29411765 | AS33: =IFERROR(AD33-L33,"") -> 5 | AT33: =IFERROR(AA33-H33,"") -> 0 | AU33: =AF33*Settings!$B$7+AG33*Settings!$B$8+AE33*Settings!$B$9+AB33*Settings!$B$10+AC33*Settings!$B$11+X33*Settings!$B$12+Y33*Settings!$B$13+Z33*Settings!$B$14 -> 5.6
A34: TE | B34: Rivaldo Fairweather | C34: 4 | D34: 24 | E34: ACT | U34: 17 | AA34: 0 | AB34: 0 | AC34: 0 | AD34: 5 | AE34: 4 | AF34: 36 | AG34: 0 | AH34: kept | AI34: =IFERROR(AB34/AA34,"") | AJ34: =IFERROR(AF34/AE34,"") -> 9 | AK34: =IFERROR(AE34/AD34,"") -> 0.8 | AL34: =IFERROR(X34/V34,"") | AM34: =IFERROR(W34/V34,"") | AN34: =IFERROR(AA34/$H$5,"") -> 0 | AO34: =IFERROR(AD34/$G$5,"") -> 0.0083333333 | AP34: =IFERROR(V34/$F$5,"") -> 0 | AQ34: =IFERROR(AA34/U34,"") -> 0 | AR34: =IFERROR(AD34/U34,"") -> 0.29411765 | AS34: =IFERROR(AD34-L34,"") -> 5 | AT34: =IFERROR(AA34-H34,"") -> 0 | AU34: =AF34*Settings!$B$7+AG34*Settings!$B$8+AE34*Settings!$B$9+AB34*Settings!$B$10+AC34*Settings!$B$11+X34*Settings!$B$12+Y34*Settings!$B$13+Z34*Settings!$B$14 -> 5.6
A35: TE | B35: Other TEs | U35: 17 | AI35: =IFERROR(AB35/AA35,"") | AJ35: =IFERROR(AF35/AE35,"") | AK35: =IFERROR(AE35/AD35,"") | AL35: =IFERROR(X35/V35,"") | AM35: =IFERROR(W35/V35,"") | AN35: =IFERROR(AA35/$H$5,"") -> 0 | AO35: =IFERROR(AD35/$G$5,"") -> 0 | AP35: =IFERROR(V35/$F$5,"") -> 0 | AQ35: =IFERROR(AA35/U35,"") -> 0 | AR35: =IFERROR(AD35/U35,"") -> 0 | AS35: =IFERROR(AD35-L35,"") -> 0 | AT35: =IFERROR(AA35-H35,"") -> 0 | AU35: =AF35*Settings!$B$7+AG35*Settings!$B$8+AE35*Settings!$B$9+AB35*Settings!$B$10+AC35*Settings!$B$11+X35*Settings!$B$12+Y35*Settings!$B$13+Z35*Settings!$B$14 -> 0
A37: YOUR TOTAL | U37: =SUM(U11:U35) -> 425 | V37: =SUM(V11:V35) -> 622 | W37: =SUM(W11:W35) -> 379 | X37: =SUM(X11:X35) -> 4023 | Y37: =SUM(Y11:Y35) -> 25 | Z37: =SUM(Z11:Z35) -> 12 | AA37: =SUM(AA11:AA35) -> 428 | AB37: =SUM(AB11:AB35) -> 1940 | ... AG37: =SUM(AG11:AG35) -> 25
A38: TEAM TARGET | V38: =$F$5 -> 629 | X38: =$I$5 -> 3992 | Y38: =$J$5 -> 25 | Z38: =$K$5 -> 12 | AA38: =$H$5 -> 428.4 | AB38: =$L$5 -> 1940 | AC38: =$M$5 -> 14 | AD38: =$G$5 -> 600 | AF38: =$I$5 -> 3992 | AG38: =$J$5 -> 25
A39: LEFT | V39: =$F$5-V37 -> 7 | X39: =$I$5-X37 -> -31 | Y39: =$J$5-Y37 -> 0 | Z39: =$K$5-Z37 -> 0 | AA39: =$H$5-AA37 -> 0.4 | AB39: =$L$5-AB37 -> 0 | AC39: =$M$5-AC37 -> 1 | AD39: =$G$5-AD37 -> 43 | AF39: =$I$5-AF37 -> 0 | AG39: =$J$5-AG37 -> 0
B40: Red = you have allocated more than the team total. Amber = more than 3% under. These are targets, not hard caps - if you disagree, edit the team total above. | AF40: Rec Yds / Rec TD are checked against the PASSING totals

Sheet ATL
A1: ATL - 2026 projections (direct entry)
A3: TEAM TOTALS | D3: all editable - these are your targets, not hard caps
B4: Games | C4: Plays/G | D4: Plays | E4: Pass Rate | F4: Pass Att | G4: Targets | H4: Rush Att | I4: Pass Yds | J4: Pass TD | K4: Int | L4: Rush Yds | M4: Rush TD
B5: 17 | C5: 62.5 | D5: =C5*B5 -> 1062.5 | E5: 0.5475 | F5: =ROUND(D5*E5,0) -> 582 | G5: =ROUND(F5*Settings!$B$4,0) -> 555 | H5: =D5-F5 -> 480.5 | I5: 3893 | J5: 21 | K5: 13 | L5: 2108 | M5: 16
A7: VACATED | B7: 29% of targets and 33% of carries left this roster - that volume is yours to reassign.
A8: STAFF | B8: NEW HC Kevin Stefanski + OC Tommy Rees. Zone-heavy run game; little pass-rate change expected. Emphasis on Robinson touches.
A10: Pos | B10: Player | C10: Dep | D10: Age | E10: Status | F10: '23 Car | G10: '24 Car | H10: '25 Car | I10: '25 RuYd | J10: '23 Tgt | K10: '24 Tgt | L10: '25 Tgt | M10: '25 ReYd | N10: '25 Tm | O10: '25 G | P10: 3y Y/C | Q10: 3y Y/R | R10: 3y Ctch | S10: 3y Comp% | T10: 3y Y/A | U10: Games | V10: Pass Att | W10: Cmp | X10: Pass Yds | Y10: Pass TD | Z10: Int | AA10: Rush Att | AB10: Rush Yds | AC10: Rush TD | AD10: Targets | AE10: Rec | AF10: Rec Yds | AG10: Rec TD | AH10: Seed | AI10: Y/C | AJ10: Y/R | AK10: Catch% | AL10: Y/A | AM10: Comp% | AN10: Rush % | AO10: Tgt % | AP10: Pass % | AQ10: Car/G | AR10: Tgt/G | AS10: dTgt | AT10: dCar | AU10: Half PPR
A11: QB | B11: Tua Tagovailoa | C11: 1 | D11: 28 | E11: QUESTIONABLE | F11: 24 | G11: 11 | H11: 16 | I11: 43 | N11: MIA | O11: 14 | P11: 3.25 | S11: 0.699 | T11: 7.56 | U11: 17 | V11: 282 | W11: 196 | X11: 2180 | Y11: 12 | Z11: 7 | AA11: 17 | AB11: 40 | AC11: 0 | AD11: 0 | AE11: 0 | AF11: 0 | AG11: 0 | AH11: kept | AI11: =IFERROR(AB11/AA11,"") -> 2.3529412 | AJ11: =IFERROR(AF11/AE11,"") | AK11: =IFERROR(AE11/AD11,"") | AL11: =IFERROR(X11/V11,"") -> 7.7304965 | AM11: =IFERROR(W11/V11,"") -> 0.69503546 | AN11: =IFERROR(AA11/$H$5,"") -> 0.035379813 | AO11: =IFERROR(AD11/$G$5,"") -> 0 | AP11: =IFERROR(V11/$F$5,"") -> 0.48453608 | AQ11: =IFERROR(AA11/U11,"") -> 1 | AR11: =IFERROR(AD11/U11,"") -> 0 | AS11: =IFERROR(AD11-L11,"") -> 0 | AT11: =IFERROR(AA11-H11,"") -> 1 | AU11: =AF11*Settings!$B$7+AG11*Settings!$B$8+AE11*Settings!$B$9+AB11*Settings!$B$10+AC11*Settings!$B$11+X11*Settings!$B$12+Y11*Settings!$B$13+Z11*Settings!$B$14 -> 125.2
A12: QB | B12: Michael Penix | C12: 2 | D12: 26 | E12: QUESTIONABLE | G12: 5 | H12: 14 | I12: 70 | N12: ATL | O12: 9 | P12: 4.26 | S12: 0.596 | T12: 7.24 | U12: 17 | V12: 218 | W12: 138 | X12: 1749 | Y12: 9 | Z12: 5 | AA12: 17 | AB12: 57 | AC12: 1 | AD12: 0 | AE12: 0 | AF12: 0 | AG12: 0 | AH12: kept | AI12: =IFERROR(AB12/AA12,"") -> 3.3529412 | AJ12: =IFERROR(AF12/AE12,"") | AK12: =IFERROR(AE12/AD12,"") | AL12: =IFERROR(X12/V12,"") -> 8.0229358 | AM12: =IFERROR(W12/V12,"") -> 0.63302752 | AN12: =IFERROR(AA12/$H$5,"") -> 0.035379813 | AO12: =IFERROR(AD12/$G$5,"") -> 0 | AP12: =IFERROR(V12/$F$5,"") -> 0.37457045 | AQ12: =IFERROR(AA12/U12,"") -> 1 | AR12: =IFERROR(AD12/U12,"") -> 0 | AS12: =IFERROR(AD12-L12,"") -> 0 | AT12: =IFERROR(AA12-H12,"") -> 3 | AU12: =AF12*Settings!$B$7+AG12*Settings!$B$8+AE12*Settings!$B$9+AB12*Settings!$B$10+AC12*Settings!$B$11+X12*Settings!$B$12+Y12*Settings!$B$13+Z12*Settings!$B$14 -> 107.66
A13: QB | B13: Cooper Rush | C13: 3 | D13: 32 | E13: ACT | F13: 1 | G13: 19 | H13: 1 | I13: -4 | N13: BAL | O13: 4 | P13: 0.43 | S13: 0.622 | T13: 5.97 | U13: 17 | V13: 12 | W13: 8 | X13: 66 | Y13: 0 | Z13: 4 | AA13: 1 | AB13: -4 | AC13: 0 | AD13: 0 | AE13: 0 | AF13: 0 | AG13: 0 | AH13: kept | AI13: =IFERROR(AB13/AA13,"") -> -4 | AJ13: =IFERROR(AF13/AE13,"") | AK13: =IFERROR(AE13/AD13,"") | AL13: =IFERROR(X13/V13,"") -> 5.5 | AM13: =IFERROR(W13/V13,"") -> 0.66666667 | AN13: =IFERROR(AA13/$H$5,"") -> 0.0020811655 | AO13: =IFERROR(AD13/$G$5,"") -> 0 | AP13: =IFERROR(V13/$F$5,"") -> 0.020618557 | AQ13: =IFERROR(AA13/U13,"") -> 0.058823529 | AR13: =IFERROR(AD13/U13,"") -> 0 | AS13: =IFERROR(AD13-L13,"") -> 0 | AT13: =IFERROR(AA13-H13,"") -> 0 | AU13: =AF13*Settings!$B$7+AG13*Settings!$B$8+AE13*Settings!$B$9+AB13*Settings!$B$10+AC13*Settings!$B$11+X13*Settings!$B$12+Y13*Settings!$B$13+Z13*Settings!$B$14 -> -5.76
A14: QB | B14: Other QBs | U14: 17 | AI14: =IFERROR(AB14/AA14,"") | AJ14: =IFERROR(AF14/AE14,"") | AK14: =IFERROR(AE14/AD14,"") | AL14: =IFERROR(X14/V14,"") | AM14: =IFERROR(W14/V14,"") | AN14: =IFERROR(AA14/$H$5,"") -> 0 | AO14: =IFERROR(AD14/$G$5,"") -> 0 | AP14: =IFERROR(V14/$F$5,"") -> 0 | AQ14: =IFERROR(AA14/U14,"") -> 0 | AR14: =IFERROR(AD14/U14,"") -> 0 | AS14: =IFERROR(AD14-L14,"") -> 0 | AT14: =IFERROR(AA14-H14,"") -> 0 | AU14: =AF14*Settings!$B$7+AG14*Settings!$B$8+AE14*Settings!$B$9+AB14*Settings!$B$10+AC14*Settings!$B$11+X14*Settings!$B$12+Y14*Settings!$B$13+Z14*Settings!$B$14 -> 0
A15: RB | B15: Bijan Robinson | C15: 1 | D15: 24 | E15: ACT | F15: 214 | G15: 304 | H15: 287 | I15: 1478 | J15: 86 | K15: 72 | L15: 103 | M15: 820 | N15: ATL | O15: 17 | P15: 4.86 | Q15: 8.78 | R15: 0.759 | U15: 17 | V15: 0 | W15: 0 | X15: 0 | Y15: 0 | Z15: 0 | AA15: 273 | AB15: 1344 | AC15: 9 | AD15: 94 | AE15: 73 | AF15: 680 | AG15: 3 | AH15: kept | AI15: =IFERROR(AB15/AA15,"") -> 4.9230769 | AJ15: =IFERROR(AF15/AE15,"") -> 9.3150685 | AK15: =IFERROR(AE15/AD15,"") -> 0.77659574 | AL15: =IFERROR(X15/V15,"") | AM15: =IFERROR(W15/V15,"") | AN15: =IFERROR(AA15/$H$5,"") -> 0.56815817 | AO15: =IFERROR(AD15/$G$5,"") -> 0.16936937 | AP15: =IFERROR(V15/$F$5,"") -> 0 | AQ15: =IFERROR(AA15/U15,"") -> 16.058824 | AR15: =IFERROR(AD15/U15,"") -> 5.5294118 | AS15: =IFERROR(AD15-L15,"") -> -9 | AT15: =IFERROR(AA15-H15,"") -> -14 | AU15: =AF15*Settings!$B$7+AG15*Settings!$B$8+AE15*Settings!$B$9+AB15*Settings!$B$10+AC15*Settings!$B$11+X15*Settings!$B$12+Y15*Settings!$B$13+Z15*Settings!$B$14 -> 310.9
A16: RB | B16: Brian Robinson | C16: 2 | D16: 27 | E16: ACT | F16: 178 | G16: 187 | H16: 92 | I16: 400 | J16: 43 | K16: 25 | L16: 12 | M16: 25 | N16: SF | O16: 17 | P16: 4.23 | Q16: 8.62 | R16: 0.8 | U16: 17 | V16: 0 | W16: 0 | X16: 0 | Y16: 0 | Z16: 0 | AA16: 117 | AB16: 500 | AC16: 4 | AD16: 11 | AE16: 9 | AF16: 62 | AG16: 0 | AH16: kept | AI16: =IFERROR(AB16/AA16,"") -> 4.2735043 | AJ16: =IFERROR(AF16/AE16,"") -> 6.8888889 | AK16: =IFERROR(AE16/AD16,"") -> 0.81818182 | AL16: =IFERROR(X16/V16,"") | AM16: =IFERROR(W16/V16,"") | AN16: =IFERROR(AA16/$H$5,"") -> 0.24349636 | AO16: =IFERROR(AD16/$G$5,"") -> 0.01981982 | AP16: =IFERROR(V16/$F$5,"") -> 0 | AQ16: =IFERROR(AA16/U16,"") -> 6.8823529 | AR16: =IFERROR(AD16/U16,"") -> 0.64705882 | AS16: =IFERROR(AD16-L16,"") -> -1 | AT16: =IFERROR(AA16-H16,"") -> 25 | AU16: =AF16*Settings!$B$7+AG16*Settings!$B$8+AE16*Settings!$B$9+AB16*Settings!$B$10+AC16*Settings!$B$11+X16*Settings!$B$12+Y16*Settings!$B$13+Z16*Settings!$B$14 -> 84.7
A17: RB | B17: Tyler Goodson | C17: 3 | D17: 25 | E17: ACT | F17: 13 | G17: 32 | H17: 9 | I17: 24 | J17: 9 | K17: 15 | L17: 3 | M17: 8 | N17: IND | O17: 11 | P17: 4.89 | Q17: 5.42 | R17: 0.704 | U17: 17 | V17: 0 | W17: 0 | X17: 0 | Y17: 0 | Z17: 0 | AA17: 22 | AB17: 76 | AC17: 1 | AD17: 4 | AE17: 4 | AF17: 25 | AG17: 0 | AH17: kept | AI17: =IFERROR(AB17/AA17,"") -> 3.4545455 | AJ17: =IFERROR(AF17/AE17,"") -> 6.25 | AK17: =IFERROR(AE17/AD17,"") -> 1 | AL17: =IFERROR(X17/V17,"") | AM17: =IFERROR(W17/V17,"") | AN17: =IFERROR(AA17/$H$5,"") -> 0.04578564 | AO17: =IFERROR(AD17/$G$5,"") -> 0.0072072072 | AP17: =IFERROR(V17/$F$5,"") -> 0 | AQ17: =IFERROR(AA17/U17,"") -> 1.2941176 | AR17: =IFERROR(AD17/U17,"") -> 0.23529412 | AS17: =IFERROR(AD17-L17,"") -> 1 | AT17: =IFERROR(AA17-H17,"") -> 13 | AU17: =AF17*Settings!$B$7+AG17*Settings!$B$8+AE17*Settings!$B$9+AB17*Settings!$B$10+AC17*Settings!$B$11+X17*Settings!$B$12+Y17*Settings!$B$13+Z17*Settings!$B$14 -> 18.1
A18: RB | B18: Nathan Carter | C18: 4 | D18: 24 | E18: ACT | H18: 9 | I18: 60 | N18: ATL | O18: 7 | P18: 6.67 | U18: 17 | V18: 0 | W18: 0 | X18: 0 | Y18: 0 | Z18: 0 | AA18: 10 | AB18: 64 | AC18: 1 | AD18: 0 | AE18: 0 | AF18: 0 | AG18: 0 | AH18: kept | AI18: =IFERROR(AB18/AA18,"") -> 6.4 | AJ18: =IFERROR(AF18/AE18,"") | AK18: =IFERROR(AE18/AD18,"") | AL18: =IFERROR(X18/V18,"") | AM18: =IFERROR(W18/V18,"") | AN18: =IFERROR(AA18/$H$5,"") -> 0.020811655 | AO18: =IFERROR(AD18/$G$5,"") -> 0 | AP18: =IFERROR(V18/$F$5,"") -> 0 | AQ18: =IFERROR(AA18/U18,"") -> 0.58823529 | AR18: =IFERROR(AD18/U18,"") -> 0 | AS18: =IFERROR(AD18-L18,"") -> 0 | AT18: =IFERROR(AA18-H18,"") -> 1 | AU18: =AF18*Settings!$B$7+AG18*Settings!$B$8+AE18*Settings!$B$9+AB18*Settings!$B$10+AC18*Settings!$B$11+X18*Settings!$B$12+Y18*Settings!$B$13+Z18*Settings!$B$14 -> 12.4
A19: RB | B19: Cash Jones | C19: 5 | D19: 24 | E19: ACT | U19: 17 | AI19: =IFERROR(AB19/AA19,"") | AJ19: =IFERROR(AF19/AE19,"") | AK19: =IFERROR(AE19/AD19,"") | AL19: =IFERROR(X19/V19,"") | AM19: =IFERROR(W19/V19,"") | AN19: =IFERROR(AA19/$H$5,"") -> 0 | AO19: =IFERROR(AD19/$G$5,"") -> 0 | AP19: =IFERROR(V19/$F$5,"") -> 0 | AQ19: =IFERROR(AA19/U19,"") -> 0 | AR19: =IFERROR(AD19/U19,"") -> 0 | AS19: =IFERROR(AD19-L19,"") -> 0 | AT19: =IFERROR(AA19-H19,"") -> 0 | AU19: =AF19*Settings!$B$7+AG19*Settings!$B$8+AE19*Settings!$B$9+AB19*Settings!$B$10+AC19*Settings!$B$11+X19*Settings!$B$12+Y19*Settings!$B$13+Z19*Settings!$B$14 -> 0
A20: RB | AI20: =IFERROR(AB20/AA20,"") | AJ20: =IFERROR(AF20/AE20,"") | AK20: =IFERROR(AE20/AD20,"") | AL20: =IFERROR(X20/V20,"") | AM20: =IFERROR(W20/V20,"") | AN20: =IFERROR(AA20/$H$5,"") -> 0 | AO20: =IFERROR(AD20/$G$5,"") -> 0 | AP20: =IFERROR(V20/$F$5,"") -> 0 | AQ20: =IFERROR(AA20/U20,"") | AR20: =IFERROR(AD20/U20,"") | AS20: =IFERROR(AD20-L20,"") -> 0 | AT20: =IFERROR(AA20-H20,"") -> 0 | AU20: =AF20*Settings!$B$7+AG20*Settings!$B$8+AE20*Settings!$B$9+AB20*Settings!$B$10+AC20*Settings!$B$11+X20*Settings!$B$12+Y20*Settings!$B$13+Z20*Settings!$B$14 -> 0
A21: RB | B21: Other RBs | U21: 17 | AI21: =IFERROR(AB21/AA21,"") | AJ21: =IFERROR(AF21/AE21,"") | AK21: =IFERROR(AE21/AD21,"") | AL21: =IFERROR(X21/V21,"") | AM21: =IFERROR(W21/V21,"") | AN21: =IFERROR(AA21/$H$5,"") -> 0 | AO21: =IFERROR(AD21/$G$5,"") -> 0 | AP21: =IFERROR(V21/$F$5,"") -> 0 | AQ21: =IFERROR(AA21/U21,"") -> 0 | AR21: =IFERROR(AD21/U21,"") -> 0 | AS21: =IFERROR(AD21-L21,"") -> 0 | AT21: =IFERROR(AA21-H21,"") -> 0 | AU21: =AF21*Settings!$B$7+AG21*Settings!$B$8+AE21*Settings!$B$9+AB21*Settings!$B$10+AC21*Settings!$B$11+X21*Settings!$B$12+Y21*Settings!$B$13+Z21*Settings!$B$14 -> 0
A22: WR | B22: Drake London | C22: 1 | D22: 25 | E22: ACT | G22: 1 | J22: 110 | K22: 158 | L22: 112 | M22: 919 | N22: ATL | O22: 12 | P22: -3 | Q22: 13.06 | R22: 0.624 | S22: 1 | U22: 17 | V22: 0 | W22: 0 | X22: 0 | Y22: 0 | Z22: 0 | AA22: 0 | AB22: 0 | AC22: 0 | AD22: 148 | AE22: 89 | AF22: 1189 | AG22: 7 | AH22: kept | AI22: =IFERROR(AB22/AA22,"") | AJ22: =IFERROR(AF22/AE22,"") -> 13.359551 | AK22: =IFERROR(AE22/AD22,"") -> 0.60135135 | AL22: =IFERROR(X22/V22,"") | AM22: =IFERROR(W22/V22,"") | AN22: =IFERROR(AA22/$H$5,"") -> 0 | AO22: =IFERROR(AD22/$G$5,"") -> 0.26666667 | AP22: =IFERROR(V22/$F$5,"") -> 0 | AQ22: =IFERROR(AA22/U22,"") -> 0 | AR22: =IFERROR(AD22/U22,"") -> 8.7058824 | AS22: =IFERROR(AD22-L22,"") -> 36 | AT22: =IFERROR(AA22-H22,"") -> 0 | AU22: =AF22*Settings!$B$7+AG22*Settings!$B$8+AE22*Settings!$B$9+AB22*Settings!$B$10+AC22*Settings!$B$11+X22*Settings!$B$12+Y22*Settings!$B$13+Z22*Settings!$B$14 -> 205.4
A23: WR | B23: Zachariah Branch | C23: 2 | D23: 22 | E23: ACT | U23: 17 | AA23: 3 | AB23: 22 | AC23: 0 | AD23: 54 | AE23: 35 | AF23: 415 | AG23: 2 | AH23: kept | AI23: =IFERROR(AB23/AA23,"") -> 7.3333333 | AJ23: =IFERROR(AF23/AE23,"") -> 11.857143 | AK23: =IFERROR(AE23/AD23,"") -> 0.64814815 | AL23: =IFERROR(X23/V23,"") | AM23: =IFERROR(W23/V23,"") | AN23: =IFERROR(AA23/$H$5,"") -> 0.0062434964 | AO23: =IFERROR(AD23/$G$5,"") -> 0.097297297 | AP23: =IFERROR(V23/$F$5,"") -> 0 | AQ23: =IFERROR(AA23/U23,"") -> 0.17647059 | AR23: =IFERROR(AD23/U23,"") -> 3.1764706 | AS23: =IFERROR(AD23-L23,"") -> 54 | AT23: =IFERROR(AA23-H23,"") -> 3 | AU23: =AF23*Settings!$B$7+AG23*Settings!$B$8+AE23*Settings!$B$9+AB23*Settings!$B$10+AC23*Settings!$B$11+X23*Settings!$B$12+Y23*Settings!$B$13+Z23*Settings!$B$14 -> 73.2
A24: WR | B24: Jahan Dotson | C24: 3 | D24: 26 | E24: ACT | G24: 1 | J24: 83 | K24: 33 | L24: 36 | M24: 262 | N24: PHI | O24: 17 | P24: 13 | Q24: 11.58 | R24: 0.566 | U24: 17 | V24: 0 | W24: 0 | X24: 0 | Y24: 0 | Z24: 0 | AA24: 0 | AB24: 1 | AC24: 0 | AD24: 43 | AE24: 25 | AF24: 326 | AG24: 2 | AH24: kept | AI24: =IFERROR(AB24/AA24,"") | AJ24: =IFERROR(AF24/AE24,"") -> 13.04 | AK24: =IFERROR(AE24/AD24,"") -> 0.58139535 | AL24: =IFERROR(X24/V24,"") | AM24: =IFERROR(W24/V24,"") | AN24: =IFERROR(AA24/$H$5,"") -> 0 | AO24: =IFERROR(AD24/$G$5,"") -> 0.077477477 | AP24: =IFERROR(V24/$F$5,"") -> 0 | AQ24: =IFERROR(AA24/U24,"") -> 0 | AR24: =IFERROR(AD24/U24,"") -> 2.5294118 | AS24: =IFERROR(AD24-L24,"") -> 7 | AT24: =IFERROR(AA24-H24,"") -> 0 | AU24: =AF24*Settings!$B$7+AG24*Settings!$B$8+AE24*Settings!$B$9+AB24*Settings!$B$10+AC24*Settings!$B$11+X24*Settings!$B$12+Y24*Settings!$B$13+Z24*Settings!$B$14 -> 57.2
A25: WR | B25: Olamide Zaccheaus | C25: 4 | D25: 29 | E25: ACT | G25: 1 | H25: 4 | I25: 25 | J25: 20 | K25: 64 | L25: 65 | M25: 313 | N25: CHI | O25: 16 | P25: 6.6 | Q25: 10.46 | R25: 0.631 | U25: 17 | V25: 0 | W25: 0 | X25: 0 | Y25: 0 | Z25: 0 | AA25: 1 | AB25: 6 | AC25: 0 | AD25: 44 | AE25: 28 | AF25: 278 | AG25: 2 | AH25: kept | AI25: =IFERROR(AB25/AA25,"") -> 6 | AJ25: =IFERROR(AF25/AE25,"") -> 9.9285714 | AK25: =IFERROR(AE25/AD25,"") -> 0.63636364 | AL25: =IFERROR(X25/V25,"") | AM25: =IFERROR(W25/V25,"") | AN25: =IFERROR(AA25/$H$5,"") -> 0.0020811655 | AO25: =IFERROR(AD25/$G$5,"") -> 0.079279279 | AP25: =IFERROR(V25/$F$5,"") -> 0 | AQ25: =IFERROR(AA25/U25,"") -> 0.058823529 | AR25: =IFERROR(AD25/U25,"") -> 2.5882353 | AS25: =IFERROR(AD25-L25,"") -> -21 | AT25: =IFERROR(AA25-H25,"") -> -3 | AU25: =AF25*Settings!$B$7+AG25*Settings!$B$8+AE25*Settings!$B$9+AB25*Settings!$B$10+AC25*Settings!$B$11+X25*Settings!$B$12+Y25*Settings!$B$13+Z25*Settings!$B$14 -> 54.4
A26: WR | B26: Dylan Drummond | C26: 5 | D26: 26 | E26: ACT | L26: 11 | M26: 42 | N26: ATL | O26: 9 | Q26: 6 | R26: 0.636 | U26: 17 | V26: 0 | W26: 0 | X26: 0 | Y26: 0 | Z26: 0 | AA26: 0 | AB26: 0 | AC26: 0 | AD26: 11 | AE26: 7 | AF26: 42 | AG26: 0 | AH26: kept | AI26: =IFERROR(AB26/AA26,"") | AJ26: =IFERROR(AF26/AE26,"") -> 6 | AK26: =IFERROR(AE26/AD26,"") -> 0.63636364 | AL26: =IFERROR(X26/V26,"") | AM26: =IFERROR(W26/V26,"") | AN26: =IFERROR(AA26/$H$5,"") -> 0 | AO26: =IFERROR(AD26/$G$5,"") -> 0.01981982 | AP26: =IFERROR(V26/$F$5,"") -> 0 | AQ26: =IFERROR(AA26/U26,"") -> 0 | AR26: =IFERROR(AD26/U26,"") -> 0.64705882 | AS26: =IFERROR(AD26-L26,"") -> 0 | AT26: =IFERROR(AA26-H26,"") -> 0 | AU26: =AF26*Settings!$B$7+AG26*Settings!$B$8+AE26*Settings!$B$9+AB26*Settings!$B$10+AC26*Settings!$B$11+X26*Settings!$B$12+Y26*Settings!$B$13+Z26*Settings!$B$14 -> 7.7
A27: WR | B27: Chris Blair | C27: 6 | D27: 28 | E27: ACT | K27: 2 | Q27: 17 | R27: 0.5 | U27: 17 | AI27: =IFERROR(AB27/AA27,"") | AJ27: =IFERROR(AF27/AE27,"") | AK27: =IFERROR(AE27/AD27,"") | AL27: =IFERROR(X27/V27,"") | AM27: =IFERROR(W27/V27,"") | AN27: =IFERROR(AA27/$H$5,"") -> 0 | AO27: =IFERROR(AD27/$G$5,"") -> 0 | AP27: =IFERROR(V27/$F$5,"") -> 0 | AQ27: =IFERROR(AA27/U27,"") -> 0 | AR27: =IFERROR(AD27/U27,"") -> 0 | AS27: =IFERROR(AD27-L27,"") -> 0 | AT27: =IFERROR(AA27-H27,"") -> 0 | AU27: =AF27*Settings!$B$7+AG27*Settings!$B$8+AE27*Settings!$B$9+AB27*Settings!$B$10+AC27*Settings!$B$11+X27*Settings!$B$12+Y27*Settings!$B$13+Z27*Settings!$B$14 -> 0
A28: WR | B28: Antwane Wells | C28: 7 | D28: 25 | E28: ACT | U28: 17 | AI28: =IFERROR(AB28/AA28,"") | AJ28: =IFERROR(AF28/AE28,"") | AK28: =IFERROR(AE28/AD28,"") | AL28: =IFERROR(X28/V28,"") | AM28: =IFERROR(W28/V28,"") | AN28: =IFERROR(AA28/$H$5,"") -> 0 | AO28: =IFERROR(AD28/$G$5,"") -> 0 | AP28: =IFERROR(V28/$F$5,"") -> 0 | AQ28: =IFERROR(AA28/U28,"") -> 0 | AR28: =IFERROR(AD28/U28,"") -> 0 | AS28: =IFERROR(AD28-L28,"") -> 0 | AT28: =IFERROR(AA28-H28,"") -> 0 | AU28: =AF28*Settings!$B$7+AG28*Settings!$B$8+AE28*Settings!$B$9+AB28*Settings!$B$10+AC28*Settings!$B$11+X28*Settings!$B$12+Y28*Settings!$B$13+Z28*Settings!$B$14 -> 0
A29: WR | B29: Vinny Anthony | C29: 8 | E29: ACT | U29: 17 | AA29: 0 | AB29: 0 | AC29: 0 | AD29: 0 | AE29: 2 | AF29: 20 | AG29: 0 | AH29: kept | AI29: =IFERROR(AB29/AA29,"") | AJ29: =IFERROR(AF29/AE29,"") -> 10 | AK29: =IFERROR(AE29/AD29,"") | AL29: =IFERROR(X29/V29,"") | AM29: =IFERROR(W29/V29,"") | AN29: =IFERROR(AA29/$H$5,"") -> 0 | AO29: =IFERROR(AD29/$G$5,"") -> 0 | AP29: =IFERROR(V29/$F$5,"") -> 0 | AQ29: =IFERROR(AA29/U29,"") -> 0 | AR29: =IFERROR(AD29/U29,"") -> 0 | AS29: =IFERROR(AD29-L29,"") -> 0 | AT29: =IFERROR(AA29-H29,"") -> 0 | AU29: =AF29*Settings!$B$7+AG29*Settings!$B$8+AE29*Settings!$B$9+AB29*Settings!$B$10+AC29*Settings!$B$11+X29*Settings!$B$12+Y29*Settings!$B$13+Z29*Settings!$B$14 -> 3
A30: WR | B30: Other WRs | U30: 17 | AI30: =IFERROR(AB30/AA30,"") | AJ30: =IFERROR(AF30/AE30,"") | AK30: =IFERROR(AE30/AD30,"") | AL30: =IFERROR(X30/V30,"") | AM30: =IFERROR(W30/V30,"") | AN30: =IFERROR(AA30/$H$5,"") -> 0 | AO30: =IFERROR(AD30/$G$5,"") -> 0 | AP30: =IFERROR(V30/$F$5,"") -> 0 | AQ30: =IFERROR(AA30/U30,"") -> 0 | AR30: =IFERROR(AD30/U30,"") -> 0 | AS30: =IFERROR(AD30-L30,"") -> 0 | AT30: =IFERROR(AA30-H30,"") -> 0 | AU30: =AF30*Settings!$B$7+AG30*Settings!$B$8+AE30*Settings!$B$9+AB30*Settings!$B$10+AC30*Settings!$B$11+X30*Settings!$B$12+Y30*Settings!$B$13+Z30*Settings!$B$14 -> 0
A31: TE | B31: Kyle Pitts | C31: 1 | D31: 25 | E31: ACT | F31: 1 | J31: 90 | K31: 74 | L31: 118 | M31: 928 | N31: ATL | O31: 17 | P31: -4 | Q31: 11.69 | R31: 0.667 | U31: 17 | V31: 0 | W31: 0 | X31: 0 | Y31: 0 | Z31: 0 | AA31: 0 | AB31: 0 | AC31: 0 | AD31: 106 | AE31: 73 | AF31: 772 | AG31: 4 | AH31: kept | AI31: =IFERROR(AB31/AA31,"") | AJ31: =IFERROR(AF31/AE31,"") -> 10.575342 | AK31: =IFERROR(AE31/AD31,"") -> 0.68867925 | AL31: =IFERROR(X31/V31,"") | AM31: =IFERROR(W31/V31,"") | AN31: =IFERROR(AA31/$H$5,"") -> 0 | AO31: =IFERROR(AD31/$G$5,"") -> 0.19099099 | AP31: =IFERROR(V31/$F$5,"") -> 0 | AQ31: =IFERROR(AA31/U31,"") -> 0 | AR31: =IFERROR(AD31/U31,"") -> 6.2352941 | AS31: =IFERROR(AD31-L31,"") -> -12 | AT31: =IFERROR(AA31-H31,"") -> 0 | AU31: =AF31*Settings!$B$7+AG31*Settings!$B$8+AE31*Settings!$B$9+AB31*Settings!$B$10+AC31*Settings!$B$11+X31*Settings!$B$12+Y31*Settings!$B$13+Z31*Settings!$B$14 -> 137.7
A32: TE | B32: Austin Hooper | C32: 2 | D32: 31 | E32: ACT | J32: 31 | K32: 59 | L32: 26 | M32: 263 | N32: NE | O32: 16 | Q32: 10.69 | R32: 0.784 | U32: 17 | V32: 0 | W32: 0 | X32: 0 | Y32: 0 | Z32: 0 | AA32: 0 | AB32: 0 | AC32: 0 | AD32: 18 | AE32: 15 | AF32: 124 | AG32: 1 | AH32: kept | AI32: =IFERROR(AB32/AA32,"") | AJ32: =IFERROR(AF32/AE32,"") -> 8.2666667 | AK32: =IFERROR(AE32/AD32,"") -> 0.83333333 | AL32: =IFERROR(X32/V32,"") | AM32: =IFERROR(W32/V32,"") | AN32: =IFERROR(AA32/$H$5,"") -> 0 | AO32: =IFERROR(AD32/$G$5,"") -> 0.032432432 | AP32: =IFERROR(V32/$F$5,"") -> 0 | AQ32: =IFERROR(AA32/U32,"") -> 0 | AR32: =IFERROR(AD32/U32,"") -> 1.0588235 | AS32: =IFERROR(AD32-L32,"") -> -8 | AT32: =IFERROR(AA32-H32,"") -> 0 | AU32: =AF32*Settings!$B$7+AG32*Settings!$B$8+AE32*Settings!$B$9+AB32*Settings!$B$10+AC32*Settings!$B$11+X32*Settings!$B$12+Y32*Settings!$B$13+Z32*Settings!$B$14 -> 25.9
A33: TE | B33: Charlie Woerner | C33: 3 | D33: 28 | E33: ACT | J33: 3 | K33: 12 | L33: 9 | M33: 48 | N33: ATL | O33: 17 | Q33: 7 | R33: 0.75 | U33: 17 | V33: 0 | W33: 0 | X33: 0 | Y33: 0 | Z33: 0 | AA33: 0 | AB33: 0 | AC33: 0 | AD33: 13 | AE33: 9 | AF33: 49 | AG33: 0 | AH33: kept | AI33: =IFERROR(AB33/AA33,"") | AJ33: =IFERROR(AF33/AE33,"") -> 5.4444444 | AK33: =IFERROR(AE33/AD33,"") -> 0.69230769 | AL33: =IFERROR(X33/V33,"") | AM33: =IFERROR(W33/V33,"") | AN33: =IFERROR(AA33/$H$5,"") -> 0 | AO33: =IFERROR(AD33/$G$5,"") -> 0.023423423 | AP33: =IFERROR(V33/$F$5,"") -> 0 | AQ33: =IFERROR(AA33/U33,"") -> 0 | AR33: =IFERROR(AD33/U33,"") -> 0.76470588 | AS33: =IFERROR(AD33-L33,"") -> 4 | AT33: =IFERROR(AA33-H33,"") -> 0 | AU33: =AF33*Settings!$B$7+AG33*Settings!$B$8+AE33*Settings!$B$9+AB33*Settings!$B$10+AC33*Settings!$B$11+X33*Settings!$B$12+Y33*Settings!$B$13+Z33*Settings!$B$14 -> 9.4
A34: TE | B34: Joshua Simon | C34: 4 | D34: 25 | E34: ACT | U34: 17 | AI34: =IFERROR(AB34/AA34,"") | AJ34: =IFERROR(AF34/AE34,"") | AK34: =IFERROR(AE34/AD34,"") | AL34: =IFERROR(X34/V34,"") | AM34: =IFERROR(W34/V34,"") | AN34: =IFERROR(AA34/$H$5,"") -> 0 | AO34: =IFERROR(AD34/$G$5,"") -> 0 | AP34: =IFERROR(V34/$F$5,"") -> 0 | AQ34: =IFERROR(AA34/U34,"") -> 0 | AR34: =IFERROR(AD34/U34,"") -> 0 | AS34: =IFERROR(AD34-L34,"") -> 0 | AT34: =IFERROR(AA34-H34,"") -> 0 | AU34: =AF34*Settings!$B$7+AG34*Settings!$B$8+AE34*Settings!$B$9+AB34*Settings!$B$10+AC34*Settings!$B$11+X34*Settings!$B$12+Y34*Settings!$B$13+Z34*Settings!$B$14 -> 0
A35: TE | B35: Other TEs | U35: 17 | AI35: =IFERROR(AB35/AA35,"") | AJ35: =IFERROR(AF35/AE35,"") | AK35: =IFERROR(AE35/AD35,"") | AL35: =IFERROR(X35/V35,"") | AM35: =IFERROR(W35/V35,"") | AN35: =IFERROR(AA35/$H$5,"") -> 0 | AO35: =IFERROR(AD35/$G$5,"") -> 0 | AP35: =IFERROR(V35/$F$5,"") -> 0 | AQ35: =IFERROR(AA35/U35,"") -> 0 | AR35: =IFERROR(AD35/U35,"") -> 0 | AS35: =IFERROR(AD35-L35,"") -> 0 | AT35: =IFERROR(AA35-H35,"") -> 0 | AU35: =AF35*Settings!$B$7+AG35*Settings!$B$8+AE35*Settings!$B$9+AB35*Settings!$B$10+AC35*Settings!$B$11+X35*Settings!$B$12+Y35*Settings!$B$13+Z35*Settings!$B$14 -> 0
A37: YOUR TOTAL | U37: =SUM(U11:U35) -> 408 | V37: =SUM(V11:V35) -> 512 | W37: =SUM(W11:W35) -> 342 | X37: =SUM(X11:X35) -> 3995 | Y37: =SUM(Y11:Y35) -> 21 | Z37: =SUM(Z11:Z35) -> 16 | AA37: =SUM(AA11:AA35) -> 461 | AB37: =SUM(AB11:AB35) -> 2106 | ... AG37: =SUM(AG11:AG35) -> 21
A38: TEAM TARGET | V38: =$F$5 -> 582 | X38: =$I$5 -> 3893 | Y38: =$J$5 -> 21 | Z38: =$K$5 -> 13 | AA38: =$H$5 -> 480.5 | AB38: =$L$5 -> 2108 | AC38: =$M$5 -> 16 | AD38: =$G$5 -> 555 | AF38: =$I$5 -> 3893 | AG38: =$J$5 -> 21
A39: LEFT | V39: =$F$5-V37 -> 70 | X39: =$I$5-X37 -> -102 | Y39: =$J$5-Y37 -> 0 | Z39: =$K$5-Z37 -> -3 | AA39: =$H$5-AA37 -> 19.5 | AB39: =$L$5-AB37 -> 2 | AC39: =$M$5-AC37 -> 0 | AD39: =$G$5-AD37 -> 9 | AF39: =$I$5-AF37 -> -89 | AG39: =$J$5-AG37 -> 0
B40: Red = you have allocated more than the team total. Amber = more than 3% under. These are targets, not hard caps - if you disagree, edit the team total above. | AF40: Rec Yds / Rec TD are checked against the PASSING totals

Sheet BAL
A1: BAL - 2026 projections (direct entry)
A3: TEAM TOTALS | D3: all editable - these are your targets, not hard caps
B4: Games | C4: Plays/G | D4: Plays | E4: Pass Rate | F4: Pass Att | G4: Targets | H4: Rush Att | I4: Pass Yds | J4: Pass TD | K4: Int | L4: Rush Yds | M4: Rush TD
B5: 17 | C5: 60.7 | D5: =C5*B5 -> 1031.9 | E5: 0.5063 | F5: =ROUND(D5*E5,0) -> 522 | G5: =ROUND(F5*Settings!$B$4,0) -> 498 | H5: =D5-F5 -> 509.9 | I5: 3763 | J5: 28 | K5: 10 | L5: 2551 | M5: 20
A7: VACATED | B7: 27% of targets and 12% of carries left this roster - that volume is yours to reassign.
A8: STAFF | B8: NEW HC Jesse Minter + OC Declan Doyle. More explosive plays expected - Doyle brings creativity and detail.
A10: Pos | B10: Player | C10: Dep | D10: Age | E10: Status | F10: '23 Car | G10: '24 Car | H10: '25 Car | I10: '25 RuYd | J10: '23 Tgt | K10: '24 Tgt | L10: '25 Tgt | M10: '25 ReYd | N10: '25 Tm | O10: '25 G | P10: 3y Y/C | Q10: 3y Y/R | R10: 3y Ctch | S10: 3y Comp% | T10: 3y Y/A | U10: Games | V10: Pass Att | W10: Cmp | X10: Pass Yds | Y10: Pass TD | Z10: Int | AA10: Rush Att | AB10: Rush Yds | AC10: Rush TD | AD10: Targets | AE10: Rec | AF10: Rec Yds | AG10: Rec TD | AH10: Seed | AI10: Y/C | AJ10: Y/R | AK10: Catch% | AL10: Y/A | AM10: Comp% | AN10: Rush % | AO10: Tgt % | AP10: Pass % | AQ10: Car/G | AR10: Tgt/G | AS10: dTgt | AT10: dCar | AU10: Half PPR
A11: QB | B11: Lamar Jackson | C11: 1 | D11: 29 | E11: ACT | F11: 139 | G11: 127 | H11: 58 | I11: 349 | N11: BAL | O11: 13 | P11: 6.44 | S11: 0.661 | T11: 8.43 | U11: 17 | V11: 450 | W11: 291 | X11: 3599 | Y11: 27 | Z11: 9 | AA11: 117 | AB11: 639 | AC11: 3 | AD11: 0 | AE11: 0 | AF11: 0 | AG11: 0 | AH11: kept | AI11: =IFERROR(AB11/AA11,"") -> 5.4615385 | AJ11: =IFERROR(AF11/AE11,"") | AK11: =IFERROR(AE11/AD11,"") | AL11: =IFERROR(X11/V11,"") -> 7.9977778 | AM11: =IFERROR(W11/V11,"") -> 0.64666667 | AN11: =IFERROR(AA11/$H$5,"") -> 0.22945676 | AO11: =IFERROR(AD11/$G$5,"") -> 0 | AP11: =IFERROR(V11/$F$5,"") -> 0.86206897 | AQ11: =IFERROR(AA11/U11,"") -> 6.8823529 | AR11: =IFERROR(AD11/U11,"") -> 0 | AS11: =IFERROR(AD11-L11,"") -> 0 | AT11: =IFERROR(AA11-H11,"") -> 59 | AU11: =AF11*Settings!$B$7+AG11*Settings!$B$8+AE11*Settings!$B$9+AB11*Settings!$B$10+AC11*Settings!$B$11+X11*Settings!$B$12+Y11*Settings!$B$13+Z11*Settings!$B$14 -> 315.86
A12: QB | B12: Tyler Huntley | C12: 2 | D12: 28 | E12: ACT | F12: 11 | G12: 25 | H12: 19 | I12: 151 | N12: BAL | O12: 5 | P12: 6.2 | S12: 0.671 | T12: 6.15 | U12: 17 | V12: 30 | W12: 20 | X12: 200 | Y12: 1 | Z12: 1 | AA12: 4 | AB12: 21 | AC12: 0 | AD12: 0 | AE12: 0 | AF12: 0 | AG12: 0 | AH12: kept | AI12: =IFERROR(AB12/AA12,"") -> 5.25 | AJ12: =IFERROR(AF12/AE12,"") | AK12: =IFERROR(AE12/AD12,"") | AL12: =IFERROR(X12/V12,"") -> 6.6666667 | AM12: =IFERROR(W12/V12,"") -> 0.66666667 | AN12: =IFERROR(AA12/$H$5,"") -> 0.0078446754 | AO12: =IFERROR(AD12/$G$5,"") -> 0 | AP12: =IFERROR(V12/$F$5,"") -> 0.057471264 | AQ12: =IFERROR(AA12/U12,"") -> 0.23529412 | AR12: =IFERROR(AD12/U12,"") -> 0 | AS12: =IFERROR(AD12-L12,"") -> 0 | AT12: =IFERROR(AA12-H12,"") -> -15 | AU12: =AF12*Settings!$B$7+AG12*Settings!$B$8+AE12*Settings!$B$9+AB12*Settings!$B$10+AC12*Settings!$B$11+X12*Settings!$B$12+Y12*Settings!$B$13+Z12*Settings!$B$14 -> 12.1
A13: QB | B13: Skylar Thompson | C13: 3 | D13: 29 | E13: ACT | G13: 1 | P13: 4 | S13: 0.636 | T13: 5.67 | U13: 17 | AI13: =IFERROR(AB13/AA13,"") | AJ13: =IFERROR(AF13/AE13,"") | AK13: =IFERROR(AE13/AD13,"") | AL13: =IFERROR(X13/V13,"") | AM13: =IFERROR(W13/V13,"") | AN13: =IFERROR(AA13/$H$5,"") -> 0 | AO13: =IFERROR(AD13/$G$5,"") -> 0 | AP13: =IFERROR(V13/$F$5,"") -> 0 | AQ13: =IFERROR(AA13/U13,"") -> 0 | AR13: =IFERROR(AD13/U13,"") -> 0 | AS13: =IFERROR(AD13-L13,"") -> 0 | AT13: =IFERROR(AA13-H13,"") -> 0 | AU13: =AF13*Settings!$B$7+AG13*Settings!$B$8+AE13*Settings!$B$9+AB13*Settings!$B$10+AC13*Settings!$B$11+X13*Settings!$B$12+Y13*Settings!$B$13+Z13*Settings!$B$14 -> 0
A14: QB | B14: Other QBs | U14: 17 | AI14: =IFERROR(AB14/AA14,"") | AJ14: =IFERROR(AF14/AE14,"") | AK14: =IFERROR(AE14/AD14,"") | AL14: =IFERROR(X14/V14,"") | AM14: =IFERROR(W14/V14,"") | AN14: =IFERROR(AA14/$H$5,"") -> 0 | AO14: =IFERROR(AD14/$G$5,"") -> 0 | AP14: =IFERROR(V14/$F$5,"") -> 0 | AQ14: =IFERROR(AA14/U14,"") -> 0 | AR14: =IFERROR(AD14/U14,"") -> 0 | AS14: =IFERROR(AD14-L14,"") -> 0 | AT14: =IFERROR(AA14-H14,"") -> 0 | AU14: =AF14*Settings!$B$7+AG14*Settings!$B$8+AE14*Settings!$B$9+AB14*Settings!$B$10+AC14*Settings!$B$11+X14*Settings!$B$12+Y14*Settings!$B$13+Z14*Settings!$B$14 -> 0
A15: RB | B15: Derrick Henry | C15: 1 | D15: 32 | E15: ACT | F15: 280 | G15: 325 | H15: 307 | I15: 1595 | J15: 36 | K15: 22 | L15: 21 | M15: 150 | N15: BAL | O15: 17 | P15: 5.13 | Q15: 8.98 | R15: 0.785 | S15: 0.5 | U15: 17 | V15: 1 | W15: 0 | X15: 0 | Y15: 0 | Z15: 0 | AA15: 289 | AB15: 1447 | AC15: 12 | AD15: 23 | AE15: 17 | AF15: 162 | AG15: 1 | AH15: kept | AI15: =IFERROR(AB15/AA15,"") -> 5.0069204 | AJ15: =IFERROR(AF15/AE15,"") -> 9.5294118 | AK15: =IFERROR(AE15/AD15,"") -> 0.73913043 | AL15: =IFERROR(X15/V15,"") -> 0 | AM15: =IFERROR(W15/V15,"") -> 0 | AN15: =IFERROR(AA15/$H$5,"") -> 0.5667778 | AO15: =IFERROR(AD15/$G$5,"") -> 0.046184739 | AP15: =IFERROR(V15/$F$5,"") -> 0.0019157088 | AQ15: =IFERROR(AA15/U15,"") -> 17 | AR15: =IFERROR(AD15/U15,"") -> 1.3529412 | AS15: =IFERROR(AD15-L15,"") -> 2 | AT15: =IFERROR(AA15-H15,"") -> -18 | AU15: =AF15*Settings!$B$7+AG15*Settings!$B$8+AE15*Settings!$B$9+AB15*Settings!$B$10+AC15*Settings!$B$11+X15*Settings!$B$12+Y15*Settings!$B$13+Z15*Settings!$B$14 -> 247.4
A16: RB | B16: Justice Hill | C16: 2 | D16: 28 | E16: ACT | F16: 84 | G16: 47 | H16: 18 | I16: 93 | J16: 39 | K16: 51 | L16: 27 | M16: 169 | N16: BAL | O16: 10 | P16: 4.75 | Q16: 8.33 | R16: 0.778 | U16: 17 | V16: 0 | W16: 0 | X16: 0 | Y16: 0 | Z16: 0 | AA16: 43 | AB16: 202 | AC16: 2 | AD16: 39 | AE16: 31 | AF16: 260 | AG16: 2 | AH16: kept | AI16: =IFERROR(AB16/AA16,"") -> 4.6976744 | AJ16: =IFERROR(AF16/AE16,"") -> 8.3870968 | AK16: =IFERROR(AE16/AD16,"") -> 0.79487179 | AL16: =IFERROR(X16/V16,"") | AM16: =IFERROR(W16/V16,"") | AN16: =IFERROR(AA16/$H$5,"") -> 0.084330261 | AO16: =IFERROR(AD16/$G$5,"") -> 0.078313253 | AP16: =IFERROR(V16/$F$5,"") -> 0 | AQ16: =IFERROR(AA16/U16,"") -> 2.5294118 | AR16: =IFERROR(AD16/U16,"") -> 2.2941176 | AS16: =IFERROR(AD16-L16,"") -> 12 | AT16: =IFERROR(AA16-H16,"") -> 25 | AU16: =AF16*Settings!$B$7+AG16*Settings!$B$8+AE16*Settings!$B$9+AB16*Settings!$B$10+AC16*Settings!$B$11+X16*Settings!$B$12+Y16*Settings!$B$13+Z16*Settings!$B$14 -> 85.7
A17: RB | B17: Adam Randall | C17: 3 | D17: 22 | E17: ACT | U17: 17 | AA17: 42 | AB17: 191 | AC17: 1 | AD17: 10 | AE17: 8 | AF17: 72 | AG17: 0 | AH17: kept | AI17: =IFERROR(AB17/AA17,"") -> 4.547619 | AJ17: =IFERROR(AF17/AE17,"") -> 9 | AK17: =IFERROR(AE17/AD17,"") -> 0.8 | AL17: =IFERROR(X17/V17,"") | AM17: =IFERROR(W17/V17,"") | AN17: =IFERROR(AA17/$H$5,"") -> 0.082369092 | AO17: =IFERROR(AD17/$G$5,"") -> 0.020080321 | AP17: =IFERROR(V17/$F$5,"") -> 0 | AQ17: =IFERROR(AA17/U17,"") -> 2.4705882 | AR17: =IFERROR(AD17/U17,"") -> 0.58823529 | AS17: =IFERROR(AD17-L17,"") -> 10 | AT17: =IFERROR(AA17-H17,"") -> 42 | AU17: =AF17*Settings!$B$7+AG17*Settings!$B$8+AE17*Settings!$B$9+AB17*Settings!$B$10+AC17*Settings!$B$11+X17*Settings!$B$12+Y17*Settings!$B$13+Z17*Settings!$B$14 -> 36.3
A18: RB | B18: Rasheen Ali | C18: 4 | D18: 25 | E18: ACT | G18: 10 | H18: 7 | I18: 24 | K18: 2 | L18: 11 | M18: 68 | N18: BAL | O18: 15 | P18: 3.24 | Q18: 7.56 | R18: 0.692 | U18: 17 | V18: 0 | W18: 0 | X18: 0 | Y18: 0 | Z18: 0 | AA18: 24 | AB18: 91 | AC18: 1 | AD18: 7 | AE18: 5 | AF18: 40 | AG18: 0 | AH18: kept | AI18: =IFERROR(AB18/AA18,"") -> 3.7916667 | AJ18: =IFERROR(AF18/AE18,"") -> 8 | AK18: =IFERROR(AE18/AD18,"") -> 0.71428571 | AL18: =IFERROR(X18/V18,"") | AM18: =IFERROR(W18/V18,"") | AN18: =IFERROR(AA18/$H$5,"") -> 0.047068053 | AO18: =IFERROR(AD18/$G$5,"") -> 0.014056225 | AP18: =IFERROR(V18/$F$5,"") -> 0 | AQ18: =IFERROR(AA18/U18,"") -> 1.4117647 | AR18: =IFERROR(AD18/U18,"") -> 0.41176471 | AS18: =IFERROR(AD18-L18,"") -> -4 | AT18: =IFERROR(AA18-H18,"") -> 17 | AU18: =AF18*Settings!$B$7+AG18*Settings!$B$8+AE18*Settings!$B$9+AB18*Settings!$B$10+AC18*Settings!$B$11+X18*Settings!$B$12+Y18*Settings!$B$13+Z18*Settings!$B$14 -> 21.6
A19: RB | B19: Dontae McMillan | C19: 5 | D19: 24 | E19: ACT | U19: 17 | AI19: =IFERROR(AB19/AA19,"") | AJ19: =IFERROR(AF19/AE19,"") | AK19: =IFERROR(AE19/AD19,"") | AL19: =IFERROR(X19/V19,"") | AM19: =IFERROR(W19/V19,"") | AN19: =IFERROR(AA19/$H$5,"") -> 0 | AO19: =IFERROR(AD19/$G$5,"") -> 0 | AP19: =IFERROR(V19/$F$5,"") -> 0 | AQ19: =IFERROR(AA19/U19,"") -> 0 | AR19: =IFERROR(AD19/U19,"") -> 0 | AS19: =IFERROR(AD19-L19,"") -> 0 | AT19: =IFERROR(AA19-H19,"") -> 0 | AU19: =AF19*Settings!$B$7+AG19*Settings!$B$8+AE19*Settings!$B$9+AB19*Settings!$B$10+AC19*Settings!$B$11+X19*Settings!$B$12+Y19*Settings!$B$13+Z19*Settings!$B$14 -> 0
A20: RB | B20: Elijah Tau-Tolliver | C20: 6 | D20: 23 | E20: ACT | U20: 17 | AI20: =IFERROR(AB20/AA20,"") | AJ20: =IFERROR(AF20/AE20,"") | AK20: =IFERROR(AE20/AD20,"") | AL20: =IFERROR(X20/V20,"") | AM20: =IFERROR(W20/V20,"") | AN20: =IFERROR(AA20/$H$5,"") -> 0 | AO20: =IFERROR(AD20/$G$5,"") -> 0 | AP20: =IFERROR(V20/$F$5,"") -> 0 | AQ20: =IFERROR(AA20/U20,"") -> 0 | AR20: =IFERROR(AD20/U20,"") -> 0 | AS20: =IFERROR(AD20-L20,"") -> 0 | AT20: =IFERROR(AA20-H20,"") -> 0 | AU20: =AF20*Settings!$B$7+AG20*Settings!$B$8+AE20*Settings!$B$9+AB20*Settings!$B$10+AC20*Settings!$B$11+X20*Settings!$B$12+Y20*Settings!$B$13+Z20*Settings!$B$14 -> 0
A21: RB | B21: Other RBs | U21: 17 | AI21: =IFERROR(AB21/AA21,"") | AJ21: =IFERROR(AF21/AE21,"") | AK21: =IFERROR(AE21/AD21,"") | AL21: =IFERROR(X21/V21,"") | AM21: =IFERROR(W21/V21,"") | AN21: =IFERROR(AA21/$H$5,"") -> 0 | AO21: =IFERROR(AD21/$G$5,"") -> 0 | AP21: =IFERROR(V21/$F$5,"") -> 0 | AQ21: =IFERROR(AA21/U21,"") -> 0 | AR21: =IFERROR(AD21/U21,"") -> 0 | AS21: =IFERROR(AD21-L21,"") -> 0 | AT21: =IFERROR(AA21-H21,"") -> 0 | AU21: =AF21*Settings!$B$7+AG21*Settings!$B$8+AE21*Settings!$B$9+AB21*Settings!$B$10+AC21*Settings!$B$11+X21*Settings!$B$12+Y21*Settings!$B$13+Z21*Settings!$B$14 -> 0
A22: WR | B22: Zay Flowers | C22: 1 | D22: 25 | E22: ACT | F22: 8 | G22: 9 | H22: 10 | I22: 62 | J22: 108 | K22: 116 | L22: 118 | M22: 1211 | N22: BAL | O22: 17 | P22: 6.44 | Q22: 13.2 | R22: 0.693 | U22: 17 | V22: 0 | W22: 0 | X22: 0 | Y22: 0 | Z22: 0 | AA22: 9 | AB22: 56 | AC22: 0 | AD22: 118 | AE22: 81 | AF22: 1140 | AG22: 6 | AH22: kept | AI22: =IFERROR(AB22/AA22,"") -> 6.2222222 | AJ22: =IFERROR(AF22/AE22,"") -> 14.074074 | AK22: =IFERROR(AE22/AD22,"") -> 0.68644068 | AL22: =IFERROR(X22/V22,"") | AM22: =IFERROR(W22/V22,"") | AN22: =IFERROR(AA22/$H$5,"") -> 0.01765052 | AO22: =IFERROR(AD22/$G$5,"") -> 0.23694779 | AP22: =IFERROR(V22/$F$5,"") -> 0 | AQ22: =IFERROR(AA22/U22,"") -> 0.52941176 | AR22: =IFERROR(AD22/U22,"") -> 6.9411765 | AS22: =IFERROR(AD22-L22,"") -> 0 | AT22: =IFERROR(AA22-H22,"") -> -1 | AU22: =AF22*Settings!$B$7+AG22*Settings!$B$8+AE22*Settings!$B$9+AB22*Settings!$B$10+AC22*Settings!$B$11+X22*Settings!$B$12+Y22*Settings!$B$13+Z22*Settings!$B$14 -> 196.1
A23: WR | B23: Rashod Bateman | C23: 2 | D23: 26 | E23: ACT | F23: 1 | J23: 56 | K23: 72 | L23: 38 | M23: 224 | N23: BAL | O23: 13 | P23: 18 | Q23: 14.03 | R23: 0.578 | U23: 17 | V23: 0 | W23: 0 | X23: 0 | Y23: 0 | Z23: 0 | AA23: 0 | AB23: 1 | AC23: 0 | AD23: 59 | AE23: 35 | AF23: 492 | AG23: 4 | AH23: kept | AI23: =IFERROR(AB23/AA23,"") | AJ23: =IFERROR(AF23/AE23,"") -> 14.057143 | AK23: =IFERROR(AE23/AD23,"") -> 0.59322034 | AL23: =IFERROR(X23/V23,"") | AM23: =IFERROR(W23/V23,"") | AN23: =IFERROR(AA23/$H$5,"") -> 0 | AO23: =IFERROR(AD23/$G$5,"") -> 0.1184739 | AP23: =IFERROR(V23/$F$5,"") -> 0 | AQ23: =IFERROR(AA23/U23,"") -> 0 | AR23: =IFERROR(AD23/U23,"") -> 3.4705882 | AS23: =IFERROR(AD23-L23,"") -> 21 | AT23: =IFERROR(AA23-H23,"") -> 0 | AU23: =AF23*Settings!$B$7+AG23*Settings!$B$8+AE23*Settings!$B$9+AB23*Settings!$B$10+AC23*Settings!$B$11+X23*Settings!$B$12+Y23*Settings!$B$13+Z23*Settings!$B$14 -> 90.8
A24: WR | B24: Ja'Kobi Lane | C24: 3 | D24: 22 | E24: ACT | U24: 17 | AA24: 1 | AB24: 3 | AC24: 0 | AD24: 49 | AE24: 30 | AF24: 427 | AG24: 3 | AH24: kept | AI24: =IFERROR(AB24/AA24,"") -> 3 | AJ24: =IFERROR(AF24/AE24,"") -> 14.233333 | AK24: =IFERROR(AE24/AD24,"") -> 0.6122449 | AL24: =IFERROR(X24/V24,"") | AM24: =IFERROR(W24/V24,"") | AN24: =IFERROR(AA24/$H$5,"") -> 0.0019611689 | AO24: =IFERROR(AD24/$G$5,"") -> 0.098393574 | AP24: =IFERROR(V24/$F$5,"") -> 0 | AQ24: =IFERROR(AA24/U24,"") -> 0.058823529 | AR24: =IFERROR(AD24/U24,"") -> 2.8823529 | AS24: =IFERROR(AD24-L24,"") -> 49 | AT24: =IFERROR(AA24-H24,"") -> 1 | AU24: =AF24*Settings!$B$7+AG24*Settings!$B$8+AE24*Settings!$B$9+AB24*Settings!$B$10+AC24*Settings!$B$11+X24*Settings!$B$12+Y24*Settings!$B$13+Z24*Settings!$B$14 -> 76
A25: WR | B25: Elijah Sarratt | C25: 4 | D25: 23 | E25: ACT | U25: 17 | AA25: 0 | AB25: 0 | AC25: 0 | AD25: 32 | AE25: 20 | AF25: 272 | AG25: 2 | AH25: kept | AI25: =IFERROR(AB25/AA25,"") | AJ25: =IFERROR(AF25/AE25,"") -> 13.6 | AK25: =IFERROR(AE25/AD25,"") -> 0.625 | AL25: =IFERROR(X25/V25,"") | AM25: =IFERROR(W25/V25,"") | AN25: =IFERROR(AA25/$H$5,"") -> 0 | AO25: =IFERROR(AD25/$G$5,"") -> 0.064257028 | AP25: =IFERROR(V25/$F$5,"") -> 0 | AQ25: =IFERROR(AA25/U25,"") -> 0 | AR25: =IFERROR(AD25/U25,"") -> 1.8823529 | AS25: =IFERROR(AD25-L25,"") -> 32 | AT25: =IFERROR(AA25-H25,"") -> 0 | AU25: =AF25*Settings!$B$7+AG25*Settings!$B$8+AE25*Settings!$B$9+AB25*Settings!$B$10+AC25*Settings!$B$11+X25*Settings!$B$12+Y25*Settings!$B$13+Z25*Settings!$B$14 -> 49.2
A26: WR | B26: Devontez Walker | C26: 5 | D26: 25 | E26: ACT | K26: 3 | L26: 8 | M26: 136 | N26: BAL | O26: 12 | Q26: 22.43 | R26: 0.636 | U26: 17 | V26: 0 | W26: 0 | X26: 0 | Y26: 0 | Z26: 0 | AA26: 0 | AB26: 1 | AC26: 0 | AD26: 17 | AE26: 12 | AF26: 188 | AG26: 2 | AH26: kept | AI26: =IFERROR(AB26/AA26,"") | AJ26: =IFERROR(AF26/AE26,"") -> 15.666667 | AK26: =IFERROR(AE26/AD26,"") -> 0.70588235 | AL26: =IFERROR(X26/V26,"") | AM26: =IFERROR(W26/V26,"") | AN26: =IFERROR(AA26/$H$5,"") -> 0 | AO26: =IFERROR(AD26/$G$5,"") -> 0.034136546 | AP26: =IFERROR(V26/$F$5,"") -> 0 | AQ26: =IFERROR(AA26/U26,"") -> 0 | AR26: =IFERROR(AD26/U26,"") -> 1 | AS26: =IFERROR(AD26-L26,"") -> 9 | AT26: =IFERROR(AA26-H26,"") -> 0 | AU26: =AF26*Settings!$B$7+AG26*Settings!$B$8+AE26*Settings!$B$9+AB26*Settings!$B$10+AC26*Settings!$B$11+X26*Settings!$B$12+Y26*Settings!$B$13+Z26*Settings!$B$14 -> 36.9
A27: WR | B27: Cornelius Johnson | C27: 6 | D27: 25 | E27: ACT | U27: 17 | AI27: =IFERROR(AB27/AA27,"") | AJ27: =IFERROR(AF27/AE27,"") | AK27: =IFERROR(AE27/AD27,"") | AL27: =IFERROR(X27/V27,"") | AM27: =IFERROR(W27/V27,"") | AN27: =IFERROR(AA27/$H$5,"") -> 0 | AO27: =IFERROR(AD27/$G$5,"") -> 0 | AP27: =IFERROR(V27/$F$5,"") -> 0 | AQ27: =IFERROR(AA27/U27,"") -> 0 | AR27: =IFERROR(AD27/U27,"") -> 0 | AS27: =IFERROR(AD27-L27,"") -> 0 | AT27: =IFERROR(AA27-H27,"") -> 0 | AU27: =AF27*Settings!$B$7+AG27*Settings!$B$8+AE27*Settings!$B$9+AB27*Settings!$B$10+AC27*Settings!$B$11+X27*Settings!$B$12+Y27*Settings!$B$13+Z27*Settings!$B$14 -> 0
A28: WR | B28: Chris Moore | C28: 7 | D28: 33 | E28: ACT | F28: 2 | H28: 1 | I28: 9 | J28: 35 | L28: 23 | M28: 207 | N28: WAS | O28: 14 | P28: 16 | Q28: 19.12 | R28: 0.569 | U28: 17 | V28: 0 | W28: 0 | X28: 0 | Y28: 0 | Z28: 0 | AA28: 0 | AB28: 1 | AC28: 0 | AD28: 2 | AE28: 2 | AF28: 16 | AG28: 0 | AH28: kept | AI28: =IFERROR(AB28/AA28,"") | AJ28: =IFERROR(AF28/AE28,"") -> 8 | AK28: =IFERROR(AE28/AD28,"") -> 1 | AL28: =IFERROR(X28/V28,"") | AM28: =IFERROR(W28/V28,"") | AN28: =IFERROR(AA28/$H$5,"") -> 0 | AO28: =IFERROR(AD28/$G$5,"") -> 0.0040160643 | AP28: =IFERROR(V28/$F$5,"") -> 0 | AQ28: =IFERROR(AA28/U28,"") -> 0 | AR28: =IFERROR(AD28/U28,"") -> 0.11764706 | AS28: =IFERROR(AD28-L28,"") -> -21 | AT28: =IFERROR(AA28-H28,"") -> -1 | AU28: =AF28*Settings!$B$7+AG28*Settings!$B$8+AE28*Settings!$B$9+AB28*Settings!$B$10+AC28*Settings!$B$11+X28*Settings!$B$12+Y28*Settings!$B$13+Z28*Settings!$B$14 -> 2.7
A29: WR | B29: LaJohntay Wester | C29: 8 | D29: 24 | E29: ACT | U29: 17 | AA29: 0 | AB29: 1 | AC29: 0 | AD29: 1 | AE29: 0 | AF29: 8 | AG29: 0 | AH29: kept | AI29: =IFERROR(AB29/AA29,"") | AJ29: =IFERROR(AF29/AE29,"") | AK29: =IFERROR(AE29/AD29,"") -> 0 | AL29: =IFERROR(X29/V29,"") | AM29: =IFERROR(W29/V29,"") | AN29: =IFERROR(AA29/$H$5,"") -> 0 | AO29: =IFERROR(AD29/$G$5,"") -> 0.0020080321 | AP29: =IFERROR(V29/$F$5,"") -> 0 | AQ29: =IFERROR(AA29/U29,"") -> 0 | AR29: =IFERROR(AD29/U29,"") -> 0.058823529 | AS29: =IFERROR(AD29-L29,"") -> 1 | AT29: =IFERROR(AA29-H29,"") -> 0 | AU29: =AF29*Settings!$B$7+AG29*Settings!$B$8+AE29*Settings!$B$9+AB29*Settings!$B$10+AC29*Settings!$B$11+X29*Settings!$B$12+Y29*Settings!$B$13+Z29*Settings!$B$14 -> 0.9
A30: WR | B30: Other WRs | U30: 17 | AI30: =IFERROR(AB30/AA30,"") | AJ30: =IFERROR(AF30/AE30,"") | AK30: =IFERROR(AE30/AD30,"") | AL30: =IFERROR(X30/V30,"") | AM30: =IFERROR(W30/V30,"") | AN30: =IFERROR(AA30/$H$5,"") -> 0 | AO30: =IFERROR(AD30/$G$5,"") -> 0 | AP30: =IFERROR(V30/$F$5,"") -> 0 | AQ30: =IFERROR(AA30/U30,"") -> 0 | AR30: =IFERROR(AD30/U30,"") -> 0 | AS30: =IFERROR(AD30-L30,"") -> 0 | AT30: =IFERROR(AA30-H30,"") -> 0 | AU30: =AF30*Settings!$B$7+AG30*Settings!$B$8+AE30*Settings!$B$9+AB30*Settings!$B$10+AC30*Settings!$B$11+X30*Settings!$B$12+Y30*Settings!$B$13+Z30*Settings!$B$14 -> 0
A31: TE | B31: Mark Andrews | C31: 1 | D31: 30 | E31: ACT | F31: 1 | G31: 4 | H31: 10 | I31: 48 | J31: 61 | K31: 69 | L31: 70 | M31: 422 | N31: BAL | O31: 17 | P31: 3.53 | Q31: 11.07 | R31: 0.74 | U31: 17 | V31: 0 | W31: 0 | X31: 0 | Y31: 0 | Z31: 0 | AA31: 8 | AB31: 29 | AC31: 1 | AD31: 78 | AE31: 54 | AF31: 568 | AG31: 7 | AH31: kept | AI31: =IFERROR(AB31/AA31,"") -> 3.625 | AJ31: =IFERROR(AF31/AE31,"") -> 10.518519 | AK31: =IFERROR(AE31/AD31,"") -> 0.69230769 | AL31: =IFERROR(X31/V31,"") | AM31: =IFERROR(W31/V31,"") | AN31: =IFERROR(AA31/$H$5,"") -> 0.015689351 | AO31: =IFERROR(AD31/$G$5,"") -> 0.15662651 | AP31: =IFERROR(V31/$F$5,"") -> 0 | AQ31: =IFERROR(AA31/U31,"") -> 0.47058824 | AR31: =IFERROR(AD31/U31,"") -> 4.5882353 | AS31: =IFERROR(AD31-L31,"") -> 8 | AT31: =IFERROR(AA31-H31,"") -> -2 | AU31: =AF31*Settings!$B$7+AG31*Settings!$B$8+AE31*Settings!$B$9+AB31*Settings!$B$10+AC31*Settings!$B$11+X31*Settings!$B$12+Y31*Settings!$B$13+Z31*Settings!$B$14 -> 134.7
A32: TE | B32: Matt Hibner | C32: 2 | D32: 24 | E32: ACT | U32: 17 | AA32: 0 | AB32: 0 | AC32: 0 | AD32: 10 | AE32: 8 | AF32: 78 | AG32: 1 | AH32: kept | AI32: =IFERROR(AB32/AA32,"") | AJ32: =IFERROR(AF32/AE32,"") -> 9.75 | AK32: =IFERROR(AE32/AD32,"") -> 0.8 | AL32: =IFERROR(X32/V32,"") | AM32: =IFERROR(W32/V32,"") | AN32: =IFERROR(AA32/$H$5,"") -> 0 | AO32: =IFERROR(AD32/$G$5,"") -> 0.020080321 | AP32: =IFERROR(V32/$F$5,"") -> 0 | AQ32: =IFERROR(AA32/U32,"") -> 0 | AR32: =IFERROR(AD32/U32,"") -> 0.58823529 | AS32: =IFERROR(AD32-L32,"") -> 10 | AT32: =IFERROR(AA32-H32,"") -> 0 | AU32: =AF32*Settings!$B$7+AG32*Settings!$B$8+AE32*Settings!$B$9+AB32*Settings!$B$10+AC32*Settings!$B$11+X32*Settings!$B$12+Y32*Settings!$B$13+Z32*Settings!$B$14 -> 17.8
A33: TE | B33: Durham Smythe | C33: 3 | D33: 30 | E33: ACT | J33: 43 | K33: 17 | L33: 6 | M33: 25 | N33: CHI | O33: 17 | Q33: 9.25 | R33: 0.727 | U33: 17 | V33: 0 | W33: 0 | X33: 0 | Y33: 0 | Z33: 0 | AA33: 0 | AB33: 0 | AC33: 0 | AD33: 15 | AE33: 10 | AF33: 94 | AG33: 1 | AH33: kept | AI33: =IFERROR(AB33/AA33,"") | AJ33: =IFERROR(AF33/AE33,"") -> 9.4 | AK33: =IFERROR(AE33/AD33,"") -> 0.66666667 | AL33: =IFERROR(X33/V33,"") | AM33: =IFERROR(W33/V33,"") | AN33: =IFERROR(AA33/$H$5,"") -> 0 | AO33: =IFERROR(AD33/$G$5,"") -> 0.030120482 | AP33: =IFERROR(V33/$F$5,"") -> 0 | AQ33: =IFERROR(AA33/U33,"") -> 0 | AR33: =IFERROR(AD33/U33,"") -> 0.88235294 | AS33: =IFERROR(AD33-L33,"") -> 9 | AT33: =IFERROR(AA33-H33,"") -> 0 | AU33: =AF33*Settings!$B$7+AG33*Settings!$B$8+AE33*Settings!$B$9+AB33*Settings!$B$10+AC33*Settings!$B$11+X33*Settings!$B$12+Y33*Settings!$B$13+Z33*Settings!$B$14 -> 20.4
A34: TE | B34: Josh Cuevas | C34: 4 | D34: 22 | E34: ACT | U34: 17 | AA34: 0 | AB34: 0 | AC34: 0 | AD34: 6 | AE34: 5 | AF34: 56 | AG34: 0 | AH34: kept | AI34: =IFERROR(AB34/AA34,"") | AJ34: =IFERROR(AF34/AE34,"") -> 11.2 | AK34: =IFERROR(AE34/AD34,"") -> 0.83333333 | AL34: =IFERROR(X34/V34,"") | AM34: =IFERROR(W34/V34,"") | AN34: =IFERROR(AA34/$H$5,"") -> 0 | AO34: =IFERROR(AD34/$G$5,"") -> 0.012048193 | AP34: =IFERROR(V34/$F$5,"") -> 0 | AQ34: =IFERROR(AA34/U34,"") -> 0 | AR34: =IFERROR(AD34/U34,"") -> 0.35294118 | AS34: =IFERROR(AD34-L34,"") -> 6 | AT34: =IFERROR(AA34-H34,"") -> 0 | AU34: =AF34*Settings!$B$7+AG34*Settings!$B$8+AE34*Settings!$B$9+AB34*Settings!$B$10+AC34*Settings!$B$11+X34*Settings!$B$12+Y34*Settings!$B$13+Z34*Settings!$B$14 -> 8.1
A35: TE | B35: Other TEs | U35: 17 | AI35: =IFERROR(AB35/AA35,"") | AJ35: =IFERROR(AF35/AE35,"") | AK35: =IFERROR(AE35/AD35,"") | AL35: =IFERROR(X35/V35,"") | AM35: =IFERROR(W35/V35,"") | AN35: =IFERROR(AA35/$H$5,"") -> 0 | AO35: =IFERROR(AD35/$G$5,"") -> 0 | AP35: =IFERROR(V35/$F$5,"") -> 0 | AQ35: =IFERROR(AA35/U35,"") -> 0 | AR35: =IFERROR(AD35/U35,"") -> 0 | AS35: =IFERROR(AD35-L35,"") -> 0 | AT35: =IFERROR(AA35-H35,"") -> 0 | AU35: =AF35*Settings!$B$7+AG35*Settings!$B$8+AE35*Settings!$B$9+AB35*Settings!$B$10+AC35*Settings!$B$11+X35*Settings!$B$12+Y35*Settings!$B$13+Z35*Settings!$B$14 -> 0
A37: YOUR TOTAL | U37: =SUM(U11:U35) -> 425 | V37: =SUM(V11:V35) -> 481 | W37: =SUM(W11:W35) -> 311 | X37: =SUM(X11:X35) -> 3799 | Y37: =SUM(Y11:Y35) -> 28 | Z37: =SUM(Z11:Z35) -> 10 | AA37: =SUM(AA11:AA35) -> 537 | AB37: =SUM(AB11:AB35) -> 2683 | ... AG37: =SUM(AG11:AG35) -> 29
A38: TEAM TARGET | V38: =$F$5 -> 522 | X38: =$I$5 -> 3763 | Y38: =$J$5 -> 28 | Z38: =$K$5 -> 10 | AA38: =$H$5 -> 509.9 | AB38: =$L$5 -> 2551 | AC38: =$M$5 -> 20 | AD38: =$G$5 -> 498 | AF38: =$I$5 -> 3763 | AG38: =$J$5 -> 28
A39: LEFT | V39: =$F$5-V37 -> 41 | X39: =$I$5-X37 -> -36 | Y39: =$J$5-Y37 -> 0 | Z39: =$K$5-Z37 -> 0 | AA39: =$H$5-AA37 -> -27.1 | AB39: =$L$5-AB37 -> -132 | AC39: =$M$5-AC37 -> 0 | AD39: =$G$5-AD37 -> 32 | AF39: =$I$5-AF37 -> -110 | AG39: =$J$5-AG37 -> -1
B40: Red = you have allocated more than the team total. Amber = more than 3% under. These are targets, not hard caps - if you disagree, edit the team total above. | AF40: Rec Yds / Rec TD are checked against the PASSING totals

Sheet BUF
A1: BUF - 2026 projections (direct entry)
A3: TEAM TOTALS | D3: all editable - these are your targets, not hard caps
B4: Games | C4: Plays/G | D4: Plays | E4: Pass Rate | F4: Pass Att | G4: Targets | H4: Rush Att | I4: Pass Yds | J4: Pass TD | K4: Int | L4: Rush Yds | M4: Rush TD
B5: 17 | C5: 62.6 | D5: =C5*B5 -> 1064.2 | E5: 0.5275 | F5: =ROUND(D5*E5,0) -> 561 | G5: =ROUND(F5*Settings!$B$4,0) -> 535 | H5: =D5-F5 -> 503.2 | I5: 4003 | J5: 28 | K5: 11 | L5: 2305 | M5: 24
A7: VACATED | B7: 9% of targets and 1% of carries left this roster - that volume is yours to reassign.
A8: STAFF | B8: NEW HC Joe Brady (promoted from OC) + OC Pete Carmichael Jr. Brady keeps play-calling. Run-lean; controlled pace continues.
A10: Pos | B10: Player | C10: Dep | D10: Age | E10: Status | F10: '23 Car | G10: '24 Car | H10: '25 Car | I10: '25 RuYd | J10: '23 Tgt | K10: '24 Tgt | L10: '25 Tgt | M10: '25 ReYd | N10: '25 Tm | O10: '25 G | P10: 3y Y/C | Q10: 3y Y/R | R10: 3y Ctch | S10: 3y Comp% | T10: 3y Y/A | U10: Games | V10: Pass Att | W10: Cmp | X10: Pass Yds | Y10: Pass TD | Z10: Int | AA10: Rush Att | AB10: Rush Yds | AC10: Rush TD | AD10: Targets | AE10: Rec | AF10: Rec Yds | AG10: Rec TD | AH10: Seed | AI10: Y/C | AJ10: Y/R | AK10: Catch% | AL10: Y/A | AM10: Comp% | AN10: Rush % | AO10: Tgt % | AP10: Pass % | AQ10: Car/G | AR10: Tgt/G | AS10: dTgt | AT10: dCar | AU10: Half PPR
A11: QB | B11: Josh Allen | C11: 1 | D11: 30 | E11: ACT | F11: 102 | G11: 94 | H11: 93 | I11: 579 | N11: BUF | O11: 17 | P11: 5.65 | S11: 0.664 | T11: 7.69 | U11: 17 | V11: 488 | W11: 329 | X11: 3760 | Y11: 26 | Z11: 10 | AA11: 110 | AB11: 558 | AC11: 11 | AD11: 0 | AE11: 0 | AF11: 0 | AG11: 0 | AH11: kept | AI11: =IFERROR(AB11/AA11,"") -> 5.0727273 | AJ11: =IFERROR(AF11/AE11,"") | AK11: =IFERROR(AE11/AD11,"") | AL11: =IFERROR(X11/V11,"") -> 7.704918 | AM11: =IFERROR(W11/V11,"") -> 0.67418033 | AN11: =IFERROR(AA11/$H$5,"") -> 0.21860095 | AO11: =IFERROR(AD11/$G$5,"") -> 0 | AP11: =IFERROR(V11/$F$5,"") -> 0.86987522 | AQ11: =IFERROR(AA11/U11,"") -> 6.4705882 | AR11: =IFERROR(AD11/U11,"") -> 0 | AS11: =IFERROR(AD11-L11,"") -> 0 | AT11: =IFERROR(AA11-H11,"") -> 17 | AU11: =AF11*Settings!$B$7+AG11*Settings!$B$8+AE11*Settings!$B$9+AB11*Settings!$B$10+AC11*Settings!$B$11+X11*Settings!$B$12+Y11*Settings!$B$13+Z11*Settings!$B$14 -> 356.2
A12: QB | B12: Shane Buechele | C12: 2 | D12: 28 | E12: ACT | H12: 1 | I12: 4 | N12: KC | O12: 1 | P12: 4 | S12: 0.5 | U12: 17 | V12: 17 | W12: 12 | X12: 84 | Y12: 1 | Z12: 0 | AA12: 2 | AB12: 11 | AC12: 0 | AD12: 0 | AE12: 0 | AF12: 0 | AG12: 0 | AH12: kept | AI12: =IFERROR(AB12/AA12,"") -> 5.5 | AJ12: =IFERROR(AF12/AE12,"") | AK12: =IFERROR(AE12/AD12,"") | AL12: =IFERROR(X12/V12,"") -> 4.9411765 | AM12: =IFERROR(W12/V12,"") -> 0.70588235 | AN12: =IFERROR(AA12/$H$5,"") -> 0.0039745628 | AO12: =IFERROR(AD12/$G$5,"") -> 0 | AP12: =IFERROR(V12/$F$5,"") -> 0.03030303 | AQ12: =IFERROR(AA12/U12,"") -> 0.11764706 | AR12: =IFERROR(AD12/U12,"") -> 0 | AS12: =IFERROR(AD12-L12,"") -> 0 | AT12: =IFERROR(AA12-H12,"") -> 1 | AU12: =AF12*Settings!$B$7+AG12*Settings!$B$8+AE12*Settings!$B$9+AB12*Settings!$B$10+AC12*Settings!$B$11+X12*Settings!$B$12+Y12*Settings!$B$13+Z12*Settings!$B$14 -> 8.46
A13: QB | B13: Kyle Allen | C13: 3 | D13: 30 | E13: ACT | I13: -3 | N13: DET | O13: 3 | S13: 0.333 | U13: 17 | V13: 27 | W13: 16 | X13: 202 | Y13: 1 | Z13: 1 | AA13: 2 | AB13: 7 | AC13: 0 | AD13: 0 | AE13: 0 | AF13: 0 | AG13: 0 | AH13: kept | AI13: =IFERROR(AB13/AA13,"") -> 3.5 | AJ13: =IFERROR(AF13/AE13,"") | AK13: =IFERROR(AE13/AD13,"") | AL13: =IFERROR(X13/V13,"") -> 7.4814815 | AM13: =IFERROR(W13/V13,"") -> 0.59259259 | AN13: =IFERROR(AA13/$H$5,"") -> 0.0039745628 | AO13: =IFERROR(AD13/$G$5,"") -> 0 | AP13: =IFERROR(V13/$F$5,"") -> 0.048128342 | AQ13: =IFERROR(AA13/U13,"") -> 0.11764706 | AR13: =IFERROR(AD13/U13,"") -> 0 | AS13: =IFERROR(AD13-L13,"") -> 0 | AT13: =IFERROR(AA13-H13,"") -> 2 | AU13: =AF13*Settings!$B$7+AG13*Settings!$B$8+AE13*Settings!$B$9+AB13*Settings!$B$10+AC13*Settings!$B$11+X13*Settings!$B$12+Y13*Settings!$B$13+Z13*Settings!$B$14 -> 10.78
A14: QB | B14: Other QBs | U14: 17 | AI14: =IFERROR(AB14/AA14,"") | AJ14: =IFERROR(AF14/AE14,"") | AK14: =IFERROR(AE14/AD14,"") | AL14: =IFERROR(X14/V14,"") | AM14: =IFERROR(W14/V14,"") | AN14: =IFERROR(AA14/$H$5,"") -> 0 | AO14: =IFERROR(AD14/$G$5,"") -> 0 | AP14: =IFERROR(V14/$F$5,"") -> 0 | AQ14: =IFERROR(AA14/U14,"") -> 0 | AR14: =IFERROR(AD14/U14,"") -> 0 | AS14: =IFERROR(AD14-L14,"") -> 0 | AT14: =IFERROR(AA14-H14,"") -> 0 | AU14: =AF14*Settings!$B$7+AG14*Settings!$B$8+AE14*Settings!$B$9+AB14*Settings!$B$10+AC14*Settings!$B$11+X14*Settings!$B$12+Y14*Settings!$B$13+Z14*Settings!$B$14 -> 0
A15: RB | B15: James Cook | C15: 1 | D15: 26 | E15: ACT | F15: 237 | G15: 207 | H15: 309 | I15: 1621 | J15: 54 | K15: 38 | L15: 40 | M15: 291 | N15: BUF | O15: 17 | P15: 4.98 | Q15: 9.12 | R15: 0.826 | U15: 17 | V15: 0 | W15: 0 | X15: 0 | Y15: 0 | Z15: 0 | AA15: 274 | AB15: 1351 | AC15: 10 | AD15: 42 | AE15: 33 | AF15: 276 | AG15: 2 | AH15: kept | AI15: =IFERROR(AB15/AA15,"") -> 4.9306569 | AJ15: =IFERROR(AF15/AE15,"") -> 8.3636364 | AK15: =IFERROR(AE15/AD15,"") -> 0.78571429 | AL15: =IFERROR(X15/V15,"") | AM15: =IFERROR(W15/V15,"") | AN15: =IFERROR(AA15/$H$5,"") -> 0.5445151 | AO15: =IFERROR(AD15/$G$5,"") -> 0.078504673 | AP15: =IFERROR(V15/$F$5,"") -> 0 | AQ15: =IFERROR(AA15/U15,"") -> 16.117647 | AR15: =IFERROR(AD15/U15,"") -> 2.4705882 | AS15: =IFERROR(AD15-L15,"") -> 2 | AT15: =IFERROR(AA15-H15,"") -> -35 | AU15: =AF15*Settings!$B$7+AG15*Settings!$B$8+AE15*Settings!$B$9+AB15*Settings!$B$10+AC15*Settings!$B$11+X15*Settings!$B$12+Y15*Settings!$B$13+Z15*Settings!$B$14 -> 251.2
A16: RB | B16: Ty Johnson | C16: 2 | D16: 28 | E16: ACT | F16: 30 | G16: 41 | H16: 50 | I16: 200 | J16: 7 | K16: 25 | L16: 33 | M16: 263 | N16: BUF | O16: 17 | P16: 4.5 | Q16: 12.43 | R16: 0.754 | U16: 17 | V16: 0 | W16: 0 | X16: 0 | Y16: 0 | Z16: 0 | AA16: 49 | AB16: 202 | AC16: 2 | AD16: 26 | AE16: 21 | AF16: 205 | AG16: 2 | AH16: kept | AI16: =IFERROR(AB16/AA16,"") -> 4.122449 | AJ16: =IFERROR(AF16/AE16,"") -> 9.7619048 | AK16: =IFERROR(AE16/AD16,"") -> 0.80769231 | AL16: =IFERROR(X16/V16,"") | AM16: =IFERROR(W16/V16,"") | AN16: =IFERROR(AA16/$H$5,"") -> 0.097376789 | AO16: =IFERROR(AD16/$G$5,"") -> 0.048598131 | AP16: =IFERROR(V16/$F$5,"") -> 0 | AQ16: =IFERROR(AA16/U16,"") -> 2.8823529 | AR16: =IFERROR(AD16/U16,"") -> 1.5294118 | AS16: =IFERROR(AD16-L16,"") -> -7 | AT16: =IFERROR(AA16-H16,"") -> -1 | AU16: =AF16*Settings!$B$7+AG16*Settings!$B$8+AE16*Settings!$B$9+AB16*Settings!$B$10+AC16*Settings!$B$11+X16*Settings!$B$12+Y16*Settings!$B$13+Z16*Settings!$B$14 -> 75.2
A17: RB | B17: Frank Gore | C17: 3 | D17: 24 | E17: ACT | U17: 17 | AA17: 19 | AB17: 87 | AC17: 1 | AD17: 2 | AE17: 1 | AF17: 11 | AG17: 0 | AH17: kept | AI17: =IFERROR(AB17/AA17,"") -> 4.5789474 | AJ17: =IFERROR(AF17/AE17,"") -> 11 | AK17: =IFERROR(AE17/AD17,"") -> 0.5 | AL17: =IFERROR(X17/V17,"") | AM17: =IFERROR(W17/V17,"") | AN17: =IFERROR(AA17/$H$5,"") -> 0.037758347 | AO17: =IFERROR(AD17/$G$5,"") -> 0.0037383178 | AP17: =IFERROR(V17/$F$5,"") -> 0 | AQ17: =IFERROR(AA17/U17,"") -> 1.1176471 | AR17: =IFERROR(AD17/U17,"") -> 0.11764706 | AS17: =IFERROR(AD17-L17,"") -> 2 | AT17: =IFERROR(AA17-H17,"") -> 19 | AU17: =AF17*Settings!$B$7+AG17*Settings!$B$8+AE17*Settings!$B$9+AB17*Settings!$B$10+AC17*Settings!$B$11+X17*Settings!$B$12+Y17*Settings!$B$13+Z17*Settings!$B$14 -> 16.3
A18: RB | B18: Ray Davis | C18: 4 | D18: 26 | E18: ACT | G18: 113 | H18: 58 | I18: 275 | K18: 19 | L18: 13 | M18: 86 | N18: BUF | O18: 17 | P18: 4.19 | Q18: 10.19 | R18: 0.844 | U18: 17 | V18: 0 | W18: 0 | X18: 0 | Y18: 0 | Z18: 0 | AA18: 63 | AB18: 268 | AC18: 2 | AD18: 15 | AE18: 11 | AF18: 92 | AG18: 1 | AH18: kept | AI18: =IFERROR(AB18/AA18,"") -> 4.2539683 | AJ18: =IFERROR(AF18/AE18,"") -> 8.3636364 | AK18: =IFERROR(AE18/AD18,"") -> 0.73333333 | AL18: =IFERROR(X18/V18,"") | AM18: =IFERROR(W18/V18,"") | AN18: =IFERROR(AA18/$H$5,"") -> 0.12519873 | AO18: =IFERROR(AD18/$G$5,"") -> 0.028037383 | AP18: =IFERROR(V18/$F$5,"") -> 0 | AQ18: =IFERROR(AA18/U18,"") -> 3.7058824 | AR18: =IFERROR(AD18/U18,"") -> 0.88235294 | AS18: =IFERROR(AD18-L18,"") -> 2 | AT18: =IFERROR(AA18-H18,"") -> 5 | AU18: =AF18*Settings!$B$7+AG18*Settings!$B$8+AE18*Settings!$B$9+AB18*Settings!$B$10+AC18*Settings!$B$11+X18*Settings!$B$12+Y18*Settings!$B$13+Z18*Settings!$B$14 -> 59.5
A19: RB | B19: Ian Wheeler | C19: 5 | D19: 24 | E19: ACT | U19: 17 | AI19: =IFERROR(AB19/AA19,"") | AJ19: =IFERROR(AF19/AE19,"") | AK19: =IFERROR(AE19/AD19,"") | AL19: =IFERROR(X19/V19,"") | AM19: =IFERROR(W19/V19,"") | AN19: =IFERROR(AA19/$H$5,"") -> 0 | AO19: =IFERROR(AD19/$G$5,"") -> 0 | AP19: =IFERROR(V19/$F$5,"") -> 0 | AQ19: =IFERROR(AA19/U19,"") -> 0 | AR19: =IFERROR(AD19/U19,"") -> 0 | AS19: =IFERROR(AD19-L19,"") -> 0 | AT19: =IFERROR(AA19-H19,"") -> 0 | AU19: =AF19*Settings!$B$7+AG19*Settings!$B$8+AE19*Settings!$B$9+AB19*Settings!$B$10+AC19*Settings!$B$11+X19*Settings!$B$12+Y19*Settings!$B$13+Z19*Settings!$B$14 -> 0
A20: RB | B20: Jackson Acker | C20: 6 | D20: 23 | E20: ACT | U20: 17 | AI20: =IFERROR(AB20/AA20,"") | AJ20: =IFERROR(AF20/AE20,"") | AK20: =IFERROR(AE20/AD20,"") | AL20: =IFERROR(X20/V20,"") | AM20: =IFERROR(W20/V20,"") | AN20: =IFERROR(AA20/$H$5,"") -> 0 | AO20: =IFERROR(AD20/$G$5,"") -> 0 | AP20: =IFERROR(V20/$F$5,"") -> 0 | AQ20: =IFERROR(AA20/U20,"") -> 0 | AR20: =IFERROR(AD20/U20,"") -> 0 | AS20: =IFERROR(AD20-L20,"") -> 0 | AT20: =IFERROR(AA20-H20,"") -> 0 | AU20: =AF20*Settings!$B$7+AG20*Settings!$B$8+AE20*Settings!$B$9+AB20*Settings!$B$10+AC20*Settings!$B$11+X20*Settings!$B$12+Y20*Settings!$B$13+Z20*Settings!$B$14 -> 0
A21: RB | B21: Other RBs | U21: 17 | AI21: =IFERROR(AB21/AA21,"") | AJ21: =IFERROR(AF21/AE21,"") | AK21: =IFERROR(AE21/AD21,"") | AL21: =IFERROR(X21/V21,"") | AM21: =IFERROR(W21/V21,"") | AN21: =IFERROR(AA21/$H$5,"") -> 0 | AO21: =IFERROR(AD21/$G$5,"") -> 0 | AP21: =IFERROR(V21/$F$5,"") -> 0 | AQ21: =IFERROR(AA21/U21,"") -> 0 | AR21: =IFERROR(AD21/U21,"") -> 0 | AS21: =IFERROR(AD21-L21,"") -> 0 | AT21: =IFERROR(AA21-H21,"") -> 0 | AU21: =AF21*Settings!$B$7+AG21*Settings!$B$8+AE21*Settings!$B$9+AB21*Settings!$B$10+AC21*Settings!$B$11+X21*Settings!$B$12+Y21*Settings!$B$13+Z21*Settings!$B$14 -> 0
A22: WR | B22: DJ Moore | C22: 1 | D22: 29 | E22: ACT | F22: 4 | G22: 14 | H22: 15 | I22: 79 | J22: 136 | K22: 140 | L22: 85 | M22: 682 | N22: CHI | O22: 17 | P22: 5.3 | Q22: 12.34 | R22: 0.676 | S22: 0.5 | U22: 17 | V22: 1 | W22: 1 | X22: 2 | Y22: 1 | Z22: 0 | AA22: 8 | AB22: 40 | AC22: 0 | AD22: 105 | AE22: 67 | AF22: 866 | AG22: 7 | AH22: kept | AI22: =IFERROR(AB22/AA22,"") -> 5 | AJ22: =IFERROR(AF22/AE22,"") -> 12.925373 | AK22: =IFERROR(AE22/AD22,"") -> 0.63809524 | AL22: =IFERROR(X22/V22,"") -> 2 | AM22: =IFERROR(W22/V22,"") -> 1 | AN22: =IFERROR(AA22/$H$5,"") -> 0.015898251 | AO22: =IFERROR(AD22/$G$5,"") -> 0.19626168 | AP22: =IFERROR(V22/$F$5,"") -> 0.0017825312 | AQ22: =IFERROR(AA22/U22,"") -> 0.47058824 | AR22: =IFERROR(AD22/U22,"") -> 6.1764706 | AS22: =IFERROR(AD22-L22,"") -> 20 | AT22: =IFERROR(AA22-H22,"") -> -7 | AU22: =AF22*Settings!$B$7+AG22*Settings!$B$8+AE22*Settings!$B$9+AB22*Settings!$B$10+AC22*Settings!$B$11+X22*Settings!$B$12+Y22*Settings!$B$13+Z22*Settings!$B$14 -> 170.18
A23: WR | B23: Khalil Shakir | C23: 2 | D23: 26 | E23: ACT | F23: 1 | G23: 2 | H23: 1 | I23: 5 | J23: 45 | K23: 100 | L23: 95 | M23: 719 | N23: BUF | O23: 16 | P23: 4.75 | Q23: 11.5 | R23: 0.779 | U23: 17 | V23: 0 | W23: 0 | X23: 0 | Y23: 0 | Z23: 0 | AA23: 2 | AB23: 9 | AC23: 0 | AD23: 85 | AE23: 66 | AF23: 701 | AG23: 4 | AH23: kept | AI23: =IFERROR(AB23/AA23,"") -> 4.5 | AJ23: =IFERROR(AF23/AE23,"") -> 10.621212 | AK23: =IFERROR(AE23/AD23,"") -> 0.77647059 | AL23: =IFERROR(X23/V23,"") | AM23: =IFERROR(W23/V23,"") | AN23: =IFERROR(AA23/$H$5,"") -> 0.0039745628 | AO23: =IFERROR(AD23/$G$5,"") -> 0.1588785 | AP23: =IFERROR(V23/$F$5,"") -> 0 | AQ23: =IFERROR(AA23/U23,"") -> 0.11764706 | AR23: =IFERROR(AD23/U23,"") -> 5 | AS23: =IFERROR(AD23-L23,"") -> -10 | AT23: =IFERROR(AA23-H23,"") -> 1 | AU23: =AF23*Settings!$B$7+AG23*Settings!$B$8+AE23*Settings!$B$9+AB23*Settings!$B$10+AC23*Settings!$B$11+X23*Settings!$B$12+Y23*Settings!$B$13+Z23*Settings!$B$14 -> 128
A24: WR | B24: Joshua Palmer | C24: 3 | D24: 26 | E24: ACT | F24: 1 | J24: 61 | K24: 65 | L24: 37 | M24: 303 | N24: BUF | O24: 12 | P24: 6 | Q24: 14.83 | R24: 0.607 | U24: 17 | V24: 0 | W24: 0 | X24: 0 | Y24: 0 | Z24: 0 | AA24: 0 | AB24: 0 | AC24: 0 | AD24: 37 | AE24: 22 | AF24: 303 | AG24: 0 | AH24: kept | AI24: =IFERROR(AB24/AA24,"") | AJ24: =IFERROR(AF24/AE24,"") -> 13.772727 | AK24: =IFERROR(AE24/AD24,"") -> 0.59459459 | AL24: =IFERROR(X24/V24,"") | AM24: =IFERROR(W24/V24,"") | AN24: =IFERROR(AA24/$H$5,"") -> 0 | AO24: =IFERROR(AD24/$G$5,"") -> 0.069158879 | AP24: =IFERROR(V24/$F$5,"") -> 0 | AQ24: =IFERROR(AA24/U24,"") -> 0 | AR24: =IFERROR(AD24/U24,"") -> 2.1764706 | AS24: =IFERROR(AD24-L24,"") -> 0 | AT24: =IFERROR(AA24-H24,"") -> 0 | AU24: =AF24*Settings!$B$7+AG24*Settings!$B$8+AE24*Settings!$B$9+AB24*Settings!$B$10+AC24*Settings!$B$11+X24*Settings!$B$12+Y24*Settings!$B$13+Z24*Settings!$B$14 -> 41.3
A25: WR | B25: Keon Coleman | C25: 4 | D25: 23 | E25: ACT | G25: 1 | K25: 57 | L25: 59 | M25: 404 | N25: BUF | O25: 13 | P25: 9 | Q25: 14.33 | R25: 0.578 | U25: 17 | V25: 0 | W25: 0 | X25: 0 | Y25: 0 | Z25: 0 | AA25: 0 | AB25: 1 | AC25: 0 | AD25: 34 | AE25: 20 | AF25: 273 | AG25: 2 | AH25: kept | AI25: =IFERROR(AB25/AA25,"") | AJ25: =IFERROR(AF25/AE25,"") -> 13.65 | AK25: =IFERROR(AE25/AD25,"") -> 0.58823529 | AL25: =IFERROR(X25/V25,"") | AM25: =IFERROR(W25/V25,"") | AN25: =IFERROR(AA25/$H$5,"") -> 0 | AO25: =IFERROR(AD25/$G$5,"") -> 0.063551402 | AP25: =IFERROR(V25/$F$5,"") -> 0 | AQ25: =IFERROR(AA25/U25,"") -> 0 | AR25: =IFERROR(AD25/U25,"") -> 2 | AS25: =IFERROR(AD25-L25,"") -> -25 | AT25: =IFERROR(AA25-H25,"") -> 0 | AU25: =AF25*Settings!$B$7+AG25*Settings!$B$8+AE25*Settings!$B$9+AB25*Settings!$B$10+AC25*Settings!$B$11+X25*Settings!$B$12+Y25*Settings!$B$13+Z25*Settings!$B$14 -> 49.4
A26: WR | B26: Skyler Bell | C26: 5 | D26: 24 | E26: ACT | U26: 17 | AA26: 0 | AB26: 1 | AC26: 0 | AD26: 31 | AE26: 16 | AF26: 205 | AG26: 1 | AH26: kept | AI26: =IFERROR(AB26/AA26,"") | AJ26: =IFERROR(AF26/AE26,"") -> 12.8125 | AK26: =IFERROR(AE26/AD26,"") -> 0.51612903 | AL26: =IFERROR(X26/V26,"") | AM26: =IFERROR(W26/V26,"") | AN26: =IFERROR(AA26/$H$5,"") -> 0 | AO26: =IFERROR(AD26/$G$5,"") -> 0.057943925 | AP26: =IFERROR(V26/$F$5,"") -> 0 | AQ26: =IFERROR(AA26/U26,"") -> 0 | AR26: =IFERROR(AD26/U26,"") -> 1.8235294 | AS26: =IFERROR(AD26-L26,"") -> 31 | AT26: =IFERROR(AA26-H26,"") -> 0 | AU26: =AF26*Settings!$B$7+AG26*Settings!$B$8+AE26*Settings!$B$9+AB26*Settings!$B$10+AC26*Settings!$B$11+X26*Settings!$B$12+Y26*Settings!$B$13+Z26*Settings!$B$14 -> 34.6
A27: WR | B27: Tyrell Shavers | C27: 6 | D27: 26 | E27: PUP | K27: 1 | L27: 23 | M27: 245 | N27: BUF | O27: 17 | Q27: 19.62 | R27: 0.667 | U27: 17 | V27: 0 | W27: 0 | X27: 0 | Y27: 0 | Z27: 0 | AA27: 0 | AB27: 1 | AC27: 0 | AD27: 7 | AE27: 4 | AF27: 63 | AG27: 0 | AH27: kept | AI27: =IFERROR(AB27/AA27,"") | AJ27: =IFERROR(AF27/AE27,"") -> 15.75 | AK27: =IFERROR(AE27/AD27,"") -> 0.57142857 | AL27: =IFERROR(X27/V27,"") | AM27: =IFERROR(W27/V27,"") | AN27: =IFERROR(AA27/$H$5,"") -> 0 | AO27: =IFERROR(AD27/$G$5,"") -> 0.013084112 | AP27: =IFERROR(V27/$F$5,"") -> 0 | AQ27: =IFERROR(AA27/U27,"") -> 0 | AR27: =IFERROR(AD27/U27,"") -> 0.41176471 | AS27: =IFERROR(AD27-L27,"") -> -16 | AT27: =IFERROR(AA27-H27,"") -> 0 | AU27: =AF27*Settings!$B$7+AG27*Settings!$B$8+AE27*Settings!$B$9+AB27*Settings!$B$10+AC27*Settings!$B$11+X27*Settings!$B$12+Y27*Settings!$B$13+Z27*Settings!$B$14 -> 8.4
A28: WR | B28: Trent Sherfield | C28: 7 | D28: 30 | E28: ACT | J28: 22 | K28: 9 | L28: 4 | M28: 21 | N28: DEN | O28: 10 | Q28: 8.64 | R28: 0.629 | U28: 17 | V28: 0 | W28: 0 | X28: 0 | Y28: 0 | Z28: 0 | AA28: 0 | AB28: 0 | AC28: 0 | AD28: 2 | AE28: 2 | AF28: 17 | AG28: 0 | AH28: kept | AI28: =IFERROR(AB28/AA28,"") | AJ28: =IFERROR(AF28/AE28,"") -> 8.5 | AK28: =IFERROR(AE28/AD28,"") -> 1 | AL28: =IFERROR(X28/V28,"") | AM28: =IFERROR(W28/V28,"") | AN28: =IFERROR(AA28/$H$5,"") -> 0 | AO28: =IFERROR(AD28/$G$5,"") -> 0.0037383178 | AP28: =IFERROR(V28/$F$5,"") -> 0 | AQ28: =IFERROR(AA28/U28,"") -> 0 | AR28: =IFERROR(AD28/U28,"") -> 0.11764706 | AS28: =IFERROR(AD28-L28,"") -> -2 | AT28: =IFERROR(AA28-H28,"") -> 0 | AU28: =AF28*Settings!$B$7+AG28*Settings!$B$8+AE28*Settings!$B$9+AB28*Settings!$B$10+AC28*Settings!$B$11+X28*Settings!$B$12+Y28*Settings!$B$13+Z28*Settings!$B$14 -> 2.7
A29: WR | B29: Dante Pettis | C29: 8 | D29: 30 | E29: ACT | K29: 28 | L29: 11 | M29: 127 | N29: NO | O29: 8 | Q29: 11.76 | R29: 0.538 | U29: 17 | V29: 0 | W29: 0 | X29: 0 | Y29: 0 | Z29: 0 | AA29: 1 | AB29: 3 | AC29: 0 | AD29: 11 | AE29: 5 | AF29: 66 | AG29: 0 | AH29: kept | AI29: =IFERROR(AB29/AA29,"") -> 3 | AJ29: =IFERROR(AF29/AE29,"") -> 13.2 | AK29: =IFERROR(AE29/AD29,"") -> 0.45454545 | AL29: =IFERROR(X29/V29,"") | AM29: =IFERROR(W29/V29,"") | AN29: =IFERROR(AA29/$H$5,"") -> 0.0019872814 | AO29: =IFERROR(AD29/$G$5,"") -> 0.020560748 | AP29: =IFERROR(V29/$F$5,"") -> 0 | AQ29: =IFERROR(AA29/U29,"") -> 0.058823529 | AR29: =IFERROR(AD29/U29,"") -> 0.64705882 | AS29: =IFERROR(AD29-L29,"") -> 0 | AT29: =IFERROR(AA29-H29,"") -> 1 | AU29: =AF29*Settings!$B$7+AG29*Settings!$B$8+AE29*Settings!$B$9+AB29*Settings!$B$10+AC29*Settings!$B$11+X29*Settings!$B$12+Y29*Settings!$B$13+Z29*Settings!$B$14 -> 9.4
A30: WR | B30: Other WRs | U30: 17 | AI30: =IFERROR(AB30/AA30,"") | AJ30: =IFERROR(AF30/AE30,"") | AK30: =IFERROR(AE30/AD30,"") | AL30: =IFERROR(X30/V30,"") | AM30: =IFERROR(W30/V30,"") | AN30: =IFERROR(AA30/$H$5,"") -> 0 | AO30: =IFERROR(AD30/$G$5,"") -> 0 | AP30: =IFERROR(V30/$F$5,"") -> 0 | AQ30: =IFERROR(AA30/U30,"") -> 0 | AR30: =IFERROR(AD30/U30,"") -> 0 | AS30: =IFERROR(AD30-L30,"") -> 0 | AT30: =IFERROR(AA30-H30,"") -> 0 | AU30: =AF30*Settings!$B$7+AG30*Settings!$B$8+AE30*Settings!$B$9+AB30*Settings!$B$10+AC30*Settings!$B$11+X30*Settings!$B$12+Y30*Settings!$B$13+Z30*Settings!$B$14 -> 0
A31: TE | B31: Dalton Kincaid | C31: 1 | D31: 26 | E31: ACT | J31: 91 | K31: 75 | L31: 49 | M31: 571 | N31: BUF | O31: 12 | Q31: 10.85 | R31: 0.726 | U31: 17 | V31: 0 | W31: 0 | X31: 0 | Y31: 0 | Z31: 0 | AA31: 0 | AB31: 0 | AC31: 0 | AD31: 80 | AE31: 56 | AF31: 688 | AG31: 5 | AH31: kept | AI31: =IFERROR(AB31/AA31,"") | AJ31: =IFERROR(AF31/AE31,"") -> 12.285714 | AK31: =IFERROR(AE31/AD31,"") -> 0.7 | AL31: =IFERROR(X31/V31,"") | AM31: =IFERROR(W31/V31,"") | AN31: =IFERROR(AA31/$H$5,"") -> 0 | AO31: =IFERROR(AD31/$G$5,"") -> 0.14953271 | AP31: =IFERROR(V31/$F$5,"") -> 0 | AQ31: =IFERROR(AA31/U31,"") -> 0 | AR31: =IFERROR(AD31/U31,"") -> 4.7058824 | AS31: =IFERROR(AD31-L31,"") -> 31 | AT31: =IFERROR(AA31-H31,"") -> 0 | AU31: =AF31*Settings!$B$7+AG31*Settings!$B$8+AE31*Settings!$B$9+AB31*Settings!$B$10+AC31*Settings!$B$11+X31*Settings!$B$12+Y31*Settings!$B$13+Z31*Settings!$B$14 -> 126.8
A32: TE | B32: Dawson Knox | C32: 2 | D32: 29 | E32: ACT | J32: 36 | K32: 33 | L32: 49 | M32: 417 | N32: BUF | O32: 17 | Q32: 11.43 | R32: 0.678 | U32: 17 | V32: 0 | W32: 0 | X32: 0 | Y32: 0 | Z32: 0 | AA32: 0 | AB32: 0 | AC32: 0 | AD32: 38 | AE32: 26 | AF32: 299 | AG32: 3 | AH32: kept | AI32: =IFERROR(AB32/AA32,"") | AJ32: =IFERROR(AF32/AE32,"") -> 11.5 | AK32: =IFERROR(AE32/AD32,"") -> 0.68421053 | AL32: =IFERROR(X32/V32,"") | AM32: =IFERROR(W32/V32,"") | AN32: =IFERROR(AA32/$H$5,"") -> 0 | AO32: =IFERROR(AD32/$G$5,"") -> 0.071028037 | AP32: =IFERROR(V32/$F$5,"") -> 0 | AQ32: =IFERROR(AA32/U32,"") -> 0 | AR32: =IFERROR(AD32/U32,"") -> 2.2352941 | AS32: =IFERROR(AD32-L32,"") -> -11 | AT32: =IFERROR(AA32-H32,"") -> 0 | AU32: =AF32*Settings!$B$7+AG32*Settings!$B$8+AE32*Settings!$B$9+AB32*Settings!$B$10+AC32*Settings!$B$11+X32*Settings!$B$12+Y32*Settings!$B$13+Z32*Settings!$B$14 -> 60.9
A33: TE | B33: Jackson Hawes | C33: 3 | D33: 25 | E33: ACT | L33: 19 | M33: 187 | N33: BUF | O33: 17 | Q33: 11.69 | R33: 0.842 | U33: 17 | V33: 0 | W33: 0 | X33: 0 | Y33: 0 | Z33: 0 | AA33: 0 | AB33: 0 | AC33: 0 | AD33: 15 | AE33: 12 | AF33: 128 | AG33: 1 | AH33: kept | AI33: =IFERROR(AB33/AA33,"") | AJ33: =IFERROR(AF33/AE33,"") -> 10.666667 | AK33: =IFERROR(AE33/AD33,"") -> 0.8 | AL33: =IFERROR(X33/V33,"") | AM33: =IFERROR(W33/V33,"") | AN33: =IFERROR(AA33/$H$5,"") -> 0 | AO33: =IFERROR(AD33/$G$5,"") -> 0.028037383 | AP33: =IFERROR(V33/$F$5,"") -> 0 | AQ33: =IFERROR(AA33/U33,"") -> 0 | AR33: =IFERROR(AD33/U33,"") -> 0.88235294 | AS33: =IFERROR(AD33-L33,"") -> -4 | AT33: =IFERROR(AA33-H33,"") -> 0 | AU33: =AF33*Settings!$B$7+AG33*Settings!$B$8+AE33*Settings!$B$9+AB33*Settings!$B$10+AC33*Settings!$B$11+X33*Settings!$B$12+Y33*Settings!$B$13+Z33*Settings!$B$14 -> 24.8
A34: TE | B34: Keleki Latu | C34: 4 | D34: 23 | E34: ACT | L34: 4 | M34: 35 | N34: BUF | O34: 5 | Q34: 8.75 | R34: 1 | U34: 17 | V34: 0 | W34: 0 | X34: 0 | Y34: 0 | Z34: 0 | AA34: 0 | AB34: 0 | AC34: 0 | AD34: 6 | AE34: 7 | AF34: 80 | AG34: 0 | AH34: kept | AI34: =IFERROR(AB34/AA34,"") | AJ34: =IFERROR(AF34/AE34,"") -> 11.428571 | AK34: =IFERROR(AE34/AD34,"") -> 1.1666667 | AL34: =IFERROR(X34/V34,"") | AM34: =IFERROR(W34/V34,"") | AN34: =IFERROR(AA34/$H$5,"") -> 0 | AO34: =IFERROR(AD34/$G$5,"") -> 0.011214953 | AP34: =IFERROR(V34/$F$5,"") -> 0 | AQ34: =IFERROR(AA34/U34,"") -> 0 | AR34: =IFERROR(AD34/U34,"") -> 0.35294118 | AS34: =IFERROR(AD34-L34,"") -> 2 | AT34: =IFERROR(AA34-H34,"") -> 0 | AU34: =AF34*Settings!$B$7+AG34*Settings!$B$8+AE34*Settings!$B$9+AB34*Settings!$B$10+AC34*Settings!$B$11+X34*Settings!$B$12+Y34*Settings!$B$13+Z34*Settings!$B$14 -> 11.5
A35: TE | B35: Other TEs | U35: 17 | AI35: =IFERROR(AB35/AA35,"") | AJ35: =IFERROR(AF35/AE35,"") | AK35: =IFERROR(AE35/AD35,"") | AL35: =IFERROR(X35/V35,"") | AM35: =IFERROR(W35/V35,"") | AN35: =IFERROR(AA35/$H$5,"") -> 0 | AO35: =IFERROR(AD35/$G$5,"") -> 0 | AP35: =IFERROR(V35/$F$5,"") -> 0 | AQ35: =IFERROR(AA35/U35,"") -> 0 | AR35: =IFERROR(AD35/U35,"") -> 0 | AS35: =IFERROR(AD35-L35,"") -> 0 | AT35: =IFERROR(AA35-H35,"") -> 0 | AU35: =AF35*Settings!$B$7+AG35*Settings!$B$8+AE35*Settings!$B$9+AB35*Settings!$B$10+AC35*Settings!$B$11+X35*Settings!$B$12+Y35*Settings!$B$13+Z35*Settings!$B$14 -> 0
A37: YOUR TOTAL | U37: =SUM(U11:U35) -> 425 | V37: =SUM(V11:V35) -> 533 | W37: =SUM(W11:W35) -> 358 | X37: =SUM(X11:X35) -> 4048 | Y37: =SUM(Y11:Y35) -> 29 | Z37: =SUM(Z11:Z35) -> 11 | AA37: =SUM(AA11:AA35) -> 530 | AB37: =SUM(AB11:AB35) -> 2539 | ... AG37: =SUM(AG11:AG35) -> 28
A38: TEAM TARGET | V38: =$F$5 -> 561 | X38: =$I$5 -> 4003 | Y38: =$J$5 -> 28 | Z38: =$K$5 -> 11 | AA38: =$H$5 -> 503.2 | AB38: =$L$5 -> 2305 | AC38: =$M$5 -> 24 | AD38: =$G$5 -> 535 | AF38: =$I$5 -> 4003 | AG38: =$J$5 -> 28
A39: LEFT | V39: =$F$5-V37 -> 28 | X39: =$I$5-X37 -> -45 | Y39: =$J$5-Y37 -> -1 | Z39: =$K$5-Z37 -> 0 | AA39: =$H$5-AA37 -> -26.8 | AB39: =$L$5-AB37 -> -234 | AC39: =$M$5-AC37 -> -2 | AD39: =$G$5-AD37 -> -1 | AF39: =$I$5-AF37 -> -270 | AG39: =$J$5-AG37 -> 0
B40: Red = you have allocated more than the team total. Amber = more than 3% under. These are targets, not hard caps - if you disagree, edit the team total above. | AF40: Rec Yds / Rec TD are checked against the PASSING totals

Sheet CAR
A1: CAR - 2026 projections (direct entry)
A3: TEAM TOTALS | D3: all editable - these are your targets, not hard caps
B4: Games | C4: Plays/G | D4: Plays | E4: Pass Rate | F4: Pass Att | G4: Targets | H4: Rush Att | I4: Pass Yds | J4: Pass TD | K4: Int | L4: Rush Yds | M4: Rush TD
B5: 17 | C5: 60.8 | D5: =C5*B5 -> 1033.6 | E5: 0.5665 | F5: =ROUND(D5*E5,0) -> 586 | G5: =ROUND(F5*Settings!$B$4,0) -> 559 | H5: =D5-F5 -> 447.6 | I5: 3513 | J5: 23 | K5: 12 | L5: 1936 | M5: 13
A7: VACATED | B7: 16% of targets and 53% of carries left this roster - that volume is yours to reassign.
A8: STAFF | B8: no coaching change recorded
A10: Pos | B10: Player | C10: Dep | D10: Age | E10: Status | F10: '23 Car | G10: '24 Car | H10: '25 Car | I10: '25 RuYd | J10: '23 Tgt | K10: '24 Tgt | L10: '25 Tgt | M10: '25 ReYd | N10: '25 Tm | O10: '25 G | P10: 3y Y/C | Q10: 3y Y/R | R10: 3y Ctch | S10: 3y Comp% | T10: 3y Y/A | U10: Games | V10: Pass Att | W10: Cmp | X10: Pass Yds | Y10: Pass TD | Z10: Int | AA10: Rush Att | AB10: Rush Yds | AC10: Rush TD | AD10: Targets | AE10: Rec | AF10: Rec Yds | AG10: Rec TD | AH10: Seed | AI10: Y/C | AJ10: Y/R | AK10: Catch% | AL10: Y/A | AM10: Comp% | AN10: Rush % | AO10: Tgt % | AP10: Pass % | AQ10: Car/G | AR10: Tgt/G | AS10: dTgt | AT10: dCar | AU10: Half PPR
A11: QB | B11: Bryce Young | C11: 1 | D11: 25 | E11: ACT | F11: 35 | G11: 38 | H11: 39 | I11: 216 | N11: CAR | O11: 16 | P11: 6.41 | S11: 0.614 | T11: 5.97 | U11: 17 | V11: 504 | W11: 318 | X11: 3288 | Y11: 22 | Z11: 12 | AA11: 55 | AB11: 250 | AC11: 3 | AD11: 0 | AE11: 0 | AF11: 0 | AG11: 0 | AH11: kept | AI11: =IFERROR(AB11/AA11,"") -> 4.5454545 | AJ11: =IFERROR(AF11/AE11,"") | AK11: =IFERROR(AE11/AD11,"") | AL11: =IFERROR(X11/V11,"") -> 6.5238095 | AM11: =IFERROR(W11/V11,"") -> 0.63095238 | AN11: =IFERROR(AA11/$H$5,"") -> 0.12287757 | AO11: =IFERROR(AD11/$G$5,"") -> 0 | AP11: =IFERROR(V11/$F$5,"") -> 0.86006826 | AQ11: =IFERROR(AA11/U11,"") -> 3.2352941 | AR11: =IFERROR(AD11/U11,"") -> 0 | AS11: =IFERROR(AD11-L11,"") -> 0 | AT11: =IFERROR(AA11-H11,"") -> 16 | AU11: =AF11*Settings!$B$7+AG11*Settings!$B$8+AE11*Settings!$B$9+AB11*Settings!$B$10+AC11*Settings!$B$11+X11*Settings!$B$12+Y11*Settings!$B$13+Z11*Settings!$B$14 -> 238.52
A12: QB | B12: Kenny Pickett | C12: 2 | D12: 28 | E12: ACT | F12: 24 | G12: 7 | H12: 5 | I12: 22 | N12: LV | O12: 6 | P12: 2.53 | S12: 0.618 | T12: 6.2 | U12: 17 | V12: 31 | W12: 20 | X12: 196 | Y12: 1 | Z12: 1 | AA12: 3 | AB12: 9 | AC12: 0 | AD12: 0 | AE12: 0 | AF12: 0 | AG12: 0 | AH12: kept | AI12: =IFERROR(AB12/AA12,"") -> 3 | AJ12: =IFERROR(AF12/AE12,"") | AK12: =IFERROR(AE12/AD12,"") | AL12: =IFERROR(X12/V12,"") -> 6.3225806 | AM12: =IFERROR(W12/V12,"") -> 0.64516129 | AN12: =IFERROR(AA12/$H$5,"") -> 0.0067024129 | AO12: =IFERROR(AD12/$G$5,"") -> 0 | AP12: =IFERROR(V12/$F$5,"") -> 0.052901024 | AQ12: =IFERROR(AA12/U12,"") -> 0.17647059 | AR12: =IFERROR(AD12/U12,"") -> 0 | AS12: =IFERROR(AD12-L12,"") -> 0 | AT12: =IFERROR(AA12-H12,"") -> -2 | AU12: =AF12*Settings!$B$7+AG12*Settings!$B$8+AE12*Settings!$B$9+AB12*Settings!$B$10+AC12*Settings!$B$11+X12*Settings!$B$12+Y12*Settings!$B$13+Z12*Settings!$B$14 -> 10.74
A13: QB | B13: Haynes King | C13: 3 | D13: 25 | E13: ACT | U13: 17 | V13: 10 | W13: 6 | X13: 33 | Y13: 0 | Z13: 0 | AA13: 0 | AB13: 0 | AC13: 0 | AH13: kept | AI13: =IFERROR(AB13/AA13,"") | AJ13: =IFERROR(AF13/AE13,"") | AK13: =IFERROR(AE13/AD13,"") | AL13: =IFERROR(X13/V13,"") -> 3.3 | AM13: =IFERROR(W13/V13,"") -> 0.6 | AN13: =IFERROR(AA13/$H$5,"") -> 0 | AO13: =IFERROR(AD13/$G$5,"") -> 0 | AP13: =IFERROR(V13/$F$5,"") -> 0.017064846 | AQ13: =IFERROR(AA13/U13,"") -> 0 | AR13: =IFERROR(AD13/U13,"") -> 0 | AS13: =IFERROR(AD13-L13,"") -> 0 | AT13: =IFERROR(AA13-H13,"") -> 0 | AU13: =AF13*Settings!$B$7+AG13*Settings!$B$8+AE13*Settings!$B$9+AB13*Settings!$B$10+AC13*Settings!$B$11+X13*Settings!$B$12+Y13*Settings!$B$13+Z13*Settings!$B$14 -> 1.32
A14: QB | B14: Other QBs | U14: 17 | AI14: =IFERROR(AB14/AA14,"") | AJ14: =IFERROR(AF14/AE14,"") | AK14: =IFERROR(AE14/AD14,"") | AL14: =IFERROR(X14/V14,"") | AM14: =IFERROR(W14/V14,"") | AN14: =IFERROR(AA14/$H$5,"") -> 0 | AO14: =IFERROR(AD14/$G$5,"") -> 0 | AP14: =IFERROR(V14/$F$5,"") -> 0 | AQ14: =IFERROR(AA14/U14,"") -> 0 | AR14: =IFERROR(AD14/U14,"") -> 0 | AS14: =IFERROR(AD14-L14,"") -> 0 | AT14: =IFERROR(AA14-H14,"") -> 0 | AU14: =AF14*Settings!$B$7+AG14*Settings!$B$8+AE14*Settings!$B$9+AB14*Settings!$B$10+AC14*Settings!$B$11+X14*Settings!$B$12+Y14*Settings!$B$13+Z14*Settings!$B$14 -> 0
A15: RB | B15: Chuba Hubbard | C15: 1 | D15: 27 | E15: ACT | F15: 238 | G15: 250 | H15: 134 | I15: 511 | J15: 44 | K15: 54 | L15: 39 | M15: 223 | N15: CAR | O15: 15 | P15: 4.19 | Q15: 5.6 | R15: 0.818 | U15: 17 | V15: 0 | W15: 0 | X15: 0 | Y15: 0 | Z15: 0 | AA15: 197 | AB15: 816 | AC15: 5 | AD15: 45 | AE15: 33 | AF15: 226 | AG15: 2 | AH15: kept | AI15: =IFERROR(AB15/AA15,"") -> 4.142132 | AJ15: =IFERROR(AF15/AE15,"") -> 6.8484848 | AK15: =IFERROR(AE15/AD15,"") -> 0.73333333 | AL15: =IFERROR(X15/V15,"") | AM15: =IFERROR(W15/V15,"") | AN15: =IFERROR(AA15/$H$5,"") -> 0.44012511 | AO15: =IFERROR(AD15/$G$5,"") -> 0.080500894 | AP15: =IFERROR(V15/$F$5,"") -> 0 | AQ15: =IFERROR(AA15/U15,"") -> 11.588235 | AR15: =IFERROR(AD15/U15,"") -> 2.6470588 | AS15: =IFERROR(AD15-L15,"") -> 6 | AT15: =IFERROR(AA15-H15,"") -> 63 | AU15: =AF15*Settings!$B$7+AG15*Settings!$B$8+AE15*Settings!$B$9+AB15*Settings!$B$10+AC15*Settings!$B$11+X15*Settings!$B$12+Y15*Settings!$B$13+Z15*Settings!$B$14 -> 162.7
A16: RB | B16: Jonathon Brooks | C16: 2 | D16: 23 | E16: ACT | G16: 9 | K16: 3 | P16: 2.44 | Q16: 7.67 | R16: 1 | U16: 17 | AA16: 167 | AB16: 700 | AC16: 4 | AD16: 35 | AE16: 27 | AF16: 200 | AG16: 1 | AH16: kept | AI16: =IFERROR(AB16/AA16,"") -> 4.1916168 | AJ16: =IFERROR(AF16/AE16,"") -> 7.4074074 | AK16: =IFERROR(AE16/AD16,"") -> 0.77142857 | AL16: =IFERROR(X16/V16,"") | AM16: =IFERROR(W16/V16,"") | AN16: =IFERROR(AA16/$H$5,"") -> 0.37310098 | AO16: =IFERROR(AD16/$G$5,"") -> 0.062611807 | AP16: =IFERROR(V16/$F$5,"") -> 0 | AQ16: =IFERROR(AA16/U16,"") -> 9.8235294 | AR16: =IFERROR(AD16/U16,"") -> 2.0588235 | AS16: =IFERROR(AD16-L16,"") -> 35 | AT16: =IFERROR(AA16-H16,"") -> 167 | AU16: =AF16*Settings!$B$7+AG16*Settings!$B$8+AE16*Settings!$B$9+AB16*Settings!$B$10+AC16*Settings!$B$11+X16*Settings!$B$12+Y16*Settings!$B$13+Z16*Settings!$B$14 -> 133.5
A17: RB | B17: AJ Dillon | C17: 3 | D17: 28 | E17: ACT | F17: 178 | H17: 12 | I17: 60 | J17: 28 | L17: 3 | M17: 21 | N17: PHI | O17: 7 | P17: 3.54 | Q17: 9.76 | R17: 0.806 | U17: 17 | V17: 0 | W17: 0 | X17: 0 | Y17: 0 | Z17: 0 | AA17: 49 | AB17: 206 | AC17: 1 | AD17: 7 | AE17: 6 | AF17: 53 | AG17: 0 | AH17: kept | AI17: =IFERROR(AB17/AA17,"") -> 4.2040816 | AJ17: =IFERROR(AF17/AE17,"") -> 8.8333333 | AK17: =IFERROR(AE17/AD17,"") -> 0.85714286 | AL17: =IFERROR(X17/V17,"") | AM17: =IFERROR(W17/V17,"") | AN17: =IFERROR(AA17/$H$5,"") -> 0.10947274 | AO17: =IFERROR(AD17/$G$5,"") -> 0.012522361 | AP17: =IFERROR(V17/$F$5,"") -> 0 | AQ17: =IFERROR(AA17/U17,"") -> 2.8823529 | AR17: =IFERROR(AD17/U17,"") -> 0.41176471 | AS17: =IFERROR(AD17-L17,"") -> 4 | AT17: =IFERROR(AA17-H17,"") -> 37 | AU17: =AF17*Settings!$B$7+AG17*Settings!$B$8+AE17*Settings!$B$9+AB17*Settings!$B$10+AC17*Settings!$B$11+X17*Settings!$B$12+Y17*Settings!$B$13+Z17*Settings!$B$14 -> 34.9
A18: RB | B18: Trevor Etienne | C18: 4 | D18: 22 | E18: ACT | H18: 20 | I18: 94 | L18: 3 | M18: 13 | N18: CAR | O18: 17 | P18: 4.7 | Q18: 4.33 | R18: 1 | U18: 17 | V18: 0 | W18: 0 | X18: 0 | Y18: 0 | Z18: 0 | AA18: 18 | AB18: 87 | AC18: 0 | AD18: 5 | AE18: 5 | AF18: 33 | AG18: 0 | AH18: kept | AI18: =IFERROR(AB18/AA18,"") -> 4.8333333 | AJ18: =IFERROR(AF18/AE18,"") -> 6.6 | AK18: =IFERROR(AE18/AD18,"") -> 1 | AL18: =IFERROR(X18/V18,"") | AM18: =IFERROR(W18/V18,"") | AN18: =IFERROR(AA18/$H$5,"") -> 0.040214477 | AO18: =IFERROR(AD18/$G$5,"") -> 0.0089445438 | AP18: =IFERROR(V18/$F$5,"") -> 0 | AQ18: =IFERROR(AA18/U18,"") -> 1.0588235 | AR18: =IFERROR(AD18/U18,"") -> 0.29411765 | AS18: =IFERROR(AD18-L18,"") -> 2 | AT18: =IFERROR(AA18-H18,"") -> -2 | AU18: =AF18*Settings!$B$7+AG18*Settings!$B$8+AE18*Settings!$B$9+AB18*Settings!$B$10+AC18*Settings!$B$11+X18*Settings!$B$12+Y18*Settings!$B$13+Z18*Settings!$B$14 -> 14.5
A19: RB | B19: Anthony Tyus | C19: 5 | D19: 23 | E19: ACT | U19: 17 | AI19: =IFERROR(AB19/AA19,"") | AJ19: =IFERROR(AF19/AE19,"") | AK19: =IFERROR(AE19/AD19,"") | AL19: =IFERROR(X19/V19,"") | AM19: =IFERROR(W19/V19,"") | AN19: =IFERROR(AA19/$H$5,"") -> 0 | AO19: =IFERROR(AD19/$G$5,"") -> 0 | AP19: =IFERROR(V19/$F$5,"") -> 0 | AQ19: =IFERROR(AA19/U19,"") -> 0 | AR19: =IFERROR(AD19/U19,"") -> 0 | AS19: =IFERROR(AD19-L19,"") -> 0 | AT19: =IFERROR(AA19-H19,"") -> 0 | AU19: =AF19*Settings!$B$7+AG19*Settings!$B$8+AE19*Settings!$B$9+AB19*Settings!$B$10+AC19*Settings!$B$11+X19*Settings!$B$12+Y19*Settings!$B$13+Z19*Settings!$B$14 -> 0
A20: RB | B20: Miles Davis | C20: 6 | D20: 26 | E20: ACT | U20: 17 | AI20: =IFERROR(AB20/AA20,"") | AJ20: =IFERROR(AF20/AE20,"") | AK20: =IFERROR(AE20/AD20,"") | AL20: =IFERROR(X20/V20,"") | AM20: =IFERROR(W20/V20,"") | AN20: =IFERROR(AA20/$H$5,"") -> 0 | AO20: =IFERROR(AD20/$G$5,"") -> 0 | AP20: =IFERROR(V20/$F$5,"") -> 0 | AQ20: =IFERROR(AA20/U20,"") -> 0 | AR20: =IFERROR(AD20/U20,"") -> 0 | AS20: =IFERROR(AD20-L20,"") -> 0 | AT20: =IFERROR(AA20-H20,"") -> 0 | AU20: =AF20*Settings!$B$7+AG20*Settings!$B$8+AE20*Settings!$B$9+AB20*Settings!$B$10+AC20*Settings!$B$11+X20*Settings!$B$12+Y20*Settings!$B$13+Z20*Settings!$B$14 -> 0
A21: RB | B21: Other RBs | U21: 17 | AI21: =IFERROR(AB21/AA21,"") | AJ21: =IFERROR(AF21/AE21,"") | AK21: =IFERROR(AE21/AD21,"") | AL21: =IFERROR(X21/V21,"") | AM21: =IFERROR(W21/V21,"") | AN21: =IFERROR(AA21/$H$5,"") -> 0 | AO21: =IFERROR(AD21/$G$5,"") -> 0 | AP21: =IFERROR(V21/$F$5,"") -> 0 | AQ21: =IFERROR(AA21/U21,"") -> 0 | AR21: =IFERROR(AD21/U21,"") -> 0 | AS21: =IFERROR(AD21-L21,"") -> 0 | AT21: =IFERROR(AA21-H21,"") -> 0 | AU21: =AF21*Settings!$B$7+AG21*Settings!$B$8+AE21*Settings!$B$9+AB21*Settings!$B$10+AC21*Settings!$B$11+X21*Settings!$B$12+Y21*Settings!$B$13+Z21*Settings!$B$14 -> 0
A22: WR | B22: Tetairoa McMillan | C22: 1 | D22: 23 | E22: ACT | L22: 122 | M22: 1014 | N22: CAR | O22: 17 | Q22: 14.49 | R22: 0.574 | U22: 17 | V22: 0 | W22: 0 | X22: 0 | Y22: 0 | Z22: 0 | AA22: 0 | AB22: 1 | AC22: 0 | AD22: 129 | AE22: 75 | AF22: 1072 | AG22: 7 | AH22: kept | AI22: =IFERROR(AB22/AA22,"") | AJ22: =IFERROR(AF22/AE22,"") -> 14.293333 | AK22: =IFERROR(AE22/AD22,"") -> 0.58139535 | AL22: =IFERROR(X22/V22,"") | AM22: =IFERROR(W22/V22,"") | AN22: =IFERROR(AA22/$H$5,"") -> 0 | AO22: =IFERROR(AD22/$G$5,"") -> 0.23076923 | AP22: =IFERROR(V22/$F$5,"") -> 0 | AQ22: =IFERROR(AA22/U22,"") -> 0 | AR22: =IFERROR(AD22/U22,"") -> 7.5882353 | AS22: =IFERROR(AD22-L22,"") -> 7 | AT22: =IFERROR(AA22-H22,"") -> 0 | AU22: =AF22*Settings!$B$7+AG22*Settings!$B$8+AE22*Settings!$B$9+AB22*Settings!$B$10+AC22*Settings!$B$11+X22*Settings!$B$12+Y22*Settings!$B$13+Z22*Settings!$B$14 -> 186.8
A23: WR | B23: John Metchie | C23: 2 | D23: 26 | E23: ACT | F23: 1 | J23: 30 | K23: 37 | L23: 4 | M23: 18 | N23: PHI | O23: 7 | P23: 4 | Q23: 9.77 | R23: 0.62 | U23: 17 | V23: 0 | W23: 0 | X23: 0 | Y23: 0 | Z23: 0 | AA23: 1 | AB23: 2 | AC23: 0 | AD23: 45 | AE23: 27 | AF23: 272 | AG23: 2 | AH23: kept | AI23: =IFERROR(AB23/AA23,"") -> 2 | AJ23: =IFERROR(AF23/AE23,"") -> 10.074074 | AK23: =IFERROR(AE23/AD23,"") -> 0.6 | AL23: =IFERROR(X23/V23,"") | AM23: =IFERROR(W23/V23,"") | AN23: =IFERROR(AA23/$H$5,"") -> 0.0022341376 | AO23: =IFERROR(AD23/$G$5,"") -> 0.080500894 | AP23: =IFERROR(V23/$F$5,"") -> 0 | AQ23: =IFERROR(AA23/U23,"") -> 0.058823529 | AR23: =IFERROR(AD23/U23,"") -> 2.6470588 | AS23: =IFERROR(AD23-L23,"") -> 41 | AT23: =IFERROR(AA23-H23,"") -> 1 | AU23: =AF23*Settings!$B$7+AG23*Settings!$B$8+AE23*Settings!$B$9+AB23*Settings!$B$10+AC23*Settings!$B$11+X23*Settings!$B$12+Y23*Settings!$B$13+Z23*Settings!$B$14 -> 52.9
A24: WR | B24: Jalen Coker | C24: 3 | D24: 24 | E24: ACT | K24: 46 | L24: 43 | M24: 394 | N24: CAR | O24: 11 | Q24: 13.42 | R24: 0.73 | S24: 1 | U24: 17 | V24: 0 | W24: 0 | X24: 0 | Y24: 0 | Z24: 0 | AA24: 0 | AB24: 0 | AC24: 0 | AD24: 83 | AE24: 57 | AF24: 694 | AG24: 4 | AH24: kept | AI24: =IFERROR(AB24/AA24,"") | AJ24: =IFERROR(AF24/AE24,"") -> 12.175439 | AK24: =IFERROR(AE24/AD24,"") -> 0.68674699 | AL24: =IFERROR(X24/V24,"") | AM24: =IFERROR(W24/V24,"") | AN24: =IFERROR(AA24/$H$5,"") -> 0 | AO24: =IFERROR(AD24/$G$5,"") -> 0.14847943 | AP24: =IFERROR(V24/$F$5,"") -> 0 | AQ24: =IFERROR(AA24/U24,"") -> 0 | AR24: =IFERROR(AD24/U24,"") -> 4.8823529 | AS24: =IFERROR(AD24-L24,"") -> 40 | AT24: =IFERROR(AA24-H24,"") -> 0 | AU24: =AF24*Settings!$B$7+AG24*Settings!$B$8+AE24*Settings!$B$9+AB24*Settings!$B$10+AC24*Settings!$B$11+X24*Settings!$B$12+Y24*Settings!$B$13+Z24*Settings!$B$14 -> 121.9
A25: WR | B25: Xavier Legette | C25: 4 | D25: 25 | E25: QUESTIONABLE | G25: 6 | H25: 1 | K25: 84 | L25: 64 | M25: 363 | N25: CAR | O25: 15 | P25: 3.43 | Q25: 10.24 | R25: 0.568 | U25: 17 | V25: 0 | W25: 0 | X25: 0 | Y25: 0 | Z25: 0 | AA25: 1 | AB25: 5 | AC25: 0 | AD25: 56 | AE25: 33 | AF25: 364 | AG25: 3 | AH25: kept | AI25: =IFERROR(AB25/AA25,"") -> 5 | AJ25: =IFERROR(AF25/AE25,"") -> 11.030303 | AK25: =IFERROR(AE25/AD25,"") -> 0.58928571 | AL25: =IFERROR(X25/V25,"") | AM25: =IFERROR(W25/V25,"") | AN25: =IFERROR(AA25/$H$5,"") -> 0.0022341376 | AO25: =IFERROR(AD25/$G$5,"") -> 0.10017889 | AP25: =IFERROR(V25/$F$5,"") -> 0 | AQ25: =IFERROR(AA25/U25,"") -> 0.058823529 | AR25: =IFERROR(AD25/U25,"") -> 3.2941176 | AS25: =IFERROR(AD25-L25,"") -> -8 | AT25: =IFERROR(AA25-H25,"") -> 0 | AU25: =AF25*Settings!$B$7+AG25*Settings!$B$8+AE25*Settings!$B$9+AB25*Settings!$B$10+AC25*Settings!$B$11+X25*Settings!$B$12+Y25*Settings!$B$13+Z25*Settings!$B$14 -> 71.4
A26: WR | B26: David Moore | C26: 5 | D26: 31 | E26: ACT | G26: 1 | H26: 1 | I26: 12 | J26: 7 | K26: 57 | L26: 1 | M26: 5 | N26: CAR | O26: 4 | P26: 6 | Q26: 11.84 | R26: 0.585 | U26: 17 | V26: 0 | W26: 0 | X26: 0 | Y26: 0 | Z26: 0 | AA26: 0 | AB26: 0 | AC26: 0 | AD26: 7 | AE26: 5 | AF26: 57 | AG26: 0 | AH26: kept | AI26: =IFERROR(AB26/AA26,"") | AJ26: =IFERROR(AF26/AE26,"") -> 11.4 | AK26: =IFERROR(AE26/AD26,"") -> 0.71428571 | AL26: =IFERROR(X26/V26,"") | AM26: =IFERROR(W26/V26,"") | AN26: =IFERROR(AA26/$H$5,"") -> 0 | AO26: =IFERROR(AD26/$G$5,"") -> 0.012522361 | AP26: =IFERROR(V26/$F$5,"") -> 0 | AQ26: =IFERROR(AA26/U26,"") -> 0 | AR26: =IFERROR(AD26/U26,"") -> 0.41176471 | AS26: =IFERROR(AD26-L26,"") -> 6 | AT26: =IFERROR(AA26-H26,"") -> -1 | AU26: =AF26*Settings!$B$7+AG26*Settings!$B$8+AE26*Settings!$B$9+AB26*Settings!$B$10+AC26*Settings!$B$11+X26*Settings!$B$12+Y26*Settings!$B$13+Z26*Settings!$B$14 -> 8.2
A27: WR | B27: Jimmy Horn | C27: 6 | D27: 23 | E27: ACT | H27: 8 | I27: 69 | L27: 15 | M27: 108 | N27: CAR | O27: 13 | P27: 8.62 | Q27: 9.82 | R27: 0.733 | U27: 17 | V27: 0 | W27: 0 | X27: 0 | Y27: 0 | Z27: 0 | AA27: 6 | AB27: 45 | AC27: 0 | AD27: 16 | AE27: 12 | AF27: 114 | AG27: 1 | AH27: kept | AI27: =IFERROR(AB27/AA27,"") -> 7.5 | AJ27: =IFERROR(AF27/AE27,"") -> 9.5 | AK27: =IFERROR(AE27/AD27,"") -> 0.75 | AL27: =IFERROR(X27/V27,"") | AM27: =IFERROR(W27/V27,"") | AN27: =IFERROR(AA27/$H$5,"") -> 0.013404826 | AO27: =IFERROR(AD27/$G$5,"") -> 0.02862254 | AP27: =IFERROR(V27/$F$5,"") -> 0 | AQ27: =IFERROR(AA27/U27,"") -> 0.35294118 | AR27: =IFERROR(AD27/U27,"") -> 0.94117647 | AS27: =IFERROR(AD27-L27,"") -> 1 | AT27: =IFERROR(AA27-H27,"") -> -2 | AU27: =AF27*Settings!$B$7+AG27*Settings!$B$8+AE27*Settings!$B$9+AB27*Settings!$B$10+AC27*Settings!$B$11+X27*Settings!$B$12+Y27*Settings!$B$13+Z27*Settings!$B$14 -> 27.9
A28: WR | B28: Brycen Tremayne | C28: 7 | D28: 26 | E28: ACT | K28: 1 | L28: 18 | M28: 160 | N28: CAR | O28: 16 | Q28: 10.53 | R28: 0.789 | U28: 17 | V28: 0 | W28: 0 | X28: 0 | Y28: 0 | Z28: 0 | AA28: 0 | AB28: 0 | AC28: 0 | AD28: 3 | AE28: 2 | AF28: 21 | AG28: 0 | AH28: kept | AI28: =IFERROR(AB28/AA28,"") | AJ28: =IFERROR(AF28/AE28,"") -> 10.5 | AK28: =IFERROR(AE28/AD28,"") -> 0.66666667 | AL28: =IFERROR(X28/V28,"") | AM28: =IFERROR(W28/V28,"") | AN28: =IFERROR(AA28/$H$5,"") -> 0 | AO28: =IFERROR(AD28/$G$5,"") -> 0.0053667263 | AP28: =IFERROR(V28/$F$5,"") -> 0 | AQ28: =IFERROR(AA28/U28,"") -> 0 | AR28: =IFERROR(AD28/U28,"") -> 0.17647059 | AS28: =IFERROR(AD28-L28,"") -> -15 | AT28: =IFERROR(AA28-H28,"") -> 0 | AU28: =AF28*Settings!$B$7+AG28*Settings!$B$8+AE28*Settings!$B$9+AB28*Settings!$B$10+AC28*Settings!$B$11+X28*Settings!$B$12+Y28*Settings!$B$13+Z28*Settings!$B$14 -> 3.1
A29: WR | B29: Casey Washington | C29: 8 | D29: 25 | E29: ACT | K29: 2 | L29: 14 | M29: 94 | N29: ATL | O29: 7 | Q29: 15.43 | R29: 0.438 | U29: 17 | V29: 0 | W29: 0 | X29: 0 | Y29: 0 | Z29: 0 | AA29: 0 | AB29: 0 | AC29: 0 | AD29: 1 | AE29: 3 | AF29: 40 | AG29: 0 | AH29: kept | AI29: =IFERROR(AB29/AA29,"") | AJ29: =IFERROR(AF29/AE29,"") -> 13.333333 | AK29: =IFERROR(AE29/AD29,"") -> 3 | AL29: =IFERROR(X29/V29,"") | AM29: =IFERROR(W29/V29,"") | AN29: =IFERROR(AA29/$H$5,"") -> 0 | AO29: =IFERROR(AD29/$G$5,"") -> 0.0017889088 | AP29: =IFERROR(V29/$F$5,"") -> 0 | AQ29: =IFERROR(AA29/U29,"") -> 0 | AR29: =IFERROR(AD29/U29,"") -> 0.058823529 | AS29: =IFERROR(AD29-L29,"") -> -13 | AT29: =IFERROR(AA29-H29,"") -> 0 | AU29: =AF29*Settings!$B$7+AG29*Settings!$B$8+AE29*Settings!$B$9+AB29*Settings!$B$10+AC29*Settings!$B$11+X29*Settings!$B$12+Y29*Settings!$B$13+Z29*Settings!$B$14 -> 5.5
A30: WR | B30: Other WRs | U30: 17 | AI30: =IFERROR(AB30/AA30,"") | AJ30: =IFERROR(AF30/AE30,"") | AK30: =IFERROR(AE30/AD30,"") | AL30: =IFERROR(X30/V30,"") | AM30: =IFERROR(W30/V30,"") | AN30: =IFERROR(AA30/$H$5,"") -> 0 | AO30: =IFERROR(AD30/$G$5,"") -> 0 | AP30: =IFERROR(V30/$F$5,"") -> 0 | AQ30: =IFERROR(AA30/U30,"") -> 0 | AR30: =IFERROR(AD30/U30,"") -> 0 | AS30: =IFERROR(AD30-L30,"") -> 0 | AT30: =IFERROR(AA30-H30,"") -> 0 | AU30: =AF30*Settings!$B$7+AG30*Settings!$B$8+AE30*Settings!$B$9+AB30*Settings!$B$10+AC30*Settings!$B$11+X30*Settings!$B$12+Y30*Settings!$B$13+Z30*Settings!$B$14 -> 0
A31: TE | B31: Ja'Tavion Sanders | C31: 1 | D31: 23 | E31: QUESTIONABLE | K31: 43 | L31: 34 | M31: 190 | N31: CAR | O31: 13 | Q31: 8.58 | R31: 0.805 | U31: 17 | V31: 0 | W31: 0 | X31: 0 | Y31: 0 | Z31: 0 | AA31: 0 | AB31: 0 | AC31: 0 | AD31: 37 | AE31: 29 | AF31: 238 | AG31: 2 | AH31: kept | AI31: =IFERROR(AB31/AA31,"") | AJ31: =IFERROR(AF31/AE31,"") -> 8.2068966 | AK31: =IFERROR(AE31/AD31,"") -> 0.78378378 | AL31: =IFERROR(X31/V31,"") | AM31: =IFERROR(W31/V31,"") | AN31: =IFERROR(AA31/$H$5,"") -> 0 | AO31: =IFERROR(AD31/$G$5,"") -> 0.066189624 | AP31: =IFERROR(V31/$F$5,"") -> 0 | AQ31: =IFERROR(AA31/U31,"") -> 0 | AR31: =IFERROR(AD31/U31,"") -> 2.1764706 | AS31: =IFERROR(AD31-L31,"") -> 3 | AT31: =IFERROR(AA31-H31,"") -> 0 | AU31: =AF31*Settings!$B$7+AG31*Settings!$B$8+AE31*Settings!$B$9+AB31*Settings!$B$10+AC31*Settings!$B$11+X31*Settings!$B$12+Y31*Settings!$B$13+Z31*Settings!$B$14 -> 50.3
A32: TE | B32: Tommy Tremble | C32: 2 | D32: 26 | E32: ACT | J32: 32 | K32: 32 | L32: 37 | M32: 249 | N32: CAR | O32: 17 | Q32: 9.27 | R32: 0.723 | U32: 17 | V32: 0 | W32: 0 | X32: 0 | Y32: 0 | Z32: 0 | AA32: 0 | AB32: 0 | AC32: 0 | AD32: 30 | AE32: 22 | AF32: 202 | AG32: 2 | AH32: kept | AI32: =IFERROR(AB32/AA32,"") | AJ32: =IFERROR(AF32/AE32,"") -> 9.1818182 | AK32: =IFERROR(AE32/AD32,"") -> 0.73333333 | AL32: =IFERROR(X32/V32,"") | AM32: =IFERROR(W32/V32,"") | AN32: =IFERROR(AA32/$H$5,"") -> 0 | AO32: =IFERROR(AD32/$G$5,"") -> 0.053667263 | AP32: =IFERROR(V32/$F$5,"") -> 0 | AQ32: =IFERROR(AA32/U32,"") -> 0 | AR32: =IFERROR(AD32/U32,"") -> 1.7647059 | AS32: =IFERROR(AD32-L32,"") -> -7 | AT32: =IFERROR(AA32-H32,"") -> 0 | AU32: =AF32*Settings!$B$7+AG32*Settings!$B$8+AE32*Settings!$B$9+AB32*Settings!$B$10+AC32*Settings!$B$11+X32*Settings!$B$12+Y32*Settings!$B$13+Z32*Settings!$B$14 -> 43.2
A33: TE | B33: Mitchell Evans | C33: 3 | D33: 23 | E33: ACT | H33: 1 | I33: 1 | L33: 25 | M33: 171 | N33: CAR | O33: 17 | P33: 1 | Q33: 9 | R33: 0.76 | U33: 17 | V33: 0 | W33: 0 | X33: 0 | Y33: 0 | Z33: 0 | AA33: 0 | AB33: 0 | AC33: 0 | AD33: 24 | AE33: 19 | AF33: 174 | AG33: 2 | AH33: kept | AI33: =IFERROR(AB33/AA33,"") | AJ33: =IFERROR(AF33/AE33,"") -> 9.1578947 | AK33: =IFERROR(AE33/AD33,"") -> 0.79166667 | AL33: =IFERROR(X33/V33,"") | AM33: =IFERROR(W33/V33,"") | AN33: =IFERROR(AA33/$H$5,"") -> 0 | AO33: =IFERROR(AD33/$G$5,"") -> 0.04293381 | AP33: =IFERROR(V33/$F$5,"") -> 0 | AQ33: =IFERROR(AA33/U33,"") -> 0 | AR33: =IFERROR(AD33/U33,"") -> 1.4117647 | AS33: =IFERROR(AD33-L33,"") -> -1 | AT33: =IFERROR(AA33-H33,"") -> -1 | AU33: =AF33*Settings!$B$7+AG33*Settings!$B$8+AE33*Settings!$B$9+AB33*Settings!$B$10+AC33*Settings!$B$11+X33*Settings!$B$12+Y33*Settings!$B$13+Z33*Settings!$B$14 -> 38.9
A34: TE | B34: James Mitchell | C34: 4 | D34: 26 | E34: ACT | J34: 2 | L34: 3 | M34: 28 | N34: CAR | O34: 5 | Q34: 11.2 | R34: 1 | U34: 17 | V34: 0 | W34: 0 | X34: 0 | Y34: 0 | Z34: 0 | AA34: 0 | AB34: 0 | AC34: 0 | AD34: 6 | AE34: 7 | AF34: 68 | AG34: 0 | AH34: kept | AI34: =IFERROR(AB34/AA34,"") | AJ34: =IFERROR(AF34/AE34,"") -> 9.7142857 | AK34: =IFERROR(AE34/AD34,"") -> 1.1666667 | AL34: =IFERROR(X34/V34,"") | AM34: =IFERROR(W34/V34,"") | AN34: =IFERROR(AA34/$H$5,"") -> 0 | AO34: =IFERROR(AD34/$G$5,"") -> 0.010733453 | AP34: =IFERROR(V34/$F$5,"") -> 0 | AQ34: =IFERROR(AA34/U34,"") -> 0 | AR34: =IFERROR(AD34/U34,"") -> 0.35294118 | AS34: =IFERROR(AD34-L34,"") -> 3 | AT34: =IFERROR(AA34-H34,"") -> 0 | AU34: =AF34*Settings!$B$7+AG34*Settings!$B$8+AE34*Settings!$B$9+AB34*Settings!$B$10+AC34*Settings!$B$11+X34*Settings!$B$12+Y34*Settings!$B$13+Z34*Settings!$B$14 -> 10.3
A35: TE | B35: Other TEs | U35: 17 | AI35: =IFERROR(AB35/AA35,"") | AJ35: =IFERROR(AF35/AE35,"") | AK35: =IFERROR(AE35/AD35,"") | AL35: =IFERROR(X35/V35,"") | AM35: =IFERROR(W35/V35,"") | AN35: =IFERROR(AA35/$H$5,"") -> 0 | AO35: =IFERROR(AD35/$G$5,"") -> 0 | AP35: =IFERROR(V35/$F$5,"") -> 0 | AQ35: =IFERROR(AA35/U35,"") -> 0 | AR35: =IFERROR(AD35/U35,"") -> 0 | AS35: =IFERROR(AD35-L35,"") -> 0 | AT35: =IFERROR(AA35-H35,"") -> 0 | AU35: =AF35*Settings!$B$7+AG35*Settings!$B$8+AE35*Settings!$B$9+AB35*Settings!$B$10+AC35*Settings!$B$11+X35*Settings!$B$12+Y35*Settings!$B$13+Z35*Settings!$B$14 -> 0
A37: YOUR TOTAL | U37: =SUM(U11:U35) -> 425 | V37: =SUM(V11:V35) -> 545 | W37: =SUM(W11:W35) -> 344 | X37: =SUM(X11:X35) -> 3517 | Y37: =SUM(Y11:Y35) -> 23 | Z37: =SUM(Z11:Z35) -> 13 | AA37: =SUM(AA11:AA35) -> 497 | AB37: =SUM(AB11:AB35) -> 2121 | ... AG37: =SUM(AG11:AG35) -> 26
A38: TEAM TARGET | V38: =$F$5 -> 586 | X38: =$I$5 -> 3513 | Y38: =$J$5 -> 23 | Z38: =$K$5 -> 12 | AA38: =$H$5 -> 447.6 | AB38: =$L$5 -> 1936 | AC38: =$M$5 -> 13 | AD38: =$G$5 -> 559 | AF38: =$I$5 -> 3513 | AG38: =$J$5 -> 23
A39: LEFT | V39: =$F$5-V37 -> 41 | X39: =$I$5-X37 -> -4 | Y39: =$J$5-Y37 -> 0 | Z39: =$K$5-Z37 -> -1 | AA39: =$H$5-AA37 -> -49.4 | AB39: =$L$5-AB37 -> -185 | AC39: =$M$5-AC37 -> 0 | AD39: =$G$5-AD37 -> 30 | AF39: =$I$5-AF37 -> -315 | AG39: =$J$5-AG37 -> -3
B40: Red = you have allocated more than the team total. Amber = more than 3% under. These are targets, not hard caps - if you disagree, edit the team total above. | AF40: Rec Yds / Rec TD are checked against the PASSING totals

Sheet CHI
A1: CHI - 2026 projections (direct entry)
A3: TEAM TOTALS | D3: all editable - these are your targets, not hard caps
B4: Games | C4: Plays/G | D4: Plays | E4: Pass Rate | F4: Pass Att | G4: Targets | H4: Rush Att | I4: Pass Yds | J4: Pass TD | K4: Int | L4: Rush Yds | M4: Rush TD
B5: 17 | C5: 63.3 | D5: =C5*B5 -> 1076.1 | E5: 0.5562 | F5: =ROUND(D5*E5,0) -> 599 | G5: =ROUND(F5*Settings!$B$4,0) -> 571 | H5: =D5-F5 -> 477.1 | I5: 3787 | J5: 24 | K5: 10 | L5: 2132 | M5: 16
A7: VACATED | B7: 29% of targets and 4% of carries left this roster - that volume is yours to reassign.
A8: STAFF | B8: HC unchanged. OC Press Taylor under Ben Johnson. Continuity maintained; no significant regression expected.
A10: Pos | B10: Player | C10: Dep | D10: Age | E10: Status | F10: '23 Car | G10: '24 Car | H10: '25 Car | I10: '25 RuYd | J10: '23 Tgt | K10: '24 Tgt | L10: '25 Tgt | M10: '25 ReYd | N10: '25 Tm | O10: '25 G | P10: 3y Y/C | Q10: 3y Y/R | R10: 3y Ctch | S10: 3y Comp% | T10: 3y Y/A | U10: Games | V10: Pass Att | W10: Cmp | X10: Pass Yds | Y10: Pass TD | Z10: Int | AA10: Rush Att | AB10: Rush Yds | AC10: Rush TD | AD10: Targets | AE10: Rec | AF10: Rec Yds | AG10: Rec TD | AH10: Seed | AI10: Y/C | AJ10: Y/R | AK10: Catch% | AL10: Y/A | AM10: Comp% | AN10: Rush % | AO10: Tgt % | AP10: Pass % | AQ10: Car/G | AR10: Tgt/G | AS10: dTgt | AT10: dCar | AU10: Half PPR
A11: QB | B11: Caleb Williams | C11: 1 | D11: 24 | E11: ACT | G11: 75 | H11: 66 | I11: 388 | L11: 2 | M11: 22 | N11: CHI | O11: 17 | P11: 6.22 | Q11: 11 | R11: 1 | S11: 0.603 | T11: 6.62 | U11: 17 | V11: 546 | W11: 330 | X11: 3823 | Y11: 27 | Z11: 9 | AA11: 76 | AB11: 396 | AC11: 2 | AD11: 2 | AE11: 2 | AF11: 22 | AG11: 1 | AH11: kept | AI11: =IFERROR(AB11/AA11,"") -> 5.2105263 | AJ11: =IFERROR(AF11/AE11,"") -> 11 | AK11: =IFERROR(AE11/AD11,"") -> 1 | AL11: =IFERROR(X11/V11,"") -> 7.0018315 | AM11: =IFERROR(W11/V11,"") -> 0.6043956 | AN11: =IFERROR(AA11/$H$5,"") -> 0.15929575 | AO11: =IFERROR(AD11/$G$5,"") -> 0.003502627 | AP11: =IFERROR(V11/$F$5,"") -> 0.9115192 | AQ11: =IFERROR(AA11/U11,"") -> 4.4705882 | AR11: =IFERROR(AD11/U11,"") -> 0.11764706 | AS11: =IFERROR(AD11-L11,"") -> 0 | AT11: =IFERROR(AA11-H11,"") -> 10 | AU11: =AF11*Settings!$B$7+AG11*Settings!$B$8+AE11*Settings!$B$9+AB11*Settings!$B$10+AC11*Settings!$B$11+X11*Settings!$B$12+Y11*Settings!$B$13+Z11*Settings!$B$14 -> 303.72
A12: QB | B12: Tyson Bagent | C12: 2 | D12: 26 | E12: ACT | F12: 20 | H12: 2 | I12: 7 | N12: CHI | O12: 3 | P12: 4.95 | S12: 0.664 | T12: 6.15 | U12: 17 | V12: 26 | W12: 18 | X12: 210 | Y12: 1 | Z12: 1 | AA12: 5 | AB12: 15 | AC12: 0 | AD12: 0 | AE12: 0 | AF12: 0 | AG12: 0 | AH12: kept | AI12: =IFERROR(AB12/AA12,"") -> 3 | AJ12: =IFERROR(AF12/AE12,"") | AK12: =IFERROR(AE12/AD12,"") | AL12: =IFERROR(X12/V12,"") -> 8.0769231 | AM12: =IFERROR(W12/V12,"") -> 0.69230769 | AN12: =IFERROR(AA12/$H$5,"") -> 0.010479983 | AO12: =IFERROR(AD12/$G$5,"") -> 0 | AP12: =IFERROR(V12/$F$5,"") -> 0.043405676 | AQ12: =IFERROR(AA12/U12,"") -> 0.29411765 | AR12: =IFERROR(AD12/U12,"") -> 0 | AS12: =IFERROR(AD12-L12,"") -> 0 | AT12: =IFERROR(AA12-H12,"") -> 3 | AU12: =AF12*Settings!$B$7+AG12*Settings!$B$8+AE12*Settings!$B$9+AB12*Settings!$B$10+AC12*Settings!$B$11+X12*Settings!$B$12+Y12*Settings!$B$13+Z12*Settings!$B$14 -> 11.9
A13: QB | B13: Case Keenum | C13: 3 | D13: 38 | E13: ACT | F13: 2 | P13: 0.5 | S13: 0.642 | T13: 5.49 | U13: 17 | AI13: =IFERROR(AB13/AA13,"") | AJ13: =IFERROR(AF13/AE13,"") | AK13: =IFERROR(AE13/AD13,"") | AL13: =IFERROR(X13/V13,"") | AM13: =IFERROR(W13/V13,"") | AN13: =IFERROR(AA13/$H$5,"") -> 0 | AO13: =IFERROR(AD13/$G$5,"") -> 0 | AP13: =IFERROR(V13/$F$5,"") -> 0 | AQ13: =IFERROR(AA13/U13,"") -> 0 | AR13: =IFERROR(AD13/U13,"") -> 0 | AS13: =IFERROR(AD13-L13,"") -> 0 | AT13: =IFERROR(AA13-H13,"") -> 0 | AU13: =AF13*Settings!$B$7+AG13*Settings!$B$8+AE13*Settings!$B$9+AB13*Settings!$B$10+AC13*Settings!$B$11+X13*Settings!$B$12+Y13*Settings!$B$13+Z13*Settings!$B$14 -> 0
A14: QB | B14: Other QBs | U14: 17 | AI14: =IFERROR(AB14/AA14,"") | AJ14: =IFERROR(AF14/AE14,"") | AK14: =IFERROR(AE14/AD14,"") | AL14: =IFERROR(X14/V14,"") | AM14: =IFERROR(W14/V14,"") | AN14: =IFERROR(AA14/$H$5,"") -> 0 | AO14: =IFERROR(AD14/$G$5,"") -> 0 | AP14: =IFERROR(V14/$F$5,"") -> 0 | AQ14: =IFERROR(AA14/U14,"") -> 0 | AR14: =IFERROR(AD14/U14,"") -> 0 | AS14: =IFERROR(AD14-L14,"") -> 0 | AT14: =IFERROR(AA14-H14,"") -> 0 | AU14: =AF14*Settings!$B$7+AG14*Settings!$B$8+AE14*Settings!$B$9+AB14*Settings!$B$10+AC14*Settings!$B$11+X14*Settings!$B$12+Y14*Settings!$B$13+Z14*Settings!$B$14 -> 0
A15: RB | B15: D'Andre Swift | C15: 1 | D15: 27 | E15: ACT | F15: 229 | G15: 253 | H15: 223 | I15: 1087 | J15: 49 | K15: 52 | L15: 48 | M15: 299 | N15: CHI | O15: 16 | P15: 4.39 | Q15: 7.82 | R15: 0.772 | U15: 17 | V15: 0 | W15: 0 | X15: 0 | Y15: 0 | Z15: 0 | AA15: 217 | AB15: 979 | AC15: 8 | AD15: 43 | AE15: 33 | AF15: 273 | AG15: 1 | AH15: kept | AI15: =IFERROR(AB15/AA15,"") -> 4.5115207 | AJ15: =IFERROR(AF15/AE15,"") -> 8.2727273 | AK15: =IFERROR(AE15/AD15,"") -> 0.76744186 | AL15: =IFERROR(X15/V15,"") | AM15: =IFERROR(W15/V15,"") | AN15: =IFERROR(AA15/$H$5,"") -> 0.45483127 | AO15: =IFERROR(AD15/$G$5,"") -> 0.07530648 | AP15: =IFERROR(V15/$F$5,"") -> 0 | AQ15: =IFERROR(AA15/U15,"") -> 12.764706 | AR15: =IFERROR(AD15/U15,"") -> 2.5294118 | AS15: =IFERROR(AD15-L15,"") -> -5 | AT15: =IFERROR(AA15-H15,"") -> -6 | AU15: =AF15*Settings!$B$7+AG15*Settings!$B$8+AE15*Settings!$B$9+AB15*Settings!$B$10+AC15*Settings!$B$11+X15*Settings!$B$12+Y15*Settings!$B$13+Z15*Settings!$B$14 -> 195.7
A16: RB | B16: Kyle Monangai | C16: 2 | D16: 24 | E16: ACT | H16: 169 | I16: 783 | L16: 30 | M16: 164 | N16: CHI | O16: 17 | P16: 4.63 | Q16: 9.11 | R16: 0.6 | U16: 17 | V16: 0 | W16: 0 | X16: 0 | Y16: 0 | Z16: 0 | AA16: 177 | AB16: 761 | AC16: 5 | AD16: 32 | AE16: 22 | AF16: 175 | AG16: 1 | AH16: kept | AI16: =IFERROR(AB16/AA16,"") -> 4.299435 | AJ16: =IFERROR(AF16/AE16,"") -> 7.9545455 | AK16: =IFERROR(AE16/AD16,"") -> 0.6875 | AL16: =IFERROR(X16/V16,"") | AM16: =IFERROR(W16/V16,"") | AN16: =IFERROR(AA16/$H$5,"") -> 0.37099141 | AO16: =IFERROR(AD16/$G$5,"") -> 0.056042032 | AP16: =IFERROR(V16/$F$5,"") -> 0 | AQ16: =IFERROR(AA16/U16,"") -> 10.411765 | AR16: =IFERROR(AD16/U16,"") -> 1.8823529 | AS16: =IFERROR(AD16-L16,"") -> 2 | AT16: =IFERROR(AA16-H16,"") -> 8 | AU16: =AF16*Settings!$B$7+AG16*Settings!$B$8+AE16*Settings!$B$9+AB16*Settings!$B$10+AC16*Settings!$B$11+X16*Settings!$B$12+Y16*Settings!$B$13+Z16*Settings!$B$14 -> 140.6
A17: RB | B17: Roschon Johnson | C17: 3 | D17: 25 | E17: ACT | F17: 81 | G17: 55 | H17: 2 | I17: 17 | J17: 40 | K17: 20 | N17: CHI | O17: 7 | P17: 3.76 | Q17: 6.26 | R17: 0.833 | U17: 17 | V17: 0 | W17: 0 | X17: 0 | Y17: 0 | Z17: 0 | AA17: 18 | AB17: 78 | AC17: 1 | AD17: 3 | AE17: 3 | AF17: 19 | AG17: 0 | AH17: kept | AI17: =IFERROR(AB17/AA17,"") -> 4.3333333 | AJ17: =IFERROR(AF17/AE17,"") -> 6.3333333 | AK17: =IFERROR(AE17/AD17,"") -> 1 | AL17: =IFERROR(X17/V17,"") | AM17: =IFERROR(W17/V17,"") | AN17: =IFERROR(AA17/$H$5,"") -> 0.03772794 | AO17: =IFERROR(AD17/$G$5,"") -> 0.0052539405 | AP17: =IFERROR(V17/$F$5,"") -> 0 | AQ17: =IFERROR(AA17/U17,"") -> 1.0588235 | AR17: =IFERROR(AD17/U17,"") -> 0.17647059 | AS17: =IFERROR(AD17-L17,"") -> 3 | AT17: =IFERROR(AA17-H17,"") -> 16 | AU17: =AF17*Settings!$B$7+AG17*Settings!$B$8+AE17*Settings!$B$9+AB17*Settings!$B$10+AC17*Settings!$B$11+X17*Settings!$B$12+Y17*Settings!$B$13+Z17*Settings!$B$14 -> 17.2
A18: RB | B18: Brittain Brown | C18: 4 | D18: 28 | E18: ACT | H18: 5 | I18: 37 | L18: 1 | N18: CHI | O18: 3 | P18: 7.4 | U18: 17 | V18: 0 | W18: 0 | X18: 0 | Y18: 0 | Z18: 0 | AA18: 8 | AB18: 54 | AC18: 2 | AD18: 0 | AE18: 0 | AF18: 0 | AG18: 0 | AH18: kept | AI18: =IFERROR(AB18/AA18,"") -> 6.75 | AJ18: =IFERROR(AF18/AE18,"") | AK18: =IFERROR(AE18/AD18,"") | AL18: =IFERROR(X18/V18,"") | AM18: =IFERROR(W18/V18,"") | AN18: =IFERROR(AA18/$H$5,"") -> 0.016767973 | AO18: =IFERROR(AD18/$G$5,"") -> 0 | AP18: =IFERROR(V18/$F$5,"") -> 0 | AQ18: =IFERROR(AA18/U18,"") -> 0.47058824 | AR18: =IFERROR(AD18/U18,"") -> 0 | AS18: =IFERROR(AD18-L18,"") -> -1 | AT18: =IFERROR(AA18-H18,"") -> 3 | AU18: =AF18*Settings!$B$7+AG18*Settings!$B$8+AE18*Settings!$B$9+AB18*Settings!$B$10+AC18*Settings!$B$11+X18*Settings!$B$12+Y18*Settings!$B$13+Z18*Settings!$B$14 -> 17.4
A19: RB | B19: Salvon Ahmed | C19: 5 | D19: 27 | E19: ACT | F19: 22 | J19: 23 | P19: 2.77 | Q19: 5.5 | R19: 0.696 | U19: 17 | AA19: 18 | AB19: 76 | AC19: 0 | AD19: 1 | AE19: 0 | AF19: 6 | AG19: 0 | AH19: kept | AI19: =IFERROR(AB19/AA19,"") -> 4.2222222 | AJ19: =IFERROR(AF19/AE19,"") | AK19: =IFERROR(AE19/AD19,"") -> 0 | AL19: =IFERROR(X19/V19,"") | AM19: =IFERROR(W19/V19,"") | AN19: =IFERROR(AA19/$H$5,"") -> 0.03772794 | AO19: =IFERROR(AD19/$G$5,"") -> 0.0017513135 | AP19: =IFERROR(V19/$F$5,"") -> 0 | AQ19: =IFERROR(AA19/U19,"") -> 1.0588235 | AR19: =IFERROR(AD19/U19,"") -> 0.058823529 | AS19: =IFERROR(AD19-L19,"") -> 1 | AT19: =IFERROR(AA19-H19,"") -> 18 | AU19: =AF19*Settings!$B$7+AG19*Settings!$B$8+AE19*Settings!$B$9+AB19*Settings!$B$10+AC19*Settings!$B$11+X19*Settings!$B$12+Y19*Settings!$B$13+Z19*Settings!$B$14 -> 8.2
A20: RB | B20: Coleman Bennett | C20: 6 | E20: ACT | U20: 17 | AI20: =IFERROR(AB20/AA20,"") | AJ20: =IFERROR(AF20/AE20,"") | AK20: =IFERROR(AE20/AD20,"") | AL20: =IFERROR(X20/V20,"") | AM20: =IFERROR(W20/V20,"") | AN20: =IFERROR(AA20/$H$5,"") -> 0 | AO20: =IFERROR(AD20/$G$5,"") -> 0 | AP20: =IFERROR(V20/$F$5,"") -> 0 | AQ20: =IFERROR(AA20/U20,"") -> 0 | AR20: =IFERROR(AD20/U20,"") -> 0 | AS20: =IFERROR(AD20-L20,"") -> 0 | AT20: =IFERROR(AA20-H20,"") -> 0 | AU20: =AF20*Settings!$B$7+AG20*Settings!$B$8+AE20*Settings!$B$9+AB20*Settings!$B$10+AC20*Settings!$B$11+X20*Settings!$B$12+Y20*Settings!$B$13+Z20*Settings!$B$14 -> 0
A21: RB | B21: Other RBs | U21: 17 | AI21: =IFERROR(AB21/AA21,"") | AJ21: =IFERROR(AF21/AE21,"") | AK21: =IFERROR(AE21/AD21,"") | AL21: =IFERROR(X21/V21,"") | AM21: =IFERROR(W21/V21,"") | AN21: =IFERROR(AA21/$H$5,"") -> 0 | AO21: =IFERROR(AD21/$G$5,"") -> 0 | AP21: =IFERROR(V21/$F$5,"") -> 0 | AQ21: =IFERROR(AA21/U21,"") -> 0 | AR21: =IFERROR(AD21/U21,"") -> 0 | AS21: =IFERROR(AD21-L21,"") -> 0 | AT21: =IFERROR(AA21-H21,"") -> 0 | AU21: =AF21*Settings!$B$7+AG21*Settings!$B$8+AE21*Settings!$B$9+AB21*Settings!$B$10+AC21*Settings!$B$11+X21*Settings!$B$12+Y21*Settings!$B$13+Z21*Settings!$B$14 -> 0
A22: WR | B22: Rome Odunze | C22: 1 | D22: 24 | E22: ACT | G22: 3 | K22: 101 | L22: 90 | M22: 661 | N22: CHI | O22: 12 | P22: 5 | Q22: 14.23 | R22: 0.513 | U22: 17 | V22: 0 | W22: 0 | X22: 0 | Y22: 0 | Z22: 0 | AA22: 1 | AB22: 3 | AC22: 0 | AD22: 118 | AE22: 61 | AF22: 915 | AG22: 8 | AH22: kept | AI22: =IFERROR(AB22/AA22,"") -> 3 | AJ22: =IFERROR(AF22/AE22,"") -> 15 | AK22: =IFERROR(AE22/AD22,"") -> 0.51694915 | AL22: =IFERROR(X22/V22,"") | AM22: =IFERROR(W22/V22,"") | AN22: =IFERROR(AA22/$H$5,"") -> 0.0020959966 | AO22: =IFERROR(AD22/$G$5,"") -> 0.20665499 | AP22: =IFERROR(V22/$F$5,"") -> 0 | AQ22: =IFERROR(AA22/U22,"") -> 0.058823529 | AR22: =IFERROR(AD22/U22,"") -> 6.9411765 | AS22: =IFERROR(AD22-L22,"") -> 28 | AT22: =IFERROR(AA22-H22,"") -> 1 | AU22: =AF22*Settings!$B$7+AG22*Settings!$B$8+AE22*Settings!$B$9+AB22*Settings!$B$10+AC22*Settings!$B$11+X22*Settings!$B$12+Y22*Settings!$B$13+Z22*Settings!$B$14 -> 170.3
A23: WR | B23: Luther Burden | C23: 2 | D23: 22 | E23: ACT | H23: 6 | I23: 37 | L23: 60 | M23: 652 | N23: CHI | O23: 15 | P23: 6.17 | Q23: 13.87 | R23: 0.783 | U23: 17 | V23: 0 | W23: 0 | X23: 0 | Y23: 0 | Z23: 0 | AA23: 9 | AB23: 47 | AC23: 0 | AD23: 109 | AE23: 74 | AF23: 968 | AG23: 6 | AH23: kept | AI23: =IFERROR(AB23/AA23,"") -> 5.2222222 | AJ23: =IFERROR(AF23/AE23,"") -> 13.081081 | AK23: =IFERROR(AE23/AD23,"") -> 0.67889908 | AL23: =IFERROR(X23/V23,"") | AM23: =IFERROR(W23/V23,"") | AN23: =IFERROR(AA23/$H$5,"") -> 0.01886397 | AO23: =IFERROR(AD23/$G$5,"") -> 0.19089317 | AP23: =IFERROR(V23/$F$5,"") -> 0 | AQ23: =IFERROR(AA23/U23,"") -> 0.52941176 | AR23: =IFERROR(AD23/U23,"") -> 6.4117647 | AS23: =IFERROR(AD23-L23,"") -> 49 | AT23: =IFERROR(AA23-H23,"") -> 3 | AU23: =AF23*Settings!$B$7+AG23*Settings!$B$8+AE23*Settings!$B$9+AB23*Settings!$B$10+AC23*Settings!$B$11+X23*Settings!$B$12+Y23*Settings!$B$13+Z23*Settings!$B$14 -> 174.5
A24: WR | B24: Jahdae Walker | C24: 3 | D24: 24 | E24: ACT | L24: 10 | M24: 87 | N24: CHI | O24: 9 | Q24: 14.5 | R24: 0.6 | U24: 17 | V24: 0 | W24: 0 | X24: 0 | Y24: 0 | Z24: 0 | AA24: 0 | AB24: 1 | AC24: 0 | AD24: 19 | AE24: 12 | AF24: 156 | AG24: 2 | AH24: kept | AI24: =IFERROR(AB24/AA24,"") | AJ24: =IFERROR(AF24/AE24,"") -> 13 | AK24: =IFERROR(AE24/AD24,"") -> 0.63157895 | AL24: =IFERROR(X24/V24,"") | AM24: =IFERROR(W24/V24,"") | AN24: =IFERROR(AA24/$H$5,"") -> 0 | AO24: =IFERROR(AD24/$G$5,"") -> 0.033274956 | AP24: =IFERROR(V24/$F$5,"") -> 0 | AQ24: =IFERROR(AA24/U24,"") -> 0 | AR24: =IFERROR(AD24/U24,"") -> 1.1176471 | AS24: =IFERROR(AD24-L24,"") -> 9 | AT24: =IFERROR(AA24-H24,"") -> 0 | AU24: =AF24*Settings!$B$7+AG24*Settings!$B$8+AE24*Settings!$B$9+AB24*Settings!$B$10+AC24*Settings!$B$11+X24*Settings!$B$12+Y24*Settings!$B$13+Z24*Settings!$B$14 -> 33.7
A25: WR | B25: Kalif Raymond | C25: 4 | D25: 31 | E25: ACT | F25: 7 | G25: 2 | H25: 2 | I25: 19 | J25: 44 | K25: 22 | L25: 30 | M25: 289 | N25: DET | O25: 15 | P25: 8.55 | Q25: 13.07 | R25: 0.792 | U25: 17 | V25: 0 | W25: 0 | X25: 0 | Y25: 0 | Z25: 0 | AA25: 2 | AB25: 14 | AC25: 0 | AD25: 25 | AE25: 20 | AF25: 228 | AG25: 1 | AH25: kept | AI25: =IFERROR(AB25/AA25,"") -> 7 | AJ25: =IFERROR(AF25/AE25,"") -> 11.4 | AK25: =IFERROR(AE25/AD25,"") -> 0.8 | AL25: =IFERROR(X25/V25,"") | AM25: =IFERROR(W25/V25,"") | AN25: =IFERROR(AA25/$H$5,"") -> 0.0041919933 | AO25: =IFERROR(AD25/$G$5,"") -> 0.043782837 | AP25: =IFERROR(V25/$F$5,"") -> 0 | AQ25: =IFERROR(AA25/U25,"") -> 0.11764706 | AR25: =IFERROR(AD25/U25,"") -> 1.4705882 | AS25: =IFERROR(AD25-L25,"") -> -5 | AT25: =IFERROR(AA25-H25,"") -> 0 | AU25: =AF25*Settings!$B$7+AG25*Settings!$B$8+AE25*Settings!$B$9+AB25*Settings!$B$10+AC25*Settings!$B$11+X25*Settings!$B$12+Y25*Settings!$B$13+Z25*Settings!$B$14 -> 40.2
A26: WR | B26: Maurice Alexander | C26: 5 | D26: 29 | E26: ACT | U26: 17 | AI26: =IFERROR(AB26/AA26,"") | AJ26: =IFERROR(AF26/AE26,"") | AK26: =IFERROR(AE26/AD26,"") | AL26: =IFERROR(X26/V26,"") | AM26: =IFERROR(W26/V26,"") | AN26: =IFERROR(AA26/$H$5,"") -> 0 | AO26: =IFERROR(AD26/$G$5,"") -> 0 | AP26: =IFERROR(V26/$F$5,"") -> 0 | AQ26: =IFERROR(AA26/U26,"") -> 0 | AR26: =IFERROR(AD26/U26,"") -> 0 | AS26: =IFERROR(AD26-L26,"") -> 0 | AT26: =IFERROR(AA26-H26,"") -> 0 | AU26: =AF26*Settings!$B$7+AG26*Settings!$B$8+AE26*Settings!$B$9+AB26*Settings!$B$10+AC26*Settings!$B$11+X26*Settings!$B$12+Y26*Settings!$B$13+Z26*Settings!$B$14 -> 0
A27: WR | B27: Zavion Thomas | C27: 6 | D27: 22 | E27: ACT | U27: 17 | AA27: 2 | AB27: 17 | AC27: 0 | AD27: 28 | AE27: 17 | AF27: 205 | AG27: 1 | AH27: kept | AI27: =IFERROR(AB27/AA27,"") -> 8.5 | AJ27: =IFERROR(AF27/AE27,"") -> 12.058824 | AK27: =IFERROR(AE27/AD27,"") -> 0.60714286 | AL27: =IFERROR(X27/V27,"") | AM27: =IFERROR(W27/V27,"") | AN27: =IFERROR(AA27/$H$5,"") -> 0.0041919933 | AO27: =IFERROR(AD27/$G$5,"") -> 0.049036778 | AP27: =IFERROR(V27/$F$5,"") -> 0 | AQ27: =IFERROR(AA27/U27,"") -> 0.11764706 | AR27: =IFERROR(AD27/U27,"") -> 1.6470588 | AS27: =IFERROR(AD27-L27,"") -> 28 | AT27: =IFERROR(AA27-H27,"") -> 2 | AU27: =AF27*Settings!$B$7+AG27*Settings!$B$8+AE27*Settings!$B$9+AB27*Settings!$B$10+AC27*Settings!$B$11+X27*Settings!$B$12+Y27*Settings!$B$13+Z27*Settings!$B$14 -> 36.7
A28: WR | B28: JP Richardson | C28: 7 | D28: 24 | E28: ACT | U28: 17 | AA28: 0 | AB28: 0 | AC28: 0 | AD28: 6 | AE28: 7 | AF28: 53 | AG28: 0 | AH28: kept | AI28: =IFERROR(AB28/AA28,"") | AJ28: =IFERROR(AF28/AE28,"") -> 7.5714286 | AK28: =IFERROR(AE28/AD28,"") -> 1.1666667 | AL28: =IFERROR(X28/V28,"") | AM28: =IFERROR(W28/V28,"") | AN28: =IFERROR(AA28/$H$5,"") -> 0 | AO28: =IFERROR(AD28/$G$5,"") -> 0.010507881 | AP28: =IFERROR(V28/$F$5,"") -> 0 | AQ28: =IFERROR(AA28/U28,"") -> 0 | AR28: =IFERROR(AD28/U28,"") -> 0.35294118 | AS28: =IFERROR(AD28-L28,"") -> 6 | AT28: =IFERROR(AA28-H28,"") -> 0 | AU28: =AF28*Settings!$B$7+AG28*Settings!$B$8+AE28*Settings!$B$9+AB28*Settings!$B$10+AC28*Settings!$B$11+X28*Settings!$B$12+Y28*Settings!$B$13+Z28*Settings!$B$14 -> 8.8
A29: WR | B29: Qadir Ismail | C29: 8 | D29: 26 | E29: ACT | U29: 17 | AI29: =IFERROR(AB29/AA29,"") | AJ29: =IFERROR(AF29/AE29,"") | AK29: =IFERROR(AE29/AD29,"") | AL29: =IFERROR(X29/V29,"") | AM29: =IFERROR(W29/V29,"") | AN29: =IFERROR(AA29/$H$5,"") -> 0 | AO29: =IFERROR(AD29/$G$5,"") -> 0 | AP29: =IFERROR(V29/$F$5,"") -> 0 | AQ29: =IFERROR(AA29/U29,"") -> 0 | AR29: =IFERROR(AD29/U29,"") -> 0 | AS29: =IFERROR(AD29-L29,"") -> 0 | AT29: =IFERROR(AA29-H29,"") -> 0 | AU29: =AF29*Settings!$B$7+AG29*Settings!$B$8+AE29*Settings!$B$9+AB29*Settings!$B$10+AC29*Settings!$B$11+X29*Settings!$B$12+Y29*Settings!$B$13+Z29*Settings!$B$14 -> 0
A30: WR | B30: Other WRs | U30: 17 | AI30: =IFERROR(AB30/AA30,"") | AJ30: =IFERROR(AF30/AE30,"") | AK30: =IFERROR(AE30/AD30,"") | AL30: =IFERROR(X30/V30,"") | AM30: =IFERROR(W30/V30,"") | AN30: =IFERROR(AA30/$H$5,"") -> 0 | AO30: =IFERROR(AD30/$G$5,"") -> 0 | AP30: =IFERROR(V30/$F$5,"") -> 0 | AQ30: =IFERROR(AA30/U30,"") -> 0 | AR30: =IFERROR(AD30/U30,"") -> 0 | AS30: =IFERROR(AD30-L30,"") -> 0 | AT30: =IFERROR(AA30-H30,"") -> 0 | AU30: =AF30*Settings!$B$7+AG30*Settings!$B$8+AE30*Settings!$B$9+AB30*Settings!$B$10+AC30*Settings!$B$11+X30*Settings!$B$12+Y30*Settings!$B$13+Z30*Settings!$B$14 -> 0
A31: TE | B31: Colston Loveland | C31: 1 | D31: 22 | E31: ACT | H31: 1 | I31: -2 | L31: 82 | M31: 713 | N31: CHI | O31: 16 | P31: -2 | Q31: 12.29 | R31: 0.707 | U31: 17 | V31: 0 | W31: 0 | X31: 0 | Y31: 0 | Z31: 0 | AA31: 1 | AB31: 1 | AC31: 0 | AD31: 115 | AE31: 77 | AF31: 915 | AG31: 7 | AH31: kept | AI31: =IFERROR(AB31/AA31,"") -> 1 | AJ31: =IFERROR(AF31/AE31,"") -> 11.883117 | AK31: =IFERROR(AE31/AD31,"") -> 0.66956522 | AL31: =IFERROR(X31/V31,"") | AM31: =IFERROR(W31/V31,"") | AN31: =IFERROR(AA31/$H$5,"") -> 0.0020959966 | AO31: =IFERROR(AD31/$G$5,"") -> 0.20140105 | AP31: =IFERROR(V31/$F$5,"") -> 0 | AQ31: =IFERROR(AA31/U31,"") -> 0.058823529 | AR31: =IFERROR(AD31/U31,"") -> 6.7647059 | AS31: =IFERROR(AD31-L31,"") -> 33 | AT31: =IFERROR(AA31-H31,"") -> 0 | AU31: =AF31*Settings!$B$7+AG31*Settings!$B$8+AE31*Settings!$B$9+AB31*Settings!$B$10+AC31*Settings!$B$11+X31*Settings!$B$12+Y31*Settings!$B$13+Z31*Settings!$B$14 -> 172.1
A32: TE | B32: Cole Kmet | C32: 2 | D32: 27 | E32: ACT | F32: 3 | J32: 90 | K32: 55 | L32: 48 | M32: 347 | N32: CHI | O32: 16 | P32: 0.67 | Q32: 10.27 | R32: 0.777 | U32: 17 | V32: 1 | W32: 0 | X32: 0 | Y32: 0 | Z32: 0 | AA32: 0 | AB32: 0 | AC32: 0 | AD32: 35 | AE32: 25 | AF32: 269 | AG32: 2 | AH32: kept | AI32: =IFERROR(AB32/AA32,"") | AJ32: =IFERROR(AF32/AE32,"") -> 10.76 | AK32: =IFERROR(AE32/AD32,"") -> 0.71428571 | AL32: =IFERROR(X32/V32,"") -> 0 | AM32: =IFERROR(W32/V32,"") -> 0 | AN32: =IFERROR(AA32/$H$5,"") -> 0 | AO32: =IFERROR(AD32/$G$5,"") -> 0.061295972 | AP32: =IFERROR(V32/$F$5,"") -> 0.0016694491 | AQ32: =IFERROR(AA32/U32,"") -> 0 | AR32: =IFERROR(AD32/U32,"") -> 2.0588235 | AS32: =IFERROR(AD32-L32,"") -> -13 | AT32: =IFERROR(AA32-H32,"") -> 0 | AU32: =AF32*Settings!$B$7+AG32*Settings!$B$8+AE32*Settings!$B$9+AB32*Settings!$B$10+AC32*Settings!$B$11+X32*Settings!$B$12+Y32*Settings!$B$13+Z32*Settings!$B$14 -> 51.4
A33: TE | B33: Stephen Carlson | C33: 3 | D33: 29 | E33: ACT | U33: 17 | AI33: =IFERROR(AB33/AA33,"") | AJ33: =IFERROR(AF33/AE33,"") | AK33: =IFERROR(AE33/AD33,"") | AL33: =IFERROR(X33/V33,"") | AM33: =IFERROR(W33/V33,"") | AN33: =IFERROR(AA33/$H$5,"") -> 0 | AO33: =IFERROR(AD33/$G$5,"") -> 0 | AP33: =IFERROR(V33/$F$5,"") -> 0 | AQ33: =IFERROR(AA33/U33,"") -> 0 | AR33: =IFERROR(AD33/U33,"") -> 0 | AS33: =IFERROR(AD33-L33,"") -> 0 | AT33: =IFERROR(AA33-H33,"") -> 0 | AU33: =AF33*Settings!$B$7+AG33*Settings!$B$8+AE33*Settings!$B$9+AB33*Settings!$B$10+AC33*Settings!$B$11+X33*Settings!$B$12+Y33*Settings!$B$13+Z33*Settings!$B$14 -> 0
A34: TE | B34: Sam Roush | C34: 4 | D34: 22 | E34: ACT | U34: 17 | AA34: 0 | AB34: 0 | AC34: 0 | AD34: 12 | AE34: 9 | AF34: 89 | AG34: 1 | AH34: kept | AI34: =IFERROR(AB34/AA34,"") | AJ34: =IFERROR(AF34/AE34,"") -> 9.8888889 | AK34: =IFERROR(AE34/AD34,"") -> 0.75 | AL34: =IFERROR(X34/V34,"") | AM34: =IFERROR(W34/V34,"") | AN34: =IFERROR(AA34/$H$5,"") -> 0 | AO34: =IFERROR(AD34/$G$5,"") -> 0.021015762 | AP34: =IFERROR(V34/$F$5,"") -> 0 | AQ34: =IFERROR(AA34/U34,"") -> 0 | AR34: =IFERROR(AD34/U34,"") -> 0.70588235 | AS34: =IFERROR(AD34-L34,"") -> 12 | AT34: =IFERROR(AA34-H34,"") -> 0 | AU34: =AF34*Settings!$B$7+AG34*Settings!$B$8+AE34*Settings!$B$9+AB34*Settings!$B$10+AC34*Settings!$B$11+X34*Settings!$B$12+Y34*Settings!$B$13+Z34*Settings!$B$14 -> 19.4
A35: TE | B35: Other TEs | U35: 17 | AI35: =IFERROR(AB35/AA35,"") | AJ35: =IFERROR(AF35/AE35,"") | AK35: =IFERROR(AE35/AD35,"") | AL35: =IFERROR(X35/V35,"") | AM35: =IFERROR(W35/V35,"") | AN35: =IFERROR(AA35/$H$5,"") -> 0 | AO35: =IFERROR(AD35/$G$5,"") -> 0 | AP35: =IFERROR(V35/$F$5,"") -> 0 | AQ35: =IFERROR(AA35/U35,"") -> 0 | AR35: =IFERROR(AD35/U35,"") -> 0 | AS35: =IFERROR(AD35-L35,"") -> 0 | AT35: =IFERROR(AA35-H35,"") -> 0 | AU35: =AF35*Settings!$B$7+AG35*Settings!$B$8+AE35*Settings!$B$9+AB35*Settings!$B$10+AC35*Settings!$B$11+X35*Settings!$B$12+Y35*Settings!$B$13+Z35*Settings!$B$14 -> 0
A37: YOUR TOTAL | U37: =SUM(U11:U35) -> 425 | V37: =SUM(V11:V35) -> 573 | W37: =SUM(W11:W35) -> 348 | X37: =SUM(X11:X35) -> 4033 | Y37: =SUM(Y11:Y35) -> 28 | Z37: =SUM(Z11:Z35) -> 10 | AA37: =SUM(AA11:AA35) -> 534 | AB37: =SUM(AB11:AB35) -> 2442 | ... AG37: =SUM(AG11:AG35) -> 31
A38: TEAM TARGET | V38: =$F$5 -> 599 | X38: =$I$5 -> 3787 | Y38: =$J$5 -> 24 | Z38: =$K$5 -> 10 | AA38: =$H$5 -> 477.1 | AB38: =$L$5 -> 2132 | AC38: =$M$5 -> 16 | AD38: =$G$5 -> 571 | AF38: =$I$5 -> 3787 | AG38: =$J$5 -> 24
A39: LEFT | V39: =$F$5-V37 -> 26 | X39: =$I$5-X37 -> -246 | Y39: =$J$5-Y37 -> -4 | Z39: =$K$5-Z37 -> 0 | AA39: =$H$5-AA37 -> -56.9 | AB39: =$L$5-AB37 -> -310 | AC39: =$M$5-AC37 -> -2 | AD39: =$G$5-AD37 -> 23 | AF39: =$I$5-AF37 -> -506 | AG39: =$J$5-AG37 -> -7
B40: Red = you have allocated more than the team total. Amber = more than 3% under. These are targets, not hard caps - if you disagree, edit the team total above. | AF40: Rec Yds / Rec TD are checked against the PASSING totals

Sheet CIN
A1: CIN - 2026 projections (direct entry)
A3: TEAM TOTALS | D3: all editable - these are your targets, not hard caps
B4: Games | C4: Plays/G | D4: Plays | E4: Pass Rate | F4: Pass Att | G4: Targets | H4: Rush Att | I4: Pass Yds | J4: Pass TD | K4: Int | L4: Rush Yds | M4: Rush TD
B5: 17 | C5: 62.3 | D5: =C5*B5 -> 1059.1 | E5: 0.6189 | F5: =ROUND(D5*E5,0) -> 655 | G5: =ROUND(F5*Settings!$B$4,0) -> 625 | H5: =D5-F5 -> 404.1 | I5: 4287 | J5: 33 | K5: 14 | L5: 1691 | M5: 13
A7: VACATED | B7: 7% of targets and 2% of carries left this roster - that volume is yours to reassign.
A8: STAFF | B8: no coaching change recorded
A10: Pos | B10: Player | C10: Dep | D10: Age | E10: Status | F10: '23 Car | G10: '24 Car | H10: '25 Car | I10: '25 RuYd | J10: '23 Tgt | K10: '24 Tgt | L10: '25 Tgt | M10: '25 ReYd | N10: '25 Tm | O10: '25 G | P10: 3y Y/C | Q10: 3y Y/R | R10: 3y Ctch | S10: 3y Comp% | T10: 3y Y/A | U10: Games | V10: Pass Att | W10: Cmp | X10: Pass Yds | Y10: Pass TD | Z10: Int | AA10: Rush Att | AB10: Rush Yds | AC10: Rush TD | AD10: Targets | AE10: Rec | AF10: Rec Yds | AG10: Rec TD | AH10: Seed | AI10: Y/C | AJ10: Y/R | AK10: Catch% | AL10: Y/A | AM10: Comp% | AN10: Rush % | AO10: Tgt % | AP10: Pass % | AQ10: Car/G | AR10: Tgt/G | AS10: dTgt | AT10: dCar | AU10: Half PPR
A11: QB | B11: Joe Burrow | C11: 1 | D11: 29 | E11: ACT | F11: 19 | G11: 31 | H11: 13 | I11: 41 | N11: CIN | O11: 8 | P11: 5.24 | S11: 0.687 | T11: 7.08 | U11: 17 | V11: 587 | W11: 397 | X11: 4207 | Y11: 33 | Z11: 11 | AA11: 46 | AB11: 161 | AC11: 1 | AD11: 0 | AE11: 0 | AF11: 0 | AG11: 0 | AH11: kept | AI11: =IFERROR(AB11/AA11,"") -> 3.5 | AJ11: =IFERROR(AF11/AE11,"") | AK11: =IFERROR(AE11/AD11,"") | AL11: =IFERROR(X11/V11,"") -> 7.1669506 | AM11: =IFERROR(W11/V11,"") -> 0.67632027 | AN11: =IFERROR(AA11/$H$5,"") -> 0.11383321 | AO11: =IFERROR(AD11/$G$5,"") -> 0 | AP11: =IFERROR(V11/$F$5,"") -> 0.89618321 | AQ11: =IFERROR(AA11/U11,"") -> 2.7058824 | AR11: =IFERROR(AD11/U11,"") -> 0 | AS11: =IFERROR(AD11-L11,"") -> 0 | AT11: =IFERROR(AA11-H11,"") -> 33 | AU11: =AF11*Settings!$B$7+AG11*Settings!$B$8+AE11*Settings!$B$9+AB11*Settings!$B$10+AC11*Settings!$B$11+X11*Settings!$B$12+Y11*Settings!$B$13+Z11*Settings!$B$14 -> 300.38
A12: QB | B12: Joe Flacco | C12: 2 | D12: 41 | E12: ACT | F12: 4 | G12: 6 | H12: 5 | I12: 13 | N12: CLE | O12: 4 | P12: 2.73 | S12: 0.618 | T12: 6.85 | U12: 17 | V12: 37 | W12: 24 | X12: 260 | Y12: 2 | Z12: 1 | AA12: 2 | AB12: 5 | AC12: 0 | AD12: 0 | AE12: 0 | AF12: 0 | AG12: 0 | AH12: kept | AI12: =IFERROR(AB12/AA12,"") -> 2.5 | AJ12: =IFERROR(AF12/AE12,"") | AK12: =IFERROR(AE12/AD12,"") | AL12: =IFERROR(X12/V12,"") -> 7.027027 | AM12: =IFERROR(W12/V12,"") -> 0.64864865 | AN12: =IFERROR(AA12/$H$5,"") -> 0.00494927 | AO12: =IFERROR(AD12/$G$5,"") -> 0 | AP12: =IFERROR(V12/$F$5,"") -> 0.05648855 | AQ12: =IFERROR(AA12/U12,"") -> 0.11764706 | AR12: =IFERROR(AD12/U12,"") -> 0 | AS12: =IFERROR(AD12-L12,"") -> 0 | AT12: =IFERROR(AA12-H12,"") -> -3 | AU12: =AF12*Settings!$B$7+AG12*Settings!$B$8+AE12*Settings!$B$9+AB12*Settings!$B$10+AC12*Settings!$B$11+X12*Settings!$B$12+Y12*Settings!$B$13+Z12*Settings!$B$14 -> 16.9
A13: QB | B13: Josh Johnson | C13: 3 | D13: 40 | E13: ACT | G13: 2 | H13: 11 | I13: 55 | N13: WAS | O13: 5 | P13: 4.31 | S13: 0.632 | T13: 6.82 | U13: 17 | V13: 1 | W13: 0 | X13: 55 | Y13: 0 | Z13: 0 | AA13: 1 | AB13: 4 | AC13: 0 | AD13: 0 | AE13: 0 | AF13: 0 | AG13: 0 | AH13: kept | AI13: =IFERROR(AB13/AA13,"") -> 4 | AJ13: =IFERROR(AF13/AE13,"") | AK13: =IFERROR(AE13/AD13,"") | AL13: =IFERROR(X13/V13,"") -> 55 | AM13: =IFERROR(W13/V13,"") -> 0 | AN13: =IFERROR(AA13/$H$5,"") -> 0.002474635 | AO13: =IFERROR(AD13/$G$5,"") -> 0 | AP13: =IFERROR(V13/$F$5,"") -> 0.0015267176 | AQ13: =IFERROR(AA13/U13,"") -> 0.058823529 | AR13: =IFERROR(AD13/U13,"") -> 0 | AS13: =IFERROR(AD13-L13,"") -> 0 | AT13: =IFERROR(AA13-H13,"") -> -10 | AU13: =AF13*Settings!$B$7+AG13*Settings!$B$8+AE13*Settings!$B$9+AB13*Settings!$B$10+AC13*Settings!$B$11+X13*Settings!$B$12+Y13*Settings!$B$13+Z13*Settings!$B$14 -> 2.6
A14: QB | B14: Other QBs | U14: 17 | AI14: =IFERROR(AB14/AA14,"") | AJ14: =IFERROR(AF14/AE14,"") | AK14: =IFERROR(AE14/AD14,"") | AL14: =IFERROR(X14/V14,"") | AM14: =IFERROR(W14/V14,"") | AN14: =IFERROR(AA14/$H$5,"") -> 0 | AO14: =IFERROR(AD14/$G$5,"") -> 0 | AP14: =IFERROR(V14/$F$5,"") -> 0 | AQ14: =IFERROR(AA14/U14,"") -> 0 | AR14: =IFERROR(AD14/U14,"") -> 0 | AS14: =IFERROR(AD14-L14,"") -> 0 | AT14: =IFERROR(AA14-H14,"") -> 0 | AU14: =AF14*Settings!$B$7+AG14*Settings!$B$8+AE14*Settings!$B$9+AB14*Settings!$B$10+AC14*Settings!$B$11+X14*Settings!$B$12+Y14*Settings!$B$13+Z14*Settings!$B$14 -> 0
A15: RB | B15: Chase Brown | C15: 1 | D15: 26 | E15: ACT | F15: 44 | G15: 229 | H15: 232 | I15: 1019 | J15: 15 | K15: 65 | L15: 88 | M15: 437 | N15: CIN | O15: 17 | P15: 4.33 | Q15: 6.96 | R15: 0.815 | U15: 17 | V15: 0 | W15: 0 | X15: 0 | Y15: 0 | Z15: 0 | AA15: 226 | AB15: 983 | AC15: 7 | AD15: 79 | AE15: 62 | AF15: 425 | AG15: 4 | AH15: kept | AI15: =IFERROR(AB15/AA15,"") -> 4.3495575 | AJ15: =IFERROR(AF15/AE15,"") -> 6.8548387 | AK15: =IFERROR(AE15/AD15,"") -> 0.78481013 | AL15: =IFERROR(X15/V15,"") | AM15: =IFERROR(W15/V15,"") | AN15: =IFERROR(AA15/$H$5,"") -> 0.55926751 | AO15: =IFERROR(AD15/$G$5,"") -> 0.1264 | AP15: =IFERROR(V15/$F$5,"") -> 0 | AQ15: =IFERROR(AA15/U15,"") -> 13.294118 | AR15: =IFERROR(AD15/U15,"") -> 4.6470588 | AS15: =IFERROR(AD15-L15,"") -> -9 | AT15: =IFERROR(AA15-H15,"") -> -6 | AU15: =AF15*Settings!$B$7+AG15*Settings!$B$8+AE15*Settings!$B$9+AB15*Settings!$B$10+AC15*Settings!$B$11+X15*Settings!$B$12+Y15*Settings!$B$13+Z15*Settings!$B$14 -> 237.8
A16: RB | B16: Samaje Perine | C16: 2 | D16: 30 | E16: ACT | F16: 53 | G16: 20 | H16: 84 | I16: 382 | J16: 56 | K16: 35 | L16: 21 | M16: 87 | N16: CIN | O16: 15 | P16: 4.54 | Q16: 9.09 | R16: 0.848 | U16: 17 | V16: 0 | W16: 0 | X16: 0 | Y16: 0 | Z16: 0 | AA16: 79 | AB16: 349 | AC16: 3 | AD16: 21 | AE16: 18 | AF16: 124 | AG16: 1 | AH16: kept | AI16: =IFERROR(AB16/AA16,"") -> 4.4177215 | AJ16: =IFERROR(AF16/AE16,"") -> 6.8888889 | AK16: =IFERROR(AE16/AD16,"") -> 0.85714286 | AL16: =IFERROR(X16/V16,"") | AM16: =IFERROR(W16/V16,"") | AN16: =IFERROR(AA16/$H$5,"") -> 0.19549616 | AO16: =IFERROR(AD16/$G$5,"") -> 0.0336 | AP16: =IFERROR(V16/$F$5,"") -> 0 | AQ16: =IFERROR(AA16/U16,"") -> 4.6470588 | AR16: =IFERROR(AD16/U16,"") -> 1.2352941 | AS16: =IFERROR(AD16-L16,"") -> 0 | AT16: =IFERROR(AA16-H16,"") -> -5 | AU16: =AF16*Settings!$B$7+AG16*Settings!$B$8+AE16*Settings!$B$9+AB16*Settings!$B$10+AC16*Settings!$B$11+X16*Settings!$B$12+Y16*Settings!$B$13+Z16*Settings!$B$14 -> 80.3
A17: RB | B17: Tahj Brooks | C17: 3 | D17: 24 | E17: ACT | H17: 16 | I17: 45 | L17: 2 | M17: 9 | N17: CIN | O17: 16 | P17: 2.81 | Q17: 9 | R17: 0.5 | U17: 17 | V17: 0 | W17: 0 | X17: 0 | Y17: 0 | Z17: 0 | AA17: 29 | AB17: 108 | AC17: 1 | AD17: 4 | AE17: 3 | AF17: 22 | AG17: 0 | AH17: kept | AI17: =IFERROR(AB17/AA17,"") -> 3.7241379 | AJ17: =IFERROR(AF17/AE17,"") -> 7.3333333 | AK17: =IFERROR(AE17/AD17,"") -> 0.75 | AL17: =IFERROR(X17/V17,"") | AM17: =IFERROR(W17/V17,"") | AN17: =IFERROR(AA17/$H$5,"") -> 0.071764415 | AO17: =IFERROR(AD17/$G$5,"") -> 0.0064 | AP17: =IFERROR(V17/$F$5,"") -> 0 | AQ17: =IFERROR(AA17/U17,"") -> 1.7058824 | AR17: =IFERROR(AD17/U17,"") -> 0.23529412 | AS17: =IFERROR(AD17-L17,"") -> 2 | AT17: =IFERROR(AA17-H17,"") -> 13 | AU17: =AF17*Settings!$B$7+AG17*Settings!$B$8+AE17*Settings!$B$9+AB17*Settings!$B$10+AC17*Settings!$B$11+X17*Settings!$B$12+Y17*Settings!$B$13+Z17*Settings!$B$14 -> 20.5
A18: RB | B18: Jamal Haynes | C18: 4 | D18: 23 | E18: ACT | U18: 17 | AA18: 15 | AB18: 58 | AC18: 0 | AD18: 3 | AE18: 2 | AF18: 15 | AG18: 0 | AH18: kept | AI18: =IFERROR(AB18/AA18,"") -> 3.8666667 | AJ18: =IFERROR(AF18/AE18,"") -> 7.5 | AK18: =IFERROR(AE18/AD18,"") -> 0.66666667 | AL18: =IFERROR(X18/V18,"") | AM18: =IFERROR(W18/V18,"") | AN18: =IFERROR(AA18/$H$5,"") -> 0.037119525 | AO18: =IFERROR(AD18/$G$5,"") -> 0.0048 | AP18: =IFERROR(V18/$F$5,"") -> 0 | AQ18: =IFERROR(AA18/U18,"") -> 0.88235294 | AR18: =IFERROR(AD18/U18,"") -> 0.17647059 | AS18: =IFERROR(AD18-L18,"") -> 3 | AT18: =IFERROR(AA18-H18,"") -> 15 | AU18: =AF18*Settings!$B$7+AG18*Settings!$B$8+AE18*Settings!$B$9+AB18*Settings!$B$10+AC18*Settings!$B$11+X18*Settings!$B$12+Y18*Settings!$B$13+Z18*Settings!$B$14 -> 8.3
A19: RB | B19: Kendall Milton | C19: 5 | D19: 24 | E19: ACT | H19: 2 | I19: 2 | N19: CIN | O19: 1 | P19: 1 | U19: 17 | V19: 0 | W19: 0 | X19: 0 | Y19: 0 | Z19: 0 | AA19: 2 | AB19: 2 | AC19: 0 | AD19: 0 | AE19: 0 | AF19: 0 | AG19: 0 | AH19: kept | AI19: =IFERROR(AB19/AA19,"") -> 1 | AJ19: =IFERROR(AF19/AE19,"") | AK19: =IFERROR(AE19/AD19,"") | AL19: =IFERROR(X19/V19,"") | AM19: =IFERROR(W19/V19,"") | AN19: =IFERROR(AA19/$H$5,"") -> 0.00494927 | AO19: =IFERROR(AD19/$G$5,"") -> 0 | AP19: =IFERROR(V19/$F$5,"") -> 0 | AQ19: =IFERROR(AA19/U19,"") -> 0.11764706 | AR19: =IFERROR(AD19/U19,"") -> 0 | AS19: =IFERROR(AD19-L19,"") -> 0 | AT19: =IFERROR(AA19-H19,"") -> 0 | AU19: =AF19*Settings!$B$7+AG19*Settings!$B$8+AE19*Settings!$B$9+AB19*Settings!$B$10+AC19*Settings!$B$11+X19*Settings!$B$12+Y19*Settings!$B$13+Z19*Settings!$B$14 -> 0.2
A20: RB | B20: Gary Brightwell | C20: 6 | D20: 28 | E20: ACT | F20: 9 | J20: 7 | P20: 2.11 | Q20: 9.4 | R20: 0.714 | U20: 17 | AI20: =IFERROR(AB20/AA20,"") | AJ20: =IFERROR(AF20/AE20,"") | AK20: =IFERROR(AE20/AD20,"") | AL20: =IFERROR(X20/V20,"") | AM20: =IFERROR(W20/V20,"") | AN20: =IFERROR(AA20/$H$5,"") -> 0 | AO20: =IFERROR(AD20/$G$5,"") -> 0 | AP20: =IFERROR(V20/$F$5,"") -> 0 | AQ20: =IFERROR(AA20/U20,"") -> 0 | AR20: =IFERROR(AD20/U20,"") -> 0 | AS20: =IFERROR(AD20-L20,"") -> 0 | AT20: =IFERROR(AA20-H20,"") -> 0 | AU20: =AF20*Settings!$B$7+AG20*Settings!$B$8+AE20*Settings!$B$9+AB20*Settings!$B$10+AC20*Settings!$B$11+X20*Settings!$B$12+Y20*Settings!$B$13+Z20*Settings!$B$14 -> 0
A21: RB | B21: Other RBs | U21: 17 | AI21: =IFERROR(AB21/AA21,"") | AJ21: =IFERROR(AF21/AE21,"") | AK21: =IFERROR(AE21/AD21,"") | AL21: =IFERROR(X21/V21,"") | AM21: =IFERROR(W21/V21,"") | AN21: =IFERROR(AA21/$H$5,"") -> 0 | AO21: =IFERROR(AD21/$G$5,"") -> 0 | AP21: =IFERROR(V21/$F$5,"") -> 0 | AQ21: =IFERROR(AA21/U21,"") -> 0 | AR21: =IFERROR(AD21/U21,"") -> 0 | AS21: =IFERROR(AD21-L21,"") -> 0 | AT21: =IFERROR(AA21-H21,"") -> 0 | AU21: =AF21*Settings!$B$7+AG21*Settings!$B$8+AE21*Settings!$B$9+AB21*Settings!$B$10+AC21*Settings!$B$11+X21*Settings!$B$12+Y21*Settings!$B$13+Z21*Settings!$B$14 -> 0
A22: WR | B22: Ja'Marr Chase | C22: 1 | D22: 26 | E22: ACT | F22: 3 | G22: 3 | H22: 3 | I22: 14 | J22: 145 | K22: 175 | L22: 185 | M22: 1412 | N22: CIN | O22: 16 | P22: 4.44 | Q22: 12.32 | R22: 0.697 | S22: 1 | U22: 17 | V22: 0 | W22: 0 | X22: 0 | Y22: 0 | Z22: 0 | AA22: 3 | AB22: 17 | AC22: 0 | AD22: 174 | AE22: 120 | AF22: 1476 | AG22: 11 | AH22: kept | AI22: =IFERROR(AB22/AA22,"") -> 5.6666667 | AJ22: =IFERROR(AF22/AE22,"") -> 12.3 | AK22: =IFERROR(AE22/AD22,"") -> 0.68965517 | AL22: =IFERROR(X22/V22,"") | AM22: =IFERROR(W22/V22,"") | AN22: =IFERROR(AA22/$H$5,"") -> 0.007423905 | AO22: =IFERROR(AD22/$G$5,"") -> 0.2784 | AP22: =IFERROR(V22/$F$5,"") -> 0 | AQ22: =IFERROR(AA22/U22,"") -> 0.17647059 | AR22: =IFERROR(AD22/U22,"") -> 10.235294 | AS22: =IFERROR(AD22-L22,"") -> -11 | AT22: =IFERROR(AA22-H22,"") -> 0 | AU22: =AF22*Settings!$B$7+AG22*Settings!$B$8+AE22*Settings!$B$9+AB22*Settings!$B$10+AC22*Settings!$B$11+X22*Settings!$B$12+Y22*Settings!$B$13+Z22*Settings!$B$14 -> 275.3
A23: WR | B23: Tee Higgins | C23: 2 | D23: 27 | E23: ACT | J23: 76 | K23: 109 | L23: 98 | M23: 846 | N23: CIN | O23: 15 | Q23: 13.87 | R23: 0.615 | U23: 17 | V23: 0 | W23: 0 | X23: 0 | Y23: 0 | Z23: 0 | AA23: 0 | AB23: 1 | AC23: 0 | AD23: 113 | AE23: 72 | AF23: 985 | AG23: 9 | AH23: kept | AI23: =IFERROR(AB23/AA23,"") | AJ23: =IFERROR(AF23/AE23,"") -> 13.680556 | AK23: =IFERROR(AE23/AD23,"") -> 0.63716814 | AL23: =IFERROR(X23/V23,"") | AM23: =IFERROR(W23/V23,"") | AN23: =IFERROR(AA23/$H$5,"") -> 0 | AO23: =IFERROR(AD23/$G$5,"") -> 0.1808 | AP23: =IFERROR(V23/$F$5,"") -> 0 | AQ23: =IFERROR(AA23/U23,"") -> 0 | AR23: =IFERROR(AD23/U23,"") -> 6.6470588 | AS23: =IFERROR(AD23-L23,"") -> 15 | AT23: =IFERROR(AA23-H23,"") -> 0 | AU23: =AF23*Settings!$B$7+AG23*Settings!$B$8+AE23*Settings!$B$9+AB23*Settings!$B$10+AC23*Settings!$B$11+X23*Settings!$B$12+Y23*Settings!$B$13+Z23*Settings!$B$14 -> 188.6
A24: WR | B24: Andrei Iosivas | C24: 3 | D24: 26 | E24: ACT | H24: 3 | I24: 14 | J24: 25 | K24: 61 | L24: 58 | M24: 435 | N24: CIN | O24: 17 | P24: 4.67 | Q24: 12.26 | R24: 0.583 | U24: 17 | V24: 0 | W24: 0 | X24: 0 | Y24: 0 | Z24: 0 | AA24: 2 | AB24: 9 | AC24: 0 | AD24: 51 | AE24: 31 | AF24: 379 | AG24: 3 | AH24: kept | AI24: =IFERROR(AB24/AA24,"") -> 4.5 | AJ24: =IFERROR(AF24/AE24,"") -> 12.225806 | AK24: =IFERROR(AE24/AD24,"") -> 0.60784314 | AL24: =IFERROR(X24/V24,"") | AM24: =IFERROR(W24/V24,"") | AN24: =IFERROR(AA24/$H$5,"") -> 0.00494927 | AO24: =IFERROR(AD24/$G$5,"") -> 0.0816 | AP24: =IFERROR(V24/$F$5,"") -> 0 | AQ24: =IFERROR(AA24/U24,"") -> 0.11764706 | AR24: =IFERROR(AD24/U24,"") -> 3 | AS24: =IFERROR(AD24-L24,"") -> -7 | AT24: =IFERROR(AA24-H24,"") -> -1 | AU24: =AF24*Settings!$B$7+AG24*Settings!$B$8+AE24*Settings!$B$9+AB24*Settings!$B$10+AC24*Settings!$B$11+X24*Settings!$B$12+Y24*Settings!$B$13+Z24*Settings!$B$14 -> 72.3
A25: WR | B25: Mitch Tinsley | C25: 4 | D25: 26 | E25: ACT | L25: 24 | M25: 116 | N25: CIN | O25: 17 | Q25: 14.5 | R25: 0.333 | U25: 17 | V25: 0 | W25: 0 | X25: 0 | Y25: 0 | Z25: 0 | AA25: 0 | AB25: 0 | AC25: 0 | AD25: 15 | AE25: 10 | AF25: 132 | AG25: 1 | AH25: kept | AI25: =IFERROR(AB25/AA25,"") | AJ25: =IFERROR(AF25/AE25,"") -> 13.2 | AK25: =IFERROR(AE25/AD25,"") -> 0.66666667 | AL25: =IFERROR(X25/V25,"") | AM25: =IFERROR(W25/V25,"") | AN25: =IFERROR(AA25/$H$5,"") -> 0 | AO25: =IFERROR(AD25/$G$5,"") -> 0.024 | AP25: =IFERROR(V25/$F$5,"") -> 0 | AQ25: =IFERROR(AA25/U25,"") -> 0 | AR25: =IFERROR(AD25/U25,"") -> 0.88235294 | AS25: =IFERROR(AD25-L25,"") -> -9 | AT25: =IFERROR(AA25-H25,"") -> 0 | AU25: =AF25*Settings!$B$7+AG25*Settings!$B$8+AE25*Settings!$B$9+AB25*Settings!$B$10+AC25*Settings!$B$11+X25*Settings!$B$12+Y25*Settings!$B$13+Z25*Settings!$B$14 -> 24.2
A26: WR | B26: Colbie Young | C26: 5 | D26: 24 | E26: ACT | U26: 17 | AA26: 0 | AB26: 0 | AC26: 0 | AD26: 15 | AE26: 10 | AF26: 119 | AG26: 1 | AH26: kept | AI26: =IFERROR(AB26/AA26,"") | AJ26: =IFERROR(AF26/AE26,"") -> 11.9 | AK26: =IFERROR(AE26/AD26,"") -> 0.66666667 | AL26: =IFERROR(X26/V26,"") | AM26: =IFERROR(W26/V26,"") | AN26: =IFERROR(AA26/$H$5,"") -> 0 | AO26: =IFERROR(AD26/$G$5,"") -> 0.024 | AP26: =IFERROR(V26/$F$5,"") -> 0 | AQ26: =IFERROR(AA26/U26,"") -> 0 | AR26: =IFERROR(AD26/U26,"") -> 0.88235294 | AS26: =IFERROR(AD26-L26,"") -> 15 | AT26: =IFERROR(AA26-H26,"") -> 0 | AU26: =AF26*Settings!$B$7+AG26*Settings!$B$8+AE26*Settings!$B$9+AB26*Settings!$B$10+AC26*Settings!$B$11+X26*Settings!$B$12+Y26*Settings!$B$13+Z26*Settings!$B$14 -> 22.9
A27: WR | B27: Noah Thomas | C27: 6 | D27: 22 | E27: ACT | U27: 17 | AA27: 0 | AB27: 0 | AC27: 0 | AD27: 4 | AE27: 3 | AF27: 36 | AG27: 0 | AH27: kept | AI27: =IFERROR(AB27/AA27,"") | AJ27: =IFERROR(AF27/AE27,"") -> 12 | AK27: =IFERROR(AE27/AD27,"") -> 0.75 | AL27: =IFERROR(X27/V27,"") | AM27: =IFERROR(W27/V27,"") | AN27: =IFERROR(AA27/$H$5,"") -> 0 | AO27: =IFERROR(AD27/$G$5,"") -> 0.0064 | AP27: =IFERROR(V27/$F$5,"") -> 0 | AQ27: =IFERROR(AA27/U27,"") -> 0 | AR27: =IFERROR(AD27/U27,"") -> 0.23529412 | AS27: =IFERROR(AD27-L27,"") -> 4 | AT27: =IFERROR(AA27-H27,"") -> 0 | AU27: =AF27*Settings!$B$7+AG27*Settings!$B$8+AE27*Settings!$B$9+AB27*Settings!$B$10+AC27*Settings!$B$11+X27*Settings!$B$12+Y27*Settings!$B$13+Z27*Settings!$B$14 -> 5.1
A28: WR | B28: Kendric Pryor | C28: 7 | D28: 28 | E28: ACT | K28: 1 | Q28: 9 | R28: 1 | U28: 17 | AI28: =IFERROR(AB28/AA28,"") | AJ28: =IFERROR(AF28/AE28,"") | AK28: =IFERROR(AE28/AD28,"") | AL28: =IFERROR(X28/V28,"") | AM28: =IFERROR(W28/V28,"") | AN28: =IFERROR(AA28/$H$5,"") -> 0 | AO28: =IFERROR(AD28/$G$5,"") -> 0 | AP28: =IFERROR(V28/$F$5,"") -> 0 | AQ28: =IFERROR(AA28/U28,"") -> 0 | AR28: =IFERROR(AD28/U28,"") -> 0 | AS28: =IFERROR(AD28-L28,"") -> 0 | AT28: =IFERROR(AA28-H28,"") -> 0 | AU28: =AF28*Settings!$B$7+AG28*Settings!$B$8+AE28*Settings!$B$9+AB28*Settings!$B$10+AC28*Settings!$B$11+X28*Settings!$B$12+Y28*Settings!$B$13+Z28*Settings!$B$14 -> 0
A29: WR | B29: Charlie Jones | C29: 8 | D29: 27 | E29: ACT | F29: 2 | J29: 9 | K29: 1 | L29: 1 | N29: CIN | O29: 14 | P29: 6.5 | Q29: 8.62 | R29: 0.727 | U29: 17 | V29: 0 | W29: 0 | X29: 0 | Y29: 0 | Z29: 0 | AA29: 0 | AB29: 0 | AC29: 0 | AD29: 2 | AE29: 2 | AF29: 22 | AG29: 0 | AH29: kept | AI29: =IFERROR(AB29/AA29,"") | AJ29: =IFERROR(AF29/AE29,"") -> 11 | AK29: =IFERROR(AE29/AD29,"") -> 1 | AL29: =IFERROR(X29/V29,"") | AM29: =IFERROR(W29/V29,"") | AN29: =IFERROR(AA29/$H$5,"") -> 0 | AO29: =IFERROR(AD29/$G$5,"") -> 0.0032 | AP29: =IFERROR(V29/$F$5,"") -> 0 | AQ29: =IFERROR(AA29/U29,"") -> 0 | AR29: =IFERROR(AD29/U29,"") -> 0.11764706 | AS29: =IFERROR(AD29-L29,"") -> 1 | AT29: =IFERROR(AA29-H29,"") -> 0 | AU29: =AF29*Settings!$B$7+AG29*Settings!$B$8+AE29*Settings!$B$9+AB29*Settings!$B$10+AC29*Settings!$B$11+X29*Settings!$B$12+Y29*Settings!$B$13+Z29*Settings!$B$14 -> 3.2
A30: WR | B30: Other WRs | U30: 17 | AI30: =IFERROR(AB30/AA30,"") | AJ30: =IFERROR(AF30/AE30,"") | AK30: =IFERROR(AE30/AD30,"") | AL30: =IFERROR(X30/V30,"") | AM30: =IFERROR(W30/V30,"") | AN30: =IFERROR(AA30/$H$5,"") -> 0 | AO30: =IFERROR(AD30/$G$5,"") -> 0 | AP30: =IFERROR(V30/$F$5,"") -> 0 | AQ30: =IFERROR(AA30/U30,"") -> 0 | AR30: =IFERROR(AD30/U30,"") -> 0 | AS30: =IFERROR(AD30-L30,"") -> 0 | AT30: =IFERROR(AA30-H30,"") -> 0 | AU30: =AF30*Settings!$B$7+AG30*Settings!$B$8+AE30*Settings!$B$9+AB30*Settings!$B$10+AC30*Settings!$B$11+X30*Settings!$B$12+Y30*Settings!$B$13+Z30*Settings!$B$14 -> 0
A31: TE | B31: Mike Gesicki | C31: 1 | D31: 30 | E31: ACT | J31: 45 | K31: 83 | L31: 42 | M31: 307 | N31: CIN | O31: 13 | Q31: 9.97 | R31: 0.718 | U31: 17 | V31: 0 | W31: 0 | X31: 0 | Y31: 0 | Z31: 0 | AA31: 0 | AB31: 0 | AC31: 0 | AD31: 58 | AE31: 40 | AF31: 417 | AG31: 3 | AH31: kept | AI31: =IFERROR(AB31/AA31,"") | AJ31: =IFERROR(AF31/AE31,"") -> 10.425 | AK31: =IFERROR(AE31/AD31,"") -> 0.68965517 | AL31: =IFERROR(X31/V31,"") | AM31: =IFERROR(W31/V31,"") | AN31: =IFERROR(AA31/$H$5,"") -> 0 | AO31: =IFERROR(AD31/$G$5,"") -> 0.0928 | AP31: =IFERROR(V31/$F$5,"") -> 0 | AQ31: =IFERROR(AA31/U31,"") -> 0 | AR31: =IFERROR(AD31/U31,"") -> 3.4117647 | AS31: =IFERROR(AD31-L31,"") -> 16 | AT31: =IFERROR(AA31-H31,"") -> 0 | AU31: =AF31*Settings!$B$7+AG31*Settings!$B$8+AE31*Settings!$B$9+AB31*Settings!$B$10+AC31*Settings!$B$11+X31*Settings!$B$12+Y31*Settings!$B$13+Z31*Settings!$B$14 -> 79.7
A32: TE | B32: Erick All | C32: 2 | D32: 25 | E32: ACT | K32: 22 | Q32: 7.9 | R32: 0.909 | U32: 17 | AA32: 0 | AB32: 0 | AC32: 0 | AD32: 31 | AE32: 26 | AF32: 243 | AG32: 2 | AH32: kept | AI32: =IFERROR(AB32/AA32,"") | AJ32: =IFERROR(AF32/AE32,"") -> 9.3461538 | AK32: =IFERROR(AE32/AD32,"") -> 0.83870968 | AL32: =IFERROR(X32/V32,"") | AM32: =IFERROR(W32/V32,"") | AN32: =IFERROR(AA32/$H$5,"") -> 0 | AO32: =IFERROR(AD32/$G$5,"") -> 0.0496 | AP32: =IFERROR(V32/$F$5,"") -> 0 | AQ32: =IFERROR(AA32/U32,"") -> 0 | AR32: =IFERROR(AD32/U32,"") -> 1.8235294 | AS32: =IFERROR(AD32-L32,"") -> 31 | AT32: =IFERROR(AA32-H32,"") -> 0 | AU32: =AF32*Settings!$B$7+AG32*Settings!$B$8+AE32*Settings!$B$9+AB32*Settings!$B$10+AC32*Settings!$B$11+X32*Settings!$B$12+Y32*Settings!$B$13+Z32*Settings!$B$14 -> 49.3
A33: TE | B33: Drew Sample | C33: 3 | D33: 30 | E33: ACT | G33: 1 | H33: 1 | I33: 3 | J33: 27 | K33: 22 | L33: 20 | M33: 106 | N33: CIN | O33: 17 | P33: -0.5 | Q33: 6.63 | R33: 0.826 | U33: 17 | V33: 0 | W33: 0 | X33: 0 | Y33: 0 | Z33: 0 | AA33: 0 | AB33: 0 | AC33: 0 | AD33: 18 | AE33: 14 | AF33: 107 | AG33: 1 | AH33: kept | AI33: =IFERROR(AB33/AA33,"") | AJ33: =IFERROR(AF33/AE33,"") -> 7.6428571 | AK33: =IFERROR(AE33/AD33,"") -> 0.77777778 | AL33: =IFERROR(X33/V33,"") | AM33: =IFERROR(W33/V33,"") | AN33: =IFERROR(AA33/$H$5,"") -> 0 | AO33: =IFERROR(AD33/$G$5,"") -> 0.0288 | AP33: =IFERROR(V33/$F$5,"") -> 0 | AQ33: =IFERROR(AA33/U33,"") -> 0 | AR33: =IFERROR(AD33/U33,"") -> 1.0588235 | AS33: =IFERROR(AD33-L33,"") -> -2 | AT33: =IFERROR(AA33-H33,"") -> -1 | AU33: =AF33*Settings!$B$7+AG33*Settings!$B$8+AE33*Settings!$B$9+AB33*Settings!$B$10+AC33*Settings!$B$11+X33*Settings!$B$12+Y33*Settings!$B$13+Z33*Settings!$B$14 -> 23.7
A34: TE | B34: Jack Endries | C34: 4 | D34: 22 | E34: ACT | U34: 17 | AA34: 0 | AB34: 0 | AC34: 0 | AD34: 17 | AE34: 12 | AF34: 125 | AG34: 1 | AH34: kept | AI34: =IFERROR(AB34/AA34,"") | AJ34: =IFERROR(AF34/AE34,"") -> 10.416667 | AK34: =IFERROR(AE34/AD34,"") -> 0.70588235 | AL34: =IFERROR(X34/V34,"") | AM34: =IFERROR(W34/V34,"") | AN34: =IFERROR(AA34/$H$5,"") -> 0 | AO34: =IFERROR(AD34/$G$5,"") -> 0.0272 | AP34: =IFERROR(V34/$F$5,"") -> 0 | AQ34: =IFERROR(AA34/U34,"") -> 0 | AR34: =IFERROR(AD34/U34,"") -> 1 | AS34: =IFERROR(AD34-L34,"") -> 17 | AT34: =IFERROR(AA34-H34,"") -> 0 | AU34: =AF34*Settings!$B$7+AG34*Settings!$B$8+AE34*Settings!$B$9+AB34*Settings!$B$10+AC34*Settings!$B$11+X34*Settings!$B$12+Y34*Settings!$B$13+Z34*Settings!$B$14 -> 24.5
A35: TE | B35: Other TEs | U35: 17 | AI35: =IFERROR(AB35/AA35,"") | AJ35: =IFERROR(AF35/AE35,"") | AK35: =IFERROR(AE35/AD35,"") | AL35: =IFERROR(X35/V35,"") | AM35: =IFERROR(W35/V35,"") | AN35: =IFERROR(AA35/$H$5,"") -> 0 | AO35: =IFERROR(AD35/$G$5,"") -> 0 | AP35: =IFERROR(V35/$F$5,"") -> 0 | AQ35: =IFERROR(AA35/U35,"") -> 0 | AR35: =IFERROR(AD35/U35,"") -> 0 | AS35: =IFERROR(AD35-L35,"") -> 0 | AT35: =IFERROR(AA35-H35,"") -> 0 | AU35: =AF35*Settings!$B$7+AG35*Settings!$B$8+AE35*Settings!$B$9+AB35*Settings!$B$10+AC35*Settings!$B$11+X35*Settings!$B$12+Y35*Settings!$B$13+Z35*Settings!$B$14 -> 0
A37: YOUR TOTAL | U37: =SUM(U11:U35) -> 425 | V37: =SUM(V11:V35) -> 625 | W37: =SUM(W11:W35) -> 421 | X37: =SUM(X11:X35) -> 4522 | Y37: =SUM(Y11:Y35) -> 35 | Z37: =SUM(Z11:Z35) -> 12 | AA37: =SUM(AA11:AA35) -> 405 | AB37: =SUM(AB11:AB35) -> 1697 | ... AG37: =SUM(AG11:AG35) -> 37
A38: TEAM TARGET | V38: =$F$5 -> 655 | X38: =$I$5 -> 4287 | Y38: =$J$5 -> 33 | Z38: =$K$5 -> 14 | AA38: =$H$5 -> 404.1 | AB38: =$L$5 -> 1691 | AC38: =$M$5 -> 13 | AD38: =$G$5 -> 625 | AF38: =$I$5 -> 4287 | AG38: =$J$5 -> 33
A39: LEFT | V39: =$F$5-V37 -> 30 | X39: =$I$5-X37 -> -235 | Y39: =$J$5-Y37 -> -2 | Z39: =$K$5-Z37 -> 2 | AA39: =$H$5-AA37 -> -0.9 | AB39: =$L$5-AB37 -> -6 | AC39: =$M$5-AC37 -> 1 | AD39: =$G$5-AD37 -> 20 | AF39: =$I$5-AF37 -> -340 | AG39: =$J$5-AG37 -> -4
B40: Red = you have allocated more than the team total. Amber = more than 3% under. These are targets, not hard caps - if you disagree, edit the team total above. | AF40: Rec Yds / Rec TD are checked against the PASSING totals

Sheet CLE
A1: CLE - 2026 projections (direct entry)
A3: TEAM TOTALS | D3: all editable - these are your targets, not hard caps
B4: Games | C4: Plays/G | D4: Plays | E4: Pass Rate | F4: Pass Att | G4: Targets | H4: Rush Att | I4: Pass Yds | J4: Pass TD | K4: Int | L4: Rush Yds | M4: Rush TD
B5: 17 | C5: 63.2 | D5: =C5*B5 -> 1074.4 | E5: 0.5923 | F5: =ROUND(D5*E5,0) -> 636 | G5: =ROUND(F5*Settings!$B$4,0) -> 607 | H5: =D5-F5 -> 438.4 | I5: 3649 | J5: 21 | K5: 17 | L5: 1790 | M5: 12
A7: VACATED | B7: 15% of targets and 7% of carries left this roster - that volume is yours to reassign.
A8: STAFF | B8: NEW HC Todd Monken + OC Travis Switzer. Shift toward MORE RUN given QB uncertainty - lower pass rate.
A10: Pos | B10: Player | C10: Dep | D10: Age | E10: Status | F10: '23 Car | G10: '24 Car | H10: '25 Car | I10: '25 RuYd | J10: '23 Tgt | K10: '24 Tgt | L10: '25 Tgt | M10: '25 ReYd | N10: '25 Tm | O10: '25 G | P10: 3y Y/C | Q10: 3y Y/R | R10: 3y Ctch | S10: 3y Comp% | T10: 3y Y/A | U10: Games | V10: Pass Att | W10: Cmp | X10: Pass Yds | Y10: Pass TD | Z10: Int | AA10: Rush Att | AB10: Rush Yds | AC10: Rush TD | AD10: Targets | AE10: Rec | AF10: Rec Yds | AG10: Rec TD | AH10: Seed | AI10: Y/C | AJ10: Y/R | AK10: Catch% | AL10: Y/A | AM10: Comp% | AN10: Rush % | AO10: Tgt % | AP10: Pass % | AQ10: Car/G | AR10: Tgt/G | AS10: dTgt | AT10: dCar | AU10: Half PPR
A11: QB | B11: Deshaun Watson | C11: 1 | D11: 30 | E11: ACT | F11: 25 | G11: 30 | P11: 5.27 | S11: 0.625 | T11: 5.85 | U11: 17 | V11: 254 | W11: 155 | X11: 1663 | Y11: 9 | Z11: 7 | AA11: 37 | AB11: 158 | AC11: 1 | AH11: kept | AI11: =IFERROR(AB11/AA11,"") -> 4.2702703 | AJ11: =IFERROR(AF11/AE11,"") | AK11: =IFERROR(AE11/AD11,"") | AL11: =IFERROR(X11/V11,"") -> 6.5472441 | AM11: =IFERROR(W11/V11,"") -> 0.61023622 | AN11: =IFERROR(AA11/$H$5,"") -> 0.08439781 | AO11: =IFERROR(AD11/$G$5,"") -> 0 | AP11: =IFERROR(V11/$F$5,"") -> 0.39937107 | AQ11: =IFERROR(AA11/U11,"") -> 2.1764706 | AR11: =IFERROR(AD11/U11,"") -> 0 | AS11: =IFERROR(AD11-L11,"") -> 0 | AT11: =IFERROR(AA11-H11,"") -> 37 | AU11: =AF11*Settings!$B$7+AG11*Settings!$B$8+AE11*Settings!$B$9+AB11*Settings!$B$10+AC11*Settings!$B$11+X11*Settings!$B$12+Y11*Settings!$B$13+Z11*Settings!$B$14 -> 110.32
A12: QB | B12: Shedeur Sanders | C12: 2 | D12: 24 | E12: ACT | H12: 19 | I12: 169 | N12: CLE | O12: 8 | P12: 8.89 | S12: 0.566 | T12: 6.6 | U12: 17 | V12: 265 | W12: 158 | X12: 1729 | Y12: 9 | Z12: 9 | AA12: 27 | AB12: 152 | AC12: 1 | AD12: 0 | AE12: 0 | AF12: 0 | AG12: 0 | AH12: kept | AI12: =IFERROR(AB12/AA12,"") -> 5.6296296 | AJ12: =IFERROR(AF12/AE12,"") | AK12: =IFERROR(AE12/AD12,"") | AL12: =IFERROR(X12/V12,"") -> 6.5245283 | AM12: =IFERROR(W12/V12,"") -> 0.59622642 | AN12: =IFERROR(AA12/$H$5,"") -> 0.061587591 | AO12: =IFERROR(AD12/$G$5,"") -> 0 | AP12: =IFERROR(V12/$F$5,"") -> 0.41666667 | AQ12: =IFERROR(AA12/U12,"") -> 1.5882353 | AR12: =IFERROR(AD12/U12,"") -> 0 | AS12: =IFERROR(AD12-L12,"") -> 0 | AT12: =IFERROR(AA12-H12,"") -> 8 | AU12: =AF12*Settings!$B$7+AG12*Settings!$B$8+AE12*Settings!$B$9+AB12*Settings!$B$10+AC12*Settings!$B$11+X12*Settings!$B$12+Y12*Settings!$B$13+Z12*Settings!$B$14 -> 108.36
A13: QB | B13: Taylen Green | C13: 3 | D13: 23 | E13: ACT | U13: 17 | V13: 40 | W13: 24 | X13: 276 | Y13: 2 | Z13: 1 | AA13: 12 | AB13: 45 | AC13: 1 | AH13: kept | AI13: =IFERROR(AB13/AA13,"") -> 3.75 | AJ13: =IFERROR(AF13/AE13,"") | AK13: =IFERROR(AE13/AD13,"") | AL13: =IFERROR(X13/V13,"") -> 6.9 | AM13: =IFERROR(W13/V13,"") -> 0.6 | AN13: =IFERROR(AA13/$H$5,"") -> 0.027372263 | AO13: =IFERROR(AD13/$G$5,"") -> 0 | AP13: =IFERROR(V13/$F$5,"") -> 0.062893082 | AQ13: =IFERROR(AA13/U13,"") -> 0.70588235 | AR13: =IFERROR(AD13/U13,"") -> 0 | AS13: =IFERROR(AD13-L13,"") -> 0 | AT13: =IFERROR(AA13-H13,"") -> 12 | AU13: =AF13*Settings!$B$7+AG13*Settings!$B$8+AE13*Settings!$B$9+AB13*Settings!$B$10+AC13*Settings!$B$11+X13*Settings!$B$12+Y13*Settings!$B$13+Z13*Settings!$B$14 -> 27.54
A14: QB | B14: Other QBs | U14: 17 | AI14: =IFERROR(AB14/AA14,"") | AJ14: =IFERROR(AF14/AE14,"") | AK14: =IFERROR(AE14/AD14,"") | AL14: =IFERROR(X14/V14,"") | AM14: =IFERROR(W14/V14,"") | AN14: =IFERROR(AA14/$H$5,"") -> 0 | AO14: =IFERROR(AD14/$G$5,"") -> 0 | AP14: =IFERROR(V14/$F$5,"") -> 0 | AQ14: =IFERROR(AA14/U14,"") -> 0 | AR14: =IFERROR(AD14/U14,"") -> 0 | AS14: =IFERROR(AD14-L14,"") -> 0 | AT14: =IFERROR(AA14-H14,"") -> 0 | AU14: =AF14*Settings!$B$7+AG14*Settings!$B$8+AE14*Settings!$B$9+AB14*Settings!$B$10+AC14*Settings!$B$11+X14*Settings!$B$12+Y14*Settings!$B$13+Z14*Settings!$B$14 -> 0
A15: RB | B15: Quinshon Judkins | C15: 1 | D15: 22 | E15: ACT | H15: 230 | I15: 827 | L15: 36 | M15: 171 | N15: CLE | O15: 14 | P15: 3.6 | Q15: 6.58 | R15: 0.722 | U15: 17 | V15: 0 | W15: 0 | X15: 0 | Y15: 0 | Z15: 0 | AA15: 268 | AB15: 1032 | AC15: 7 | AD15: 40 | AE15: 29 | AF15: 203 | AG15: 1 | AH15: kept | AI15: =IFERROR(AB15/AA15,"") -> 3.8507463 | AJ15: =IFERROR(AF15/AE15,"") -> 7 | AK15: =IFERROR(AE15/AD15,"") -> 0.725 | AL15: =IFERROR(X15/V15,"") | AM15: =IFERROR(W15/V15,"") | AN15: =IFERROR(AA15/$H$5,"") -> 0.61131387 | AO15: =IFERROR(AD15/$G$5,"") -> 0.065897858 | AP15: =IFERROR(V15/$F$5,"") -> 0 | AQ15: =IFERROR(AA15/U15,"") -> 15.764706 | AR15: =IFERROR(AD15/U15,"") -> 2.3529412 | AS15: =IFERROR(AD15-L15,"") -> 4 | AT15: =IFERROR(AA15-H15,"") -> 38 | AU15: =AF15*Settings!$B$7+AG15*Settings!$B$8+AE15*Settings!$B$9+AB15*Settings!$B$10+AC15*Settings!$B$11+X15*Settings!$B$12+Y15*Settings!$B$13+Z15*Settings!$B$14 -> 186
A16: RB | B16: Dylan Sampson | C16: 2 | D16: 21 | E16: ACT | H16: 65 | I16: 175 | L16: 40 | M16: 271 | N16: CLE | O16: 15 | P16: 2.69 | Q16: 8.21 | R16: 0.825 | U16: 17 | V16: 0 | W16: 0 | X16: 0 | Y16: 0 | Z16: 0 | AA16: 78 | AB16: 284 | AC16: 1 | AD16: 38 | AE16: 33 | AF16: 260 | AG16: 2 | AH16: kept | AI16: =IFERROR(AB16/AA16,"") -> 3.6410256 | AJ16: =IFERROR(AF16/AE16,"") -> 7.8787879 | AK16: =IFERROR(AE16/AD16,"") -> 0.86842105 | AL16: =IFERROR(X16/V16,"") | AM16: =IFERROR(W16/V16,"") | AN16: =IFERROR(AA16/$H$5,"") -> 0.17791971 | AO16: =IFERROR(AD16/$G$5,"") -> 0.062602965 | AP16: =IFERROR(V16/$F$5,"") -> 0 | AQ16: =IFERROR(AA16/U16,"") -> 4.5882353 | AR16: =IFERROR(AD16/U16,"") -> 2.2352941 | AS16: =IFERROR(AD16-L16,"") -> -2 | AT16: =IFERROR(AA16-H16,"") -> 13 | AU16: =AF16*Settings!$B$7+AG16*Settings!$B$8+AE16*Settings!$B$9+AB16*Settings!$B$10+AC16*Settings!$B$11+X16*Settings!$B$12+Y16*Settings!$B$13+Z16*Settings!$B$14 -> 88.9
A17: RB | B17: Raheim Sanders | C17: 3 | D17: 24 | E17: ACT | H17: 27 | I17: 92 | L17: 4 | M17: 21 | N17: CLE | O17: 4 | P17: 3.41 | Q17: 7 | R17: 0.75 | U17: 17 | V17: 0 | W17: 0 | X17: 0 | Y17: 0 | Z17: 0 | AA17: 32 | AB17: 115 | AC17: 1 | AD17: 6 | AE17: 5 | AF17: 38 | AG17: 0 | AH17: kept | AI17: =IFERROR(AB17/AA17,"") -> 3.59375 | AJ17: =IFERROR(AF17/AE17,"") -> 7.6 | AK17: =IFERROR(AE17/AD17,"") -> 0.83333333 | AL17: =IFERROR(X17/V17,"") | AM17: =IFERROR(W17/V17,"") | AN17: =IFERROR(AA17/$H$5,"") -> 0.072992701 | AO17: =IFERROR(AD17/$G$5,"") -> 0.0098846787 | AP17: =IFERROR(V17/$F$5,"") -> 0 | AQ17: =IFERROR(AA17/U17,"") -> 1.8823529 | AR17: =IFERROR(AD17/U17,"") -> 0.35294118 | AS17: =IFERROR(AD17-L17,"") -> 2 | AT17: =IFERROR(AA17-H17,"") -> 5 | AU17: =AF17*Settings!$B$7+AG17*Settings!$B$8+AE17*Settings!$B$9+AB17*Settings!$B$10+AC17*Settings!$B$11+X17*Settings!$B$12+Y17*Settings!$B$13+Z17*Settings!$B$14 -> 23.8
A18: RB | B18: Ahmani Marshall | C18: 4 | D18: 24 | E18: ACT | U18: 17 | AI18: =IFERROR(AB18/AA18,"") | AJ18: =IFERROR(AF18/AE18,"") | AK18: =IFERROR(AE18/AD18,"") | AL18: =IFERROR(X18/V18,"") | AM18: =IFERROR(W18/V18,"") | AN18: =IFERROR(AA18/$H$5,"") -> 0 | AO18: =IFERROR(AD18/$G$5,"") -> 0 | AP18: =IFERROR(V18/$F$5,"") -> 0 | AQ18: =IFERROR(AA18/U18,"") -> 0 | AR18: =IFERROR(AD18/U18,"") -> 0 | AS18: =IFERROR(AD18-L18,"") -> 0 | AT18: =IFERROR(AA18-H18,"") -> 0 | AU18: =AF18*Settings!$B$7+AG18*Settings!$B$8+AE18*Settings!$B$9+AB18*Settings!$B$10+AC18*Settings!$B$11+X18*Settings!$B$12+Y18*Settings!$B$13+Z18*Settings!$B$14 -> 0
A19: RB | B19: Davon Booth | C19: 5 | D19: 24 | E19: ACT | U19: 17 | AI19: =IFERROR(AB19/AA19,"") | AJ19: =IFERROR(AF19/AE19,"") | AK19: =IFERROR(AE19/AD19,"") | AL19: =IFERROR(X19/V19,"") | AM19: =IFERROR(W19/V19,"") | AN19: =IFERROR(AA19/$H$5,"") -> 0 | AO19: =IFERROR(AD19/$G$5,"") -> 0 | AP19: =IFERROR(V19/$F$5,"") -> 0 | AQ19: =IFERROR(AA19/U19,"") -> 0 | AR19: =IFERROR(AD19/U19,"") -> 0 | AS19: =IFERROR(AD19-L19,"") -> 0 | AT19: =IFERROR(AA19-H19,"") -> 0 | AU19: =AF19*Settings!$B$7+AG19*Settings!$B$8+AE19*Settings!$B$9+AB19*Settings!$B$10+AC19*Settings!$B$11+X19*Settings!$B$12+Y19*Settings!$B$13+Z19*Settings!$B$14 -> 0
A20: RB | B20: Michael Burton | C20: 6 | D20: 34 | E20: ACT | F20: 7 | G20: 7 | J20: 3 | K20: 10 | P20: 1.21 | Q20: 5.62 | R20: 1 | U20: 17 | AA20: 5 | AB20: 9 | AC20: 0 | AD20: 4 | AE20: 4 | AF20: 22 | AG20: 0 | AH20: kept | AI20: =IFERROR(AB20/AA20,"") -> 1.8 | AJ20: =IFERROR(AF20/AE20,"") -> 5.5 | AK20: =IFERROR(AE20/AD20,"") -> 1 | AL20: =IFERROR(X20/V20,"") | AM20: =IFERROR(W20/V20,"") | AN20: =IFERROR(AA20/$H$5,"") -> 0.011405109 | AO20: =IFERROR(AD20/$G$5,"") -> 0.0065897858 | AP20: =IFERROR(V20/$F$5,"") -> 0 | AQ20: =IFERROR(AA20/U20,"") -> 0.29411765 | AR20: =IFERROR(AD20/U20,"") -> 0.23529412 | AS20: =IFERROR(AD20-L20,"") -> 4 | AT20: =IFERROR(AA20-H20,"") -> 5 | AU20: =AF20*Settings!$B$7+AG20*Settings!$B$8+AE20*Settings!$B$9+AB20*Settings!$B$10+AC20*Settings!$B$11+X20*Settings!$B$12+Y20*Settings!$B$13+Z20*Settings!$B$14 -> 5.1
A21: RB | B21: Other RBs | U21: 17 | AI21: =IFERROR(AB21/AA21,"") | AJ21: =IFERROR(AF21/AE21,"") | AK21: =IFERROR(AE21/AD21,"") | AL21: =IFERROR(X21/V21,"") | AM21: =IFERROR(W21/V21,"") | AN21: =IFERROR(AA21/$H$5,"") -> 0 | AO21: =IFERROR(AD21/$G$5,"") -> 0 | AP21: =IFERROR(V21/$F$5,"") -> 0 | AQ21: =IFERROR(AA21/U21,"") -> 0 | AR21: =IFERROR(AD21/U21,"") -> 0 | AS21: =IFERROR(AD21-L21,"") -> 0 | AT21: =IFERROR(AA21-H21,"") -> 0 | AU21: =AF21*Settings!$B$7+AG21*Settings!$B$8+AE21*Settings!$B$9+AB21*Settings!$B$10+AC21*Settings!$B$11+X21*Settings!$B$12+Y21*Settings!$B$13+Z21*Settings!$B$14 -> 0
A22: WR | B22: Jerry Jeudy | C22: 1 | D22: 27 | E22: ACT | H22: 1 | I22: 5 | J22: 87 | K22: 145 | L22: 106 | M22: 602 | N22: CLE | O22: 17 | P22: 5 | Q22: 13.35 | R22: 0.574 | U22: 17 | V22: 0 | W22: 0 | X22: 0 | Y22: 0 | Z22: 0 | AA22: 0 | AB22: 2 | AC22: 0 | AD22: 88 | AE22: 47 | AF22: 635 | AG22: 3 | AH22: kept | AI22: =IFERROR(AB22/AA22,"") | AJ22: =IFERROR(AF22/AE22,"") -> 13.510638 | AK22: =IFERROR(AE22/AD22,"") -> 0.53409091 | AL22: =IFERROR(X22/V22,"") | AM22: =IFERROR(W22/V22,"") | AN22: =IFERROR(AA22/$H$5,"") -> 0 | AO22: =IFERROR(AD22/$G$5,"") -> 0.14497529 | AP22: =IFERROR(V22/$F$5,"") -> 0 | AQ22: =IFERROR(AA22/U22,"") -> 0 | AR22: =IFERROR(AD22/U22,"") -> 5.1764706 | AS22: =IFERROR(AD22-L22,"") -> -18 | AT22: =IFERROR(AA22-H22,"") -> -1 | AU22: =AF22*Settings!$B$7+AG22*Settings!$B$8+AE22*Settings!$B$9+AB22*Settings!$B$10+AC22*Settings!$B$11+X22*Settings!$B$12+Y22*Settings!$B$13+Z22*Settings!$B$14 -> 105.2
A23: WR | B23: KC Concepcion | C23: 2 | D23: 21 | E23: QUESTIONABLE | U23: 17 | AA23: 4 | AB23: 28 | AC23: 0 | AD23: 95 | AE23: 57 | AF23: 729 | AG23: 4 | AH23: kept | AI23: =IFERROR(AB23/AA23,"") -> 7 | AJ23: =IFERROR(AF23/AE23,"") -> 12.789474 | AK23: =IFERROR(AE23/AD23,"") -> 0.6 | AL23: =IFERROR(X23/V23,"") | AM23: =IFERROR(W23/V23,"") | AN23: =IFERROR(AA23/$H$5,"") -> 0.0091240876 | AO23: =IFERROR(AD23/$G$5,"") -> 0.15650741 | AP23: =IFERROR(V23/$F$5,"") -> 0 | AQ23: =IFERROR(AA23/U23,"") -> 0.23529412 | AR23: =IFERROR(AD23/U23,"") -> 5.5882353 | AS23: =IFERROR(AD23-L23,"") -> 95 | AT23: =IFERROR(AA23-H23,"") -> 4 | AU23: =AF23*Settings!$B$7+AG23*Settings!$B$8+AE23*Settings!$B$9+AB23*Settings!$B$10+AC23*Settings!$B$11+X23*Settings!$B$12+Y23*Settings!$B$13+Z23*Settings!$B$14 -> 128.2
A24: WR | B24: Denzel Boston | C24: 3 | D24: 22 | E24: ACT | U24: 17 | AA24: 1 | AB24: 3 | AC24: 0 | AD24: 83 | AE24: 49 | AF24: 636 | AG24: 3 | AH24: kept | AI24: =IFERROR(AB24/AA24,"") -> 3 | AJ24: =IFERROR(AF24/AE24,"") -> 12.979592 | AK24: =IFERROR(AE24/AD24,"") -> 0.59036145 | AL24: =IFERROR(X24/V24,"") | AM24: =IFERROR(W24/V24,"") | AN24: =IFERROR(AA24/$H$5,"") -> 0.0022810219 | AO24: =IFERROR(AD24/$G$5,"") -> 0.13673806 | AP24: =IFERROR(V24/$F$5,"") -> 0 | AQ24: =IFERROR(AA24/U24,"") -> 0.058823529 | AR24: =IFERROR(AD24/U24,"") -> 4.8823529 | AS24: =IFERROR(AD24-L24,"") -> 83 | AT24: =IFERROR(AA24-H24,"") -> 1 | AU24: =AF24*Settings!$B$7+AG24*Settings!$B$8+AE24*Settings!$B$9+AB24*Settings!$B$10+AC24*Settings!$B$11+X24*Settings!$B$12+Y24*Settings!$B$13+Z24*Settings!$B$14 -> 106.4
A25: WR | B25: Cedric Tillman | C25: 4 | D25: 26 | E25: ACT | F25: 1 | G25: 1 | J25: 44 | K25: 49 | L25: 39 | M25: 270 | N25: CLE | O25: 13 | P25: 1.5 | Q25: 11.73 | R25: 0.538 | U25: 17 | V25: 0 | W25: 0 | X25: 0 | Y25: 0 | Z25: 0 | AA25: 0 | AB25: 0 | AC25: 0 | AD25: 21 | AE25: 12 | AF25: 157 | AG25: 1 | AH25: kept | AI25: =IFERROR(AB25/AA25,"") | AJ25: =IFERROR(AF25/AE25,"") -> 13.083333 | AK25: =IFERROR(AE25/AD25,"") -> 0.57142857 | AL25: =IFERROR(X25/V25,"") | AM25: =IFERROR(W25/V25,"") | AN25: =IFERROR(AA25/$H$5,"") -> 0 | AO25: =IFERROR(AD25/$G$5,"") -> 0.034596376 | AP25: =IFERROR(V25/$F$5,"") -> 0 | AQ25: =IFERROR(AA25/U25,"") -> 0 | AR25: =IFERROR(AD25/U25,"") -> 1.2352941 | AS25: =IFERROR(AD25-L25,"") -> -18 | AT25: =IFERROR(AA25-H25,"") -> 0 | AU25: =AF25*Settings!$B$7+AG25*Settings!$B$8+AE25*Settings!$B$9+AB25*Settings!$B$10+AC25*Settings!$B$11+X25*Settings!$B$12+Y25*Settings!$B$13+Z25*Settings!$B$14 -> 27.7
A26: WR | B26: Isaiah Bond | C26: 5 | D26: 22 | E26: ACT | H26: 5 | I26: 29 | L26: 44 | M26: 338 | N26: CLE | O26: 16 | P26: 5.8 | Q26: 18.78 | R26: 0.409 | U26: 17 | V26: 0 | W26: 0 | X26: 0 | Y26: 0 | Z26: 0 | AA26: 3 | AB26: 17 | AC26: 0 | AD26: 24 | AE26: 13 | AF26: 184 | AG26: 1 | AH26: kept | AI26: =IFERROR(AB26/AA26,"") -> 5.6666667 | AJ26: =IFERROR(AF26/AE26,"") -> 14.153846 | AK26: =IFERROR(AE26/AD26,"") -> 0.54166667 | AL26: =IFERROR(X26/V26,"") | AM26: =IFERROR(W26/V26,"") | AN26: =IFERROR(AA26/$H$5,"") -> 0.0068430657 | AO26: =IFERROR(AD26/$G$5,"") -> 0.039538715 | AP26: =IFERROR(V26/$F$5,"") -> 0 | AQ26: =IFERROR(AA26/U26,"") -> 0.17647059 | AR26: =IFERROR(AD26/U26,"") -> 1.4117647 | AS26: =IFERROR(AD26-L26,"") -> -20 | AT26: =IFERROR(AA26-H26,"") -> -2 | AU26: =AF26*Settings!$B$7+AG26*Settings!$B$8+AE26*Settings!$B$9+AB26*Settings!$B$10+AC26*Settings!$B$11+X26*Settings!$B$12+Y26*Settings!$B$13+Z26*Settings!$B$14 -> 32.6
A27: WR | B27: Malachi Corley | C27: 6 | D27: 24 | E27: ACT | G27: 2 | H27: 13 | I27: 127 | K27: 6 | L27: 14 | M27: 79 | N27: CLE | O27: 13 | P27: 10.2 | Q27: 6.79 | R27: 0.7 | U27: 17 | V27: 0 | W27: 0 | X27: 0 | Y27: 0 | Z27: 0 | AA27: 8 | AB27: 57 | AC27: 0 | AD27: 3 | AE27: 2 | AF27: 22 | AG27: 0 | AH27: kept | AI27: =IFERROR(AB27/AA27,"") -> 7.125 | AJ27: =IFERROR(AF27/AE27,"") -> 11 | AK27: =IFERROR(AE27/AD27,"") -> 0.66666667 | AL27: =IFERROR(X27/V27,"") | AM27: =IFERROR(W27/V27,"") | AN27: =IFERROR(AA27/$H$5,"") -> 0.018248175 | AO27: =IFERROR(AD27/$G$5,"") -> 0.0049423394 | AP27: =IFERROR(V27/$F$5,"") -> 0 | AQ27: =IFERROR(AA27/U27,"") -> 0.47058824 | AR27: =IFERROR(AD27/U27,"") -> 0.17647059 | AS27: =IFERROR(AD27-L27,"") -> -11 | AT27: =IFERROR(AA27-H27,"") -> -5 | AU27: =AF27*Settings!$B$7+AG27*Settings!$B$8+AE27*Settings!$B$9+AB27*Settings!$B$10+AC27*Settings!$B$11+X27*Settings!$B$12+Y27*Settings!$B$13+Z27*Settings!$B$14 -> 8.9
A28: WR | B28: Tylan Wallace | C28: 7 | D28: 27 | E28: ACT | J28: 2 | K28: 12 | L28: 8 | M28: 45 | N28: BAL | O28: 14 | Q28: 15.56 | R28: 0.727 | U28: 17 | V28: 0 | W28: 0 | X28: 0 | Y28: 0 | Z28: 0 | AA28: 0 | AB28: 0 | AC28: 0 | AD28: 2 | AE28: 1 | AF28: 10 | AG28: 0 | AH28: kept | AI28: =IFERROR(AB28/AA28,"") | AJ28: =IFERROR(AF28/AE28,"") -> 10 | AK28: =IFERROR(AE28/AD28,"") -> 0.5 | AL28: =IFERROR(X28/V28,"") | AM28: =IFERROR(W28/V28,"") | AN28: =IFERROR(AA28/$H$5,"") -> 0 | AO28: =IFERROR(AD28/$G$5,"") -> 0.0032948929 | AP28: =IFERROR(V28/$F$5,"") -> 0 | AQ28: =IFERROR(AA28/U28,"") -> 0 | AR28: =IFERROR(AD28/U28,"") -> 0.11764706 | AS28: =IFERROR(AD28-L28,"") -> -6 | AT28: =IFERROR(AA28-H28,"") -> 0 | AU28: =AF28*Settings!$B$7+AG28*Settings!$B$8+AE28*Settings!$B$9+AB28*Settings!$B$10+AC28*Settings!$B$11+X28*Settings!$B$12+Y28*Settings!$B$13+Z28*Settings!$B$14 -> 1.5
A29: WR | B29: Jamari Thrash | C29: 8 | D29: 25 | E29: ACT | K29: 7 | L29: 15 | M29: 107 | N29: CLE | O29: 9 | Q29: 9.92 | R29: 0.591 | U29: 17 | V29: 0 | W29: 0 | X29: 0 | Y29: 0 | Z29: 0 | AA29: 0 | AB29: 0 | AC29: 0 | AD29: 0 | AE29: 0 | AF29: 2 | AG29: 0 | AH29: kept | AI29: =IFERROR(AB29/AA29,"") | AJ29: =IFERROR(AF29/AE29,"") | AK29: =IFERROR(AE29/AD29,"") | AL29: =IFERROR(X29/V29,"") | AM29: =IFERROR(W29/V29,"") | AN29: =IFERROR(AA29/$H$5,"") -> 0 | AO29: =IFERROR(AD29/$G$5,"") -> 0 | AP29: =IFERROR(V29/$F$5,"") -> 0 | AQ29: =IFERROR(AA29/U29,"") -> 0 | AR29: =IFERROR(AD29/U29,"") -> 0 | AS29: =IFERROR(AD29-L29,"") -> -15 | AT29: =IFERROR(AA29-H29,"") -> 0 | AU29: =AF29*Settings!$B$7+AG29*Settings!$B$8+AE29*Settings!$B$9+AB29*Settings!$B$10+AC29*Settings!$B$11+X29*Settings!$B$12+Y29*Settings!$B$13+Z29*Settings!$B$14 -> 0.2
A30: WR | B30: Other WRs | U30: 17 | AI30: =IFERROR(AB30/AA30,"") | AJ30: =IFERROR(AF30/AE30,"") | AK30: =IFERROR(AE30/AD30,"") | AL30: =IFERROR(X30/V30,"") | AM30: =IFERROR(W30/V30,"") | AN30: =IFERROR(AA30/$H$5,"") -> 0 | AO30: =IFERROR(AD30/$G$5,"") -> 0 | AP30: =IFERROR(V30/$F$5,"") -> 0 | AQ30: =IFERROR(AA30/U30,"") -> 0 | AR30: =IFERROR(AD30/U30,"") -> 0 | AS30: =IFERROR(AD30-L30,"") -> 0 | AT30: =IFERROR(AA30-H30,"") -> 0 | AU30: =AF30*Settings!$B$7+AG30*Settings!$B$8+AE30*Settings!$B$9+AB30*Settings!$B$10+AC30*Settings!$B$11+X30*Settings!$B$12+Y30*Settings!$B$13+Z30*Settings!$B$14 -> 0
A31: TE | B31: Harold Fannin | C31: 1 | D31: 22 | E31: ACT | H31: 7 | I31: 13 | L31: 107 | M31: 731 | N31: CLE | O31: 16 | P31: 1.86 | Q31: 10.15 | R31: 0.673 | U31: 17 | V31: 0 | W31: 0 | X31: 0 | Y31: 0 | Z31: 0 | AA31: 7 | AB31: 19 | AC31: 0 | AD31: 108 | AE31: 72 | AF31: 754 | AG31: 5 | AH31: kept | AI31: =IFERROR(AB31/AA31,"") -> 2.7142857 | AJ31: =IFERROR(AF31/AE31,"") -> 10.472222 | AK31: =IFERROR(AE31/AD31,"") -> 0.66666667 | AL31: =IFERROR(X31/V31,"") | AM31: =IFERROR(W31/V31,"") | AN31: =IFERROR(AA31/$H$5,"") -> 0.015967153 | AO31: =IFERROR(AD31/$G$5,"") -> 0.17792422 | AP31: =IFERROR(V31/$F$5,"") -> 0 | AQ31: =IFERROR(AA31/U31,"") -> 0.41176471 | AR31: =IFERROR(AD31/U31,"") -> 6.3529412 | AS31: =IFERROR(AD31-L31,"") -> 1 | AT31: =IFERROR(AA31-H31,"") -> 0 | AU31: =AF31*Settings!$B$7+AG31*Settings!$B$8+AE31*Settings!$B$9+AB31*Settings!$B$10+AC31*Settings!$B$11+X31*Settings!$B$12+Y31*Settings!$B$13+Z31*Settings!$B$14 -> 143.3
A32: TE | B32: Joe Royer | C32: 2 | D32: 24 | E32: ACT | U32: 17 | AA32: 0 | AB32: 0 | AC32: 0 | AD32: 13 | AE32: 8 | AF32: 79 | AG32: 1 | AH32: kept | AI32: =IFERROR(AB32/AA32,"") | AJ32: =IFERROR(AF32/AE32,"") -> 9.875 | AK32: =IFERROR(AE32/AD32,"") -> 0.61538462 | AL32: =IFERROR(X32/V32,"") | AM32: =IFERROR(W32/V32,"") | AN32: =IFERROR(AA32/$H$5,"") -> 0 | AO32: =IFERROR(AD32/$G$5,"") -> 0.021416804 | AP32: =IFERROR(V32/$F$5,"") -> 0 | AQ32: =IFERROR(AA32/U32,"") -> 0 | AR32: =IFERROR(AD32/U32,"") -> 0.76470588 | AS32: =IFERROR(AD32-L32,"") -> 13 | AT32: =IFERROR(AA32-H32,"") -> 0 | AU32: =AF32*Settings!$B$7+AG32*Settings!$B$8+AE32*Settings!$B$9+AB32*Settings!$B$10+AC32*Settings!$B$11+X32*Settings!$B$12+Y32*Settings!$B$13+Z32*Settings!$B$14 -> 17.9
A33: TE | B33: Blake Whiteheart | C33: 3 | D33: 26 | E33: ACT | K33: 9 | L33: 6 | M33: 4 | N33: CLE | O33: 17 | Q33: 6.88 | R33: 0.533 | U33: 17 | V33: 0 | W33: 0 | X33: 0 | Y33: 0 | Z33: 0 | AA33: 0 | AB33: 0 | AC33: 0 | AD33: 5 | AE33: 3 | AF33: 23 | AG33: 0 | AH33: kept | AI33: =IFERROR(AB33/AA33,"") | AJ33: =IFERROR(AF33/AE33,"") -> 7.6666667 | AK33: =IFERROR(AE33/AD33,"") -> 0.6 | AL33: =IFERROR(X33/V33,"") | AM33: =IFERROR(W33/V33,"") | AN33: =IFERROR(AA33/$H$5,"") -> 0 | AO33: =IFERROR(AD33/$G$5,"") -> 0.0082372323 | AP33: =IFERROR(V33/$F$5,"") -> 0 | AQ33: =IFERROR(AA33/U33,"") -> 0 | AR33: =IFERROR(AD33/U33,"") -> 0.29411765 | AS33: =IFERROR(AD33-L33,"") -> -1 | AT33: =IFERROR(AA33-H33,"") -> 0 | AU33: =AF33*Settings!$B$7+AG33*Settings!$B$8+AE33*Settings!$B$9+AB33*Settings!$B$10+AC33*Settings!$B$11+X33*Settings!$B$12+Y33*Settings!$B$13+Z33*Settings!$B$14 -> 3.8
A34: TE | B34: Jack Stoll | C34: 4 | D34: 28 | E34: ACT | J34: 8 | K34: 3 | L34: 11 | M34: 46 | N34: NO | O34: 15 | Q34: 7.23 | R34: 0.591 | U34: 17 | V34: 0 | W34: 0 | X34: 0 | Y34: 0 | Z34: 0 | AA34: 0 | AB34: 0 | AC34: 0 | AD34: 7 | AE34: 4 | AF34: 35 | AG34: 0 | AH34: kept | AI34: =IFERROR(AB34/AA34,"") | AJ34: =IFERROR(AF34/AE34,"") -> 8.75 | AK34: =IFERROR(AE34/AD34,"") -> 0.57142857 | AL34: =IFERROR(X34/V34,"") | AM34: =IFERROR(W34/V34,"") | AN34: =IFERROR(AA34/$H$5,"") -> 0 | AO34: =IFERROR(AD34/$G$5,"") -> 0.011532125 | AP34: =IFERROR(V34/$F$5,"") -> 0 | AQ34: =IFERROR(AA34/U34,"") -> 0 | AR34: =IFERROR(AD34/U34,"") -> 0.41176471 | AS34: =IFERROR(AD34-L34,"") -> -4 | AT34: =IFERROR(AA34-H34,"") -> 0 | AU34: =AF34*Settings!$B$7+AG34*Settings!$B$8+AE34*Settings!$B$9+AB34*Settings!$B$10+AC34*Settings!$B$11+X34*Settings!$B$12+Y34*Settings!$B$13+Z34*Settings!$B$14 -> 5.5
A35: TE | B35: Other TEs | U35: 17 | AI35: =IFERROR(AB35/AA35,"") | AJ35: =IFERROR(AF35/AE35,"") | AK35: =IFERROR(AE35/AD35,"") | AL35: =IFERROR(X35/V35,"") | AM35: =IFERROR(W35/V35,"") | AN35: =IFERROR(AA35/$H$5,"") -> 0 | AO35: =IFERROR(AD35/$G$5,"") -> 0 | AP35: =IFERROR(V35/$F$5,"") -> 0 | AQ35: =IFERROR(AA35/U35,"") -> 0 | AR35: =IFERROR(AD35/U35,"") -> 0 | AS35: =IFERROR(AD35-L35,"") -> 0 | AT35: =IFERROR(AA35-H35,"") -> 0 | AU35: =AF35*Settings!$B$7+AG35*Settings!$B$8+AE35*Settings!$B$9+AB35*Settings!$B$10+AC35*Settings!$B$11+X35*Settings!$B$12+Y35*Settings!$B$13+Z35*Settings!$B$14 -> 0
A37: YOUR TOTAL | U37: =SUM(U11:U35) -> 425 | V37: =SUM(V11:V35) -> 559 | W37: =SUM(W11:W35) -> 337 | X37: =SUM(X11:X35) -> 3668 | Y37: =SUM(Y11:Y35) -> 20 | Z37: =SUM(Z11:Z35) -> 17 | AA37: =SUM(AA11:AA35) -> 482 | AB37: =SUM(AB11:AB35) -> 1921 | ... AG37: =SUM(AG11:AG35) -> 21
A38: TEAM TARGET | V38: =$F$5 -> 636 | X38: =$I$5 -> 3649 | Y38: =$J$5 -> 21 | Z38: =$K$5 -> 17 | AA38: =$H$5 -> 438.4 | AB38: =$L$5 -> 1790 | AC38: =$M$5 -> 12 | AD38: =$G$5 -> 607 | AF38: =$I$5 -> 3649 | AG38: =$J$5 -> 21
A39: LEFT | V39: =$F$5-V37 -> 77 | X39: =$I$5-X37 -> -19 | Y39: =$J$5-Y37 -> 1 | Z39: =$K$5-Z37 -> 0 | AA39: =$H$5-AA37 -> -43.6 | AB39: =$L$5-AB37 -> -131 | AC39: =$M$5-AC37 -> 0 | AD39: =$G$5-AD37 -> 70 | AF39: =$I$5-AF37 -> -140 | AG39: =$J$5-AG37 -> 0
B40: Red = you have allocated more than the team total. Amber = more than 3% under. These are targets, not hard caps - if you disagree, edit the team total above. | AF40: Rec Yds / Rec TD are checked against the PASSING totals

Sheet DAL
A1: DAL - 2026 projections (direct entry)
A3: TEAM TOTALS | D3: all editable - these are your targets, not hard caps
B4: Games | C4: Plays/G | D4: Plays | E4: Pass Rate | F4: Pass Att | G4: Targets | H4: Rush Att | I4: Pass Yds | J4: Pass TD | K4: Int | L4: Rush Yds | M4: Rush TD
B5: 17 | C5: 64.2 | D5: =C5*B5 -> 1091.4 | E5: 0.5845 | F5: =ROUND(D5*E5,0) -> 638 | G5: =ROUND(F5*Settings!$B$4,0) -> 609 | H5: =D5-F5 -> 453.4 | I5: 4320 | J5: 28 | K5: 12 | L5: 1957 | M5: 14
A7: VACATED | B7: 7% of targets and 4% of carries left this roster - that volume is yours to reassign.
A8: STAFF | B8: no coaching change recorded
A10: Pos | B10: Player | C10: Dep | D10: Age | E10: Status | F10: '23 Car | G10: '24 Car | H10: '25 Car | I10: '25 RuYd | J10: '23 Tgt | K10: '24 Tgt | L10: '25 Tgt | M10: '25 ReYd | N10: '25 Tm | O10: '25 G | P10: 3y Y/C | Q10: 3y Y/R | R10: 3y Ctch | S10: 3y Comp% | T10: 3y Y/A | U10: Games | V10: Pass Att | W10: Cmp | X10: Pass Yds | Y10: Pass TD | Z10: Int | AA10: Rush Att | AB10: Rush Yds | AC10: Rush TD | AD10: Targets | AE10: Rec | AF10: Rec Yds | AG10: Rec TD | AH10: Seed | AI10: Y/C | AJ10: Y/R | AK10: Catch% | AL10: Y/A | AM10: Comp% | AN10: Rush % | AO10: Tgt % | AP10: Pass % | AQ10: Car/G | AR10: Tgt/G | AS10: dTgt | AT10: dCar | AU10: Half PPR
A11: QB | B11: Dak Prescott | C11: 1 | D11: 33 | E11: ACT | F11: 43 | G11: 11 | H11: 37 | I11: 177 | N11: DAL | O11: 17 | P11: 5.2 | S11: 0.677 | T11: 7.48 | U11: 17 | V11: 575 | W11: 382 | X11: 4271 | Y11: 30 | Z11: 11 | AA11: 47 | AB11: 171 | AC11: 2 | AD11: 0 | AE11: 0 | AF11: 0 | AG11: 0 | AH11: kept | AI11: =IFERROR(AB11/AA11,"") -> 3.6382979 | AJ11: =IFERROR(AF11/AE11,"") | AK11: =IFERROR(AE11/AD11,"") | AL11: =IFERROR(X11/V11,"") -> 7.4278261 | AM11: =IFERROR(W11/V11,"") -> 0.66434783 | AN11: =IFERROR(AA11/$H$5,"") -> 0.10366123 | AO11: =IFERROR(AD11/$G$5,"") -> 0 | AP11: =IFERROR(V11/$F$5,"") -> 0.90125392 | AQ11: =IFERROR(AA11/U11,"") -> 2.7647059 | AR11: =IFERROR(AD11/U11,"") -> 0 | AS11: =IFERROR(AD11-L11,"") -> 0 | AT11: =IFERROR(AA11-H11,"") -> 10 | AU11: =AF11*Settings!$B$7+AG11*Settings!$B$8+AE11*Settings!$B$9+AB11*Settings!$B$10+AC11*Settings!$B$11+X11*Settings!$B$12+Y11*Settings!$B$13+Z11*Settings!$B$14 -> 297.94
A12: QB | B12: Joe Milton | C12: 2 | D12: 26 | E12: ACT | G12: 7 | H12: 5 | I12: 50 | N12: DAL | O12: 4 | P12: 5.5 | S12: 0.698 | T12: 8 | U12: 17 | V12: 26 | W12: 16 | X12: 190 | Y12: 1 | Z12: 1 | AA12: 3 | AB12: 17 | AC12: 0 | AD12: 0 | AE12: 0 | AF12: 0 | AG12: 0 | AH12: kept | AI12: =IFERROR(AB12/AA12,"") -> 5.6666667 | AJ12: =IFERROR(AF12/AE12,"") | AK12: =IFERROR(AE12/AD12,"") | AL12: =IFERROR(X12/V12,"") -> 7.3076923 | AM12: =IFERROR(W12/V12,"") -> 0.61538462 | AN12: =IFERROR(AA12/$H$5,"") -> 0.006616674 | AO12: =IFERROR(AD12/$G$5,"") -> 0 | AP12: =IFERROR(V12/$F$5,"") -> 0.040752351 | AQ12: =IFERROR(AA12/U12,"") -> 0.17647059 | AR12: =IFERROR(AD12/U12,"") -> 0 | AS12: =IFERROR(AD12-L12,"") -> 0 | AT12: =IFERROR(AA12-H12,"") -> -2 | AU12: =AF12*Settings!$B$7+AG12*Settings!$B$8+AE12*Settings!$B$9+AB12*Settings!$B$10+AC12*Settings!$B$11+X12*Settings!$B$12+Y12*Settings!$B$13+Z12*Settings!$B$14 -> 11.3
A13: QB | B13: Sam Howell | C13: 3 | D13: 25 | E13: ACT | F13: 44 | G13: 1 | J13: 1 | P13: 5.89 | Q13: 4 | R13: 1 | S13: 0.628 | T13: 6.34 | U13: 17 | V13: 33 | W13: 19 | X13: 182 | Y13: 1 | Z13: 1 | AA13: 1 | AB13: 6 | AC13: 0 | AH13: kept | AI13: =IFERROR(AB13/AA13,"") -> 6 | AJ13: =IFERROR(AF13/AE13,"") | AK13: =IFERROR(AE13/AD13,"") | AL13: =IFERROR(X13/V13,"") -> 5.5151515 | AM13: =IFERROR(W13/V13,"") -> 0.57575758 | AN13: =IFERROR(AA13/$H$5,"") -> 0.002205558 | AO13: =IFERROR(AD13/$G$5,"") -> 0 | AP13: =IFERROR(V13/$F$5,"") -> 0.051724138 | AQ13: =IFERROR(AA13/U13,"") -> 0.058823529 | AR13: =IFERROR(AD13/U13,"") -> 0 | AS13: =IFERROR(AD13-L13,"") -> 0 | AT13: =IFERROR(AA13-H13,"") -> 1 | AU13: =AF13*Settings!$B$7+AG13*Settings!$B$8+AE13*Settings!$B$9+AB13*Settings!$B$10+AC13*Settings!$B$11+X13*Settings!$B$12+Y13*Settings!$B$13+Z13*Settings!$B$14 -> 9.88
A14: QB | B14: Other QBs | U14: 17 | AI14: =IFERROR(AB14/AA14,"") | AJ14: =IFERROR(AF14/AE14,"") | AK14: =IFERROR(AE14/AD14,"") | AL14: =IFERROR(X14/V14,"") | AM14: =IFERROR(W14/V14,"") | AN14: =IFERROR(AA14/$H$5,"") -> 0 | AO14: =IFERROR(AD14/$G$5,"") -> 0 | AP14: =IFERROR(V14/$F$5,"") -> 0 | AQ14: =IFERROR(AA14/U14,"") -> 0 | AR14: =IFERROR(AD14/U14,"") -> 0 | AS14: =IFERROR(AD14-L14,"") -> 0 | AT14: =IFERROR(AA14-H14,"") -> 0 | AU14: =AF14*Settings!$B$7+AG14*Settings!$B$8+AE14*Settings!$B$9+AB14*Settings!$B$10+AC14*Settings!$B$11+X14*Settings!$B$12+Y14*Settings!$B$13+Z14*Settings!$B$14 -> 0
A15: RB | B15: Javonte Williams | C15: 1 | D15: 26 | E15: ACT | F15: 217 | G15: 139 | H15: 252 | I15: 1201 | J15: 58 | K15: 70 | L15: 51 | M15: 137 | N15: DAL | O15: 16 | P15: 4.09 | Q15: 5.31 | R15: 0.749 | U15: 17 | V15: 0 | W15: 0 | X15: 0 | Y15: 0 | Z15: 0 | AA15: 242 | AB15: 1110 | AC15: 10 | AD15: 45 | AE15: 33 | AF15: 185 | AG15: 1 | AH15: kept | AI15: =IFERROR(AB15/AA15,"") -> 4.5867769 | AJ15: =IFERROR(AF15/AE15,"") -> 5.6060606 | AK15: =IFERROR(AE15/AD15,"") -> 0.73333333 | AL15: =IFERROR(X15/V15,"") | AM15: =IFERROR(W15/V15,"") | AN15: =IFERROR(AA15/$H$5,"") -> 0.53374504 | AO15: =IFERROR(AD15/$G$5,"") -> 0.073891626 | AP15: =IFERROR(V15/$F$5,"") -> 0 | AQ15: =IFERROR(AA15/U15,"") -> 14.235294 | AR15: =IFERROR(AD15/U15,"") -> 2.6470588 | AS15: =IFERROR(AD15-L15,"") -> -6 | AT15: =IFERROR(AA15-H15,"") -> -10 | AU15: =AF15*Settings!$B$7+AG15*Settings!$B$8+AE15*Settings!$B$9+AB15*Settings!$B$10+AC15*Settings!$B$11+X15*Settings!$B$12+Y15*Settings!$B$13+Z15*Settings!$B$14 -> 212
A16: RB | B16: Malik Davis | C16: 2 | D16: 27 | E16: ACT | H16: 52 | I16: 250 | L16: 5 | M16: 16 | N16: DAL | O16: 10 | P16: 4.81 | Q16: 8 | R16: 0.4 | U16: 17 | V16: 0 | W16: 0 | X16: 0 | Y16: 0 | Z16: 0 | AA16: 49 | AB16: 223 | AC16: 2 | AD16: 8 | AE16: 5 | AF16: 38 | AG16: 0 | AH16: kept | AI16: =IFERROR(AB16/AA16,"") -> 4.5510204 | AJ16: =IFERROR(AF16/AE16,"") -> 7.6 | AK16: =IFERROR(AE16/AD16,"") -> 0.625 | AL16: =IFERROR(X16/V16,"") | AM16: =IFERROR(W16/V16,"") | AN16: =IFERROR(AA16/$H$5,"") -> 0.10807234 | AO16: =IFERROR(AD16/$G$5,"") -> 0.013136289 | AP16: =IFERROR(V16/$F$5,"") -> 0 | AQ16: =IFERROR(AA16/U16,"") -> 2.8823529 | AR16: =IFERROR(AD16/U16,"") -> 0.47058824 | AS16: =IFERROR(AD16-L16,"") -> 3 | AT16: =IFERROR(AA16-H16,"") -> -3 | AU16: =AF16*Settings!$B$7+AG16*Settings!$B$8+AE16*Settings!$B$9+AB16*Settings!$B$10+AC16*Settings!$B$11+X16*Settings!$B$12+Y16*Settings!$B$13+Z16*Settings!$B$14 -> 40.6
A17: RB | B17: Jaydon Blue | C17: 3 | D17: 22 | E17: ACT | H17: 38 | I17: 129 | L17: 1 | M17: 5 | N17: DAL | O17: 5 | P17: 3.39 | Q17: 5 | R17: 1 | U17: 17 | V17: 0 | W17: 0 | X17: 0 | Y17: 0 | Z17: 0 | AA17: 67 | AB17: 269 | AC17: 2 | AD17: 11 | AE17: 10 | AF17: 71 | AG17: 0 | AH17: kept | AI17: =IFERROR(AB17/AA17,"") -> 4.0149254 | AJ17: =IFERROR(AF17/AE17,"") -> 7.1 | AK17: =IFERROR(AE17/AD17,"") -> 0.90909091 | AL17: =IFERROR(X17/V17,"") | AM17: =IFERROR(W17/V17,"") | AN17: =IFERROR(AA17/$H$5,"") -> 0.14777239 | AO17: =IFERROR(AD17/$G$5,"") -> 0.018062397 | AP17: =IFERROR(V17/$F$5,"") -> 0 | AQ17: =IFERROR(AA17/U17,"") -> 3.9411765 | AR17: =IFERROR(AD17/U17,"") -> 0.64705882 | AS17: =IFERROR(AD17-L17,"") -> 10 | AT17: =IFERROR(AA17-H17,"") -> 29 | AU17: =AF17*Settings!$B$7+AG17*Settings!$B$8+AE17*Settings!$B$9+AB17*Settings!$B$10+AC17*Settings!$B$11+X17*Settings!$B$12+Y17*Settings!$B$13+Z17*Settings!$B$14 -> 51
A18: RB | B18: Phil Mafah | C18: 4 | D18: 23 | E18: ACT | H18: 5 | I18: 18 | L18: 2 | M18: 11 | N18: DAL | O18: 1 | P18: 3.6 | Q18: 5.5 | R18: 1 | U18: 17 | V18: 0 | W18: 0 | X18: 0 | Y18: 0 | Z18: 0 | AA18: 24 | AB18: 113 | AC18: 1 | AD18: 3 | AE18: 5 | AF18: 38 | AG18: 0 | AH18: kept | AI18: =IFERROR(AB18/AA18,"") -> 4.7083333 | AJ18: =IFERROR(AF18/AE18,"") -> 7.6 | AK18: =IFERROR(AE18/AD18,"") -> 1.6666667 | AL18: =IFERROR(X18/V18,"") | AM18: =IFERROR(W18/V18,"") | AN18: =IFERROR(AA18/$H$5,"") -> 0.052933392 | AO18: =IFERROR(AD18/$G$5,"") -> 0.0049261084 | AP18: =IFERROR(V18/$F$5,"") -> 0 | AQ18: =IFERROR(AA18/U18,"") -> 1.4117647 | AR18: =IFERROR(AD18/U18,"") -> 0.17647059 | AS18: =IFERROR(AD18-L18,"") -> 1 | AT18: =IFERROR(AA18-H18,"") -> 19 | AU18: =AF18*Settings!$B$7+AG18*Settings!$B$8+AE18*Settings!$B$9+AB18*Settings!$B$10+AC18*Settings!$B$11+X18*Settings!$B$12+Y18*Settings!$B$13+Z18*Settings!$B$14 -> 23.6
A19: RB | B19: Israel Abanikanda | C19: 5 | D19: 23 | E19: ACT | F19: 22 | J19: 11 | P19: 3.18 | Q19: 6.14 | R19: 0.636 | U19: 17 | AI19: =IFERROR(AB19/AA19,"") | AJ19: =IFERROR(AF19/AE19,"") | AK19: =IFERROR(AE19/AD19,"") | AL19: =IFERROR(X19/V19,"") | AM19: =IFERROR(W19/V19,"") | AN19: =IFERROR(AA19/$H$5,"") -> 0 | AO19: =IFERROR(AD19/$G$5,"") -> 0 | AP19: =IFERROR(V19/$F$5,"") -> 0 | AQ19: =IFERROR(AA19/U19,"") -> 0 | AR19: =IFERROR(AD19/U19,"") -> 0 | AS19: =IFERROR(AD19-L19,"") -> 0 | AT19: =IFERROR(AA19-H19,"") -> 0 | AU19: =AF19*Settings!$B$7+AG19*Settings!$B$8+AE19*Settings!$B$9+AB19*Settings!$B$10+AC19*Settings!$B$11+X19*Settings!$B$12+Y19*Settings!$B$13+Z19*Settings!$B$14 -> 0
A20: RB | B20: Dominic Richardson | C20: 6 | D20: 25 | E20: ACT | U20: 17 | AI20: =IFERROR(AB20/AA20,"") | AJ20: =IFERROR(AF20/AE20,"") | AK20: =IFERROR(AE20/AD20,"") | AL20: =IFERROR(X20/V20,"") | AM20: =IFERROR(W20/V20,"") | AN20: =IFERROR(AA20/$H$5,"") -> 0 | AO20: =IFERROR(AD20/$G$5,"") -> 0 | AP20: =IFERROR(V20/$F$5,"") -> 0 | AQ20: =IFERROR(AA20/U20,"") -> 0 | AR20: =IFERROR(AD20/U20,"") -> 0 | AS20: =IFERROR(AD20-L20,"") -> 0 | AT20: =IFERROR(AA20-H20,"") -> 0 | AU20: =AF20*Settings!$B$7+AG20*Settings!$B$8+AE20*Settings!$B$9+AB20*Settings!$B$10+AC20*Settings!$B$11+X20*Settings!$B$12+Y20*Settings!$B$13+Z20*Settings!$B$14 -> 0
A21: RB | B21: Other RBs | U21: 17 | AI21: =IFERROR(AB21/AA21,"") | AJ21: =IFERROR(AF21/AE21,"") | AK21: =IFERROR(AE21/AD21,"") | AL21: =IFERROR(X21/V21,"") | AM21: =IFERROR(W21/V21,"") | AN21: =IFERROR(AA21/$H$5,"") -> 0 | AO21: =IFERROR(AD21/$G$5,"") -> 0 | AP21: =IFERROR(V21/$F$5,"") -> 0 | AQ21: =IFERROR(AA21/U21,"") -> 0 | AR21: =IFERROR(AD21/U21,"") -> 0 | AS21: =IFERROR(AD21-L21,"") -> 0 | AT21: =IFERROR(AA21-H21,"") -> 0 | AU21: =AF21*Settings!$B$7+AG21*Settings!$B$8+AE21*Settings!$B$9+AB21*Settings!$B$10+AC21*Settings!$B$11+X21*Settings!$B$12+Y21*Settings!$B$13+Z21*Settings!$B$14 -> 0
A22: WR | B22: CeeDee Lamb | C22: 1 | D22: 27 | E22: ACT | F22: 14 | G22: 14 | H22: 1 | I22: 2 | J22: 181 | K22: 152 | L22: 117 | M22: 1077 | N22: DAL | O22: 14 | P22: 6.38 | Q22: 12.93 | R22: 0.691 | U22: 17 | V22: 0 | W22: 0 | X22: 0 | Y22: 0 | Z22: 0 | AA22: 3 | AB22: 17 | AC22: 0 | AD22: 151 | AE22: 98 | AF22: 1309 | AG22: 7 | AH22: kept | AI22: =IFERROR(AB22/AA22,"") -> 5.6666667 | AJ22: =IFERROR(AF22/AE22,"") -> 13.357143 | AK22: =IFERROR(AE22/AD22,"") -> 0.64900662 | AL22: =IFERROR(X22/V22,"") | AM22: =IFERROR(W22/V22,"") | AN22: =IFERROR(AA22/$H$5,"") -> 0.006616674 | AO22: =IFERROR(AD22/$G$5,"") -> 0.24794745 | AP22: =IFERROR(V22/$F$5,"") -> 0 | AQ22: =IFERROR(AA22/U22,"") -> 0.17647059 | AR22: =IFERROR(AD22/U22,"") -> 8.8823529 | AS22: =IFERROR(AD22-L22,"") -> 34 | AT22: =IFERROR(AA22-H22,"") -> 2 | AU22: =AF22*Settings!$B$7+AG22*Settings!$B$8+AE22*Settings!$B$9+AB22*Settings!$B$10+AC22*Settings!$B$11+X22*Settings!$B$12+Y22*Settings!$B$13+Z22*Settings!$B$14 -> 223.6
A23: WR | B23: George Pickens | C23: 2 | D23: 25 | E23: ACT | F23: 3 | G23: 2 | J23: 106 | K23: 103 | L23: 137 | M23: 1429 | N23: DAL | O23: 17 | P23: 2.4 | Q23: 16.13 | R23: 0.621 | U23: 17 | V23: 0 | W23: 0 | X23: 0 | Y23: 0 | Z23: 0 | AA23: 0 | AB23: 1 | AC23: 0 | AD23: 128 | AE23: 82 | AF23: 1205 | AG23: 8 | AH23: kept | AI23: =IFERROR(AB23/AA23,"") | AJ23: =IFERROR(AF23/AE23,"") -> 14.695122 | AK23: =IFERROR(AE23/AD23,"") -> 0.640625 | AL23: =IFERROR(X23/V23,"") | AM23: =IFERROR(W23/V23,"") | AN23: =IFERROR(AA23/$H$5,"") -> 0 | AO23: =IFERROR(AD23/$G$5,"") -> 0.21018062 | AP23: =IFERROR(V23/$F$5,"") -> 0 | AQ23: =IFERROR(AA23/U23,"") -> 0 | AR23: =IFERROR(AD23/U23,"") -> 7.5294118 | AS23: =IFERROR(AD23-L23,"") -> -9 | AT23: =IFERROR(AA23-H23,"") -> 0 | AU23: =AF23*Settings!$B$7+AG23*Settings!$B$8+AE23*Settings!$B$9+AB23*Settings!$B$10+AC23*Settings!$B$11+X23*Settings!$B$12+Y23*Settings!$B$13+Z23*Settings!$B$14 -> 209.6
A24: WR | B24: Ryan Flournoy | C24: 3 | D24: 26 | E24: ACT | H24: 4 | I24: 25 | K24: 14 | L24: 56 | M24: 475 | N24: DAL | O24: 16 | P24: 6.25 | Q24: 11.54 | R24: 0.714 | U24: 17 | V24: 0 | W24: 0 | X24: 0 | Y24: 0 | Z24: 0 | AA24: 2 | AB24: 10 | AC24: 0 | AD24: 58 | AE24: 41 | AF24: 470 | AG24: 3 | AH24: kept | AI24: =IFERROR(AB24/AA24,"") -> 5 | AJ24: =IFERROR(AF24/AE24,"") -> 11.463415 | AK24: =IFERROR(AE24/AD24,"") -> 0.70689655 | AL24: =IFERROR(X24/V24,"") | AM24: =IFERROR(W24/V24,"") | AN24: =IFERROR(AA24/$H$5,"") -> 0.004411116 | AO24: =IFERROR(AD24/$G$5,"") -> 0.095238095 | AP24: =IFERROR(V24/$F$5,"") -> 0 | AQ24: =IFERROR(AA24/U24,"") -> 0.11764706 | AR24: =IFERROR(AD24/U24,"") -> 3.4117647 | AS24: =IFERROR(AD24-L24,"") -> 2 | AT24: =IFERROR(AA24-H24,"") -> -2 | AU24: =AF24*Settings!$B$7+AG24*Settings!$B$8+AE24*Settings!$B$9+AB24*Settings!$B$10+AC24*Settings!$B$11+X24*Settings!$B$12+Y24*Settings!$B$13+Z24*Settings!$B$14 -> 86.5
A25: WR | B25: KaVontae Turpin | C25: 4 | D25: 30 | E25: ACT | F25: 11 | G25: 16 | H25: 17 | I25: 89 | J25: 18 | K25: 52 | L25: 38 | M25: 396 | N25: DAL | O25: 15 | P25: 6.61 | Q25: 13.67 | R25: 0.639 | U25: 17 | V25: 0 | W25: 0 | X25: 0 | Y25: 0 | Z25: 0 | AA25: 15 | AB25: 92 | AC25: 0 | AD25: 29 | AE25: 21 | AF25: 274 | AG25: 2 | AH25: kept | AI25: =IFERROR(AB25/AA25,"") -> 6.1333333 | AJ25: =IFERROR(AF25/AE25,"") -> 13.047619 | AK25: =IFERROR(AE25/AD25,"") -> 0.72413793 | AL25: =IFERROR(X25/V25,"") | AM25: =IFERROR(W25/V25,"") | AN25: =IFERROR(AA25/$H$5,"") -> 0.03308337 | AO25: =IFERROR(AD25/$G$5,"") -> 0.047619048 | AP25: =IFERROR(V25/$F$5,"") -> 0 | AQ25: =IFERROR(AA25/U25,"") -> 0.88235294 | AR25: =IFERROR(AD25/U25,"") -> 1.7058824 | AS25: =IFERROR(AD25-L25,"") -> -9 | AT25: =IFERROR(AA25-H25,"") -> -2 | AU25: =AF25*Settings!$B$7+AG25*Settings!$B$8+AE25*Settings!$B$9+AB25*Settings!$B$10+AC25*Settings!$B$11+X25*Settings!$B$12+Y25*Settings!$B$13+Z25*Settings!$B$14 -> 59.1
A26: WR | B26: Marquez Valdes-Scantling | C26: 5 | D26: 31 | E26: ACT | G26: 1 | J26: 42 | K26: 35 | L26: 8 | M26: 40 | N26: SF | O26: 5 | P26: 4 | Q26: 17.62 | R26: 0.494 | U26: 17 | V26: 0 | W26: 0 | X26: 0 | Y26: 0 | Z26: 0 | AA26: 0 | AB26: 1 | AC26: 0 | AD26: 10 | AE26: 7 | AF26: 107 | AG26: 1 | AH26: kept | AI26: =IFERROR(AB26/AA26,"") | AJ26: =IFERROR(AF26/AE26,"") -> 15.285714 | AK26: =IFERROR(AE26/AD26,"") -> 0.7 | AL26: =IFERROR(X26/V26,"") | AM26: =IFERROR(W26/V26,"") | AN26: =IFERROR(AA26/$H$5,"") -> 0 | AO26: =IFERROR(AD26/$G$5,"") -> 0.016420361 | AP26: =IFERROR(V26/$F$5,"") -> 0 | AQ26: =IFERROR(AA26/U26,"") -> 0 | AR26: =IFERROR(AD26/U26,"") -> 0.58823529 | AS26: =IFERROR(AD26-L26,"") -> 2 | AT26: =IFERROR(AA26-H26,"") -> 0 | AU26: =AF26*Settings!$B$7+AG26*Settings!$B$8+AE26*Settings!$B$9+AB26*Settings!$B$10+AC26*Settings!$B$11+X26*Settings!$B$12+Y26*Settings!$B$13+Z26*Settings!$B$14 -> 20.3
A27: WR | B27: Jonathan Mingo | C27: 6 | D27: 25 | E27: ACT | J27: 85 | K27: 16 | L27: 5 | M27: 25 | N27: DAL | O27: 6 | Q27: 9.98 | R27: 0.462 | U27: 17 | V27: 0 | W27: 0 | X27: 0 | Y27: 0 | Z27: 0 | AA27: 0 | AB27: 0 | AC27: 0 | AD27: 6 | AE27: 6 | AF27: 71 | AG27: 0 | AH27: kept | AI27: =IFERROR(AB27/AA27,"") | AJ27: =IFERROR(AF27/AE27,"") -> 11.833333 | AK27: =IFERROR(AE27/AD27,"") -> 1 | AL27: =IFERROR(X27/V27,"") | AM27: =IFERROR(W27/V27,"") | AN27: =IFERROR(AA27/$H$5,"") -> 0 | AO27: =IFERROR(AD27/$G$5,"") -> 0.0098522167 | AP27: =IFERROR(V27/$F$5,"") -> 0 | AQ27: =IFERROR(AA27/U27,"") -> 0 | AR27: =IFERROR(AD27/U27,"") -> 0.35294118 | AS27: =IFERROR(AD27-L27,"") -> 1 | AT27: =IFERROR(AA27-H27,"") -> 0 | AU27: =AF27*Settings!$B$7+AG27*Settings!$B$8+AE27*Settings!$B$9+AB27*Settings!$B$10+AC27*Settings!$B$11+X27*Settings!$B$12+Y27*Settings!$B$13+Z27*Settings!$B$14 -> 10.1
