Workbook

Sheet Start Here
B2: 2026 PROJECTIONS - START HERE
B4: How this works
B5: Team totals are already projected for you from 10 years of NFL data.
B6: Your job is one thing: decide what SHARE of each team's volume every
B7: player gets. Excel does the rest and updates as you type.
B9: Where to work
B10: The 32 team tabs (ARI ... WAS). One offense per screen:
B11: top - team control totals (editable, already filled in)
B12: then - LAST 3 YEARS: plays, pass rate, yards, TDs for context
B13: then - OUT / IN / STAFF: who left, who arrived, coaching notes
B14: middle - players, with 3 years of usage beside each input
B15: footer - SHARE TOTALS, which must read 100%
... B74: Rebuild any time with build_workbook.py - it backs up the old file first, but your edits are NOT carried over yet.

Sheet ARI
A1: ARI - 2026 projections
A3: TEAM TOTALS | C3: blue = edit; everything below divides these up
B4: Games | C4: Plays/G | D4: Plays | E4: Pass Rate | F4: Pass Att | G4: Targets | H4: Rush Att | I4: Pass Yds | J4: Pass TD | K4: Int | L4: Rush Yds | M4: Rush TD
B5: 17 | C5: 62.2 | D5: =C5*B5 | E5: 0.595 | F5: 585 | G5: =ROUND(F5*Settings!$B$4,0) | H5: 428 | I5: 3992 | J5: 25 | K5: 12 | L5: 1978 | M5: 14
A7: LAST 3 YEARS | B7: Season | C7: Plays | D7: Plays/G | E7: Pass Rate | F7: Pass Att | G7: Rush Att | H7: Pass Yds | I7: Rush Yds | J7: Pass TD | K7: Rush TD | L7: Y/A | M7: Y/C
B8: 2023 | C8: 1068 | D8: 62.8235 | E8: 0.559 | F8: 555 | G8: 471 | H8: 3430 | I8: 2365 | J8: 18 | K8: 17 | L8: 6.1802 | M8: 5.0212
B9: 2024 | C9: 1036 | D9: 60.9412 | E9: 0.5531 | F9: 543 | G9: 463 | H9: 3859 | I9: 2451 | J9: 21 | K9: 18 | L9: 7.1068 | M9: 5.2937
B10: 2025 | C10: 1074 | D10: 63.1765 | E10: 0.6592 | F10: 649 | G10: 366 | H10: 4354 | I10: 1583 | J10: 29 | K10: 9 | L10: 6.7088 | M10: 4.3251
A12: OUT | B12: 24% of targets and 70% of carries left. Share is team-relative - it does NOT follow the player. | H12: Michael Carter (7t/25r -> TEN), Bam Knight (5t/23r -> NOT ON ANY ROSTER), Emari Demercado (3t/12r -> KC), Kyler Murray (0t/8r -> MIN), Greg Dortch (5t/2r -> DET)
A13: IN | B13: 5 new: Tyler Allgeier (RB, from ATL - had 3% there), Kendrick Bourne (WR, from SF - had 10% there), Evan Hull (RB, from NO - had 0% there), Devin Duvernay (WR, from CHI - had 1% there), Gardner Minshew (QB, from KC)
A14: STAFF | B14: NEW HC Mike LaFleur + OC Nathaniel Hackett. Pass rate projected to DROP 69.4% -> 58%. Biggest scheme change in the league - revisit Pass Rate above.
A16: Pos | B16: Player | C16: Dep | D16: Age | E16: Status | F16: 2023 Tgt% | G16: 2024 Tgt% | H16: 2025 Tgt% | I16: 2025 Rush% | J16: Games | K16: Pass % | L16: Tgt % | M16: Rush % | N16: Catch % | O16: Rec Eff x | P16: Rush Eff x | Q16: RZ Tgt x | R16: RZ Rush x | S16: Pass Yds | T16: Pass TD | U16: Int | V16: Targets | W16: Rec | X16: Rec Yds | Y16: Yds/Rec | Z16: Rec TD | AA16: Rush Att | AB16: Rush Yds | AC16: Yds/Car | AD16: Rush TD | AE16: Half PPR
A17: QB | B17: Jacoby Brissett | C17: 1 | D17: 33 | E17: ACT | I17: 0.0992 | J17: 17 | K17: 0.92 | L17: 0.0007 | M17: 0.0727 | O17: 1 | P17: 1.06 | Q17: 1 | R17: 0.99 | S17: =IFERROR(K17*$I$5,0) | T17: =IFERROR(K17*$J$5,0) | U17: =IFERROR(K17*$K$5,0) | V17: =IFERROR(L17*$G$5,0) | W17: =IFERROR(V17*N17,0) | X17: =IFERROR(L17*O17/SUMPRODUCT($L$17:$L$41,$O$17:$O$41)*$I$5,0) | Y17: =IFERROR(X17/W17,0) | Z17: =IFERROR(L17*Q17/SUMPRODUCT($L$17:$L$41,$Q$17:$Q$41)*$J$5,0) | AA17: =IFERROR(M17*$H$5,0) | AB17: =IFERROR(M17*P17/SUMPRODUCT($M$17:$M$41,$P$17:$P$41)*$L$5,0) | AC17: =IFERROR(AB17/AA17,0) | AD17: =IFERROR(M17*R17/SUMPRODUCT($M$17:$M$41,$R$17:$R$41)*$M$5,0) | AE17: =X17*Settings!$B$7+Z17*Settings!$B$8+W17*Settings!$B$9+AB17*Settings!$B$10+AD17*Settings!$B$11+S17*Settings!$B$12+T17*Settings!$B$13+U17*Settings!$B$14
A18: QB | B18: Carson Beck | C18: 2 | D18: 23 | E18: role avg (rookie) | J18: 17 | K18: 0.068 | L18: 0.0018 | M18: 0.0221 | O18: 1 | P18: 1 | Q18: 1 | R18: 1 | S18: =IFERROR(K18*$I$5,0) | T18: =IFERROR(K18*$J$5,0) | U18: =IFERROR(K18*$K$5,0) | V18: =IFERROR(L18*$G$5,0) | W18: =IFERROR(V18*N18,0) | X18: =IFERROR(L18*O18/SUMPRODUCT($L$17:$L$41,$O$17:$O$41)*$I$5,0) | Y18: =IFERROR(X18/W18,0) | Z18: =IFERROR(L18*Q18/SUMPRODUCT($L$17:$L$41,$Q$17:$Q$41)*$J$5,0) | AA18: =IFERROR(M18*$H$5,0) | AB18: =IFERROR(M18*P18/SUMPRODUCT($M$17:$M$41,$P$17:$P$41)*$L$5,0) | AC18: =IFERROR(AB18/AA18,0) | AD18: =IFERROR(M18*R18/SUMPRODUCT($M$17:$M$41,$R$17:$R$41)*$M$5,0) | AE18: =X18*Settings!$B$7+Z18*Settings!$B$8+W18*Settings!$B$9+AB18*Settings!$B$10+AD18*Settings!$B$11+S18*Settings!$B$12+T18*Settings!$B$13+U18*Settings!$B$14
A19: QB | B19: Kedon Slovis | C19: 3 | D19: 25 | E19: ACT | J19: 17 | K19: 0.012 | L19: 0.0007 | M19: 0.0034 | O19: 1 | P19: 1 | Q19: 1 | R19: 1 | S19: =IFERROR(K19*$I$5,0) | T19: =IFERROR(K19*$J$5,0) | U19: =IFERROR(K19*$K$5,0) | V19: =IFERROR(L19*$G$5,0) | W19: =IFERROR(V19*N19,0) | X19: =IFERROR(L19*O19/SUMPRODUCT($L$17:$L$41,$O$17:$O$41)*$I$5,0) | Y19: =IFERROR(X19/W19,0) | Z19: =IFERROR(L19*Q19/SUMPRODUCT($L$17:$L$41,$Q$17:$Q$41)*$J$5,0) | AA19: =IFERROR(M19*$H$5,0) | AB19: =IFERROR(M19*P19/SUMPRODUCT($M$17:$M$41,$P$17:$P$41)*$L$5,0) | AC19: =IFERROR(AB19/AA19,0) | AD19: =IFERROR(M19*R19/SUMPRODUCT($M$17:$M$41,$R$17:$R$41)*$M$5,0) | AE19: =X19*Settings!$B$7+Z19*Settings!$B$8+W19*Settings!$B$9+AB19*Settings!$B$10+AD19*Settings!$B$11+S19*Settings!$B$12+T19*Settings!$B$13+U19*Settings!$B$14
A20: QB | B20: Other QBs | S20: =IFERROR(K20*$I$5,0) | T20: =IFERROR(K20*$J$5,0) | U20: =IFERROR(K20*$K$5,0) | V20: =IFERROR(L20*$G$5,0) | W20: =IFERROR(V20*N20,0) | X20: =IFERROR(L20*O20/SUMPRODUCT($L$17:$L$41,$O$17:$O$41)*$I$5,0) | Y20: =IFERROR(X20/W20,0) | Z20: =IFERROR(L20*Q20/SUMPRODUCT($L$17:$L$41,$Q$17:$Q$41)*$J$5,0) | AA20: =IFERROR(M20*$H$5,0) | AB20: =IFERROR(M20*P20/SUMPRODUCT($M$17:$M$41,$P$17:$P$41)*$L$5,0) | AC20: =IFERROR(AB20/AA20,0) | AD20: =IFERROR(M20*R20/SUMPRODUCT($M$17:$M$41,$R$17:$R$41)*$M$5,0) | AE20: =X20*Settings!$B$7+Z20*Settings!$B$8+W20*Settings!$B$9+AB20*Settings!$B$10+AD20*Settings!$B$11+S20*Settings!$B$12+T20*Settings!$B$13+U20*Settings!$B$14
A21: RB | B21: Jeremiyah Love | C21: 1 | D21: 21 | E21: role avg (rookie) | J21: 17 | L21: 0.0827 | M21: 0.3829 | N21: 0.75 | O21: 1 | P21: 1 | Q21: 1 | R21: 1 | S21: =IFERROR(K21*$I$5,0) | T21: =IFERROR(K21*$J$5,0) | U21: =IFERROR(K21*$K$5,0) | V21: =IFERROR(L21*$G$5,0) | W21: =IFERROR(V21*N21,0) | X21: =IFERROR(L21*O21/SUMPRODUCT($L$17:$L$41,$O$17:$O$41)*$I$5,0) | Y21: =IFERROR(X21/W21,0) | Z21: =IFERROR(L21*Q21/SUMPRODUCT($L$17:$L$41,$Q$17:$Q$41)*$J$5,0) | AA21: =IFERROR(M21*$H$5,0) | AB21: =IFERROR(M21*P21/SUMPRODUCT($M$17:$M$41,$P$17:$P$41)*$L$5,0) | AC21: =IFERROR(AB21/AA21,0) | AD21: =IFERROR(M21*R21/SUMPRODUCT($M$17:$M$41,$R$17:$R$41)*$M$5,0) | AE21: =X21*Settings!$B$7+Z21*Settings!$B$8+W21*Settings!$B$9+AB21*Settings!$B$10+AD21*Settings!$B$11+S21*Settings!$B$12+T21*Settings!$B$13+U21*Settings!$B$14
A22: RB | B22: Tyler Allgeier | C22: 2 | D22: 26 | E22: role avg (from ATL) | F22: 0.0453 | G22: 0.0241 | H22: 0.0308 | I22: 0.3082 | J22: 17 | L22: 0.0432 | M22: 0.1598 | N22: 0.894 | O22: 0.96 | P22: 0.89 | Q22: 0.93 | R22: 1.85 | S22: =IFERROR(K22*$I$5,0) | T22: =IFERROR(K22*$J$5,0) | U22: =IFERROR(K22*$K$5,0) | V22: =IFERROR(L22*$G$5,0) | W22: =IFERROR(V22*N22,0) | X22: =IFERROR(L22*O22/SUMPRODUCT($L$17:$L$41,$O$17:$O$41)*$I$5,0) | Y22: =IFERROR(X22/W22,0) | Z22: =IFERROR(L22*Q22/SUMPRODUCT($L$17:$L$41,$Q$17:$Q$41)*$J$5,0) | AA22: =IFERROR(M22*$H$5,0) | AB22: =IFERROR(M22*P22/SUMPRODUCT($M$17:$M$41,$P$17:$P$41)*$L$5,0) | AC22: =IFERROR(AB22/AA22,0) | AD22: =IFERROR(M22*R22/SUMPRODUCT($M$17:$M$41,$R$17:$R$41)*$M$5,0) | AE22: =X22*Settings!$B$7+Z22*Settings!$B$8+W22*Settings!$B$9+AB22*Settings!$B$10+AD22*Settings!$B$11+S22*Settings!$B$12+T22*Settings!$B$13+U22*Settings!$B$14
A23: RB | B23: James Conner | C23: 3 | D23: 31 | E23: QUESTIONABLE | F23: 0.0611 | G23: 0.1052 | H23: 0.0146 | I23: 0.0882 | J23: 17 | L23: 0.0505 | M23: 0.1784 | N23: 0.8497 | O23: 0.92 | P23: 0.88 | Q23: 1.11 | R23: 2.13 | S23: =IFERROR(K23*$I$5,0) | T23: =IFERROR(K23*$J$5,0) | U23: =IFERROR(K23*$K$5,0) | V23: =IFERROR(L23*$G$5,0) | W23: =IFERROR(V23*N23,0) | X23: =IFERROR(L23*O23/SUMPRODUCT($L$17:$L$41,$O$17:$O$41)*$I$5,0) | Y23: =IFERROR(X23/W23,0) | Z23: =IFERROR(L23*Q23/SUMPRODUCT($L$17:$L$41,$Q$17:$Q$41)*$J$5,0) | AA23: =IFERROR(M23*$H$5,0) | AB23: =IFERROR(M23*P23/SUMPRODUCT($M$17:$M$41,$P$17:$P$41)*$L$5,0) | AC23: =IFERROR(AB23/AA23,0) | AD23: =IFERROR(M23*R23/SUMPRODUCT($M$17:$M$41,$R$17:$R$41)*$M$5,0) | AE23: =X23*Settings!$B$7+Z23*Settings!$B$8+W23*Settings!$B$9+AB23*Settings!$B$10+AD23*Settings!$B$11+S23*Settings!$B$12+T23*Settings!$B$13+U23*Settings!$B$14
A24: RB | B24: Zonovan Knight | C24: 4 | D24: 25 | E24: ACT | F24: 0.0017 | H24: 0.0502 | I24: 0.2259 | J24: 17 | L24: 0.0305 | M24: 0.0558 | N24: 0.7278 | O24: 0.85 | P24: 0.81 | Q24: 1.39 | R24: 2.5 | S24: =IFERROR(K24*$I$5,0) | T24: =IFERROR(K24*$J$5,0) | U24: =IFERROR(K24*$K$5,0) | V24: =IFERROR(L24*$G$5,0) | W24: =IFERROR(V24*N24,0) | X24: =IFERROR(L24*O24/SUMPRODUCT($L$17:$L$41,$O$17:$O$41)*$I$5,0) | Y24: =IFERROR(X24/W24,0) | Z24: =IFERROR(L24*Q24/SUMPRODUCT($L$17:$L$41,$Q$17:$Q$41)*$J$5,0) | AA24: =IFERROR(M24*$H$5,0) | AB24: =IFERROR(M24*P24/SUMPRODUCT($M$17:$M$41,$P$17:$P$41)*$L$5,0) | AC24: =IFERROR(AB24/AA24,0) | AD24: =IFERROR(M24*R24/SUMPRODUCT($M$17:$M$41,$R$17:$R$41)*$M$5,0) | AE24: =X24*Settings!$B$7+Z24*Settings!$B$8+W24*Settings!$B$9+AB24*Settings!$B$10+AD24*Settings!$B$11+S24*Settings!$B$12+T24*Settings!$B$13+U24*Settings!$B$14
A25: RB | B25: Trey Benson | C25: 5 | D25: 24 | E25: ACT | G25: 0.0115 | H25: 0.0259 | I25: 0.0799 | J25: 17 | L25: 0.012 | M25: 0.0702 | N25: 0.9364 | O25: 1.02 | P25: 1 | Q25: 1.12 | R25: 0.89 | S25: =IFERROR(K25*$I$5,0) | T25: =IFERROR(K25*$J$5,0) | U25: =IFERROR(K25*$K$5,0) | V25: =IFERROR(L25*$G$5,0) | W25: =IFERROR(V25*N25,0) | X25: =IFERROR(L25*O25/SUMPRODUCT($L$17:$L$41,$O$17:$O$41)*$I$5,0) | Y25: =IFERROR(X25/W25,0) | Z25: =IFERROR(L25*Q25/SUMPRODUCT($L$17:$L$41,$Q$17:$Q$41)*$J$5,0) | AA25: =IFERROR(M25*$H$5,0) | AB25: =IFERROR(M25*P25/SUMPRODUCT($M$17:$M$41,$P$17:$P$41)*$L$5,0) | AC25: =IFERROR(AB25/AA25,0) | AD25: =IFERROR(M25*R25/SUMPRODUCT($M$17:$M$41,$R$17:$R$41)*$M$5,0) | AE25: =X25*Settings!$B$7+Z25*Settings!$B$8+W25*Settings!$B$9+AB25*Settings!$B$10+AD25*Settings!$B$11+S25*Settings!$B$12+T25*Settings!$B$13+U25*Settings!$B$14
A26: RB | B26: Corey Kiner | C26: 6 | D26: 24 | E26: ACT | H26: 0.0049 | I26: 0.0331 | J26: 17 | L26: 0.0043 | M26: 0.0209 | N26: 0.6667 | O26: 0.96 | P26: 1.04 | Q26: 1.14 | R26: 1.14 | S26: =IFERROR(K26*$I$5,0) | T26: =IFERROR(K26*$J$5,0) | U26: =IFERROR(K26*$K$5,0) | V26: =IFERROR(L26*$G$5,0) | W26: =IFERROR(V26*N26,0) | X26: =IFERROR(L26*O26/SUMPRODUCT($L$17:$L$41,$O$17:$O$41)*$I$5,0) | Y26: =IFERROR(X26/W26,0) | Z26: =IFERROR(L26*Q26/SUMPRODUCT($L$17:$L$41,$Q$17:$Q$41)*$J$5,0) | AA26: =IFERROR(M26*$H$5,0) | AB26: =IFERROR(M26*P26/SUMPRODUCT($M$17:$M$41,$P$17:$P$41)*$L$5,0) | AC26: =IFERROR(AB26/AA26,0) | AD26: =IFERROR(M26*R26/SUMPRODUCT($M$17:$M$41,$R$17:$R$41)*$M$5,0) | AE26: =X26*Settings!$B$7+Z26*Settings!$B$8+W26*Settings!$B$9+AB26*Settings!$B$10+AD26*Settings!$B$11+S26*Settings!$B$12+T26*Settings!$B$13+U26*Settings!$B$14
A27: RB | B27: Other RBs | S27: =IFERROR(K27*$I$5,0) | T27: =IFERROR(K27*$J$5,0) | U27: =IFERROR(K27*$K$5,0) | V27: =IFERROR(L27*$G$5,0) | W27: =IFERROR(V27*N27,0) | X27: =IFERROR(L27*O27/SUMPRODUCT($L$17:$L$41,$O$17:$O$41)*$I$5,0) | Y27: =IFERROR(X27/W27,0) | Z27: =IFERROR(L27*Q27/SUMPRODUCT($L$17:$L$41,$Q$17:$Q$41)*$J$5,0) | AA27: =IFERROR(M27*$H$5,0) | AB27: =IFERROR(M27*P27/SUMPRODUCT($M$17:$M$41,$P$17:$P$41)*$L$5,0) | AC27: =IFERROR(AB27/AA27,0) | AD27: =IFERROR(M27*R27/SUMPRODUCT($M$17:$M$41,$R$17:$R$41)*$M$5,0) | AE27: =X27*Settings!$B$7+Z27*Settings!$B$8+W27*Settings!$B$9+AB27*Settings!$B$10+AD27*Settings!$B$11+S27*Settings!$B$12+T27*Settings!$B$13+U27*Settings!$B$14
A28: WR | B28: Marvin Harrison | C28: 1 | D28: 23 | E28: ACT | G28: 0.2218 | H28: 0.1183 | J28: 17 | L28: 0.1736 | M28: 0.008 | N28: 0.5492 | O28: 1.09 | P28: 1 | Q28: 0.89 | R28: 1 | S28: =IFERROR(K28*$I$5,0) | T28: =IFERROR(K28*$J$5,0) | U28: =IFERROR(K28*$K$5,0) | V28: =IFERROR(L28*$G$5,0) | W28: =IFERROR(V28*N28,0) | X28: =IFERROR(L28*O28/SUMPRODUCT($L$17:$L$41,$O$17:$O$41)*$I$5,0) | Y28: =IFERROR(X28/W28,0) | Z28: =IFERROR(L28*Q28/SUMPRODUCT($L$17:$L$41,$Q$17:$Q$41)*$J$5,0) | AA28: =IFERROR(M28*$H$5,0) | AB28: =IFERROR(M28*P28/SUMPRODUCT($M$17:$M$41,$P$17:$P$41)*$L$5,0) | AC28: =IFERROR(AB28/AA28,0) | AD28: =IFERROR(M28*R28/SUMPRODUCT($M$17:$M$41,$R$17:$R$41)*$M$5,0) | AE28: =X28*Settings!$B$7+Z28*Settings!$B$8+W28*Settings!$B$9+AB28*Settings!$B$10+AD28*Settings!$B$11+S28*Settings!$B$12+T28*Settings!$B$13+U28*Settings!$B$14
A29: WR | B29: Michael Wilson | C29: 2 | D29: 26 | E29: ACT | F29: 0.1074 | G29: 0.1358 | H29: 0.2042 | J29: 17 | L29: 0.1441 | M29: 0.0029 | N29: 0.6379 | O29: 1.14 | P29: 1.01 | Q29: 0.94 | R29: 1 | S29: =IFERROR(K29*$I$5,0) | T29: =IFERROR(K29*$J$5,0) | U29: =IFERROR(K29*$K$5,0) | V29: =IFERROR(L29*$G$5,0) | W29: =IFERROR(V29*N29,0) | X29: =IFERROR(L29*O29/SUMPRODUCT($L$17:$L$41,$O$17:$O$41)*$I$5,0) | Y29: =IFERROR(X29/W29,0) | Z29: =IFERROR(L29*Q29/SUMPRODUCT($L$17:$L$41,$Q$17:$Q$41)*$J$5,0) | AA29: =IFERROR(M29*$H$5,0) | AB29: =IFERROR(M29*P29/SUMPRODUCT($M$17:$M$41,$P$17:$P$41)*$L$5,0) | AC29: =IFERROR(AB29/AA29,0) | AD29: =IFERROR(M29*R29/SUMPRODUCT($M$17:$M$41,$R$17:$R$41)*$M$5,0) | AE29: =X29*Settings!$B$7+Z29*Settings!$B$8+W29*Settings!$B$9+AB29*Settings!$B$10+AD29*Settings!$B$11+S29*Settings!$B$12+T29*Settings!$B$13+U29*Settings!$B$14
A30: WR | B30: Kendrick Bourne | C30: 3 | D30: 31 | E30: role avg (from SF) | F30: 0.1017 | G30: 0.076 | H30: 0.0964 | J30: 17 | L30: 0.0839 | M30: 0.0025 | N30: 0.7056 | O30: 1.19 | P30: 1.01 | Q30: 0.88 | R30: 1 | S30: =IFERROR(K30*$I$5,0) | T30: =IFERROR(K30*$J$5,0) | U30: =IFERROR(K30*$K$5,0) | V30: =IFERROR(L30*$G$5,0) | W30: =IFERROR(V30*N30,0) | X30: =IFERROR(L30*O30/SUMPRODUCT($L$17:$L$41,$O$17:$O$41)*$I$5,0) | Y30: =IFERROR(X30/W30,0) | Z30: =IFERROR(L30*Q30/SUMPRODUCT($L$17:$L$41,$Q$17:$Q$41)*$J$5,0) | AA30: =IFERROR(M30*$H$5,0) | AB30: =IFERROR(M30*P30/SUMPRODUCT($M$17:$M$41,$P$17:$P$41)*$L$5,0) | AC30: =IFERROR(AB30/AA30,0) | AD30: =IFERROR(M30*R30/SUMPRODUCT($M$17:$M$41,$R$17:$R$41)*$M$5,0) | AE30: =X30*Settings!$B$7+Z30*Settings!$B$8+W30*Settings!$B$9+AB30*Settings!$B$10+AD30*Settings!$B$11+S30*Settings!$B$12+T30*Settings!$B$13+U30*Settings!$B$14
A31: WR | B31: Xavier Weaver | C31: 4 | D31: 25 | E31: ACT | G31: 0.0038 | H31: 0.0211 | J31: 17 | L31: 0.0278 | M31: 0.0008 | N31: 0.5385 | O31: 0.9 | P31: 1 | Q31: 1.01 | R31: 1 | S31: =IFERROR(K31*$I$5,0) | T31: =IFERROR(K31*$J$5,0) | U31: =IFERROR(K31*$K$5,0) | V31: =IFERROR(L31*$G$5,0) | W31: =IFERROR(V31*N31,0) | X31: =IFERROR(L31*O31/SUMPRODUCT($L$17:$L$41,$O$17:$O$41)*$I$5,0) | Y31: =IFERROR(X31/W31,0) | Z31: =IFERROR(L31*Q31/SUMPRODUCT($L$17:$L$41,$Q$17:$Q$41)*$J$5,0) | AA31: =IFERROR(M31*$H$5,0) | AB31: =IFERROR(M31*P31/SUMPRODUCT($M$17:$M$41,$P$17:$P$41)*$L$5,0) | AC31: =IFERROR(AB31/AA31,0) | AD31: =IFERROR(M31*R31/SUMPRODUCT($M$17:$M$41,$R$17:$R$41)*$M$5,0) | AE31: =X31*Settings!$B$7+Z31*Settings!$B$8+W31*Settings!$B$9+AB31*Settings!$B$10+AD31*Settings!$B$11+S31*Settings!$B$12+T31*Settings!$B$13+U31*Settings!$B$14
A32: WR | B32: Reggie Virgil | C32: 5 | D32: 22 | E32: role avg (rookie) | J32: 17 | L32: 0.0192 | M32: 0.0019 | N32: 0.65 | O32: 1 | P32: 1 | Q32: 1 | R32: 1 | S32: =IFERROR(K32*$I$5,0) | T32: =IFERROR(K32*$J$5,0) | U32: =IFERROR(K32*$K$5,0) | V32: =IFERROR(L32*$G$5,0) | W32: =IFERROR(V32*N32,0) | X32: =IFERROR(L32*O32/SUMPRODUCT($L$17:$L$41,$O$17:$O$41)*$I$5,0) | Y32: =IFERROR(X32/W32,0) | Z32: =IFERROR(L32*Q32/SUMPRODUCT($L$17:$L$41,$Q$17:$Q$41)*$J$5,0) | AA32: =IFERROR(M32*$H$5,0) | AB32: =IFERROR(M32*P32/SUMPRODUCT($M$17:$M$41,$P$17:$P$41)*$L$5,0) | AC32: =IFERROR(AB32/AA32,0) | AD32: =IFERROR(M32*R32/SUMPRODUCT($M$17:$M$41,$R$17:$R$41)*$M$5,0) | AE32: =X32*Settings!$B$7+Z32*Settings!$B$8+W32*Settings!$B$9+AB32*Settings!$B$10+AD32*Settings!$B$11+S32*Settings!$B$12+T32*Settings!$B$13+U32*Settings!$B$14
A33: WR | B33: Simi Fehoko | C33: 6 | D33: 28 | E33: ACT | F33: 0.0033 | G33: 0.0326 | J33: 17 | L33: 0.0169 | M33: 0.0007 | N33: 0.4167 | O33: 0.92 | P33: 1 | Q33: 1 | R33: 1 | S33: =IFERROR(K33*$I$5,0) | T33: =IFERROR(K33*$J$5,0) | U33: =IFERROR(K33*$K$5,0) | V33: =IFERROR(L33*$G$5,0) | W33: =IFERROR(V33*N33,0) | X33: =IFERROR(L33*O33/SUMPRODUCT($L$17:$L$41,$O$17:$O$41)*$I$5,0) | Y33: =IFERROR(X33/W33,0) | Z33: =IFERROR(L33*Q33/SUMPRODUCT($L$17:$L$41,$Q$17:$Q$41)*$J$5,0) | AA33: =IFERROR(M33*$H$5,0) | AB33: =IFERROR(M33*P33/SUMPRODUCT($M$17:$M$41,$P$17:$P$41)*$L$5,0) | AC33: =IFERROR(AB33/AA33,0) | AD33: =IFERROR(M33*R33/SUMPRODUCT($M$17:$M$41,$R$17:$R$41)*$M$5,0) | AE33: =X33*Settings!$B$7+Z33*Settings!$B$8+W33*Settings!$B$9+AB33*Settings!$B$10+AD33*Settings!$B$11+S33*Settings!$B$12+T33*Settings!$B$13+U33*Settings!$B$14
A34: WR | B34: Devin Duvernay | C34: 7 | D34: 28 | E34: role avg (from CHI) | F34: 0.0189 | G34: 0.0307 | H34: 0.0094 | J34: 17 | L34: 0.0061 | M34: 0.0019 | N34: 0.4825 | O34: 0.89 | P34: 0.9 | Q34: 1.28 | R34: 1.5 | S34: =IFERROR(K34*$I$5,0) | T34: =IFERROR(K34*$J$5,0) | U34: =IFERROR(K34*$K$5,0) | V34: =IFERROR(L34*$G$5,0) | W34: =IFERROR(V34*N34,0) | X34: =IFERROR(L34*O34/SUMPRODUCT($L$17:$L$41,$O$17:$O$41)*$I$5,0) | Y34: =IFERROR(X34/W34,0) | Z34: =IFERROR(L34*Q34/SUMPRODUCT($L$17:$L$41,$Q$17:$Q$41)*$J$5,0) | AA34: =IFERROR(M34*$H$5,0) | AB34: =IFERROR(M34*P34/SUMPRODUCT($M$17:$M$41,$P$17:$P$41)*$L$5,0) | AC34: =IFERROR(AB34/AA34,0) | AD34: =IFERROR(M34*R34/SUMPRODUCT($M$17:$M$41,$R$17:$R$41)*$M$5,0) | AE34: =X34*Settings!$B$7+Z34*Settings!$B$8+W34*Settings!$B$9+AB34*Settings!$B$10+AD34*Settings!$B$11+S34*Settings!$B$12+T34*Settings!$B$13+U34*Settings!$B$14
A35: WR | B35: Ihmir Smith-Marsette | C35: 8 | D35: 26 | E35: ACT | F35: 0.0187 | J35: 17 | L35: 0.0117 | M35: 0.0098 | N35: 0.8 | O35: 0.95 | P35: 1.37 | Q35: 1 | R35: 1.05 | S35: =IFERROR(K35*$I$5,0) | T35: =IFERROR(K35*$J$5,0) | U35: =IFERROR(K35*$K$5,0) | V35: =IFERROR(L35*$G$5,0) | W35: =IFERROR(V35*N35,0) | X35: =IFERROR(L35*O35/SUMPRODUCT($L$17:$L$41,$O$17:$O$41)*$I$5,0) | Y35: =IFERROR(X35/W35,0) | Z35: =IFERROR(L35*Q35/SUMPRODUCT($L$17:$L$41,$Q$17:$Q$41)*$J$5,0) | AA35: =IFERROR(M35*$H$5,0) | AB35: =IFERROR(M35*P35/SUMPRODUCT($M$17:$M$41,$P$17:$P$41)*$L$5,0) | AC35: =IFERROR(AB35/AA35,0) | AD35: =IFERROR(M35*R35/SUMPRODUCT($M$17:$M$41,$R$17:$R$41)*$M$5,0) | AE35: =X35*Settings!$B$7+Z35*Settings!$B$8+W35*Settings!$B$9+AB35*Settings!$B$10+AD35*Settings!$B$11+S35*Settings!$B$12+T35*Settings!$B$13+U35*Settings!$B$14
A36: WR | B36: Other WRs | S36: =IFERROR(K36*$I$5,0) | T36: =IFERROR(K36*$J$5,0) | U36: =IFERROR(K36*$K$5,0) | V36: =IFERROR(L36*$G$5,0) | W36: =IFERROR(V36*N36,0) | X36: =IFERROR(L36*O36/SUMPRODUCT($L$17:$L$41,$O$17:$O$41)*$I$5,0) | Y36: =IFERROR(X36/W36,0) | Z36: =IFERROR(L36*Q36/SUMPRODUCT($L$17:$L$41,$Q$17:$Q$41)*$J$5,0) | AA36: =IFERROR(M36*$H$5,0) | AB36: =IFERROR(M36*P36/SUMPRODUCT($M$17:$M$41,$P$17:$P$41)*$L$5,0) | AC36: =IFERROR(AB36/AA36,0) | AD36: =IFERROR(M36*R36/SUMPRODUCT($M$17:$M$41,$R$17:$R$41)*$M$5,0) | AE36: =X36*Settings!$B$7+Z36*Settings!$B$8+W36*Settings!$B$9+AB36*Settings!$B$10+AD36*Settings!$B$11+S36*Settings!$B$12+T36*Settings!$B$13+U36*Settings!$B$14
A37: TE | B37: Trey McBride | C37: 1 | D37: 26 | E37: ACT | F37: 0.1963 | G37: 0.2811 | H37: 0.2739 | J37: 17 | L37: 0.2208 | M37: 0.0019 | N37: 0.7521 | O37: 1.07 | P37: 0.97 | Q37: 1.21 | R37: 1.57 | S37: =IFERROR(K37*$I$5,0) | T37: =IFERROR(K37*$J$5,0) | U37: =IFERROR(K37*$K$5,0) | V37: =IFERROR(L37*$G$5,0) | W37: =IFERROR(V37*N37,0) | X37: =IFERROR(L37*O37/SUMPRODUCT($L$17:$L$41,$O$17:$O$41)*$I$5,0) | Y37: =IFERROR(X37/W37,0) | Z37: =IFERROR(L37*Q37/SUMPRODUCT($L$17:$L$41,$Q$17:$Q$41)*$J$5,0) | AA37: =IFERROR(M37*$H$5,0) | AB37: =IFERROR(M37*P37/SUMPRODUCT($M$17:$M$41,$P$17:$P$41)*$L$5,0) | AC37: =IFERROR(AB37/AA37,0) | AD37: =IFERROR(M37*R37/SUMPRODUCT($M$17:$M$41,$R$17:$R$41)*$M$5,0) | AE37: =X37*Settings!$B$7+Z37*Settings!$B$8+W37*Settings!$B$9+AB37*Settings!$B$10+AD37*Settings!$B$11+S37*Settings!$B$12+T37*Settings!$B$13+U37*Settings!$B$14
A38: TE | B38: Elijah Higgins | C38: 2 | D38: 25 | E38: ACT | F38: 0.0352 | G38: 0.0459 | H38: 0.06 | J38: 17 | L38: 0.0497 | M38: 0.0008 | N38: 0.8078 | O38: 1.07 | P38: 1 | Q38: 0.94 | R38: 1 | S38: =IFERROR(K38*$I$5,0) | T38: =IFERROR(K38*$J$5,0) | U38: =IFERROR(K38*$K$5,0) | V38: =IFERROR(L38*$G$5,0) | W38: =IFERROR(V38*N38,0) | X38: =IFERROR(L38*O38/SUMPRODUCT($L$17:$L$41,$O$17:$O$41)*$I$5,0) | Y38: =IFERROR(X38/W38,0) | Z38: =IFERROR(L38*Q38/SUMPRODUCT($L$17:$L$41,$Q$17:$Q$41)*$J$5,0) | AA38: =IFERROR(M38*$H$5,0) | AB38: =IFERROR(M38*P38/SUMPRODUCT($M$17:$M$41,$P$17:$P$41)*$L$5,0) | AC38: =IFERROR(AB38/AA38,0) | AD38: =IFERROR(M38*R38/SUMPRODUCT($M$17:$M$41,$R$17:$R$41)*$M$5,0) | AE38: =X38*Settings!$B$7+Z38*Settings!$B$8+W38*Settings!$B$9+AB38*Settings!$B$10+AD38*Settings!$B$11+S38*Settings!$B$12+T38*Settings!$B$13+U38*Settings!$B$14
A39: TE | B39: Teagan Quitoriano | C39: 3 | D39: 26 | E39: ACT | F39: 0.0053 | J39: 17 | L39: 0.0099 | M39: 0.0008 | N39: 0.6667 | O39: 1.05 | P39: 1 | Q39: 1 | R39: 1 | S39: =IFERROR(K39*$I$5,0) | T39: =IFERROR(K39*$J$5,0) | U39: =IFERROR(K39*$K$5,0) | V39: =IFERROR(L39*$G$5,0) | W39: =IFERROR(V39*N39,0) | X39: =IFERROR(L39*O39/SUMPRODUCT($L$17:$L$41,$O$17:$O$41)*$I$5,0) | Y39: =IFERROR(X39/W39,0) | Z39: =IFERROR(L39*Q39/SUMPRODUCT($L$17:$L$41,$Q$17:$Q$41)*$J$5,0) | AA39: =IFERROR(M39*$H$5,0) | AB39: =IFERROR(M39*P39/SUMPRODUCT($M$17:$M$41,$P$17:$P$41)*$L$5,0) | AC39: =IFERROR(AB39/AA39,0) | AD39: =IFERROR(M39*R39/SUMPRODUCT($M$17:$M$41,$R$17:$R$41)*$M$5,0) | AE39: =X39*Settings!$B$7+Z39*Settings!$B$8+W39*Settings!$B$9+AB39*Settings!$B$10+AD39*Settings!$B$11+S39*Settings!$B$12+T39*Settings!$B$13+U39*Settings!$B$14
A40: TE | B40: Rivaldo Fairweather | C40: 4 | D40: 24 | E40: role avg (rookie) | J40: 17 | L40: 0.0099 | M40: 0.0019 | N40: 0.65 | O40: 1 | P40: 1 | Q40: 1 | R40: 1 | S40: =IFERROR(K40*$I$5,0) | T40: =IFERROR(K40*$J$5,0) | U40: =IFERROR(K40*$K$5,0) | V40: =IFERROR(L40*$G$5,0) | W40: =IFERROR(V40*N40,0) | X40: =IFERROR(L40*O40/SUMPRODUCT($L$17:$L$41,$O$17:$O$41)*$I$5,0) | Y40: =IFERROR(X40/W40,0) | Z40: =IFERROR(L40*Q40/SUMPRODUCT($L$17:$L$41,$Q$17:$Q$41)*$J$5,0) | AA40: =IFERROR(M40*$H$5,0) | AB40: =IFERROR(M40*P40/SUMPRODUCT($M$17:$M$41,$P$17:$P$41)*$L$5,0) | AC40: =IFERROR(AB40/AA40,0) | AD40: =IFERROR(M40*R40/SUMPRODUCT($M$17:$M$41,$R$17:$R$41)*$M$5,0) | AE40: =X40*Settings!$B$7+Z40*Settings!$B$8+W40*Settings!$B$9+AB40*Settings!$B$10+AD40*Settings!$B$11+S40*Settings!$B$12+T40*Settings!$B$13+U40*Settings!$B$14
A41: TE | B41: Other TEs | S41: =IFERROR(K41*$I$5,0) | T41: =IFERROR(K41*$J$5,0) | U41: =IFERROR(K41*$K$5,0) | V41: =IFERROR(L41*$G$5,0) | W41: =IFERROR(V41*N41,0) | X41: =IFERROR(L41*O41/SUMPRODUCT($L$17:$L$41,$O$17:$O$41)*$I$5,0) | Y41: =IFERROR(X41/W41,0) | Z41: =IFERROR(L41*Q41/SUMPRODUCT($L$17:$L$41,$Q$17:$Q$41)*$J$5,0) | AA41: =IFERROR(M41*$H$5,0) | AB41: =IFERROR(M41*P41/SUMPRODUCT($M$17:$M$41,$P$17:$P$41)*$L$5,0) | AC41: =IFERROR(AB41/AA41,0) | AD41: =IFERROR(M41*R41/SUMPRODUCT($M$17:$M$41,$R$17:$R$41)*$M$5,0) | AE41: =X41*Settings!$B$7+Z41*Settings!$B$8+W41*Settings!$B$9+AB41*Settings!$B$10+AD41*Settings!$B$11+S41*Settings!$B$12+T41*Settings!$B$13+U41*Settings!$B$14
B43: SHARE TOTALS - must equal 100% | E43: each column is a share of this team's season total - it must add to 100% | K43: =SUM(K17:K41) | L43: =SUM(L17:L41) | M43: =SUM(M17:M41) | S43: =SUM(S17:S41) | T43: =SUM(T17:T41) | U43: =SUM(U17:U41) | V43: =SUM(V17:V41) | W43: =SUM(W17:W41) | X43: =SUM(X17:X41) | Y43: =SUM(Y17:Y41) | Z43: =SUM(Z17:Z41) | ... AE43: =SUM(AE17:AE41)
B45: Green = balanced. Red = your shares don't add to 100%; player totals won't match the team totals until they do.

Sheet ATL
A1: ATL - 2026 projections
A3: TEAM TOTALS | C3: blue = edit; everything below divides these up
B4: Games | C4: Plays/G | D4: Plays | E4: Pass Rate | F4: Pass Att | G4: Targets | H4: Rush Att | I4: Pass Yds | J4: Pass TD | K4: Int | L4: Rush Yds | M4: Rush TD
B5: 17 | C5: 62.5 | D5: =C5*B5 | E5: 0.5475 | F5: 548 | G5: =ROUND(F5*Settings!$B$4,0) | H5: 481 | I5: 3893 | J5: 21 | K5: 13 | L5: 2108 | M5: 16
A7: LAST 3 YEARS | B7: Season | C7: Plays | D7: Plays/G | E7: Pass Rate | F7: Pass Att | G7: Rush Att | H7: Pass Yds | I7: Rush Yds | J7: Pass TD | K7: Rush TD | L7: Y/A | M7: Y/C
B8: 2023 | C8: 1092 | D8: 64.2353 | E8: 0.522 | F8: 530 | G8: 522 | H8: 3775 | I8: 2159 | J8: 17 | K8: 14 | L8: 7.1226 | M8: 4.136
B9: 2024 | C9: 1086 | D9: 63.8824 | E9: 0.5442 | F9: 559 | G9: 495 | H9: 4283 | I9: 2219 | J9: 21 | K9: 18 | L9: 7.6619 | M9: 4.4828
B10: 2025 | C10: 1048 | D10: 61.6471 | E10: 0.5448 | F10: 545 | G10: 477 | H10: 3703 | I10: 2138 | J10: 19 | K10: 17 | L10: 6.7945 | M10: 4.4822
A12: OUT | B12: 29% of targets and 33% of carries left. Share is team-relative - it does NOT follow the player. | H12: Tyler Allgeier (3t/31r -> ARI), Darnell Mooney (14t/0r -> NYG), David Sills V (7t/0r -> TB), Casey Washington (3t/0r -> CAR), KhaDarel Hodge (2t/0r -> SF)
A13: IN | B13: 8 new: Brian Robinson (RB, from SF - had 2% there), Olamide Zaccheaus (WR, from CHI - had 12% there), Jahan Dotson (WR, from PHI - had 8% there), Austin Hooper (TE, from NE - had 5% there), Tua Tagovailoa (QB, from MIA)
A14: STAFF | B14: NEW HC Kevin Stefanski + OC Tommy Rees. Zone-heavy run game; little pass-rate change expected. Emphasis on Robinson touches.
A16: Pos | B16: Player | C16: Dep | D16: Age | E16: Status | F16: 2023 Tgt% | G16: 2024 Tgt% | H16: 2025 Tgt% | I16: 2025 Rush% | J16: Games | K16: Pass % | L16: Tgt % | M16: Rush % | N16: Catch % | O16: Rec Eff x | P16: Rush Eff x | Q16: RZ Tgt x | R16: RZ Rush x | S16: Pass Yds | T16: Pass TD | U16: Int | V16: Targets | W16: Rec | X16: Rec Yds | Y16: Yds/Rec | Z16: Rec TD | AA16: Rush Att | AB16: Rush Yds | AC16: Yds/Car | AD16: Rush TD | AE16: Half PPR
A17: QB | B17: Tua Tagovailoa | C17: 1 | D17: 28 | E17: role avg (from MIA) | I17: 0.0377 | J17: 17 | K17: 0.92 | L17: 0.0018 | M17: 0.0651 | O17: 1 | P17: 0.86 | Q17: 1 | R17: 0.9 | S17: =IFERROR(K17*$I$5,0) | T17: =IFERROR(K17*$J$5,0) | U17: =IFERROR(K17*$K$5,0) | V17: =IFERROR(L17*$G$5,0) | W17: =IFERROR(V17*N17,0) | X17: =IFERROR(L17*O17/SUMPRODUCT($L$17:$L$41,$O$17:$O$41)*$I$5,0) | Y17: =IFERROR(X17/W17,0) | Z17: =IFERROR(L17*Q17/SUMPRODUCT($L$17:$L$41,$Q$17:$Q$41)*$J$5,0) | AA17: =IFERROR(M17*$H$5,0) | AB17: =IFERROR(M17*P17/SUMPRODUCT($M$17:$M$41,$P$17:$P$41)*$L$5,0) | AC17: =IFERROR(AB17/AA17,0) | AD17: =IFERROR(M17*R17/SUMPRODUCT($M$17:$M$41,$R$17:$R$41)*$M$5,0) | AE17: =X17*Settings!$B$7+Z17*Settings!$B$8+W17*Settings!$B$9+AB17*Settings!$B$10+AD17*Settings!$B$11+S17*Settings!$B$12+T17*Settings!$B$13+U17*Settings!$B$14
A18: QB | B18: Michael Penix | C18: 2 | D18: 26 | E18: QUESTIONABLE | I18: 0.0302 | J18: 17 | K18: 0.068 | L18: 0.0008 | M18: 0.0198 | O18: 1 | P18: 0.97 | Q18: 1 | R18: 1.23 | S18: =IFERROR(K18*$I$5,0) | T18: =IFERROR(K18*$J$5,0) | U18: =IFERROR(K18*$K$5,0) | V18: =IFERROR(L18*$G$5,0) | W18: =IFERROR(V18*N18,0) | X18: =IFERROR(L18*O18/SUMPRODUCT($L$17:$L$41,$O$17:$O$41)*$I$5,0) | Y18: =IFERROR(X18/W18,0) | Z18: =IFERROR(L18*Q18/SUMPRODUCT($L$17:$L$41,$Q$17:$Q$41)*$J$5,0) | AA18: =IFERROR(M18*$H$5,0) | AB18: =IFERROR(M18*P18/SUMPRODUCT($M$17:$M$41,$P$17:$P$41)*$L$5,0) | AC18: =IFERROR(AB18/AA18,0) | AD18: =IFERROR(M18*R18/SUMPRODUCT($M$17:$M$41,$R$17:$R$41)*$M$5,0) | AE18: =X18*Settings!$B$7+Z18*Settings!$B$8+W18*Settings!$B$9+AB18*Settings!$B$10+AD18*Settings!$B$11+S18*Settings!$B$12+T18*Settings!$B$13+U18*Settings!$B$14
A19: QB | B19: Cooper Rush | C19: 3 | D19: 32 | E19: role avg (from BAL) | I19: 0.002 | J19: 17 | K19: 0.012 | L19: 0.0018 | M19: 0.0057 | O19: 1 | P19: 1 | Q19: 1 | R19: 2.5 | S19: =IFERROR(K19*$I$5,0) | T19: =IFERROR(K19*$J$5,0) | U19: =IFERROR(K19*$K$5,0) | V19: =IFERROR(L19*$G$5,0) | W19: =IFERROR(V19*N19,0) | X19: =IFERROR(L19*O19/SUMPRODUCT($L$17:$L$41,$O$17:$O$41)*$I$5,0) | Y19: =IFERROR(X19/W19,0) | Z19: =IFERROR(L19*Q19/SUMPRODUCT($L$17:$L$41,$Q$17:$Q$41)*$J$5,0) | AA19: =IFERROR(M19*$H$5,0) | AB19: =IFERROR(M19*P19/SUMPRODUCT($M$17:$M$41,$P$17:$P$41)*$L$5,0) | AC19: =IFERROR(AB19/AA19,0) | AD19: =IFERROR(M19*R19/SUMPRODUCT($M$17:$M$41,$R$17:$R$41)*$M$5,0) | AE19: =X19*Settings!$B$7+Z19*Settings!$B$8+W19*Settings!$B$9+AB19*Settings!$B$10+AD19*Settings!$B$11+S19*Settings!$B$12+T19*Settings!$B$13+U19*Settings!$B$14
A20: QB | B20: Other QBs | S20: =IFERROR(K20*$I$5,0) | T20: =IFERROR(K20*$J$5,0) | U20: =IFERROR(K20*$K$5,0) | V20: =IFERROR(L20*$G$5,0) | W20: =IFERROR(V20*N20,0) | X20: =IFERROR(L20*O20/SUMPRODUCT($L$17:$L$41,$O$17:$O$41)*$I$5,0) | Y20: =IFERROR(X20/W20,0) | Z20: =IFERROR(L20*Q20/SUMPRODUCT($L$17:$L$41,$Q$17:$Q$41)*$J$5,0) | AA20: =IFERROR(M20*$H$5,0) | AB20: =IFERROR(M20*P20/SUMPRODUCT($M$17:$M$41,$P$17:$P$41)*$L$5,0) | AC20: =IFERROR(AB20/AA20,0) | AD20: =IFERROR(M20*R20/SUMPRODUCT($M$17:$M$41,$R$17:$R$41)*$M$5,0) | AE20: =X20*Settings!$B$7+Z20*Settings!$B$8+W20*Settings!$B$9+AB20*Settings!$B$10+AD20*Settings!$B$11+S20*Settings!$B$12+T20*Settings!$B$13+U20*Settings!$B$14
A21: RB | B21: Bijan Robinson | C21: 1 | D21: 24 | E21: ACT | F21: 0.1693 | G21: 0.1336 | H21: 0.1985 | I21: 0.6185 | J21: 17 | L21: 0.1525 | M21: 0.5358 | N21: 0.7725 | O21: 0.95 | P21: 1.08 | Q21: 1.09 | R21: 0.91 | S21: =IFERROR(K21*$I$5,0) | T21: =IFERROR(K21*$J$5,0) | U21: =IFERROR(K21*$K$5,0) | V21: =IFERROR(L21*$G$5,0) | W21: =IFERROR(V21*N21,0) | X21: =IFERROR(L21*O21/SUMPRODUCT($L$17:$L$41,$O$17:$O$41)*$I$5,0) | Y21: =IFERROR(X21/W21,0) | Z21: =IFERROR(L21*Q21/SUMPRODUCT($L$17:$L$41,$Q$17:$Q$41)*$J$5,0) | AA21: =IFERROR(M21*$H$5,0) | AB21: =IFERROR(M21*P21/SUMPRODUCT($M$17:$M$41,$P$17:$P$41)*$L$5,0) | AC21: =IFERROR(AB21/AA21,0) | AD21: =IFERROR(M21*R21/SUMPRODUCT($M$17:$M$41,$R$17:$R$41)*$M$5,0) | AE21: =X21*Settings!$B$7+Z21*Settings!$B$8+W21*Settings!$B$9+AB21*Settings!$B$10+AD21*Settings!$B$11+S21*Settings!$B$12+T21*Settings!$B$13+U21*Settings!$B$14
A22: RB | B22: Brian Robinson | C22: 2 | D22: 27 | E22: role avg (from SF) | F22: 0.0715 | G22: 0.0496 | H22: 0.0218 | I22: 0.1991 | J22: 17 | L22: 0.0378 | M22: 0.2558 | N22: 0.7349 | O22: 0.79 | P22: 1 | Q22: 1.16 | R22: 0.91 | S22: =IFERROR(K22*$I$5,0) | T22: =IFERROR(K22*$J$5,0) | U22: =IFERROR(K22*$K$5,0) | V22: =IFERROR(L22*$G$5,0) | W22: =IFERROR(V22*N22,0) | X22: =IFERROR(L22*O22/SUMPRODUCT($L$17:$L$41,$O$17:$O$41)*$I$5,0) | Y22: =IFERROR(X22/W22,0) | Z22: =IFERROR(L22*Q22/SUMPRODUCT($L$17:$L$41,$Q$17:$Q$41)*$J$5,0) | AA22: =IFERROR(M22*$H$5,0) | AB22: =IFERROR(M22*P22/SUMPRODUCT($M$17:$M$41,$P$17:$P$41)*$L$5,0) | AC22: =IFERROR(AB22/AA22,0) | AD22: =IFERROR(M22*R22/SUMPRODUCT($M$17:$M$41,$R$17:$R$41)*$M$5,0) | AE22: =X22*Settings!$B$7+Z22*Settings!$B$8+W22*Settings!$B$9+AB22*Settings!$B$10+AD22*Settings!$B$11+S22*Settings!$B$12+T22*Settings!$B$13+U22*Settings!$B$14
A23: RB | B23: Tyler Goodson | C23: 3 | D23: 25 | E23: role avg (from IND) | F23: 0.0165 | G23: 0.0305 | H23: 0.0057 | I23: 0.0209 | J23: 17 | L23: 0.0203 | M23: 0.0568 | N23: 0.6945 | O23: 0.83 | P23: 0.93 | Q23: 1.05 | R23: 0.98 | S23: =IFERROR(K23*$I$5,0) | T23: =IFERROR(K23*$J$5,0) | U23: =IFERROR(K23*$K$5,0) | V23: =IFERROR(L23*$G$5,0) | W23: =IFERROR(V23*N23,0) | X23: =IFERROR(L23*O23/SUMPRODUCT($L$17:$L$41,$O$17:$O$41)*$I$5,0) | Y23: =IFERROR(X23/W23,0) | Z23: =IFERROR(L23*Q23/SUMPRODUCT($L$17:$L$41,$Q$17:$Q$41)*$J$5,0) | AA23: =IFERROR(M23*$H$5,0) | AB23: =IFERROR(M23*P23/SUMPRODUCT($M$17:$M$41,$P$17:$P$41)*$L$5,0) | AC23: =IFERROR(AB23/AA23,0) | AD23: =IFERROR(M23*R23/SUMPRODUCT($M$17:$M$41,$R$17:$R$41)*$M$5,0) | AE23: =X23*Settings!$B$7+Z23*Settings!$B$8+W23*Settings!$B$9+AB23*Settings!$B$10+AD23*Settings!$B$11+S23*Settings!$B$12+T23*Settings!$B$13+U23*Settings!$B$14
A24: RB | B24: Nathan Carter | C24: 4 | D24: 24 | E24: ACT | I24: 0.0194 | J24: 17 | L24: 0.0026 | M24: 0.0203 | O24: 1 | P24: 1.14 | Q24: 1 | R24: 1 | S24: =IFERROR(K24*$I$5,0) | T24: =IFERROR(K24*$J$5,0) | U24: =IFERROR(K24*$K$5,0) | V24: =IFERROR(L24*$G$5,0) | W24: =IFERROR(V24*N24,0) | X24: =IFERROR(L24*O24/SUMPRODUCT($L$17:$L$41,$O$17:$O$41)*$I$5,0) | Y24: =IFERROR(X24/W24,0) | Z24: =IFERROR(L24*Q24/SUMPRODUCT($L$17:$L$41,$Q$17:$Q$41)*$J$5,0) | AA24: =IFERROR(M24*$H$5,0) | AB24: =IFERROR(M24*P24/SUMPRODUCT($M$17:$M$41,$P$17:$P$41)*$L$5,0) | AC24: =IFERROR(AB24/AA24,0) | AD24: =IFERROR(M24*R24/SUMPRODUCT($M$17:$M$41,$R$17:$R$41)*$M$5,0) | AE24: =X24*Settings!$B$7+Z24*Settings!$B$8+W24*Settings!$B$9+AB24*Settings!$B$10+AD24*Settings!$B$11+S24*Settings!$B$12+T24*Settings!$B$13+U24*Settings!$B$14
A25: RB | B25: Cash Jones | C25: 5 | D25: 24 | E25: role avg (rookie) | J25: 17 | L25: 0.0046 | M25: 0.0112 | N25: 0.75 | O25: 1 | P25: 1 | Q25: 1 | R25: 1 | S25: =IFERROR(K25*$I$5,0) | T25: =IFERROR(K25*$J$5,0) | U25: =IFERROR(K25*$K$5,0) | V25: =IFERROR(L25*$G$5,0) | W25: =IFERROR(V25*N25,0) | X25: =IFERROR(L25*O25/SUMPRODUCT($L$17:$L$41,$O$17:$O$41)*$I$5,0) | Y25: =IFERROR(X25/W25,0) | Z25: =IFERROR(L25*Q25/SUMPRODUCT($L$17:$L$41,$Q$17:$Q$41)*$J$5,0) | AA25: =IFERROR(M25*$H$5,0) | AB25: =IFERROR(M25*P25/SUMPRODUCT($M$17:$M$41,$P$17:$P$41)*$L$5,0) | AC25: =IFERROR(AB25/AA25,0) | AD25: =IFERROR(M25*R25/SUMPRODUCT($M$17:$M$41,$R$17:$R$41)*$M$5,0) | AE25: =X25*Settings!$B$7+Z25*Settings!$B$8+W25*Settings!$B$9+AB25*Settings!$B$10+AD25*Settings!$B$11+S25*Settings!$B$12+T25*Settings!$B$13+U25*Settings!$B$14
A26: RB
A27: RB | B27: Other RBs | S27: =IFERROR(K27*$I$5,0) | T27: =IFERROR(K27*$J$5,0) | U27: =IFERROR(K27*$K$5,0) | V27: =IFERROR(L27*$G$5,0) | W27: =IFERROR(V27*N27,0) | X27: =IFERROR(L27*O27/SUMPRODUCT($L$17:$L$41,$O$17:$O$41)*$I$5,0) | Y27: =IFERROR(X27/W27,0) | Z27: =IFERROR(L27*Q27/SUMPRODUCT($L$17:$L$41,$Q$17:$Q$41)*$J$5,0) | AA27: =IFERROR(M27*$H$5,0) | AB27: =IFERROR(M27*P27/SUMPRODUCT($M$17:$M$41,$P$17:$P$41)*$L$5,0) | AC27: =IFERROR(AB27/AA27,0) | AD27: =IFERROR(M27*R27/SUMPRODUCT($M$17:$M$41,$R$17:$R$41)*$M$5,0) | AE27: =X27*Settings!$B$7+Z27*Settings!$B$8+W27*Settings!$B$9+AB27*Settings!$B$10+AD27*Settings!$B$11+S27*Settings!$B$12+T27*Settings!$B$13+U27*Settings!$B$14
A28: WR | B28: Drake London | C28: 1 | D28: 25 | E28: ACT | F28: 0.2165 | G28: 0.2931 | H28: 0.2158 | J28: 17 | L28: 0.2331 | M28: 0.0061 | N28: 0.6208 | O28: 1.08 | P28: 1 | Q28: 1.21 | R28: 1 | S28: =IFERROR(K28*$I$5,0) | T28: =IFERROR(K28*$J$5,0) | U28: =IFERROR(K28*$K$5,0) | V28: =IFERROR(L28*$G$5,0) | W28: =IFERROR(V28*N28,0) | X28: =IFERROR(L28*O28/SUMPRODUCT($L$17:$L$41,$O$17:$O$41)*$I$5,0) | Y28: =IFERROR(X28/W28,0) | Z28: =IFERROR(L28*Q28/SUMPRODUCT($L$17:$L$41,$Q$17:$Q$41)*$J$5,0) | AA28: =IFERROR(M28*$H$5,0) | AB28: =IFERROR(M28*P28/SUMPRODUCT($M$17:$M$41,$P$17:$P$41)*$L$5,0) | AC28: =IFERROR(AB28/AA28,0) | AD28: =IFERROR(M28*R28/SUMPRODUCT($M$17:$M$41,$R$17:$R$41)*$M$5,0) | AE28: =X28*Settings!$B$7+Z28*Settings!$B$8+W28*Settings!$B$9+AB28*Settings!$B$10+AD28*Settings!$B$11+S28*Settings!$B$12+T28*Settings!$B$13+U28*Settings!$B$14
A29: WR | B29: Zachariah Branch | C29: 2 | D29: 22 | E29: role avg (rookie) | J29: 17 | L29: 0.1337 | M29: 0.0043 | N29: 0.65 | O29: 1 | P29: 1 | Q29: 1 | R29: 1 | S29: =IFERROR(K29*$I$5,0) | T29: =IFERROR(K29*$J$5,0) | U29: =IFERROR(K29*$K$5,0) | V29: =IFERROR(L29*$G$5,0) | W29: =IFERROR(V29*N29,0) | X29: =IFERROR(L29*O29/SUMPRODUCT($L$17:$L$41,$O$17:$O$41)*$I$5,0) | Y29: =IFERROR(X29/W29,0) | Z29: =IFERROR(L29*Q29/SUMPRODUCT($L$17:$L$41,$Q$17:$Q$41)*$J$5,0) | AA29: =IFERROR(M29*$H$5,0) | AB29: =IFERROR(M29*P29/SUMPRODUCT($M$17:$M$41,$P$17:$P$41)*$L$5,0) | AC29: =IFERROR(AB29/AA29,0) | AD29: =IFERROR(M29*R29/SUMPRODUCT($M$17:$M$41,$R$17:$R$41)*$M$5,0) | AE29: =X29*Settings!$B$7+Z29*Settings!$B$8+W29*Settings!$B$9+AB29*Settings!$B$10+AD29*Settings!$B$11+S29*Settings!$B$12+T29*Settings!$B$13+U29*Settings!$B$14
A30: WR | B30: Jahan Dotson | C30: 3 | D30: 26 | E30: role avg (from PHI) | F30: 0.1381 | G30: 0.0789 | H30: 0.0776 | J30: 17 | L30: 0.0904 | M30: 0.0037 | N30: 0.5408 | O30: 0.93 | P30: 1.07 | Q30: 0.91 | R30: 1 | S30: =IFERROR(K30*$I$5,0) | T30: =IFERROR(K30*$J$5,0) | U30: =IFERROR(K30*$K$5,0) | V30: =IFERROR(L30*$G$5,0) | W30: =IFERROR(V30*N30,0) | X30: =IFERROR(L30*O30/SUMPRODUCT($L$17:$L$41,$O$17:$O$41)*$I$5,0) | Y30: =IFERROR(X30/W30,0) | Z30: =IFERROR(L30*Q30/SUMPRODUCT($L$17:$L$41,$Q$17:$Q$41)*$J$5,0) | AA30: =IFERROR(M30*$H$5,0) | AB30: =IFERROR(M30*P30/SUMPRODUCT($M$17:$M$41,$P$17:$P$41)*$L$5,0) | AC30: =IFERROR(AB30/AA30,0) | AD30: =IFERROR(M30*R30/SUMPRODUCT($M$17:$M$41,$R$17:$R$41)*$M$5,0) | AE30: =X30*Settings!$B$7+Z30*Settings!$B$8+W30*Settings!$B$9+AB30*Settings!$B$10+AD30*Settings!$B$11+S30*Settings!$B$12+T30*Settings!$B$13+U30*Settings!$B$14
A31: WR | B31: Olamide Zaccheaus | C31: 4 | D31: 29 | E31: role avg (from CHI) | F31: 0.0381 | G31: 0.127 | H31: 0.1222 | I31: 0.0081 | J31: 17 | L31: 0.0368 | M31: 0.0023 | N31: 0.6113 | O31: 0.88 | P31: 1.05 | Q31: 2.37 | R31: 1 | S31: =IFERROR(K31*$I$5,0) | T31: =IFERROR(K31*$J$5,0) | U31: =IFERROR(K31*$K$5,0) | V31: =IFERROR(L31*$G$5,0) | W31: =IFERROR(V31*N31,0) | X31: =IFERROR(L31*O31/SUMPRODUCT($L$17:$L$41,$O$17:$O$41)*$I$5,0) | Y31: =IFERROR(X31/W31,0) | Z31: =IFERROR(L31*Q31/SUMPRODUCT($L$17:$L$41,$Q$17:$Q$41)*$J$5,0) | AA31: =IFERROR(M31*$H$5,0) | AB31: =IFERROR(M31*P31/SUMPRODUCT($M$17:$M$41,$P$17:$P$41)*$L$5,0) | AC31: =IFERROR(AB31/AA31,0) | AD31: =IFERROR(M31*R31/SUMPRODUCT($M$17:$M$41,$R$17:$R$41)*$M$5,0) | AE31: =X31*Settings!$B$7+Z31*Settings!$B$8+W31*Settings!$B$9+AB31*Settings!$B$10+AD31*Settings!$B$11+S31*Settings!$B$12+T31*Settings!$B$13+U31*Settings!$B$14
A32: WR | B32: Dylan Drummond | C32: 5 | D32: 26 | E32: ACT | H32: 0.0212 | J32: 17 | L32: 0.0188 | M32: 0.0009 | N32: 0.6364 | O32: 0.83 | P32: 1 | Q32: 1.49 | R32: 1 | S32: =IFERROR(K32*$I$5,0) | T32: =IFERROR(K32*$J$5,0) | U32: =IFERROR(K32*$K$5,0) | V32: =IFERROR(L32*$G$5,0) | W32: =IFERROR(V32*N32,0) | X32: =IFERROR(L32*O32/SUMPRODUCT($L$17:$L$41,$O$17:$O$41)*$I$5,0) | Y32: =IFERROR(X32/W32,0) | Z32: =IFERROR(L32*Q32/SUMPRODUCT($L$17:$L$41,$Q$17:$Q$41)*$J$5,0) | AA32: =IFERROR(M32*$H$5,0) | AB32: =IFERROR(M32*P32/SUMPRODUCT($M$17:$M$41,$P$17:$P$41)*$L$5,0) | AC32: =IFERROR(AB32/AA32,0) | AD32: =IFERROR(M32*R32/SUMPRODUCT($M$17:$M$41,$R$17:$R$41)*$M$5,0) | AE32: =X32*Settings!$B$7+Z32*Settings!$B$8+W32*Settings!$B$9+AB32*Settings!$B$10+AD32*Settings!$B$11+S32*Settings!$B$12+T32*Settings!$B$13+U32*Settings!$B$14
A33: WR | B33: Chris Blair | C33: 6 | D33: 28 | E33: ACT | G33: 0.0037 | J33: 17 | L33: 0.0068 | M33: 0.0008 | N33: 0.5 | O33: 1.01 | P33: 1 | Q33: 1 | R33: 1 | S33: =IFERROR(K33*$I$5,0) | T33: =IFERROR(K33*$J$5,0) | U33: =IFERROR(K33*$K$5,0) | V33: =IFERROR(L33*$G$5,0) | W33: =IFERROR(V33*N33,0) | X33: =IFERROR(L33*O33/SUMPRODUCT($L$17:$L$41,$O$17:$O$41)*$I$5,0) | Y33: =IFERROR(X33/W33,0) | Z33: =IFERROR(L33*Q33/SUMPRODUCT($L$17:$L$41,$Q$17:$Q$41)*$J$5,0) | AA33: =IFERROR(M33*$H$5,0) | AB33: =IFERROR(M33*P33/SUMPRODUCT($M$17:$M$41,$P$17:$P$41)*$L$5,0) | AC33: =IFERROR(AB33/AA33,0) | AD33: =IFERROR(M33*R33/SUMPRODUCT($M$17:$M$41,$R$17:$R$41)*$M$5,0) | AE33: =X33*Settings!$B$7+Z33*Settings!$B$8+W33*Settings!$B$9+AB33*Settings!$B$10+AD33*Settings!$B$11+S33*Settings!$B$12+T33*Settings!$B$13+U33*Settings!$B$14
A34: WR | B34: Antwane Wells | C34: 7 | D34: 25 | E34: role avg (rookie) | J34: 17 | L34: 0.006 | M34: 0.0022 | N34: 0.65 | O34: 1 | P34: 1 | Q34: 1 | R34: 1 | S34: =IFERROR(K34*$I$5,0) | T34: =IFERROR(K34*$J$5,0) | U34: =IFERROR(K34*$K$5,0) | V34: =IFERROR(L34*$G$5,0) | W34: =IFERROR(V34*N34,0) | X34: =IFERROR(L34*O34/SUMPRODUCT($L$17:$L$41,$O$17:$O$41)*$I$5,0) | Y34: =IFERROR(X34/W34,0) | Z34: =IFERROR(L34*Q34/SUMPRODUCT($L$17:$L$41,$Q$17:$Q$41)*$J$5,0) | AA34: =IFERROR(M34*$H$5,0) | AB34: =IFERROR(M34*P34/SUMPRODUCT($M$17:$M$41,$P$17:$P$41)*$L$5,0) | AC34: =IFERROR(AB34/AA34,0) | AD34: =IFERROR(M34*R34/SUMPRODUCT($M$17:$M$41,$R$17:$R$41)*$M$5,0) | AE34: =X34*Settings!$B$7+Z34*Settings!$B$8+W34*Settings!$B$9+AB34*Settings!$B$10+AD34*Settings!$B$11+S34*Settings!$B$12+T34*Settings!$B$13+U34*Settings!$B$14
A35: WR | B35: Vinny Anthony | C35: 8 | E35: role avg (rookie) | J35: 17 | L35: 0.0049 | M35: 0.002 | N35: 0.65 | O35: 1 | P35: 1 | Q35: 1 | R35: 1 | S35: =IFERROR(K35*$I$5,0) | T35: =IFERROR(K35*$J$5,0) | U35: =IFERROR(K35*$K$5,0) | V35: =IFERROR(L35*$G$5,0) | W35: =IFERROR(V35*N35,0) | X35: =IFERROR(L35*O35/SUMPRODUCT($L$17:$L$41,$O$17:$O$41)*$I$5,0) | Y35: =IFERROR(X35/W35,0) | Z35: =IFERROR(L35*Q35/SUMPRODUCT($L$17:$L$41,$Q$17:$Q$41)*$J$5,0) | AA35: =IFERROR(M35*$H$5,0) | AB35: =IFERROR(M35*P35/SUMPRODUCT($M$17:$M$41,$P$17:$P$41)*$L$5,0) | AC35: =IFERROR(AB35/AA35,0) | AD35: =IFERROR(M35*R35/SUMPRODUCT($M$17:$M$41,$R$17:$R$41)*$M$5,0) | AE35: =X35*Settings!$B$7+Z35*Settings!$B$8+W35*Settings!$B$9+AB35*Settings!$B$10+AD35*Settings!$B$11+S35*Settings!$B$12+T35*Settings!$B$13+U35*Settings!$B$14
A36: WR | B36: Other WRs | S36: =IFERROR(K36*$I$5,0) | T36: =IFERROR(K36*$J$5,0) | U36: =IFERROR(K36*$K$5,0) | V36: =IFERROR(L36*$G$5,0) | W36: =IFERROR(V36*N36,0) | X36: =IFERROR(L36*O36/SUMPRODUCT($L$17:$L$41,$O$17:$O$41)*$I$5,0) | Y36: =IFERROR(X36/W36,0) | Z36: =IFERROR(L36*Q36/SUMPRODUCT($L$17:$L$41,$Q$17:$Q$41)*$J$5,0) | AA36: =IFERROR(M36*$H$5,0) | AB36: =IFERROR(M36*P36/SUMPRODUCT($M$17:$M$41,$P$17:$P$41)*$L$5,0) | AC36: =IFERROR(AB36/AA36,0) | AD36: =IFERROR(M36*R36/SUMPRODUCT($M$17:$M$41,$R$17:$R$41)*$M$5,0) | AE36: =X36*Settings!$B$7+Z36*Settings!$B$8+W36*Settings!$B$9+AB36*Settings!$B$10+AD36*Settings!$B$11+S36*Settings!$B$12+T36*Settings!$B$13+U36*Settings!$B$14
A37: TE | B37: Kyle Pitts | C37: 1 | D37: 25 | E37: ACT | F37: 0.1772 | G37: 0.1373 | H37: 0.2274 | J37: 17 | L37: 0.1751 | M37: 0.0022 | N37: 0.6812 | O37: 1.05 | P37: 1 | Q37: 1.02 | R37: 1 | S37: =IFERROR(K37*$I$5,0) | T37: =IFERROR(K37*$J$5,0) | U37: =IFERROR(K37*$K$5,0) | V37: =IFERROR(L37*$G$5,0) | W37: =IFERROR(V37*N37,0) | X37: =IFERROR(L37*O37/SUMPRODUCT($L$17:$L$41,$O$17:$O$41)*$I$5,0) | Y37: =IFERROR(X37/W37,0) | Z37: =IFERROR(L37*Q37/SUMPRODUCT($L$17:$L$41,$Q$17:$Q$41)*$J$5,0) | AA37: =IFERROR(M37*$H$5,0) | AB37: =IFERROR(M37*P37/SUMPRODUCT($M$17:$M$41,$P$17:$P$41)*$L$5,0) | AC37: =IFERROR(AB37/AA37,0) | AD37: =IFERROR(M37*R37/SUMPRODUCT($M$17:$M$41,$R$17:$R$41)*$M$5,0) | AE37: =X37*Settings!$B$7+Z37*Settings!$B$8+W37*Settings!$B$9+AB37*Settings!$B$10+AD37*Settings!$B$11+S37*Settings!$B$12+T37*Settings!$B$13+U37*Settings!$B$14
A38: TE | B38: Austin Hooper | C38: 2 | D38: 31 | E38: role avg (from NE) | F38: 0.0584 | G38: 0.118 | H38: 0.0539 | J38: 17 | L38: 0.052 | M38: 0.002 | N38: 0.7935 | O38: 1.08 | P38: 1 | Q38: 1.29 | R38: 1 | S38: =IFERROR(K38*$I$5,0) | T38: =IFERROR(K38*$J$5,0) | U38: =IFERROR(K38*$K$5,0) | V38: =IFERROR(L38*$G$5,0) | W38: =IFERROR(V38*N38,0) | X38: =IFERROR(L38*O38/SUMPRODUCT($L$17:$L$41,$O$17:$O$41)*$I$5,0) | Y38: =IFERROR(X38/W38,0) | Z38: =IFERROR(L38*Q38/SUMPRODUCT($L$17:$L$41,$Q$17:$Q$41)*$J$5,0) | AA38: =IFERROR(M38*$H$5,0) | AB38: =IFERROR(M38*P38/SUMPRODUCT($M$17:$M$41,$P$17:$P$41)*$L$5,0) | AC38: =IFERROR(AB38/AA38,0) | AD38: =IFERROR(M38*R38/SUMPRODUCT($M$17:$M$41,$R$17:$R$41)*$M$5,0) | AE38: =X38*Settings!$B$7+Z38*Settings!$B$8+W38*Settings!$B$9+AB38*Settings!$B$10+AD38*Settings!$B$11+S38*Settings!$B$12+T38*Settings!$B$13+U38*Settings!$B$14
A39: TE | B39: Charlie Woerner | C39: 3 | D39: 28 | E39: ACT | F39: 0.0064 | G39: 0.0223 | H39: 0.0173 | J39: 17 | L39: 0.0157 | M39: 0.0009 | N39: 0.8237 | O39: 0.92 | P39: 1 | Q39: 1 | R39: 1 | S39: =IFERROR(K39*$I$5,0) | T39: =IFERROR(K39*$J$5,0) | U39: =IFERROR(K39*$K$5,0) | V39: =IFERROR(L39*$G$5,0) | W39: =IFERROR(V39*N39,0) | X39: =IFERROR(L39*O39/SUMPRODUCT($L$17:$L$41,$O$17:$O$41)*$I$5,0) | Y39: =IFERROR(X39/W39,0) | Z39: =IFERROR(L39*Q39/SUMPRODUCT($L$17:$L$41,$Q$17:$Q$41)*$J$5,0) | AA39: =IFERROR(M39*$H$5,0) | AB39: =IFERROR(M39*P39/SUMPRODUCT($M$17:$M$41,$P$17:$P$41)*$L$5,0) | AC39: =IFERROR(AB39/AA39,0) | AD39: =IFERROR(M39*R39/SUMPRODUCT($M$17:$M$41,$R$17:$R$41)*$M$5,0) | AE39: =X39*Settings!$B$7+Z39*Settings!$B$8+W39*Settings!$B$9+AB39*Settings!$B$10+AD39*Settings!$B$11+S39*Settings!$B$12+T39*Settings!$B$13+U39*Settings!$B$14
A40: TE | B40: Joshua Simon | C40: 4 | D40: 25 | E40: role avg (rookie) | J40: 17 | L40: 0.0044 | M40: 0.0022 | N40: 0.65 | O40: 1 | P40: 1 | Q40: 1 | R40: 1 | S40: =IFERROR(K40*$I$5,0) | T40: =IFERROR(K40*$J$5,0) | U40: =IFERROR(K40*$K$5,0) | V40: =IFERROR(L40*$G$5,0) | W40: =IFERROR(V40*N40,0) | X40: =IFERROR(L40*O40/SUMPRODUCT($L$17:$L$41,$O$17:$O$41)*$I$5,0) | Y40: =IFERROR(X40/W40,0) | Z40: =IFERROR(L40*Q40/SUMPRODUCT($L$17:$L$41,$Q$17:$Q$41)*$J$5,0) | AA40: =IFERROR(M40*$H$5,0) | AB40: =IFERROR(M40*P40/SUMPRODUCT($M$17:$M$41,$P$17:$P$41)*$L$5,0) | AC40: =IFERROR(AB40/AA40,0) | AD40: =IFERROR(M40*R40/SUMPRODUCT($M$17:$M$41,$R$17:$R$41)*$M$5,0) | AE40: =X40*Settings!$B$7+Z40*Settings!$B$8+W40*Settings!$B$9+AB40*Settings!$B$10+AD40*Settings!$B$11+S40*Settings!$B$12+T40*Settings!$B$13+U40*Settings!$B$14
A41: TE | B41: Other TEs | S41: =IFERROR(K41*$I$5,0) | T41: =IFERROR(K41*$J$5,0) | U41: =IFERROR(K41*$K$5,0) | V41: =IFERROR(L41*$G$5,0) | W41: =IFERROR(V41*N41,0) | X41: =IFERROR(L41*O41/SUMPRODUCT($L$17:$L$41,$O$17:$O$41)*$I$5,0) | Y41: =IFERROR(X41/W41,0) | Z41: =IFERROR(L41*Q41/SUMPRODUCT($L$17:$L$41,$Q$17:$Q$41)*$J$5,0) | AA41: =IFERROR(M41*$H$5,0) | AB41: =IFERROR(M41*P41/SUMPRODUCT($M$17:$M$41,$P$17:$P$41)*$L$5,0) | AC41: =IFERROR(AB41/AA41,0) | AD41: =IFERROR(M41*R41/SUMPRODUCT($M$17:$M$41,$R$17:$R$41)*$M$5,0) | AE41: =X41*Settings!$B$7+Z41*Settings!$B$8+W41*Settings!$B$9+AB41*Settings!$B$10+AD41*Settings!$B$11+S41*Settings!$B$12+T41*Settings!$B$13+U41*Settings!$B$14
B43: SHARE TOTALS - must equal 100% | E43: each column is a share of this team's season total - it must add to 100% | K43: =SUM(K17:K41) | L43: =SUM(L17:L41) | M43: =SUM(M17:M41) | S43: =SUM(S17:S41) | T43: =SUM(T17:T41) | U43: =SUM(U17:U41) | V43: =SUM(V17:V41) | W43: =SUM(W17:W41) | X43: =SUM(X17:X41) | Y43: =SUM(Y17:Y41) | Z43: =SUM(Z17:Z41) | ... AE43: =SUM(AE17:AE41)
B45: Green = balanced. Red = your shares don't add to 100%; player totals won't match the team totals until they do.

Sheet BAL
A1: BAL - 2026 projections
A3: TEAM TOTALS | C3: blue = edit; everything below divides these up
B4: Games | C4: Plays/G | D4: Plays | E4: Pass Rate | F4: Pass Att | G4: Targets | H4: Rush Att | I4: Pass Yds | J4: Pass TD | K4: Int | L4: Rush Yds | M4: Rush TD
B5: 17 | C5: 60.7 | D5: =C5*B5 | E5: 0.5063 | F5: 483 | G5: =ROUND(F5*Settings!$B$4,0) | H5: 509 | I5: 3763 | J5: 28 | K5: 10 | L5: 2551 | M5: 20
A7: LAST 3 YEARS | B7: Season | C7: Plays | D7: Plays/G | E7: Pass Rate | F7: Pass Att | G7: Rush Att | H7: Pass Yds | I7: Rush Yds | J7: Pass TD | K7: Rush TD | L7: Y/A | M7: Y/C
B8: 2023 | C8: 1076 | D8: 63.2941 | E8: 0.4972 | F8: 494 | G8: 541 | H8: 3881 | I8: 2661 | J8: 27 | K8: 26 | L8: 7.8563 | M8: 4.9187
B9: 2024 | C9: 1055 | D9: 62.0588 | E9: 0.4749 | F9: 477 | G9: 554 | H9: 4189 | I9: 3189 | J9: 41 | K9: 21 | L9: 8.782 | M9: 5.7563
B10: 2025 | C10: 974 | D10: 57.2941 | E10: 0.4795 | F10: 422 | G10: 507 | H10: 3278 | I10: 2662 | J10: 23 | K10: 23 | L10: 7.7678 | M10: 5.2505
A12: OUT | B12: 27% of targets and 12% of carries left. Share is team-relative - it does NOT follow the player. | H12: Keaton Mitchell (3t/12r -> LAC), DeAndre Hopkins (10t/0r -> NOT ON ANY ROSTER), Isaiah Likely (9t/0r -> NYG), Charlie Kolar (4t/0r -> LAC), Tylan Wallace (2t/0r -> CLE)
A13: IN | B13: 2 new: Chris Moore (WR, from WAS - had 5% there), Durham Smythe (TE, from CHI - had 1% there)
A14: STAFF | B14: NEW HC Jesse Minter + OC Declan Doyle. More explosive plays expected - Doyle brings creativity and detail.
A16: Pos | B16: Player | C16: Dep | D16: Age | E16: Status | F16: 2023 Tgt% | G16: 2024 Tgt% | H16: 2025 Tgt% | I16: 2025 Rush% | J16: Games | K16: Pass % | L16: Tgt % | M16: Rush % | N16: Catch % | O16: Rec Eff x | P16: Rush Eff x | Q16: RZ Tgt x | R16: RZ Rush x | S16: Pass Yds | T16: Pass TD | U16: Int | V16: Targets | W16: Rec | X16: Rec Yds | Y16: Yds/Rec | Z16: Rec TD | AA16: Rush Att | AB16: Rush Yds | AC16: Yds/Car | AD16: Rush TD | AE16: Half PPR
A17: QB | B17: Lamar Jackson | C17: 1 | D17: 29 | E17: ACT | I17: 0.1184 | J17: 17 | K17: 0.92 | L17: 0.0008 | M17: 0.1607 | O17: 1 | P17: 1.13 | Q17: 1 | R17: 1.05 | S17: =IFERROR(K17*$I$5,0) | T17: =IFERROR(K17*$J$5,0) | U17: =IFERROR(K17*$K$5,0) | V17: =IFERROR(L17*$G$5,0) | W17: =IFERROR(V17*N17,0) | X17: =IFERROR(L17*O17/SUMPRODUCT($L$17:$L$41,$O$17:$O$41)*$I$5,0) | Y17: =IFERROR(X17/W17,0) | Z17: =IFERROR(L17*Q17/SUMPRODUCT($L$17:$L$41,$Q$17:$Q$41)*$J$5,0) | AA17: =IFERROR(M17*$H$5,0) | AB17: =IFERROR(M17*P17/SUMPRODUCT($M$17:$M$41,$P$17:$P$41)*$L$5,0) | AC17: =IFERROR(AB17/AA17,0) | AD17: =IFERROR(M17*R17/SUMPRODUCT($M$17:$M$41,$R$17:$R$41)*$M$5,0) | AE17: =X17*Settings!$B$7+Z17*Settings!$B$8+W17*Settings!$B$9+AB17*Settings!$B$10+AD17*Settings!$B$11+S17*Settings!$B$12+T17*Settings!$B$13+U17*Settings!$B$14
A18: QB | B18: Tyler Huntley | C18: 2 | D18: 28 | E18: ACT | I18: 0.0388 | J18: 17 | K18: 0.068 | L18: 0.0008 | M18: 0.0298 | O18: 1 | P18: 1.16 | Q18: 1 | R18: 1.29 | S18: =IFERROR(K18*$I$5,0) | T18: =IFERROR(K18*$J$5,0) | U18: =IFERROR(K18*$K$5,0) | V18: =IFERROR(L18*$G$5,0) | W18: =IFERROR(V18*N18,0) | X18: =IFERROR(L18*O18/SUMPRODUCT($L$17:$L$41,$O$17:$O$41)*$I$5,0) | Y18: =IFERROR(X18/W18,0) | Z18: =IFERROR(L18*Q18/SUMPRODUCT($L$17:$L$41,$Q$17:$Q$41)*$J$5,0) | AA18: =IFERROR(M18*$H$5,0) | AB18: =IFERROR(M18*P18/SUMPRODUCT($M$17:$M$41,$P$17:$P$41)*$L$5,0) | AC18: =IFERROR(AB18/AA18,0) | AD18: =IFERROR(M18*R18/SUMPRODUCT($M$17:$M$41,$R$17:$R$41)*$M$5,0) | AE18: =X18*Settings!$B$7+Z18*Settings!$B$8+W18*Settings!$B$9+AB18*Settings!$B$10+AD18*Settings!$B$11+S18*Settings!$B$12+T18*Settings!$B$13+U18*Settings!$B$14
A19: QB | B19: Skylar Thompson | C19: 3 | D19: 29 | E19: ACT | J19: 17 | K19: 0.012 | L19: 0.0008 | M19: 0.0035 | O19: 1 | P19: 1 | Q19: 1 | R19: 1 | S19: =IFERROR(K19*$I$5,0) | T19: =IFERROR(K19*$J$5,0) | U19: =IFERROR(K19*$K$5,0) | V19: =IFERROR(L19*$G$5,0) | W19: =IFERROR(V19*N19,0) | X19: =IFERROR(L19*O19/SUMPRODUCT($L$17:$L$41,$O$17:$O$41)*$I$5,0) | Y19: =IFERROR(X19/W19,0) | Z19: =IFERROR(L19*Q19/SUMPRODUCT($L$17:$L$41,$Q$17:$Q$41)*$J$5,0) | AA19: =IFERROR(M19*$H$5,0) | AB19: =IFERROR(M19*P19/SUMPRODUCT($M$17:$M$41,$P$17:$P$41)*$L$5,0) | AC19: =IFERROR(AB19/AA19,0) | AD19: =IFERROR(M19*R19/SUMPRODUCT($M$17:$M$41,$R$17:$R$41)*$M$5,0) | AE19: =X19*Settings!$B$7+Z19*Settings!$B$8+W19*Settings!$B$9+AB19*Settings!$B$10+AD19*Settings!$B$11+S19*Settings!$B$12+T19*Settings!$B$13+U19*Settings!$B$14
A20: QB | B20: Other QBs | S20: =IFERROR(K20*$I$5,0) | T20: =IFERROR(K20*$J$5,0) | U20: =IFERROR(K20*$K$5,0) | V20: =IFERROR(L20*$G$5,0) | W20: =IFERROR(V20*N20,0) | X20: =IFERROR(L20*O20/SUMPRODUCT($L$17:$L$41,$O$17:$O$41)*$I$5,0) | Y20: =IFERROR(X20/W20,0) | Z20: =IFERROR(L20*Q20/SUMPRODUCT($L$17:$L$41,$Q$17:$Q$41)*$J$5,0) | AA20: =IFERROR(M20*$H$5,0) | AB20: =IFERROR(M20*P20/SUMPRODUCT($M$17:$M$41,$P$17:$P$41)*$L$5,0) | AC20: =IFERROR(AB20/AA20,0) | AD20: =IFERROR(M20*R20/SUMPRODUCT($M$17:$M$41,$R$17:$R$41)*$M$5,0) | AE20: =X20*Settings!$B$7+Z20*Settings!$B$8+W20*Settings!$B$9+AB20*Settings!$B$10+AD20*Settings!$B$11+S20*Settings!$B$12+T20*Settings!$B$13+U20*Settings!$B$14
A21: RB | B21: Derrick Henry | C21: 1 | D21: 32 | E21: ACT | F21: 0.0753 | G21: 0.0481 | H21: 0.0516 | I21: 0.6265 | J21: 17 | L21: 0.0694 | M21: 0.5414 | N21: 0.7718 | O21: 0.94 | P21: 0.97 | Q21: 0.93 | R21: 1.09 | S21: =IFERROR(K21*$I$5,0) | T21: =IFERROR(K21*$J$5,0) | U21: =IFERROR(K21*$K$5,0) | V21: =IFERROR(L21*$G$5,0) | W21: =IFERROR(V21*N21,0) | X21: =IFERROR(L21*O21/SUMPRODUCT($L$17:$L$41,$O$17:$O$41)*$I$5,0) | Y21: =IFERROR(X21/W21,0) | Z21: =IFERROR(L21*Q21/SUMPRODUCT($L$17:$L$41,$Q$17:$Q$41)*$J$5,0) | AA21: =IFERROR(M21*$H$5,0) | AB21: =IFERROR(M21*P21/SUMPRODUCT($M$17:$M$41,$P$17:$P$41)*$L$5,0) | AC21: =IFERROR(AB21/AA21,0) | AD21: =IFERROR(M21*R21/SUMPRODUCT($M$17:$M$41,$R$17:$R$41)*$M$5,0) | AE21: =X21*Settings!$B$7+Z21*Settings!$B$8+W21*Settings!$B$9+AB21*Settings!$B$10+AD21*Settings!$B$11+S21*Settings!$B$12+T21*Settings!$B$13+U21*Settings!$B$14
A22: RB | B22: Justice Hill | C22: 2 | D22: 28 | E22: ACT | F22: 0.0819 | G22: 0.1116 | H22: 0.0663 | I22: 0.0367 | J22: 17 | L22: 0.0686 | M22: 0.128 | N22: 0.7789 | O22: 0.84 | P22: 0.93 | Q22: 0.95 | R22: 0.79 | S22: =IFERROR(K22*$I$5,0) | T22: =IFERROR(K22*$J$5,0) | U22: =IFERROR(K22*$K$5,0) | V22: =IFERROR(L22*$G$5,0) | W22: =IFERROR(V22*N22,0) | X22: =IFERROR(L22*O22/SUMPRODUCT($L$17:$L$41,$O$17:$O$41)*$I$5,0) | Y22: =IFERROR(X22/W22,0) | Z22: =IFERROR(L22*Q22/SUMPRODUCT($L$17:$L$41,$Q$17:$Q$41)*$J$5,0) | AA22: =IFERROR(M22*$H$5,0) | AB22: =IFERROR(M22*P22/SUMPRODUCT($M$17:$M$41,$P$17:$P$41)*$L$5,0) | AC22: =IFERROR(AB22/AA22,0) | AD22: =IFERROR(M22*R22/SUMPRODUCT($M$17:$M$41,$R$17:$R$41)*$M$5,0) | AE22: =X22*Settings!$B$7+Z22*Settings!$B$8+W22*Settings!$B$9+AB22*Settings!$B$10+AD22*Settings!$B$11+S22*Settings!$B$12+T22*Settings!$B$13+U22*Settings!$B$14
A23: RB | B23: Adam Randall | C23: 3 | D23: 22 | E23: role avg (rookie) | J23: 17 | L23: 0.0196 | M23: 0.0568 | N23: 0.75 | O23: 1 | P23: 1 | Q23: 1 | R23: 1 | S23: =IFERROR(K23*$I$5,0) | T23: =IFERROR(K23*$J$5,0) | U23: =IFERROR(K23*$K$5,0) | V23: =IFERROR(L23*$G$5,0) | W23: =IFERROR(V23*N23,0) | X23: =IFERROR(L23*O23/SUMPRODUCT($L$17:$L$41,$O$17:$O$41)*$I$5,0) | Y23: =IFERROR(X23/W23,0) | Z23: =IFERROR(L23*Q23/SUMPRODUCT($L$17:$L$41,$Q$17:$Q$41)*$J$5,0) | AA23: =IFERROR(M23*$H$5,0) | AB23: =IFERROR(M23*P23/SUMPRODUCT($M$17:$M$41,$P$17:$P$41)*$L$5,0) | AC23: =IFERROR(AB23/AA23,0) | AD23: =IFERROR(M23*R23/SUMPRODUCT($M$17:$M$41,$R$17:$R$41)*$M$5,0) | AE23: =X23*Settings!$B$7+Z23*Settings!$B$8+W23*Settings!$B$9+AB23*Settings!$B$10+AD23*Settings!$B$11+S23*Settings!$B$12+T23*Settings!$B$13+U23*Settings!$B$14
A24: RB | B24: Rasheen Ali | C24: 4 | D24: 25 | E24: ACT | G24: 0.0044 | H24: 0.027 | I24: 0.0143 | J24: 17 | L24: 0.0181 | M24: 0.0177 | N24: 0.8182 | O24: 0.93 | P24: 0.89 | Q24: 1.01 | R24: 0.97 | S24: =IFERROR(K24*$I$5,0) | T24: =IFERROR(K24*$J$5,0) | U24: =IFERROR(K24*$K$5,0) | V24: =IFERROR(L24*$G$5,0) | W24: =IFERROR(V24*N24,0) | X24: =IFERROR(L24*O24/SUMPRODUCT($L$17:$L$41,$O$17:$O$41)*$I$5,0) | Y24: =IFERROR(X24/W24,0) | Z24: =IFERROR(L24*Q24/SUMPRODUCT($L$17:$L$41,$Q$17:$Q$41)*$J$5,0) | AA24: =IFERROR(M24*$H$5,0) | AB24: =IFERROR(M24*P24/SUMPRODUCT($M$17:$M$41,$P$17:$P$41)*$L$5,0) | AC24: =IFERROR(AB24/AA24,0) | AD24: =IFERROR(M24*R24/SUMPRODUCT($M$17:$M$41,$R$17:$R$41)*$M$5,0) | AE24: =X24*Settings!$B$7+Z24*Settings!$B$8+W24*Settings!$B$9+AB24*Settings!$B$10+AD24*Settings!$B$11+S24*Settings!$B$12+T24*Settings!$B$13+U24*Settings!$B$14
A25: RB | B25: Dontae McMillan | C25: 5 | D25: 24 | E25: role avg (rookie) | J25: 17 | L25: 0.0046 | M25: 0.0094 | N25: 0.75 | O25: 1 | P25: 1 | Q25: 1 | R25: 1 | S25: =IFERROR(K25*$I$5,0) | T25: =IFERROR(K25*$J$5,0) | U25: =IFERROR(K25*$K$5,0) | V25: =IFERROR(L25*$G$5,0) | W25: =IFERROR(V25*N25,0) | X25: =IFERROR(L25*O25/SUMPRODUCT($L$17:$L$41,$O$17:$O$41)*$I$5,0) | Y25: =IFERROR(X25/W25,0) | Z25: =IFERROR(L25*Q25/SUMPRODUCT($L$17:$L$41,$Q$17:$Q$41)*$J$5,0) | AA25: =IFERROR(M25*$H$5,0) | AB25: =IFERROR(M25*P25/SUMPRODUCT($M$17:$M$41,$P$17:$P$41)*$L$5,0) | AC25: =IFERROR(AB25/AA25,0) | AD25: =IFERROR(M25*R25/SUMPRODUCT($M$17:$M$41,$R$17:$R$41)*$M$5,0) | AE25: =X25*Settings!$B$7+Z25*Settings!$B$8+W25*Settings!$B$9+AB25*Settings!$B$10+AD25*Settings!$B$11+S25*Settings!$B$12+T25*Settings!$B$13+U25*Settings!$B$14
A26: RB | B26: Elijah Tau-Tolliver | C26: 6 | D26: 23 | E26: role avg (rookie) | J26: 17 | L26: 0.0049 | M26: 0.0042 | N26: 0.75 | O26: 1 | P26: 1 | Q26: 1 | R26: 1 | S26: =IFERROR(K26*$I$5,0) | T26: =IFERROR(K26*$J$5,0) | U26: =IFERROR(K26*$K$5,0) | V26: =IFERROR(L26*$G$5,0) | W26: =IFERROR(V26*N26,0) | X26: =IFERROR(L26*O26/SUMPRODUCT($L$17:$L$41,$O$17:$O$41)*$I$5,0) | Y26: =IFERROR(X26/W26,0) | Z26: =IFERROR(L26*Q26/SUMPRODUCT($L$17:$L$41,$Q$17:$Q$41)*$J$5,0) | AA26: =IFERROR(M26*$H$5,0) | AB26: =IFERROR(M26*P26/SUMPRODUCT($M$17:$M$41,$P$17:$P$41)*$L$5,0) | AC26: =IFERROR(AB26/AA26,0) | AD26: =IFERROR(M26*R26/SUMPRODUCT($M$17:$M$41,$R$17:$R$41)*$M$5,0) | AE26: =X26*Settings!$B$7+Z26*Settings!$B$8+W26*Settings!$B$9+AB26*Settings!$B$10+AD26*Settings!$B$11+S26*Settings!$B$12+T26*Settings!$B$13+U26*Settings!$B$14
A27: RB | B27: Other RBs | S27: =IFERROR(K27*$I$5,0) | T27: =IFERROR(K27*$J$5,0) | U27: =IFERROR(K27*$K$5,0) | V27: =IFERROR(L27*$G$5,0) | W27: =IFERROR(V27*N27,0) | X27: =IFERROR(L27*O27/SUMPRODUCT($L$17:$L$41,$O$17:$O$41)*$I$5,0) | Y27: =IFERROR(X27/W27,0) | Z27: =IFERROR(L27*Q27/SUMPRODUCT($L$17:$L$41,$Q$17:$Q$41)*$J$5,0) | AA27: =IFERROR(M27*$H$5,0) | AB27: =IFERROR(M27*P27/SUMPRODUCT($M$17:$M$41,$P$17:$P$41)*$L$5,0) | AC27: =IFERROR(AB27/AA27,0) | AD27: =IFERROR(M27*R27/SUMPRODUCT($M$17:$M$41,$R$17:$R$41)*$M$5,0) | AE27: =X27*Settings!$B$7+Z27*Settings!$B$8+W27*Settings!$B$9+AB27*Settings!$B$10+AD27*Settings!$B$11+S27*Settings!$B$12+T27*Settings!$B$13+U27*Settings!$B$14
A28: WR | B28: Zay Flowers | C28: 1 | D28: 25 | E28: ACT | F28: 0.2269 | G28: 0.2538 | H28: 0.2899 | I28: 0.0204 | J28: 17 | L28: 0.2548 | M28: 0.0166 | N28: 0.6982 | O28: 1.11 | P28: 1.05 | Q28: 0.82 | R28: 0.98 | S28: =IFERROR(K28*$I$5,0) | T28: =IFERROR(K28*$J$5,0) | U28: =IFERROR(K28*$K$5,0) | V28: =IFERROR(L28*$G$5,0) | W28: =IFERROR(V28*N28,0) | X28: =IFERROR(L28*O28/SUMPRODUCT($L$17:$L$41,$O$17:$O$41)*$I$5,0) | Y28: =IFERROR(X28/W28,0) | Z28: =IFERROR(L28*Q28/SUMPRODUCT($L$17:$L$41,$Q$17:$Q$41)*$J$5,0) | AA28: =IFERROR(M28*$H$5,0) | AB28: =IFERROR(M28*P28/SUMPRODUCT($M$17:$M$41,$P$17:$P$41)*$L$5,0) | AC28: =IFERROR(AB28/AA28,0) | AD28: =IFERROR(M28*R28/SUMPRODUCT($M$17:$M$41,$R$17:$R$41)*$M$5,0) | AE28: =X28*Settings!$B$7+Z28*Settings!$B$8+W28*Settings!$B$9+AB28*Settings!$B$10+AD28*Settings!$B$11+S28*Settings!$B$12+T28*Settings!$B$13+U28*Settings!$B$14
A29: WR | B29: Rashod Bateman | C29: 2 | D29: 26 | E29: ACT | F29: 0.1176 | G29: 0.1575 | H29: 0.0934 | J29: 17 | L29: 0.1261 | M29: 0.0037 | N29: 0.5585 | O29: 0.92 | P29: 1.12 | Q29: 0.98 | R29: 1 | S29: =IFERROR(K29*$I$5,0) | T29: =IFERROR(K29*$J$5,0) | U29: =IFERROR(K29*$K$5,0) | V29: =IFERROR(L29*$G$5,0) | W29: =IFERROR(V29*N29,0) | X29: =IFERROR(L29*O29/SUMPRODUCT($L$17:$L$41,$O$17:$O$41)*$I$5,0) | Y29: =IFERROR(X29/W29,0) | Z29: =IFERROR(L29*Q29/SUMPRODUCT($L$17:$L$41,$Q$17:$Q$41)*$J$5,0) | AA29: =IFERROR(M29*$H$5,0) | AB29: =IFERROR(M29*P29/SUMPRODUCT($M$17:$M$41,$P$17:$P$41)*$L$5,0) | AC29: =IFERROR(AB29/AA29,0) | AD29: =IFERROR(M29*R29/SUMPRODUCT($M$17:$M$41,$R$17:$R$41)*$M$5,0) | AE29: =X29*Settings!$B$7+Z29*Settings!$B$8+W29*Settings!$B$9+AB29*Settings!$B$10+AD29*Settings!$B$11+S29*Settings!$B$12+T29*Settings!$B$13+U29*Settings!$B$14
A30: WR | B30: Ja'Kobi Lane | C30: 3 | D30: 22 | E30: role avg (rookie) | J30: 17 | L30: 0.0919 | M30: 0.0027 | N30: 0.65 | O30: 1 | P30: 1 | Q30: 1 | R30: 1 | S30: =IFERROR(K30*$I$5,0) | T30: =IFERROR(K30*$J$5,0) | U30: =IFERROR(K30*$K$5,0) | V30: =IFERROR(L30*$G$5,0) | W30: =IFERROR(V30*N30,0) | X30: =IFERROR(L30*O30/SUMPRODUCT($L$17:$L$41,$O$17:$O$41)*$I$5,0) | Y30: =IFERROR(X30/W30,0) | Z30: =IFERROR(L30*Q30/SUMPRODUCT($L$17:$L$41,$Q$17:$Q$41)*$J$5,0) | AA30: =IFERROR(M30*$H$5,0) | AB30: =IFERROR(M30*P30/SUMPRODUCT($M$17:$M$41,$P$17:$P$41)*$L$5,0) | AC30: =IFERROR(AB30/AA30,0) | AD30: =IFERROR(M30*R30/SUMPRODUCT($M$17:$M$41,$R$17:$R$41)*$M$5,0) | AE30: =X30*Settings!$B$7+Z30*Settings!$B$8+W30*Settings!$B$9+AB30*Settings!$B$10+AD30*Settings!$B$11+S30*Settings!$B$12+T30*Settings!$B$13+U30*Settings!$B$14
A31: WR | B31: Elijah Sarratt | C31: 4 | D31: 23 | E31: role avg (rookie) | J31: 17 | L31: 0.0475 | M31: 0.0022 | N31: 0.65 | O31: 1 | P31: 1 | Q31: 1 | R31: 1 | S31: =IFERROR(K31*$I$5,0) | T31: =IFERROR(K31*$J$5,0) | U31: =IFERROR(K31*$K$5,0) | V31: =IFERROR(L31*$G$5,0) | W31: =IFERROR(V31*N31,0) | X31: =IFERROR(L31*O31/SUMPRODUCT($L$17:$L$41,$O$17:$O$41)*$I$5,0) | Y31: =IFERROR(X31/W31,0) | Z31: =IFERROR(L31*Q31/SUMPRODUCT($L$17:$L$41,$Q$17:$Q$41)*$J$5,0) | AA31: =IFERROR(M31*$H$5,0) | AB31: =IFERROR(M31*P31/SUMPRODUCT($M$17:$M$41,$P$17:$P$41)*$L$5,0) | AC31: =IFERROR(AB31/AA31,0) | AD31: =IFERROR(M31*R31/SUMPRODUCT($M$17:$M$41,$R$17:$R$41)*$M$5,0) | AE31: =X31*Settings!$B$7+Z31*Settings!$B$8+W31*Settings!$B$9+AB31*Settings!$B$10+AD31*Settings!$B$11+S31*Settings!$B$12+T31*Settings!$B$13+U31*Settings!$B$14
A32: WR | B32: Devontez Walker | C32: 5 | D32: 25 | E32: ACT | G32: 0.0066 | H32: 0.0197 | J32: 17 | L32: 0.0169 | M32: 0.0008 | N32: 0.6207 | O32: 1.17 | P32: 1 | Q32: 1.01 | R32: 1 | S32: =IFERROR(K32*$I$5,0) | T32: =IFERROR(K32*$J$5,0) | U32: =IFERROR(K32*$K$5,0) | V32: =IFERROR(L32*$G$5,0) | W32: =IFERROR(V32*N32,0) | X32: =IFERROR(L32*O32/SUMPRODUCT($L$17:$L$41,$O$17:$O$41)*$I$5,0) | Y32: =IFERROR(X32/W32,0) | Z32: =IFERROR(L32*Q32/SUMPRODUCT($L$17:$L$41,$Q$17:$Q$41)*$J$5,0) | AA32: =IFERROR(M32*$H$5,0) | AB32: =IFERROR(M32*P32/SUMPRODUCT($M$17:$M$41,$P$17:$P$41)*$L$5,0) | AC32: =IFERROR(AB32/AA32,0) | AD32: =IFERROR(M32*R32/SUMPRODUCT($M$17:$M$41,$R$17:$R$41)*$M$5,0) | AE32: =X32*Settings!$B$7+Z32*Settings!$B$8+W32*Settings!$B$9+AB32*Settings!$B$10+AD32*Settings!$B$11+S32*Settings!$B$12+T32*Settings!$B$13+U32*Settings!$B$14
A33: WR | B33: Cornelius Johnson | C33: 6 | D33: 25 | E33: role avg (rookie) | J33: 17 | L33: 0.0083 | M33: 0.002 | N33: 0.65 | O33: 1 | P33: 1 | Q33: 1 | R33: 1 | S33: =IFERROR(K33*$I$5,0) | T33: =IFERROR(K33*$J$5,0) | U33: =IFERROR(K33*$K$5,0) | V33: =IFERROR(L33*$G$5,0) | W33: =IFERROR(V33*N33,0) | X33: =IFERROR(L33*O33/SUMPRODUCT($L$17:$L$41,$O$17:$O$41)*$I$5,0) | Y33: =IFERROR(X33/W33,0) | Z33: =IFERROR(L33*Q33/SUMPRODUCT($L$17:$L$41,$Q$17:$Q$41)*$J$5,0) | AA33: =IFERROR(M33*$H$5,0) | AB33: =IFERROR(M33*P33/SUMPRODUCT($M$17:$M$41,$P$17:$P$41)*$L$5,0) | AC33: =IFERROR(AB33/AA33,0) | AD33: =IFERROR(M33*R33/SUMPRODUCT($M$17:$M$41,$R$17:$R$41)*$M$5,0) | AE33: =X33*Settings!$B$7+Z33*Settings!$B$8+W33*Settings!$B$9+AB33*Settings!$B$10+AD33*Settings!$B$11+S33*Settings!$B$12+T33*Settings!$B$13+U33*Settings!$B$14
A34: WR | B34: Chris Moore | C34: 7 | D34: 33 | E34: role avg (from WAS) | F34: 0.0732 | H34: 0.0532 | I34: 0.0021 | J34: 17 | L34: 0.0054 | M34: 0.0021 | N34: 0.5274 | O34: 1.19 | P34: 1.11 | Q34: 2.05 | R34: 1 | S34: =IFERROR(K34*$I$5,0) | T34: =IFERROR(K34*$J$5,0) | U34: =IFERROR(K34*$K$5,0) | V34: =IFERROR(L34*$G$5,0) | W34: =IFERROR(V34*N34,0) | X34: =IFERROR(L34*O34/SUMPRODUCT($L$17:$L$41,$O$17:$O$41)*$I$5,0) | Y34: =IFERROR(X34/W34,0) | Z34: =IFERROR(L34*Q34/SUMPRODUCT($L$17:$L$41,$Q$17:$Q$41)*$J$5,0) | AA34: =IFERROR(M34*$H$5,0) | AB34: =IFERROR(M34*P34/SUMPRODUCT($M$17:$M$41,$P$17:$P$41)*$L$5,0) | AC34: =IFERROR(AB34/AA34,0) | AD34: =IFERROR(M34*R34/SUMPRODUCT($M$17:$M$41,$R$17:$R$41)*$M$5,0) | AE34: =X34*Settings!$B$7+Z34*Settings!$B$8+W34*Settings!$B$9+AB34*Settings!$B$10+AD34*Settings!$B$11+S34*Settings!$B$12+T34*Settings!$B$13+U34*Settings!$B$14
A35: WR | B35: LaJohntay Wester | C35: 8 | D35: 24 | E35: role avg (rookie) | J35: 17 | L35: 0.005 | M35: 0.002 | N35: 0.65 | O35: 1 | P35: 1 | Q35: 1 | R35: 1 | S35: =IFERROR(K35*$I$5,0) | T35: =IFERROR(K35*$J$5,0) | U35: =IFERROR(K35*$K$5,0) | V35: =IFERROR(L35*$G$5,0) | W35: =IFERROR(V35*N35,0) | X35: =IFERROR(L35*O35/SUMPRODUCT($L$17:$L$41,$O$17:$O$41)*$I$5,0) | Y35: =IFERROR(X35/W35,0) | Z35: =IFERROR(L35*Q35/SUMPRODUCT($L$17:$L$41,$Q$17:$Q$41)*$J$5,0) | AA35: =IFERROR(M35*$H$5,0) | AB35: =IFERROR(M35*P35/SUMPRODUCT($M$17:$M$41,$P$17:$P$41)*$L$5,0) | AC35: =IFERROR(AB35/AA35,0) | AD35: =IFERROR(M35*R35/SUMPRODUCT($M$17:$M$41,$R$17:$R$41)*$M$5,0) | AE35: =X35*Settings!$B$7+Z35*Settings!$B$8+W35*Settings!$B$9+AB35*Settings!$B$10+AD35*Settings!$B$11+S35*Settings!$B$12+T35*Settings!$B$13+U35*Settings!$B$14
A36: WR | B36: Other WRs | S36: =IFERROR(K36*$I$5,0) | T36: =IFERROR(K36*$J$5,0) | U36: =IFERROR(K36*$K$5,0) | V36: =IFERROR(L36*$G$5,0) | W36: =IFERROR(V36*N36,0) | X36: =IFERROR(L36*O36/SUMPRODUCT($L$17:$L$41,$O$17:$O$41)*$I$5,0) | Y36: =IFERROR(X36/W36,0) | Z36: =IFERROR(L36*Q36/SUMPRODUCT($L$17:$L$41,$Q$17:$Q$41)*$J$5,0) | AA36: =IFERROR(M36*$H$5,0) | AB36: =IFERROR(M36*P36/SUMPRODUCT($M$17:$M$41,$P$17:$P$41)*$L$5,0) | AC36: =IFERROR(AB36/AA36,0) | AD36: =IFERROR(M36*R36/SUMPRODUCT($M$17:$M$41,$R$17:$R$41)*$M$5,0) | AE36: =X36*Settings!$B$7+Z36*Settings!$B$8+W36*Settings!$B$9+AB36*Settings!$B$10+AD36*Settings!$B$11+S36*Settings!$B$12+T36*Settings!$B$13+U36*Settings!$B$14
A37: TE | B37: Mark Andrews | C37: 1 | D37: 30 | E37: ACT | F37: 0.1282 | G37: 0.151 | H37: 0.172 | I37: 0.0204 | J37: 17 | L37: 0.1543 | M37: 0.01 | N37: 0.7288 | O37: 0.92 | P37: 0.91 | Q37: 1.41 | R37: 1.2 | S37: =IFERROR(K37*$I$5,0) | T37: =IFERROR(K37*$J$5,0) | U37: =IFERROR(K37*$K$5,0) | V37: =IFERROR(L37*$G$5,0) | W37: =IFERROR(V37*N37,0) | X37: =IFERROR(L37*O37/SUMPRODUCT($L$17:$L$41,$O$17:$O$41)*$I$5,0) | Y37: =IFERROR(X37/W37,0) | Z37: =IFERROR(L37*Q37/SUMPRODUCT($L$17:$L$41,$Q$17:$Q$41)*$J$5,0) | AA37: =IFERROR(M37*$H$5,0) | AB37: =IFERROR(M37*P37/SUMPRODUCT($M$17:$M$41,$P$17:$P$41)*$L$5,0) | AC37: =IFERROR(AB37/AA37,0) | AD37: =IFERROR(M37*R37/SUMPRODUCT($M$17:$M$41,$R$17:$R$41)*$M$5,0) | AE37: =X37*Settings!$B$7+Z37*Settings!$B$8+W37*Settings!$B$9+AB37*Settings!$B$10+AD37*Settings!$B$11+S37*Settings!$B$12+T37*Settings!$B$13+U37*Settings!$B$14
A38: TE | B38: Matt Hibner | C38: 2 | D38: 24 | E38: role avg (rookie) | J38: 17 | L38: 0.0732 | M38: 0.002 | N38: 0.65 | O38: 1 | P38: 1 | Q38: 1 | R38: 1 | S38: =IFERROR(K38*$I$5,0) | T38: =IFERROR(K38*$J$5,0) | U38: =IFERROR(K38*$K$5,0) | V38: =IFERROR(L38*$G$5,0) | W38: =IFERROR(V38*N38,0) | X38: =IFERROR(L38*O38/SUMPRODUCT($L$17:$L$41,$O$17:$O$41)*$I$5,0) | Y38: =IFERROR(X38/W38,0) | Z38: =IFERROR(L38*Q38/SUMPRODUCT($L$17:$L$41,$Q$17:$Q$41)*$J$5,0) | AA38: =IFERROR(M38*$H$5,0) | AB38: =IFERROR(M38*P38/SUMPRODUCT($M$17:$M$41,$P$17:$P$41)*$L$5,0) | AC38: =IFERROR(AB38/AA38,0) | AD38: =IFERROR(M38*R38/SUMPRODUCT($M$17:$M$41,$R$17:$R$41)*$M$5,0) | AE38: =X38*Settings!$B$7+Z38*Settings!$B$8+W38*Settings!$B$9+AB38*Settings!$B$10+AD38*Settings!$B$11+S38*Settings!$B$12+T38*Settings!$B$13+U38*Settings!$B$14
A39: TE | B39: Durham Smythe | C39: 3 | D39: 30 | E39: role avg (from CHI) | F39: 0.0783 | G39: 0.0299 | H39: 0.0113 | J39: 17 | L39: 0.0223 | M39: 0.0021 | N39: 0.6531 | O39: 0.82 | P39: 1 | Q39: 1.3 | R39: 1 | S39: =IFERROR(K39*$I$5,0) | T39: =IFERROR(K39*$J$5,0) | U39: =IFERROR(K39*$K$5,0) | V39: =IFERROR(L39*$G$5,0) | W39: =IFERROR(V39*N39,0) | X39: =IFERROR(L39*O39/SUMPRODUCT($L$17:$L$41,$O$17:$O$41)*$I$5,0) | Y39: =IFERROR(X39/W39,0) | Z39: =IFERROR(L39*Q39/SUMPRODUCT($L$17:$L$41,$Q$17:$Q$41)*$J$5,0) | AA39: =IFERROR(M39*$H$5,0) | AB39: =IFERROR(M39*P39/SUMPRODUCT($M$17:$M$41,$P$17:$P$41)*$L$5,0) | AC39: =IFERROR(AB39/AA39,0) | AD39: =IFERROR(M39*R39/SUMPRODUCT($M$17:$M$41,$R$17:$R$41)*$M$5,0) | AE39: =X39*Settings!$B$7+Z39*Settings!$B$8+W39*Settings!$B$9+AB39*Settings!$B$10+AD39*Settings!$B$11+S39*Settings!$B$12+T39*Settings!$B$13+U39*Settings!$B$14
A40: TE | B40: Josh Cuevas | C40: 4 | D40: 22 | E40: role avg (rookie) | J40: 17 | L40: 0.0069 | M40: 0.0021 | N40: 0.65 | O40: 1 | P40: 1 | Q40: 1 | R40: 1 | S40: =IFERROR(K40*$I$5,0) | T40: =IFERROR(K40*$J$5,0) | U40: =IFERROR(K40*$K$5,0) | V40: =IFERROR(L40*$G$5,0) | W40: =IFERROR(V40*N40,0) | X40: =IFERROR(L40*O40/SUMPRODUCT($L$17:$L$41,$O$17:$O$41)*$I$5,0) | Y40: =IFERROR(X40/W40,0) | Z40: =IFERROR(L40*Q40/SUMPRODUCT($L$17:$L$41,$Q$17:$Q$41)*$J$5,0) | AA40: =IFERROR(M40*$H$5,0) | AB40: =IFERROR(M40*P40/SUMPRODUCT($M$17:$M$41,$P$17:$P$41)*$L$5,0) | AC40: =IFERROR(AB40/AA40,0) | AD40: =IFERROR(M40*R40/SUMPRODUCT($M$17:$M$41,$R$17:$R$41)*$M$5,0) | AE40: =X40*Settings!$B$7+Z40*Settings!$B$8+W40*Settings!$B$9+AB40*Settings!$B$10+AD40*Settings!$B$11+S40*Settings!$B$12+T40*Settings!$B$13+U40*Settings!$B$14
A41: TE | B41: Other TEs | S41: =IFERROR(K41*$I$5,0) | T41: =IFERROR(K41*$J$5,0) | U41: =IFERROR(K41*$K$5,0) | V41: =IFERROR(L41*$G$5,0) | W41: =IFERROR(V41*N41,0) | X41: =IFERROR(L41*O41/SUMPRODUCT($L$17:$L$41,$O$17:$O$41)*$I$5,0) | Y41: =IFERROR(X41/W41,0) | Z41: =IFERROR(L41*Q41/SUMPRODUCT($L$17:$L$41,$Q$17:$Q$41)*$J$5,0) | AA41: =IFERROR(M41*$H$5,0) | AB41: =IFERROR(M41*P41/SUMPRODUCT($M$17:$M$41,$P$17:$P$41)*$L$5,0) | AC41: =IFERROR(AB41/AA41,0) | AD41: =IFERROR(M41*R41/SUMPRODUCT($M$17:$M$41,$R$17:$R$41)*$M$5,0) | AE41: =X41*Settings!$B$7+Z41*Settings!$B$8+W41*Settings!$B$9+AB41*Settings!$B$10+AD41*Settings!$B$11+S41*Settings!$B$12+T41*Settings!$B$13+U41*Settings!$B$14
B43: SHARE TOTALS - must equal 100% | E43: each column is a share of this team's season total - it must add to 100% | K43: =SUM(K17:K41) | L43: =SUM(L17:L41) | M43: =SUM(M17:M41) | S43: =SUM(S17:S41) | T43: =SUM(T17:T41) | U43: =SUM(U17:U41) | V43: =SUM(V17:V41) | W43: =SUM(W17:W41) | X43: =SUM(X17:X41) | Y43: =SUM(Y17:Y41) | Z43: =SUM(Z17:Z41) | ... AE43: =SUM(AE17:AE41)
B45: Green = balanced. Red = your shares don't add to 100%; player totals won't match the team totals until they do.

Sheet BUF
A1: BUF - 2026 projections
A3: TEAM TOTALS | C3: blue = edit; everything below divides these up
B4: Games | C4: Plays/G | D4: Plays | E4: Pass Rate | F4: Pass Att | G4: Targets | H4: Rush Att | I4: Pass Yds | J4: Pass TD | K4: Int | L4: Rush Yds | M4: Rush TD
B5: 17 | C5: 62.6 | D5: =C5*B5 | E5: 0.5275 | F5: 529 | G5: =ROUND(F5*Settings!$B$4,0) | H5: 503 | I5: 4003 | J5: 28 | K5: 11 | L5: 2305 | M5: 24
A7: LAST 3 YEARS | B7: Season | C7: Plays | D7: Plays/G | E7: Pass Rate | F7: Pass Att | G7: Rush Att | H7: Pass Yds | I7: Rush Yds | J7: Pass TD | K7: Rush TD | L7: Y/A | M7: Y/C
B8: 2023 | C8: 1115 | D8: 65.5882 | E8: 0.5408 | F8: 579 | G8: 512 | H8: 4306 | I8: 2212 | J8: 29 | K8: 22 | L8: 7.437 | M8: 4.3203
B9: 2024 | C9: 1025 | D9: 60.2941 | E9: 0.521 | F9: 520 | G9: 491 | H9: 3938 | I9: 2230 | J9: 30 | K9: 32 | L9: 7.5731 | M9: 4.5418
B10: 2025 | C10: 1082 | D10: 63.6471 | E10: 0.4945 | F10: 495 | G10: 547 | H10: 3981 | I10: 2714 | J10: 29 | K10: 30 | L10: 8.0424 | M10: 4.9616
A12: OUT | B12: 9% of targets and 1% of carries left. Share is team-relative - it does NOT follow the player. | H12: Gabe Davis (4t/0r -> NOT ON ANY ROSTER), Elijah Moore (4t/1r -> PHI), Curtis Samuel (2t/0r -> NOT ON ANY ROSTER)
A13: IN | B13: 7 new: DJ Moore (WR, from CHI - had 16% there), Dante Pettis (WR, from NO - had 2% there), Shane Zylstra (TE, from DET - had 1% there), Trent Sherfield (WR, from DEN - had 1% there), Shane Buechele (QB, from KC)
A14: STAFF | B14: NEW HC Joe Brady (promoted from OC) + OC Pete Carmichael Jr. Brady keeps play-calling. Run-lean; controlled pace continues.
A16: Pos | B16: Player | C16: Dep | D16: Age | E16: Status | F16: 2023 Tgt% | G16: 2024 Tgt% | H16: 2025 Tgt% | I16: 2025 Rush% | J16: Games | K16: Pass % | L16: Tgt % | M16: Rush % | N16: Catch % | O16: Rec Eff x | P16: Rush Eff x | Q16: RZ Tgt x | R16: RZ Rush x | S16: Pass Yds | T16: Pass TD | U16: Int | V16: Targets | W16: Rec | X16: Rec Yds | Y16: Yds/Rec | Z16: Rec TD | AA16: Rush Att | AB16: Rush Yds | AC16: Yds/Car | AD16: Rush TD | AE16: Half PPR
A17: QB | B17: Josh Allen | C17: 1 | D17: 30 | E17: ACT | I17: 0.1785 | J17: 17 | K17: 0.9433 | L17: 0.0007 | M17: 0.1647 | O17: 1 | P17: 1.15 | Q17: 1 | R17: 1.55 | S17: =IFERROR(K17*$I$5,0) | T17: =IFERROR(K17*$J$5,0) | U17: =IFERROR(K17*$K$5,0) | V17: =IFERROR(L17*$G$5,0) | W17: =IFERROR(V17*N17,0) | X17: =IFERROR(L17*O17/SUMPRODUCT($L$17:$L$41,$O$17:$O$41)*$I$5,0) | Y17: =IFERROR(X17/W17,0) | Z17: =IFERROR(L17*Q17/SUMPRODUCT($L$17:$L$41,$Q$17:$Q$41)*$J$5,0) | AA17: =IFERROR(M17*$H$5,0) | AB17: =IFERROR(M17*P17/SUMPRODUCT($M$17:$M$41,$P$17:$P$41)*$L$5,0) | AC17: =IFERROR(AB17/AA17,0) | AD17: =IFERROR(M17*R17/SUMPRODUCT($M$17:$M$41,$R$17:$R$41)*$M$5,0) | AE17: =X17*Settings!$B$7+Z17*Settings!$B$8+W17*Settings!$B$9+AB17*Settings!$B$10+AD17*Settings!$B$11+S17*Settings!$B$12+T17*Settings!$B$13+U17*Settings!$B$14
A18: QB | B18: Shane Buechele | C18: 2 | D18: 28 | E18: role avg (from KC) | I18: 0.0024 | J18: 17 | K18: 0.0482 | L18: 0.0017 | M18: 0.0118 | O18: 1 | P18: 1 | Q18: 1 | R18: 1 | S18: =IFERROR(K18*$I$5,0) | T18: =IFERROR(K18*$J$5,0) | U18: =IFERROR(K18*$K$5,0) | V18: =IFERROR(L18*$G$5,0) | W18: =IFERROR(V18*N18,0) | X18: =IFERROR(L18*O18/SUMPRODUCT($L$17:$L$41,$O$17:$O$41)*$I$5,0) | Y18: =IFERROR(X18/W18,0) | Z18: =IFERROR(L18*Q18/SUMPRODUCT($L$17:$L$41,$Q$17:$Q$41)*$J$5,0) | AA18: =IFERROR(M18*$H$5,0) | AB18: =IFERROR(M18*P18/SUMPRODUCT($M$17:$M$41,$P$17:$P$41)*$L$5,0) | AC18: =IFERROR(AB18/AA18,0) | AD18: =IFERROR(M18*R18/SUMPRODUCT($M$17:$M$41,$R$17:$R$41)*$M$5,0) | AE18: =X18*Settings!$B$7+Z18*Settings!$B$8+W18*Settings!$B$9+AB18*Settings!$B$10+AD18*Settings!$B$11+S18*Settings!$B$12+T18*Settings!$B$13+U18*Settings!$B$14
A19: QB | B19: Kyle Allen | C19: 3 | D19: 30 | E19: role avg (from DET) | J19: 17 | K19: 0.0085 | L19: 0.0017 | M19: 0.0096 | O19: 1 | P19: 1 | Q19: 1 | R19: 1 | S19: =IFERROR(K19*$I$5,0) | T19: =IFERROR(K19*$J$5,0) | U19: =IFERROR(K19*$K$5,0) | V19: =IFERROR(L19*$G$5,0) | W19: =IFERROR(V19*N19,0) | X19: =IFERROR(L19*O19/SUMPRODUCT($L$17:$L$41,$O$17:$O$41)*$I$5,0) | Y19: =IFERROR(X19/W19,0) | Z19: =IFERROR(L19*Q19/SUMPRODUCT($L$17:$L$41,$Q$17:$Q$41)*$J$5,0) | AA19: =IFERROR(M19*$H$5,0) | AB19: =IFERROR(M19*P19/SUMPRODUCT($M$17:$M$41,$P$17:$P$41)*$L$5,0) | AC19: =IFERROR(AB19/AA19,0) | AD19: =IFERROR(M19*R19/SUMPRODUCT($M$17:$M$41,$R$17:$R$41)*$M$5,0) | AE19: =X19*Settings!$B$7+Z19*Settings!$B$8+W19*Settings!$B$9+AB19*Settings!$B$10+AD19*Settings!$B$11+S19*Settings!$B$12+T19*Settings!$B$13+U19*Settings!$B$14
A20: QB | B20: Other QBs | S20: =IFERROR(K20*$I$5,0) | T20: =IFERROR(K20*$J$5,0) | U20: =IFERROR(K20*$K$5,0) | V20: =IFERROR(L20*$G$5,0) | W20: =IFERROR(V20*N20,0) | X20: =IFERROR(L20*O20/SUMPRODUCT($L$17:$L$41,$O$17:$O$41)*$I$5,0) | Y20: =IFERROR(X20/W20,0) | Z20: =IFERROR(L20*Q20/SUMPRODUCT($L$17:$L$41,$Q$17:$Q$41)*$J$5,0) | AA20: =IFERROR(M20*$H$5,0) | AB20: =IFERROR(M20*P20/SUMPRODUCT($M$17:$M$41,$P$17:$P$41)*$L$5,0) | AC20: =IFERROR(AB20/AA20,0) | AD20: =IFERROR(M20*R20/SUMPRODUCT($M$17:$M$41,$R$17:$R$41)*$M$5,0) | AE20: =X20*Settings!$B$7+Z20*Settings!$B$8+W20*Settings!$B$9+AB20*Settings!$B$10+AD20*Settings!$B$11+S20*Settings!$B$12+T20*Settings!$B$13+U20*Settings!$B$14
A21: RB | B21: James Cook | C21: 1 | D21: 26 | E21: ACT | F21: 0.0991 | G21: 0.0768 | H21: 0.0835 | I21: 0.5931 | J21: 17 | L21: 0.0793 | M21: 0.4978 | N21: 0.8278 | O21: 0.93 | P21: 1.02 | Q21: 0.89 | R21: 0.85 | S21: =IFERROR(K21*$I$5,0) | T21: =IFERROR(K21*$J$5,0) | U21: =IFERROR(K21*$K$5,0) | V21: =IFERROR(L21*$G$5,0) | W21: =IFERROR(V21*N21,0) | X21: =IFERROR(L21*O21/SUMPRODUCT($L$17:$L$41,$O$17:$O$41)*$I$5,0) | Y21: =IFERROR(X21/W21,0) | Z21: =IFERROR(L21*Q21/SUMPRODUCT($L$17:$L$41,$Q$17:$Q$41)*$J$5,0) | AA21: =IFERROR(M21*$H$5,0) | AB21: =IFERROR(M21*P21/SUMPRODUCT($M$17:$M$41,$P$17:$P$41)*$L$5,0) | AC21: =IFERROR(AB21/AA21,0) | AD21: =IFERROR(M21*R21/SUMPRODUCT($M$17:$M$41,$R$17:$R$41)*$M$5,0) | AE21: =X21*Settings!$B$7+Z21*Settings!$B$8+W21*Settings!$B$9+AB21*Settings!$B$10+AD21*Settings!$B$11+S21*Settings!$B$12+T21*Settings!$B$13+U21*Settings!$B$14
A22: RB | B22: Ty Johnson | C22: 2 | D22: 28 | E22: ACT | F22: 0.0128 | G22: 0.0505 | H22: 0.0689 | I22: 0.096 | J22: 17 | L22: 0.048 | M22: 0.148 | N22: 0.7599 | O22: 1.08 | P22: 0.93 | Q22: 1.12 | R22: 0.86 | S22: =IFERROR(K22*$I$5,0) | T22: =IFERROR(K22*$J$5,0) | U22: =IFERROR(K22*$K$5,0) | V22: =IFERROR(L22*$G$5,0) | W22: =IFERROR(V22*N22,0) | X22: =IFERROR(L22*O22/SUMPRODUCT($L$17:$L$41,$O$17:$O$41)*$I$5,0) | Y22: =IFERROR(X22/W22,0) | Z22: =IFERROR(L22*Q22/SUMPRODUCT($L$17:$L$41,$Q$17:$Q$41)*$J$5,0) | AA22: =IFERROR(M22*$H$5,0) | AB22: =IFERROR(M22*P22/SUMPRODUCT($M$17:$M$41,$P$17:$P$41)*$L$5,0) | AC22: =IFERROR(AB22/AA22,0) | AD22: =IFERROR(M22*R22/SUMPRODUCT($M$17:$M$41,$R$17:$R$41)*$M$5,0) | AE22: =X22*Settings!$B$7+Z22*Settings!$B$8+W22*Settings!$B$9+AB22*Settings!$B$10+AD22*Settings!$B$11+S22*Settings!$B$12+T22*Settings!$B$13+U22*Settings!$B$14
A23: RB | B23: Frank Gore | C23: 3 | D23: 24 | E23: role avg (rookie) | J23: 17 | L23: 0.0201 | M23: 0.0732 | N23: 0.75 | O23: 1 | P23: 1 | Q23: 1 | R23: 1 | S23: =IFERROR(K23*$I$5,0) | T23: =IFERROR(K23*$J$5,0) | U23: =IFERROR(K23*$K$5,0) | V23: =IFERROR(L23*$G$5,0) | W23: =IFERROR(V23*N23,0) | X23: =IFERROR(L23*O23/SUMPRODUCT($L$17:$L$41,$O$17:$O$41)*$I$5,0) | Y23: =IFERROR(X23/W23,0) | Z23: =IFERROR(L23*Q23/SUMPRODUCT($L$17:$L$41,$Q$17:$Q$41)*$J$5,0) | AA23: =IFERROR(M23*$H$5,0) | AB23: =IFERROR(M23*P23/SUMPRODUCT($M$17:$M$41,$P$17:$P$41)*$L$5,0) | AC23: =IFERROR(AB23/AA23,0) | AD23: =IFERROR(M23*R23/SUMPRODUCT($M$17:$M$41,$R$17:$R$41)*$M$5,0) | AE23: =X23*Settings!$B$7+Z23*Settings!$B$8+W23*Settings!$B$9+AB23*Settings!$B$10+AD23*Settings!$B$11+S23*Settings!$B$12+T23*Settings!$B$13+U23*Settings!$B$14
A24: RB | B24: Ray Davis | C24: 4 | D24: 26 | E24: ACT | G24: 0.0384 | H24: 0.0271 | I24: 0.1113 | J24: 17 | L24: 0.0192 | M24: 0.0412 | N24: 0.8163 | O24: 0.98 | P24: 0.9 | Q24: 1.4 | R24: 1.78 | S24: =IFERROR(K24*$I$5,0) | T24: =IFERROR(K24*$J$5,0) | U24: =IFERROR(K24*$K$5,0) | V24: =IFERROR(L24*$G$5,0) | W24: =IFERROR(V24*N24,0) | X24: =IFERROR(L24*O24/SUMPRODUCT($L$17:$L$41,$O$17:$O$41)*$I$5,0) | Y24: =IFERROR(X24/W24,0) | Z24: =IFERROR(L24*Q24/SUMPRODUCT($L$17:$L$41,$Q$17:$Q$41)*$J$5,0) | AA24: =IFERROR(M24*$H$5,0) | AB24: =IFERROR(M24*P24/SUMPRODUCT($M$17:$M$41,$P$17:$P$41)*$L$5,0) | AC24: =IFERROR(AB24/AA24,0) | AD24: =IFERROR(M24*R24/SUMPRODUCT($M$17:$M$41,$R$17:$R$41)*$M$5,0) | AE24: =X24*Settings!$B$7+Z24*Settings!$B$8+W24*Settings!$B$9+AB24*Settings!$B$10+AD24*Settings!$B$11+S24*Settings!$B$12+T24*Settings!$B$13+U24*Settings!$B$14
A25: RB | B25: Ian Wheeler | C25: 5 | D25: 24 | E25: role avg (rookie) | J25: 17 | L25: 0.003 | M25: 0.0174 | N25: 0.75 | O25: 1 | P25: 1 | Q25: 1 | R25: 1 | S25: =IFERROR(K25*$I$5,0) | T25: =IFERROR(K25*$J$5,0) | U25: =IFERROR(K25*$K$5,0) | V25: =IFERROR(L25*$G$5,0) | W25: =IFERROR(V25*N25,0) | X25: =IFERROR(L25*O25/SUMPRODUCT($L$17:$L$41,$O$17:$O$41)*$I$5,0) | Y25: =IFERROR(X25/W25,0) | Z25: =IFERROR(L25*Q25/SUMPRODUCT($L$17:$L$41,$Q$17:$Q$41)*$J$5,0) | AA25: =IFERROR(M25*$H$5,0) | AB25: =IFERROR(M25*P25/SUMPRODUCT($M$17:$M$41,$P$17:$P$41)*$L$5,0) | AC25: =IFERROR(AB25/AA25,0) | AD25: =IFERROR(M25*R25/SUMPRODUCT($M$17:$M$41,$R$17:$R$41)*$M$5,0) | AE25: =X25*Settings!$B$7+Z25*Settings!$B$8+W25*Settings!$B$9+AB25*Settings!$B$10+AD25*Settings!$B$11+S25*Settings!$B$12+T25*Settings!$B$13+U25*Settings!$B$14
A26: RB | B26: Jackson Acker | C26: 6 | D26: 23 | E26: role avg (rookie) | J26: 17 | L26: 0.0032 | M26: 0.0043 | N26: 0.75 | O26: 1 | P26: 1 | Q26: 1 | R26: 1 | S26: =IFERROR(K26*$I$5,0) | T26: =IFERROR(K26*$J$5,0) | U26: =IFERROR(K26*$K$5,0) | V26: =IFERROR(L26*$G$5,0) | W26: =IFERROR(V26*N26,0) | X26: =IFERROR(L26*O26/SUMPRODUCT($L$17:$L$41,$O$17:$O$41)*$I$5,0) | Y26: =IFERROR(X26/W26,0) | Z26: =IFERROR(L26*Q26/SUMPRODUCT($L$17:$L$41,$Q$17:$Q$41)*$J$5,0) | AA26: =IFERROR(M26*$H$5,0) | AB26: =IFERROR(M26*P26/SUMPRODUCT($M$17:$M$41,$P$17:$P$41)*$L$5,0) | AC26: =IFERROR(AB26/AA26,0) | AD26: =IFERROR(M26*R26/SUMPRODUCT($M$17:$M$41,$R$17:$R$41)*$M$5,0) | AE26: =X26*Settings!$B$7+Z26*Settings!$B$8+W26*Settings!$B$9+AB26*Settings!$B$10+AD26*Settings!$B$11+S26*Settings!$B$12+T26*Settings!$B$13+U26*Settings!$B$14
A27: RB | B27: Other RBs | S27: =IFERROR(K27*$I$5,0) | T27: =IFERROR(K27*$J$5,0) | U27: =IFERROR(K27*$K$5,0) | V27: =IFERROR(L27*$G$5,0) | W27: =IFERROR(V27*N27,0) | X27: =IFERROR(L27*O27/SUMPRODUCT($L$17:$L$41,$O$17:$O$41)*$I$5,0) | Y27: =IFERROR(X27/W27,0) | Z27: =IFERROR(L27*Q27/SUMPRODUCT($L$17:$L$41,$Q$17:$Q$41)*$J$5,0) | AA27: =IFERROR(M27*$H$5,0) | AB27: =IFERROR(M27*P27/SUMPRODUCT($M$17:$M$41,$P$17:$P$41)*$L$5,0) | AC27: =IFERROR(AB27/AA27,0) | AD27: =IFERROR(M27*R27/SUMPRODUCT($M$17:$M$41,$R$17:$R$41)*$M$5,0) | AE27: =X27*Settings!$B$7+Z27*Settings!$B$8+W27*Settings!$B$9+AB27*Settings!$B$10+AD27*Settings!$B$11+S27*Settings!$B$12+T27*Settings!$B$13+U27*Settings!$B$14
A28: WR | B28: DJ Moore | C28: 1 | D28: 29 | E28: role avg (from CHI) | F28: 0.2851 | G28: 0.2657 | H28: 0.1598 | I28: 0.0304 | J28: 17 | L28: 0.2068 | M28: 0.0132 | N28: 0.6453 | O28: 1.1 | P28: 1.06 | Q28: 0.96 | R28: 1.06 | S28: =IFERROR(K28*$I$5,0) | T28: =IFERROR(K28*$J$5,0) | U28: =IFERROR(K28*$K$5,0) | V28: =IFERROR(L28*$G$5,0) | W28: =IFERROR(V28*N28,0) | X28: =IFERROR(L28*O28/SUMPRODUCT($L$17:$L$41,$O$17:$O$41)*$I$5,0) | Y28: =IFERROR(X28/W28,0) | Z28: =IFERROR(L28*Q28/SUMPRODUCT($L$17:$L$41,$Q$17:$Q$41)*$J$5,0) | AA28: =IFERROR(M28*$H$5,0) | AB28: =IFERROR(M28*P28/SUMPRODUCT($M$17:$M$41,$P$17:$P$41)*$L$5,0) | AC28: =IFERROR(AB28/AA28,0) | AD28: =IFERROR(M28*R28/SUMPRODUCT($M$17:$M$41,$R$17:$R$41)*$M$5,0) | AE28: =X28*Settings!$B$7+Z28*Settings!$B$8+W28*Settings!$B$9+AB28*Settings!$B$10+AD28*Settings!$B$11+S28*Settings!$B$12+T28*Settings!$B$13+U28*Settings!$B$14
A29: WR | B29: Khalil Shakir | C29: 2 | D29: 26 | E29: ACT | F29: 0.0826 | G29: 0.202 | H29: 0.1983 | I29: 0.0019 | J29: 17 | L29: 0.1443 | M29: 0.0034 | N29: 0.7817 | O29: 1.09 | P29: 1 | Q29: 0.95 | R29: 1.18 | S29: =IFERROR(K29*$I$5,0) | T29: =IFERROR(K29*$J$5,0) | U29: =IFERROR(K29*$K$5,0) | V29: =IFERROR(L29*$G$5,0) | W29: =IFERROR(V29*N29,0) | X29: =IFERROR(L29*O29/SUMPRODUCT($L$17:$L$41,$O$17:$O$41)*$I$5,0) | Y29: =IFERROR(X29/W29,0) | Z29: =IFERROR(L29*Q29/SUMPRODUCT($L$17:$L$41,$Q$17:$Q$41)*$J$5,0) | AA29: =IFERROR(M29*$H$5,0) | AB29: =IFERROR(M29*P29/SUMPRODUCT($M$17:$M$41,$P$17:$P$41)*$L$5,0) | AC29: =IFERROR(AB29/AA29,0) | AD29: =IFERROR(M29*R29/SUMPRODUCT($M$17:$M$41,$R$17:$R$41)*$M$5,0) | AE29: =X29*Settings!$B$7+Z29*Settings!$B$8+W29*Settings!$B$9+AB29*Settings!$B$10+AD29*Settings!$B$11+S29*Settings!$B$12+T29*Settings!$B$13+U29*Settings!$B$14
A30: WR | B30: Joshua Palmer | C30: 3 | D30: 26 | E30: ACT | F30: 0.0993 | G30: 0.1324 | H30: 0.0772 | J30: 17 | L30: 0.0875 | M30: 0.0025 | N30: 0.6011 | O30: 1.07 | P30: 1.03 | Q30: 1.05 | R30: 1 | S30: =IFERROR(K30*$I$5,0) | T30: =IFERROR(K30*$J$5,0) | U30: =IFERROR(K30*$K$5,0) | V30: =IFERROR(L30*$G$5,0) | W30: =IFERROR(V30*N30,0) | X30: =IFERROR(L30*O30/SUMPRODUCT($L$17:$L$41,$O$17:$O$41)*$I$5,0) | Y30: =IFERROR(X30/W30,0) | Z30: =IFERROR(L30*Q30/SUMPRODUCT($L$17:$L$41,$Q$17:$Q$41)*$J$5,0) | AA30: =IFERROR(M30*$H$5,0) | AB30: =IFERROR(M30*P30/SUMPRODUCT($M$17:$M$41,$P$17:$P$41)*$L$5,0) | AC30: =IFERROR(AB30/AA30,0) | AD30: =IFERROR(M30*R30/SUMPRODUCT($M$17:$M$41,$R$17:$R$41)*$M$5,0) | AE30: =X30*Settings!$B$7+Z30*Settings!$B$8+W30*Settings!$B$9+AB30*Settings!$B$10+AD30*Settings!$B$11+S30*Settings!$B$12+T30*Settings!$B$13+U30*Settings!$B$14
A31: WR | B31: Keon Coleman | C31: 4 | D31: 23 | E31: ACT | G31: 0.1152 | H31: 0.1232 | J31: 17 | L31: 0.0852 | M31: 0.002 | N31: 0.5933 | O31: 0.98 | P31: 1.04 | Q31: 1.24 | R31: 1 | S31: =IFERROR(K31*$I$5,0) | T31: =IFERROR(K31*$J$5,0) | U31: =IFERROR(K31*$K$5,0) | V31: =IFERROR(L31*$G$5,0) | W31: =IFERROR(V31*N31,0) | X31: =IFERROR(L31*O31/SUMPRODUCT($L$17:$L$41,$O$17:$O$41)*$I$5,0) | Y31: =IFERROR(X31/W31,0) | Z31: =IFERROR(L31*Q31/SUMPRODUCT($L$17:$L$41,$Q$17:$Q$41)*$J$5,0) | AA31: =IFERROR(M31*$H$5,0) | AB31: =IFERROR(M31*P31/SUMPRODUCT($M$17:$M$41,$P$17:$P$41)*$L$5,0) | AC31: =IFERROR(AB31/AA31,0) | AD31: =IFERROR(M31*R31/SUMPRODUCT($M$17:$M$41,$R$17:$R$41)*$M$5,0) | AE31: =X31*Settings!$B$7+Z31*Settings!$B$8+W31*Settings!$B$9+AB31*Settings!$B$10+AD31*Settings!$B$11+S31*Settings!$B$12+T31*Settings!$B$13+U31*Settings!$B$14
A32: WR | B32: Skyler Bell | C32: 5 | D32: 24 | E32: role avg (rookie) | J32: 17 | L32: 0.0224 | M32: 0.0022 | N32: 0.65 | O32: 1 | P32: 1 | Q32: 1 | R32: 1 | S32: =IFERROR(K32*$I$5,0) | T32: =IFERROR(K32*$J$5,0) | U32: =IFERROR(K32*$K$5,0) | V32: =IFERROR(L32*$G$5,0) | W32: =IFERROR(V32*N32,0) | X32: =IFERROR(L32*O32/SUMPRODUCT($L$17:$L$41,$O$17:$O$41)*$I$5,0) | Y32: =IFERROR(X32/W32,0) | Z32: =IFERROR(L32*Q32/SUMPRODUCT($L$17:$L$41,$Q$17:$Q$41)*$J$5,0) | AA32: =IFERROR(M32*$H$5,0) | AB32: =IFERROR(M32*P32/SUMPRODUCT($M$17:$M$41,$P$17:$P$41)*$L$5,0) | AC32: =IFERROR(AB32/AA32,0) | AD32: =IFERROR(M32*R32/SUMPRODUCT($M$17:$M$41,$R$17:$R$41)*$M$5,0) | AE32: =X32*Settings!$B$7+Z32*Settings!$B$8+W32*Settings!$B$9+AB32*Settings!$B$10+AD32*Settings!$B$11+S32*Settings!$B$12+T32*Settings!$B$13+U32*Settings!$B$14
A33: WR | B33: Tyrell Shavers | C33: 6 | D33: 26 | E33: PUP | G33: 0.002 | H33: 0.048 | J33: 17 | L33: 0.0325 | M33: 0.0008 | N33: 0.6855 | O33: 1.5 | P33: 1 | Q33: 1 | R33: 1 | S33: =IFERROR(K33*$I$5,0) | T33: =IFERROR(K33*$J$5,0) | U33: =IFERROR(K33*$K$5,0) | V33: =IFERROR(L33*$G$5,0) | W33: =IFERROR(V33*N33,0) | X33: =IFERROR(L33*O33/SUMPRODUCT($L$17:$L$41,$O$17:$O$41)*$I$5,0) | Y33: =IFERROR(X33/W33,0) | Z33: =IFERROR(L33*Q33/SUMPRODUCT($L$17:$L$41,$Q$17:$Q$41)*$J$5,0) | AA33: =IFERROR(M33*$H$5,0) | AB33: =IFERROR(M33*P33/SUMPRODUCT($M$17:$M$41,$P$17:$P$41)*$L$5,0) | AC33: =IFERROR(AB33/AA33,0) | AD33: =IFERROR(M33*R33/SUMPRODUCT($M$17:$M$41,$R$17:$R$41)*$M$5,0) | AE33: =X33*Settings!$B$7+Z33*Settings!$B$8+W33*Settings!$B$9+AB33*Settings!$B$10+AD33*Settings!$B$11+S33*Settings!$B$12+T33*Settings!$B$13+U33*Settings!$B$14
A34: WR | B34: Trent Sherfield | C34: 7 | D34: 30 | E34: role avg (from DEN) | F34: 0.0404 | G34: 0.0174 | H34: 0.0068 | J34: 17 | L34: 0.0115 | M34: 0.0022 | N34: 0.7395 | O34: 0.94 | P34: 1 | Q34: 1.05 | R34: 1 | S34: =IFERROR(K34*$I$5,0) | T34: =IFERROR(K34*$J$5,0) | U34: =IFERROR(K34*$K$5,0) | V34: =IFERROR(L34*$G$5,0) | W34: =IFERROR(V34*N34,0) | X34: =IFERROR(L34*O34/SUMPRODUCT($L$17:$L$41,$O$17:$O$41)*$I$5,0) | Y34: =IFERROR(X34/W34,0) | Z34: =IFERROR(L34*Q34/SUMPRODUCT($L$17:$L$41,$Q$17:$Q$41)*$J$5,0) | AA34: =IFERROR(M34*$H$5,0) | AB34: =IFERROR(M34*P34/SUMPRODUCT($M$17:$M$41,$P$17:$P$41)*$L$5,0) | AC34: =IFERROR(AB34/AA34,0) | AD34: =IFERROR(M34*R34/SUMPRODUCT($M$17:$M$41,$R$17:$R$41)*$M$5,0) | AE34: =X34*Settings!$B$7+Z34*Settings!$B$8+W34*Settings!$B$9+AB34*Settings!$B$10+AD34*Settings!$B$11+S34*Settings!$B$12+T34*Settings!$B$13+U34*Settings!$B$14
A35: WR | B35: Dante Pettis | C35: 8 | D35: 30 | E35: role avg (from NO) | G35: 0.0542 | H35: 0.0195 | J35: 17 | L35: 0.0033 | M35: 0.002 | N35: 0.6721 | O35: 1.11 | P35: 1 | Q35: 2.5 | R35: 1 | S35: =IFERROR(K35*$I$5,0) | T35: =IFERROR(K35*$J$5,0) | U35: =IFERROR(K35*$K$5,0) | V35: =IFERROR(L35*$G$5,0) | W35: =IFERROR(V35*N35,0) | X35: =IFERROR(L35*O35/SUMPRODUCT($L$17:$L$41,$O$17:$O$41)*$I$5,0) | Y35: =IFERROR(X35/W35,0) | Z35: =IFERROR(L35*Q35/SUMPRODUCT($L$17:$L$41,$Q$17:$Q$41)*$J$5,0) | AA35: =IFERROR(M35*$H$5,0) | AB35: =IFERROR(M35*P35/SUMPRODUCT($M$17:$M$41,$P$17:$P$41)*$L$5,0) | AC35: =IFERROR(AB35/AA35,0) | AD35: =IFERROR(M35*R35/SUMPRODUCT($M$17:$M$41,$R$17:$R$41)*$M$5,0) | AE35: =X35*Settings!$B$7+Z35*Settings!$B$8+W35*Settings!$B$9+AB35*Settings!$B$10+AD35*Settings!$B$11+S35*Settings!$B$12+T35*Settings!$B$13+U35*Settings!$B$14
A36: WR | B36: Other WRs | S36: =IFERROR(K36*$I$5,0) | T36: =IFERROR(K36*$J$5,0) | U36: =IFERROR(K36*$K$5,0) | V36: =IFERROR(L36*$G$5,0) | W36: =IFERROR(V36*N36,0) | X36: =IFERROR(L36*O36/SUMPRODUCT($L$17:$L$41,$O$17:$O$41)*$I$5,0) | Y36: =IFERROR(X36/W36,0) | Z36: =IFERROR(L36*Q36/SUMPRODUCT($L$17:$L$41,$Q$17:$Q$41)*$J$5,0) | AA36: =IFERROR(M36*$H$5,0) | AB36: =IFERROR(M36*P36/SUMPRODUCT($M$17:$M$41,$P$17:$P$41)*$L$5,0) | AC36: =IFERROR(AB36/AA36,0) | AD36: =IFERROR(M36*R36/SUMPRODUCT($M$17:$M$41,$R$17:$R$41)*$M$5,0) | AE36: =X36*Settings!$B$7+Z36*Settings!$B$8+W36*Settings!$B$9+AB36*Settings!$B$10+AD36*Settings!$B$11+S36*Settings!$B$12+T36*Settings!$B$13+U36*Settings!$B$14
A37: TE | B37: Dalton Kincaid | C37: 1 | D37: 26 | E37: ACT | F37: 0.167 | G37: 0.1515 | H37: 0.1023 | J37: 17 | L37: 0.1245 | M37: 0.001 | N37: 0.7352 | O37: 1.07 | P37: 1 | Q37: 0.97 | R37: 1 | S37: =IFERROR(K37*$I$5,0) | T37: =IFERROR(K37*$J$5,0) | U37: =IFERROR(K37*$K$5,0) | V37: =IFERROR(L37*$G$5,0) | W37: =IFERROR(V37*N37,0) | X37: =IFERROR(L37*O37/SUMPRODUCT($L$17:$L$41,$O$17:$O$41)*$I$5,0) | Y37: =IFERROR(X37/W37,0) | Z37: =IFERROR(L37*Q37/SUMPRODUCT($L$17:$L$41,$Q$17:$Q$41)*$J$5,0) | AA37: =IFERROR(M37*$H$5,0) | AB37: =IFERROR(M37*P37/SUMPRODUCT($M$17:$M$41,$P$17:$P$41)*$L$5,0) | AC37: =IFERROR(AB37/AA37,0) | AD37: =IFERROR(M37*R37/SUMPRODUCT($M$17:$M$41,$R$17:$R$41)*$M$5,0) | AE37: =X37*Settings!$B$7+Z37*Settings!$B$8+W37*Settings!$B$9+AB37*Settings!$B$10+AD37*Settings!$B$11+S37*Settings!$B$12+T37*Settings!$B$13+U37*Settings!$B$14
A38: TE | B38: Dawson Knox | C38: 2 | D38: 29 | E38: ACT | F38: 0.0661 | G38: 0.0667 | H38: 0.1023 | J38: 17 | L38: 0.0695 | M38: 0.0009 | N38: 0.695 | O38: 1.01 | P38: 1 | Q38: 1.43 | R38: 1 | S38: =IFERROR(K38*$I$5,0) | T38: =IFERROR(K38*$J$5,0) | U38: =IFERROR(K38*$K$5,0) | V38: =IFERROR(L38*$G$5,0) | W38: =IFERROR(V38*N38,0) | X38: =IFERROR(L38*O38/SUMPRODUCT($L$17:$L$41,$O$17:$O$41)*$I$5,0) | Y38: =IFERROR(X38/W38,0) | Z38: =IFERROR(L38*Q38/SUMPRODUCT($L$17:$L$41,$Q$17:$Q$41)*$J$5,0) | AA38: =IFERROR(M38*$H$5,0) | AB38: =IFERROR(M38*P38/SUMPRODUCT($M$17:$M$41,$P$17:$P$41)*$L$5,0) | AC38: =IFERROR(AB38/AA38,0) | AD38: =IFERROR(M38*R38/SUMPRODUCT($M$17:$M$41,$R$17:$R$41)*$M$5,0) | AE38: =X38*Settings!$B$7+Z38*Settings!$B$8+W38*Settings!$B$9+AB38*Settings!$B$10+AD38*Settings!$B$11+S38*Settings!$B$12+T38*Settings!$B$13+U38*Settings!$B$14
A39: TE | B39: Jackson Hawes | C39: 3 | D39: 25 | E39: ACT | H39: 0.0397 | J39: 17 | L39: 0.0286 | M39: 0.0009 | N39: 0.8421 | O39: 1.09 | P39: 1 | Q39: 1.12 | R39: 1 | S39: =IFERROR(K39*$I$5,0) | T39: =IFERROR(K39*$J$5,0) | U39: =IFERROR(K39*$K$5,0) | V39: =IFERROR(L39*$G$5,0) | W39: =IFERROR(V39*N39,0) | X39: =IFERROR(L39*O39/SUMPRODUCT($L$17:$L$41,$O$17:$O$41)*$I$5,0) | Y39: =IFERROR(X39/W39,0) | Z39: =IFERROR(L39*Q39/SUMPRODUCT($L$17:$L$41,$Q$17:$Q$41)*$J$5,0) | AA39: =IFERROR(M39*$H$5,0) | AB39: =IFERROR(M39*P39/SUMPRODUCT($M$17:$M$41,$P$17:$P$41)*$L$5,0) | AC39: =IFERROR(AB39/AA39,0) | AD39: =IFERROR(M39*R39/SUMPRODUCT($M$17:$M$41,$R$17:$R$41)*$M$5,0) | AE39: =X39*Settings!$B$7+Z39*Settings!$B$8+W39*Settings!$B$9+AB39*Settings!$B$10+AD39*Settings!$B$11+S39*Settings!$B$12+T39*Settings!$B$13+U39*Settings!$B$14
A40: TE | B40: Keleki Latu | C40: 4 | D40: 23 | E40: ACT | H40: 0.0084 | J40: 17 | L40: 0.007 | M40: 0.0009 | N40: 1 | O40: 1.01 | P40: 1 | Q40: 1 | R40: 1 | S40: =IFERROR(K40*$I$5,0) | T40: =IFERROR(K40*$J$5,0) | U40: =IFERROR(K40*$K$5,0) | V40: =IFERROR(L40*$G$5,0) | W40: =IFERROR(V40*N40,0) | X40: =IFERROR(L40*O40/SUMPRODUCT($L$17:$L$41,$O$17:$O$41)*$I$5,0) | Y40: =IFERROR(X40/W40,0) | Z40: =IFERROR(L40*Q40/SUMPRODUCT($L$17:$L$41,$Q$17:$Q$41)*$J$5,0) | AA40: =IFERROR(M40*$H$5,0) | AB40: =IFERROR(M40*P40/SUMPRODUCT($M$17:$M$41,$P$17:$P$41)*$L$5,0) | AC40: =IFERROR(AB40/AA40,0) | AD40: =IFERROR(M40*R40/SUMPRODUCT($M$17:$M$41,$R$17:$R$41)*$M$5,0) | AE40: =X40*Settings!$B$7+Z40*Settings!$B$8+W40*Settings!$B$9+AB40*Settings!$B$10+AD40*Settings!$B$11+S40*Settings!$B$12+T40*Settings!$B$13+U40*Settings!$B$14
A41: TE | B41: Other TEs | S41: =IFERROR(K41*$I$5,0) | T41: =IFERROR(K41*$J$5,0) | U41: =IFERROR(K41*$K$5,0) | V41: =IFERROR(L41*$G$5,0) | W41: =IFERROR(V41*N41,0) | X41: =IFERROR(L41*O41/SUMPRODUCT($L$17:$L$41,$O$17:$O$41)*$I$5,0) | Y41: =IFERROR(X41/W41,0) | Z41: =IFERROR(L41*Q41/SUMPRODUCT($L$17:$L$41,$Q$17:$Q$41)*$J$5,0) | AA41: =IFERROR(M41*$H$5,0) | AB41: =IFERROR(M41*P41/SUMPRODUCT($M$17:$M$41,$P$17:$P$41)*$L$5,0) | AC41: =IFERROR(AB41/AA41,0) | AD41: =IFERROR(M41*R41/SUMPRODUCT($M$17:$M$41,$R$17:$R$41)*$M$5,0) | AE41: =X41*Settings!$B$7+Z41*Settings!$B$8+W41*Settings!$B$9+AB41*Settings!$B$10+AD41*Settings!$B$11+S41*Settings!$B$12+T41*Settings!$B$13+U41*Settings!$B$14
B43: SHARE TOTALS - must equal 100% | E43: each column is a share of this team's season total - it must add to 100% | K43: =SUM(K17:K41) | L43: =SUM(L17:L41) | M43: =SUM(M17:M41) | S43: =SUM(S17:S41) | T43: =SUM(T17:T41) | U43: =SUM(U17:U41) | V43: =SUM(V17:V41) | W43: =SUM(W17:W41) | X43: =SUM(X17:X41) | Y43: =SUM(Y17:Y41) | Z43: =SUM(Z17:Z41) | ... AE43: =SUM(AE17:AE41)
B45: Green = balanced. Red = your shares don't add to 100%; player totals won't match the team totals until they do.

Sheet CAR
A1: CAR - 2026 projections
A3: TEAM TOTALS | C3: blue = edit; everything below divides these up
B4: Games | C4: Plays/G | D4: Plays | E4: Pass Rate | F4: Pass Att | G4: Targets | H4: Rush Att | I4: Pass Yds | J4: Pass TD | K4: Int | L4: Rush Yds | M4: Rush TD
B5: 17 | C5: 60.8 | D5: =C5*B5 | E5: 0.5665 | F5: 545 | G5: =ROUND(F5*Settings!$B$4,0) | H5: 448 | I5: 3513 | J5: 23 | K5: 12 | L5: 1936 | M5: 13
A7: LAST 3 YEARS | B7: Season | C7: Plays | D7: Plays/G | E7: Pass Rate | F7: Pass Att | G7: Rush Att | H7: Pass Yds | I7: Rush Yds | J7: Pass TD | K7: Rush TD | L7: Y/A | M7: Y/C
B8: 2023 | C8: 1096 | D8: 64.4706 | E8: 0.594 | F8: 586 | G8: 445 | H8: 3245 | I8: 1769 | J8: 13 | K8: 7 | L8: 5.5375 | M8: 3.9753
B9: 2024 | C9: 993 | D9: 58.4118 | E9: 0.5871 | F9: 547 | G9: 410 | H9: 3411 | I9: 1878 | J9: 22 | K9: 18 | L9: 6.2358 | M9: 4.5805
B10: 2025 | C10: 1011 | D10: 59.4706 | E10: 0.544 | F10: 515 | G10: 461 | H10: 3304 | I10: 1977 | J10: 24 | K10: 9 | L10: 6.4155 | M10: 4.2885
A12: OUT | B12: 16% of targets and 53% of carries left. Share is team-relative - it does NOT follow the player. | H12: Rico Dowdle (10t/53r -> PIT), Hunter Renfrow (5t/0r -> NOT ON ANY ROSTER)
A13: IN | B13: 5 new: Casey Washington (WR, from ATL - had 3% there), AJ Dillon (RB, from PHI - had 1% there), Kenny Pickett (QB, from LV), John Metchie (WR, from PHI - had 1% there), Feleipe Franks (TE, from ATL)
A14: STAFF | B14: no coaching change recorded - add one in manual/coaching_changes.csv
A16: Pos | B16: Player | C16: Dep | D16: Age | E16: Status | F16: 2023 Tgt% | G16: 2024 Tgt% | H16: 2025 Tgt% | I16: 2025 Rush% | J16: Games | K16: Pass % | L16: Tgt % | M16: Rush % | N16: Catch % | O16: Rec Eff x | P16: Rush Eff x | Q16: RZ Tgt x | R16: RZ Rush x | S16: Pass Yds | T16: Pass TD | U16: Int | V16: Targets | W16: Rec | X16: Rec Yds | Y16: Yds/Rec | Z16: Rec TD | AA16: Rush Att | AB16: Rush Yds | AC16: Yds/Car | AD16: Rush TD | AE16: Half PPR
A17: QB | B17: Bryce Young | C17: 1 | D17: 25 | E17: ACT | I17: 0.088 | J17: 17 | K17: 0.92 | L17: 0.0008 | M17: 0.102 | O17: 1 | P17: 1.26 | Q17: 1 | R17: 1.41 | S17: =IFERROR(K17*$I$5,0) | T17: =IFERROR(K17*$J$5,0) | U17: =IFERROR(K17*$K$5,0) | V17: =IFERROR(L17*$G$5,0) | W17: =IFERROR(V17*N17,0) | X17: =IFERROR(L17*O17/SUMPRODUCT($L$17:$L$41,$O$17:$O$41)*$I$5,0) | Y17: =IFERROR(X17/W17,0) | Z17: =IFERROR(L17*Q17/SUMPRODUCT($L$17:$L$41,$Q$17:$Q$41)*$J$5,0) | AA17: =IFERROR(M17*$H$5,0) | AB17: =IFERROR(M17*P17/SUMPRODUCT($M$17:$M$41,$P$17:$P$41)*$L$5,0) | AC17: =IFERROR(AB17/AA17,0) | AD17: =IFERROR(M17*R17/SUMPRODUCT($M$17:$M$41,$R$17:$R$41)*$M$5,0) | AE17: =X17*Settings!$B$7+Z17*Settings!$B$8+W17*Settings!$B$9+AB17*Settings!$B$10+AD17*Settings!$B$11+S17*Settings!$B$12+T17*Settings!$B$13+U17*Settings!$B$14
A18: QB | B18: Kenny Pickett | C18: 2 | D18: 28 | E18: role avg (from LV) | I18: 0.0138 | J18: 17 | K18: 0.068 | L18: 0.0018 | M18: 0.0156 | O18: 1 | P18: 0.93 | Q18: 1 | R18: 1.58 | S18: =IFERROR(K18*$I$5,0) | T18: =IFERROR(K18*$J$5,0) | U18: =IFERROR(K18*$K$5,0) | V18: =IFERROR(L18*$G$5,0) | W18: =IFERROR(V18*N18,0) | X18: =IFERROR(L18*O18/SUMPRODUCT($L$17:$L$41,$O$17:$O$41)*$I$5,0) | Y18: =IFERROR(X18/W18,0) | Z18: =IFERROR(L18*Q18/SUMPRODUCT($L$17:$L$41,$Q$17:$Q$41)*$J$5,0) | AA18: =IFERROR(M18*$H$5,0) | AB18: =IFERROR(M18*P18/SUMPRODUCT($M$17:$M$41,$P$17:$P$41)*$L$5,0) | AC18: =IFERROR(AB18/AA18,0) | AD18: =IFERROR(M18*R18/SUMPRODUCT($M$17:$M$41,$R$17:$R$41)*$M$5,0) | AE18: =X18*Settings!$B$7+Z18*Settings!$B$8+W18*Settings!$B$9+AB18*Settings!$B$10+AD18*Settings!$B$11+S18*Settings!$B$12+T18*Settings!$B$13+U18*Settings!$B$14
A19: QB | B19: Haynes King | C19: 3 | D19: 25 | E19: role avg (rookie) | J19: 17 | K19: 0.012 | L19: 0.0018 | M19: 0.0116 | O19: 1 | P19: 1 | Q19: 1 | R19: 1 | S19: =IFERROR(K19*$I$5,0) | T19: =IFERROR(K19*$J$5,0) | U19: =IFERROR(K19*$K$5,0) | V19: =IFERROR(L19*$G$5,0) | W19: =IFERROR(V19*N19,0) | X19: =IFERROR(L19*O19/SUMPRODUCT($L$17:$L$41,$O$17:$O$41)*$I$5,0) | Y19: =IFERROR(X19/W19,0) | Z19: =IFERROR(L19*Q19/SUMPRODUCT($L$17:$L$41,$Q$17:$Q$41)*$J$5,0) | AA19: =IFERROR(M19*$H$5,0) | AB19: =IFERROR(M19*P19/SUMPRODUCT($M$17:$M$41,$P$17:$P$41)*$L$5,0) | AC19: =IFERROR(AB19/AA19,0) | AD19: =IFERROR(M19*R19/SUMPRODUCT($M$17:$M$41,$R$17:$R$41)*$M$5,0) | AE19: =X19*Settings!$B$7+Z19*Settings!$B$8+W19*Settings!$B$9+AB19*Settings!$B$10+AD19*Settings!$B$11+S19*Settings!$B$12+T19*Settings!$B$13+U19*Settings!$B$14
A20: QB | B20: Other QBs | S20: =IFERROR(K20*$I$5,0) | T20: =IFERROR(K20*$J$5,0) | U20: =IFERROR(K20*$K$5,0) | V20: =IFERROR(L20*$G$5,0) | W20: =IFERROR(V20*N20,0) | X20: =IFERROR(L20*O20/SUMPRODUCT($L$17:$L$41,$O$17:$O$41)*$I$5,0) | Y20: =IFERROR(X20/W20,0) | Z20: =IFERROR(L20*Q20/SUMPRODUCT($L$17:$L$41,$Q$17:$Q$41)*$J$5,0) | AA20: =IFERROR(M20*$H$5,0) | AB20: =IFERROR(M20*P20/SUMPRODUCT($M$17:$M$41,$P$17:$P$41)*$L$5,0) | AC20: =IFERROR(AB20/AA20,0) | AD20: =IFERROR(M20*R20/SUMPRODUCT($M$17:$M$41,$R$17:$R$41)*$M$5,0) | AE20: =X20*Settings!$B$7+Z20*Settings!$B$8+W20*Settings!$B$9+AB20*Settings!$B$10+AD20*Settings!$B$11+S20*Settings!$B$12+T20*Settings!$B$13+U20*Settings!$B$14
A21: RB | B21: Chuba Hubbard | C21: 1 | D21: 27 | E21: ACT | F21: 0.0824 | G21: 0.1042 | H21: 0.0813 | I21: 0.3025 | J21: 17 | L21: 0.0879 | M21: 0.5811 | N21: 0.803 | O21: 0.82 | P21: 0.93 | Q21: 1.01 | R21: 0.91 | S21: =IFERROR(K21*$I$5,0) | T21: =IFERROR(K21*$J$5,0) | U21: =IFERROR(K21*$K$5,0) | V21: =IFERROR(L21*$G$5,0) | W21: =IFERROR(V21*N21,0) | X21: =IFERROR(L21*O21/SUMPRODUCT($L$17:$L$41,$O$17:$O$41)*$I$5,0) | Y21: =IFERROR(X21/W21,0) | Z21: =IFERROR(L21*Q21/SUMPRODUCT($L$17:$L$41,$Q$17:$Q$41)*$J$5,0) | AA21: =IFERROR(M21*$H$5,0) | AB21: =IFERROR(M21*P21/SUMPRODUCT($M$17:$M$41,$P$17:$P$41)*$L$5,0) | AC21: =IFERROR(AB21/AA21,0) | AD21: =IFERROR(M21*R21/SUMPRODUCT($M$17:$M$41,$R$17:$R$41)*$M$5,0) | AE21: =X21*Settings!$B$7+Z21*Settings!$B$8+W21*Settings!$B$9+AB21*Settings!$B$10+AD21*Settings!$B$11+S21*Settings!$B$12+T21*Settings!$B$13+U21*Settings!$B$14
A22: RB | B22: Jonathon Brooks | C22: 2 | D22: 23 | E22: ACT | G22: 0.0058 | J22: 17 | L22: 0.0256 | M22: 0.1224 | N22: 1 | O22: 1.02 | P22: 0.85 | Q22: 1.01 | R22: 0.86 | S22: =IFERROR(K22*$I$5,0) | T22: =IFERROR(K22*$J$5,0) | U22: =IFERROR(K22*$K$5,0) | V22: =IFERROR(L22*$G$5,0) | W22: =IFERROR(V22*N22,0) | X22: =IFERROR(L22*O22/SUMPRODUCT($L$17:$L$41,$O$17:$O$41)*$I$5,0) | Y22: =IFERROR(X22/W22,0) | Z22: =IFERROR(L22*Q22/SUMPRODUCT($L$17:$L$41,$Q$17:$Q$41)*$J$5,0) | AA22: =IFERROR(M22*$H$5,0) | AB22: =IFERROR(M22*P22/SUMPRODUCT($M$17:$M$41,$P$17:$P$41)*$L$5,0) | AC22: =IFERROR(AB22/AA22,0) | AD22: =IFERROR(M22*R22/SUMPRODUCT($M$17:$M$41,$R$17:$R$41)*$M$5,0) | AE22: =X22*Settings!$B$7+Z22*Settings!$B$8+W22*Settings!$B$9+AB22*Settings!$B$10+AD22*Settings!$B$11+S22*Settings!$B$12+T22*Settings!$B$13+U22*Settings!$B$14
A23: RB | B23: AJ Dillon | C23: 3 | D23: 28 | E23: role avg (from PHI) | F23: 0.0499 | H23: 0.0065 | I23: 0.026 | J23: 17 | L23: 0.0127 | M23: 0.0632 | N23: 0.9011 | O23: 1 | P23: 0.98 | Q23: 1.01 | R23: 2.5 | S23: =IFERROR(K23*$I$5,0) | T23: =IFERROR(K23*$J$5,0) | U23: =IFERROR(K23*$K$5,0) | V23: =IFERROR(L23*$G$5,0) | W23: =IFERROR(V23*N23,0) | X23: =IFERROR(L23*O23/SUMPRODUCT($L$17:$L$41,$O$17:$O$41)*$I$5,0) | Y23: =IFERROR(X23/W23,0) | Z23: =IFERROR(L23*Q23/SUMPRODUCT($L$17:$L$41,$Q$17:$Q$41)*$J$5,0) | AA23: =IFERROR(M23*$H$5,0) | AB23: =IFERROR(M23*P23/SUMPRODUCT($M$17:$M$41,$P$17:$P$41)*$L$5,0) | AC23: =IFERROR(AB23/AA23,0) | AD23: =IFERROR(M23*R23/SUMPRODUCT($M$17:$M$41,$R$17:$R$41)*$M$5,0) | AE23: =X23*Settings!$B$7+Z23*Settings!$B$8+W23*Settings!$B$9+AB23*Settings!$B$10+AD23*Settings!$B$11+S23*Settings!$B$12+T23*Settings!$B$13+U23*Settings!$B$14
A24: RB | B24: Trevor Etienne | C24: 4 | D24: 22 | E24: ACT | H24: 0.0063 | I24: 0.0451 | J24: 17 | L24: 0.0062 | M24: 0.0395 | N24: 1 | O24: 0.95 | P24: 1.03 | Q24: 1 | R24: 1.29 | S24: =IFERROR(K24*$I$5,0) | T24: =IFERROR(K24*$J$5,0) | U24: =IFERROR(K24*$K$5,0) | V24: =IFERROR(L24*$G$5,0) | W24: =IFERROR(V24*N24,0) | X24: =IFERROR(L24*O24/SUMPRODUCT($L$17:$L$41,$O$17:$O$41)*$I$5,0) | Y24: =IFERROR(X24/W24,0) | Z24: =IFERROR(L24*Q24/SUMPRODUCT($L$17:$L$41,$Q$17:$Q$41)*$J$5,0) | AA24: =IFERROR(M24*$H$5,0) | AB24: =IFERROR(M24*P24/SUMPRODUCT($M$17:$M$41,$P$17:$P$41)*$L$5,0) | AC24: =IFERROR(AB24/AA24,0) | AD24: =IFERROR(M24*R24/SUMPRODUCT($M$17:$M$41,$R$17:$R$41)*$M$5,0) | AE24: =X24*Settings!$B$7+Z24*Settings!$B$8+W24*Settings!$B$9+AB24*Settings!$B$10+AD24*Settings!$B$11+S24*Settings!$B$12+T24*Settings!$B$13+U24*Settings!$B$14
A25: RB | B25: Anthony Tyus | C25: 5 | D25: 23 | E25: role avg (rookie) | J25: 17 | L25: 0.0045 | M25: 0.0197 | N25: 0.75 | O25: 1 | P25: 1 | Q25: 1 | R25: 1 | S25: =IFERROR(K25*$I$5,0) | T25: =IFERROR(K25*$J$5,0) | U25: =IFERROR(K25*$K$5,0) | V25: =IFERROR(L25*$G$5,0) | W25: =IFERROR(V25*N25,0) | X25: =IFERROR(L25*O25/SUMPRODUCT($L$17:$L$41,$O$17:$O$41)*$I$5,0) | Y25: =IFERROR(X25/W25,0) | Z25: =IFERROR(L25*Q25/SUMPRODUCT($L$17:$L$41,$Q$17:$Q$41)*$J$5,0) | AA25: =IFERROR(M25*$H$5,0) | AB25: =IFERROR(M25*P25/SUMPRODUCT($M$17:$M$41,$P$17:$P$41)*$L$5,0) | AC25: =IFERROR(AB25/AA25,0) | AD25: =IFERROR(M25*R25/SUMPRODUCT($M$17:$M$41,$R$17:$R$41)*$M$5,0) | AE25: =X25*Settings!$B$7+Z25*Settings!$B$8+W25*Settings!$B$9+AB25*Settings!$B$10+AD25*Settings!$B$11+S25*Settings!$B$12+T25*Settings!$B$13+U25*Settings!$B$14
A26: RB | B26: Miles Davis | C26: 6 | D26: 26 | E26: role avg (rookie) | J26: 17 | L26: 0.0034 | M26: 0.0052 | N26: 0.75 | O26: 1 | P26: 1 | Q26: 1 | R26: 1 | S26: =IFERROR(K26*$I$5,0) | T26: =IFERROR(K26*$J$5,0) | U26: =IFERROR(K26*$K$5,0) | V26: =IFERROR(L26*$G$5,0) | W26: =IFERROR(V26*N26,0) | X26: =IFERROR(L26*O26/SUMPRODUCT($L$17:$L$41,$O$17:$O$41)*$I$5,0) | Y26: =IFERROR(X26/W26,0) | Z26: =IFERROR(L26*Q26/SUMPRODUCT($L$17:$L$41,$Q$17:$Q$41)*$J$5,0) | AA26: =IFERROR(M26*$H$5,0) | AB26: =IFERROR(M26*P26/SUMPRODUCT($M$17:$M$41,$P$17:$P$41)*$L$5,0) | AC26: =IFERROR(AB26/AA26,0) | AD26: =IFERROR(M26*R26/SUMPRODUCT($M$17:$M$41,$R$17:$R$41)*$M$5,0) | AE26: =X26*Settings!$B$7+Z26*Settings!$B$8+W26*Settings!$B$9+AB26*Settings!$B$10+AD26*Settings!$B$11+S26*Settings!$B$12+T26*Settings!$B$13+U26*Settings!$B$14
A27: RB | B27: Other RBs | S27: =IFERROR(K27*$I$5,0) | T27: =IFERROR(K27*$J$5,0) | U27: =IFERROR(K27*$K$5,0) | V27: =IFERROR(L27*$G$5,0) | W27: =IFERROR(V27*N27,0) | X27: =IFERROR(L27*O27/SUMPRODUCT($L$17:$L$41,$O$17:$O$41)*$I$5,0) | Y27: =IFERROR(X27/W27,0) | Z27: =IFERROR(L27*Q27/SUMPRODUCT($L$17:$L$41,$Q$17:$Q$41)*$J$5,0) | AA27: =IFERROR(M27*$H$5,0) | AB27: =IFERROR(M27*P27/SUMPRODUCT($M$17:$M$41,$P$17:$P$41)*$L$5,0) | AC27: =IFERROR(AB27/AA27,0) | AD27: =IFERROR(M27*R27/SUMPRODUCT($M$17:$M$41,$R$17:$R$41)*$M$5,0) | AE27: =X27*Settings!$B$7+Z27*Settings!$B$8+W27*Settings!$B$9+AB27*Settings!$B$10+AD27*Settings!$B$11+S27*Settings!$B$12+T27*Settings!$B$13+U27*Settings!$B$14
A28: WR | B28: Tetairoa McMillan | C28: 1 | D28: 23 | E28: ACT | H28: 0.2542 | J28: 17 | L28: 0.2323 | M28: 0.0087 | N28: 0.5738 | O28: 1.18 | P28: 1 | Q28: 0.95 | R28: 1 | S28: =IFERROR(K28*$I$5,0) | T28: =IFERROR(K28*$J$5,0) | U28: =IFERROR(K28*$K$5,0) | V28: =IFERROR(L28*$G$5,0) | W28: =IFERROR(V28*N28,0) | X28: =IFERROR(L28*O28/SUMPRODUCT($L$17:$L$41,$O$17:$O$41)*$I$5,0) | Y28: =IFERROR(X28/W28,0) | Z28: =IFERROR(L28*Q28/SUMPRODUCT($L$17:$L$41,$Q$17:$Q$41)*$J$5,0) | AA28: =IFERROR(M28*$H$5,0) | AB28: =IFERROR(M28*P28/SUMPRODUCT($M$17:$M$41,$P$17:$P$41)*$L$5,0) | AC28: =IFERROR(AB28/AA28,0) | AD28: =IFERROR(M28*R28/SUMPRODUCT($M$17:$M$41,$R$17:$R$41)*$M$5,0) | AE28: =X28*Settings!$B$7+Z28*Settings!$B$8+W28*Settings!$B$9+AB28*Settings!$B$10+AD28*Settings!$B$11+S28*Settings!$B$12+T28*Settings!$B$13+U28*Settings!$B$14
A29: WR | B29: John Metchie | C29: 2 | D29: 26 | E29: role avg (from PHI) | F29: 0.053 | G29: 0.0676 | H29: 0.0086 | J29: 17 | L29: 0.1345 | M29: 0.0089 | N29: 0.7298 | O29: 0.86 | P29: 1 | Q29: 0.83 | R29: 1.08 | S29: =IFERROR(K29*$I$5,0) | T29: =IFERROR(K29*$J$5,0) | U29: =IFERROR(K29*$K$5,0) | V29: =IFERROR(L29*$G$5,0) | W29: =IFERROR(V29*N29,0) | X29: =IFERROR(L29*O29/SUMPRODUCT($L$17:$L$41,$O$17:$O$41)*$I$5,0) | Y29: =IFERROR(X29/W29,0) | Z29: =IFERROR(L29*Q29/SUMPRODUCT($L$17:$L$41,$Q$17:$Q$41)*$J$5,0) | AA29: =IFERROR(M29*$H$5,0) | AB29: =IFERROR(M29*P29/SUMPRODUCT($M$17:$M$41,$P$17:$P$41)*$L$5,0) | AC29: =IFERROR(AB29/AA29,0) | AD29: =IFERROR(M29*R29/SUMPRODUCT($M$17:$M$41,$R$17:$R$41)*$M$5,0) | AE29: =X29*Settings!$B$7+Z29*Settings!$B$8+W29*Settings!$B$9+AB29*Settings!$B$10+AD29*Settings!$B$11+S29*Settings!$B$12+T29*Settings!$B$13+U29*Settings!$B$14
A30: WR | B30: Jalen Coker | C30: 3 | D30: 24 | E30: ACT | G30: 0.0888 | H30: 0.0896 | J30: 17 | L30: 0.09 | M30: 0.0014 | N30: 0.7405 | O30: 1.29 | P30: 1 | Q30: 0.89 | R30: 1 | S30: =IFERROR(K30*$I$5,0) | T30: =IFERROR(K30*$J$5,0) | U30: =IFERROR(K30*$K$5,0) | V30: =IFERROR(L30*$G$5,0) | W30: =IFERROR(V30*N30,0) | X30: =IFERROR(L30*O30/SUMPRODUCT($L$17:$L$41,$O$17:$O$41)*$I$5,0) | Y30: =IFERROR(X30/W30,0) | Z30: =IFERROR(L30*Q30/SUMPRODUCT($L$17:$L$41,$Q$17:$Q$41)*$J$5,0) | AA30: =IFERROR(M30*$H$5,0) | AB30: =IFERROR(M30*P30/SUMPRODUCT($M$17:$M$41,$P$17:$P$41)*$L$5,0) | AC30: =IFERROR(AB30/AA30,0) | AD30: =IFERROR(M30*R30/SUMPRODUCT($M$17:$M$41,$R$17:$R$41)*$M$5,0) | AE30: =X30*Settings!$B$7+Z30*Settings!$B$8+W30*Settings!$B$9+AB30*Settings!$B$10+AD30*Settings!$B$11+S30*Settings!$B$12+T30*Settings!$B$13+U30*Settings!$B$14
A31: WR | B31: Xavier Legette | C31: 4 | D31: 25 | E31: QUESTIONABLE | G31: 0.1622 | H31: 0.1333 | I31: 0.0023 | J31: 17 | L31: 0.1056 | M31: 0.0036 | N31: 0.5611 | O31: 0.89 | P31: 0.98 | Q31: 1.29 | R31: 1 | S31: =IFERROR(K31*$I$5,0) | T31: =IFERROR(K31*$J$5,0) | U31: =IFERROR(K31*$K$5,0) | V31: =IFERROR(L31*$G$5,0) | W31: =IFERROR(V31*N31,0) | X31: =IFERROR(L31*O31/SUMPRODUCT($L$17:$L$41,$O$17:$O$41)*$I$5,0) | Y31: =IFERROR(X31/W31,0) | Z31: =IFERROR(L31*Q31/SUMPRODUCT($L$17:$L$41,$Q$17:$Q$41)*$J$5,0) | AA31: =IFERROR(M31*$H$5,0) | AB31: =IFERROR(M31*P31/SUMPRODUCT($M$17:$M$41,$P$17:$P$41)*$L$5,0) | AC31: =IFERROR(AB31/AA31,0) | AD31: =IFERROR(M31*R31/SUMPRODUCT($M$17:$M$41,$R$17:$R$41)*$M$5,0) | AE31: =X31*Settings!$B$7+Z31*Settings!$B$8+W31*Settings!$B$9+AB31*Settings!$B$10+AD31*Settings!$B$11+S31*Settings!$B$12+T31*Settings!$B$13+U31*Settings!$B$14
A32: WR | B32: David Moore | C32: 5 | D32: 31 | E32: ACT | F32: 0.0127 | G32: 0.11 | H32: 0.0021 | I32: 0.0023 | J32: 17 | L32: 0.048 | M32: 0.0027 | N32: 0.6898 | O32: 1.02 | P32: 1.08 | Q32: 2.19 | R32: 1.63 | S32: =IFERROR(K32*$I$5,0) | T32: =IFERROR(K32*$J$5,0) | U32: =IFERROR(K32*$K$5,0) | V32: =IFERROR(L32*$G$5,0) | W32: =IFERROR(V32*N32,0) | X32: =IFERROR(L32*O32/SUMPRODUCT($L$17:$L$41,$O$17:$O$41)*$I$5,0) | Y32: =IFERROR(X32/W32,0) | Z32: =IFERROR(L32*Q32/SUMPRODUCT($L$17:$L$41,$Q$17:$Q$41)*$J$5,0) | AA32: =IFERROR(M32*$H$5,0) | AB32: =IFERROR(M32*P32/SUMPRODUCT($M$17:$M$41,$P$17:$P$41)*$L$5,0) | AC32: =IFERROR(AB32/AA32,0) | AD32: =IFERROR(M32*R32/SUMPRODUCT($M$17:$M$41,$R$17:$R$41)*$M$5,0) | AE32: =X32*Settings!$B$7+Z32*Settings!$B$8+W32*Settings!$B$9+AB32*Settings!$B$10+AD32*Settings!$B$11+S32*Settings!$B$12+T32*Settings!$B$13+U32*Settings!$B$14
A33: WR | B33: Jimmy Horn | C33: 6 | D33: 23 | E33: ACT | H33: 0.0312 | I33: 0.0181 | J33: 17 | L33: 0.024 | M33: 0.0052 | N33: 0.7333 | O33: 1.02 | P33: 1.27 | Q33: 1.21 | R33: 1 | S33: =IFERROR(K33*$I$5,0) | T33: =IFERROR(K33*$J$5,0) | U33: =IFERROR(K33*$K$5,0) | V33: =IFERROR(L33*$G$5,0) | W33: =IFERROR(V33*N33,0) | X33: =IFERROR(L33*O33/SUMPRODUCT($L$17:$L$41,$O$17:$O$41)*$I$5,0) | Y33: =IFERROR(X33/W33,0) | Z33: =IFERROR(L33*Q33/SUMPRODUCT($L$17:$L$41,$Q$17:$Q$41)*$J$5,0) | AA33: =IFERROR(M33*$H$5,0) | AB33: =IFERROR(M33*P33/SUMPRODUCT($M$17:$M$41,$P$17:$P$41)*$L$5,0) | AC33: =IFERROR(AB33/AA33,0) | AD33: =IFERROR(M33*R33/SUMPRODUCT($M$17:$M$41,$R$17:$R$41)*$M$5,0) | AE33: =X33*Settings!$B$7+Z33*Settings!$B$8+W33*Settings!$B$9+AB33*Settings!$B$10+AD33*Settings!$B$11+S33*Settings!$B$12+T33*Settings!$B$13+U33*Settings!$B$14
A34: WR | B34: Brycen Tremayne | C34: 7 | D34: 26 | E34: ACT | G34: 0.002 | H34: 0.0375 | J34: 17 | L34: 0.0221 | M34: 0.001 | N34: 0.7933 | O34: 1.08 | P34: 1 | Q34: 0.96 | R34: 1 | S34: =IFERROR(K34*$I$5,0) | T34: =IFERROR(K34*$J$5,0) | U34: =IFERROR(K34*$K$5,0) | V34: =IFERROR(L34*$G$5,0) | W34: =IFERROR(V34*N34,0) | X34: =IFERROR(L34*O34/SUMPRODUCT($L$17:$L$41,$O$17:$O$41)*$I$5,0) | Y34: =IFERROR(X34/W34,0) | Z34: =IFERROR(L34*Q34/SUMPRODUCT($L$17:$L$41,$Q$17:$Q$41)*$J$5,0) | AA34: =IFERROR(M34*$H$5,0) | AB34: =IFERROR(M34*P34/SUMPRODUCT($M$17:$M$41,$P$17:$P$41)*$L$5,0) | AC34: =IFERROR(AB34/AA34,0) | AD34: =IFERROR(M34*R34/SUMPRODUCT($M$17:$M$41,$R$17:$R$41)*$M$5,0) | AE34: =X34*Settings!$B$7+Z34*Settings!$B$8+W34*Settings!$B$9+AB34*Settings!$B$10+AD34*Settings!$B$11+S34*Settings!$B$12+T34*Settings!$B$13+U34*Settings!$B$14
A35: WR | B35: Casey Washington | C35: 8 | D35: 25 | E35: role avg (from ATL) | G35: 0.0037 | H35: 0.027 | J35: 17 | L35: 0.0048 | M35: 0.0024 | N35: 0.4576 | O35: 0.97 | P35: 1 | Q35: 1 | R35: 1 | S35: =IFERROR(K35*$I$5,0) | T35: =IFERROR(K35*$J$5,0) | U35: =IFERROR(K35*$K$5,0) | V35: =IFERROR(L35*$G$5,0) | W35: =IFERROR(V35*N35,0) | X35: =IFERROR(L35*O35/SUMPRODUCT($L$17:$L$41,$O$17:$O$41)*$I$5,0) | Y35: =IFERROR(X35/W35,0) | Z35: =IFERROR(L35*Q35/SUMPRODUCT($L$17:$L$41,$Q$17:$Q$41)*$J$5,0) | AA35: =IFERROR(M35*$H$5,0) | AB35: =IFERROR(M35*P35/SUMPRODUCT($M$17:$M$41,$P$17:$P$41)*$L$5,0) | AC35: =IFERROR(AB35/AA35,0) | AD35: =IFERROR(M35*R35/SUMPRODUCT($M$17:$M$41,$R$17:$R$41)*$M$5,0) | AE35: =X35*Settings!$B$7+Z35*Settings!$B$8+W35*Settings!$B$9+AB35*Settings!$B$10+AD35*Settings!$B$11+S35*Settings!$B$12+T35*Settings!$B$13+U35*Settings!$B$14
A36: WR | B36: Other WRs | S36: =IFERROR(K36*$I$5,0) | T36: =IFERROR(K36*$J$5,0) | U36: =IFERROR(K36*$K$5,0) | V36: =IFERROR(L36*$G$5,0) | W36: =IFERROR(V36*N36,0) | X36: =IFERROR(L36*O36/SUMPRODUCT($L$17:$L$41,$O$17:$O$41)*$I$5,0) | Y36: =IFERROR(X36/W36,0) | Z36: =IFERROR(L36*Q36/SUMPRODUCT($L$17:$L$41,$Q$17:$Q$41)*$J$5,0) | AA36: =IFERROR(M36*$H$5,0) | AB36: =IFERROR(M36*P36/SUMPRODUCT($M$17:$M$41,$P$17:$P$41)*$L$5,0) | AC36: =IFERROR(AB36/AA36,0) | AD36: =IFERROR(M36*R36/SUMPRODUCT($M$17:$M$41,$R$17:$R$41)*$M$5,0) | AE36: =X36*Settings!$B$7+Z36*Settings!$B$8+W36*Settings!$B$9+AB36*Settings!$B$10+AD36*Settings!$B$11+S36*Settings!$B$12+T36*Settings!$B$13+U36*Settings!$B$14
A37: TE | B37: Ja'Tavion Sanders | C37: 1 | D37: 23 | E37: QUESTIONABLE | G37: 0.083 | H37: 0.0708 | J37: 17 | L37: 0.0861 | M37: 0.0012 | N37: 0.8166 | O37: 0.99 | P37: 1 | Q37: 1.09 | R37: 1 | S37: =IFERROR(K37*$I$5,0) | T37: =IFERROR(K37*$J$5,0) | U37: =IFERROR(K37*$K$5,0) | V37: =IFERROR(L37*$G$5,0) | W37: =IFERROR(V37*N37,0) | X37: =IFERROR(L37*O37/SUMPRODUCT($L$17:$L$41,$O$17:$O$41)*$I$5,0) | Y37: =IFERROR(X37/W37,0) | Z37: =IFERROR(L37*Q37/SUMPRODUCT($L$17:$L$41,$Q$17:$Q$41)*$J$5,0) | AA37: =IFERROR(M37*$H$5,0) | AB37: =IFERROR(M37*P37/SUMPRODUCT($M$17:$M$41,$P$17:$P$41)*$L$5,0) | AC37: =IFERROR(AB37/AA37,0) | AD37: =IFERROR(M37*R37/SUMPRODUCT($M$17:$M$41,$R$17:$R$41)*$M$5,0) | AE37: =X37*Settings!$B$7+Z37*Settings!$B$8+W37*Settings!$B$9+AB37*Settings!$B$10+AD37*Settings!$B$11+S37*Settings!$B$12+T37*Settings!$B$13+U37*Settings!$B$14
A38: TE | B38: Tommy Tremble | C38: 2 | D38: 26 | E38: ACT | F38: 0.0599 | G38: 0.0618 | H38: 0.0771 | J38: 17 | L38: 0.0616 | M38: 0.001 | N38: 0.7248 | O38: 1.01 | P38: 1 | Q38: 1.06 | R38: 1 | S38: =IFERROR(K38*$I$5,0) | T38: =IFERROR(K38*$J$5,0) | U38: =IFERROR(K38*$K$5,0) | V38: =IFERROR(L38*$G$5,0) | W38: =IFERROR(V38*N38,0) | X38: =IFERROR(L38*O38/SUMPRODUCT($L$17:$L$41,$O$17:$O$41)*$I$5,0) | Y38: =IFERROR(X38/W38,0) | Z38: =IFERROR(L38*Q38/SUMPRODUCT($L$17:$L$41,$Q$17:$Q$41)*$J$5,0) | AA38: =IFERROR(M38*$H$5,0) | AB38: =IFERROR(M38*P38/SUMPRODUCT($M$17:$M$41,$P$17:$P$41)*$L$5,0) | AC38: =IFERROR(AB38/AA38,0) | AD38: =IFERROR(M38*R38/SUMPRODUCT($M$17:$M$41,$R$17:$R$41)*$M$5,0) | AE38: =X38*Settings!$B$7+Z38*Settings!$B$8+W38*Settings!$B$9+AB38*Settings!$B$10+AD38*Settings!$B$11+S38*Settings!$B$12+T38*Settings!$B$13+U38*Settings!$B$14
A39: TE | B39: Mitchell Evans | C39: 3 | D39: 23 | E39: ACT | H39: 0.0521 | I39: 0.0023 | J39: 17 | L39: 0.0404 | M39: 0.0027 | N39: 0.76 | O39: 1 | P39: 0.96 | Q39: 1.14 | R39: 1 | S39: =IFERROR(K39*$I$5,0) | T39: =IFERROR(K39*$J$5,0) | U39: =IFERROR(K39*$K$5,0) | V39: =IFERROR(L39*$G$5,0) | W39: =IFERROR(V39*N39,0) | X39: =IFERROR(L39*O39/SUMPRODUCT($L$17:$L$41,$O$17:$O$41)*$I$5,0) | Y39: =IFERROR(X39/W39,0) | Z39: =IFERROR(L39*Q39/SUMPRODUCT($L$17:$L$41,$Q$17:$Q$41)*$J$5,0) | AA39: =IFERROR(M39*$H$5,0) | AB39: =IFERROR(M39*P39/SUMPRODUCT($M$17:$M$41,$P$17:$P$41)*$L$5,0) | AC39: =IFERROR(AB39/AA39,0) | AD39: =IFERROR(M39*R39/SUMPRODUCT($M$17:$M$41,$R$17:$R$41)*$M$5,0) | AE39: =X39*Settings!$B$7+Z39*Settings!$B$8+W39*Settings!$B$9+AB39*Settings!$B$10+AD39*Settings!$B$11+S39*Settings!$B$12+T39*Settings!$B$13+U39*Settings!$B$14
A40: TE | B40: James Mitchell | C40: 4 | D40: 26 | E40: ACT | F40: 0.0035 | H40: 0.0063 | J40: 17 | L40: 0.0058 | M40: 0.001 | N40: 1 | O40: 1.06 | P40: 1 | Q40: 1 | R40: 1 | S40: =IFERROR(K40*$I$5,0) | T40: =IFERROR(K40*$J$5,0) | U40: =IFERROR(K40*$K$5,0) | V40: =IFERROR(L40*$G$5,0) | W40: =IFERROR(V40*N40,0) | X40: =IFERROR(L40*O40/SUMPRODUCT($L$17:$L$41,$O$17:$O$41)*$I$5,0) | Y40: =IFERROR(X40/W40,0) | Z40: =IFERROR(L40*Q40/SUMPRODUCT($L$17:$L$41,$Q$17:$Q$41)*$J$5,0) | AA40: =IFERROR(M40*$H$5,0) | AB40: =IFERROR(M40*P40/SUMPRODUCT($M$17:$M$41,$P$17:$P$41)*$L$5,0) | AC40: =IFERROR(AB40/AA40,0) | AD40: =IFERROR(M40*R40/SUMPRODUCT($M$17:$M$41,$R$17:$R$41)*$M$5,0) | AE40: =X40*Settings!$B$7+Z40*Settings!$B$8+W40*Settings!$B$9+AB40*Settings!$B$10+AD40*Settings!$B$11+S40*Settings!$B$12+T40*Settings!$B$13+U40*Settings!$B$14
A41: TE | B41: Other TEs | S41: =IFERROR(K41*$I$5,0) | T41: =IFERROR(K41*$J$5,0) | U41: =IFERROR(K41*$K$5,0) | V41: =IFERROR(L41*$G$5,0) | W41: =IFERROR(V41*N41,0) | X41: =IFERROR(L41*O41/SUMPRODUCT($L$17:$L$41,$O$17:$O$41)*$I$5,0) | Y41: =IFERROR(X41/W41,0) | Z41: =IFERROR(L41*Q41/SUMPRODUCT($L$17:$L$41,$Q$17:$Q$41)*$J$5,0) | AA41: =IFERROR(M41*$H$5,0) | AB41: =IFERROR(M41*P41/SUMPRODUCT($M$17:$M$41,$P$17:$P$41)*$L$5,0) | AC41: =IFERROR(AB41/AA41,0) | AD41: =IFERROR(M41*R41/SUMPRODUCT($M$17:$M$41,$R$17:$R$41)*$M$5,0) | AE41: =X41*Settings!$B$7+Z41*Settings!$B$8+W41*Settings!$B$9+AB41*Settings!$B$10+AD41*Settings!$B$11+S41*Settings!$B$12+T41*Settings!$B$13+U41*Settings!$B$14
B43: SHARE TOTALS - must equal 100% | E43: each column is a share of this team's season total - it must add to 100% | K43: =SUM(K17:K41) | L43: =SUM(L17:L41) | M43: =SUM(M17:M41) | S43: =SUM(S17:S41) | T43: =SUM(T17:T41) | U43: =SUM(U17:U41) | V43: =SUM(V17:V41) | W43: =SUM(W17:W41) | X43: =SUM(X17:X41) | Y43: =SUM(Y17:Y41) | Z43: =SUM(Z17:Z41) | ... AE43: =SUM(AE17:AE41)
B45: Green = balanced. Red = your shares don't add to 100%; player totals won't match the team totals until they do.

Sheet CHI
A1: CHI - 2026 projections
A3: TEAM TOTALS | C3: blue = edit; everything below divides these up
B4: Games | C4: Plays/G | D4: Plays | E4: Pass Rate | F4: Pass Att | G4: Targets | H4: Rush Att | I4: Pass Yds | J4: Pass TD | K4: Int | L4: Rush Yds | M4: Rush TD
B5: 17 | C5: 63.3 | D5: =C5*B5 | E5: 0.5562 | F5: 556 | G5: =ROUND(F5*Settings!$B$4,0) | H5: 477 | I5: 3787 | J5: 24 | K5: 10 | L5: 2132 | M5: 16
A7: LAST 3 YEARS | B7: Season | C7: Plays | D7: Plays/G | E7: Pass Rate | F7: Pass Att | G7: Rush Att | H7: Pass Yds | I7: Rush Yds | J7: Pass TD | K7: Rush TD | L7: Y/A | M7: Y/C
B8: 2023 | C8: 1097 | D8: 64.5294 | E8: 0.5132 | F8: 513 | G8: 534 | H8: 3421 | I8: 2399 | J8: 19 | K8: 16 | L8: 6.6686 | M8: 4.4925
B9: 2024 | C9: 1065 | D9: 62.6471 | E9: 0.5953 | F9: 566 | G9: 431 | H9: 3552 | I9: 1734 | J9: 20 | K9: 13 | L9: 6.2756 | M9: 4.0232
B10: 2025 | C10: 1103 | D10: 64.8824 | E10: 0.5422 | F10: 574 | G10: 505 | H10: 3991 | I10: 2451 | J10: 28 | K10: 19 | L10: 6.953 | M10: 4.8535
A12: OUT | B12: 29% of targets and 4% of carries left. Share is team-relative - it does NOT follow the player. | H12: DJ Moore (16t/3r -> BUF), Olamide Zaccheaus (12t/1r -> ATL), Durham Smythe (1t/0r -> BAL)
A13: IN | B13: 2 new: Kalif Raymond (WR, from DET - had 5% there), Scotty Miller (WR, from PIT - had 3% there)
A14: STAFF | B14: HC unchanged. OC Press Taylor under Ben Johnson. Continuity maintained; no significant regression expected.
A16: Pos | B16: Player | C16: Dep | D16: Age | E16: Status | F16: 2023 Tgt% | G16: 2024 Tgt% | H16: 2025 Tgt% | I16: 2025 Rush% | J16: Games | K16: Pass % | L16: Tgt % | M16: Rush % | N16: Catch % | O16: Rec Eff x | P16: Rush Eff x | Q16: RZ Tgt x | R16: RZ Rush x | S16: Pass Yds | T16: Pass TD | U16: Int | V16: Targets | W16: Rec | X16: Rec Yds | Y16: Yds/Rec | Z16: Rec TD | AA16: Rush Att | AB16: Rush Yds | AC16: Yds/Car | AD16: Rush TD | AE16: Half PPR
A17: QB | B17: Caleb Williams | C17: 1 | D17: 24 | E17: ACT | H17: 0.0038 | I17: 0.1336 | J17: 17 | K17: 0.97 | L17: 0.0035 | M17: 0.1275 | O17: 1.04 | P17: 1.26 | Q17: 1.38 | R17: 1.23 | S17: =IFERROR(K17*$I$5,0) | T17: =IFERROR(K17*$J$5,0) | U17: =IFERROR(K17*$K$5,0) | V17: =IFERROR(L17*$G$5,0) | W17: =IFERROR(V17*N17,0) | X17: =IFERROR(L17*O17/SUMPRODUCT($L$17:$L$41,$O$17:$O$41)*$I$5,0) | Y17: =IFERROR(X17/W17,0) | Z17: =IFERROR(L17*Q17/SUMPRODUCT($L$17:$L$41,$Q$17:$Q$41)*$J$5,0) | AA17: =IFERROR(M17*$H$5,0) | AB17: =IFERROR(M17*P17/SUMPRODUCT($M$17:$M$41,$P$17:$P$41)*$L$5,0) | AC17: =IFERROR(AB17/AA17,0) | AD17: =IFERROR(M17*R17/SUMPRODUCT($M$17:$M$41,$R$17:$R$41)*$M$5,0) | AE17: =X17*Settings!$B$7+Z17*Settings!$B$8+W17*Settings!$B$9+AB17*Settings!$B$10+AD17*Settings!$B$11+S17*Settings!$B$12+T17*Settings!$B$13+U17*Settings!$B$14
A18: QB | B18: Tyson Bagent | C18: 2 | D18: 26 | E18: ACT | I18: 0.004 | J18: 17 | K18: 0.0255 | L18: 0.0008 | M18: 0.0163 | O18: 1 | P18: 0.97 | Q18: 1 | R18: 1.62 | S18: =IFERROR(K18*$I$5,0) | T18: =IFERROR(K18*$J$5,0) | U18: =IFERROR(K18*$K$5,0) | V18: =IFERROR(L18*$G$5,0) | W18: =IFERROR(V18*N18,0) | X18: =IFERROR(L18*O18/SUMPRODUCT($L$17:$L$41,$O$17:$O$41)*$I$5,0) | Y18: =IFERROR(X18/W18,0) | Z18: =IFERROR(L18*Q18/SUMPRODUCT($L$17:$L$41,$Q$17:$Q$41)*$J$5,0) | AA18: =IFERROR(M18*$H$5,0) | AB18: =IFERROR(M18*P18/SUMPRODUCT($M$17:$M$41,$P$17:$P$41)*$L$5,0) | AC18: =IFERROR(AB18/AA18,0) | AD18: =IFERROR(M18*R18/SUMPRODUCT($M$17:$M$41,$R$17:$R$41)*$M$5,0) | AE18: =X18*Settings!$B$7+Z18*Settings!$B$8+W18*Settings!$B$9+AB18*Settings!$B$10+AD18*Settings!$B$11+S18*Settings!$B$12+T18*Settings!$B$13+U18*Settings!$B$14
A19: QB | B19: Case Keenum | C19: 3 | D19: 38 | E19: ACT | J19: 17 | K19: 0.0045 | L19: 0.0008 | M19: 0.0059 | O19: 1 | P19: 0.92 | Q19: 1 | R19: 1.1 | S19: =IFERROR(K19*$I$5,0) | T19: =IFERROR(K19*$J$5,0) | U19: =IFERROR(K19*$K$5,0) | V19: =IFERROR(L19*$G$5,0) | W19: =IFERROR(V19*N19,0) | X19: =IFERROR(L19*O19/SUMPRODUCT($L$17:$L$41,$O$17:$O$41)*$I$5,0) | Y19: =IFERROR(X19/W19,0) | Z19: =IFERROR(L19*Q19/SUMPRODUCT($L$17:$L$41,$Q$17:$Q$41)*$J$5,0) | AA19: =IFERROR(M19*$H$5,0) | AB19: =IFERROR(M19*P19/SUMPRODUCT($M$17:$M$41,$P$17:$P$41)*$L$5,0) | AC19: =IFERROR(AB19/AA19,0) | AD19: =IFERROR(M19*R19/SUMPRODUCT($M$17:$M$41,$R$17:$R$41)*$M$5,0) | AE19: =X19*Settings!$B$7+Z19*Settings!$B$8+W19*Settings!$B$9+AB19*Settings!$B$10+AD19*Settings!$B$11+S19*Settings!$B$12+T19*Settings!$B$13+U19*Settings!$B$14
A20: QB | B20: Other QBs | S20: =IFERROR(K20*$I$5,0) | T20: =IFERROR(K20*$J$5,0) | U20: =IFERROR(K20*$K$5,0) | V20: =IFERROR(L20*$G$5,0) | W20: =IFERROR(V20*N20,0) | X20: =IFERROR(L20*O20/SUMPRODUCT($L$17:$L$41,$O$17:$O$41)*$I$5,0) | Y20: =IFERROR(X20/W20,0) | Z20: =IFERROR(L20*Q20/SUMPRODUCT($L$17:$L$41,$Q$17:$Q$41)*$J$5,0) | AA20: =IFERROR(M20*$H$5,0) | AB20: =IFERROR(M20*P20/SUMPRODUCT($M$17:$M$41,$P$17:$P$41)*$L$5,0) | AC20: =IFERROR(AB20/AA20,0) | AD20: =IFERROR(M20*R20/SUMPRODUCT($M$17:$M$41,$R$17:$R$41)*$M$5,0) | AE20: =X20*Settings!$B$7+Z20*Settings!$B$8+W20*Settings!$B$9+AB20*Settings!$B$10+AD20*Settings!$B$11+S20*Settings!$B$12+T20*Settings!$B$13+U20*Settings!$B$14
A21: RB | B21: D'Andre Swift | C21: 1 | D21: 27 | E21: ACT | F21: 0.0933 | G21: 0.0987 | H21: 0.0902 | I21: 0.4514 | J21: 17 | L21: 0.0975 | M21: 0.4326 | N21: 0.7566 | O21: 0.9 | P21: 0.97 | Q21: 0.88 | R21: 0.91 | S21: =IFERROR(K21*$I$5,0) | T21: =IFERROR(K21*$J$5,0) | U21: =IFERROR(K21*$K$5,0) | V21: =IFERROR(L21*$G$5,0) | W21: =IFERROR(V21*N21,0) | X21: =IFERROR(L21*O21/SUMPRODUCT($L$17:$L$41,$O$17:$O$41)*$I$5,0) | Y21: =IFERROR(X21/W21,0) | Z21: =IFERROR(L21*Q21/SUMPRODUCT($L$17:$L$41,$Q$17:$Q$41)*$J$5,0) | AA21: =IFERROR(M21*$H$5,0) | AB21: =IFERROR(M21*P21/SUMPRODUCT($M$17:$M$41,$P$17:$P$41)*$L$5,0) | AC21: =IFERROR(AB21/AA21,0) | AD21: =IFERROR(M21*R21/SUMPRODUCT($M$17:$M$41,$R$17:$R$41)*$M$5,0) | AE21: =X21*Settings!$B$7+Z21*Settings!$B$8+W21*Settings!$B$9+AB21*Settings!$B$10+AD21*Settings!$B$11+S21*Settings!$B$12+T21*Settings!$B$13+U21*Settings!$B$14
A22: RB | B22: Kyle Monangai | C22: 2 | D22: 24 | E22: ACT | H22: 0.0564 | I22: 0.3421 | J22: 17 | L22: 0.0555 | M22: 0.2606 | N22: 0.6 | O22: 0.84 | P22: 0.94 | Q22: 0.96 | R22: 1.14 | S22: =IFERROR(K22*$I$5,0) | T22: =IFERROR(K22*$J$5,0) | U22: =IFERROR(K22*$K$5,0) | V22: =IFERROR(L22*$G$5,0) | W22: =IFERROR(V22*N22,0) | X22: =IFERROR(L22*O22/SUMPRODUCT($L$17:$L$41,$O$17:$O$41)*$I$5,0) | Y22: =IFERROR(X22/W22,0) | Z22: =IFERROR(L22*Q22/SUMPRODUCT($L$17:$L$41,$Q$17:$Q$41)*$J$5,0) | AA22: =IFERROR(M22*$H$5,0) | AB22: =IFERROR(M22*P22/SUMPRODUCT($M$17:$M$41,$P$17:$P$41)*$L$5,0) | AC22: =IFERROR(AB22/AA22,0) | AD22: =IFERROR(M22*R22/SUMPRODUCT($M$17:$M$41,$R$17:$R$41)*$M$5,0) | AE22: =X22*Settings!$B$7+Z22*Settings!$B$8+W22*Settings!$B$9+AB22*Settings!$B$10+AD22*Settings!$B$11+S22*Settings!$B$12+T22*Settings!$B$13+U22*Settings!$B$14
A23: RB | B23: Roschon Johnson | C23: 3 | D23: 25 | E23: ACT | F23: 0.0839 | G23: 0.038 | I23: 0.004 | J23: 17 | L23: 0.0422 | M23: 0.0684 | N23: 0.8208 | O23: 0.86 | P23: 1.06 | Q23: 1.04 | R23: 1.97 | S23: =IFERROR(K23*$I$5,0) | T23: =IFERROR(K23*$J$5,0) | U23: =IFERROR(K23*$K$5,0) | V23: =IFERROR(L23*$G$5,0) | W23: =IFERROR(V23*N23,0) | X23: =IFERROR(L23*O23/SUMPRODUCT($L$17:$L$41,$O$17:$O$41)*$I$5,0) | Y23: =IFERROR(X23/W23,0) | Z23: =IFERROR(L23*Q23/SUMPRODUCT($L$17:$L$41,$Q$17:$Q$41)*$J$5,0) | AA23: =IFERROR(M23*$H$5,0) | AB23: =IFERROR(M23*P23/SUMPRODUCT($M$17:$M$41,$P$17:$P$41)*$L$5,0) | AC23: =IFERROR(AB23/AA23,0) | AD23: =IFERROR(M23*R23/SUMPRODUCT($M$17:$M$41,$R$17:$R$41)*$M$5,0) | AE23: =X23*Settings!$B$7+Z23*Settings!$B$8+W23*Settings!$B$9+AB23*Settings!$B$10+AD23*Settings!$B$11+S23*Settings!$B$12+T23*Settings!$B$13+U23*Settings!$B$14
A24: RB | B24: Brittain Brown | C24: 4 | D24: 28 | E24: ACT | H24: 0.0019 | I24: 0.0101 | J24: 17 | L24: 0.0054 | M24: 0.012 | O24: 1 | P24: 1.1 | Q24: 1 | R24: 1 | S24: =IFERROR(K24*$I$5,0) | T24: =IFERROR(K24*$J$5,0) | U24: =IFERROR(K24*$K$5,0) | V24: =IFERROR(L24*$G$5,0) | W24: =IFERROR(V24*N24,0) | X24: =IFERROR(L24*O24/SUMPRODUCT($L$17:$L$41,$O$17:$O$41)*$I$5,0) | Y24: =IFERROR(X24/W24,0) | Z24: =IFERROR(L24*Q24/SUMPRODUCT($L$17:$L$41,$Q$17:$Q$41)*$J$5,0) | AA24: =IFERROR(M24*$H$5,0) | AB24: =IFERROR(M24*P24/SUMPRODUCT($M$17:$M$41,$P$17:$P$41)*$L$5,0) | AC24: =IFERROR(AB24/AA24,0) | AD24: =IFERROR(M24*R24/SUMPRODUCT($M$17:$M$41,$R$17:$R$41)*$M$5,0) | AE24: =X24*Settings!$B$7+Z24*Settings!$B$8+W24*Settings!$B$9+AB24*Settings!$B$10+AD24*Settings!$B$11+S24*Settings!$B$12+T24*Settings!$B$13+U24*Settings!$B$14
A25: RB | B25: Salvon Ahmed | C25: 5 | D25: 27 | E25: ACT | F25: 0.0419 | J25: 17 | L25: 0.0276 | M25: 0.0291 | N25: 0.6957 | O25: 0.7 | P25: 0.75 | Q25: 1.7 | R25: 1.26 | S25: =IFERROR(K25*$I$5,0) | T25: =IFERROR(K25*$J$5,0) | U25: =IFERROR(K25*$K$5,0) | V25: =IFERROR(L25*$G$5,0) | W25: =IFERROR(V25*N25,0) | X25: =IFERROR(L25*O25/SUMPRODUCT($L$17:$L$41,$O$17:$O$41)*$I$5,0) | Y25: =IFERROR(X25/W25,0) | Z25: =IFERROR(L25*Q25/SUMPRODUCT($L$17:$L$41,$Q$17:$Q$41)*$J$5,0) | AA25: =IFERROR(M25*$H$5,0) | AB25: =IFERROR(M25*P25/SUMPRODUCT($M$17:$M$41,$P$17:$P$41)*$L$5,0) | AC25: =IFERROR(AB25/AA25,0) | AD25: =IFERROR(M25*R25/SUMPRODUCT($M$17:$M$41,$R$17:$R$41)*$M$5,0) | AE25: =X25*Settings!$B$7+Z25*Settings!$B$8+W25*Settings!$B$9+AB25*Settings!$B$10+AD25*Settings!$B$11+S25*Settings!$B$12+T25*Settings!$B$13+U25*Settings!$B$14
A26: RB | B26: Coleman Bennett | C26: 6 | E26: role avg (rookie) | J26: 17 | L26: 0.0036 | M26: 0.004 | N26: 0.75 | O26: 1 | P26: 1 | Q26: 1 | R26: 1 | S26: =IFERROR(K26*$I$5,0) | T26: =IFERROR(K26*$J$5,0) | U26: =IFERROR(K26*$K$5,0) | V26: =IFERROR(L26*$G$5,0) | W26: =IFERROR(V26*N26,0) | X26: =IFERROR(L26*O26/SUMPRODUCT($L$17:$L$41,$O$17:$O$41)*$I$5,0) | Y26: =IFERROR(X26/W26,0) | Z26: =IFERROR(L26*Q26/SUMPRODUCT($L$17:$L$41,$Q$17:$Q$41)*$J$5,0) | AA26: =IFERROR(M26*$H$5,0) | AB26: =IFERROR(M26*P26/SUMPRODUCT($M$17:$M$41,$P$17:$P$41)*$L$5,0) | AC26: =IFERROR(AB26/AA26,0) | AD26: =IFERROR(M26*R26/SUMPRODUCT($M$17:$M$41,$R$17:$R$41)*$M$5,0) | AE26: =X26*Settings!$B$7+Z26*Settings!$B$8+W26*Settings!$B$9+AB26*Settings!$B$10+AD26*Settings!$B$11+S26*Settings!$B$12+T26*Settings!$B$13+U26*Settings!$B$14
A27: RB | B27: Other RBs | S27: =IFERROR(K27*$I$5,0) | T27: =IFERROR(K27*$J$5,0) | U27: =IFERROR(K27*$K$5,0) | V27: =IFERROR(L27*$G$5,0) | W27: =IFERROR(V27*N27,0) | X27: =IFERROR(L27*O27/SUMPRODUCT($L$17:$L$41,$O$17:$O$41)*$I$5,0) | Y27: =IFERROR(X27/W27,0) | Z27: =IFERROR(L27*Q27/SUMPRODUCT($L$17:$L$41,$Q$17:$Q$41)*$J$5,0) | AA27: =IFERROR(M27*$H$5,0) | AB27: =IFERROR(M27*P27/SUMPRODUCT($M$17:$M$41,$P$17:$P$41)*$L$5,0) | AC27: =IFERROR(AB27/AA27,0) | AD27: =IFERROR(M27*R27/SUMPRODUCT($M$17:$M$41,$R$17:$R$41)*$M$5,0) | AE27: =X27*Settings!$B$7+Z27*Settings!$B$8+W27*Settings!$B$9+AB27*Settings!$B$10+AD27*Settings!$B$11+S27*Settings!$B$12+T27*Settings!$B$13+U27*Settings!$B$14
A28: WR | B28: Rome Odunze | C28: 1 | D28: 24 | E28: ACT | G28: 0.1917 | H28: 0.1692 | J28: 17 | L28: 0.2088 | M28: 0.0116 | N28: 0.5099 | O28: 1.02 | P28: 1.03 | Q28: 1.03 | R28: 1 | S28: =IFERROR(K28*$I$5,0) | T28: =IFERROR(K28*$J$5,0) | U28: =IFERROR(K28*$K$5,0) | V28: =IFERROR(L28*$G$5,0) | W28: =IFERROR(V28*N28,0) | X28: =IFERROR(L28*O28/SUMPRODUCT($L$17:$L$41,$O$17:$O$41)*$I$5,0) | Y28: =IFERROR(X28/W28,0) | Z28: =IFERROR(L28*Q28/SUMPRODUCT($L$17:$L$41,$Q$17:$Q$41)*$J$5,0) | AA28: =IFERROR(M28*$H$5,0) | AB28: =IFERROR(M28*P28/SUMPRODUCT($M$17:$M$41,$P$17:$P$41)*$L$5,0) | AC28: =IFERROR(AB28/AA28,0) | AD28: =IFERROR(M28*R28/SUMPRODUCT($M$17:$M$41,$R$17:$R$41)*$M$5,0) | AE28: =X28*Settings!$B$7+Z28*Settings!$B$8+W28*Settings!$B$9+AB28*Settings!$B$10+AD28*Settings!$B$11+S28*Settings!$B$12+T28*Settings!$B$13+U28*Settings!$B$14
A29: WR | B29: Luther Burden | C29: 2 | D29: 22 | E29: ACT | H29: 0.1128 | I29: 0.0121 | J29: 17 | L29: 0.1361 | M29: 0.0096 | N29: 0.7833 | O29: 1.34 | P29: 1.05 | Q29: 0.82 | R29: 1 | S29: =IFERROR(K29*$I$5,0) | T29: =IFERROR(K29*$J$5,0) | U29: =IFERROR(K29*$K$5,0) | V29: =IFERROR(L29*$G$5,0) | W29: =IFERROR(V29*N29,0) | X29: =IFERROR(L29*O29/SUMPRODUCT($L$17:$L$41,$O$17:$O$41)*$I$5,0) | Y29: =IFERROR(X29/W29,0) | Z29: =IFERROR(L29*Q29/SUMPRODUCT($L$17:$L$41,$Q$17:$Q$41)*$J$5,0) | AA29: =IFERROR(M29*$H$5,0) | AB29: =IFERROR(M29*P29/SUMPRODUCT($M$17:$M$41,$P$17:$P$41)*$L$5,0) | AC29: =IFERROR(AB29/AA29,0) | AD29: =IFERROR(M29*R29/SUMPRODUCT($M$17:$M$41,$R$17:$R$41)*$M$5,0) | AE29: =X29*Settings!$B$7+Z29*Settings!$B$8+W29*Settings!$B$9+AB29*Settings!$B$10+AD29*Settings!$B$11+S29*Settings!$B$12+T29*Settings!$B$13+U29*Settings!$B$14
A30: WR | B30: Jahdae Walker | C30: 3 | D30: 24 | E30: ACT | H30: 0.0188 | J30: 17 | L30: 0.0576 | M30: 0.0019 | N30: 0.6 | O30: 1.05 | P30: 1 | Q30: 0.91 | R30: 1 | S30: =IFERROR(K30*$I$5,0) | T30: =IFERROR(K30*$J$5,0) | U30: =IFERROR(K30*$K$5,0) | V30: =IFERROR(L30*$G$5,0) | W30: =IFERROR(V30*N30,0) | X30: =IFERROR(L30*O30/SUMPRODUCT($L$17:$L$41,$O$17:$O$41)*$I$5,0) | Y30: =IFERROR(X30/W30,0) | Z30: =IFERROR(L30*Q30/SUMPRODUCT($L$17:$L$41,$Q$17:$Q$41)*$J$5,0) | AA30: =IFERROR(M30*$H$5,0) | AB30: =IFERROR(M30*P30/SUMPRODUCT($M$17:$M$41,$P$17:$P$41)*$L$5,0) | AC30: =IFERROR(AB30/AA30,0) | AD30: =IFERROR(M30*R30/SUMPRODUCT($M$17:$M$41,$R$17:$R$41)*$M$5,0) | AE30: =X30*Settings!$B$7+Z30*Settings!$B$8+W30*Settings!$B$9+AB30*Settings!$B$10+AD30*Settings!$B$11+S30*Settings!$B$12+T30*Settings!$B$13+U30*Settings!$B$14
A31: WR | B31: Kalif Raymond | C31: 4 | D31: 31 | E31: role avg (from DET) | F31: 0.0767 | G31: 0.0421 | H31: 0.0545 | I31: 0.0046 | J31: 17 | L31: 0.052 | M31: 0.0027 | N31: 0.7922 | O31: 1.12 | P31: 1.15 | Q31: 0.91 | R31: 1.23 | S31: =IFERROR(K31*$I$5,0) | T31: =IFERROR(K31*$J$5,0) | U31: =IFERROR(K31*$K$5,0) | V31: =IFERROR(L31*$G$5,0) | W31: =IFERROR(V31*N31,0) | X31: =IFERROR(L31*O31/SUMPRODUCT($L$17:$L$41,$O$17:$O$41)*$I$5,0) | Y31: =IFERROR(X31/W31,0) | Z31: =IFERROR(L31*Q31/SUMPRODUCT($L$17:$L$41,$Q$17:$Q$41)*$J$5,0) | AA31: =IFERROR(M31*$H$5,0) | AB31: =IFERROR(M31*P31/SUMPRODUCT($M$17:$M$41,$P$17:$P$41)*$L$5,0) | AC31: =IFERROR(AB31/AA31,0) | AD31: =IFERROR(M31*R31/SUMPRODUCT($M$17:$M$41,$R$17:$R$41)*$M$5,0) | AE31: =X31*Settings!$B$7+Z31*Settings!$B$8+W31*Settings!$B$9+AB31*Settings!$B$10+AD31*Settings!$B$11+S31*Settings!$B$12+T31*Settings!$B$13+U31*Settings!$B$14
A32: WR | B32: Maurice Alexander | C32: 5 | D32: 29 | E32: role avg (rookie) | J32: 17 | L32: 0.0183 | M32: 0.0019 | N32: 0.65 | O32: 1 | P32: 1 | Q32: 1 | R32: 1 | S32: =IFERROR(K32*$I$5,0) | T32: =IFERROR(K32*$J$5,0) | U32: =IFERROR(K32*$K$5,0) | V32: =IFERROR(L32*$G$5,0) | W32: =IFERROR(V32*N32,0) | X32: =IFERROR(L32*O32/SUMPRODUCT($L$17:$L$41,$O$17:$O$41)*$I$5,0) | Y32: =IFERROR(X32/W32,0) | Z32: =IFERROR(L32*Q32/SUMPRODUCT($L$17:$L$41,$Q$17:$Q$41)*$J$5,0) | AA32: =IFERROR(M32*$H$5,0) | AB32: =IFERROR(M32*P32/SUMPRODUCT($M$17:$M$41,$P$17:$P$41)*$L$5,0) | AC32: =IFERROR(AB32/AA32,0) | AD32: =IFERROR(M32*R32/SUMPRODUCT($M$17:$M$41,$R$17:$R$41)*$M$5,0) | AE32: =X32*Settings!$B$7+Z32*Settings!$B$8+W32*Settings!$B$9+AB32*Settings!$B$10+AD32*Settings!$B$11+S32*Settings!$B$12+T32*Settings!$B$13+U32*Settings!$B$14
A33: WR | B33: Zavion Thomas | C33: 6 | D33: 22 | E33: role avg (rookie) | J33: 17 | L33: 0.0092 | M33: 0.0019 | N33: 0.65 | O33: 1 | P33: 1 | Q33: 1 | R33: 1 | S33: =IFERROR(K33*$I$5,0) | T33: =IFERROR(K33*$J$5,0) | U33: =IFERROR(K33*$K$5,0) | V33: =IFERROR(L33*$G$5,0) | W33: =IFERROR(V33*N33,0) | X33: =IFERROR(L33*O33/SUMPRODUCT($L$17:$L$41,$O$17:$O$41)*$I$5,0) | Y33: =IFERROR(X33/W33,0) | Z33: =IFERROR(L33*Q33/SUMPRODUCT($L$17:$L$41,$Q$17:$Q$41)*$J$5,0) | AA33: =IFERROR(M33*$H$5,0) | AB33: =IFERROR(M33*P33/SUMPRODUCT($M$17:$M$41,$P$17:$P$41)*$L$5,0) | AC33: =IFERROR(AB33/AA33,0) | AD33: =IFERROR(M33*R33/SUMPRODUCT($M$17:$M$41,$R$17:$R$41)*$M$5,0) | AE33: =X33*Settings!$B$7+Z33*Settings!$B$8+W33*Settings!$B$9+AB33*Settings!$B$10+AD33*Settings!$B$11+S33*Settings!$B$12+T33*Settings!$B$13+U33*Settings!$B$14
A34: WR | B34: JP Richardson | C34: 7 | D34: 24 | E34: role avg (rookie) | J34: 17 | L34: 0.0045 | M34: 0.002 | N34: 0.65 | O34: 1 | P34: 1 | Q34: 1 | R34: 1 | S34: =IFERROR(K34*$I$5,0) | T34: =IFERROR(K34*$J$5,0) | U34: =IFERROR(K34*$K$5,0) | V34: =IFERROR(L34*$G$5,0) | W34: =IFERROR(V34*N34,0) | X34: =IFERROR(L34*O34/SUMPRODUCT($L$17:$L$41,$O$17:$O$41)*$I$5,0) | Y34: =IFERROR(X34/W34,0) | Z34: =IFERROR(L34*Q34/SUMPRODUCT($L$17:$L$41,$Q$17:$Q$41)*$J$5,0) | AA34: =IFERROR(M34*$H$5,0) | AB34: =IFERROR(M34*P34/SUMPRODUCT($M$17:$M$41,$P$17:$P$41)*$L$5,0) | AC34: =IFERROR(AB34/AA34,0) | AD34: =IFERROR(M34*R34/SUMPRODUCT($M$17:$M$41,$R$17:$R$41)*$M$5,0) | AE34: =X34*Settings!$B$7+Z34*Settings!$B$8+W34*Settings!$B$9+AB34*Settings!$B$10+AD34*Settings!$B$11+S34*Settings!$B$12+T34*Settings!$B$13+U34*Settings!$B$14
A35: WR | B35: Qadir Ismail | C35: 8 | D35: 26 | E35: role avg (rookie) | J35: 17 | L35: 0.0052 | M35: 0.0019 | N35: 0.65 | O35: 1 | P35: 1 | Q35: 1 | R35: 1 | S35: =IFERROR(K35*$I$5,0) | T35: =IFERROR(K35*$J$5,0) | U35: =IFERROR(K35*$K$5,0) | V35: =IFERROR(L35*$G$5,0) | W35: =IFERROR(V35*N35,0) | X35: =IFERROR(L35*O35/SUMPRODUCT($L$17:$L$41,$O$17:$O$41)*$I$5,0) | Y35: =IFERROR(X35/W35,0) | Z35: =IFERROR(L35*Q35/SUMPRODUCT($L$17:$L$41,$Q$17:$Q$41)*$J$5,0) | AA35: =IFERROR(M35*$H$5,0) | AB35: =IFERROR(M35*P35/SUMPRODUCT($M$17:$M$41,$P$17:$P$41)*$L$5,0) | AC35: =IFERROR(AB35/AA35,0) | AD35: =IFERROR(M35*R35/SUMPRODUCT($M$17:$M$41,$R$17:$R$41)*$M$5,0) | AE35: =X35*Settings!$B$7+Z35*Settings!$B$8+W35*Settings!$B$9+AB35*Settings!$B$10+AD35*Settings!$B$11+S35*Settings!$B$12+T35*Settings!$B$13+U35*Settings!$B$14
A36: WR | B36: Other WRs | S36: =IFERROR(K36*$I$5,0) | T36: =IFERROR(K36*$J$5,0) | U36: =IFERROR(K36*$K$5,0) | V36: =IFERROR(L36*$G$5,0) | W36: =IFERROR(V36*N36,0) | X36: =IFERROR(L36*O36/SUMPRODUCT($L$17:$L$41,$O$17:$O$41)*$I$5,0) | Y36: =IFERROR(X36/W36,0) | Z36: =IFERROR(L36*Q36/SUMPRODUCT($L$17:$L$41,$Q$17:$Q$41)*$J$5,0) | AA36: =IFERROR(M36*$H$5,0) | AB36: =IFERROR(M36*P36/SUMPRODUCT($M$17:$M$41,$P$17:$P$41)*$L$5,0) | AC36: =IFERROR(AB36/AA36,0) | AD36: =IFERROR(M36*R36/SUMPRODUCT($M$17:$M$41,$R$17:$R$41)*$M$5,0) | AE36: =X36*Settings!$B$7+Z36*Settings!$B$8+W36*Settings!$B$9+AB36*Settings!$B$10+AD36*Settings!$B$11+S36*Settings!$B$12+T36*Settings!$B$13+U36*Settings!$B$14
A37: TE | B37: Colston Loveland | C37: 1 | D37: 22 | E37: ACT | H37: 0.1541 | I37: 0.002 | J37: 17 | L37: 0.158 | M37: 0.0022 | N37: 0.7073 | O37: 1.13 | P37: 1 | Q37: 1.24 | R37: 1.35 | S37: =IFERROR(K37*$I$5,0) | T37: =IFERROR(K37*$J$5,0) | U37: =IFERROR(K37*$K$5,0) | V37: =IFERROR(L37*$G$5,0) | W37: =IFERROR(V37*N37,0) | X37: =IFERROR(L37*O37/SUMPRODUCT($L$17:$L$41,$O$17:$O$41)*$I$5,0) | Y37: =IFERROR(X37/W37,0) | Z37: =IFERROR(L37*Q37/SUMPRODUCT($L$17:$L$41,$Q$17:$Q$41)*$J$5,0) | AA37: =IFERROR(M37*$H$5,0) | AB37: =IFERROR(M37*P37/SUMPRODUCT($M$17:$M$41,$P$17:$P$41)*$L$5,0) | AC37: =IFERROR(AB37/AA37,0) | AD37: =IFERROR(M37*R37/SUMPRODUCT($M$17:$M$41,$R$17:$R$41)*$M$5,0) | AE37: =X37*Settings!$B$7+Z37*Settings!$B$8+W37*Settings!$B$9+AB37*Settings!$B$10+AD37*Settings!$B$11+S37*Settings!$B$12+T37*Settings!$B$13+U37*Settings!$B$14
A38: TE | B38: Cole Kmet | C38: 2 | D38: 27 | E38: ACT | F38: 0.1887 | G38: 0.1044 | H38: 0.0902 | J38: 17 | L38: 0.0921 | M38: 0.0039 | N38: 0.7343 | O38: 1.07 | P38: 0.89 | Q38: 1.27 | R38: 1.22 | S38: =IFERROR(K38*$I$5,0) | T38: =IFERROR(K38*$J$5,0) | U38: =IFERROR(K38*$K$5,0) | V38: =IFERROR(L38*$G$5,0) | W38: =IFERROR(V38*N38,0) | X38: =IFERROR(L38*O38/SUMPRODUCT($L$17:$L$41,$O$17:$O$41)*$I$5,0) | Y38: =IFERROR(X38/W38,0) | Z38: =IFERROR(L38*Q38/SUMPRODUCT($L$17:$L$41,$Q$17:$Q$41)*$J$5,0) | AA38: =IFERROR(M38*$H$5,0) | AB38: =IFERROR(M38*P38/SUMPRODUCT($M$17:$M$41,$P$17:$P$41)*$L$5,0) | AC38: =IFERROR(AB38/AA38,0) | AD38: =IFERROR(M38*R38/SUMPRODUCT($M$17:$M$41,$R$17:$R$41)*$M$5,0) | AE38: =X38*Settings!$B$7+Z38*Settings!$B$8+W38*Settings!$B$9+AB38*Settings!$B$10+AD38*Settings!$B$11+S38*Settings!$B$12+T38*Settings!$B$13+U38*Settings!$B$14
A39: TE | B39: Stephen Carlson | C39: 3 | D39: 29 | E39: role avg (rookie) | J39: 17 | L39: 0.014 | M39: 0.002 | N39: 0.65 | O39: 1 | P39: 1 | Q39: 1 | R39: 1 | S39: =IFERROR(K39*$I$5,0) | T39: =IFERROR(K39*$J$5,0) | U39: =IFERROR(K39*$K$5,0) | V39: =IFERROR(L39*$G$5,0) | W39: =IFERROR(V39*N39,0) | X39: =IFERROR(L39*O39/SUMPRODUCT($L$17:$L$41,$O$17:$O$41)*$I$5,0) | Y39: =IFERROR(X39/W39,0) | Z39: =IFERROR(L39*Q39/SUMPRODUCT($L$17:$L$41,$Q$17:$Q$41)*$J$5,0) | AA39: =IFERROR(M39*$H$5,0) | AB39: =IFERROR(M39*P39/SUMPRODUCT($M$17:$M$41,$P$17:$P$41)*$L$5,0) | AC39: =IFERROR(AB39/AA39,0) | AD39: =IFERROR(M39*R39/SUMPRODUCT($M$17:$M$41,$R$17:$R$41)*$M$5,0) | AE39: =X39*Settings!$B$7+Z39*Settings!$B$8+W39*Settings!$B$9+AB39*Settings!$B$10+AD39*Settings!$B$11+S39*Settings!$B$12+T39*Settings!$B$13+U39*Settings!$B$14
A40: TE | B40: Sam Roush | C40: 4 | D40: 22 | E40: role avg (rookie) | J40: 17 | L40: 0.0072 | M40: 0.002 | N40: 0.65 | O40: 1 | P40: 1 | Q40: 1 | R40: 1 | S40: =IFERROR(K40*$I$5,0) | T40: =IFERROR(K40*$J$5,0) | U40: =IFERROR(K40*$K$5,0) | V40: =IFERROR(L40*$G$5,0) | W40: =IFERROR(V40*N40,0) | X40: =IFERROR(L40*O40/SUMPRODUCT($L$17:$L$41,$O$17:$O$41)*$I$5,0) | Y40: =IFERROR(X40/W40,0) | Z40: =IFERROR(L40*Q40/SUMPRODUCT($L$17:$L$41,$Q$17:$Q$41)*$J$5,0) | AA40: =IFERROR(M40*$H$5,0) | AB40: =IFERROR(M40*P40/SUMPRODUCT($M$17:$M$41,$P$17:$P$41)*$L$5,0) | AC40: =IFERROR(AB40/AA40,0) | AD40: =IFERROR(M40*R40/SUMPRODUCT($M$17:$M$41,$R$17:$R$41)*$M$5,0) | AE40: =X40*Settings!$B$7+Z40*Settings!$B$8+W40*Settings!$B$9+AB40*Settings!$B$10+AD40*Settings!$B$11+S40*Settings!$B$12+T40*Settings!$B$13+U40*Settings!$B$14
A41: TE | B41: Other TEs | S41: =IFERROR(K41*$I$5,0) | T41: =IFERROR(K41*$J$5,0) | U41: =IFERROR(K41*$K$5,0) | V41: =IFERROR(L41*$G$5,0) | W41: =IFERROR(V41*N41,0) | X41: =IFERROR(L41*O41/SUMPRODUCT($L$17:$L$41,$O$17:$O$41)*$I$5,0) | Y41: =IFERROR(X41/W41,0) | Z41: =IFERROR(L41*Q41/SUMPRODUCT($L$17:$L$41,$Q$17:$Q$41)*$J$5,0) | AA41: =IFERROR(M41*$H$5,0) | AB41: =IFERROR(M41*P41/SUMPRODUCT($M$17:$M$41,$P$17:$P$41)*$L$5,0) | AC41: =IFERROR(AB41/AA41,0) | AD41: =IFERROR(M41*R41/SUMPRODUCT($M$17:$M$41,$R$17:$R$41)*$M$5,0) | AE41: =X41*Settings!$B$7+Z41*Settings!$B$8+W41*Settings!$B$9+AB41*Settings!$B$10+AD41*Settings!$B$11+S41*Settings!$B$12+T41*Settings!$B$13+U41*Settings!$B$14
B43: SHARE TOTALS - must equal 100% | E43: each column is a share of this team's season total - it must add to 100% | K43: =SUM(K17:K41) | L43: =SUM(L17:L41) | M43: =SUM(M17:M41) | S43: =SUM(S17:S41) | T43: =SUM(T17:T41) | U43: =SUM(U17:U41) | V43: =SUM(V17:V41) | W43: =SUM(W17:W41) | X43: =SUM(X17:X41) | Y43: =SUM(Y17:Y41) | Z43: =SUM(Z17:Z41) | ... AE43: =SUM(AE17:AE41)
B45: Green = balanced. Red = your shares don't add to 100%; player totals won't match the team totals until they do.

Sheet CIN
A1: CIN - 2026 projections
A3: TEAM TOTALS | C3: blue = edit; everything below divides these up
B4: Games | C4: Plays/G | D4: Plays | E4: Pass Rate | F4: Pass Att | G4: Targets | H4: Rush Att | I4: Pass Yds | J4: Pass TD | K4: Int | L4: Rush Yds | M4: Rush TD
B5: 17 | C5: 62.3 | D5: =C5*B5 | E5: 0.6189 | F5: 613 | G5: =ROUND(F5*Settings!$B$4,0) | H5: 403 | I5: 4287 | J5: 33 | K5: 14 | L5: 1691 | M5: 13
A7: LAST 3 YEARS | B7: Season | C7: Plays | D7: Plays/G | E7: Pass Rate | F7: Pass Att | G7: Rush Att | H7: Pass Yds | I7: Rush Yds | J7: Pass TD | K7: Rush TD | L7: Y/A | M7: Y/C
B8: 2023 | C8: 1048 | D8: 61.6471 | E8: 0.6345 | F8: 615 | G8: 383 | H8: 4257 | I8: 1527 | J8: 27 | K8: 12 | L8: 6.922 | M8: 3.9869
B9: 2024 | C9: 1080 | D9: 63.5294 | E9: 0.6481 | F9: 652 | G9: 380 | H9: 4918 | I9: 1574 | J9: 43 | K9: 11 | L9: 7.5429 | M9: 4.1421
B10: 2025 | C10: 1057 | D10: 62.1765 | E10: 0.6395 | F10: 640 | G10: 381 | H10: 4244 | I10: 1591 | J10: 36 | K10: 11 | L10: 6.6312 | M10: 4.1759
A12: OUT | B12: 7% of targets and 2% of carries left. Share is team-relative - it does NOT follow the player. | H12: Noah Fant (7t/0r -> NO), Jake Browning (0t/2r -> TB)
A13: IN | B13: 2 new: Josh Johnson (QB, from WAS), Joe Flacco (QB, from CLE)
A14: STAFF | B14: no coaching change recorded - add one in manual/coaching_changes.csv
A16: Pos | B16: Player | C16: Dep | D16: Age | E16: Status | F16: 2023 Tgt% | G16: 2024 Tgt% | H16: 2025 Tgt% | I16: 2025 Rush% | J16: Games | K16: Pass % | L16: Tgt % | M16: Rush % | N16: Catch % | O16: Rec Eff x | P16: Rush Eff x | Q16: RZ Tgt x | R16: RZ Rush x | S16: Pass Yds | T16: Pass TD | U16: Int | V16: Targets | W16: Rec | X16: Rec Yds | Y16: Yds/Rec | Z16: Rec TD | AA16: Rush Att | AB16: Rush Yds | AC16: Yds/Car | AD16: Rush TD | AE16: Half PPR
A17: QB | B17: Joe Burrow | C17: 1 | D17: 29 | E17: ACT | I17: 0.035 | J17: 17 | K17: 0.92 | L17: 0.0007 | M17: 0.0696 | O17: 1 | P17: 1.08 | Q17: 1 | R17: 0.95 | S17: =IFERROR(K17*$I$5,0) | T17: =IFERROR(K17*$J$5,0) | U17: =IFERROR(K17*$K$5,0) | V17: =IFERROR(L17*$G$5,0) | W17: =IFERROR(V17*N17,0) | X17: =IFERROR(L17*O17/SUMPRODUCT($L$17:$L$41,$O$17:$O$41)*$I$5,0) | Y17: =IFERROR(X17/W17,0) | Z17: =IFERROR(L17*Q17/SUMPRODUCT($L$17:$L$41,$Q$17:$Q$41)*$J$5,0) | AA17: =IFERROR(M17*$H$5,0) | AB17: =IFERROR(M17*P17/SUMPRODUCT($M$17:$M$41,$P$17:$P$41)*$L$5,0) | AC17: =IFERROR(AB17/AA17,0) | AD17: =IFERROR(M17*R17/SUMPRODUCT($M$17:$M$41,$R$17:$R$41)*$M$5,0) | AE17: =X17*Settings!$B$7+Z17*Settings!$B$8+W17*Settings!$B$9+AB17*Settings!$B$10+AD17*Settings!$B$11+S17*Settings!$B$12+T17*Settings!$B$13+U17*Settings!$B$14
A18: QB | B18: Joe Flacco | C18: 2 | D18: 41 | E18: role avg (from CLE) | I18: 0.012 | J18: 17 | K18: 0.068 | L18: 0.0019 | M18: 0.0284 | O18: 1 | P18: 0.93 | Q18: 1 | R18: 1.05 | S18: =IFERROR(K18*$I$5,0) | T18: =IFERROR(K18*$J$5,0) | U18: =IFERROR(K18*$K$5,0) | V18: =IFERROR(L18*$G$5,0) | W18: =IFERROR(V18*N18,0) | X18: =IFERROR(L18*O18/SUMPRODUCT($L$17:$L$41,$O$17:$O$41)*$I$5,0) | Y18: =IFERROR(X18/W18,0) | Z18: =IFERROR(L18*Q18/SUMPRODUCT($L$17:$L$41,$Q$17:$Q$41)*$J$5,0) | AA18: =IFERROR(M18*$H$5,0) | AB18: =IFERROR(M18*P18/SUMPRODUCT($M$17:$M$41,$P$17:$P$41)*$L$5,0) | AC18: =IFERROR(AB18/AA18,0) | AD18: =IFERROR(M18*R18/SUMPRODUCT($M$17:$M$41,$R$17:$R$41)*$M$5,0) | AE18: =X18*Settings!$B$7+Z18*Settings!$B$8+W18*Settings!$B$9+AB18*Settings!$B$10+AD18*Settings!$B$11+S18*Settings!$B$12+T18*Settings!$B$13+U18*Settings!$B$14
A19: QB | B19: Josh Johnson | C19: 3 | D19: 40 | E19: role avg (from WAS) | I19: 0.0233 | J19: 17 | K19: 0.012 | L19: 0.0019 | M19: 0.0105 | O19: 1 | P19: 0.9 | Q19: 1 | R19: 1.13 | S19: =IFERROR(K19*$I$5,0) | T19: =IFERROR(K19*$J$5,0) | U19: =IFERROR(K19*$K$5,0) | V19: =IFERROR(L19*$G$5,0) | W19: =IFERROR(V19*N19,0) | X19: =IFERROR(L19*O19/SUMPRODUCT($L$17:$L$41,$O$17:$O$41)*$I$5,0) | Y19: =IFERROR(X19/W19,0) | Z19: =IFERROR(L19*Q19/SUMPRODUCT($L$17:$L$41,$Q$17:$Q$41)*$J$5,0) | AA19: =IFERROR(M19*$H$5,0) | AB19: =IFERROR(M19*P19/SUMPRODUCT($M$17:$M$41,$P$17:$P$41)*$L$5,0) | AC19: =IFERROR(AB19/AA19,0) | AD19: =IFERROR(M19*R19/SUMPRODUCT($M$17:$M$41,$R$17:$R$41)*$M$5,0) | AE19: =X19*Settings!$B$7+Z19*Settings!$B$8+W19*Settings!$B$9+AB19*Settings!$B$10+AD19*Settings!$B$11+S19*Settings!$B$12+T19*Settings!$B$13+U19*Settings!$B$14
A20: QB | B20: Other QBs | S20: =IFERROR(K20*$I$5,0) | T20: =IFERROR(K20*$J$5,0) | U20: =IFERROR(K20*$K$5,0) | V20: =IFERROR(L20*$G$5,0) | W20: =IFERROR(V20*N20,0) | X20: =IFERROR(L20*O20/SUMPRODUCT($L$17:$L$41,$O$17:$O$41)*$I$5,0) | Y20: =IFERROR(X20/W20,0) | Z20: =IFERROR(L20*Q20/SUMPRODUCT($L$17:$L$41,$Q$17:$Q$41)*$J$5,0) | AA20: =IFERROR(M20*$H$5,0) | AB20: =IFERROR(M20*P20/SUMPRODUCT($M$17:$M$41,$P$17:$P$41)*$L$5,0) | AC20: =IFERROR(AB20/AA20,0) | AD20: =IFERROR(M20*R20/SUMPRODUCT($M$17:$M$41,$R$17:$R$41)*$M$5,0) | AE20: =X20*Settings!$B$7+Z20*Settings!$B$8+W20*Settings!$B$9+AB20*Settings!$B$10+AD20*Settings!$B$11+S20*Settings!$B$12+T20*Settings!$B$13+U20*Settings!$B$14
A21: RB | B21: Chase Brown | C21: 1 | D21: 26 | E21: ACT | F21: 0.0253 | G21: 0.1035 | H21: 0.1447 | I21: 0.6253 | J21: 17 | L21: 0.1129 | M21: 0.5864 | N21: 0.8212 | O21: 0.86 | P21: 1.01 | Q21: 1 | R21: 0.93 | S21: =IFERROR(K21*$I$5,0) | T21: =IFERROR(K21*$J$5,0) | U21: =IFERROR(K21*$K$5,0) | V21: =IFERROR(L21*$G$5,0) | W21: =IFERROR(V21*N21,0) | X21: =IFERROR(L21*O21/SUMPRODUCT($L$17:$L$41,$O$17:$O$41)*$I$5,0) | Y21: =IFERROR(X21/W21,0) | Z21: =IFERROR(L21*Q21/SUMPRODUCT($L$17:$L$41,$Q$17:$Q$41)*$J$5,0) | AA21: =IFERROR(M21*$H$5,0) | AB21: =IFERROR(M21*P21/SUMPRODUCT($M$17:$M$41,$P$17:$P$41)*$L$5,0) | AC21: =IFERROR(AB21/AA21,0) | AD21: =IFERROR(M21*R21/SUMPRODUCT($M$17:$M$41,$R$17:$R$41)*$M$5,0) | AE21: =X21*Settings!$B$7+Z21*Settings!$B$8+W21*Settings!$B$9+AB21*Settings!$B$10+AD21*Settings!$B$11+S21*Settings!$B$12+T21*Settings!$B$13+U21*Settings!$B$14
A22: RB | B22: Samaje Perine | C22: 2 | D22: 30 | E22: ACT | F22: 0.1174 | G22: 0.0612 | H22: 0.0345 | I22: 0.2264 | J22: 17 | L22: 0.0527 | M22: 0.1763 | N22: 0.8242 | O22: 0.95 | P22: 1.06 | Q22: 0.9 | R22: 0.99 | S22: =IFERROR(K22*$I$5,0) | T22: =IFERROR(K22*$J$5,0) | U22: =IFERROR(K22*$K$5,0) | V22: =IFERROR(L22*$G$5,0) | W22: =IFERROR(V22*N22,0) | X22: =IFERROR(L22*O22/SUMPRODUCT($L$17:$L$41,$O$17:$O$41)*$I$5,0) | Y22: =IFERROR(X22/W22,0) | Z22: =IFERROR(L22*Q22/SUMPRODUCT($L$17:$L$41,$Q$17:$Q$41)*$J$5,0) | AA22: =IFERROR(M22*$H$5,0) | AB22: =IFERROR(M22*P22/SUMPRODUCT($M$17:$M$41,$P$17:$P$41)*$L$5,0) | AC22: =IFERROR(AB22/AA22,0) | AD22: =IFERROR(M22*R22/SUMPRODUCT($M$17:$M$41,$R$17:$R$41)*$M$5,0) | AE22: =X22*Settings!$B$7+Z22*Settings!$B$8+W22*Settings!$B$9+AB22*Settings!$B$10+AD22*Settings!$B$11+S22*Settings!$B$12+T22*Settings!$B$13+U22*Settings!$B$14
A23: RB | B23: Tahj Brooks | C23: 3 | D23: 24 | E23: ACT | H23: 0.0033 | I23: 0.0431 | J23: 17 | L23: 0.0079 | M23: 0.0532 | N23: 0.5 | O23: 0.97 | P23: 0.85 | Q23: 1 | R23: 1 | S23: =IFERROR(K23*$I$5,0) | T23: =IFERROR(K23*$J$5,0) | U23: =IFERROR(K23*$K$5,0) | V23: =IFERROR(L23*$G$5,0) | W23: =IFERROR(V23*N23,0) | X23: =IFERROR(L23*O23/SUMPRODUCT($L$17:$L$41,$O$17:$O$41)*$I$5,0) | Y23: =IFERROR(X23/W23,0) | Z23: =IFERROR(L23*Q23/SUMPRODUCT($L$17:$L$41,$Q$17:$Q$41)*$J$5,0) | AA23: =IFERROR(M23*$H$5,0) | AB23: =IFERROR(M23*P23/SUMPRODUCT($M$17:$M$41,$P$17:$P$41)*$L$5,0) | AC23: =IFERROR(AB23/AA23,0) | AD23: =IFERROR(M23*R23/SUMPRODUCT($M$17:$M$41,$R$17:$R$41)*$M$5,0) | AE23: =X23*Settings!$B$7+Z23*Settings!$B$8+W23*Settings!$B$9+AB23*Settings!$B$10+AD23*Settings!$B$11+S23*Settings!$B$12+T23*Settings!$B$13+U23*Settings!$B$14
A24: RB | B24: Jamal Haynes | C24: 4 | D24: 23 | E24: role avg (rookie) | J24: 17 | L24: 0.0048 | M24: 0.0146 | N24: 0.75 | O24: 1 | P24: 1 | Q24: 1 | R24: 1 | S24: =IFERROR(K24*$I$5,0) | T24: =IFERROR(K24*$J$5,0) | U24: =IFERROR(K24*$K$5,0) | V24: =IFERROR(L24*$G$5,0) | W24: =IFERROR(V24*N24,0) | X24: =IFERROR(L24*O24/SUMPRODUCT($L$17:$L$41,$O$17:$O$41)*$I$5,0) | Y24: =IFERROR(X24/W24,0) | Z24: =IFERROR(L24*Q24/SUMPRODUCT($L$17:$L$41,$Q$17:$Q$41)*$J$5,0) | AA24: =IFERROR(M24*$H$5,0) | AB24: =IFERROR(M24*P24/SUMPRODUCT($M$17:$M$41,$P$17:$P$41)*$L$5,0) | AC24: =IFERROR(AB24/AA24,0) | AD24: =IFERROR(M24*R24/SUMPRODUCT($M$17:$M$41,$R$17:$R$41)*$M$5,0) | AE24: =X24*Settings!$B$7+Z24*Settings!$B$8+W24*Settings!$B$9+AB24*Settings!$B$10+AD24*Settings!$B$11+S24*Settings!$B$12+T24*Settings!$B$13+U24*Settings!$B$14
A25: RB | B25: Kendall Milton | C25: 5 | D25: 24 | E25: ACT | I25: 0.0054 | J25: 17 | L25: 0.0019 | M25: 0.0097 | O25: 1 | P25: 0.93 | Q25: 1 | R25: 1 | S25: =IFERROR(K25*$I$5,0) | T25: =IFERROR(K25*$J$5,0) | U25: =IFERROR(K25*$K$5,0) | V25: =IFERROR(L25*$G$5,0) | W25: =IFERROR(V25*N25,0) | X25: =IFERROR(L25*O25/SUMPRODUCT($L$17:$L$41,$O$17:$O$41)*$I$5,0) | Y25: =IFERROR(X25/W25,0) | Z25: =IFERROR(L25*Q25/SUMPRODUCT($L$17:$L$41,$Q$17:$Q$41)*$J$5,0) | AA25: =IFERROR(M25*$H$5,0) | AB25: =IFERROR(M25*P25/SUMPRODUCT($M$17:$M$41,$P$17:$P$41)*$L$5,0) | AC25: =IFERROR(AB25/AA25,0) | AD25: =IFERROR(M25*R25/SUMPRODUCT($M$17:$M$41,$R$17:$R$41)*$M$5,0) | AE25: =X25*Settings!$B$7+Z25*Settings!$B$8+W25*Settings!$B$9+AB25*Settings!$B$10+AD25*Settings!$B$11+S25*Settings!$B$12+T25*Settings!$B$13+U25*Settings!$B$14
A26: RB | B26: Gary Brightwell | C26: 6 | D26: 28 | E26: ACT | F26: 0.0144 | J26: 17 | L26: 0.0102 | M26: 0.0146 | N26: 0.7143 | O26: 0.99 | P26: 0.85 | Q26: 1 | R26: 1 | S26: =IFERROR(K26*$I$5,0) | T26: =IFERROR(K26*$J$5,0) | U26: =IFERROR(K26*$K$5,0) | V26: =IFERROR(L26*$G$5,0) | W26: =IFERROR(V26*N26,0) | X26: =IFERROR(L26*O26/SUMPRODUCT($L$17:$L$41,$O$17:$O$41)*$I$5,0) | Y26: =IFERROR(X26/W26,0) | Z26: =IFERROR(L26*Q26/SUMPRODUCT($L$17:$L$41,$Q$17:$Q$41)*$J$5,0) | AA26: =IFERROR(M26*$H$5,0) | AB26: =IFERROR(M26*P26/SUMPRODUCT($M$17:$M$41,$P$17:$P$41)*$L$5,0) | AC26: =IFERROR(AB26/AA26,0) | AD26: =IFERROR(M26*R26/SUMPRODUCT($M$17:$M$41,$R$17:$R$41)*$M$5,0) | AE26: =X26*Settings!$B$7+Z26*Settings!$B$8+W26*Settings!$B$9+AB26*Settings!$B$10+AD26*Settings!$B$11+S26*Settings!$B$12+T26*Settings!$B$13+U26*Settings!$B$14
A27: RB | B27: Other RBs | S27: =IFERROR(K27*$I$5,0) | T27: =IFERROR(K27*$J$5,0) | U27: =IFERROR(K27*$K$5,0) | V27: =IFERROR(L27*$G$5,0) | W27: =IFERROR(V27*N27,0) | X27: =IFERROR(L27*O27/SUMPRODUCT($L$17:$L$41,$O$17:$O$41)*$I$5,0) | Y27: =IFERROR(X27/W27,0) | Z27: =IFERROR(L27*Q27/SUMPRODUCT($L$17:$L$41,$Q$17:$Q$41)*$J$5,0) | AA27: =IFERROR(M27*$H$5,0) | AB27: =IFERROR(M27*P27/SUMPRODUCT($M$17:$M$41,$P$17:$P$41)*$L$5,0) | AC27: =IFERROR(AB27/AA27,0) | AD27: =IFERROR(M27*R27/SUMPRODUCT($M$17:$M$41,$R$17:$R$41)*$M$5,0) | AE27: =X27*Settings!$B$7+Z27*Settings!$B$8+W27*Settings!$B$9+AB27*Settings!$B$10+AD27*Settings!$B$11+S27*Settings!$B$12+T27*Settings!$B$13+U27*Settings!$B$14
A28: WR | B28: Ja'Marr Chase | C28: 1 | D28: 26 | E28: ACT | F28: 0.2449 | G28: 0.2787 | H28: 0.3043 | I28: 0.0081 | J28: 17 | L28: 0.2742 | M28: 0.0105 | N28: 0.6941 | O28: 1.14 | P28: 1.03 | Q28: 1.03 | R28: 1 | S28: =IFERROR(K28*$I$5,0) | T28: =IFERROR(K28*$J$5,0) | U28: =IFERROR(K28*$K$5,0) | V28: =IFERROR(L28*$G$5,0) | W28: =IFERROR(V28*N28,0) | X28: =IFERROR(L28*O28/SUMPRODUCT($L$17:$L$41,$O$17:$O$41)*$I$5,0) | Y28: =IFERROR(X28/W28,0) | Z28: =IFERROR(L28*Q28/SUMPRODUCT($L$17:$L$41,$Q$17:$Q$41)*$J$5,0) | AA28: =IFERROR(M28*$H$5,0) | AB28: =IFERROR(M28*P28/SUMPRODUCT($M$17:$M$41,$P$17:$P$41)*$L$5,0) | AC28: =IFERROR(AB28/AA28,0) | AD28: =IFERROR(M28*R28/SUMPRODUCT($M$17:$M$41,$R$17:$R$41)*$M$5,0) | AE28: =X28*Settings!$B$7+Z28*Settings!$B$8+W28*Settings!$B$9+AB28*Settings!$B$10+AD28*Settings!$B$11+S28*Settings!$B$12+T28*Settings!$B$13+U28*Settings!$B$14
A29: WR | B29: Tee Higgins | C29: 2 | D29: 27 | E29: ACT | F29: 0.1284 | G29: 0.1736 | H29: 0.1612 | J29: 17 | L29: 0.1592 | M29: 0.0028 | N29: 0.6113 | O29: 1.15 | P29: 1 | Q29: 1.09 | R29: 1 | S29: =IFERROR(K29*$I$5,0) | T29: =IFERROR(K29*$J$5,0) | U29: =IFERROR(K29*$K$5,0) | V29: =IFERROR(L29*$G$5,0) | W29: =IFERROR(V29*N29,0) | X29: =IFERROR(L29*O29/SUMPRODUCT($L$17:$L$41,$O$17:$O$41)*$I$5,0) | Y29: =IFERROR(X29/W29,0) | Z29: =IFERROR(L29*Q29/SUMPRODUCT($L$17:$L$41,$Q$17:$Q$41)*$J$5,0) | AA29: =IFERROR(M29*$H$5,0) | AB29: =IFERROR(M29*P29/SUMPRODUCT($M$17:$M$41,$P$17:$P$41)*$L$5,0) | AC29: =IFERROR(AB29/AA29,0) | AD29: =IFERROR(M29*R29/SUMPRODUCT($M$17:$M$41,$R$17:$R$41)*$M$5,0) | AE29: =X29*Settings!$B$7+Z29*Settings!$B$8+W29*Settings!$B$9+AB29*Settings!$B$10+AD29*Settings!$B$11+S29*Settings!$B$12+T29*Settings!$B$13+U29*Settings!$B$14
A30: WR | B30: Andrei Iosivas | C30: 3 | D30: 26 | E30: ACT | F30: 0.0422 | G30: 0.0971 | H30: 0.0954 | I30: 0.0081 | J30: 17 | L30: 0.0927 | M30: 0.0055 | N30: 0.5813 | O30: 0.98 | P30: 1.01 | Q30: 0.97 | R30: 1 | S30: =IFERROR(K30*$I$5,0) | T30: =IFERROR(K30*$J$5,0) | U30: =IFERROR(K30*$K$5,0) | V30: =IFERROR(L30*$G$5,0) | W30: =IFERROR(V30*N30,0) | X30: =IFERROR(L30*O30/SUMPRODUCT($L$17:$L$41,$O$17:$O$41)*$I$5,0) | Y30: =IFERROR(X30/W30,0) | Z30: =IFERROR(L30*Q30/SUMPRODUCT($L$17:$L$41,$Q$17:$Q$41)*$J$5,0) | AA30: =IFERROR(M30*$H$5,0) | AB30: =IFERROR(M30*P30/SUMPRODUCT($M$17:$M$41,$P$17:$P$41)*$L$5,0) | AC30: =IFERROR(AB30/AA30,0) | AD30: =IFERROR(M30*R30/SUMPRODUCT($M$17:$M$41,$R$17:$R$41)*$M$5,0) | AE30: =X30*Settings!$B$7+Z30*Settings!$B$8+W30*Settings!$B$9+AB30*Settings!$B$10+AD30*Settings!$B$11+S30*Settings!$B$12+T30*Settings!$B$13+U30*Settings!$B$14
A31: WR | B31: Mitch Tinsley | C31: 4 | D31: 26 | E31: ACT | H31: 0.0395 | J31: 17 | L31: 0.0417 | M31: 0.0009 | N31: 0.3333 | O31: 0.83 | P31: 1 | Q31: 1.23 | R31: 1 | S31: =IFERROR(K31*$I$5,0) | T31: =IFERROR(K31*$J$5,0) | U31: =IFERROR(K31*$K$5,0) | V31: =IFERROR(L31*$G$5,0) | W31: =IFERROR(V31*N31,0) | X31: =IFERROR(L31*O31/SUMPRODUCT($L$17:$L$41,$O$17:$O$41)*$I$5,0) | Y31: =IFERROR(X31/W31,0) | Z31: =IFERROR(L31*Q31/SUMPRODUCT($L$17:$L$41,$Q$17:$Q$41)*$J$5,0) | AA31: =IFERROR(M31*$H$5,0) | AB31: =IFERROR(M31*P31/SUMPRODUCT($M$17:$M$41,$P$17:$P$41)*$L$5,0) | AC31: =IFERROR(AB31/AA31,0) | AD31: =IFERROR(M31*R31/SUMPRODUCT($M$17:$M$41,$R$17:$R$41)*$M$5,0) | AE31: =X31*Settings!$B$7+Z31*Settings!$B$8+W31*Settings!$B$9+AB31*Settings!$B$10+AD31*Settings!$B$11+S31*Settings!$B$12+T31*Settings!$B$13+U31*Settings!$B$14
A32: WR | B32: Colbie Young | C32: 5 | D32: 24 | E32: role avg (rookie) | J32: 17 | L32: 0.022 | M32: 0.0024 | N32: 0.65 | O32: 1 | P32: 1 | Q32: 1 | R32: 1 | S32: =IFERROR(K32*$I$5,0) | T32: =IFERROR(K32*$J$5,0) | U32: =IFERROR(K32*$K$5,0) | V32: =IFERROR(L32*$G$5,0) | W32: =IFERROR(V32*N32,0) | X32: =IFERROR(L32*O32/SUMPRODUCT($L$17:$L$41,$O$17:$O$41)*$I$5,0) | Y32: =IFERROR(X32/W32,0) | Z32: =IFERROR(L32*Q32/SUMPRODUCT($L$17:$L$41,$Q$17:$Q$41)*$J$5,0) | AA32: =IFERROR(M32*$H$5,0) | AB32: =IFERROR(M32*P32/SUMPRODUCT($M$17:$M$41,$P$17:$P$41)*$L$5,0) | AC32: =IFERROR(AB32/AA32,0) | AD32: =IFERROR(M32*R32/SUMPRODUCT($M$17:$M$41,$R$17:$R$41)*$M$5,0) | AE32: =X32*Settings!$B$7+Z32*Settings!$B$8+W32*Settings!$B$9+AB32*Settings!$B$10+AD32*Settings!$B$11+S32*Settings!$B$12+T32*Settings!$B$13+U32*Settings!$B$14
A33: WR | B33: Noah Thomas | C33: 6 | D33: 22 | E33: role avg (rookie) | J33: 17 | L33: 0.0094 | M33: 0.0022 | N33: 0.65 | O33: 1 | P33: 1 | Q33: 1 | R33: 1 | S33: =IFERROR(K33*$I$5,0) | T33: =IFERROR(K33*$J$5,0) | U33: =IFERROR(K33*$K$5,0) | V33: =IFERROR(L33*$G$5,0) | W33: =IFERROR(V33*N33,0) | X33: =IFERROR(L33*O33/SUMPRODUCT($L$17:$L$41,$O$17:$O$41)*$I$5,0) | Y33: =IFERROR(X33/W33,0) | Z33: =IFERROR(L33*Q33/SUMPRODUCT($L$17:$L$41,$Q$17:$Q$41)*$J$5,0) | AA33: =IFERROR(M33*$H$5,0) | AB33: =IFERROR(M33*P33/SUMPRODUCT($M$17:$M$41,$P$17:$P$41)*$L$5,0) | AC33: =IFERROR(AB33/AA33,0) | AD33: =IFERROR(M33*R33/SUMPRODUCT($M$17:$M$41,$R$17:$R$41)*$M$5,0) | AE33: =X33*Settings!$B$7+Z33*Settings!$B$8+W33*Settings!$B$9+AB33*Settings!$B$10+AD33*Settings!$B$11+S33*Settings!$B$12+T33*Settings!$B$13+U33*Settings!$B$14
A34: WR | B34: Kendric Pryor | C34: 7 | D34: 28 | E34: ACT | G34: 0.0016 | J34: 17 | L34: 0.0026 | M34: 0.0009 | N34: 1 | O34: 1.01 | P34: 1 | Q34: 1 | R34: 1 | S34: =IFERROR(K34*$I$5,0) | T34: =IFERROR(K34*$J$5,0) | U34: =IFERROR(K34*$K$5,0) | V34: =IFERROR(L34*$G$5,0) | W34: =IFERROR(V34*N34,0) | X34: =IFERROR(L34*O34/SUMPRODUCT($L$17:$L$41,$O$17:$O$41)*$I$5,0) | Y34: =IFERROR(X34/W34,0) | Z34: =IFERROR(L34*Q34/SUMPRODUCT($L$17:$L$41,$Q$17:$Q$41)*$J$5,0) | AA34: =IFERROR(M34*$H$5,0) | AB34: =IFERROR(M34*P34/SUMPRODUCT($M$17:$M$41,$P$17:$P$41)*$L$5,0) | AC34: =IFERROR(AB34/AA34,0) | AD34: =IFERROR(M34*R34/SUMPRODUCT($M$17:$M$41,$R$17:$R$41)*$M$5,0) | AE34: =X34*Settings!$B$7+Z34*Settings!$B$8+W34*Settings!$B$9+AB34*Settings!$B$10+AD34*Settings!$B$11+S34*Settings!$B$12+T34*Settings!$B$13+U34*Settings!$B$14
A35: WR | B35: Charlie Jones | C35: 8 | D35: 27 | E35: ACT | F35: 0.0152 | G35: 0.0016 | H35: 0.0016 | J35: 17 | L35: 0.0039 | M35: 0.0043 | N35: 0.8937 | O35: 0.98 | P35: 1.05 | Q35: 1 | R35: 1 | S35: =IFERROR(K35*$I$5,0) | T35: =IFERROR(K35*$J$5,0) | U35: =IFERROR(K35*$K$5,0) | V35: =IFERROR(L35*$G$5,0) | W35: =IFERROR(V35*N35,0) | X35: =IFERROR(L35*O35/SUMPRODUCT($L$17:$L$41,$O$17:$O$41)*$I$5,0) | Y35: =IFERROR(X35/W35,0) | Z35: =IFERROR(L35*Q35/SUMPRODUCT($L$17:$L$41,$Q$17:$Q$41)*$J$5,0) | AA35: =IFERROR(M35*$H$5,0) | AB35: =IFERROR(M35*P35/SUMPRODUCT($M$17:$M$41,$P$17:$P$41)*$L$5,0) | AC35: =IFERROR(AB35/AA35,0) | AD35: =IFERROR(M35*R35/SUMPRODUCT($M$17:$M$41,$R$17:$R$41)*$M$5,0) | AE35: =X35*Settings!$B$7+Z35*Settings!$B$8+W35*Settings!$B$9+AB35*Settings!$B$10+AD35*Settings!$B$11+S35*Settings!$B$12+T35*Settings!$B$13+U35*Settings!$B$14
A36: WR | B36: Other WRs | S36: =IFERROR(K36*$I$5,0) | T36: =IFERROR(K36*$J$5,0) | U36: =IFERROR(K36*$K$5,0) | V36: =IFERROR(L36*$G$5,0) | W36: =IFERROR(V36*N36,0) | X36: =IFERROR(L36*O36/SUMPRODUCT($L$17:$L$41,$O$17:$O$41)*$I$5,0) | Y36: =IFERROR(X36/W36,0) | Z36: =IFERROR(L36*Q36/SUMPRODUCT($L$17:$L$41,$Q$17:$Q$41)*$J$5,0) | AA36: =IFERROR(M36*$H$5,0) | AB36: =IFERROR(M36*P36/SUMPRODUCT($M$17:$M$41,$P$17:$P$41)*$L$5,0) | AC36: =IFERROR(AB36/AA36,0) | AD36: =IFERROR(M36*R36/SUMPRODUCT($M$17:$M$41,$R$17:$R$41)*$M$5,0) | AE36: =X36*Settings!$B$7+Z36*Settings!$B$8+W36*Settings!$B$9+AB36*Settings!$B$10+AD36*Settings!$B$11+S36*Settings!$B$12+T36*Settings!$B$13+U36*Settings!$B$14
A37: TE | B37: Mike Gesicki | C37: 1 | D37: 30 | E37: ACT | F37: 0.0832 | G37: 0.1322 | H37: 0.0691 | J37: 17 | L37: 0.1062 | M37: 0.0012 | N37: 0.7012 | O37: 1 | P37: 1 | Q37: 1.01 | R37: 1 | S37: =IFERROR(K37*$I$5,0) | T37: =IFERROR(K37*$J$5,0) | U37: =IFERROR(K37*$K$5,0) | V37: =IFERROR(L37*$G$5,0) | W37: =IFERROR(V37*N37,0) | X37: =IFERROR(L37*O37/SUMPRODUCT($L$17:$L$41,$O$17:$O$41)*$I$5,0) | Y37: =IFERROR(X37/W37,0) | Z37: =IFERROR(L37*Q37/SUMPRODUCT($L$17:$L$41,$Q$17:$Q$41)*$J$5,0) | AA37: =IFERROR(M37*$H$5,0) | AB37: =IFERROR(M37*P37/SUMPRODUCT($M$17:$M$41,$P$17:$P$41)*$L$5,0) | AC37: =IFERROR(AB37/AA37,0) | AD37: =IFERROR(M37*R37/SUMPRODUCT($M$17:$M$41,$R$17:$R$41)*$M$5,0) | AE37: =X37*Settings!$B$7+Z37*Settings!$B$8+W37*Settings!$B$9+AB37*Settings!$B$10+AD37*Settings!$B$11+S37*Settings!$B$12+T37*Settings!$B$13+U37*Settings!$B$14
A38: TE | B38: Erick All | C38: 2 | D38: 25 | E38: ACT | G38: 0.035 | J38: 17 | L38: 0.041 | M38: 0.001 | N38: 0.9091 | O38: 0.96 | P38: 1 | Q38: 0.91 | R38: 1 | S38: =IFERROR(K38*$I$5,0) | T38: =IFERROR(K38*$J$5,0) | U38: =IFERROR(K38*$K$5,0) | V38: =IFERROR(L38*$G$5,0) | W38: =IFERROR(V38*N38,0) | X38: =IFERROR(L38*O38/SUMPRODUCT($L$17:$L$41,$O$17:$O$41)*$I$5,0) | Y38: =IFERROR(X38/W38,0) | Z38: =IFERROR(L38*Q38/SUMPRODUCT($L$17:$L$41,$Q$17:$Q$41)*$J$5,0) | AA38: =IFERROR(M38*$H$5,0) | AB38: =IFERROR(M38*P38/SUMPRODUCT($M$17:$M$41,$P$17:$P$41)*$L$5,0) | AC38: =IFERROR(AB38/AA38,0) | AD38: =IFERROR(M38*R38/SUMPRODUCT($M$17:$M$41,$R$17:$R$41)*$M$5,0) | AE38: =X38*Settings!$B$7+Z38*Settings!$B$8+W38*Settings!$B$9+AB38*Settings!$B$10+AD38*Settings!$B$11+S38*Settings!$B$12+T38*Settings!$B$13+U38*Settings!$B$14
A39: TE | B39: Drew Sample | C39: 3 | D39: 30 | E39: ACT | F39: 0.0456 | G39: 0.035 | H39: 0.0329 | I39: 0.0027 | J39: 17 | L39: 0.0336 | M39: 0.0025 | N39: 0.8107 | O39: 0.86 | P39: 0.96 | Q39: 0.93 | R39: 1.55 | S39: =IFERROR(K39*$I$5,0) | T39: =IFERROR(K39*$J$5,0) | U39: =IFERROR(K39*$K$5,0) | V39: =IFERROR(L39*$G$5,0) | W39: =IFERROR(V39*N39,0) | X39: =IFERROR(L39*O39/SUMPRODUCT($L$17:$L$41,$O$17:$O$41)*$I$5,0) | Y39: =IFERROR(X39/W39,0) | Z39: =IFERROR(L39*Q39/SUMPRODUCT($L$17:$L$41,$Q$17:$Q$41)*$J$5,0) | AA39: =IFERROR(M39*$H$5,0) | AB39: =IFERROR(M39*P39/SUMPRODUCT($M$17:$M$41,$P$17:$P$41)*$L$5,0) | AC39: =IFERROR(AB39/AA39,0) | AD39: =IFERROR(M39*R39/SUMPRODUCT($M$17:$M$41,$R$17:$R$41)*$M$5,0) | AE39: =X39*Settings!$B$7+Z39*Settings!$B$8+W39*Settings!$B$9+AB39*Settings!$B$10+AD39*Settings!$B$11+S39*Settings!$B$12+T39*Settings!$B$13+U39*Settings!$B$14
A40: TE | B40: Jack Endries | C40: 4 | D40: 22 | E40: role avg (rookie) | J40: 17 | L40: 0.0184 | M40: 0.0024 | N40: 0.65 | O40: 1 | P40: 1 | Q40: 1 | R40: 1 | S40: =IFERROR(K40*$I$5,0) | T40: =IFERROR(K40*$J$5,0) | U40: =IFERROR(K40*$K$5,0) | V40: =IFERROR(L40*$G$5,0) | W40: =IFERROR(V40*N40,0) | X40: =IFERROR(L40*O40/SUMPRODUCT($L$17:$L$41,$O$17:$O$41)*$I$5,0) | Y40: =IFERROR(X40/W40,0) | Z40: =IFERROR(L40*Q40/SUMPRODUCT($L$17:$L$41,$Q$17:$Q$41)*$J$5,0) | AA40: =IFERROR(M40*$H$5,0) | AB40: =IFERROR(M40*P40/SUMPRODUCT($M$17:$M$41,$P$17:$P$41)*$L$5,0) | AC40: =IFERROR(AB40/AA40,0) | AD40: =IFERROR(M40*R40/SUMPRODUCT($M$17:$M$41,$R$17:$R$41)*$M$5,0) | AE40: =X40*Settings!$B$7+Z40*Settings!$B$8+W40*Settings!$B$9+AB40*Settings!$B$10+AD40*Settings!$B$11+S40*Settings!$B$12+T40*Settings!$B$13+U40*Settings!$B$14
A41: TE | B41: Other TEs | S41: =IFERROR(K41*$I$5,0) | T41: =IFERROR(K41*$J$5,0) | U41: =IFERROR(K41*$K$5,0) | V41: =IFERROR(L41*$G$5,0) | W41: =IFERROR(V41*N41,0) | X41: =IFERROR(L41*O41/SUMPRODUCT($L$17:$L$41,$O$17:$O$41)*$I$5,0) | Y41: =IFERROR(X41/W41,0) | Z41: =IFERROR(L41*Q41/SUMPRODUCT($L$17:$L$41,$Q$17:$Q$41)*$J$5,0) | AA41: =IFERROR(M41*$H$5,0) | AB41: =IFERROR(M41*P41/SUMPRODUCT($M$17:$M$41,$P$17:$P$41)*$L$5,0) | AC41: =IFERROR(AB41/AA41,0) | AD41: =IFERROR(M41*R41/SUMPRODUCT($M$17:$M$41,$R$17:$R$41)*$M$5,0) | AE41: =X41*Settings!$B$7+Z41*Settings!$B$8+W41*Settings!$B$9+AB41*Settings!$B$10+AD41*Settings!$B$11+S41*Settings!$B$12+T41*Settings!$B$13+U41*Settings!$B$14
B43: SHARE TOTALS - must equal 100% | E43: each column is a share of this team's season total - it must add to 100% | K43: =SUM(K17:K41) | L43: =SUM(L17:L41) | M43: =SUM(M17:M41) | S43: =SUM(S17:S41) | T43: =SUM(T17:T41) | U43: =SUM(U17:U41) | V43: =SUM(V17:V41) | W43: =SUM(W17:W41) | X43: =SUM(X17:X41) | Y43: =SUM(Y17:Y41) | Z43: =SUM(Z17:Z41) | ... AE43: =SUM(AE17:AE41)
B45: Green = balanced. Red = your shares don't add to 100%; player totals won't match the team totals until they do.

Sheet CLE
A1: CLE - 2026 projections
A3: TEAM TOTALS | C3: blue = edit; everything below divides these up
B4: Games | C4: Plays/G | D4: Plays | E4: Pass Rate | F4: Pass Att | G4: Targets | H4: Rush Att | I4: Pass Yds | J4: Pass TD | K4: Int | L4: Rush Yds | M4: Rush TD
B5: 17 | C5: 63.2 | D5: =C5*B5 | E5: 0.5923 | F5: 586 | G5: =ROUND(F5*Settings!$B$4,0) | H5: 438 | I5: 3649 | J5: 21 | K5: 17 | L5: 1790 | M5: 12
A7: LAST 3 YEARS | B7: Season | C7: Plays | D7: Plays/G | E7: Pass Rate | F7: Pass Att | G7: Rush Att | H7: Pass Yds | I7: Rush Yds | J7: Pass TD | K7: Rush TD | L7: Y/A | M7: Y/C
B8: 2023 | C8: 1187 | D8: 69.8235 | E8: 0.5636 | F8: 624 | G8: 518 | H8: 4011 | I8: 2017 | J8: 24 | K8: 15 | L8: 6.4279 | M8: 3.8938
B9: 2024 | C9: 1118 | D9: 65.7647 | E9: 0.6503 | F9: 661 | G9: 391 | H9: 3879 | I9: 1608 | J9: 19 | K9: 8 | L9: 5.8684 | M9: 4.1125
B10: 2025 | C10: 1030 | D10: 60.5882 | E10: 0.5913 | F10: 558 | G10: 421 | H10: 3152 | I10: 1649 | J10: 16 | K10: 10 | L10: 5.6487 | M10: 3.9169
A12: OUT | B12: 15% of targets and 7% of carries left. Share is team-relative - it does NOT follow the player. | H12: David Njoku (9t/0r -> LAC), Jerome Ford (6t/6r -> WAS), Joe Flacco (0t/1r -> CIN)
A13: IN | B13: 3 new: Tylan Wallace (WR, from BAL - had 2% there), Jack Stoll (TE, from NO - had 2% there), Brenden Bates (TE, from HOU - had 0% there)
A14: STAFF | B14: NEW HC Todd Monken + OC Travis Switzer. Shift toward MORE RUN given QB uncertainty - lower pass rate.
A16: Pos | B16: Player | C16: Dep | D16: Age | E16: Status | F16: 2023 Tgt% | G16: 2024 Tgt% | H16: 2025 Tgt% | I16: 2025 Rush% | J16: Games | K16: Pass % | L16: Tgt % | M16: Rush % | N16: Catch % | O16: Rec Eff x | P16: Rush Eff x | Q16: RZ Tgt x | R16: RZ Rush x | S16: Pass Yds | T16: Pass TD | U16: Int | V16: Targets | W16: Rec | X16: Rec Yds | Y16: Yds/Rec | Z16: Rec TD | AA16: Rush Att | AB16: Rush Yds | AC16: Yds/Car | AD16: Rush TD | AE16: Half PPR
A17: QB | B17: Deshaun Watson | C17: 1 | D17: 30 | E17: ACT | J17: 17 | K17: 0.92 | L17: 0.0008 | M17: 0.0683 | O17: 1 | P17: 1.16 | Q17: 1 | R17: 1.06 | S17: =IFERROR(K17*$I$5,0) | T17: =IFERROR(K17*$J$5,0) | U17: =IFERROR(K17*$K$5,0) | V17: =IFERROR(L17*$G$5,0) | W17: =IFERROR(V17*N17,0) | X17: =IFERROR(L17*O17/SUMPRODUCT($L$17:$L$41,$O$17:$O$41)*$I$5,0) | Y17: =IFERROR(X17/W17,0) | Z17: =IFERROR(L17*Q17/SUMPRODUCT($L$17:$L$41,$Q$17:$Q$41)*$J$5,0) | AA17: =IFERROR(M17*$H$5,0) | AB17: =IFERROR(M17*P17/SUMPRODUCT($M$17:$M$41,$P$17:$P$41)*$L$5,0) | AC17: =IFERROR(AB17/AA17,0) | AD17: =IFERROR(M17*R17/SUMPRODUCT($M$17:$M$41,$R$17:$R$41)*$M$5,0) | AE17: =X17*Settings!$B$7+Z17*Settings!$B$8+W17*Settings!$B$9+AB17*Settings!$B$10+AD17*Settings!$B$11+S17*Settings!$B$12+T17*Settings!$B$13+U17*Settings!$B$14
A18: QB | B18: Shedeur Sanders | C18: 2 | D18: 24 | E18: ACT | I18: 0.0456 | J18: 17 | K18: 0.068 | L18: 0.0008 | M18: 0.0343 | O18: 1 | P18: 1.5 | Q18: 1 | R18: 0.95 | S18: =IFERROR(K18*$I$5,0) | T18: =IFERROR(K18*$J$5,0) | U18: =IFERROR(K18*$K$5,0) | V18: =IFERROR(L18*$G$5,0) | W18: =IFERROR(V18*N18,0) | X18: =IFERROR(L18*O18/SUMPRODUCT($L$17:$L$41,$O$17:$O$41)*$I$5,0) | Y18: =IFERROR(X18/W18,0) | Z18: =IFERROR(L18*Q18/SUMPRODUCT($L$17:$L$41,$Q$17:$Q$41)*$J$5,0) | AA18: =IFERROR(M18*$H$5,0) | AB18: =IFERROR(M18*P18/SUMPRODUCT($M$17:$M$41,$P$17:$P$41)*$L$5,0) | AC18: =IFERROR(AB18/AA18,0) | AD18: =IFERROR(M18*R18/SUMPRODUCT($M$17:$M$41,$R$17:$R$41)*$M$5,0) | AE18: =X18*Settings!$B$7+Z18*Settings!$B$8+W18*Settings!$B$9+AB18*Settings!$B$10+AD18*Settings!$B$11+S18*Settings!$B$12+T18*Settings!$B$13+U18*Settings!$B$14
A19: QB | B19: Taylen Green | C19: 3 | D19: 23 | E19: role avg (rookie) | J19: 17 | K19: 0.012 | L19: 0.0018 | M19: 0.0182 | O19: 1 | P19: 1 | Q19: 1 | R19: 1 | S19: =IFERROR(K19*$I$5,0) | T19: =IFERROR(K19*$J$5,0) | U19: =IFERROR(K19*$K$5,0) | V19: =IFERROR(L19*$G$5,0) | W19: =IFERROR(V19*N19,0) | X19: =IFERROR(L19*O19/SUMPRODUCT($L$17:$L$41,$O$17:$O$41)*$I$5,0) | Y19: =IFERROR(X19/W19,0) | Z19: =IFERROR(L19*Q19/SUMPRODUCT($L$17:$L$41,$Q$17:$Q$41)*$J$5,0) | AA19: =IFERROR(M19*$H$5,0) | AB19: =IFERROR(M19*P19/SUMPRODUCT($M$17:$M$41,$P$17:$P$41)*$L$5,0) | AC19: =IFERROR(AB19/AA19,0) | AD19: =IFERROR(M19*R19/SUMPRODUCT($M$17:$M$41,$R$17:$R$41)*$M$5,0) | AE19: =X19*Settings!$B$7+Z19*Settings!$B$8+W19*Settings!$B$9+AB19*Settings!$B$10+AD19*Settings!$B$11+S19*Settings!$B$12+T19*Settings!$B$13+U19*Settings!$B$14
A20: QB | B20: Other QBs | S20: =IFERROR(K20*$I$5,0) | T20: =IFERROR(K20*$J$5,0) | U20: =IFERROR(K20*$K$5,0) | V20: =IFERROR(L20*$G$5,0) | W20: =IFERROR(V20*N20,0) | X20: =IFERROR(L20*O20/SUMPRODUCT($L$17:$L$41,$O$17:$O$41)*$I$5,0) | Y20: =IFERROR(X20/W20,0) | Z20: =IFERROR(L20*Q20/SUMPRODUCT($L$17:$L$41,$Q$17:$Q$41)*$J$5,0) | AA20: =IFERROR(M20*$H$5,0) | AB20: =IFERROR(M20*P20/SUMPRODUCT($M$17:$M$41,$P$17:$P$41)*$L$5,0) | AC20: =IFERROR(AB20/AA20,0) | AD20: =IFERROR(M20*R20/SUMPRODUCT($M$17:$M$41,$R$17:$R$41)*$M$5,0) | AE20: =X20*Settings!$B$7+Z20*Settings!$B$8+W20*Settings!$B$9+AB20*Settings!$B$10+AD20*Settings!$B$11+S20*Settings!$B$12+T20*Settings!$B$13+U20*Settings!$B$14
A21: RB | B21: Quinshon Judkins | C21: 1 | D21: 22 | E21: ACT | H21: 0.069 | I21: 0.5516 | J21: 17 | L21: 0.0732 | M21: 0.5027 | N21: 0.7222 | O21: 0.86 | P21: 0.92 | Q21: 1 | R21: 1.06 | S21: =IFERROR(K21*$I$5,0) | T21: =IFERROR(K21*$J$5,0) | U21: =IFERROR(K21*$K$5,0) | V21: =IFERROR(L21*$G$5,0) | W21: =IFERROR(V21*N21,0) | X21: =IFERROR(L21*O21/SUMPRODUCT($L$17:$L$41,$O$17:$O$41)*$I$5,0) | Y21: =IFERROR(X21/W21,0) | Z21: =IFERROR(L21*Q21/SUMPRODUCT($L$17:$L$41,$Q$17:$Q$41)*$J$5,0) | AA21: =IFERROR(M21*$H$5,0) | AB21: =IFERROR(M21*P21/SUMPRODUCT($M$17:$M$41,$P$17:$P$41)*$L$5,0) | AC21: =IFERROR(AB21/AA21,0) | AD21: =IFERROR(M21*R21/SUMPRODUCT($M$17:$M$41,$R$17:$R$41)*$M$5,0) | AE21: =X21*Settings!$B$7+Z21*Settings!$B$8+W21*Settings!$B$9+AB21*Settings!$B$10+AD21*Settings!$B$11+S21*Settings!$B$12+T21*Settings!$B$13+U21*Settings!$B$14
A22: RB | B22: Dylan Sampson | C22: 2 | D22: 21 | E22: ACT | H22: 0.0766 | I22: 0.1559 | J22: 17 | L22: 0.0606 | M22: 0.179 | N22: 0.825 | O22: 1.08 | P22: 0.76 | Q22: 1.2 | R22: 0.82 | S22: =IFERROR(K22*$I$5,0) | T22: =IFERROR(K22*$J$5,0) | U22: =IFERROR(K22*$K$5,0) | V22: =IFERROR(L22*$G$5,0) | W22: =IFERROR(V22*N22,0) | X22: =IFERROR(L22*O22/SUMPRODUCT($L$17:$L$41,$O$17:$O$41)*$I$5,0) | Y22: =IFERROR(X22/W22,0) | Z22: =IFERROR(L22*Q22/SUMPRODUCT($L$17:$L$41,$Q$17:$Q$41)*$J$5,0) | AA22: =IFERROR(M22*$H$5,0) | AB22: =IFERROR(M22*P22/SUMPRODUCT($M$17:$M$41,$P$17:$P$41)*$L$5,0) | AC22: =IFERROR(AB22/AA22,0) | AD22: =IFERROR(M22*R22/SUMPRODUCT($M$17:$M$41,$R$17:$R$41)*$M$5,0) | AE22: =X22*Settings!$B$7+Z22*Settings!$B$8+W22*Settings!$B$9+AB22*Settings!$B$10+AD22*Settings!$B$11+S22*Settings!$B$12+T22*Settings!$B$13+U22*Settings!$B$14
A23: RB | B23: Raheim Sanders | C23: 3 | D23: 24 | E23: ACT | H23: 0.0077 | I23: 0.0647 | J23: 17 | L23: 0.0136 | M23: 0.0763 | N23: 0.75 | O23: 0.98 | P23: 0.92 | Q23: 1 | R23: 1.28 | S23: =IFERROR(K23*$I$5,0) | T23: =IFERROR(K23*$J$5,0) | U23: =IFERROR(K23*$K$5,0) | V23: =IFERROR(L23*$G$5,0) | W23: =IFERROR(V23*N23,0) | X23: =IFERROR(L23*O23/SUMPRODUCT($L$17:$L$41,$O$17:$O$41)*$I$5,0) | Y23: =IFERROR(X23/W23,0) | Z23: =IFERROR(L23*Q23/SUMPRODUCT($L$17:$L$41,$Q$17:$Q$41)*$J$5,0) | AA23: =IFERROR(M23*$H$5,0) | AB23: =IFERROR(M23*P23/SUMPRODUCT($M$17:$M$41,$P$17:$P$41)*$L$5,0) | AC23: =IFERROR(AB23/AA23,0) | AD23: =IFERROR(M23*R23/SUMPRODUCT($M$17:$M$41,$R$17:$R$41)*$M$5,0) | AE23: =X23*Settings!$B$7+Z23*Settings!$B$8+W23*Settings!$B$9+AB23*Settings!$B$10+AD23*Settings!$B$11+S23*Settings!$B$12+T23*Settings!$B$13+U23*Settings!$B$14
A24: RB | B24: Ahmani Marshall | C24: 4 | D24: 24 | E24: role avg (rookie) | J24: 17 | L24: 0.0078 | M24: 0.0404 | N24: 0.75 | O24: 1 | P24: 1 | Q24: 1 | R24: 1 | S24: =IFERROR(K24*$I$5,0) | T24: =IFERROR(K24*$J$5,0) | U24: =IFERROR(K24*$K$5,0) | V24: =IFERROR(L24*$G$5,0) | W24: =IFERROR(V24*N24,0) | X24: =IFERROR(L24*O24/SUMPRODUCT($L$17:$L$41,$O$17:$O$41)*$I$5,0) | Y24: =IFERROR(X24/W24,0) | Z24: =IFERROR(L24*Q24/SUMPRODUCT($L$17:$L$41,$Q$17:$Q$41)*$J$5,0) | AA24: =IFERROR(M24*$H$5,0) | AB24: =IFERROR(M24*P24/SUMPRODUCT($M$17:$M$41,$P$17:$P$41)*$L$5,0) | AC24: =IFERROR(AB24/AA24,0) | AD24: =IFERROR(M24*R24/SUMPRODUCT($M$17:$M$41,$R$17:$R$41)*$M$5,0) | AE24: =X24*Settings!$B$7+Z24*Settings!$B$8+W24*Settings!$B$9+AB24*Settings!$B$10+AD24*Settings!$B$11+S24*Settings!$B$12+T24*Settings!$B$13+U24*Settings!$B$14
A25: RB | B25: Davon Booth | C25: 5 | D25: 24 | E25: role avg (rookie) | J25: 17 | L25: 0.0044 | M25: 0.012 | N25: 0.75 | O25: 1 | P25: 1 | Q25: 1 | R25: 1 | S25: =IFERROR(K25*$I$5,0) | T25: =IFERROR(K25*$J$5,0) | U25: =IFERROR(K25*$K$5,0) | V25: =IFERROR(L25*$G$5,0) | W25: =IFERROR(V25*N25,0) | X25: =IFERROR(L25*O25/SUMPRODUCT($L$17:$L$41,$O$17:$O$41)*$I$5,0) | Y25: =IFERROR(X25/W25,0) | Z25: =IFERROR(L25*Q25/SUMPRODUCT($L$17:$L$41,$Q$17:$Q$41)*$J$5,0) | AA25: =IFERROR(M25*$H$5,0) | AB25: =IFERROR(M25*P25/SUMPRODUCT($M$17:$M$41,$P$17:$P$41)*$L$5,0) | AC25: =IFERROR(AB25/AA25,0) | AD25: =IFERROR(M25*R25/SUMPRODUCT($M$17:$M$41,$R$17:$R$41)*$M$5,0) | AE25: =X25*Settings!$B$7+Z25*Settings!$B$8+W25*Settings!$B$9+AB25*Settings!$B$10+AD25*Settings!$B$11+S25*Settings!$B$12+T25*Settings!$B$13+U25*Settings!$B$14
A26: RB | B26: Michael Burton | C26: 6 | D26: 34 | E26: ACT | F26: 0.0063 | G26: 0.0182 | J26: 17 | L26: 0.009 | M26: 0.0111 | N26: 1 | O26: 0.92 | P26: 0.81 | Q26: 1.26 | R26: 2.28 | S26: =IFERROR(K26*$I$5,0) | T26: =IFERROR(K26*$J$5,0) | U26: =IFERROR(K26*$K$5,0) | V26: =IFERROR(L26*$G$5,0) | W26: =IFERROR(V26*N26,0) | X26: =IFERROR(L26*O26/SUMPRODUCT($L$17:$L$41,$O$17:$O$41)*$I$5,0) | Y26: =IFERROR(X26/W26,0) | Z26: =IFERROR(L26*Q26/SUMPRODUCT($L$17:$L$41,$Q$17:$Q$41)*$J$5,0) | AA26: =IFERROR(M26*$H$5,0) | AB26: =IFERROR(M26*P26/SUMPRODUCT($M$17:$M$41,$P$17:$P$41)*$L$5,0) | AC26: =IFERROR(AB26/AA26,0) | AD26: =IFERROR(M26*R26/SUMPRODUCT($M$17:$M$41,$R$17:$R$41)*$M$5,0) | AE26: =X26*Settings!$B$7+Z26*Settings!$B$8+W26*Settings!$B$9+AB26*Settings!$B$10+AD26*Settings!$B$11+S26*Settings!$B$12+T26*Settings!$B$13+U26*Settings!$B$14
A27: RB | B27: Other RBs | S27: =IFERROR(K27*$I$5,0) | T27: =IFERROR(K27*$J$5,0) | U27: =IFERROR(K27*$K$5,0) | V27: =IFERROR(L27*$G$5,0) | W27: =IFERROR(V27*N27,0) | X27: =IFERROR(L27*O27/SUMPRODUCT($L$17:$L$41,$O$17:$O$41)*$I$5,0) | Y27: =IFERROR(X27/W27,0) | Z27: =IFERROR(L27*Q27/SUMPRODUCT($L$17:$L$41,$Q$17:$Q$41)*$J$5,0) | AA27: =IFERROR(M27*$H$5,0) | AB27: =IFERROR(M27*P27/SUMPRODUCT($M$17:$M$41,$P$17:$P$41)*$L$5,0) | AC27: =IFERROR(AB27/AA27,0) | AD27: =IFERROR(M27*R27/SUMPRODUCT($M$17:$M$41,$R$17:$R$41)*$M$5,0) | AE27: =X27*Settings!$B$7+Z27*Settings!$B$8+W27*Settings!$B$9+AB27*Settings!$B$10+AD27*Settings!$B$11+S27*Settings!$B$12+T27*Settings!$B$13+U27*Settings!$B$14
A28: WR | B28: Jerry Jeudy | C28: 1 | D28: 27 | E28: ACT | F28: 0.1824 | G28: 0.2287 | H28: 0.2031 | I28: 0.0024 | J28: 17 | L28: 0.2006 | M28: 0.015 | N28: 0.5453 | O28: 1.1 | P28: 1.01 | Q28: 0.94 | R28: 1 | S28: =IFERROR(K28*$I$5,0) | T28: =IFERROR(K28*$J$5,0) | U28: =IFERROR(K28*$K$5,0) | V28: =IFERROR(L28*$G$5,0) | W28: =IFERROR(V28*N28,0) | X28: =IFERROR(L28*O28/SUMPRODUCT($L$17:$L$41,$O$17:$O$41)*$I$5,0) | Y28: =IFERROR(X28/W28,0) | Z28: =IFERROR(L28*Q28/SUMPRODUCT($L$17:$L$41,$Q$17:$Q$41)*$J$5,0) | AA28: =IFERROR(M28*$H$5,0) | AB28: =IFERROR(M28*P28/SUMPRODUCT($M$17:$M$41,$P$17:$P$41)*$L$5,0) | AC28: =IFERROR(AB28/AA28,0) | AD28: =IFERROR(M28*R28/SUMPRODUCT($M$17:$M$41,$R$17:$R$41)*$M$5,0) | AE28: =X28*Settings!$B$7+Z28*Settings!$B$8+W28*Settings!$B$9+AB28*Settings!$B$10+AD28*Settings!$B$11+S28*Settings!$B$12+T28*Settings!$B$13+U28*Settings!$B$14
A29: WR | B29: KC Concepcion | C29: 2 | D29: 21 | E29: role avg (rookie) | J29: 17 | L29: 0.1339 | M29: 0.0071 | N29: 0.65 | O29: 1 | P29: 1 | Q29: 1 | R29: 1 | S29: =IFERROR(K29*$I$5,0) | T29: =IFERROR(K29*$J$5,0) | U29: =IFERROR(K29*$K$5,0) | V29: =IFERROR(L29*$G$5,0) | W29: =IFERROR(V29*N29,0) | X29: =IFERROR(L29*O29/SUMPRODUCT($L$17:$L$41,$O$17:$O$41)*$I$5,0) | Y29: =IFERROR(X29/W29,0) | Z29: =IFERROR(L29*Q29/SUMPRODUCT($L$17:$L$41,$Q$17:$Q$41)*$J$5,0) | AA29: =IFERROR(M29*$H$5,0) | AB29: =IFERROR(M29*P29/SUMPRODUCT($M$17:$M$41,$P$17:$P$41)*$L$5,0) | AC29: =IFERROR(AB29/AA29,0) | AD29: =IFERROR(M29*R29/SUMPRODUCT($M$17:$M$41,$R$17:$R$41)*$M$5,0) | AE29: =X29*Settings!$B$7+Z29*Settings!$B$8+W29*Settings!$B$9+AB29*Settings!$B$10+AD29*Settings!$B$11+S29*Settings!$B$12+T29*Settings!$B$13+U29*Settings!$B$14
A30: WR | B30: Denzel Boston | C30: 3 | D30: 22 | E30: role avg (rookie) | J30: 17 | L30: 0.0809 | M30: 0.003 | N30: 0.65 | O30: 1 | P30: 1 | Q30: 1 | R30: 1 | S30: =IFERROR(K30*$I$5,0) | T30: =IFERROR(K30*$J$5,0) | U30: =IFERROR(K30*$K$5,0) | V30: =IFERROR(L30*$G$5,0) | W30: =IFERROR(V30*N30,0) | X30: =IFERROR(L30*O30/SUMPRODUCT($L$17:$L$41,$O$17:$O$41)*$I$5,0) | Y30: =IFERROR(X30/W30,0) | Z30: =IFERROR(L30*Q30/SUMPRODUCT($L$17:$L$41,$Q$17:$Q$41)*$J$5,0) | AA30: =IFERROR(M30*$H$5,0) | AB30: =IFERROR(M30*P30/SUMPRODUCT($M$17:$M$41,$P$17:$P$41)*$L$5,0) | AC30: =IFERROR(AB30/AA30,0) | AD30: =IFERROR(M30*R30/SUMPRODUCT($M$17:$M$41,$R$17:$R$41)*$M$5,0) | AE30: =X30*Settings!$B$7+Z30*Settings!$B$8+W30*Settings!$B$9+AB30*Settings!$B$10+AD30*Settings!$B$11+S30*Settings!$B$12+T30*Settings!$B$13+U30*Settings!$B$14
A31: WR | B31: Cedric Tillman | C31: 4 | D31: 26 | E31: ACT | F31: 0.0737 | G31: 0.0773 | H31: 0.0747 | J31: 17 | L31: 0.061 | M31: 0.0023 | N31: 0.5388 | O31: 1.04 | P31: 0.96 | Q31: 1.14 | R31: 1 | S31: =IFERROR(K31*$I$5,0) | T31: =IFERROR(K31*$J$5,0) | U31: =IFERROR(K31*$K$5,0) | V31: =IFERROR(L31*$G$5,0) | W31: =IFERROR(V31*N31,0) | X31: =IFERROR(L31*O31/SUMPRODUCT($L$17:$L$41,$O$17:$O$41)*$I$5,0) | Y31: =IFERROR(X31/W31,0) | Z31: =IFERROR(L31*Q31/SUMPRODUCT($L$17:$L$41,$Q$17:$Q$41)*$J$5,0) | AA31: =IFERROR(M31*$H$5,0) | AB31: =IFERROR(M31*P31/SUMPRODUCT($M$17:$M$41,$P$17:$P$41)*$L$5,0) | AC31: =IFERROR(AB31/AA31,0) | AD31: =IFERROR(M31*R31/SUMPRODUCT($M$17:$M$41,$R$17:$R$41)*$M$5,0) | AE31: =X31*Settings!$B$7+Z31*Settings!$B$8+W31*Settings!$B$9+AB31*Settings!$B$10+AD31*Settings!$B$11+S31*Settings!$B$12+T31*Settings!$B$13+U31*Settings!$B$14
A32: WR | B32: Isaiah Bond | C32: 5 | D32: 22 | E32: ACT | H32: 0.0843 | I32: 0.012 | J32: 17 | L32: 0.057 | M32: 0.0036 | N32: 0.4091 | O32: 1.19 | P32: 1.09 | Q32: 1.1 | R32: 1 | S32: =IFERROR(K32*$I$5,0) | T32: =IFERROR(K32*$J$5,0) | U32: =IFERROR(K32*$K$5,0) | V32: =IFERROR(L32*$G$5,0) | W32: =IFERROR(V32*N32,0) | X32: =IFERROR(L32*O32/SUMPRODUCT($L$17:$L$41,$O$17:$O$41)*$I$5,0) | Y32: =IFERROR(X32/W32,0) | Z32: =IFERROR(L32*Q32/SUMPRODUCT($L$17:$L$41,$Q$17:$Q$41)*$J$5,0) | AA32: =IFERROR(M32*$H$5,0) | AB32: =IFERROR(M32*P32/SUMPRODUCT($M$17:$M$41,$P$17:$P$41)*$L$5,0) | AC32: =IFERROR(AB32/AA32,0) | AD32: =IFERROR(M32*R32/SUMPRODUCT($M$17:$M$41,$R$17:$R$41)*$M$5,0) | AE32: =X32*Settings!$B$7+Z32*Settings!$B$8+W32*Settings!$B$9+AB32*Settings!$B$10+AD32*Settings!$B$11+S32*Settings!$B$12+T32*Settings!$B$13+U32*Settings!$B$14
A33: WR | B33: Malachi Corley | C33: 6 | D33: 24 | E33: ACT | G33: 0.0102 | H33: 0.0268 | I33: 0.0312 | J33: 17 | L33: 0.0177 | M33: 0.0053 | N33: 0.7019 | O33: 0.92 | P33: 1.5 | Q33: 1.01 | R33: 1.61 | S33: =IFERROR(K33*$I$5,0) | T33: =IFERROR(K33*$J$5,0) | U33: =IFERROR(K33*$K$5,0) | V33: =IFERROR(L33*$G$5,0) | W33: =IFERROR(V33*N33,0) | X33: =IFERROR(L33*O33/SUMPRODUCT($L$17:$L$41,$O$17:$O$41)*$I$5,0) | Y33: =IFERROR(X33/W33,0) | Z33: =IFERROR(L33*Q33/SUMPRODUCT($L$17:$L$41,$Q$17:$Q$41)*$J$5,0) | AA33: =IFERROR(M33*$H$5,0) | AB33: =IFERROR(M33*P33/SUMPRODUCT($M$17:$M$41,$P$17:$P$41)*$L$5,0) | AC33: =IFERROR(AB33/AA33,0) | AD33: =IFERROR(M33*R33/SUMPRODUCT($M$17:$M$41,$R$17:$R$41)*$M$5,0) | AE33: =X33*Settings!$B$7+Z33*Settings!$B$8+W33*Settings!$B$9+AB33*Settings!$B$10+AD33*Settings!$B$11+S33*Settings!$B$12+T33*Settings!$B$13+U33*Settings!$B$14
A34: WR | B34: Tylan Wallace | C34: 7 | D34: 27 | E34: role avg (from BAL) | F34: 0.0042 | G34: 0.0263 | H34: 0.0197 | J34: 17 | L34: 0.0054 | M34: 0.0023 | N34: 0.6486 | O34: 1.02 | P34: 1 | Q34: 2.15 | R34: 1 | S34: =IFERROR(K34*$I$5,0) | T34: =IFERROR(K34*$J$5,0) | U34: =IFERROR(K34*$K$5,0) | V34: =IFERROR(L34*$G$5,0) | W34: =IFERROR(V34*N34,0) | X34: =IFERROR(L34*O34/SUMPRODUCT($L$17:$L$41,$O$17:$O$41)*$I$5,0) | Y34: =IFERROR(X34/W34,0) | Z34: =IFERROR(L34*Q34/SUMPRODUCT($L$17:$L$41,$Q$17:$Q$41)*$J$5,0) | AA34: =IFERROR(M34*$H$5,0) | AB34: =IFERROR(M34*P34/SUMPRODUCT($M$17:$M$41,$P$17:$P$41)*$L$5,0) | AC34: =IFERROR(AB34/AA34,0) | AD34: =IFERROR(M34*R34/SUMPRODUCT($M$17:$M$41,$R$17:$R$41)*$M$5,0) | AE34: =X34*Settings!$B$7+Z34*Settings!$B$8+W34*Settings!$B$9+AB34*Settings!$B$10+AD34*Settings!$B$11+S34*Settings!$B$12+T34*Settings!$B$13+U34*Settings!$B$14
A35: WR | B35: Jamari Thrash | C35: 8 | D35: 25 | E35: ACT | G35: 0.011 | H35: 0.0287 | J35: 17 | L35: 0.0144 | M35: 0.0008 | N35: 0.5774 | O35: 0.97 | P35: 1 | Q35: 1.03 | R35: 1 | S35: =IFERROR(K35*$I$5,0) | T35: =IFERROR(K35*$J$5,0) | U35: =IFERROR(K35*$K$5,0) | V35: =IFERROR(L35*$G$5,0) | W35: =IFERROR(V35*N35,0) | X35: =IFERROR(L35*O35/SUMPRODUCT($L$17:$L$41,$O$17:$O$41)*$I$5,0) | Y35: =IFERROR(X35/W35,0) | Z35: =IFERROR(L35*Q35/SUMPRODUCT($L$17:$L$41,$Q$17:$Q$41)*$J$5,0) | AA35: =IFERROR(M35*$H$5,0) | AB35: =IFERROR(M35*P35/SUMPRODUCT($M$17:$M$41,$P$17:$P$41)*$L$5,0) | AC35: =IFERROR(AB35/AA35,0) | AD35: =IFERROR(M35*R35/SUMPRODUCT($M$17:$M$41,$R$17:$R$41)*$M$5,0) | AE35: =X35*Settings!$B$7+Z35*Settings!$B$8+W35*Settings!$B$9+AB35*Settings!$B$10+AD35*Settings!$B$11+S35*Settings!$B$12+T35*Settings!$B$13+U35*Settings!$B$14
A36: WR | B36: Other WRs | S36: =IFERROR(K36*$I$5,0) | T36: =IFERROR(K36*$J$5,0) | U36: =IFERROR(K36*$K$5,0) | V36: =IFERROR(L36*$G$5,0) | W36: =IFERROR(V36*N36,0) | X36: =IFERROR(L36*O36/SUMPRODUCT($L$17:$L$41,$O$17:$O$41)*$I$5,0) | Y36: =IFERROR(X36/W36,0) | Z36: =IFERROR(L36*Q36/SUMPRODUCT($L$17:$L$41,$Q$17:$Q$41)*$J$5,0) | AA36: =IFERROR(M36*$H$5,0) | AB36: =IFERROR(M36*P36/SUMPRODUCT($M$17:$M$41,$P$17:$P$41)*$L$5,0) | AC36: =IFERROR(AB36/AA36,0) | AD36: =IFERROR(M36*R36/SUMPRODUCT($M$17:$M$41,$R$17:$R$41)*$M$5,0) | AE36: =X36*Settings!$B$7+Z36*Settings!$B$8+W36*Settings!$B$9+AB36*Settings!$B$10+AD36*Settings!$B$11+S36*Settings!$B$12+T36*Settings!$B$13+U36*Settings!$B$14
A37: TE | B37: Harold Fannin | C37: 1 | D37: 22 | E37: ACT | H37: 0.205 | I37: 0.0168 | J37: 17 | L37: 0.1798 | M37: 0.013 | N37: 0.6729 | O37: 1.11 | P37: 0.86 | Q37: 1.02 | R37: 1.34 | S37: =IFERROR(K37*$I$5,0) | T37: =IFERROR(K37*$J$5,0) | U37: =IFERROR(K37*$K$5,0) | V37: =IFERROR(L37*$G$5,0) | W37: =IFERROR(V37*N37,0) | X37: =IFERROR(L37*O37/SUMPRODUCT($L$17:$L$41,$O$17:$O$41)*$I$5,0) | Y37: =IFERROR(X37/W37,0) | Z37: =IFERROR(L37*Q37/SUMPRODUCT($L$17:$L$41,$Q$17:$Q$41)*$J$5,0) | AA37: =IFERROR(M37*$H$5,0) | AB37: =IFERROR(M37*P37/SUMPRODUCT($M$17:$M$41,$P$17:$P$41)*$L$5,0) | AC37: =IFERROR(AB37/AA37,0) | AD37: =IFERROR(M37*R37/SUMPRODUCT($M$17:$M$41,$R$17:$R$41)*$M$5,0) | AE37: =X37*Settings!$B$7+Z37*Settings!$B$8+W37*Settings!$B$9+AB37*Settings!$B$10+AD37*Settings!$B$11+S37*Settings!$B$12+T37*Settings!$B$13+U37*Settings!$B$14
A38: TE | B38: Joe Royer | C38: 2 | D38: 24 | E38: role avg (rookie) | J38: 17 | L38: 0.0575 | M38: 0.0023 | N38: 0.65 | O38: 1 | P38: 1 | Q38: 1 | R38: 1 | S38: =IFERROR(K38*$I$5,0) | T38: =IFERROR(K38*$J$5,0) | U38: =IFERROR(K38*$K$5,0) | V38: =IFERROR(L38*$G$5,0) | W38: =IFERROR(V38*N38,0) | X38: =IFERROR(L38*O38/SUMPRODUCT($L$17:$L$41,$O$17:$O$41)*$I$5,0) | Y38: =IFERROR(X38/W38,0) | Z38: =IFERROR(L38*Q38/SUMPRODUCT($L$17:$L$41,$Q$17:$Q$41)*$J$5,0) | AA38: =IFERROR(M38*$H$5,0) | AB38: =IFERROR(M38*P38/SUMPRODUCT($M$17:$M$41,$P$17:$P$41)*$L$5,0) | AC38: =IFERROR(AB38/AA38,0) | AD38: =IFERROR(M38*R38/SUMPRODUCT($M$17:$M$41,$R$17:$R$41)*$M$5,0) | AE38: =X38*Settings!$B$7+Z38*Settings!$B$8+W38*Settings!$B$9+AB38*Settings!$B$10+AD38*Settings!$B$11+S38*Settings!$B$12+T38*Settings!$B$13+U38*Settings!$B$14
A39: TE | B39: Blake Whiteheart | C39: 3 | D39: 26 | E39: ACT | G39: 0.0142 | H39: 0.0115 | J39: 17 | L39: 0.0141 | M39: 0.0009 | N39: 0.4266 | O39: 0.83 | P39: 1 | Q39: 1.27 | R39: 1 | S39: =IFERROR(K39*$I$5,0) | T39: =IFERROR(K39*$J$5,0) | U39: =IFERROR(K39*$K$5,0) | V39: =IFERROR(L39*$G$5,0) | W39: =IFERROR(V39*N39,0) | X39: =IFERROR(L39*O39/SUMPRODUCT($L$17:$L$41,$O$17:$O$41)*$I$5,0) | Y39: =IFERROR(X39/W39,0) | Z39: =IFERROR(L39*Q39/SUMPRODUCT($L$17:$L$41,$Q$17:$Q$41)*$J$5,0) | AA39: =IFERROR(M39*$H$5,0) | AB39: =IFERROR(M39*P39/SUMPRODUCT($M$17:$M$41,$P$17:$P$41)*$L$5,0) | AC39: =IFERROR(AB39/AA39,0) | AD39: =IFERROR(M39*R39/SUMPRODUCT($M$17:$M$41,$R$17:$R$41)*$M$5,0) | AE39: =X39*Settings!$B$7+Z39*Settings!$B$8+W39*Settings!$B$9+AB39*Settings!$B$10+AD39*Settings!$B$11+S39*Settings!$B$12+T39*Settings!$B$13+U39*Settings!$B$14
A40: TE | B40: Jack Stoll | C40: 4 | D40: 28 | E40: role avg (from NO) | F40: 0.0152 | G40: 0.0072 | H40: 0.0195 | J40: 17 | L40: 0.006 | M40: 0.0023 | N40: 0.5858 | O40: 0.86 | P40: 1 | Q40: 1.5 | R40: 1 | S40: =IFERROR(K40*$I$5,0) | T40: =IFERROR(K40*$J$5,0) | U40: =IFERROR(K40*$K$5,0) | V40: =IFERROR(L40*$G$5,0) | W40: =IFERROR(V40*N40,0) | X40: =IFERROR(L40*O40/SUMPRODUCT($L$17:$L$41,$O$17:$O$41)*$I$5,0) | Y40: =IFERROR(X40/W40,0) | Z40: =IFERROR(L40*Q40/SUMPRODUCT($L$17:$L$41,$Q$17:$Q$41)*$J$5,0) | AA40: =IFERROR(M40*$H$5,0) | AB40: =IFERROR(M40*P40/SUMPRODUCT($M$17:$M$41,$P$17:$P$41)*$L$5,0) | AC40: =IFERROR(AB40/AA40,0) | AD40: =IFERROR(M40*R40/SUMPRODUCT($M$17:$M$41,$R$17:$R$41)*$M$5,0) | AE40: =X40*Settings!$B$7+Z40*Settings!$B$8+W40*Settings!$B$9+AB40*Settings!$B$10+AD40*Settings!$B$11+S40*Settings!$B$12+T40*Settings!$B$13+U40*Settings!$B$14
A41: TE | B41: Other TEs | S41: =IFERROR(K41*$I$5,0) | T41: =IFERROR(K41*$J$5,0) | U41: =IFERROR(K41*$K$5,0) | V41: =IFERROR(L41*$G$5,0) | W41: =IFERROR(V41*N41,0) | X41: =IFERROR(L41*O41/SUMPRODUCT($L$17:$L$41,$O$17:$O$41)*$I$5,0) | Y41: =IFERROR(X41/W41,0) | Z41: =IFERROR(L41*Q41/SUMPRODUCT($L$17:$L$41,$Q$17:$Q$41)*$J$5,0) | AA41: =IFERROR(M41*$H$5,0) | AB41: =IFERROR(M41*P41/SUMPRODUCT($M$17:$M$41,$P$17:$P$41)*$L$5,0) | AC41: =IFERROR(AB41/AA41,0) | AD41: =IFERROR(M41*R41/SUMPRODUCT($M$17:$M$41,$R$17:$R$41)*$M$5,0) | AE41: =X41*Settings!$B$7+Z41*Settings!$B$8+W41*Settings!$B$9+AB41*Settings!$B$10+AD41*Settings!$B$11+S41*Settings!$B$12+T41*Settings!$B$13+U41*Settings!$B$14
B43: SHARE TOTALS - must equal 100% | E43: each column is a share of this team's season total - it must add to 100% | K43: =SUM(K17:K41) | L43: =SUM(L17:L41) | M43: =SUM(M17:M41) | S43: =SUM(S17:S41) | T43: =SUM(T17:T41) | U43: =SUM(U17:U41) | V43: =SUM(V17:V41) | W43: =SUM(W17:W41) | X43: =SUM(X17:X41) | Y43: =SUM(Y17:Y41) | Z43: =SUM(Z17:Z41) | ... AE43: =SUM(AE17:AE41)
B45: Green = balanced. Red = your shares don't add to 100%; player totals won't match the team totals until they do.

Sheet DAL
A1: DAL - 2026 projections
A3: TEAM TOTALS | C3: blue = edit; everything below divides these up
B4: Games | C4: Plays/G | D4: Plays | E4: Pass Rate | F4: Pass Att | G4: Targets | H4: Rush Att | I4: Pass Yds | J4: Pass TD | K4: Int | L4: Rush Yds | M4: Rush TD
B5: 17 | C5: 64.2 | D5: =C5*B5 | E5: 0.5845 | F5: 601 | G5: =ROUND(F5*Settings!$B$4,0) | H5: 453 | I5: 4320 | J5: 28 | K5: 12 | L5: 1957 | M5: 14
A7: LAST 3 YEARS | B7: Season | C7: Plays | D7: Plays/G | E7: Pass Rate | F7: Pass Att | G7: Rush Att | H7: Pass Yds | I7: Rush Yds | J7: Pass TD | K7: Rush TD | L7: Y/A | M7: Y/C
B8: 2023 | C8: 1122 | D8: 66 | E8: 0.5829 | F8: 614 | G8: 468 | H8: 4660 | I8: 1920 | J8: 36 | K8: 14 | L8: 7.5896 | M8: 4.1026
B9: 2024 | C9: 1104 | D9: 64.9412 | E9: 0.6114 | F9: 637 | G9: 429 | H9: 4092 | I9: 1705 | J9: 23 | K9: 6 | L9: 6.4239 | M9: 3.9744
B10: 2025 | C10: 1120 | D10: 65.8824 | E10: 0.5848 | F10: 624 | G10: 465 | H10: 4735 | I10: 2136 | J10: 31 | K10: 18 | L10: 7.5881 | M10: 4.5935
A12: OUT | B12: 7% of targets and 4% of carries left. Share is team-relative - it does NOT follow the player. | H12: Jalen Tolbert (6t/0r -> MIA), Miles Sanders (1t/4r -> NOT ON ANY ROSTER)
A13: IN | B13: 2 new: Tyler Johnson (WR, from NYJ - had 4% there), Marquez Valdes-Scantling (WR, from SF - had 1% there)
A14: STAFF | B14: no coaching change recorded - add one in manual/coaching_changes.csv
A16: Pos | B16: Player | C16: Dep | D16: Age | E16: Status | F16: 2023 Tgt% | G16: 2024 Tgt% | H16: 2025 Tgt% | I16: 2025 Rush% | J16: Games | K16: Pass % | L16: Tgt % | M16: Rush % | N16: Catch % | O16: Rec Eff x | P16: Rush Eff x | Q16: RZ Tgt x | R16: RZ Rush x | S16: Pass Yds | T16: Pass TD | U16: Int | V16: Targets | W16: Rec | X16: Rec Yds | Y16: Yds/Rec | Z16: Rec TD | AA16: Rush Att | AB16: Rush Yds | AC16: Yds/Car | AD16: Rush TD | AE16: Half PPR
A17: QB | B17: Dak Prescott | C17: 1 | D17: 33 | E17: ACT | I17: 0.0824 | J17: 17 | K17: 0.92 | L17: 0.0007 | M17: 0.0773 | O17: 1 | P17: 1.07 | Q17: 1 | R17: 1.29 | S17: =IFERROR(K17*$I$5,0) | T17: =IFERROR(K17*$J$5,0) | U17: =IFERROR(K17*$K$5,0) | V17: =IFERROR(L17*$G$5,0) | W17: =IFERROR(V17*N17,0) | X17: =IFERROR(L17*O17/SUMPRODUCT($L$17:$L$41,$O$17:$O$41)*$I$5,0) | Y17: =IFERROR(X17/W17,0) | Z17: =IFERROR(L17*Q17/SUMPRODUCT($L$17:$L$41,$Q$17:$Q$41)*$J$5,0) | AA17: =IFERROR(M17*$H$5,0) | AB17: =IFERROR(M17*P17/SUMPRODUCT($M$17:$M$41,$P$17:$P$41)*$L$5,0) | AC17: =IFERROR(AB17/AA17,0) | AD17: =IFERROR(M17*R17/SUMPRODUCT($M$17:$M$41,$R$17:$R$41)*$M$5,0) | AE17: =X17*Settings!$B$7+Z17*Settings!$B$8+W17*Settings!$B$9+AB17*Settings!$B$10+AD17*Settings!$B$11+S17*Settings!$B$12+T17*Settings!$B$13+U17*Settings!$B$14
A18: QB | B18: Joe Milton | C18: 2 | D18: 26 | E18: ACT | I18: 0.0111 | J18: 17 | K18: 0.068 | L18: 0.0007 | M18: 0.013 | O18: 1 | P18: 1.19 | Q18: 1 | R18: 1.03 | S18: =IFERROR(K18*$I$5,0) | T18: =IFERROR(K18*$J$5,0) | U18: =IFERROR(K18*$K$5,0) | V18: =IFERROR(L18*$G$5,0) | W18: =IFERROR(V18*N18,0) | X18: =IFERROR(L18*O18/SUMPRODUCT($L$17:$L$41,$O$17:$O$41)*$I$5,0) | Y18: =IFERROR(X18/W18,0) | Z18: =IFERROR(L18*Q18/SUMPRODUCT($L$17:$L$41,$Q$17:$Q$41)*$J$5,0) | AA18: =IFERROR(M18*$H$5,0) | AB18: =IFERROR(M18*P18/SUMPRODUCT($M$17:$M$41,$P$17:$P$41)*$L$5,0) | AC18: =IFERROR(AB18/AA18,0) | AD18: =IFERROR(M18*R18/SUMPRODUCT($M$17:$M$41,$R$17:$R$41)*$M$5,0) | AE18: =X18*Settings!$B$7+Z18*Settings!$B$8+W18*Settings!$B$9+AB18*Settings!$B$10+AD18*Settings!$B$11+S18*Settings!$B$12+T18*Settings!$B$13+U18*Settings!$B$14
A19: QB | B19: Sam Howell | C19: 3 | D19: 25 | E19: ACT | F19: 0.0017 | J19: 17 | K19: 0.012 | L19: 0.0017 | M19: 0.0695 | O19: 0.98 | P19: 1.13 | Q19: 1.85 | R19: 1.67 | S19: =IFERROR(K19*$I$5,0) | T19: =IFERROR(K19*$J$5,0) | U19: =IFERROR(K19*$K$5,0) | V19: =IFERROR(L19*$G$5,0) | W19: =IFERROR(V19*N19,0) | X19: =IFERROR(L19*O19/SUMPRODUCT($L$17:$L$41,$O$17:$O$41)*$I$5,0) | Y19: =IFERROR(X19/W19,0) | Z19: =IFERROR(L19*Q19/SUMPRODUCT($L$17:$L$41,$Q$17:$Q$41)*$J$5,0) | AA19: =IFERROR(M19*$H$5,0) | AB19: =IFERROR(M19*P19/SUMPRODUCT($M$17:$M$41,$P$17:$P$41)*$L$5,0) | AC19: =IFERROR(AB19/AA19,0) | AD19: =IFERROR(M19*R19/SUMPRODUCT($M$17:$M$41,$R$17:$R$41)*$M$5,0) | AE19: =X19*Settings!$B$7+Z19*Settings!$B$8+W19*Settings!$B$9+AB19*Settings!$B$10+AD19*Settings!$B$11+S19*Settings!$B$12+T19*Settings!$B$13+U19*Settings!$B$14
A20: QB | B20: Other QBs | S20: =IFERROR(K20*$I$5,0) | T20: =IFERROR(K20*$J$5,0) | U20: =IFERROR(K20*$K$5,0) | V20: =IFERROR(L20*$G$5,0) | W20: =IFERROR(V20*N20,0) | X20: =IFERROR(L20*O20/SUMPRODUCT($L$17:$L$41,$O$17:$O$41)*$I$5,0) | Y20: =IFERROR(X20/W20,0) | Z20: =IFERROR(L20*Q20/SUMPRODUCT($L$17:$L$41,$Q$17:$Q$41)*$J$5,0) | AA20: =IFERROR(M20*$H$5,0) | AB20: =IFERROR(M20*P20/SUMPRODUCT($M$17:$M$41,$P$17:$P$41)*$L$5,0) | AC20: =IFERROR(AB20/AA20,0) | AD20: =IFERROR(M20*R20/SUMPRODUCT($M$17:$M$41,$R$17:$R$41)*$M$5,0) | AE20: =X20*Settings!$B$7+Z20*Settings!$B$8+W20*Settings!$B$9+AB20*Settings!$B$10+AD20*Settings!$B$11+S20*Settings!$B$12+T20*Settings!$B$13+U20*Settings!$B$14
A21: RB | B21: Javonte Williams | C21: 1 | D21: 26 | E21: ACT | F21: 0.1216 | G21: 0.1275 | H21: 0.084 | I21: 0.5612 | J21: 17 | L21: 0.094 | M21: 0.488 | N21: 0.7283 | O21: 0.62 | P21: 0.94 | Q21: 0.94 | R21: 1 | S21: =IFERROR(K21*$I$5,0) | T21: =IFERROR(K21*$J$5,0) | U21: =IFERROR(K21*$K$5,0) | V21: =IFERROR(L21*$G$5,0) | W21: =IFERROR(V21*N21,0) | X21: =IFERROR(L21*O21/SUMPRODUCT($L$17:$L$41,$O$17:$O$41)*$I$5,0) | Y21: =IFERROR(X21/W21,0) | Z21: =IFERROR(L21*Q21/SUMPRODUCT($L$17:$L$41,$Q$17:$Q$41)*$J$5,0) | AA21: =IFERROR(M21*$H$5,0) | AB21: =IFERROR(M21*P21/SUMPRODUCT($M$17:$M$41,$P$17:$P$41)*$L$5,0) | AC21: =IFERROR(AB21/AA21,0) | AD21: =IFERROR(M21*R21/SUMPRODUCT($M$17:$M$41,$R$17:$R$41)*$M$5,0) | AE21: =X21*Settings!$B$7+Z21*Settings!$B$8+W21*Settings!$B$9+AB21*Settings!$B$10+AD21*Settings!$B$11+S21*Settings!$B$12+T21*Settings!$B$13+U21*Settings!$B$14
A22: RB | B22: Malik Davis | C22: 2 | D22: 27 | E22: ACT | H22: 0.0082 | I22: 0.1158 | J22: 17 | L22: 0.0183 | M22: 0.1434 | N22: 0.4 | O22: 0.88 | P22: 1.01 | Q22: 1 | R22: 0.82 | S22: =IFERROR(K22*$I$5,0) | T22: =IFERROR(K22*$J$5,0) | U22: =IFERROR(K22*$K$5,0) | V22: =IFERROR(L22*$G$5,0) | W22: =IFERROR(V22*N22,0) | X22: =IFERROR(L22*O22/SUMPRODUCT($L$17:$L$41,$O$17:$O$41)*$I$5,0) | Y22: =IFERROR(X22/W22,0) | Z22: =IFERROR(L22*Q22/SUMPRODUCT($L$17:$L$41,$Q$17:$Q$41)*$J$5,0) | AA22: =IFERROR(M22*$H$5,0) | AB22: =IFERROR(M22*P22/SUMPRODUCT($M$17:$M$41,$P$17:$P$41)*$L$5,0) | AC22: =IFERROR(AB22/AA22,0) | AD22: =IFERROR(M22*R22/SUMPRODUCT($M$17:$M$41,$R$17:$R$41)*$M$5,0) | AE22: =X22*Settings!$B$7+Z22*Settings!$B$8+W22*Settings!$B$9+AB22*Settings!$B$10+AD22*Settings!$B$11+S22*Settings!$B$12+T22*Settings!$B$13+U22*Settings!$B$14
A23: RB | B23: Jaydon Blue | C23: 3 | D23: 22 | E23: ACT | H23: 0.0016 | I23: 0.0846 | J23: 17 | L23: 0.0074 | M23: 0.0755 | N23: 1 | O23: 0.98 | P23: 0.81 | Q23: 1 | R23: 1.02 | S23: =IFERROR(K23*$I$5,0) | T23: =IFERROR(K23*$J$5,0) | U23: =IFERROR(K23*$K$5,0) | V23: =IFERROR(L23*$G$5,0) | W23: =IFERROR(V23*N23,0) | X23: =IFERROR(L23*O23/SUMPRODUCT($L$17:$L$41,$O$17:$O$41)*$I$5,0) | Y23: =IFERROR(X23/W23,0) | Z23: =IFERROR(L23*Q23/SUMPRODUCT($L$17:$L$41,$Q$17:$Q$41)*$J$5,0) | AA23: =IFERROR(M23*$H$5,0) | AB23: =IFERROR(M23*P23/SUMPRODUCT($M$17:$M$41,$P$17:$P$41)*$L$5,0) | AC23: =IFERROR(AB23/AA23,0) | AD23: =IFERROR(M23*R23/SUMPRODUCT($M$17:$M$41,$R$17:$R$41)*$M$5,0) | AE23: =X23*Settings!$B$7+Z23*Settings!$B$8+W23*Settings!$B$9+AB23*Settings!$B$10+AD23*Settings!$B$11+S23*Settings!$B$12+T23*Settings!$B$13+U23*Settings!$B$14
A24: RB | B24: Phil Mafah | C24: 4 | D24: 23 | E24: ACT | H24: 0.0033 | I24: 0.0111 | J24: 17 | L24: 0.0047 | M24: 0.0229 | N24: 1 | O24: 0.97 | P24: 0.95 | Q24: 1 | R24: 0.94 | S24: =IFERROR(K24*$I$5,0) | T24: =IFERROR(K24*$J$5,0) | U24: =IFERROR(K24*$K$5,0) | V24: =IFERROR(L24*$G$5,0) | W24: =IFERROR(V24*N24,0) | X24: =IFERROR(L24*O24/SUMPRODUCT($L$17:$L$41,$O$17:$O$41)*$I$5,0) | Y24: =IFERROR(X24/W24,0) | Z24: =IFERROR(L24*Q24/SUMPRODUCT($L$17:$L$41,$Q$17:$Q$41)*$J$5,0) | AA24: =IFERROR(M24*$H$5,0) | AB24: =IFERROR(M24*P24/SUMPRODUCT($M$17:$M$41,$P$17:$P$41)*$L$5,0) | AC24: =IFERROR(AB24/AA24,0) | AD24: =IFERROR(M24*R24/SUMPRODUCT($M$17:$M$41,$R$17:$R$41)*$M$5,0) | AE24: =X24*Settings!$B$7+Z24*Settings!$B$8+W24*Settings!$B$9+AB24*Settings!$B$10+AD24*Settings!$B$11+S24*Settings!$B$12+T24*Settings!$B$13+U24*Settings!$B$14
A25: RB | B25: Israel Abanikanda | C25: 5 | D25: 23 | E25: ACT | F25: 0.0195 | J25: 17 | L25: 0.0122 | M25: 0.0415 | N25: 0.6364 | O25: 0.88 | P25: 0.86 | Q25: 1 | R25: 1 | S25: =IFERROR(K25*$I$5,0) | T25: =IFERROR(K25*$J$5,0) | U25: =IFERROR(K25*$K$5,0) | V25: =IFERROR(L25*$G$5,0) | W25: =IFERROR(V25*N25,0) | X25: =IFERROR(L25*O25/SUMPRODUCT($L$17:$L$41,$O$17:$O$41)*$I$5,0) | Y25: =IFERROR(X25/W25,0) | Z25: =IFERROR(L25*Q25/SUMPRODUCT($L$17:$L$41,$Q$17:$Q$41)*$J$5,0) | AA25: =IFERROR(M25*$H$5,0) | AB25: =IFERROR(M25*P25/SUMPRODUCT($M$17:$M$41,$P$17:$P$41)*$L$5,0) | AC25: =IFERROR(AB25/AA25,0) | AD25: =IFERROR(M25*R25/SUMPRODUCT($M$17:$M$41,$R$17:$R$41)*$M$5,0) | AE25: =X25*Settings!$B$7+Z25*Settings!$B$8+W25*Settings!$B$9+AB25*Settings!$B$10+AD25*Settings!$B$11+S25*Settings!$B$12+T25*Settings!$B$13+U25*Settings!$B$14
A26: RB | B26: Dominic Richardson | C26: 6 | D26: 25 | E26: role avg (rookie) | J26: 17 | L26: 0.0024 | M26: 0.0077 | N26: 0.75 | O26: 1 | P26: 1 | Q26: 1 | R26: 1 | S26: =IFERROR(K26*$I$5,0) | T26: =IFERROR(K26*$J$5,0) | U26: =IFERROR(K26*$K$5,0) | V26: =IFERROR(L26*$G$5,0) | W26: =IFERROR(V26*N26,0) | X26: =IFERROR(L26*O26/SUMPRODUCT($L$17:$L$41,$O$17:$O$41)*$I$5,0) | Y26: =IFERROR(X26/W26,0) | Z26: =IFERROR(L26*Q26/SUMPRODUCT($L$17:$L$41,$Q$17:$Q$41)*$J$5,0) | AA26: =IFERROR(M26*$H$5,0) | AB26: =IFERROR(M26*P26/SUMPRODUCT($M$17:$M$41,$P$17:$P$41)*$L$5,0) | AC26: =IFERROR(AB26/AA26,0) | AD26: =IFERROR(M26*R26/SUMPRODUCT($M$17:$M$41,$R$17:$R$41)*$M$5,0) | AE26: =X26*Settings!$B$7+Z26*Settings!$B$8+W26*Settings!$B$9+AB26*Settings!$B$10+AD26*Settings!$B$11+S26*Settings!$B$12+T26*Settings!$B$13+U26*Settings!$B$14
A27: RB | B27: Other RBs | S27: =IFERROR(K27*$I$5,0) | T27: =IFERROR(K27*$J$5,0) | U27: =IFERROR(K27*$K$5,0) | V27: =IFERROR(L27*$G$5,0) | W27: =IFERROR(V27*N27,0) | X27: =IFERROR(L27*O27/SUMPRODUCT($L$17:$L$41,$O$17:$O$41)*$I$5,0) | Y27: =IFERROR(X27/W27,0) | Z27: =IFERROR(L27*Q27/SUMPRODUCT($L$17:$L$41,$Q$17:$Q$41)*$J$5,0) | AA27: =IFERROR(M27*$H$5,0) | AB27: =IFERROR(M27*P27/SUMPRODUCT($M$17:$M$41,$P$17:$P$41)*$L$5,0) | AC27: =IFERROR(AB27/AA27,0) | AD27: =IFERROR(M27*R27/SUMPRODUCT($M$17:$M$41,$R$17:$R$41)*$M$5,0) | AE27: =X27*Settings!$B$7+Z27*Settings!$B$8+W27*Settings!$B$9+AB27*Settings!$B$10+AD27*Settings!$B$11+S27*Settings!$B$12+T27*Settings!$B$13+U27*Settings!$B$14
A28: WR | B28: CeeDee Lamb | C28: 1 | D28: 27 | E28: ACT | F28: 0.2992 | G28: 0.2444 | H28: 0.1928 | I28: 0.0022 | J28: 17 | L28: 0.2203 | M28: 0.0249 | N28: 0.672 | O28: 1.18 | P28: 1 | Q28: 0.97 | R28: 0.98 | S28: =IFERROR(K28*$I$5,0) | T28: =IFERROR(K28*$J$5,0) | U28: =IFERROR(K28*$K$5,0) | V28: =IFERROR(L28*$G$5,0) | W28: =IFERROR(V28*N28,0) | X28: =IFERROR(L28*O28/SUMPRODUCT($L$17:$L$41,$O$17:$O$41)*$I$5,0) | Y28: =IFERROR(X28/W28,0) | Z28: =IFERROR(L28*Q28/SUMPRODUCT($L$17:$L$41,$Q$17:$Q$41)*$J$5,0) | AA28: =IFERROR(M28*$H$5,0) | AB28: =IFERROR(M28*P28/SUMPRODUCT($M$17:$M$41,$P$17:$P$41)*$L$5,0) | AC28: =IFERROR(AB28/AA28,0) | AD28: =IFERROR(M28*R28/SUMPRODUCT($M$17:$M$41,$R$17:$R$41)*$M$5,0) | AE28: =X28*Settings!$B$7+Z28*Settings!$B$8+W28*Settings!$B$9+AB28*Settings!$B$10+AD28*Settings!$B$11+S28*Settings!$B$12+T28*Settings!$B$13+U28*Settings!$B$14
A29: WR | B29: George Pickens | C29: 2 | D29: 25 | E29: ACT | F29: 0.219 | G29: 0.2239 | H29: 0.2257 | J29: 17 | L29: 0.1805 | M29: 0.0088 | N29: 0.6333 | O29: 1.27 | P29: 0.92 | Q29: 1.12 | R29: 1 | S29: =IFERROR(K29*$I$5,0) | T29: =IFERROR(K29*$J$5,0) | U29: =IFERROR(K29*$K$5,0) | V29: =IFERROR(L29*$G$5,0) | W29: =IFERROR(V29*N29,0) | X29: =IFERROR(L29*O29/SUMPRODUCT($L$17:$L$41,$O$17:$O$41)*$I$5,0) | Y29: =IFERROR(X29/W29,0) | Z29: =IFERROR(L29*Q29/SUMPRODUCT($L$17:$L$41,$Q$17:$Q$41)*$J$5,0) | AA29: =IFERROR(M29*$H$5,0) | AB29: =IFERROR(M29*P29/SUMPRODUCT($M$17:$M$41,$P$17:$P$41)*$L$5,0) | AC29: =IFERROR(AB29/AA29,0) | AD29: =IFERROR(M29*R29/SUMPRODUCT($M$17:$M$41,$R$17:$R$41)*$M$5,0) | AE29: =X29*Settings!$B$7+Z29*Settings!$B$8+W29*Settings!$B$9+AB29*Settings!$B$10+AD29*Settings!$B$11+S29*Settings!$B$12+T29*Settings!$B$13+U29*Settings!$B$14
A30: WR | B30: Ryan Flournoy | C30: 3 | D30: 26 | E30: ACT | G30: 0.0225 | H30: 0.0923 | I30: 0.0089 | J30: 17 | L30: 0.0748 | M30: 0.0066 | N30: 0.7143 | O30: 1.06 | P30: 1.05 | Q30: 0.95 | R30: 1 | S30: =IFERROR(K30*$I$5,0) | T30: =IFERROR(K30*$J$5,0) | U30: =IFERROR(K30*$K$5,0) | V30: =IFERROR(L30*$G$5,0) | W30: =IFERROR(V30*N30,0) | X30: =IFERROR(L30*O30/SUMPRODUCT($L$17:$L$41,$O$17:$O$41)*$I$5,0) | Y30: =IFERROR(X30/W30,0) | Z30: =IFERROR(L30*Q30/SUMPRODUCT($L$17:$L$41,$Q$17:$Q$41)*$J$5,0) | AA30: =IFERROR(M30*$H$5,0) | AB30: =IFERROR(M30*P30/SUMPRODUCT($M$17:$M$41,$P$17:$P$41)*$L$5,0) | AC30: =IFERROR(AB30/AA30,0) | AD30: =IFERROR(M30*R30/SUMPRODUCT($M$17:$M$41,$R$17:$R$41)*$M$5,0) | AE30: =X30*Settings!$B$7+Z30*Settings!$B$8+W30*Settings!$B$9+AB30*Settings!$B$10+AD30*Settings!$B$11+S30*Settings!$B$12+T30*Settings!$B$13+U30*Settings!$B$14
A31: WR | B31: KaVontae Turpin | C31: 4 | D31: 30 | E31: ACT | F31: 0.0298 | G31: 0.0836 | H31: 0.0626 | I31: 0.0379 | J31: 17 | L31: 0.0571 | M31: 0.0072 | N31: 0.6522 | O31: 1.14 | P31: 1.2 | Q31: 1.07 | R31: 1.24 | S31: =IFERROR(K31*$I$5,0) | T31: =IFERROR(K31*$J$5,0) | U31: =IFERROR(K31*$K$5,0) | V31: =IFERROR(L31*$G$5,0) | W31: =IFERROR(V31*N31,0) | X31: =IFERROR(L31*O31/SUMPRODUCT($L$17:$L$41,$O$17:$O$41)*$I$5,0) | Y31: =IFERROR(X31/W31,0) | Z31: =IFERROR(L31*Q31/SUMPRODUCT($L$17:$L$41,$Q$17:$Q$41)*$J$5,0) | AA31: =IFERROR(M31*$H$5,0) | AB31: =IFERROR(M31*P31/SUMPRODUCT($M$17:$M$41,$P$17:$P$41)*$L$5,0) | AC31: =IFERROR(AB31/AA31,0) | AD31: =IFERROR(M31*R31/SUMPRODUCT($M$17:$M$41,$R$17:$R$41)*$M$5,0) | AE31: =X31*Settings!$B$7+Z31*Settings!$B$8+W31*Settings!$B$9+AB31*Settings!$B$10+AD31*Settings!$B$11+S31*Settings!$B$12+T31*Settings!$B$13+U31*Settings!$B$14
A32: WR | B32: Marquez Valdes-Scantling | C32: 5 | D32: 31 | E32: role avg (from SF) | F32: 0.0701 | G32: 0.0677 | H32: 0.0145 | J32: 17 | L32: 0.0318 | M32: 0.0023 | N32: 0.4958 | O32: 1.03 | P32: 0.99 | Q32: 1.05 | R32: 1 | S32: =IFERROR(K32*$I$5,0) | T32: =IFERROR(K32*$J$5,0) | U32: =IFERROR(K32*$K$5,0) | V32: =IFERROR(L32*$G$5,0) | W32: =IFERROR(V32*N32,0) | X32: =IFERROR(L32*O32/SUMPRODUCT($L$17:$L$41,$O$17:$O$41)*$I$5,0) | Y32: =IFERROR(X32/W32,0) | Z32: =IFERROR(L32*Q32/SUMPRODUCT($L$17:$L$41,$Q$17:$Q$41)*$J$5,0) | AA32: =IFERROR(M32*$H$5,0) | AB32: =IFERROR(M32*P32/SUMPRODUCT($M$17:$M$41,$P$17:$P$41)*$L$5,0) | AC32: =IFERROR(AB32/AA32,0) | AD32: =IFERROR(M32*R32/SUMPRODUCT($M$17:$M$41,$R$17:$R$41)*$M$5,0) | AE32: =X32*Settings!$B$7+Z32*Settings!$B$8+W32*Settings!$B$9+AB32*Settings!$B$10+AD32*Settings!$B$11+S32*Settings!$B$12+T32*Settings!$B$13+U32*Settings!$B$14
A33: WR | B33: Jonathan Mingo | C33: 6 | D33: 25 | E33: ACT | F33: 0.1592 | G33: 0.0257 | H33: 0.0082 | J33: 17 | L33: 0.0427 | M33: 0.0008 | N33: 0.3414 | O33: 0.77 | P33: 1 | Q33: 1.03 | R33: 1 | S33: =IFERROR(K33*$I$5,0) | T33: =IFERROR(K33*$J$5,0) | U33: =IFERROR(K33*$K$5,0) | V33: =IFERROR(L33*$G$5,0) | W33: =IFERROR(V33*N33,0) | X33: =IFERROR(L33*O33/SUMPRODUCT($L$17:$L$41,$O$17:$O$41)*$I$5,0) | Y33: =IFERROR(X33/W33,0) | Z33: =IFERROR(L33*Q33/SUMPRODUCT($L$17:$L$41,$Q$17:$Q$41)*$J$5,0) | AA33: =IFERROR(M33*$H$5,0) | AB33: =IFERROR(M33*P33/SUMPRODUCT($M$17:$M$41,$P$17:$P$41)*$L$5,0) | AC33: =IFERROR(AB33/AA33,0) | AD33: =IFERROR(M33*R33/SUMPRODUCT($M$17:$M$41,$R$17:$R$41)*$M$5,0) | AE33: =X33*Settings!$B$7+Z33*Settings!$B$8+W33*Settings!$B$9+AB33*Settings!$B$10+AD33*Settings!$B$11+S33*Settings!$B$12+T33*Settings!$B$13+U33*Settings!$B$14
A34: WR | B34: Tyler Johnson | C34: 7 | D34: 27 | E34: role avg (from NYJ) | F34: 0.0054 | G34: 0.0758 | H34: 0.0381 | J34: 17 | L34: 0.0135 | M34: 0.0023 | N34: 0.653 | O34: 1.25 | P34: 1 | Q34: 2.39 | R34: 1 | S34: =IFERROR(K34*$I$5,0) | T34: =IFERROR(K34*$J$5,0) | U34: =IFERROR(K34*$K$5,0) | V34: =IFERROR(L34*$G$5,0) | W34: =IFERROR(V34*N34,0) | X34: =IFERROR(L34*O34/SUMPRODUCT($L$17:$L$41,$O$17:$O$41)*$I$5,0) | Y34: =IFERROR(X34/W34,0) | Z34: =IFERROR(L34*Q34/SUMPRODUCT($L$17:$L$41,$Q$17:$Q$41)*$J$5,0) | AA34: =IFERROR(M34*$H$5,0) | AB34: =IFERROR(M34*P34/SUMPRODUCT($M$17:$M$41,$P$17:$P$41)*$L$5,0) | AC34: =IFERROR(AB34/AA34,0) | AD34: =IFERROR(M34*R34/SUMPRODUCT($M$17:$M$41,$R$17:$R$41)*$M$5,0) | AE34: =X34*Settings!$B$7+Z34*Settings!$B$8+W34*Settings!$B$9+AB34*Settings!$B$10+AD34*Settings!$B$11+S34*Settings!$B$12+T34*Settings!$B$13+U34*Settings!$B$14
